Workbook

Sheet LogicCommon
A2: ロジック共通定義 | B2: ModuleID : | C2: MA | D2: LogicID : | E2: MABCL0420 | F2: Pj.ID : | G2: MC
B3: SubModuleID : | C3: MABC | D3: LogicClass : | E3: MABCL_BpSubReg | F3: SuperClassPj.ID :
D4: LogicName : | E4: 取引先補助マスタ登録 | F4: SuperLogicID : | G4: MA.MAUDL5010
A5: 概要 :
A6: 詳細 :

Sheet BpSub_UpdChk01
A1: * | B1: * | D1: L | E1: 1
A2: * | D2: オペレーション実装仕様書 Operation Specification Implementation Sheet | E2: ModuleID : | F2: =IF(LogicCommon!C2="","",LogicCommon!C2) -> MA | G2: LogicID : | H2: =IF(LogicCommon!E2="","",LogicCommon!E2) -> MABCL0420 | I2: Ope.ID : | J2: BpSub_UpdChk01 | K2: Pj.ID : | L2: =IF(LogicCommon!G2="","",LogicCommon!G2) -> MC | M2: Ope.Body : | N2: =L4 & ".Checker" -> MA.MAUDL5010.Checker
A3: * | D3: =IF(LogicCommon!A3="","",LogicCommon!A3) | E3: SubModuleID : | F3: =IF(LogicCommon!C3="","",LogicCommon!C3) -> MABC | G3: LogicClass : | H3: =IF(LogicCommon!E3="","",LogicCommon!E3) -> MABCL_BpSubReg | I3: Ope.Method : | J3: @ | K3: SuperClassPj.ID : | L3: =IF(LogicCommon!G3="","",LogicCommon!G3) | M3: ReportID : | O3: Gene.Type : | P3: ALL
A4: * | E4: Version : | F4: 000000 | G4: LogicName : | H4: =IF(LogicCommon!E4="","",LogicCommon!E4) -> 取引先補助マスタ登録 | I4: Ope.Name : | J4: 登録前チェック | K4: SuperLogicID : | L4: =IF(LogicCommon!G4="","",LogicCommon!G4) -> MA.MAUDL5010
A5: * | E5: ACType :
A6: * | D6: 概要 : | E6: 取引先補助マスタを登録する前のチェックを行う | U6: ID
A7: # | I7: U | K7: K | L7: K | M7: K | N7: K | O7: K | P7: K | Q7: K | R7: K | S7: K | T7: o
A8: # | D8: ブロック名 Block Name | E8: 型 Type | G8: super/share | H8: 対象ブロック名 Target Block Name | K8: REQUIRED | L8: LIST_LOGIC | M8: LIST_OUT | N8: LIST_OUT_BASE | O8: LIST_IN | P8: LIST_IN_BASE | Q8: AT_LEAST_ONE | R8: CHK_PTN | S8: BEFORE_AFTER | T8: TargetName | X8: ブロック備考 Block Remarks
A9: # | D9: 項目名 Field Name | E9: 型 Type | F9: 桁 Digits | G9: フルネーム Full Name | H9: 日本語名 Japanese Name | I9: 上り項目 Request Message Field | J9: 下り項目 Response Message Field | V9: 条件および編集方法 Conditions and Editing Methods | X9: 項目備考 Field Remarks
A10: # | T10: 上り項目 Request Message Field | U10: 下り項目 Response Message Field
A11: 10 | B11: * | D11: BpSub_UpdChk01_Dtl | E11: L | G11: $super$ | H11: DBC:MA.MAM_BP_SUB
A12: 10 | D12: bp_cd | E12: #MA.BP_CD | G12: BP cd. | H12: 取引先ＣＤ | I12: E | K12: E | L12: MA.MAUAL0010.Bp | M12: cst_flg;acst_flg;bcst_flg;rcst_flg;sppl_flg;asppl_flg;bsppl_flg;psppl_flg;cred_flg;dlv_flg;maker_flg;dest_flg;ar_dpt_typ;bill_dpt_typ;onr_prsppl_flg;repurc_obli_flg | N12: cst_flg;acst_flg;bcst_flg;rcst_flg;sppl_flg;asppl_flg;bsppl_flg;psppl_flg;cred_flg;dlv_flg;maker_flg;dest_flg;ar_dpt_typ;bill_dpt_typ;onr_prsppl_flg;repurc_obli_flg | O12: MAC_BP_IS_SRCH_TYP.COMM | P12: bp_is_srch_typ
A13: 10 | D13: st_dt_key | E13: #MA.DT | G13: Application start date_[Before change] | H13: 適用開始日_[変更前] | I13: E
A14: 10 | D14: st_dt | E14: #MA.DT | G14: Application start date | H14: 適用開始日 | I14: E | K14: E | S14: E1:BF
A15: 10 | D15: end_dt | E15: #MA.DT | G15: Application end date | H15: 適用終了日 | I15: E | K15: E | S15: E1:AF
A16: 10 | D16: zip_cd | E16: #MA.ZIP_CD | G16: Zip code | H16: 郵便番号 | I16: E | Q16: E1 | R16: ZIP
A17: 10 | D17: addr1 | E17: #MA.ADDR1 | G17: Address 1 | H17: 住所１ | I17: E | Q17: E1
A18: 10 | D18: addr2 | E18: #MA.ADDR2 | G18: Address 2 | H18: 住所２ | I18: E | Q18: E1
A19: 10 | D19: addr3 | E19: #MA.ADDR3 | G19: Address 3 | H19: 住所３ | I19: E | Q19: E1
A20: 10 | D20: addr4 | E20: #MA.ADDR4 | G20: Address 4 | H20: 住所４ | I20: E | Q20: E1
A21: 10 | D21: tel | E21: #MA.TEL | G21: TEL | H21: ＴＥＬ | I21: E | Q21: E1 | R21: TEL
A22: 10 | D22: fax | E22: #MA.TEL | G22: FAX | H22: ＦＡＸ | I22: E | Q22: E1 | R22: TEL
A23: 10 | D23: ar_dpt_cd | E23: #MA.DPT_CD | G23: AR dept. cd. | H23: 債権部門ＣＤ | I23: E | L23: MA.MAUAL0010.Dpt | O23: MAC_DPT_IS_SRCH_TYP.AR;st_dt | P23: dpt_is_srch_typ;dt | Q23: E1
A24: 10 | D24: cst_cntct_dpt | E24: #MA.CNTCT_DPT | G24: Customer dept. | H24: 得意先部署 | I24: E | Q24: E1
A25: 10 | D25: cst_cntct_psn | E25: #MA.CNTCT_PSN | G25: Customer PIC | H25: 得意先担当者 | I25: E | Q25: E1
A26: 10 | D26: cst_cntct_psn_title | E26: #MA.BP_PSN_TITLE | G26: Form of address for Customer PIC | H26: 得意先担当者敬称 | I26: E | Q26: E1
A27: 10 | D27: sls_tax_cd | E27: #MA.TAX_CD | G27: Sales tax cd. | H27: 売上税ＣＤ | I27: E | L27: MA.MAUAL0010.SlsTax | Q27: E1
A28: 10 | D28: sls_anly_cd1 | E28: #MA.SLS_ANLY_CD | G28: Sales analysis cd. 1 | H28: 販売分析ＣＤ１ | I28: E | L28: MA.MAUAL0010.SlsAnly1 | Q28: E1
A29: 10 | D29: sls_anly_cd2 | E29: #MA.SLS_ANLY_CD | G29: Sales analysis cd. 2 | H29: 販売分析ＣＤ２ | I29: E | L29: MA.MAUAL0010.SlsAnly2 | Q29: E1
A30: 10 | D30: sls_anly_cd3 | E30: #MA.SLS_ANLY_CD | G30: Sales analysis cd. 3 | H30: 販売分析ＣＤ３ | I30: E | L30: MA.MAUAL0010.SlsAnly3 | Q30: E1
A31: 10 | D31: bcst_dpt_cd | E31: #MA.DPT_CD | G31: Billing customer dept. in charge cd. | H31: 請求先担当部門ＣＤ | I31: E | L31: MA.MAUAL0010.Dpt | O31: MAC_DPT_IS_SRCH_TYP.AR;st_dt | P31: dpt_is_srch_typ;dt | Q31: E1
A32: 10 | D32: bill_zip_cd | E32: #MA.ZIP_CD | G32: Invoice send-to zip code | H32: 請求書送付郵便番号 | I32: E | Q32: E1 | R32: ZIP
A33: 10 | D33: bill_addr1 | E33: #MA.ADDR1 | G33: Invoice send-to address 1 | H33: 請求書送付住所１ | I33: E | Q33: E1
A34: 10 | D34: bill_addr2 | E34: #MA.ADDR2 | G34: Invoice send-to address 2 | H34: 請求書送付住所２ | I34: E | Q34: E1
A35: 10 | D35: bill_addr3 | E35: #MA.ADDR3 | G35: Invoice send-to address 3 | H35: 請求書送付住所３ | I35: E | Q35: E1
A36: 10 | D36: bill_addr4 | E36: #MA.ADDR4 | G36: Invoice send-to address 4 | H36: 請求書送付住所４ | I36: E | Q36: E1
A37: 10 | D37: bill_tel | E37: #MA.TEL | G37: Invoice send-to TEL | H37: 請求書送付ＴＥＬ | I37: E | Q37: E1 | R37: TEL
A38: 10 | D38: bill_bcst_nm | E38: #MA.BILL_BCST_NM | G38: Invoice destination | H38: 請求書宛先 | I38: E | Q38: E1
A39: 10 | D39: bill_bcst_dpt | E39: #MA.BP_CNTCT_DPT | G39: Invoice send-to dept. | H39: 請求書送付部署 | I39: E | Q39: E1
A40: 10 | D40: bill_bcst_psn | E40: #MA.BP_CNTCT_PSN | G40: Invoice send-to PIC | H40: 請求書送付担当者 | I40: E | Q40: E1
A41: 10 | D41: bill_bcst_psn_title | E41: #MA.BP_PSN_TITLE | G41: Invoice send-to PIC honorific | H41: 請求書送付担当者敬称 | I41: E | Q41: E1
A42: 10 | D42: vmi_purc_dpt_cd | E42: #MA.DPT_CD | G42: VMI purchasing dept. cd. | H42: ＶＭＩ購買部門ＣＤ | I42: E | L42: MA.MAUAL0010.Dpt | O42: MAC_DPT_IS_SRCH_TYP.PURC;st_dt | P42: dpt_is_srch_typ;dt | Q42: E1
A43: 10 | D43: sppl_cntct_dpt | E43: #MA.CNTCT_DPT | G43: Supplier dept. | H43: 発注先部署 | I43: E | Q43: E1
A44: 10 | D44: sppl_cntct_psn | E44: #MA.CNTCT_PSN | G44: Supplier PIC | H44: 発注先担当者 | I44: E | Q44: E1
A45: 10 | D45: sppl_cntct_psn_title | E45: #MA.BP_PSN_TITLE | G45: Supplier PIC form of address | H45: 発注先担当者敬称 | I45: E | Q45: E1
A46: 10 | D46: purc_tax_cd | E46: #MA.TAX_CD | G46: Purchase tax cd. | H46: 仕入税ＣＤ | I46: E | L46: MA.MAUAL0010.PurcTax | Q46: E1
A47: 10 | D47: prov_tax_cd | E47: #MA.TAX_CD | G47: Supply tax cd. | H47: 支給税ＣＤ | I47: E | L47: MA.MAUAL0010.ProvTax | O47: repurc_obli_flg | P47: repurc_obli_flg | Q47: E1
A48: 10 | D48: ap_dpt_cd | E48: #MA.DPT_CD | G48: AP dept. cd. | H48: 債務部門ＣＤ | I48: E | L48: MA.MAUAL0010.Dpt | O48: MAC_DPT_IS_SRCH_TYP.AP;st_dt | P48: dpt_is_srch_typ;dt | Q48: E1
A49: 10 | D49: bsppl_dpt_cd | E49: #MA.DPT_CD | G49: Cd. of dept. in charge of scheduled payee | H49: 支払予定管理先担当部門ＣＤ | I49: E | L49: MA.MAUAL0010.Dpt | O49: MAC_DPT_IS_SRCH_TYP.AP;st_dt | P49: dpt_is_srch_typ;dt | Q49: E1
A50: 10 | D50: pay_dpt_cd | E50: #MA.DPT_CD | G50: Payment dept. cd. | H50: 支払部門ＣＤ | I50: E | L50: MA.MAUAL0010.Dpt | O50: MAC_DPT_IS_SRCH_TYP.AP;st_dt | P50: dpt_is_srch_typ;dt | Q50: E1
A51: 10 | D51: dlv_cntct_dpt | E51: #MA.BP_CNTCT_DPT | G51: Delivery destination dept. | H51: 納品先部署 | I51: E | Q51: E1
A52: 10 | D52: dlv_cntct_psn | E52: #MA.BP_CNTCT_PSN | G52: Delivery destination PIC | H52: 納品先担当者 | I52: E | Q52: E1
A53: 10 | D53: dlv_cntct_psn_title | E53: #MA.BP_PSN_TITLE | G53: Delivery destination PIC honorific | H53: 納品先担当者敬称 | I53: E | Q53: E1
A54: 10 | D54: memo1 | E54: #MA.MST_MEMO1 | G54: Memo 1 | H54: メモ１ | I54: E
A55: 10 | D55: memo2 | E55: #MA.MST_MEMO2 | G55: Memo 2 | H55: メモ２ | I55: E
A56: 10 | D56: memo3 | E56: #MA.MST_MEMO3 | G56: Memo 3 | H56: メモ３ | I56: E
A57: 10 | D57: del_flg | E57: #MA.FLG | G57: Logical delete | H57: 論理削除 | I57: E
A58: 10 | D58: upd_cntr | E58: #MA.UPD_CNT | G58: Update counter | H58: 更新カウンタ | I58: E
A59: 10 | D59: cst_flg | E59: #MA.FLG | G59: Customer | H59: 得意先
A60: 10 | D60: acst_flg | E60: #MA.FLG | G60: AR customer | H60: 売掛先
A61: 10 | D61: bcst_flg | E61: #MA.FLG | G61: Billing customer | H61: 請求先
A62: 10 | D62: rcst_flg | E62: #MA.FLG | G62: Payer | H62: 入金先
A63: 10 | D63: sppl_flg | E63: #MA.FLG | G63: Supplier | H63: 発注先
A64: 10 | D64: asppl_flg | E64: #MA.FLG | G64: AP supplier | H64: 買掛先
A65: 10 | D65: bsppl_flg | E65: #MA.FLG | G65: Scheduled payee | H65: 支払予定管理先
A66: 10 | D66: psppl_flg | E66: #MA.FLG | G66: Payee | H66: 支払先
A67: 10 | D67: cred_flg | E67: #MA.FLG | G67: Credit managed BP | H67: 与信管理先
A68: 10 | D68: dlv_flg | E68: #MA.FLG | G68: Delivery destination | H68: 納品先
A69: 10 | D69: maker_flg | E69: #MA.FLG | G69: Maker | H69: メーカ
A70: 10 | D70: dest_flg | E70: #MA.FLG | G70: Distribution channel | H70: 仕向先
... A74: 10 | D74: repurc_obli_flg | E74: #MA.FLG | G74: Repurchase obligation | H74: 買戻義務
A75: 10 | D75: memo4 | E75: #MA.MST_MEMO4 | G75: Memo 4 | H75: メモ４ | I75: E
A76: 10 | D76: memo5 | E76: #MA.MST_MEMO5 | G76: Memo 5 | H76: メモ５ | I76: E
A77: 10 | D77: memo6 | E77: #MA.MST_MEMO6 | G77: Memo 6 | H77: メモ６ | I77: E
A78: 10 | D78: memo7 | E78: #MA.MST_MEMO7 | G78: Memo 7 | H78: メモ７ | I78: E
A79: 10 | D79: memo8 | E79: #MA.MST_MEMO8 | G79: Memo 8 | H79: メモ８ | I79: E
A80: 10 | D80: memo9 | E80: #MA.MST_MEMO9 | G80: Memo 9 | H80: メモ９ | I80: E
A81: 10 | D81: memo10 | E81: #MA.MST_MEMO10 | G81: Memo 10 | H81: メモ１０ | I81: E
A82: 10 | D82: memo11 | E82: #MA.MST_MEMO11 | G82: Memo 11 | H82: メモ１１ | I82: E
A83: 10 | D83: memo12 | E83: #MA.MST_MEMO12 | G83: Memo 12 | H83: メモ１２ | I83: E
A84: 10 | D84: memo13 | E84: #MA.MST_MEMO13 | G84: Memo 13 | H84: メモ１３ | I84: E
A85: 10 | D85: memo14 | E85: #MA.MST_MEMO14 | G85: Memo 14 | H85: メモ１４ | I85: E
A86: 10 | D86: memo15 | E86: #MA.MST_MEMO15 | G86: Memo 15 | H86: メモ１５ | I86: E
... A91: 10 | D91: memo20 | E91: #MA.MST_MEMO20 | G91: Memo 20 | H91: メモ２０ | I91: E
D92: 詳細 :

Sheet BpSub_Upd01
A1: * | B1: * | D1: L | E1: 1
A2: * | D2: オペレーション実装仕様書 Operation Specification Implementation Sheet | E2: ModuleID : | F2: =IF(LogicCommon!C2="","",LogicCommon!C2) -> MA | G2: LogicID : | H2: =IF(LogicCommon!E2="","",LogicCommon!E2) -> MABCL0420 | I2: Ope.ID : | J2: BpSub_Upd01 | K2: Pj.ID : | L2: =IF(LogicCommon!G2="","",LogicCommon!G2) -> MC | M2: Ope.Body : | N2: "mcframe.serverMAUD.MAUDL6010.MAUDL_RLUpdater"
A3: * | D3: =IF(LogicCommon!A3="","",LogicCommon!A3) | E3: SubModuleID : | F3: =IF(LogicCommon!C3="","",LogicCommon!C3) -> MABC | G3: LogicClass : | H3: =IF(LogicCommon!E3="","",LogicCommon!E3) -> MABCL_BpSubReg | I3: Ope.Method : | J3: @ | K3: SuperClassPj.ID : | L3: =IF(LogicCommon!G3="","",LogicCommon!G3) | M3: ReportID : | O3: Gene.Type : | P3: ALL
A4: * | E4: Version : | F4: 000000 | G4: LogicName : | H4: =IF(LogicCommon!E4="","",LogicCommon!E4) -> 取引先補助マスタ登録 | I4: Ope.Name : | J4: 登録処理 | K4: SuperLogicID : | L4: =IF(LogicCommon!G4="","",LogicCommon!G4) -> MA.MAUDL5010
A5: * | E5: ACType :
A6: * | D6: 概要 : | E6: 取引先補助マスタを登録する | L6: ID | N6: ID | P6: ID | R6: ID
A7: # | I7: U | K7: o | L7: UPDATE.updMaster | M7: o | N7: MAIN.chkMaster | O7: o | Q7: o
A8: # | D8: ブロック名 Block Name | E8: 型 Type | G8: super/share | H8: 対象ブロック名 Target Block Name | K8: TargetName | L8: DBC.MA.MAM_BP_SUB | M8: TargetName | N8: DBC.MA.MAM_BP_SUB | O8: TargetName | Q8: TargetName | U8: ブロック備考 Block Remarks
A9: # | D9: 項目名 Field Name | E9: 型 Type | F9: 桁 Digits | G9: フルネーム Full Name | H9: 日本語名 Japanese Name | I9: 上り項目 Request Message Field | J9: 下り項目 Response Message Field | S9: 条件および編集方法 Conditions and Editing Methods | U9: 項目備考 Field Remarks
A10: # | K10: 上り項目 Request Message Field | L10: 下り項目 Response Message Field | M10: 上り項目 Request Message Field | N10: 下り項目 Response Message Field | O10: 上り項目 Request Message Field | P10: 下り項目 Response Message Field | Q10: 上り項目 Request Message Field | R10: 下り項目 Response Message Field
A11: 10 | B11: * | D11: BpSub_Upd01_Dtl | E11: L | G11: $share$ | H11: MA.MABCL0420.BpSub_UpdChk01.BpSub_UpdChk01_Dtl | K11: L | M11: L
A12: 10 | D12: bp_cd | E12: #MA.BP_CD | G12: BP cd. | H12: 取引先ＣＤ | I12: E | K12: E | M12: E
A13: 10 | D13: st_dt_key | E13: #MA.DT | G13: Application start date_[Before change] | H13: 適用開始日_[変更前] | I13: E
A14: 10 | D14: st_dt | E14: #MA.DT | G14: Application start date | H14: 適用開始日 | I14: E | K14: E | M14: E
A15: 10 | D15: end_dt | E15: #MA.DT | G15: Application end date | H15: 適用終了日 | I15: E | K15: E
A16: 10 | D16: zip_cd | E16: #MA.ZIP_CD | G16: Zip code | H16: 郵便番号 | I16: E | K16: E
A17: 10 | D17: addr1 | E17: #MA.ADDR1 | G17: Address 1 | H17: 住所１ | I17: E | K17: E
A18: 10 | D18: addr2 | E18: #MA.ADDR2 | G18: Address 2 | H18: 住所２ | I18: E | K18: E
A19: 10 | D19: addr3 | E19: #MA.ADDR3 | G19: Address 3 | H19: 住所３ | I19: E | K19: E
A20: 10 | D20: addr4 | E20: #MA.ADDR4 | G20: Address 4 | H20: 住所４ | I20: E | K20: E
A21: 10 | D21: tel | E21: #MA.TEL | G21: TEL | H21: ＴＥＬ | I21: E | K21: E
A22: 10 | D22: fax | E22: #MA.TEL | G22: FAX | H22: ＦＡＸ | I22: E | K22: E
A23: 10 | D23: ar_dpt_cd | E23: #MA.DPT_CD | G23: AR dept. cd. | H23: 債権部門ＣＤ | I23: E | K23: E
A24: 10 | D24: cst_cntct_dpt | E24: #MA.CNTCT_DPT | G24: Customer dept. | H24: 得意先部署 | I24: E | K24: E
A25: 10 | D25: cst_cntct_psn | E25: #MA.CNTCT_PSN | G25: Customer PIC | H25: 得意先担当者 | I25: E | K25: E
A26: 10 | D26: cst_cntct_psn_title | E26: #MA.BP_PSN_TITLE | G26: Form of address for Customer PIC | H26: 得意先担当者敬称 | I26: E | K26: E
... A75: 10 | D75: memo20 | E75: #MA.MST_MEMO20 | G75: Memo 20 | H75: メモ２０ | I75: E | K75: E
D76: 詳細 :

Sheet BpSub_DelChk01
A1: * | B1: * | D1: L | E1: 1
A2: * | D2: オペレーション実装仕様書 Operation Specification Implementation Sheet | E2: ModuleID : | F2: =IF(LogicCommon!C2="","",LogicCommon!C2) -> MA | G2: LogicID : | H2: =IF(LogicCommon!E2="","",LogicCommon!E2) -> MABCL0420 | I2: Ope.ID : | J2: BpSub_DelChk01 | K2: Pj.ID : | L2: =IF(LogicCommon!G2="","",LogicCommon!G2) -> MC | M2: Ope.Body : | N2: =L4 & ".Checker" -> MA.MAUDL5010.Checker
A3: * | D3: =IF(LogicCommon!A3="","",LogicCommon!A3) | E3: SubModuleID : | F3: =IF(LogicCommon!C3="","",LogicCommon!C3) -> MABC | G3: LogicClass : | H3: =IF(LogicCommon!E3="","",LogicCommon!E3) -> MABCL_BpSubReg | I3: Ope.Method : | J3: @ | K3: SuperClassPj.ID : | L3: =IF(LogicCommon!G3="","",LogicCommon!G3) | M3: ReportID : | O3: Gene.Type : | P3: ALL
A4: * | E4: Version : | F4: 000000 | G4: LogicName : | H4: =IF(LogicCommon!E4="","",LogicCommon!E4) -> 取引先補助マスタ登録 | I4: Ope.Name : | J4: 削除チェック | K4: SuperLogicID : | L4: =IF(LogicCommon!G4="","",LogicCommon!G4) -> MA.MAUDL5010
A5: * | E5: ACType :
A6: * | D6: 概要 : | E6: 取引先補助マスタを削除する前のチェックを行う | M6: ID
A7: # | I7: U | K7: K | L7: o
A8: # | D8: ブロック名 Block Name | E8: 型 Type | G8: super/share | H8: 対象ブロック名 Target Block Name | K8: REQUIRED | L8: TargetName | P8: ブロック備考 Block Remarks
A9: # | D9: 項目名 Field Name | E9: 型 Type | F9: 桁 Digits | G9: フルネーム Full Name | H9: 日本語名 Japanese Name | I9: 上り項目 Request Message Field | J9: 下り項目 Response Message Field | N9: 条件および編集方法 Conditions and Editing Methods | P9: 項目備考 Field Remarks
A10: # | L10: 上り項目 Request Message Field | M10: 下り項目 Response Message Field
A11: 10 | B11: * | D11: BpSub_DelChk01_Dtl | E11: L
A12: 10 | D12: bp_cd | E12: #MA.BP_CD | G12: BP cd. | H12: 取引先ＣＤ | I12: E | K12: E
A13: 10 | D13: st_dt | E13: #MA.DT | G13: Application start date | H13: 適用開始日 | I13: E | K13: E
A14: 10 | D14: upd_cntr | E14: #MA.UPD_CNT | G14: Update counter | H14: 更新カウンタ | I14: E
D15: 詳細 :

Sheet BpSub_Del01
A1: * | B1: * | D1: L | E1: 1
A2: * | D2: オペレーション実装仕様書 Operation Specification Implementation Sheet | E2: ModuleID : | F2: =IF(LogicCommon!C2="","",LogicCommon!C2) -> MA | G2: LogicID : | H2: =IF(LogicCommon!E2="","",LogicCommon!E2) -> MABCL0420 | I2: Ope.ID : | J2: BpSub_Del01 | K2: Pj.ID : | L2: =IF(LogicCommon!G2="","",LogicCommon!G2) -> MC | M2: Ope.Body : | N2: "mcframe.serverMAUD.MAUDL6010.MAUDL_RLDeleter"
A3: * | D3: =IF(LogicCommon!A3="","",LogicCommon!A3) | E3: SubModuleID : | F3: =IF(LogicCommon!C3="","",LogicCommon!C3) -> MABC | G3: LogicClass : | H3: =IF(LogicCommon!E3="","",LogicCommon!E3) -> MABCL_BpSubReg | I3: Ope.Method : | J3: @ | K3: SuperClassPj.ID : | L3: =IF(LogicCommon!G3="","",LogicCommon!G3) | M3: ReportID : | O3: Gene.Type : | P3: ALL
A4: * | E4: Version : | F4: 000000 | G4: LogicName : | H4: =IF(LogicCommon!E4="","",LogicCommon!E4) -> 取引先補助マスタ登録 | I4: Ope.Name : | J4: 削除処理 | K4: SuperLogicID : | L4: =IF(LogicCommon!G4="","",LogicCommon!G4) -> MA.MAUDL5010
A5: * | E5: ACType :
A6: * | D6: 概要 : | E6: 取引先補助マスタを削除する | L6: ID | N6: ID
A7: # | I7: U | K7: o | L7: UPDATE.updMaster1 | M7: o
A8: # | D8: ブロック名 Block Name | E8: 型 Type | G8: super/share | H8: 対象ブロック名 Target Block Name | K8: TargetName | L8: DBC.MA.MAM_BP_SUB | M8: TargetName | Q8: ブロック備考 Block Remarks
A9: # | D9: 項目名 Field Name | E9: 型 Type | F9: 桁 Digits | G9: フルネーム Full Name | H9: 日本語名 Japanese Name | I9: 上り項目 Request Message Field | J9: 下り項目 Response Message Field | O9: 条件および編集方法 Conditions and Editing Methods | Q9: 項目備考 Field Remarks
A10: # | K10: 上り項目 Request Message Field | L10: 下り項目 Response Message Field | M10: 上り項目 Request Message Field | N10: 下り項目 Response Message Field
A11: 10 | B11: * | D11: BpSub_Del01_Dtl | E11: L | G11: $share$ | H11: MA.MABCL0420.BpSub_DelChk01.BpSub_DelChk01_Dtl | K11: L
A12: 10 | D12: bp_cd | E12: #MA.BP_CD | G12: BP cd. | H12: 取引先ＣＤ | I12: E | K12: E
A13: 10 | D13: st_dt | E13: #MA.DT | G13: Application start date | H13: 適用開始日 | I13: E | K13: E
A14: 10 | D14: upd_cntr | E14: #MA.UPD_CNT | G14: Update counter | H14: 更新カウンタ | I14: E | K14: E
D15: 詳細 :

Sheet Srch01
A1: * | B1: * | D1: L | E1: 1
A2: * | D2: オペレーション実装仕様書 Operation Specification Implementation Sheet | E2: ModuleID : | F2: =IF(LogicCommon!C2="","",LogicCommon!C2) -> MA | G2: LogicID : | H2: =IF(LogicCommon!E2="","",LogicCommon!E2) -> MABCL0420 | I2: Ope.ID : | J2: Srch01 | K2: Pj.ID : | L2: =IF(LogicCommon!G2="","",LogicCommon!G2) -> MC | M2: Ope.Body : | N2: "mcframe.serverMAUD.MAUDL6010.MAUDL_RLSearcher"
A3: * | D3: =IF(LogicCommon!A3="","",LogicCommon!A3) | E3: SubModuleID : | F3: =IF(LogicCommon!C3="","",LogicCommon!C3) -> MABC | G3: LogicClass : | H3: =IF(LogicCommon!E3="","",LogicCommon!E3) -> MABCL_BpSubReg | I3: Ope.Method : | J3: @ | K3: SuperClassPj.ID : | L3: =IF(LogicCommon!G3="","",LogicCommon!G3) | M3: ReportID : | O3: Gene.Type : | P3: ALL
A4: * | E4: Version : | F4: 000000 | G4: LogicName : | H4: =IF(LogicCommon!E4="","",LogicCommon!E4) -> 取引先補助マスタ登録 | I4: Ope.Name : | J4: 検索 | K4: SuperLogicID : | L4: =IF(LogicCommon!G4="","",LogicCommon!G4) -> MA.MAUDL5010
A5: * | E5: ACType :
A6: * | D6: 概要 : | E6: 検索処理を行う | L6: ID | N6: ID
A7: # | I7: U | K7: o | L7: SELECT.c0 | M7: o
A8: # | D8: ブロック名 Block Name | E8: 型 Type | G8: super/share | H8: 対象ブロック名 Target Block Name | K8: TargetName | L8: DBC.MA.MAM_BP_SUB | M8: TargetName | Q8: ブロック備考 Block Remarks
A9: # | D9: 項目名 Field Name | E9: 型 Type | F9: 桁 Digits | G9: フルネーム Full Name | H9: 日本語名 Japanese Name | I9: 上り項目 Request Message Field | J9: 下り項目 Response Message Field | O9: 条件および編集方法 Conditions and Editing Methods | Q9: 項目備考 Field Remarks
A10: # | K10: 上り項目 Request Message Field | L10: 下り項目 Response Message Field | M10: 上り項目 Request Message Field | N10: 下り項目 Response Message Field
A11: 10 | B11: * | D11: Srch01_Cnd | E11: R
A12: 10 | D12: st_dt_fr | E12: #MA.DT | G12: Application start date FROM | H12: 適用開始日ＦＲＯＭ | I12: E
A13: 10 | D13: st_dt_to | E13: #MA.DT | G13: Application start date TO | H13: 適用開始日ＴＯ | I13: E
A14: 10 | D14: end_dt_fr | E14: #MA.DT | G14: Application end date FROM | H14: 適用終了日ＦＲＯＭ | I14: E
A15: 10 | D15: end_dt_to | E15: #MA.DT | G15: Application end date TO | H15: 適用終了日ＴＯ | I15: E
A16: 10 | D16: bp_cd | E16: #MA.BP_CD | G16: BP cd. | H16: 取引先ＣＤ | I16: E
A17: 10 | D17: bp_nm | E17: #MA.BP_NM | G17: BP name | H17: 取引先名 | I17: E
A18: 10 | D18: new_st_dt | E18: #MA.DT | G18: New application start date | H18: 新適用開始日 | I18: E
A19: 10 | D19: dpt_cd | E19: #MA.DPT_CD | G19: Dept. cd. | H19: 部門ＣＤ | I19: E
A20: 10 | D20: dpt_nm | E20: #MA.DPT_NM | G20: Dept. name | H20: 部門名 | I20: E
A21: 10 | D21: ar_dpt_cd | E21: #MA.DPT_CD | G21: AR dept. cd. | H21: 債権部門ＣＤ | I21: E
A22: 10 | D22: ar_dpt_nm | E22: #MA.DPT_NM | G22: AR dept. name | H22: 債権部門名 | I22: E
A23: 10 | D23: bcst_dpt_cd | E23: #MA.DPT_CD | G23: Billing customer dept. in charge cd. | H23: 請求先担当部門ＣＤ | I23: E
... A93: 10 | D93: bp_grp_nm10 | E93: #MA.BP_GRP_NM | G93: BP classification name 10 | H93: 取引先分類名１０ | I93: E
A95: 20 | B95: * | D95: Srch01_Rslt | E95: L | L95: L
A96: 20 | D96: del_flg | E96: #MA.FLG | G96: Logical delete | H96: 論理削除 | J96: E | L96: E
A97: 20 | D97: bp_cd | E97: #MA.BP_CD | G97: BP cd. | H97: 取引先ＣＤ | J97: E | L97: E
A98: 20 | D98: bp_nm | E98: #MA.BP_NM | G98: BP name | H98: 取引先名 | J98: E | L98: E
A99: 20 | D99: cst_flg | E99: #MA.FLG | G99: Customer | H99: 得意先 | J99: E | L99: E
A100: 20 | D100: acst_flg | E100: #MA.FLG | G100: AR customer | H100: 売掛先 | J100: E | L100: E
A101: 20 | D101: bcst_flg | E101: #MA.FLG | G101: Billing customer | H101: 請求先 | J101: E | L101: E
A102: 20 | D102: rcst_flg | E102: #MA.FLG | G102: Payer | H102: 入金先 | J102: E | L102: E
A103: 20 | D103: dlv_flg | E103: #MA.FLG | G103: Delivery destination | H103: 納品先 | J103: E | L103: E
A104: 20 | D104: dest_flg | E104: #MA.FLG | G104: Distribution channel | H104: 仕向先 | J104: E | L104: E
A105: 20 | D105: cred_flg | E105: #MA.FLG | G105: Credit managed BP | H105: 与信管理先 | J105: E | L105: E
A106: 20 | D106: sppl_flg | E106: #MA.FLG | G106: Supplier | H106: 発注先 | J106: E | L106: E
A107: 20 | D107: asppl_flg | E107: #MA.FLG | G107: AP supplier | H107: 買掛先 | J107: E | L107: E
... A190: 20 | D190: ins_func_id | E190: #MA.FUNC_ID | G190: Entry function ID | H190: 登録機能ＩＤ | J190: E | L190: E
A191: 20 | D191: ins_func_nm | E191: #MA.FUNC_NM | G191: Entry function name | H191: 登録機能名 | J191: E
A192: 20 | D192: upd_cntr | E192: #MA.UPD_CNT | G192: Update counter | H192: 更新カウンタ | J192: E | L192: E
A193: 20 | D193: upd_usr_id | E193: #MA.FCM_USR_ID | G193: Update user ID | H193: 更新ユーザＩＤ | J193: E | L193: E
A194: 20 | D194: upd_usr_nm | E194: #MA.FCM_USR_NM | G194: Update user name | H194: 更新ユーザ名 | J194: E | L194: E
A195: 20 | D195: upd_ts | E195: #MA.SYS_TS | G195: Update date and time | H195: 更新日時 | J195: E | L195: E
A196: 20 | D196: upd_func_id | E196: #MA.FUNC_ID | G196: Update function ID | H196: 更新機能ＩＤ | J196: E | L196: E
A197: 20 | D197: upd_func_nm | E197: #MA.FUNC_NM | G197: Update function name | H197: 更新機能名 | J197: E
A198: 20 | D198: upd_srv_req_no | E198: #MA.SRV_REQ_NO | G198: Update request No. | H198: 更新リクエストＮＯ | J198: E | L198: E
A199: 20 | D199: del_usr_id | E199: #MA.FCM_USR_ID | G199: Logical delete user ID | H199: 論理削除ユーザＩＤ | J199: E | L199: E
A200: 20 | D200: del_usr_nm | E200: #MA.FCM_USR_NM | G200: Logical delete user name | H200: 論理削除ユーザ名 | J200: E | L200: E
A201: 20 | D201: del_ts | E201: #MA.SYS_TS | G201: Logical delete date and time | H201: 論理削除日時 | J201: E | L201: E
D202: 詳細 :

Sheet Sprt01
A1: * | B1: * | D1: L | E1: 1
A2: * | D2: オペレーション実装仕様書 Operation Specification Implementation Sheet | E2: ModuleID : | F2: =IF(LogicCommon!C2="","",LogicCommon!C2) -> MA | G2: LogicID : | H2: =IF(LogicCommon!E2="","",LogicCommon!E2) -> MABCL0420 | I2: Ope.ID : | J2: Sprt01 | K2: Pj.ID : | L2: =IF(LogicCommon!G2="","",LogicCommon!G2) -> MC | M2: Ope.Body : | N2: "mcframe.serverMAUD.MAUDL6010.MAUDL_RLStEndDupChecker"
A3: * | D3: =IF(LogicCommon!A3="","",LogicCommon!A3) | E3: SubModuleID : | F3: =IF(LogicCommon!C3="","",LogicCommon!C3) -> MABC | G3: LogicClass : | H3: =IF(LogicCommon!E3="","",LogicCommon!E3) -> MABCL_BpSubReg | I3: Ope.Method : | J3: @ | K3: SuperClassPj.ID : | L3: =IF(LogicCommon!G3="","",LogicCommon!G3) | M3: ReportID : | O3: Gene.Type : | P3: ALL
A4: * | E4: Version : | F4: 000000 | G4: LogicName : | H4: =IF(LogicCommon!E4="","",LogicCommon!E4) -> 取引先補助マスタ登録 | I4: Ope.Name : | J4: 補正 | K4: SuperLogicID : | L4: =IF(LogicCommon!G4="","",LogicCommon!G4) -> MA.MAUDL5010
A5: * | E5: ACType :
A6: * | D6: 概要 : | E6: 重複期間の補正を行う | L6: ID | N6: ID
A7: # | I7: U | K7: o | L7: UPDATE.updMaster | M7: o
A8: # | D8: ブロック名 Block Name | E8: 型 Type | G8: super/share | H8: 対象ブロック名 Target Block Name | K8: TargetName | L8: DBC.MA.MAM_BP_SUB | M8: TargetName | Q8: ブロック備考 Block Remarks
A9: # | D9: 項目名 Field Name | E9: 型 Type | F9: 桁 Digits | G9: フルネーム Full Name | H9: 日本語名 Japanese Name | I9: 上り項目 Request Message Field | J9: 下り項目 Response Message Field | O9: 条件および編集方法 Conditions and Editing Methods | Q9: 項目備考 Field Remarks
A10: # | K10: 上り項目 Request Message Field | L10: 下り項目 Response Message Field | M10: 上り項目 Request Message Field | N10: 下り項目 Response Message Field
A11: 10 | B11: * | D11: Sprt01_Dtl | E11: L | K11: L
A12: 10 | D12: st_dt_key | E12: #MA.DT | G12: Application start date_[Before change] | H12: 適用開始日_[変更前] | I12: E | J12: E
A13: 10 | D13: del_flg | E13: #MA.FLG | G13: Logical delete | H13: 論理削除 | I13: E | J13: E | K13: E
A14: 10 | D14: bp_cd | E14: #MA.BP_CD | G14: BP cd. | H14: 取引先ＣＤ | I14: E | J14: E | K14: E
A15: 10 | D15: bp_nm | E15: #MA.BP_NM | G15: BP name | H15: 取引先名 | I15: E | J15: E | K15: E
A16: 10 | D16: cst_flg | E16: #MA.FLG | G16: Customer | H16: 得意先 | I16: E | J16: E | K16: E
A17: 10 | D17: acst_flg | E17: #MA.FLG | G17: AR customer | H17: 売掛先 | I17: E | J17: E | K17: E
A18: 10 | D18: bcst_flg | E18: #MA.FLG | G18: Billing customer | H18: 請求先 | I18: E | J18: E | K18: E
A19: 10 | D19: rcst_flg | E19: #MA.FLG | G19: Payer | H19: 入金先 | I19: E | J19: E | K19: E
A20: 10 | D20: dlv_flg | E20: #MA.FLG | G20: Delivery destination | H20: 納品先 | I20: E | J20: E | K20: E
A21: 10 | D21: dest_flg | E21: #MA.FLG | G21: Distribution channel | H21: 仕向先 | I21: E | J21: E | K21: E
A22: 10 | D22: cred_flg | E22: #MA.FLG | G22: Credit managed BP | H22: 与信管理先 | I22: E | J22: E | K22: E
A23: 10 | D23: sppl_flg | E23: #MA.FLG | G23: Supplier | H23: 発注先 | I23: E | J23: E | K23: E
A24: 10 | D24: asppl_flg | E24: #MA.FLG | G24: AP supplier | H24: 買掛先 | I24: E | J24: E | K24: E
... A103: 10 | D103: memo20 | E103: #MA.MST_MEMO20 | G103: Memo 20 | H103: メモ２０ | I103: E | J103: E | K103: E
A104: 10 | D104: ins_usr_id | E104: #MA.FCM_USR_ID | G104: Entry user ID | H104: 登録ユーザＩＤ | J104: E
A105: 10 | D105: ins_usr_nm | E105: #MA.FCM_USR_NM | G105: Entry user name | H105: 登録ユーザ名 | J105: E
A106: 10 | D106: ins_ts | E106: #MA.SYS_TS | G106: Entry date and time | H106: 登録日時 | J106: E
A107: 10 | D107: ins_func_id | E107: #MA.FUNC_ID | G107: Entry function ID | H107: 登録機能ＩＤ | J107: E
A108: 10 | D108: ins_func_nm | E108: #MA.FUNC_NM | G108: Entry function name | H108: 登録機能名 | J108: E
A109: 10 | D109: upd_cntr | E109: #MA.UPD_CNT | G109: Update counter | H109: 更新カウンタ | I109: E | J109: E | K109: E
A110: 10 | D110: upd_usr_id | E110: #MA.FCM_USR_ID | G110: Update user ID | H110: 更新ユーザＩＤ | J110: E
A111: 10 | D111: upd_usr_nm | E111: #MA.FCM_USR_NM | G111: Update user name | H111: 更新ユーザ名 | J111: E
A112: 10 | D112: upd_ts | E112: #MA.SYS_TS | G112: Update date and time | H112: 更新日時 | J112: E
A113: 10 | D113: upd_func_id | E113: #MA.FUNC_ID | G113: Update function ID | H113: 更新機能ＩＤ | J113: E
A114: 10 | D114: upd_func_nm | E114: #MA.FUNC_NM | G114: Update function name | H114: 更新機能名 | J114: E
A115: 10 | D115: upd_srv_req_no | E115: #MA.SRV_REQ_NO | G115: Update request No. | H115: 更新リクエストＮＯ | J115: E
A116: 10 | D116: del_usr_id | E116: #MA.FCM_USR_ID | G116: Logical delete user ID | H116: 論理削除ユーザＩＤ | J116: E
A117: 10 | D117: del_usr_nm | E117: #MA.FCM_USR_NM | G117: Logical delete user name | H117: 論理削除ユーザ名 | J117: E
A118: 10 | D118: del_ts | E118: #MA.SYS_TS | G118: Logical delete date and time | H118: 論理削除日時 | J118: E
D119: 詳細 :

Sheet Upd01
A1: * | B1: * | D1: L | E1: 1
A2: * | D2: オペレーション実装仕様書 Operation Specification Implementation Sheet | E2: ModuleID : | F2: =IF(LogicCommon!C2="","",LogicCommon!C2) -> MA | G2: LogicID : | H2: =IF(LogicCommon!E2="","",LogicCommon!E2) -> MABCL0420 | I2: Ope.ID : | J2: Upd01 | K2: Pj.ID : | L2: =IF(LogicCommon!G2="","",LogicCommon!G2) -> MC | M2: Ope.Body : | N2: "mcframe.serverMAUD.MAUDL6010.MAUDL_RLUpdater"
A3: * | D3: =IF(LogicCommon!A3="","",LogicCommon!A3) | E3: SubModuleID : | F3: =IF(LogicCommon!C3="","",LogicCommon!C3) -> MABC | G3: LogicClass : | H3: =IF(LogicCommon!E3="","",LogicCommon!E3) -> MABCL_BpSubReg | I3: Ope.Method : | J3: @ | K3: SuperClassPj.ID : | L3: =IF(LogicCommon!G3="","",LogicCommon!G3) | M3: ReportID : | O3: Gene.Type : | P3: ALL
A4: * | E4: Version : | F4: 000000 | G4: LogicName : | H4: =IF(LogicCommon!E4="","",LogicCommon!E4) -> 取引先補助マスタ登録 | I4: Ope.Name : | J4: 登録 | K4: SuperLogicID : | L4: =IF(LogicCommon!G4="","",LogicCommon!G4) -> MA.MAUDL5010
A5: * | E5: ACType :
A6: * | D6: 概要 : | E6: 登録処理を行う | L6: ID | N6: ID | P6: ID | R6: ID
A7: # | I7: U | K7: o | L7: CALL_OPE01.chk01 | M7: o | N7: CALL_OPE01.upd01 | O7: o | Q7: o
A8: # | D8: ブロック名 Block Name | E8: 型 Type | G8: super/share | H8: 対象ブロック名 Target Block Name | K8: TargetName | L8: OPE.MA.MABCL0420.BpSub_UpdChk01 | M8: TargetName | N8: OPE.MA.MABCL0420.BpSub_Upd01 | O8: TargetName | Q8: TargetName | U8: ブロック備考 Block Remarks
A9: # | D9: 項目名 Field Name | E9: 型 Type | F9: 桁 Digits | G9: フルネーム Full Name | H9: 日本語名 Japanese Name | I9: 上り項目 Request Message Field | J9: 下り項目 Response Message Field | S9: 条件および編集方法 Conditions and Editing Methods | U9: 項目備考 Field Remarks
A10: # | K10: 上り項目 Request Message Field | L10: 下り項目 Response Message Field | M10: 上り項目 Request Message Field | N10: 下り項目 Response Message Field | O10: 上り項目 Request Message Field | P10: 下り項目 Response Message Field | Q10: 上り項目 Request Message Field | R10: 下り項目 Response Message Field
A11: 10 | B11: * | D11: Upd01_Dtl | E11: L | G11: $share$ | H11: MA.MABCL0420.BpSub_Upd01.BpSub_Upd01_Dtl | K11: BpSub_UpdChk01_Dtl | M11: BpSub_Upd01_Dtl
A12: 10 | D12: bp_cd | E12: #MA.BP_CD | G12: BP cd. | H12: 取引先ＣＤ | I12: E | K12: E | M12: E
A13: 10 | D13: st_dt_key | E13: #MA.DT | G13: Application start date_[Before change] | H13: 適用開始日_[変更前] | I13: E | K13: E | M13: E
A14: 10 | D14: st_dt | E14: #MA.DT | G14: Application start date | H14: 適用開始日 | I14: E | K14: E | M14: E
A15: 10 | D15: end_dt | E15: #MA.DT | G15: Application end date | H15: 適用終了日 | I15: E | K15: E | M15: E
A16: 10 | D16: zip_cd | E16: #MA.ZIP_CD | G16: Zip code | H16: 郵便番号 | I16: E | K16: E | M16: E
A17: 10 | D17: addr1 | E17: #MA.ADDR1 | G17: Address 1 | H17: 住所１ | I17: E | K17: E | M17: E
A18: 10 | D18: addr2 | E18: #MA.ADDR2 | G18: Address 2 | H18: 住所２ | I18: E | K18: E | M18: E
A19: 10 | D19: addr3 | E19: #MA.ADDR3 | G19: Address 3 | H19: 住所３ | I19: E | K19: E | M19: E
A20: 10 | D20: addr4 | E20: #MA.ADDR4 | G20: Address 4 | H20: 住所４ | I20: E | K20: E | M20: E
A21: 10 | D21: tel | E21: #MA.TEL | G21: TEL | H21: ＴＥＬ | I21: E | K21: E | M21: E
A22: 10 | D22: fax | E22: #MA.TEL | G22: FAX | H22: ＦＡＸ | I22: E | K22: E | M22: E
A23: 10 | D23: ar_dpt_cd | E23: #MA.DPT_CD | G23: AR dept. cd. | H23: 債権部門ＣＤ | I23: E | K23: E | M23: E
... A75: 10 | D75: memo20 | E75: #MA.MST_MEMO20 | G75: Memo 20 | H75: メモ２０ | I75: E | K75: E | M75: E
D76: 詳細 :

Sheet Del01
A1: * | B1: * | D1: L | E1: 1
A2: * | D2: オペレーション実装仕様書 Operation Specification Implementation Sheet | E2: ModuleID : | F2: =IF(LogicCommon!C2="","",LogicCommon!C2) -> MA | G2: LogicID : | H2: =IF(LogicCommon!E2="","",LogicCommon!E2) -> MABCL0420 | I2: Ope.ID : | J2: Del01 | K2: Pj.ID : | L2: =IF(LogicCommon!G2="","",LogicCommon!G2) -> MC | M2: Ope.Body : | N2: "mcframe.serverMAUD.MAUDL6010.MAUDL_RLDeleter"
A3: * | D3: =IF(LogicCommon!A3="","",LogicCommon!A3) | E3: SubModuleID : | F3: =IF(LogicCommon!C3="","",LogicCommon!C3) -> MABC | G3: LogicClass : | H3: =IF(LogicCommon!E3="","",LogicCommon!E3) -> MABCL_BpSubReg | I3: Ope.Method : | J3: @ | K3: SuperClassPj.ID : | L3: =IF(LogicCommon!G3="","",LogicCommon!G3) | M3: ReportID : | O3: Gene.Type : | P3: ALL
A4: * | E4: Version : | F4: 000000 | G4: LogicName : | H4: =IF(LogicCommon!E4="","",LogicCommon!E4) -> 取引先補助マスタ登録 | I4: Ope.Name : | J4: 削除 | K4: SuperLogicID : | L4: =IF(LogicCommon!G4="","",LogicCommon!G4) -> MA.MAUDL5010
A5: * | E5: ACType :
A6: * | D6: 概要 : | E6: 削除処理を行う | L6: ID | N6: ID
A7: # | I7: U | K7: o | L7: CALL_OPE01.chk01 | M7: o | N7: CALL_OPE01.del01
A8: # | D8: ブロック名 Block Name | E8: 型 Type | G8: super/share | H8: 対象ブロック名 Target Block Name | K8: TargetName | L8: OPE.MA.MABCL0420.BpSub_DelChk01 | M8: TargetName | N8: OPE.MA.MABCL0420.BpSub_Del01 | Q8: ブロック備考 Block Remarks
A9: # | D9: 項目名 Field Name | E9: 型 Type | F9: 桁 Digits | G9: フルネーム Full Name | H9: 日本語名 Japanese Name | I9: 上り項目 Request Message Field | J9: 下り項目 Response Message Field | O9: 条件および編集方法 Conditions and Editing Methods | Q9: 項目備考 Field Remarks
A10: # | K10: 上り項目 Request Message Field | L10: 下り項目 Response Message Field | M10: 上り項目 Request Message Field | N10: 下り項目 Response Message Field
A11: 10 | B11: * | D11: Del01_Dtl | E11: L | G11: $share$ | H11: MA.MABCL0420.BpSub_Del01.BpSub_Del01_Dtl | K11: BpSub_DelChk01_Dtl | M11: BpSub_Del01_Dtl
A12: 10 | D12: bp_cd | E12: #MA.BP_CD | G12: BP cd. | H12: 取引先ＣＤ | I12: E | K12: E | M12: E
A13: 10 | D13: st_dt | E13: #MA.DT | G13: Application start date | H13: 適用開始日 | I13: E | K13: E | M13: E
A14: 10 | D14: upd_cntr | E14: #MA.UPD_CNT | G14: Update counter | H14: 更新カウンタ | I14: E | K14: E | M14: E
D15: 詳細 :

Sheet 来歴
A1: 変更来歴
A3: Rev. | H3: 修正番号 | O3: 変更内容 | AQ3: 変更箇所
A4: 1 | O4: 初版
A5: 1.1 | H5: MA7031#100 | O5: BpSub_UpdChk01_Dtlブロックに以下の項目を追加 ・memo4～memo20 | AQ5: BpSub_UpdChk01
A6: " | H6: " | O6: BpSub_Upd01_Dtlブロックに以下の項目を追加 ・memo4～memo20 | AQ6: BpSub_Upd01
A7: " | H7: " | O7: Srch01_Cndブロックに以下の項目を追加 ・memo4～memo20 Srch01_Rsltブロックに以下の項目を追加 ・memo4～memo20 | AQ7: Srch01
A8: " | H8: " | O8: Sprt01_Dtlブロックに以下の項目を追加 ・memo4～memo20 | AQ8: Sprt01
A9: " | H9: " | O9: Upd01_Dtlブロックに以下の項目を追加 ・memo4～memo20 | AQ9: Upd01
A10: 1.2 | O10: 英語の名称を追記 | AQ10: 全般
