Workbook

Sheet LogicCommon
A2: ロジック共通定義 | B2: ModuleID : | C2: MA | D2: LogicID : | E2: MABCL0540 | F2: Pj.ID : | G2: MC
B3: SubModuleID : | C3: MABC | D3: LogicClass : | E3: MABCL_CstReg | F3: SuperClassPj.ID :
D4: LogicName : | E4: 得意先登録 | F4: SuperLogicID : | G4: MA.MAUDL5010
A5: 概要 :
A6: 詳細 :

Sheet BpCst_UpdChk01
A1: * | B1: * | D1: L | E1: 1
A2: * | D2: オペレーション実装仕様書 Operation Specification Implementation Sheet | E2: ModuleID : | F2: =IF(LogicCommon!C2="","",LogicCommon!C2) -> MA | G2: LogicID : | H2: =IF(LogicCommon!E2="","",LogicCommon!E2) -> MABCL0540 | I2: Ope.ID : | J2: BpCst_UpdChk01 | K2: Pj.ID : | L2: =IF(LogicCommon!G2="","",LogicCommon!G2) -> MC | M2: Ope.Body : | N2: =L4 & ".Checker" -> MA.MAUDL5010.Checker
A3: * | E3: SubModuleID : | F3: =IF(LogicCommon!C3="","",LogicCommon!C3) -> MABC | G3: LogicClass : | H3: =IF(LogicCommon!E3="","",LogicCommon!E3) -> MABCL_CstReg | I3: Ope.Method : | J3: @ | K3: SuperClassPj.ID : | L3: =IF(LogicCommon!G3="","",LogicCommon!G3) | M3: ReportID : | O3: Gene.Type : | P3: ALL
A4: * | E4: Version : | F4: 000000 | G4: LogicName : | H4: =IF(LogicCommon!E4="","",LogicCommon!E4) -> 得意先登録 | I4: Ope.Name : | J4: チェック | K4: SuperLogicID : | L4: =IF(LogicCommon!G4="","",LogicCommon!G4) -> MA.MAUDL5010
A5: * | E5: ACType :
A6: * | D6: 概要 : | E6: 取引先マスタの登録前のチェックを行います。 | T6: ID
A7: # | I7: U | K7: K | L7: K | M7: K | N7: K | O7: K | P7: K | Q7: K | R7: K | S7: o
A8: # | D8: ブロック名 Block Name | E8: 型 Type | G8: super/share | H8: 対象ブロック名 Target Block Name | K8: REQUIRED | L8: CONST | M8: LIST_LOGIC | N8: LIST_OUT | O8: LIST_OUT_BASE | P8: LIST_IN | Q8: LIST_IN_BASE | R8: SMALL_LARGE | S8: TargetName | W8: ブロック備考 Block Remarks
A9: # | D9: 項目名 Field Name | E9: 型 Type | F9: 桁 Digits | G9: フルネーム Full Name | H9: 日本語名 Japanese Name | I9: 上り項目 Request Message Field | J9: 下り項目 Response Message Field | U9: 条件および編集方法 Conditions and Editing Methods | W9: 項目備考 Field Remarks
A10: # | S10: 上り項目 Request Message Field | T10: 下り項目 Response Message Field
A11: 10 | B11: * | D11: BpCst_UpdChk01_Dtl | E11: L
A12: 10 | D12: bp_cd | E12: #MA.BP_CD | G12: BP cd. | H12: 取引先ＣＤ | I12: E | K12: E | M12: MA.MAUAL0010.Bp | N12: bcst_flg | O12: bcst_flg | P12: MAC_BP_IS_SRCH_TYP.CST | Q12: bp_is_srch_typ
A13: 10 | D13: acst_cd | E13: #MA.BP_CD | G13: AR customer cd. | H13: 売掛先ＣＤ | I13: E | M13: MA.MAUAL0010.Bp | P13: MAC_BP_IS_SRCH_TYP.ACST | Q13: bp_is_srch_typ
A14: 10 | D14: ar_dpt_typ | E14: #MA.AR_DPT_TYP | G14: AR dept. type | H14: 債権部門区分 | I14: E | L14: MAC_AR_DPT_TYP
A15: 10 | D15: ar_dpt_cd | E15: #MA.DPT_CD | G15: AR dept. cd. | H15: 債権部門ＣＤ | I15: E
A16: 10 | D16: check_ar_dpt_cd | E16: #MA.DPT_CD | G16: AR dept. cd. | H16: 債権部門ＣＤ | I16: E | M16: MA.MAUAL0010.Dpt | P16: MAC_DPT_IS_SRCH_TYP.AR;true | Q16: dpt_is_srch_typ;mode_today_flg
A17: 10 | D17: cst_cntct_dpt | E17: #MA.CNTCT_DPT | G17: Customer dept. | H17: 得意先部署 | I17: E
A18: 10 | D18: cst_cntct_psn | E18: #MA.CNTCT_PSN | G18: Customer PIC | H18: 得意先担当者 | I18: E
A19: 10 | D19: cst_cntct_psn_title | E19: #MA.BP_PSN_TITLE | G19: Form of address for Customer PIC | H19: 得意先担当者敬称 | I19: E
A20: 10 | D20: cst_sundry_flg | E20: #MA.FLG | G20: Miscellaneous customer | H20: 得意先諸口 | I20: E
A21: 10 | D21: sls_upri_req_typ | E21: #MA.SLS_UPRI_REQ_TYP | G21: Sales unit price acquisition type | H21: 販売単価取得区分 | I21: E | L21: MAC_SLS_UPRI_REQ_TYP
A22: 10 | D22: sls_upri_cng_flg | E22: #MA.FLG | G22: Allow sales unit price change | H22: 販売単価変更許可 | I22: E
A23: 10 | D23: sls_upri_rnd_typ | E23: #MA.RND_TYP | G23: Sales unit price rounding type | H23: 販売単価端数処理区分 | I23: E | L23: MAC_RND_TYP
A24: 10 | D24: sls_amt_rnd_typ | E24: #MA.RND_TYP | G24: Rounding type (Sales amount) | H24: 売上金額端数処理区分 | I24: E | K24: E | L24: MAC_RND_TYP
A25: 10 | D25: sls_tax_calc_typ | E25: #MA.TAX_CALC_TYP | G25: Sales tax calculation type | H25: 売上税計算区分 | I25: E | L25: MAC_TAX_CALC_TYP
A26: 10 | D26: sls_tax_rnd_typ | E26: #MA.RND_TYP | G26: Sales tax rounding type | H26: 売上税額端数処理区分 | I26: E | K26: E | L26: MAC_RND_TYP
A27: 10 | D27: sls_basis_typ | E27: #MA.SLS_BASIS_TYP | G27: Revenue recording type | H27: 売上計上区分 | I27: E | L27: MAC_SLS_BASIS_TYP
A28: 10 | D28: ship_schd_split_typ | E28: #MA.SHIP_SCHD_SPLIT_TYP | G28: Shipping schedule split type | H28: 出荷予定分割区分 | I28: E | L28: MAC_SHIP_SCHD_SPLIT_TYP
A29: 10 | D29: bill_basis_typ | E29: #MA.BILL_BASIS_TYP | G29: Billing initial base type | H29: 請求起算区分 | I29: E | L29: MAC_BILL_BASIS_TYP
A30: 10 | D30: bill_crryovr_times | E30: #MA.CRRYOVR_TIMES | G30: Billing carry-over count | H30: 請求繰越回数 | I30: E | R30: 0:99
A31: 10 | D31: lot_back_stop_typ | E31: #MA.LOT_BACK_STOP_TYP | G31: Lot reverse prohibit type | H31: ロット逆転禁止区分 | I31: E | L31: MAC_LOT_BACK_STOP_TYP
A32: 10 | D32: slip_each_lot_typ | E32: #MA.SLIP_EACH_LOT_TYP | G32: Lot details split type | H32: ロット明細分割区分 | I32: E | L32: MAC_SLIP_EACH_LOT_TYP
A33: 10 | D33: cst_ship_form_cd | E33: #MA.SLIP_FORM_CD | G33: Customer delivery note cd. | H33: 得意先納品書ＣＤ | I33: E | M33: MA.MAUAL0010.SlipForm
A34: 10 | D34: stk_lst_issue_flg | E34: #MA.FLG | G34: Issue identification tag | H34: 現品票発行 | I34: E
A35: 10 | D35: stk_lst_form_cd | E35: #MA.SLIP_FORM_CD | G35: Identification tag cd. | H35: 現品票ＣＤ | I35: E | M35: MA.MAUAL0010.SlipForm
A36: 10 | D36: sls_tax_cd | E36: #MA.TAX_CD | G36: Sales tax cd. | H36: 売上税ＣＤ | I36: E | M36: MA.MAUAL0010.SlsTax
A37: 10 | D37: sls_tax_cd_prio_flg | E37: #MA.FLG | G37: Sales tax priority | H37: 売上税優先 | I37: E
A38: 10 | D38: wrk_ar_flg | E38: #MA.FLG | G38: AR management by sales project | H38: 案件別債権管理 | I38: E
A39: 10 | D39: cst_iv_flg | E39: #MA.FLG | G39: Customer invoice transaction | H39: 得意先インボイス取引 | I39: E
A40: 10 | D40: ship_lt | E40: #MA.LT | G40: Shipping LT (For demand) | H40: 出荷ＬＴ（需要情報用） | I40: E | R40: 0:
A41: 10 | D41: cst_tterm_cd1 | E41: #MA.TTERM_CD | G41: Customer BP terms cd. 1 | H41: 得意先取引先条件ＣＤ１ | I41: E | M41: MA.MAUAL0010.Tterm1
A42: 10 | D42: cst_tterm_cd2 | E42: #MA.TTERM_CD | G42: Customer BP terms cd. 2 | H42: 得意先取引先条件ＣＤ２ | I42: E | M42: MA.MAUAL0010.Tterm2
A43: 10 | D43: cst_tterm_cd3 | E43: #MA.TTERM_CD | G43: Customer BP terms cd. 3 | H43: 得意先取引先条件ＣＤ３ | I43: E | M43: MA.MAUAL0010.Tterm3
A44: 10 | D44: sls_anly_cd1 | E44: #MA.SLS_ANLY_CD | G44: Sales analysis cd. 1 | H44: 販売分析ＣＤ１ | I44: E | M44: MA.MAUAL0010.SlsAnly1
A45: 10 | D45: sls_anly_cd2 | E45: #MA.SLS_ANLY_CD | G45: Sales analysis cd. 2 | H45: 販売分析ＣＤ２ | I45: E | M45: MA.MAUAL0010.SlsAnly2
A46: 10 | D46: sls_anly_cd3 | E46: #MA.SLS_ANLY_CD | G46: Sales analysis cd. 3 | H46: 販売分析ＣＤ３ | I46: E | M46: MA.MAUAL0010.SlsAnly3
A47: 10 | D47: bcst_flg | E47: #MA.FLG | G47: Billing customer | H47: 請求先 | I47: E
A48: 10 | D48: bcst_cd | E48: #MA.BP_CD | G48: Billing customer cd. | H48: 請求先ＣＤ | I48: E | M48: MA.MAUAL0010.Bp | P48: MAC_BP_IS_SRCH_TYP.BCST;bcst_flg;bp_cd | Q48: bp_is_srch_typ;check_rem_flg;ref_bp_cd
A49: 10 | D49: cst_prnt_typ | E49: #MA.PRNT_TYP | G49: Report issue type (Customer) | H49: 帳票発行区分（得意先） | I49: E | L49: MAC_PRNT_TYP
A50: 10 | D50: upd_cntr | E50: #MA.UPD_CNT | G50: Update counter | H50: 更新カウンタ | I50: E
A51: 10 | D51: not_lg_mix_flg | E51: #MA.FLG | G51: Prohibit mixed distribution group flg. | H51: 物流グループ混在不可ＦＬＧ | I51: E
A52: 10 | D52: not_lot_mix_flg | E52: #MA.FLG | G52: Prohibit mixed lots flg. | H52: ロット混在不可ＦＬＧ | I52: E
A53: 10 | D53: not_sublot_mix_flg | E53: #MA.FLG | G53: Prohibit mixed sublots flg. | H53: サブロット混在不可ＦＬＧ | I53: E
D54: 詳細 :

Sheet BpCst_Upd01
A1: * | B1: * | D1: L | E1: 1
A2: * | D2: オペレーション実装仕様書 Operation Specification Implementation Sheet | E2: ModuleID : | F2: =IF(LogicCommon!C2="","",LogicCommon!C2) -> MA | G2: LogicID : | H2: =IF(LogicCommon!E2="","",LogicCommon!E2) -> MABCL0540 | I2: Ope.ID : | J2: BpCst_Upd01 | K2: Pj.ID : | L2: =IF(LogicCommon!G2="","",LogicCommon!G2) -> MC | M2: Ope.Body : | N2: "mcframe.serverMAUD.MAUDL6010.MAUDL_RLUpdater"
A3: * | E3: SubModuleID : | F3: =IF(LogicCommon!C3="","",LogicCommon!C3) -> MABC | G3: LogicClass : | H3: =IF(LogicCommon!E3="","",LogicCommon!E3) -> MABCL_CstReg | I3: Ope.Method : | J3: @ | K3: SuperClassPj.ID : | L3: =IF(LogicCommon!G3="","",LogicCommon!G3) | M3: ReportID : | O3: Gene.Type : | P3: ALL
A4: * | E4: Version : | F4: 000000 | G4: LogicName : | H4: =IF(LogicCommon!E4="","",LogicCommon!E4) -> 得意先登録 | I4: Ope.Name : | J4: 登録 | K4: SuperLogicID : | L4: =IF(LogicCommon!G4="","",LogicCommon!G4) -> MA.MAUDL5010
A5: * | E5: ACType :
A6: * | D6: 概要 : | E6: 取引先マスタの登録を行います。 | L6: ID | N6: ID | P6: ID | R6: ID
A7: # | I7: U | K7: o | L7: UPDATE.updMaster | M7: o | N7: MAIN.chkMaster | O7: o | Q7: o
A8: # | D8: ブロック名 Block Name | E8: 型 Type | G8: super/share | H8: 対象ブロック名 Target Block Name | K8: TargetName | L8: DBC.MA.MAM_BP | M8: TargetName | N8: DBC.MA.MAM_BP | O8: TargetName | Q8: TargetName | U8: ブロック備考 Block Remarks
A9: # | D9: 項目名 Field Name | E9: 型 Type | F9: 桁 Digits | G9: フルネーム Full Name | H9: 日本語名 Japanese Name | I9: 上り項目 Request Message Field | J9: 下り項目 Response Message Field | S9: 条件および編集方法 Conditions and Editing Methods | U9: 項目備考 Field Remarks
A10: # | K10: 上り項目 Request Message Field | L10: 下り項目 Response Message Field | M10: 上り項目 Request Message Field | N10: 下り項目 Response Message Field | O10: 上り項目 Request Message Field | P10: 下り項目 Response Message Field | Q10: 上り項目 Request Message Field | R10: 下り項目 Response Message Field
A11: 10 | B11: * | D11: BpCst_Upd01_Dtl | E11: L | G11: $share$ | H11: MA.MABCL0540.BpCst_UpdChk01.BpCst_UpdChk01_Dtl | K11: L | M11: L
A12: 10 | D12: bp_cd | E12: #MA.BP_CD | G12: BP cd. | H12: 取引先ＣＤ | I12: E | K12: E | M12: E
A13: 10 | D13: acst_cd | E13: #MA.BP_CD | G13: AR customer cd. | H13: 売掛先ＣＤ | I13: E | K13: E
A14: 10 | D14: ar_dpt_typ | E14: #MA.AR_DPT_TYP | G14: AR dept. type | H14: 債権部門区分 | I14: E | K14: E
A15: 10 | D15: ar_dpt_cd | E15: #MA.DPT_CD | G15: AR dept. cd. | H15: 債権部門ＣＤ | I15: E | K15: E
A16: 10 | D16: cst_cntct_dpt | E16: #MA.CNTCT_DPT | G16: Customer dept. | H16: 得意先部署 | I16: E | K16: E
A17: 10 | D17: cst_cntct_psn | E17: #MA.CNTCT_PSN | G17: Customer PIC | H17: 得意先担当者 | I17: E | K17: E
A18: 10 | D18: cst_cntct_psn_title | E18: #MA.BP_PSN_TITLE | G18: Form of address for Customer PIC | H18: 得意先担当者敬称 | I18: E | K18: E
A19: 10 | D19: cst_sundry_flg | E19: #MA.FLG | G19: Miscellaneous customer | H19: 得意先諸口 | I19: E | K19: E
A20: 10 | D20: sls_upri_req_typ | E20: #MA.SLS_UPRI_REQ_TYP | G20: Sales unit price acquisition type | H20: 販売単価取得区分 | I20: E | K20: E
A21: 10 | D21: sls_upri_cng_flg | E21: #MA.FLG | G21: Allow sales unit price change | H21: 販売単価変更許可 | I21: E | K21: E
A22: 10 | D22: sls_upri_rnd_typ | E22: #MA.RND_TYP | G22: Sales unit price rounding type | H22: 販売単価端数処理区分 | I22: E | K22: E
A23: 10 | D23: sls_amt_rnd_typ | E23: #MA.RND_TYP | G23: Rounding type (Sales amount) | H23: 売上金額端数処理区分 | I23: E | K23: E
A24: 10 | D24: sls_tax_calc_typ | E24: #MA.TAX_CALC_TYP | G24: Sales tax calculation type | H24: 売上税計算区分 | I24: E | K24: E
... A51: 10 | D51: not_sublot_mix_flg | E51: #MA.FLG | G51: Prohibit mixed sublots flg. | H51: サブロット混在不可ＦＬＧ | I51: E | K51: E
D52: 詳細 :

Sheet Srch01
A1: * | B1: * | D1: L | E1: 1
A2: * | D2: オペレーション実装仕様書 Operation Specification Implementation Sheet | E2: ModuleID : | F2: =IF(LogicCommon!C2="","",LogicCommon!C2) -> MA | G2: LogicID : | H2: =IF(LogicCommon!E2="","",LogicCommon!E2) -> MABCL0540 | I2: Ope.ID : | J2: Srch01 | K2: Pj.ID : | L2: =IF(LogicCommon!G2="","",LogicCommon!G2) -> MC | M2: Ope.Body : | N2: "mcframe.serverMAUD.MAUDL6010.MAUDL_RLSearcher"
A3: * | D3: =IF(LogicCommon!A3="","",LogicCommon!A3) | E3: SubModuleID : | F3: =IF(LogicCommon!C3="","",LogicCommon!C3) -> MABC | G3: LogicClass : | H3: =IF(LogicCommon!E3="","",LogicCommon!E3) -> MABCL_CstReg | I3: Ope.Method : | J3: @ | K3: SuperClassPj.ID : | L3: =IF(LogicCommon!G3="","",LogicCommon!G3) | M3: ReportID : | O3: Gene.Type : | P3: ALL
A4: * | E4: Version : | F4: 000000 | G4: LogicName : | H4: =IF(LogicCommon!E4="","",LogicCommon!E4) -> 得意先登録 | I4: Ope.Name : | J4: 検索 | K4: SuperLogicID : | L4: =IF(LogicCommon!G4="","",LogicCommon!G4) -> MA.MAUDL5010
A5: * | E5: ACType :
A6: * | D6: 概要 : | E6: 得意先関連マスタの検索を行います。 | M6: ID | O6: ID | Q6: ID | S6: ID | U6: ID | W6: ID | Y6: ID | AA6: ID
A7: # | I7: U | K7: K | L7: o | M7: SELECT.c0 | N7: o | O7: SELECT_SUB1.c1 | P7: o | Q7: SELECT_SUB2.c2 | R7: o | S7: SELECT_SUB3.c3 | T7: o | U7: SELECT_SUB4.c4 | V7: o | W7: SELECT_SUB5.c5 | X7: o | Y7: SELECT_SUB6.c6 | Z7: o | AA7: SELECT_SUB7.c7
A8: # | D8: ブロック名 Block Name | E8: 型 Type | G8: super/share | H8: 対象ブロック名 Target Block Name | K8: CONST | L8: TargetName | M8: DBC.MA.MAM_BP | N8: TargetName | O8: DBC.MA.MAM_CST_USR | P8: TargetName | Q8: DBC.MA.MAM_CST_SLS_UPRI_RANK | R8: TargetName | S8: DBC.MA.MAM_CST_DLV | T8: TargetName | U8: DBC.MA.MAM_SHIP_VALID_CTL | V8: TargetName | W8: DBC.MA.MAM_SLO_ALLOC_GD | X8: TargetName | Y8: DBC.MA.MAM_EDI_IF_CTL | Z8: TargetName | AA8: DBC.MA.MAM_BP_ITM | AD8: ブロック備考 Block Remarks
A9: # | D9: 項目名 Field Name | E9: 型 Type | F9: 桁 Digits | G9: フルネーム Full Name | H9: 日本語名 Japanese Name | I9: 上り項目 Request Message Field | J9: 下り項目 Response Message Field | AB9: 条件および編集方法 Conditions and Editing Methods | AD9: 項目備考 Field Remarks
A10: # | L10: 上り項目 Request Message Field | M10: 下り項目 Response Message Field | N10: 上り項目 Request Message Field | O10: 下り項目 Response Message Field | P10: 上り項目 Request Message Field | Q10: 下り項目 Response Message Field | R10: 上り項目 Request Message Field | S10: 下り項目 Response Message Field | T10: 上り項目 Request Message Field | U10: 下り項目 Response Message Field | V10: 上り項目 Request Message Field | W10: 下り項目 Response Message Field | X10: 上り項目 Request Message Field | Y10: 下り項目 Response Message Field | Z10: 上り項目 Request Message Field | AA10: 下り項目 Response Message Field
A11: 10 | B11: * | D11: Srch01_Cnd | E11: R
A12: 10 | D12: st_dt_fr | E12: #MA.DT | G12: Application start date FROM | H12: 適用開始日ＦＲＯＭ | I12: E
A13: 10 | D13: st_dt_to | E13: #MA.DT | G13: Application start date TO | H13: 適用開始日ＴＯ | I13: E
A14: 10 | D14: end_dt_fr | E14: #MA.DT | G14: Application end date FROM | H14: 適用終了日ＦＲＯＭ | I14: E
A15: 10 | D15: end_dt_to | E15: #MA.DT | G15: Application end date TO | H15: 適用終了日ＴＯ | I15: E
A16: 10 | D16: bp_cd | E16: #MA.BP_CD | G16: BP cd. | H16: 取引先ＣＤ | I16: E
A17: 10 | D17: bp_nm | E17: #MA.BP_NM | G17: BP name | H17: 取引先名 | I17: E
A18: 10 | D18: off_del_flg | E18: #MA.FLG | G18: Logical delete. Off | H18: 論理削除.オフ | I18: E
A19: 10 | D19: on_del_flg | E19: #MA.FLG | G19: Logical delete. On | H19: 論理削除.オン | I19: E
A21: 20 | B21: * | D21: Srch01_Rslt1 | E21: L | M21: L
A22: 20 | D22: bp_cd | E22: #MA.BP_CD | G22: BP cd. | H22: 取引先ＣＤ | J22: E | M22: E
A23: 20 | D23: acst_flg | E23: #MA.FLG | G23: AR customer | H23: 売掛先 | J23: E | M23: E
A24: 20 | D24: acst_cd | E24: #MA.BP_CD | G24: AR customer cd. | H24: 売掛先ＣＤ | J24: E | M24: E
A25: 20 | D25: acst_nm | E25: #MA.BP_NM | G25: AR customer name | H25: 売掛先名 | J25: E | M25: E
A26: 20 | D26: ar_dpt_typ | E26: #MA.AR_DPT_TYP | G26: AR dept. type | H26: 債権部門区分 | J26: E | K26: MAC_AR_DPT_TYP | M26: E
A27: 20 | D27: ar_dpt_typ_nm | E27: =E26&"_NM" -> #MA.AR_DPT_TYP_NM | G27: AR dept. type name | H27: 債権部門区分名 | J27: E
A28: 20 | D28: ar_dpt_cd | E28: #MA.DPT_CD | G28: AR dept. cd. | H28: 債権部門ＣＤ | J28: E | M28: E
A29: 20 | D29: ar_dpt_nm | E29: #MA.DPT_NM | G29: AR dept. name | H29: 債権部門名 | J29: E | M29: E
A30: 20 | D30: cst_cntct_dpt | E30: #MA.CNTCT_DPT | G30: Customer dept. | H30: 得意先部署 | J30: E | M30: E
A31: 20 | D31: cst_cntct_psn | E31: #MA.CNTCT_PSN | G31: Customer PIC | H31: 得意先担当者 | J31: E | M31: E
A32: 20 | D32: cst_cntct_psn_title | E32: #MA.BP_PSN_TITLE | G32: Form of address for Customer PIC | H32: 得意先担当者敬称 | J32: E | M32: E
A33: 20 | D33: cst_sundry_flg | E33: #MA.FLG | G33: Miscellaneous customer | H33: 得意先諸口 | J33: E | M33: E
A34: 20 | D34: sls_upri_req_typ | E34: #MA.SLS_UPRI_REQ_TYP | G34: Sales unit price acquisition type | H34: 販売単価取得区分 | J34: E | K34: MAC_SLS_UPRI_REQ_TYP | M34: E
A35: 20 | D35: =D34&"_nm" -> sls_upri_req_typ_nm | E35: =E34&"_NM" -> #MA.SLS_UPRI_REQ_TYP_NM | G35: Sales unit price acquisition type name | H35: 販売単価取得区分名 | J35: E
A36: 20 | D36: sls_upri_cng_flg | E36: #MA.FLG | G36: Allow sales unit price change | H36: 販売単価変更許可 | J36: E | M36: E
A37: 20 | D37: sls_upri_rnd_typ | E37: #MA.RND_TYP | G37: Sales unit price rounding type | H37: 販売単価端数処理区分 | J37: E | K37: MAC_RND_TYP | M37: E
A38: 20 | D38: =D37&"_nm" -> sls_upri_rnd_typ_nm | E38: =E37&"_NM" -> #MA.RND_TYP_NM | G38: Sales unit rounding type name | H38: 販売単価端数処理区分名 | J38: E
A39: 20 | D39: sls_amt_rnd_typ | E39: #MA.RND_TYP | G39: Rounding type (Sales amount) | H39: 売上金額端数処理区分 | J39: E | K39: MAC_RND_TYP | M39: E
A40: 20 | D40: =D39&"_nm" -> sls_amt_rnd_typ_nm | E40: =E39&"_NM" -> #MA.RND_TYP_NM | G40: Rounding type name (Sales amount) | H40: 売上金額端数処理区分名 | J40: E
A41: 20 | D41: sls_tax_calc_typ | E41: #MA.TAX_CALC_TYP | G41: Sales tax calculation type | H41: 売上税計算区分 | J41: E | K41: MAC_TAX_CALC_TYP | M41: E
A42: 20 | D42: =D41&"_nm" -> sls_tax_calc_typ_nm | E42: =E41&"_NM" -> #MA.TAX_CALC_TYP_NM | G42: Sales tax calculation type name | H42: 売上税計算区分名 | J42: E
A43: 20 | D43: sls_tax_rnd_typ | E43: #MA.RND_TYP | G43: Sales tax rounding type | H43: 売上税額端数処理区分 | J43: E | K43: MAC_RND_TYP | M43: E
A44: 20 | D44: =D43&"_nm" -> sls_tax_rnd_typ_nm | E44: =E43&"_NM" -> #MA.RND_TYP_NM | G44: Rounding type | H44: 売上税額端数処理区分名 | J44: E
A45: 20 | D45: sls_basis_typ | E45: #MA.SLS_BASIS_TYP | G45: Revenue recording type | H45: 売上計上区分 | J45: E | K45: MAC_SLS_BASIS_TYP | M45: E
A46: 20 | D46: =D45&"_nm" -> sls_basis_typ_nm | E46: =E45&"_NM" -> #MA.SLS_BASIS_TYP_NM | G46: Revenue recording type name | H46: 売上計上区分名 | J46: E
A47: 20 | D47: ship_schd_split_typ | E47: #MA.SHIP_SCHD_SPLIT_TYP | G47: Shipping schedule split type | H47: 出荷予定分割区分 | J47: E | K47: MAC_SHIP_SCHD_SPLIT_TYP | M47: E
A48: 20 | D48: =D47&"_nm" -> ship_schd_split_typ_nm | E48: =E47&"_NM" -> #MA.SHIP_SCHD_SPLIT_TYP_NM | G48: Shipping schedule split type name | H48: 出荷予定分割区分名 | J48: E
A49: 20 | D49: bill_basis_typ | E49: #MA.BILL_BASIS_TYP | G49: Billing initial base type | H49: 請求起算区分 | J49: E | K49: MAC_BILL_BASIS_TYP | M49: E
A50: 20 | D50: =D49&"_nm" -> bill_basis_typ_nm | E50: =E49&"_NM" -> #MA.BILL_BASIS_TYP_NM | G50: Billing calculation base type name | H50: 請求起算区分名 | J50: E
A51: 20 | D51: bill_crryovr_times | E51: #MA.CRRYOVR_TIMES | G51: Billing carry-over count | H51: 請求繰越回数 | J51: E | M51: E
A52: 20 | D52: lot_back_stop_typ | E52: #MA.LOT_BACK_STOP_TYP | G52: Lot reverse prohibit type | H52: ロット逆転禁止区分 | J52: E | K52: MAC_LOT_BACK_STOP_TYP | M52: E
A53: 20 | D53: =D52&"_nm" -> lot_back_stop_typ_nm | E53: =E52&"_NM" -> #MA.LOT_BACK_STOP_TYP_NM | G53: Lot reverse prohibit type name | H53: ロット逆転禁止区分名 | J53: E
A54: 20 | D54: slip_each_lot_typ | E54: #MA.SLIP_EACH_LOT_TYP | G54: Lot details split type | H54: ロット明細分割区分 | J54: E | K54: MAC_SLIP_EACH_LOT_TYP | M54: E
A55: 20 | D55: =D54&"_nm" -> slip_each_lot_typ_nm | E55: =E54&"_NM" -> #MA.SLIP_EACH_LOT_TYP_NM | G55: Lot details split type name | H55: ロット明細分割区分名 | J55: E
A56: 20 | D56: cst_ship_form_cd | E56: #MA.SLIP_FORM_CD | G56: Customer delivery note cd. | H56: 得意先納品書ＣＤ | J56: E | M56: E
A57: 20 | D57: cst_ship_form_nm | E57: #MA.SLIP_FORM_NM | G57: Customer delivery note name | H57: 得意先納品書名 | J57: E | M57: E
A58: 20 | D58: stk_lst_issue_flg | E58: #MA.FLG | G58: Issue identification tag | H58: 現品票発行 | J58: E | M58: E
A59: 20 | D59: stk_lst_form_cd | E59: #MA.SLIP_FORM_CD | G59: Identification tag cd. | H59: 現品票ＣＤ | J59: E | M59: E
A60: 20 | D60: stk_lst_form_nm | E60: #MA.SLIP_FORM_NM | G60: Identification tag name | H60: 現品票名 | J60: E | M60: E
A61: 20 | D61: sls_tax_cd | E61: #MA.TAX_CD | G61: Sales tax cd. | H61: 売上税ＣＤ | J61: E | M61: E
A62: 20 | D62: sls_tax_nm | E62: #MA.TAX_NM | G62: Sales tax name | H62: 売上税名 | J62: E | M62: E
A63: 20 | D63: sls_tax_cd_prio_flg | E63: #MA.FLG | G63: Sales tax priority | H63: 売上税優先 | J63: E | M63: E
A64: 20 | D64: wrk_ar_flg | E64: #MA.FLG | G64: AR management by sales project | H64: 案件別債権管理 | J64: E | M64: E
A65: 20 | D65: cst_iv_flg | E65: #MA.FLG | G65: Customer invoice transaction | H65: 得意先インボイス取引 | J65: E | M65: E
A66: 20 | D66: ship_lt | E66: #MA.LT | G66: Shipping LT (For demand) | H66: 出荷ＬＴ（需要情報用） | J66: E | M66: E
A67: 20 | D67: cst_tterm_cd1 | E67: #MA.TTERM_CD | G67: Customer BP terms cd. 1 | H67: 得意先取引先条件ＣＤ１ | J67: E | M67: E
... A81: 20 | D81: bcst_nm | E81: #MA.BP_NM | G81: Billing customer name | H81: 請求先名 | J81: E | M81: E
A82: 20 | D82: cst_prnt_typ | E82: #MA.PRNT_TYP | G82: Report issue type (Customer) | H82: 帳票発行区分（得意先） | J82: E | K82: MAC_PRNT_TYP | M82: E
A83: 20 | D83: cst_prnt_typ_nm | E83: #MA.PRNT_TYP_NM | G83: Report issue type name (Customer) | H83: 帳票発行区分名（得意先） | J83: E
A84: 20 | D84: ins_usr_id | E84: #MA.FCM_USR_ID | G84: Entry user ID | H84: 登録ユーザＩＤ | J84: E | M84: E
A85: 20 | D85: ins_usr_nm | E85: #MA.FCM_USR_NM | G85: Entry user name | H85: 登録ユーザ名 | J85: E | M85: E
A86: 20 | D86: ins_ts | E86: #MA.SYS_TS | G86: Entry date and time | H86: 登録日時 | J86: E | M86: E
A87: 20 | D87: ins_func_id | E87: #MA.FUNC_ID | G87: Entry function ID | H87: 登録機能ＩＤ | J87: E | M87: E
A88: 20 | D88: ins_func_nm | E88: #MA.FUNC_NM | G88: Entry function name | H88: 登録機能名 | J88: E
A89: 20 | D89: upd_cntr | E89: #MA.UPD_CNT | G89: Update counter | H89: 更新カウンタ | J89: E | M89: E
A90: 20 | D90: upd_usr_id | E90: #MA.FCM_USR_ID | G90: Update user ID | H90: 更新ユーザＩＤ | J90: E | M90: E
A91: 20 | D91: upd_usr_nm | E91: #MA.FCM_USR_NM | G91: Update user name | H91: 更新ユーザ名 | J91: E | M91: E
A92: 20 | D92: upd_ts | E92: #MA.SYS_TS | G92: Update date and time | H92: 更新日時 | J92: E | M92: E
A93: 20 | D93: upd_func_id | E93: #MA.FUNC_ID | G93: Update function ID | H93: 更新機能ＩＤ | J93: E | M93: E
A94: 20 | D94: upd_func_nm | E94: #MA.FUNC_NM | G94: Update function name | H94: 更新機能名 | J94: E
A95: 20 | D95: upd_srv_req_no | E95: #MA.SRV_REQ_NO | G95: Update request No. | H95: 更新リクエストＮＯ | J95: E | M95: E
A96: 20 | D96: del_usr_id | E96: #MA.FCM_USR_ID | G96: Logical delete user ID | H96: 論理削除ユーザＩＤ | J96: E | M96: E
A97: 20 | D97: del_usr_nm | E97: #MA.FCM_USR_NM | G97: Logical delete user name | H97: 論理削除ユーザ名 | J97: E | M97: E
A98: 20 | D98: del_ts | E98: #MA.SYS_TS | G98: Logical delete date and time | H98: 論理削除日時 | J98: E | M98: E
A99: 20 | D99: not_lg_mix_flg | E99: #MA.FLG | G99: Prohibit mixed distribution group flg. | H99: 物流グループ混在不可ＦＬＧ | J99: E | M99: E
A100: 20 | D100: not_lot_mix_flg | E100: #MA.FLG | G100: Prohibit mixed lots flg. | H100: ロット混在不可ＦＬＧ | J100: E | M100: E
A101: 20 | D101: not_sublot_mix_flg | E101: #MA.FLG | G101: Prohibit mixed sublots flg. | H101: サブロット混在不可ＦＬＧ | J101: E | M101: E
A103: 30 | B103: * | D103: Srch01_Rslt2 | E103: L | O103: L
A104: 30 | D104: del_flg | E104: #MA.FLG | G104: Logical delete | H104: 論理削除 | J104: E | O104: E
A105: 30 | D105: cst_cd | E105: #MA.BP_CD | G105: Customer cd. | H105: 得意先ＣＤ | J105: E | O105: E
A106: 30 | D106: st_dt | E106: #MA.DT | G106: Application start date | H106: 適用開始日 | J106: E | O106: E
A107: 30 | D107: end_dt | E107: #MA.DT | G107: Application end date | H107: 適用終了日 | J107: E | O107: E
A108: 30 | D108: usr_cd | E108: #MA.USR_ID | G108: PIC cd. | H108: 担当者ＣＤ | J108: E | O108: E
A109: 30 | D109: usr_nm | E109: #MA.USR_NM | G109: PIC name | H109: 担当者名 | J109: E | O109: E
A110: 30 | D110: dpt_cd | E110: #MA.DPT_CD | G110: Dept. cd. | H110: 部門ＣＤ | J110: E | O110: E
A111: 30 | D111: dpt_nm | E111: #MA.DPT_NM | G111: Dept. name | H111: 部門名 | J111: E | O111: E
A112: 30 | D112: memo1 | E112: #MA.MST_MEMO1 | G112: Memo 1 | H112: メモ１ | J112: E | O112: E
A113: 30 | D113: memo2 | E113: #MA.MST_MEMO2 | G113: Memo 2 | H113: メモ２ | J113: E | O113: E
A114: 30 | D114: memo3 | E114: #MA.MST_MEMO3 | G114: Memo 3 | H114: メモ３ | J114: E | O114: E
A115: 30 | D115: ins_usr_id | E115: #MA.FCM_USR_ID | G115: Entry user ID | H115: 登録ユーザＩＤ | J115: E | O115: E
...

Sheet Upd01
A1: * | B1: * | D1: L | E1: 1
A2: * | D2: オペレーション実装仕様書 Operation Specification Implementation Sheet | E2: ModuleID : | F2: =IF(LogicCommon!C2="","",LogicCommon!C2) -> MA | G2: LogicID : | H2: =IF(LogicCommon!E2="","",LogicCommon!E2) -> MABCL0540 | I2: Ope.ID : | J2: Upd01 | K2: Pj.ID : | L2: =IF(LogicCommon!G2="","",LogicCommon!G2) -> MC | M2: Ope.Body : | N2: "mcframe.serverMAUD.MAUDL6010.MAUDL_RLUpdater"
A3: * | D3: =IF(LogicCommon!A3="","",LogicCommon!A3) | E3: SubModuleID : | F3: =IF(LogicCommon!C3="","",LogicCommon!C3) -> MABC | G3: LogicClass : | H3: =IF(LogicCommon!E3="","",LogicCommon!E3) -> MABCL_CstReg | I3: Ope.Method : | J3: @ | K3: SuperClassPj.ID : | L3: =IF(LogicCommon!G3="","",LogicCommon!G3) | M3: ReportID : | O3: Gene.Type : | P3: ALL
A4: * | E4: Version : | F4: 000000 | G4: LogicName : | H4: =IF(LogicCommon!E4="","",LogicCommon!E4) -> 得意先登録 | I4: Ope.Name : | J4: 登録 | K4: SuperLogicID : | L4: =IF(LogicCommon!G4="","",LogicCommon!G4) -> MA.MAUDL5010
A5: * | E5: ACType :
A6: * | D6: 概要 : | E6: 得意先関連マスタの登録を行います。 | L6: ID | N6: ID | P6: ID | R6: ID | T6: ID | V6: ID | X6: ID | Z6: ID | AB6: ID | AD6: ID | AF6: ID | AH6: ID | AJ6: ID | AL6: ID | AN6: ID | AP6: ID
A7: # | I7: U | K7: o | L7: CALL_OPE01.chk01 | M7: o | N7: CALL_OPE01.upd01 | O7: o | P7: CALL_OPE02.chk02 | Q7: o | R7: CALL_OPE02.upd02 | S7: o | T7: CALL_OPE03.chk03 | U7: o | V7: CALL_OPE03.upd03 | W7: o | X7: CALL_OPE04.chk04 | Y7: o | Z7: CALL_OPE04.upd04 | AA7: o | AB7: CALL_OPE05.chk05 | AC7: o | AD7: CALL_OPE05.upd05 | AE7: o | AF7: CALL_OPE06.chk06 | AG7: o | AH7: CALL_OPE06.upd06 | AI7: o | AJ7: CALL_OPE07.chk07 | AK7: o | AL7: CALL_OPE07.upd07 | AM7: o | AN7: CALL_OPE08.chk08 | AO7: o | AP7: CALL_OPE08.upd08
A8: # | D8: ブロック名 Block Name | E8: 型 Type | G8: super/share | H8: 対象ブロック名 Target Block Name | K8: TargetName | L8: OPE.MA.MABCL0540.BpCst_UpdChk01 | M8: TargetName | N8: OPE.MA.MABCL0540.BpCst_Upd01 | O8: TargetName | P8: OPE.MA.MABSL0650.CstUsr_UpdChk01 | Q8: TargetName | R8: OPE.MA.MABSL0650.CstUsr_Upd01 | S8: TargetName | T8: OPE.MA.MABSL0230.CstSlsUpriRank_UpdChk01 | U8: TargetName | V8: OPE.MA.MABSL0230.CstSlsUpriRank_Upd01 | W8: TargetName | X8: OPE.MA.MABSL0660.CstDlv_UpdChk01 | Y8: TargetName | Z8: OPE.MA.MABSL0660.CstDlv_Upd01 | AA8: TargetName | AB8: OPE.MA.MABSL0480.ShipValidCtl_UpdChk01 | AC8: TargetName | AD8: OPE.MA.MABSL0480.ShipValidCtl_Upd01 | AE8: TargetName | AF8: OPE.MA.MABSL0520.SloAllocGd_UpdChk01 | AG8: TargetName | AH8: OPE.MA.MABSL0520.SloAllocGd_Upd01 | AI8: TargetName | AJ8: OPE.MA.MABSL1230.EdiIfCtl_UpdChk01 | AK8: TargetName | AL8: OPE.MA.MABSL1230.EdiIfCtl_Upd01 | AM8: TargetName | AN8: OPE.MA.MABSL0640.BpItm_UpdChk01 | AO8: TargetName | AP8: OPE.MA.MABSL0640.BpItm_Upd01 | AS8: ブロック備考 Block Remarks
A9: # | D9: 項目名 Field Name | E9: 型 Type | F9: 桁 Digits | G9: フルネーム Full Name | H9: 日本語名 Japanese Name | I9: 上り項目 Request Message Field | J9: 下り項目 Response Message Field | AQ9: 条件および編集方法 Conditions and Editing Methods | AS9: 項目備考 Field Remarks
A10: # | K10: 上り項目 Request Message Field | L10: 下り項目 Response Message Field | M10: 上り項目 Request Message Field | N10: 下り項目 Response Message Field | O10: 上り項目 Request Message Field | P10: 下り項目 Response Message Field | Q10: 上り項目 Request Message Field | R10: 下り項目 Response Message Field | S10: 上り項目 Request Message Field | T10: 下り項目 Response Message Field | U10: 上り項目 Request Message Field | V10: 下り項目 Response Message Field | W10: 上り項目 Request Message Field | X10: 下り項目 Response Message Field | Y10: 上り項目 Request Message Field | Z10: 下り項目 Response Message Field | AA10: 上り項目 Request Message Field | AB10: 下り項目 Response Message Field | AC10: 上り項目 Request Message Field | AD10: 下り項目 Response Message Field | AE10: 上り項目 Request Message Field | AF10: 下り項目 Response Message Field | AG10: 上り項目 Request Message Field | AH10: 下り項目 Response Message Field | AI10: 上り項目 Request Message Field | AJ10: 下り項目 Response Message Field | AK10: 上り項目 Request Message Field | AL10: 下り項目 Response Message Field | AM10: 上り項目 Request Message Field | AN10: 下り項目 Response Message Field | AO10: 上り項目 Request Message Field | AP10: 下り項目 Response Message Field
A11: 10 | B11: * | D11: Upd01_Dtl1 | E11: L | G11: $share$ | H11: MA.MABCL0540.BpCst_Upd01.BpCst_Upd01_Dtl | K11: BpCst_UpdChk01_Dtl | M11: BpCst_Upd01_Dtl
A12: 10 | D12: bp_cd | E12: #MA.BP_CD | G12: BP cd. | H12: 取引先ＣＤ | I12: E | K12: E | M12: E
A13: 10 | D13: acst_cd | E13: #MA.BP_CD | G13: AR customer cd. | H13: 売掛先ＣＤ | I13: E | K13: E | M13: E
A14: 10 | D14: ar_dpt_typ | E14: #MA.AR_DPT_TYP | G14: AR dept. type | H14: 債権部門区分 | I14: E | K14: E | M14: E
A15: 10 | D15: ar_dpt_cd | E15: #MA.DPT_CD | G15: AR dept. cd. | H15: 債権部門ＣＤ | I15: E | K15: E | M15: E
A16: 10 | D16: check_ar_dpt_cd | E16: #MA.DPT_CD | G16: AR dept. cd. | H16: 債権部門ＣＤ | I16: E | K16: E
A17: 10 | D17: cst_cntct_dpt | E17: #MA.CNTCT_DPT | G17: Customer dept. | H17: 得意先部署 | I17: E | K17: E | M17: E
A18: 10 | D18: cst_cntct_psn | E18: #MA.CNTCT_PSN | G18: Customer PIC | H18: 得意先担当者 | I18: E | K18: E | M18: E
A19: 10 | D19: cst_cntct_psn_title | E19: #MA.BP_PSN_TITLE | G19: Form of address for Customer PIC | H19: 得意先担当者敬称 | I19: E | K19: E | M19: E
A20: 10 | D20: cst_sundry_flg | E20: #MA.FLG | G20: Miscellaneous customer | H20: 得意先諸口 | I20: E | K20: E | M20: E
A21: 10 | D21: sls_upri_req_typ | E21: #MA.SLS_UPRI_REQ_TYP | G21: Sales unit price acquisition type | H21: 販売単価取得区分 | I21: E | K21: E | M21: E
A22: 10 | D22: sls_upri_cng_flg | E22: #MA.FLG | G22: Allow sales unit price change | H22: 販売単価変更許可 | I22: E | K22: E | M22: E
A23: 10 | D23: sls_upri_rnd_typ | E23: #MA.RND_TYP | G23: Sales unit price rounding type | H23: 販売単価端数処理区分 | I23: E | K23: E | M23: E
A24: 10 | D24: sls_amt_rnd_typ | E24: #MA.RND_TYP | G24: Rounding type (Sales amount) | H24: 売上金額端数処理区分 | I24: E | K24: E | M24: E
A25: 10 | D25: sls_tax_calc_typ | E25: #MA.TAX_CALC_TYP | G25: Sales tax calculation type | H25: 売上税計算区分 | I25: E | K25: E | M25: E
A26: 10 | D26: sls_tax_rnd_typ | E26: #MA.RND_TYP | G26: Sales tax rounding type | H26: 売上税額端数処理区分 | I26: E | K26: E | M26: E
A27: 10 | D27: sls_basis_typ | E27: #MA.SLS_BASIS_TYP | G27: Revenue recording type | H27: 売上計上区分 | I27: E | K27: E | M27: E
A28: 10 | D28: ship_schd_split_typ | E28: #MA.SHIP_SCHD_SPLIT_TYP | G28: Shipping schedule split type | H28: 出荷予定分割区分 | I28: E | K28: E | M28: E
... A46: 10 | D46: sls_anly_cd3 | E46: #MA.SLS_ANLY_CD | G46: Sales analysis cd. 3 | H46: 販売分析ＣＤ３ | I46: E | K46: E | M46: E
A47: 10 | D47: bcst_flg | E47: #MA.FLG | G47: Billing customer | H47: 請求先 | I47: E | K47: E
A48: 10 | D48: bcst_cd | E48: #MA.BP_CD | G48: Billing customer cd. | H48: 請求先ＣＤ | I48: E | K48: E | M48: E
A49: 10 | D49: cst_prnt_typ | E49: #MA.PRNT_TYP | G49: Report issue type (Customer) | H49: 帳票発行区分（得意先） | I49: E | K49: E | M49: E
A50: 10 | D50: upd_cntr | E50: #MA.UPD_CNT | G50: Update counter | H50: 更新カウンタ | I50: E | K50: E | M50: E
A51: 10 | D51: not_lg_mix_flg | E51: #MA.FLG | G51: Prohibit mixed distribution group flg. | H51: 物流グループ混在不可ＦＬＧ | I51: E | K51: E | M51: E
A52: 10 | D52: not_lot_mix_flg | E52: #MA.FLG | G52: Prohibit mixed lots flg. | H52: ロット混在不可ＦＬＧ | I52: E | K52: E | M52: E
A53: 10 | D53: not_sublot_mix_flg | E53: #MA.FLG | G53: Prohibit mixed sublots flg. | H53: サブロット混在不可ＦＬＧ | I53: E | K53: E | M53: E
A55: 20 | B55: * | D55: Upd01_Dtl2 | E55: L | G55: $share$ | H55: MA.MABSL0650.CstUsr_Upd01.CstUsr_Upd01_Dtl | O55: CstUsr_UpdChk01_Dtl | Q55: CstUsr_Upd01_Dtl
A56: 20 | D56: cst_cd | E56: #MA.BP_CD | G56: Customer cd. | H56: 得意先ＣＤ | I56: E | O56: E | Q56: E
A57: 20 | D57: st_dt_key | E57: #MA.DT | G57: Application start date_[Before change] | H57: 適用開始日_[変更前] | I57: E | O57: E | Q57: E
A58: 20 | D58: st_dt | E58: #MA.DT | G58: Application start date | H58: 適用開始日 | I58: E | O58: E | Q58: E
A59: 20 | D59: end_dt | E59: #MA.DT | G59: Application end date | H59: 適用終了日 | I59: E | O59: E | Q59: E
A60: 20 | D60: usr_cd | E60: #MA.USR_ID | G60: PIC cd. | H60: 担当者ＣＤ | I60: E | O60: E | Q60: E
A61: 20 | D61: dpt_cd | E61: #MA.DPT_CD | G61: Dept. cd. | H61: 部門ＣＤ | I61: E | O61: E | Q61: E
A62: 20 | D62: memo1 | E62: #MA.MST_MEMO1 | G62: Memo 1 | H62: メモ１ | I62: E | O62: E | Q62: E
A63: 20 | D63: memo2 | E63: #MA.MST_MEMO2 | G63: Memo 2 | H63: メモ２ | I63: E | O63: E | Q63: E
A64: 20 | D64: memo3 | E64: #MA.MST_MEMO3 | G64: Memo 3 | H64: メモ３ | I64: E | O64: E | Q64: E
A65: 20 | D65: del_flg | E65: #MA.FLG | G65: Logical delete | H65: 論理削除 | I65: E | O65: E | Q65: E
A66: 20 | D66: upd_cntr | E66: #MA.UPD_CNT | G66: Update counter | H66: 更新カウンタ | I66: E | O66: E | Q66: E
A68: 30 | B68: * | D68: Upd01_Dtl3 | E68: L | G68: $share$ | H68: MA.MABSL0230.CstSlsUpriRank_Upd01.CstSlsUpriRank_Upd01_Dtl | S68: CstSlsUpriRank_UpdChk01_Dtl | U68: CstSlsUpriRank_Upd01_Dtl
A69: 30 | D69: cst_cd | E69: #MA.BP_CD | G69: Customer cd. | H69: 得意先ＣＤ | I69: E | S69: E | U69: E
A70: 30 | D70: dlv_cd | E70: #MA.BP_CD | G70: Delivery destination cd. | H70: 納品先ＣＤ | I70: E | S70: E | U70: E
A71: 30 | D71: dest_cd1 | E71: #MA.BP_CD | G71: Distribution channel cd. 1 | H71: 仕向先ＣＤ１ | I71: E | S71: E | U71: E
A72: 30 | D72: dest_cd2 | E72: #MA.BP_CD | G72: Distribution channel cd. 2 | H72: 仕向先ＣＤ２ | I72: E | S72: E | U72: E
A73: 30 | D73: dest_cd3 | E73: #MA.BP_CD | G73: Distribution channel cd. 3 | H73: 仕向先ＣＤ３ | I73: E | S73: E | U73: E
A74: 30 | D74: st_dt_key | E74: #MA.DT | G74: Application start date_[Before change] | H74: 適用開始日_[変更前] | I74: E | S74: E | U74: E
A75: 30 | D75: st_dt | E75: #MA.DT | G75: Application start date | H75: 適用開始日 | I75: E | S75: E | U75: E
A76: 30 | D76: end_dt | E76: #MA.DT | G76: Application end date | H76: 適用終了日 | I76: E | S76: E | U76: E
A77: 30 | D77: sls_upri_rank_cd | E77: #MA.SLS_UPRI_RANK_CD | G77: Sales unit price rank cd. | H77: 販売単価ランクＣＤ | I77: E | S77: E | U77: E
A78: 30 | D78: memo1 | E78: #MA.MST_MEMO1 | G78: Memo 1 | H78: メモ１ | I78: E | S78: E | U78: E
A79: 30 | D79: memo2 | E79: #MA.MST_MEMO2 | G79: Memo 2 | H79: メモ２ | I79: E | S79: E | U79: E
A80: 30 | D80: memo3 | E80: #MA.MST_MEMO3 | G80: Memo 3 | H80: メモ３ | I80: E | S80: E | U80: E
... A82: 30 | D82: upd_cntr | E82: #MA.UPD_CNT | G82: Update counter | H82: 更新カウンタ | I82: E | S82: E | U82: E
A84: 40 | B84: * | D84: Upd01_Dtl4 | E84: L | G84: $share$ | H84: MA.MABSL0660.CstDlv_Upd01.CstDlv_Upd01_Dtl | W84: CstDlv_UpdChk01_Dtl | Y84: CstDlv_Upd01_Dtl
A85: 40 | D85: cst_cd | E85: #MA.BP_CD | G85: Customer cd. | H85: 得意先ＣＤ | I85: E | W85: E | Y85: E
A86: 40 | D86: dlv_cd | E86: #MA.BP_CD | G86: Delivery destination cd. | H86: 納品先ＣＤ | I86: E | W86: E | Y86: E
A87: 40 | D87: st_dt_key | E87: #MA.DT | G87: Application start date_[Before change] | H87: 適用開始日_[変更前] | I87: E | W87: E | Y87: E
A88: 40 | D88: st_dt | E88: #MA.DT | G88: Application start date | H88: 適用開始日 | I88: E | W88: E | Y88: E
A89: 40 | D89: end_dt | E89: #MA.DT | G89: Application end date | H89: 適用終了日 | I89: E | W89: E | Y89: E
A90: 40 | D90: memo1 | E90: #MA.MST_MEMO1 | G90: Memo 1 | H90: メモ１ | I90: E | W90: E | Y90: E
A91: 40 | D91: memo2 | E91: #MA.MST_MEMO2 | G91: Memo 2 | H91: メモ２ | I91: E | W91: E | Y91: E
A92: 40 | D92: memo3 | E92: #MA.MST_MEMO3 | G92: Memo 3 | H92: メモ３ | I92: E | W92: E | Y92: E
A93: 40 | D93: del_flg | E93: #MA.FLG | G93: Logical delete | H93: 論理削除 | I93: E | W93: E | Y93: E
A94: 40 | D94: upd_cntr | E94: #MA.UPD_CNT | G94: Update counter | H94: 更新カウンタ | I94: E | W94: E | Y94: E
A96: 50 | B96: * | D96: Upd01_Dtl5 | E96: L | G96: $share$ | H96: MA.MABSL0480.ShipValidCtl_Upd01.ShipValidCtl_Upd01_Dtl | AA96: ShipValidCtl_UpdChk01_Dtl | AC96: ShipValidCtl_Upd01_Dtl
A97: 50 | D97: cst_cd | E97: #MA.BP_CD | G97: Customer cd. | H97: 得意先ＣＤ | I97: E | AA97: E | AC97: E
A98: 50 | D98: dlv_cd | E98: #MA.BP_CD | G98: Delivery destination cd. | H98: 納品先ＣＤ | I98: E | AA98: E | AC98: E
A99: 50 | D99: ship_valid_grp_cd | E99: #MA.SHIP_VALID_GRP_CD | G99: Shipping expiration date group cd. | H99: 出荷有効期限グループＣＤ | I99: E | AA99: E | AC99: E
A100: 50 | D100: valid_days | E100: #MA.SHIP_VALID_DAYS | G100: Expiration number of days | H100: 有効期限日数 | I100: E | AA100: E | AC100: E
A101: 50 | D101: memo1 | E101: #MA.MST_MEMO1 | G101: Memo 1 | H101: メモ１ | I101: E | AA101: E | AC101: E
A102: 50 | D102: memo2 | E102: #MA.MST_MEMO2 | G102: Memo 2 | H102: メモ２ | I102: E | AA102: E | AC102: E
A103: 50 | D103: memo3 | E103: #MA.MST_MEMO3 | G103: Memo 3 | H103: メモ３ | I103: E | AA103: E | AC103: E
A104: 50 | D104: del_flg | E104: #MA.FLG | G104: Logical delete | H104: 論理削除 | I104: E | AA104: E | AC104: E
A105: 50 | D105: upd_cntr | E105: #MA.UPD_CNT | G105: Update counter | H105: 更新カウンタ | I105: E | AA105: E | AC105: E
A107: 60 | B107: * | D107: Upd01_Dtl6 | E107: L | G107: $share$ | H107: MA.MABSL0520.SloAllocGd_Upd01.SloAllocGd_Upd01_Dtl | AE107: SloAllocGd_UpdChk01_Dtl | AG107: SloAllocGd_Upd01_Dtl
A108: 60 | D108: cst_cd | E108: #MA.BP_CD | G108: Customer cd. | H108: 得意先ＣＤ | I108: E | AE108: E | AG108: E
A109: 60 | D109: dlv_cd | E109: #MA.BP_CD | G109: Delivery destination cd. | H109: 納品先ＣＤ | I109: E | AE109: E | AG109: E
A110: 60 | D110: gd_cd | E110: #MA.STK_GD_CD | G110: Grading cd. | H110: 格付ＣＤ | I110: E | AE110: E | AG110: E
A111: 60 | D111: memo1 | E111: #MA.MST_MEMO1 | G111: Memo 1 | H111: メモ１ | I111: E | AE111: E | AG111: E
A112: 60 | D112: memo2 | E112: #MA.MST_MEMO2 | G112: Memo 2 | H112: メモ２ | I112: E | AE112: E | AG112: E
A113: 60 | D113: memo3 | E113: #MA.MST_MEMO3 | G113: Memo 3 | H113: メモ３ | I113: E | AE113: E | AG113: E
A114: 60 | D114: del_flg | E114: #MA.FLG | G114: Logical delete | H114: 論理削除 | I114: E | AE114: E | AG114: E
A115: 60 | D115: upd_cntr | E115: #MA.UPD_CNT | G115: Update counter | H115: 更新カウンタ | I115: E | AE115: E | AG115: E
A117: 70 | B117: * | D117: Upd01_Dtl7 | E117: L | G117: $share$ | H117: MA.MABSL1230.EdiIfCtl_Upd01.EdiIfCtl_Upd01_Dtl | AI117: EdiIfCtl_UpdChk01_Dtl | AK117: EdiIfCtl_Upd01_Dtl
A118: 70 | D118: bp_cd | E118: #MA.BP_CD | G118: BP cd. | H118: 取引先ＣＤ | I118: E | AI118: E | AK118: E
A119: 70 | D119: if_proc_typ | E119: #MA.IF_PROC_TYP | G119: IF process type | H119: ＩＦ処理区分 | I119: E | AI119: E | AK119: E
A120: 70 | D120: not_onr_prov_flg | E120: #MA.FLG | G120: Not for chargeable supply | H120: 有償支給対象外 | I120: E | AI120: E | AK120: E
A121: 70 | D121: st_dt_key | E121: #MA.DT | G121: Application start date_[Before change] | H121: 適用開始日_[変更前] | I121: E | AI121: E | AK121: E
A122: 70 | D122: st_dt | E122: #MA.DT | G122: Application start date | H122: 適用開始日 | I122: E | AI122: E | AK122: E
A123: 70 | D123: end_dt | E123: #MA.DT | G123: Application end date | H123: 適用終了日 | I123: E | AI123: E | AK123: E
A124: 70 | D124: ext_sys_cd | E124: #MA.EXT_SYS_CD | G124: External system cd. | H124: 外部システムＣＤ | I124: E | AI124: E | AK124: E
...

Sheet 来歴
A1: 変更来歴
A3: Rev. | H3: 修正番号 | O3: 変更内容 | AQ3: 変更箇所
A4: 1 | O4: 初版
A5: 1.1 | H5: MA7031#100 | O5: BpCst_UpdChk01_Dtlブロックに以下の項目を追加 ・not_lg_mix_flg、not_lot_mix_flg、not_sublot_mix_flg | AQ5: BpCst_UpdChk01
A6: " | H6: " | O6: BpCst_Upd01_Dtlブロックに以下の項目を追加 ・not_lg_mix_flg、not_lot_mix_flg、not_sublot_mix_flg | AQ6: BpCst_Upd01
A7: " | H7: " | O7: Srch01_Rslt1ブロックに以下の項目を追加 ・not_lg_mix_flg、not_lot_mix_flg、not_sublot_mix_flg | AQ7: Srch01
A8: " | H8: " | O8: Upd01_Dtl1ブロックに以下の項目を追加 ・not_lg_mix_flg、not_lot_mix_flg、not_sublot_mix_flg | AQ8: Upd01
A9: 1.2 | O9: 英語の名称を追記 | AQ9: 全般
