Workbook

Sheet LogicCommon
A2: ロジック共通定義 | B2: ModuleID : | C2: MA | D2: LogicID : | E2: MABCL0030 | F2: Pj.ID : | G2: MC
B3: SubModuleID : | C3: MABC | D3: LogicClass : | E3: MABCL_MultiReg | F3: SuperClassPj.ID :
D4: LogicName : | E4: マルチマスタ登録 | F4: SuperLogicID : | G4: MA.MAUDL5010
A5: 概要 :
A6: 詳細 :
B7: MABCL0031 | C7: データアクセス基本マスタ
C8: 部門基本マスタ
C9: 部門階層マスタ
C10: 承認役割マスタ
C11: 国マスタ
C12: 地域マスタ
C13: 通貨マスタ
C14: 単位マスタ
C15: 銀行マスタ
C16: 銀行支店マスタ
B18: MABCL0032 | C18: 口座マスタ
C19: 為替レート基本マスタ
C20: カレンダ基本マスタ
C21: 品目仕訳マスタ
C22: 会計品目分類マスタ
C23: 会計理由マスタ
C24: 工場・物流倉庫マスタ
C25: 製造場所グループマスタ
C26: 物流グループマスタ
C27: 総量引当場所グループマスタ
B29: MABCL0033 | C29: ワーキンググループマスタ
C30: 工程マスタ
C31: 工数管理マスタ
C32: 工数理由マスタ
C33: 販売単価分類マスタ
C34: 販売単価ランクマスタ
C35: 相殺グループマスタ
C36: 出荷有効期限グループマスタ
C37: 品目出荷グループマスタ
C38: 輸送方法マスタ
B40: MABCL0034 | C40: 梱包容器マスタ
C41: 港マスタ
C42: 格付マスタ
C43: 取引マスタ
C44: 伝票帳票マスタ
C45: 購買内示グループマスタ
C46: 品目仕様分類マスタ
C47: 品目構成グループマスタ
C48: 仕訳実行マスタ
C49: 仕訳グループマスタ
B51: MABCL0035 | C51: 仕訳パタンマスタ
C52: 自動仕訳キーマスタ
C53: 検査パタンマスタ
C54: 勤務種類マスタ
C55: 出荷条件マスタ
C56: 出荷作業マスタ
C57: 資源マスタ
C58: ＨＳ分類マスタ
C59: 配賦パタンマスタ
C60: 原価品群グループマスタ
C61: 計算実行パタンマスタ
B63: MABCL0036 | C63: 汎用配賦分類マスタ
C64: 計算カテゴリマスタ
C65: 原価レポートパタンマスタ
C66: 原価メニューマスタ
C67: 倉庫事業者マスタ

Sheet Srch01
A1: * | B1: * | D1: L | E1: 1
A2: * | D2: オペレーション実装仕様書 Operation Specification Implementation Sheet | E2: ModuleID : | F2: =IF(LogicCommon!C2="","",LogicCommon!C2) -> MA | G2: LogicID : | H2: =IF(LogicCommon!E2="","",LogicCommon!E2) -> MABCL0030 | I2: Ope.ID : | J2: Srch01 | K2: Pj.ID : | L2: =IF(LogicCommon!G2="","",LogicCommon!G2) -> MC | M2: Ope.Body : | N2: "mcframe.serverMAUD.MAUDL6020.MAUDL_LCLRLSearcher"
A3: * | D3: =IF(LogicCommon!A3="","",LogicCommon!A3) | E3: SubModuleID : | F3: =IF(LogicCommon!C3="","",LogicCommon!C3) -> MABC | G3: LogicClass : | H3: =IF(LogicCommon!E3="","",LogicCommon!E3) -> MABCL_MultiReg | I3: Ope.Method : | J3: @ | K3: SuperClassPj.ID : | L3: =IF(LogicCommon!G3="","",LogicCommon!G3) | M3: ReportID : | O3: Gene.Type : | P3: ALL
A4: * | E4: Version : | F4: 000000 | G4: LogicName : | H4: =IF(LogicCommon!E4="","",LogicCommon!E4) -> マルチマスタ登録 | I4: Ope.Name : | J4: 検索 | K4: SuperLogicID : | L4: =IF(LogicCommon!G4="","",LogicCommon!G4) -> MA.MAUDL5010
A5: * | E5: ACType : | L5: 0 | N5: 1 | P5: 2 | R5: 3 | T5: 4 | V5: 5 | X5: 6 | Z5: 7 | AB5: 8 | AD5: 9 | AF5: 10 | AH5: 11 | AJ5: 12 | AL5: 13 | AN5: 14 | AP5: 15 | AR5: 16 | AT5: 17 | AV5: 18 | AX5: 19 | AZ5: 20 | BB5: 21 | BD5: 22 | BF5: 23 | BH5: 24 | BJ5: 25 | BL5: 26 | BN5: 27 | BP5: 28 | BR5: 29 | BT5: 30 | BV5: 31 | BX5: 32 | BZ5: 33 | CB5: 34 | CD5: 35 | CF5: 36 | CH5: 37 | CJ5: 38 | CL5: 39 | CN5: 40 | CP5: 41 | CR5: 42 | CT5: 43 | CV5: 44 | CX5: 45 | CZ5: 46 | DB5: 47 | DD5: 48 | DF5: 49 | DH5: 50 | DJ5: 51 | DL5: 52 | DN5: 53 | DP5: 54 | DR5: 55 | DT5: 56 | DV5: 57 | DX5: 58 | DZ5: 59 | EB5: 60 | ED5: 61 | EF5: 62 | EH5: 63 | EJ5: 64 | EL5: 65 | EN5: 66 | EP5: 67 | ER5: 68 | ET5: 69 | EV5: 70 | EX5: 71 | EZ5: 72 | FB5: 73 | FD5: 74 | FF5: 75 | FH5: 76 | FJ5: 77 | FL5: 78 | FN5: 79 | FP5: 80 | FR5: 81 | FT5: 82 | FV5: 83 | FX5: 84 | FZ5: 85 | GB5: 86 | GD5: 87 | GF5: 88 | GH5: 89 | GJ5: 90 | GL5: 91 | GN5: 92 | GP5: 93 | GR5: 94 | GT5: 95 | GV5: 96 | GX5: 97 | GZ5: 98 | HB5: 99 | HD5: 100 | HF5: 101 | HH5: 102 | HJ5: 103 | HL5: 104 | HN5: 105 | HP5: 106 | HR5: 107 | HT5: 108 | HV5: 109 | HX5: 110 | HZ5: 111
A6: * | D6: 概要 : | E6: 複数のマスタ、名称マスタの検索を行います。 | L6: DA | M6: ID | O6: ID | P6: DPT_BASE | Q6: ID | S6: ID | T6: DPT_LVL | U6: ID | W6: ID | X6: APRV_ROLE | Y6: ID | AA6: ID | AB6: CNTRY | AC6: ID | AE6: ID | AF6: AREA | AG6: ID | AI6: ID | AJ6: CUR | AK6: ID | AM6: ID | AN6: UNIT | AO6: ID | AQ6: ID | AR6: BANK | AS6: ID | AU6: ID | AV6: BANK_BRANCH | AW6: ID | AY6: ID | AZ6: BANK_AC | BA6: ID | BC6: ID | BD6: XRATE | BE6: ID | BG6: ID | BH6: CAL_BASE | BI6: ID | BK6: ID | BL6: ITM_JNL | BM6: ID | BO6: ID | BP6: AC_ITM_GRP | BQ6: ID | BS6: ID | BT6: AC_RSN | BU6: ID | BW6: ID | BX6: SITE | BY6: ID | CA6: ID | CB6: LOC_GRP | CC6: ID | CE6: ID | CF6: LG_GRP | CG6: ID | CI6: ID | CJ6: ALLOC_GRP | CK6: ID | CM6: ID | CN6: WG | CO6: ID | CQ6: ID | CR6: OPER | CS6: ID | CU6: ID | CV6: WK_COST | CW6: ID | CY6: ID | CZ6: WK_RSN | DA6: ID | DC6: ID | DD6: SLS_UPRI_GRP | DE6: ID | DG6: ID | DH6: SLS_UPRI_RANK | DI6: ID | DK6: ID | DL6: SETOFF_GRP | DM6: ID | DO6: ID | DP6: SHIP_VALID | DQ6: ID | DS6: ID | DT6: ITM_SHIP_GRP | DU6: ID | DW6: ID | DX6: TRNSPT | DY6: ID | EA6: ID | EB6: EX_CNTNR | EC6: ID | EE6: ID | EF6: EXIM_PORT | EG6: ID | EI6: ID | EJ6: STK_GD | EK6: ID | EM6: ID | EN6: TRD | EO6: ID | EQ6: ID | ER6: SLIP_FORM | ES6: ID | EU6: ID | EV6: PF_GRP | EW6: ID | EY6: ID | EZ6: ITM_SPEC_GRP | FA6: ID | FC6: ID | FD6: ITM_COMP_GRP | FE6: ID | FG6: ID | FH6: JNL_ACT | FI6: ID | FK6: ID | FL6: JNL_GRP | FM6: ID | FO6: ID | FP6: JNL_PTN_BASE | FQ6: ID | FS6: ID | FT6: AUTO_JNL_KEY | FU6: ID | FW6: ID | FX6: INSP_PTN | FY6: ID | GA6: ID | GB6: WK_DAY | GC6: ID | GE6: ID | GF6: SHIP_TERM | GG6: ID | GI6: ID | GJ6: SHIP_WK | GK6: ID | GM6: ID | GN6: RSRC | GO6: ID | GQ6: ID | GR6: HS_GRP | GS6: ID | GU6: ID | GV6: ALC_PTN | GW6: ID | GY6: ID | GZ6: CTG_GRP | HA6: ID | HC6: ID | HD6: ACT_PTN | HE6: ID | HG6: ID | HH6: GP_ALC | HI6: ID | HK6: ID | HL6: CALC_CTG | HM6: ID | HO6: ID | HP6: RPT_PTN | HQ6: ID | HS6: ID | HT6: COST_MENU | HU6: ID | HW6: ID | HX6: SITE_CO | HY6: ID | IA6: ID
A7: # | I7: U | K7: K | L7: o | M7: =L6&".c"&L5 -> DA.c0 | N7: o | O7: =L6&"_LCL.c"&N5 -> DA_LCL.c1 | P7: o | Q7: =P6&".c"&P5 -> DPT_BASE.c2 | R7: o | S7: =P6&"_LCL.c"&R5 -> DPT_BASE_LCL.c3 | T7: o | U7: =T6&".c"&T5 -> DPT_LVL.c4 | V7: o | W7: =T6&"_LCL.c"&V5 -> DPT_LVL_LCL.c5 | X7: o | Y7: =X6&".c"&X5 -> APRV_ROLE.c6 | Z7: o | AA7: =X6&"_LCL.c"&Z5 -> APRV_ROLE_LCL.c7 | AB7: o | AC7: =AB6&".c"&AB5 -> CNTRY.c8 | AD7: o | AE7: =AB6&"_LCL.c"&AD5 -> CNTRY_LCL.c9 | AF7: o | AG7: =AF6&".c"&AF5 -> AREA.c10 | AH7: o | AI7: =AF6&"_LCL.c"&AH5 -> AREA_LCL.c11 | AJ7: o | AK7: =AJ6&".c"&AJ5 -> CUR.c12 | AL7: o | AM7: =AJ6&"_LCL.c"&AL5 -> CUR_LCL.c13 | AN7: o | AO7: =AN6&".c"&AN5 -> UNIT.c14 | AP7: o | AQ7: =AN6&"_LCL.c"&AP5 -> UNIT_LCL.c15 | AR7: o | AS7: =AR6&".c"&AR5 -> BANK.c16 | AT7: o | AU7: =AR6&"_LCL.c"&AT5 -> BANK_LCL.c17 | AV7: o | AW7: =AV6&".c"&AV5 -> BANK_BRANCH.c18 | AX7: o | AY7: =AV6&"_LCL.c"&AX5 -> BANK_BRANCH_LCL.c19 | AZ7: o | BA7: =AZ6&".c"&AZ5 -> BANK_AC.c20 | BB7: o | BC7: =AZ6&"_LCL.c"&BB5 -> BANK_AC_LCL.c21 | BD7: o | BE7: =BD6&".c"&BD5 -> XRATE.c22 | BF7: o | BG7: =BD6&"_LCL.c"&BF5 -> XRATE_LCL.c23 | BH7: o | BI7: =BH6&".c"&BH5 -> CAL_BASE.c24 | BJ7: o | BK7: =BH6&"_LCL.c"&BJ5 -> CAL_BASE_LCL.c25 | BL7: o | BM7: =BL6&".c"&BL5 -> ITM_JNL.c26 | BN7: o | BO7: =BL6&"_LCL.c"&BN5 -> ITM_JNL_LCL.c27 | BP7: o | BQ7: =BP6&".c"&BP5 -> AC_ITM_GRP.c28 | BR7: o | BS7: =BP6&"_LCL.c"&BR5 -> AC_ITM_GRP_LCL.c29 | BT7: o | BU7: =BT6&".c"&BT5 -> AC_RSN.c30 | BV7: o | BW7: =BT6&"_LCL.c"&BV5 -> AC_RSN_LCL.c31 | BX7: o | BY7: =BX6&".c"&BX5 -> SITE.c32 | BZ7: o | CA7: =BX6&"_LCL.c"&BZ5 -> SITE_LCL.c33 | CB7: o | CC7: =CB6&".c"&CB5 -> LOC_GRP.c34 | CD7: o | CE7: =CB6&"_LCL.c"&CD5 -> LOC_GRP_LCL.c35 | CF7: o | CG7: =CF6&".c"&CF5 -> LG_GRP.c36 | CH7: o | CI7: =CF6&"_LCL.c"&CH5 -> LG_GRP_LCL.c37 | CJ7: o | CK7: =CJ6&".c"&CJ5 -> ALLOC_GRP.c38 | CL7: o | CM7: =CJ6&"_LCL.c"&CL5 -> ALLOC_GRP_LCL.c39 | CN7: o | CO7: =CN6&".c"&CN5 -> WG.c40 | CP7: o | CQ7: =CN6&"_LCL.c"&CP5 -> WG_LCL.c41 | CR7: o | CS7: =CR6&".c"&CR5 -> OPER.c42 | CT7: o | CU7: =CR6&"_LCL.c"&CT5 -> OPER_LCL.c43 | CV7: o | CW7: =CV6&".c"&CV5 -> WK_COST.c44 | CX7: o | CY7: =CV6&"_LCL.c"&CX5 -> WK_COST_LCL.c45 | CZ7: o | DA7: =CZ6&".c"&CZ5 -> WK_RSN.c46 | DB7: o | DC7: =CZ6&"_LCL.c"&DB5 -> WK_RSN_LCL.c47 | DD7: o | DE7: =DD6&".c"&DD5 -> SLS_UPRI_GRP.c48 | DF7: o | DG7: =DD6&"_LCL.c"&DF5 -> SLS_UPRI_GRP_LCL.c49 | DH7: o | DI7: =DH6&".c"&DH5 -> SLS_UPRI_RANK.c50 | DJ7: o | DK7: =DH6&"_LCL.c"&DJ5 -> SLS_UPRI_RANK_LCL.c51 | DL7: o | DM7: =DL6&".c"&DL5 -> SETOFF_GRP.c52 | DN7: o | DO7: =DL6&"_LCL.c"&DN5 -> SETOFF_GRP_LCL.c53 | DP7: o | DQ7: =DP6&".c"&DP5 -> SHIP_VALID.c54 | DR7: o | DS7: =DP6&"_LCL.c"&DR5 -> SHIP_VALID_LCL.c55 | DT7: o | DU7: =DT6&".c"&DT5 -> ITM_SHIP_GRP.c56 | DV7: o | DW7: =DT6&"_LCL.c"&DV5 -> ITM_SHIP_GRP_LCL.c57 | DX7: o | DY7: =DX6&".c"&DX5 -> TRNSPT.c58 | DZ7: o | EA7: =DX6&"_LCL.c"&DZ5 -> TRNSPT_LCL.c59 | EB7: o | EC7: =EB6&".c"&EB5 -> EX_CNTNR.c60 | ED7: o | EE7: =EB6&"_LCL.c"&ED5 -> EX_CNTNR_LCL.c61 | EF7: o | EG7: =EF6&".c"&EF5 -> EXIM_PORT.c62 | EH7: o | EI7: =EF6&"_LCL.c"&EH5 -> EXIM_PORT_LCL.c63 | EJ7: o | EK7: =EJ6&".c"&EJ5 -> STK_GD.c64 | EL7: o | EM7: =EJ6&"_LCL.c"&EL5 -> STK_GD_LCL.c65 | EN7: o | EO7: =EN6&".c"&EN5 -> TRD.c66 | EP7: o | EQ7: =EN6&"_LCL.c"&EP5 -> TRD_LCL.c67 | ER7: o | ES7: =ER6&".c"&ER5 -> SLIP_FORM.c68 | ET7: o | EU7: =ER6&"_LCL.c"&ET5 -> SLIP_FORM_LCL.c69 | EV7: o | EW7: =EV6&".c"&EV5 -> PF_GRP.c70 | EX7: o | EY7: =EV6&"_LCL.c"&EX5 -> PF_GRP_LCL.c71 | EZ7: o | FA7: =EZ6&".c"&EZ5 -> ITM_SPEC_GRP.c72 | FB7: o | FC7: =EZ6&"_LCL.c"&FB5 -> ITM_SPEC_GRP_LCL.c73 | FD7: o | FE7: =FD6&".c"&FD5 -> ITM_COMP_GRP.c74 | FF7: o | FG7: =FD6&"_LCL.c"&FF5 -> ITM_COMP_GRP_LCL.c75 | FH7: o | FI7: =FH6&".c"&FH5 -> JNL_ACT.c76 | FJ7: o | FK7: =FH6&"_LCL.c"&FJ5 -> JNL_ACT_LCL.c77 | FL7: o | FM7: =FL6&".c"&FL5 -> JNL_GRP.c78 | FN7: o | FO7: =FL6&"_LCL.c"&FN5 -> JNL_GRP_LCL.c79 | FP7: o | FQ7: =FP6&".c"&FP5 -> JNL_PTN_BASE.c80 | FR7: o | FS7: =FP6&"_LCL.c"&FR5 -> JNL_PTN_BASE_LCL.c81 | FT7: o | FU7: =FT6&".c"&FT5 -> AUTO_JNL_KEY.c82 | FV7: o | FW7: =FT6&"_LCL.c"&FV5 -> AUTO_JNL_KEY_LCL.c83 | FX7: o | FY7: =FX6&".c"&FX5 -> INSP_PTN.c84 | FZ7: o | GA7: =FX6&"_LCL.c"&FZ5 -> INSP_PTN_LCL.c85 | GB7: o | GC7: =GB6&".c"&GB5 -> WK_DAY.c86 | GD7: o | GE7: =GB6&"_LCL.c"&GD5 -> WK_DAY_LCL.c87 | GF7: o | GG7: =GF6&".c"&GF5 -> SHIP_TERM.c88 | GH7: o | GI7: =GF6&"_LCL.c"&GH5 -> SHIP_TERM_LCL.c89 | GJ7: o | GK7: =GJ6&".c"&GJ5 -> SHIP_WK.c90 | GL7: o | GM7: =GJ6&"_LCL.c"&GL5 -> SHIP_WK_LCL.c91 | GN7: o | GO7: =GN6&".c"&GN5 -> RSRC.c92 | GP7: o | GQ7: =GN6&"_LCL.c"&GP5 -> RSRC_LCL.c93 | GR7: o | GS7: =GR6&".c"&GR5 -> HS_GRP.c94 | GT7: o | GU7: =GR6&"_LCL.c"&GT5 -> HS_GRP_LCL.c95 | GV7: o | GW7: =GV6&".c"&GV5 -> ALC_PTN.c96 | GX7: o | GY7: =GV6&"_LCL.c"&GX5 -> ALC_PTN_LCL.c97 | GZ7: o | HA7: =GZ6&".c"&GZ5 -> CTG_GRP.c98 | HB7: o | HC7: =GZ6&"_LCL.c"&HB5 -> CTG_GRP_LCL.c99 | HD7: o | HE7: =HD6&".c"&HD5 -> ACT_PTN.c100 | HF7: o | HG7: =HD6&"_LCL.c"&HF5 -> ACT_PTN_LCL.c101 | HH7: o | HI7: =HH6&".c"&HH5 -> GP_ALC.c102 | HJ7: o | HK7: =HH6&"_LCL.c"&HJ5 -> GP_ALC_LCL.c103 | HL7: o | HM7: =HL6&".c"&HL5 -> CALC_CTG.c104 | HN7: o | HO7: =HL6&"_LCL.c"&HN5 -> CALC_CTG_LCL.c105 | HP7: o | HQ7: =HP6&".c"&HP5 -> RPT_PTN.c106 | HR7: o | HS7: =HP6&"_LCL.c"&HR5 -> RPT_PTN_LCL.c107 | HT7: o | HU7: =HT6&".c"&HT5 -> COST_MENU.c108 | HV7: o | HW7: =HT6&"_LCL.c"&HV5 -> COST_MENU_LCL.c109 | HX7: o | HY7: =HX6&".c"&HX5 -> SITE_CO.c110 | HZ7: o | IA7: =HX6&"_LCL.c"&HZ5 -> SITE_CO_LCL.c111
A8: # | D8: ブロック名 Block Name | E8: 型 Type | G8: super/share | H8: 対象ブロック名 Target Block Name | K8: CONST | L8: TargetName | M8: ="DBC.MA.MAM_"&L6 -> DBC.MA.MAM_DA | N8: TargetName | O8: ="DBC.MA.MAM_"&L6&"_LCL" -> DBC.MA.MAM_DA_LCL | P8: TargetName | Q8: ="DBC.MA.MAM_"&P6 -> DBC.MA.MAM_DPT_BASE | R8: TargetName | S8: ="DBC.MA.MAM_"&P6&"_LCL" -> DBC.MA.MAM_DPT_BASE_LCL | T8: TargetName | U8: ="DBC.MA.MAM_"&T6 -> DBC.MA.MAM_DPT_LVL | V8: TargetName | W8: ="DBC.MA.MAM_"&T6&"_LCL" -> DBC.MA.MAM_DPT_LVL_LCL | X8: TargetName | Y8: ="DBC.MA.MAM_"&X6 -> DBC.MA.MAM_APRV_ROLE | Z8: TargetName | AA8: ="DBC.MA.MAM_"&X6&"_LCL" -> DBC.MA.MAM_APRV_ROLE_LCL | AB8: TargetName | AC8: ="DBC.MA.MAM_"&AB6 -> DBC.MA.MAM_CNTRY | AD8: TargetName | AE8: ="DBC.MA.MAM_"&AB6&"_LCL" -> DBC.MA.MAM_CNTRY_LCL | AF8: TargetName | AG8: ="DBC.MA.MAM_"&AF6 -> DBC.MA.MAM_AREA | AH8: TargetName | AI8: ="DBC.MA.MAM_"&AF6&"_LCL" -> DBC.MA.MAM_AREA_LCL | AJ8: TargetName | AK8: ="DBC.MA.MAM_"&AJ6 -> DBC.MA.MAM_CUR | AL8: TargetName | AM8: ="DBC.MA.MAM_"&AJ6&"_LCL" -> DBC.MA.MAM_CUR_LCL | AN8: TargetName | AO8: ="DBC.MA.MAM_"&AN6 -> DBC.MA.MAM_UNIT | AP8: TargetName | AQ8: ="DBC.MA.MAM_"&AN6&"_LCL" -> DBC.MA.MAM_UNIT_LCL | AR8: TargetName | AS8: ="DBC.MA.MAM_"&AR6 -> DBC.MA.MAM_BANK | AT8: TargetName | AU8: ="DBC.MA.MAM_"&AR6&"_LCL" -> DBC.MA.MAM_BANK_LCL | AV8: TargetName | AW8: ="DBC.MA.MAM_"&AV6 -> DBC.MA.MAM_BANK_BRANCH | AX8: TargetName | AY8: ="DBC.MA.MAM_"&AV6&"_LCL" -> DBC.MA.MAM_BANK_BRANCH_LCL | AZ8: TargetName | BA8: ="DBC.MA.MAM_"&AZ6 -> DBC.MA.MAM_BANK_AC | BB8: TargetName | BC8: ="DBC.MA.MAM_"&AZ6&"_LCL" -> DBC.MA.MAM_BANK_AC_LCL | BD8: TargetName | BE8: ="DBC.MA.MAM_"&BD6 -> DBC.MA.MAM_XRATE | BF8: TargetName | BG8: ="DBC.MA.MAM_"&BD6&"_LCL" -> DBC.MA.MAM_XRATE_LCL | BH8: TargetName | BI8: ="DBC.MA.MAM_"&BH6 -> DBC.MA.MAM_CAL_BASE | BJ8: TargetName | BK8: ="DBC.MA.MAM_"&BH6&"_LCL" -> DBC.MA.MAM_CAL_BASE_LCL | BL8: TargetName | BM8: ="DBC.MA.MAM_"&BL6 -> DBC.MA.MAM_ITM_JNL | BN8: TargetName | BO8: ="DBC.MA.MAM_"&BL6&"_LCL" -> DBC.MA.MAM_ITM_JNL_LCL | BP8: TargetName | BQ8: ="DBC.MA.MAM_"&BP6 -> DBC.MA.MAM_AC_ITM_GRP | BR8: TargetName | BS8: ="DBC.MA.MAM_"&BP6&"_LCL" -> DBC.MA.MAM_AC_ITM_GRP_LCL | BT8: TargetName | BU8: ="DBC.MA.MAM_"&BT6 -> DBC.MA.MAM_AC_RSN | BV8: TargetName | BW8: ="DBC.MA.MAM_"&BT6&"_LCL" -> DBC.MA.MAM_AC_RSN_LCL | BX8: TargetName | BY8: ="DBC.MA.MAM_"&BX6 -> DBC.MA.MAM_SITE | BZ8: TargetName | CA8: ="DBC.MA.MAM_"&BX6&"_LCL" -> DBC.MA.MAM_SITE_LCL | CB8: TargetName | CC8: ="DBC.MA.MAM_"&CB6 -> DBC.MA.MAM_LOC_GRP | CD8: TargetName | CE8: ="DBC.MA.MAM_"&CB6&"_LCL" -> DBC.MA.MAM_LOC_GRP_LCL | CF8: TargetName | CG8: ="DBC.MA.MAM_"&CF6 -> DBC.MA.MAM_LG_GRP | CH8: TargetName | CI8: ="DBC.MA.MAM_"&CF6&"_LCL" -> DBC.MA.MAM_LG_GRP_LCL | CJ8: TargetName | CK8: ="DBC.MA.MAM_"&CJ6 -> DBC.MA.MAM_ALLOC_GRP | CL8: TargetName | CM8: ="DBC.MA.MAM_"&CJ6&"_LCL" -> DBC.MA.MAM_ALLOC_GRP_LCL | CN8: TargetName | CO8: ="DBC.MA.MAM_"&CN6 -> DBC.MA.MAM_WG | CP8: TargetName | CQ8: ="DBC.MA.MAM_"&CN6&"_LCL" -> DBC.MA.MAM_WG_LCL | CR8: TargetName | CS8: ="DBC.MA.MAM_"&CR6 -> DBC.MA.MAM_OPER | CT8: TargetName | CU8: ="DBC.MA.MAM_"&CR6&"_LCL" -> DBC.MA.MAM_OPER_LCL | CV8: TargetName | CW8: ="DBC.MA.MAM_"&CV6 -> DBC.MA.MAM_WK_COST | CX8: TargetName | CY8: ="DBC.MA.MAM_"&CV6&"_LCL" -> DBC.MA.MAM_WK_COST_LCL | CZ8: TargetName | DA8: ="DBC.MA.MAM_"&CZ6 -> DBC.MA.MAM_WK_RSN | DB8: TargetName | DC8: ="DBC.MA.MAM_"&CZ6&"_LCL" -> DBC.MA.MAM_WK_RSN_LCL | DD8: TargetName | DE8: ="DBC.MA.MAM_"&DD6 -> DBC.MA.MAM_SLS_UPRI_GRP | DF8: TargetName | DG8: ="DBC.MA.MAM_"&DD6&"_LCL" -> DBC.MA.MAM_SLS_UPRI_GRP_LCL | DH8: TargetName | DI8: ="DBC.MA.MAM_"&DH6 -> DBC.MA.MAM_SLS_UPRI_RANK | DJ8: TargetName | DK8: ="DBC.MA.MAM_"&DH6&"_LCL" -> DBC.MA.MAM_SLS_UPRI_RANK_LCL | DL8: TargetName | DM8: ="DBC.MA.MAM_"&DL6 -> DBC.MA.MAM_SETOFF_GRP | DN8: TargetName | DO8: ="DBC.MA.MAM_"&DL6&"_LCL" -> DBC.MA.MAM_SETOFF_GRP_LCL | DP8: TargetName | DQ8: ="DBC.MA.MAM_"&DP6 -> DBC.MA.MAM_SHIP_VALID | DR8: TargetName | DS8: ="DBC.MA.MAM_"&DP6&"_LCL" -> DBC.MA.MAM_SHIP_VALID_LCL | DT8: TargetName | DU8: ="DBC.MA.MAM_"&DT6 -> DBC.MA.MAM_ITM_SHIP_GRP | DV8: TargetName | DW8: ="DBC.MA.MAM_"&DT6&"_LCL" -> DBC.MA.MAM_ITM_SHIP_GRP_LCL | DX8: TargetName | DY8: ="DBC.MA.MAM_"&DX6 -> DBC.MA.MAM_TRNSPT | DZ8: TargetName | EA8: ="DBC.MA.MAM_"&DX6&"_LCL" -> DBC.MA.MAM_TRNSPT_LCL | EB8: TargetName | EC8: ="DBC.MA.MAM_"&EB6 -> DBC.MA.MAM_EX_CNTNR | ED8: TargetName | EE8: ="DBC.MA.MAM_"&EB6&"_LCL" -> DBC.MA.MAM_EX_CNTNR_LCL | EF8: TargetName | EG8: ="DBC.MA.MAM_"&EF6 -> DBC.MA.MAM_EXIM_PORT | EH8: TargetName | EI8: ="DBC.MA.MAM_"&EF6&"_LCL" -> DBC.MA.MAM_EXIM_PORT_LCL | EJ8: TargetName | EK8: ="DBC.MA.MAM_"&EJ6 -> DBC.MA.MAM_STK_GD | EL8: TargetName | EM8: ="DBC.MA.MAM_"&EJ6&"_LCL" -> DBC.MA.MAM_STK_GD_LCL | EN8: TargetName | EO8: ="DBC.MA.MAM_"&EN6 -> DBC.MA.MAM_TRD | EP8: TargetName | EQ8: ="DBC.MA.MAM_"&EN6&"_LCL" -> DBC.MA.MAM_TRD_LCL | ER8: TargetName | ES8: ="DBC.MA.MAM_"&ER6 -> DBC.MA.MAM_SLIP_FORM | ET8: TargetName | EU8: ="DBC.MA.MAM_"&ER6&"_LCL" -> DBC.MA.MAM_SLIP_FORM_LCL | EV8: TargetName | EW8: ="DBC.MA.MAM_"&EV6 -> DBC.MA.MAM_PF_GRP | EX8: TargetName | EY8: ="DBC.MA.MAM_"&EV6&"_LCL" -> DBC.MA.MAM_PF_GRP_LCL | EZ8: TargetName | FA8: ="DBC.MA.MAM_"&EZ6 -> DBC.MA.MAM_ITM_SPEC_GRP | FB8: TargetName | FC8: ="DBC.MA.MAM_"&EZ6&"_LCL" -> DBC.MA.MAM_ITM_SPEC_GRP_LCL | FD8: TargetName | FE8: ="DBC.MA.MAM_"&FD6 -> DBC.MA.MAM_ITM_COMP_GRP | FF8: TargetName | FG8: ="DBC.MA.MAM_"&FD6&"_LCL" -> DBC.MA.MAM_ITM_COMP_GRP_LCL | FH8: TargetName | FI8: ="DBC.MA.MAM_"&FH6 -> DBC.MA.MAM_JNL_ACT | FJ8: TargetName | FK8: ="DBC.MA.MAM_"&FH6&"_LCL" -> DBC.MA.MAM_JNL_ACT_LCL | FL8: TargetName | FM8: ="DBC.MA.MAM_"&FL6 -> DBC.MA.MAM_JNL_GRP | FN8: TargetName | FO8: ="DBC.MA.MAM_"&FL6&"_LCL" -> DBC.MA.MAM_JNL_GRP_LCL | FP8: TargetName | FQ8: ="DBC.MA.MAM_"&FP6 -> DBC.MA.MAM_JNL_PTN_BASE | FR8: TargetName | FS8: ="DBC.MA.MAM_"&FP6&"_LCL" -> DBC.MA.MAM_JNL_PTN_BASE_LCL | FT8: TargetName | FU8: ="DBC.MA.MAM_"&FT6 -> DBC.MA.MAM_AUTO_JNL_KEY | FV8: TargetName | FW8: ="DBC.MA.MAM_"&FT6&"_LCL" -> DBC.MA.MAM_AUTO_JNL_KEY_LCL | FX8: TargetName | FY8: ="DBC.MA.MAM_"&FX6 -> DBC.MA.MAM_INSP_PTN | FZ8: TargetName | GA8: ="DBC.MA.MAM_"&FX6&"_LCL" -> DBC.MA.MAM_INSP_PTN_LCL | GB8: TargetName | GC8: ="DBC.MA.MAM_"&GB6 -> DBC.MA.MAM_WK_DAY | GD8: TargetName | GE8: ="DBC.MA.MAM_"&GB6&"_LCL" -> DBC.MA.MAM_WK_DAY_LCL | GF8: TargetName | GG8: ="DBC.MA.MAM_"&GF6 -> DBC.MA.MAM_SHIP_TERM | GH8: TargetName | GI8: ="DBC.MA.MAM_"&GF6&"_LCL" -> DBC.MA.MAM_SHIP_TERM_LCL | GJ8: TargetName | GK8: ="DBC.MA.MAM_"&GJ6 -> DBC.MA.MAM_SHIP_WK | GL8: TargetName | GM8: ="DBC.MA.MAM_"&GJ6&"_LCL" -> DBC.MA.MAM_SHIP_WK_LCL | GN8: TargetName | GO8: ="DBC.MA.MAM_"&GN6 -> DBC.MA.MAM_RSRC | GP8: TargetName | GQ8: ="DBC.MA.MAM_"&GN6&"_LCL" -> DBC.MA.MAM_RSRC_LCL | GR8: TargetName | GS8: ="DBC.MA.MAM_"&GR6 -> DBC.MA.MAM_HS_GRP | GT8: TargetName | GU8: ="DBC.MA.MAM_"&GR6&"_LCL" -> DBC.MA.MAM_HS_GRP_LCL | GV8: TargetName | GW8: ="DBC.MA.MAM_"&GV6 -> DBC.MA.MAM_ALC_PTN | GX8: TargetName | GY8: ="DBC.MA.MAM_"&GV6&"_LCL" -> DBC.MA.MAM_ALC_PTN_LCL | GZ8: TargetName | HA8: ="DBC.MA.MAM_"&GZ6 -> DBC.MA.MAM_CTG_GRP | HB8: TargetName | HC8: ="DBC.MA.MAM_"&GZ6&"_LCL" -> DBC.MA.MAM_CTG_GRP_LCL | HD8: TargetName | HE8: ="DBC.MA.MAM_"&HD6 -> DBC.MA.MAM_ACT_PTN | HF8: TargetName | HG8: ="DBC.MA.MAM_"&HD6&"_LCL" -> DBC.MA.MAM_ACT_PTN_LCL | HH8: TargetName | HI8: ="DBC.MA.MAM_"&HH6 -> DBC.MA.MAM_GP_ALC | HJ8: TargetName | HK8: ="DBC.MA.MAM_"&HH6&"_LCL" -> DBC.MA.MAM_GP_ALC_LCL | HL8: TargetName | HM8: ="DBC.MA.MAM_"&HL6 -> DBC.MA.MAM_CALC_CTG | HN8: TargetName | HO8: ="DBC.MA.MAM_"&HL6&"_LCL" -> DBC.MA.MAM_CALC_CTG_LCL | HP8: TargetName | HQ8: ="DBC.MA.MAM_"&HP6 -> DBC.MA.MAM_RPT_PTN | HR8: TargetName | HS8: ="DBC.MA.MAM_"&HP6&"_LCL" -> DBC.MA.MAM_RPT_PTN_LCL | HT8: TargetName | HU8: ="DBC.MA.MAM_"&HT6 -> DBC.MA.MAM_COST_MENU | HV8: TargetName | HW8: ="DBC.MA.MAM_"&HT6&"_LCL" -> DBC.MA.MAM_COST_MENU_LCL | HX8: TargetName | HY8: ="DBC.MA.MAM_"&HX6 -> DBC.MA.MAM_SITE_CO | HZ8: TargetName | IA8: ="DBC.MA.MAM_"&HX6&"_LCL" -> DBC.MA.MAM_SITE_CO_LCL | ID8: ブロック備考 Block Remarks
A9: # | D9: 項目名 Field Name | E9: 型 Type | F9: 桁 Digits | G9: フルネーム Full Name | H9: 日本語名 Japanese Name | I9: 上り項目 Request Message Field | J9: 下り項目 Response Message Field | IB9: 条件および編集方法 Conditions and Editing Methods | ID9: 項目備考 Field Remarks
A10: # | L10: 上り項目 Request Message Field | M10: 下り項目 Response Message Field | N10: 上り項目 Request Message Field | O10: 下り項目 Response Message Field | P10: 上り項目 Request Message Field | Q10: 下り項目 Response Message Field | R10: 上り項目 Request Message Field | S10: 下り項目 Response Message Field | T10: 上り項目 Request Message Field | U10: 下り項目 Response Message Field | V10: 上り項目 Request Message Field | W10: 下り項目 Response Message Field | X10: 上り項目 Request Message Field | Y10: 下り項目 Response Message Field | Z10: 上り項目 Request Message Field | AA10: 下り項目 Response Message Field | AB10: 上り項目 Request Message Field | AC10: 下り項目 Response Message Field | AD10: 上り項目 Request Message Field | AE10: 下り項目 Response Message Field | AF10: 上り項目 Request Message Field | AG10: 下り項目 Response Message Field | AH10: 上り項目 Request Message Field | AI10: 下り項目 Response Message Field | AJ10: 上り項目 Request Message Field | AK10: 下り項目 Response Message Field | AL10: 上り項目 Request Message Field | AM10: 下り項目 Response Message Field | AN10: 上り項目 Request Message Field | AO10: 下り項目 Response Message Field | AP10: 上り項目 Request Message Field | AQ10: 下り項目 Response Message Field | AR10: 上り項目 Request Message Field | AS10: 下り項目 Response Message Field | AT10: 上り項目 Request Message Field | AU10: 下り項目 Response Message Field | AV10: 上り項目 Request Message Field | AW10: 下り項目 Response Message Field | AX10: 上り項目 Request Message Field | AY10: 下り項目 Response Message Field | AZ10: 上り項目 Request Message Field | BA10: 下り項目 Response Message Field | BB10: 上り項目 Request Message Field | BC10: 下り項目 Response Message Field | BD10: 上り項目 Request Message Field | BE10: 下り項目 Response Message Field | BF10: 上り項目 Request Message Field | BG10: 下り項目 Response Message Field | BH10: 上り項目 Request Message Field | BI10: 下り項目 Response Message Field | BJ10: 上り項目 Request Message Field | BK10: 下り項目 Response Message Field | BL10: 上り項目 Request Message Field | BM10: 下り項目 Response Message Field | BN10: 上り項目 Request Message Field | BO10: 下り項目 Response Message Field | BP10: 上り項目 Request Message Field | BQ10: 下り項目 Response Message Field | BR10: 上り項目 Request Message Field | BS10: 下り項目 Response Message Field | BT10: 上り項目 Request Message Field | BU10: 下り項目 Response Message Field | BV10: 上り項目 Request Message Field | BW10: 下り項目 Response Message Field | BX10: 上り項目 Request Message Field | BY10: 下り項目 Response Message Field | BZ10: 上り項目 Request Message Field | CA10: 下り項目 Response Message Field | CB10: 上り項目 Request Message Field | CC10: 下り項目 Response Message Field | CD10: 上り項目 Request Message Field | CE10: 下り項目 Response Message Field | CF10: 上り項目 Request Message Field | CG10: 下り項目 Response Message Field | CH10: 上り項目 Request Message Field | CI10: 下り項目 Response Message Field | CJ10: 上り項目 Request Message Field | CK10: 下り項目 Response Message Field | CL10: 上り項目 Request Message Field | CM10: 下り項目 Response Message Field | CN10: 上り項目 Request Message Field | CO10: 下り項目 Response Message Field | CP10: 上り項目 Request Message Field | CQ10: 下り項目 Response Message Field | CR10: 上り項目 Request Message Field | CS10: 下り項目 Response Message Field | CT10: 上り項目 Request Message Field | CU10: 下り項目 Response Message Field | CV10: 上り項目 Request Message Field | CW10: 下り項目 Response Message Field | CX10: 上り項目 Request Message Field | CY10: 下り項目 Response Message Field | CZ10: 上り項目 Request Message Field | DA10: 下り項目 Response Message Field | DB10: 上り項目 Request Message Field | DC10: 下り項目 Response Message Field | DD10: 上り項目 Request Message Field | DE10: 下り項目 Response Message Field | DF10: 上り項目 Request Message Field | DG10: 下り項目 Response Message Field | DH10: 上り項目 Request Message Field | DI10: 下り項目 Response Message Field | DJ10: 上り項目 Request Message Field | DK10: 下り項目 Response Message Field | DL10: 上り項目 Request Message Field | DM10: 下り項目 Response Message Field | DN10: 上り項目 Request Message Field | DO10: 下り項目 Response Message Field | DP10: 上り項目 Request Message Field | DQ10: 下り項目 Response Message Field | DR10: 上り項目 Request Message Field | DS10: 下り項目 Response Message Field | DT10: 上り項目 Request Message Field | DU10: 下り項目 Response Message Field | DV10: 上り項目 Request Message Field | DW10: 下り項目 Response Message Field | DX10: 上り項目 Request Message Field | DY10: 下り項目 Response Message Field | DZ10: 上り項目 Request Message Field | EA10: 下り項目 Response Message Field | EB10: 上り項目 Request Message Field | EC10: 下り項目 Response Message Field | ED10: 上り項目 Request Message Field | EE10: 下り項目 Response Message Field | EF10: 上り項目 Request Message Field | EG10: 下り項目 Response Message Field | EH10: 上り項目 Request Message Field | EI10: 下り項目 Response Message Field | EJ10: 上り項目 Request Message Field | EK10: 下り項目 Response Message Field | EL10: 上り項目 Request Message Field | EM10: 下り項目 Response Message Field | EN10: 上り項目 Request Message Field | EO10: 下り項目 Response Message Field | EP10: 上り項目 Request Message Field | EQ10: 下り項目 Response Message Field | ER10: 上り項目 Request Message Field | ES10: 下り項目 Response Message Field | ET10: 上り項目 Request Message Field | EU10: 下り項目 Response Message Field | EV10: 上り項目 Request Message Field | EW10: 下り項目 Response Message Field | EX10: 上り項目 Request Message Field | EY10: 下り項目 Response Message Field | EZ10: 上り項目 Request Message Field | FA10: 下り項目 Response Message Field | FB10: 上り項目 Request Message Field | FC10: 下り項目 Response Message Field | FD10: 上り項目 Request Message Field | FE10: 下り項目 Response Message Field | FF10: 上り項目 Request Message Field | FG10: 下り項目 Response Message Field | FH10: 上り項目 Request Message Field | FI10: 下り項目 Response Message Field | FJ10: 上り項目 Request Message Field | FK10: 下り項目 Response Message Field | FL10: 上り項目 Request Message Field | FM10: 下り項目 Response Message Field | FN10: 上り項目 Request Message Field | FO10: 下り項目 Response Message Field | FP10: 上り項目 Request Message Field | FQ10: 下り項目 Response Message Field | FR10: 上り項目 Request Message Field | FS10: 下り項目 Response Message Field | FT10: 上り項目 Request Message Field | FU10: 下り項目 Response Message Field | FV10: 上り項目 Request Message Field | FW10: 下り項目 Response Message Field | FX10: 上り項目 Request Message Field | FY10: 下り項目 Response Message Field | FZ10: 上り項目 Request Message Field | GA10: 下り項目 Response Message Field | GB10: 上り項目 Request Message Field | GC10: 下り項目 Response Message Field | GD10: 上り項目 Request Message Field | GE10: 下り項目 Response Message Field | GF10: 上り項目 Request Message Field | GG10: 下り項目 Response Message Field | GH10: 上り項目 Request Message Field | GI10: 下り項目 Response Message Field | GJ10: 上り項目 Request Message Field | GK10: 下り項目 Response Message Field | GL10: 上り項目 Request Message Field | GM10: 下り項目 Response Message Field | GN10: 上り項目 Request Message Field | GO10: 下り項目 Response Message Field | GP10: 上り項目 Request Message Field | GQ10: 下り項目 Response Message Field | GR10: 上り項目 Request Message Field | GS10: 下り項目 Response Message Field | GT10: 上り項目 Request Message Field | GU10: 下り項目 Response Message Field | GV10: 上り項目 Request Message Field | GW10: 下り項目 Response Message Field | GX10: 上り項目 Request Message Field | GY10: 下り項目 Response Message Field | GZ10: 上り項目 Request Message Field | HA10: 下り項目 Response Message Field | HB10: 上り項目 Request Message Field | HC10: 下り項目 Response Message Field | HD10: 上り項目 Request Message Field | HE10: 下り項目 Response Message Field | HF10: 上り項目 Request Message Field | HG10: 下り項目 Response Message Field | HH10: 上り項目 Request Message Field | HI10: 下り項目 Response Message Field | HJ10: 上り項目 Request Message Field | HK10: 下り項目 Response Message Field | HL10: 上り項目 Request Message Field | HM10: 下り項目 Response Message Field | HN10: 上り項目 Request Message Field | HO10: 下り項目 Response Message Field | HP10: 上り項目 Request Message Field | HQ10: 下り項目 Response Message Field | HR10: 上り項目 Request Message Field | HS10: 下り項目 Response Message Field | HT10: 上り項目 Request Message Field | HU10: 下り項目 Response Message Field | HV10: 上り項目 Request Message Field | HW10: 下り項目 Response Message Field | HX10: 上り項目 Request Message Field | HY10: 下り項目 Response Message Field | HZ10: 上り項目 Request Message Field | IA10: 下り項目 Response Message Field
A11: 10 | B11: * | D11: Srch01_Cnd | E11: R | L11: R | P11: R | T11: R | X11: R | AB11: R | AF11: R | AJ11: R | AN11: R | AR11: R | AV11: R | AZ11: R | BD11: R | BH11: R | BL11: R | BP11: R | BT11: R | BX11: R | CB11: R | CF11: R | CJ11: R | CN11: R | CR11: R | CV11: R | CZ11: R | DD11: R | DH11: R | DL11: R | DP11: R | DT11: R | DX11: R | EB11: R | EF11: R | EJ11: R | EN11: R | ER11: R | EV11: R | EZ11: R | FD11: R | FH11: R | FL11: R | FP11: R | FT11: R | FX11: R | GB11: R | GF11: R | GJ11: R | GN11: R | GR11: R | GV11: R | GZ11: R | HD11: R | HH11: R | HL11: R | HP11: R | HT11: R | HX11: R
A12: 10 | D12: mst_nm | E12: #MA.ORA_OBJ_NM | G12: Master name | H12: マスタ名 | I12: E
A13: 10 | D13: cd | E13: C | G13: CD | H13: ＣＤ | I13: E | L13: da_cd | P13: dpt_cd | T13: dpt_lvl_cd | X13: aprv_role_cd | AB13: cntry_cd | AF13: area_cd | AJ13: cur_cd | AN13: unit_cd | AR13: bank_cd | AV13: bank_cd | AZ13: bank_ac_cd | BD13: xrate_cd | BH13: cal_cd | BL13: itm_jnl_cd | BP13: ac_itm_grp_cd | BT13: ac_rsn_cd | BX13: site_cd | CB13: loc_grp_cd | CF13: lg_grp_cd | CJ13: alloc_grp_cd | CN13: wg_cd | CR13: oper_cd | CV13: wk_cost_cd | CZ13: wk_rsn_cd | DD13: sls_upri_grp_cd | DH13: sls_upri_rank_cd | DL13: setoff_grp_cd | DP13: ship_valid_grp_cd | DT13: itm_ship_grp_cd | DX13: trnspt_cd | EB13: cntnr_cd | EF13: port_cd | EJ13: gd_cd | EN13: trd_cd | ER13: slip_form_cd | EV13: pf_grp_cd | EZ13: itm_spec_grp_cd | FD13: itm_comp_grp_cd | FH13: jnl_act_cd | FL13: jnl_grp_cd | FP13: jnl_ptn_cd | FT13: auto_jnl_key_cd | FX13: insp_ptn_cd | GB13: wk_day_cd | GF13: ship_term_cd | GJ13: ship_wk_cd | GN13: rsrc_cd | GR13: hs_grp_cd | GV13: alc_ptn_cd | GZ13: ctg_grp_cd | HD13: act_ptn_cd | HH13: gp_alc_cd | HL13: calc_ctg_cd | HP13: rpt_ptn_cd | HT13: menu_cd | HX13: site_co_cd
A14: 10 | D14: nm | E14: C | G14: Name | H14: 名 | I14: E | L14: da_nm | P14: def_dpt_nm | T14: dpt_lvl_nm | X14: aprv_role_nm | AB14: cntry_nm | AF14: area_nm | AJ14: cur_nm | AN14: unit_nm | AR14: bank_nm | AV14: branch_nm | AZ14: bank_ac_nm | BD14: xrate_nm | BH14: cal_nm | BL14: itm_jnl_nm | BP14: ac_itm_grp_nm | BT14: ac_rsn_nm | BX14: site_nm | CB14: loc_grp_nm | CF14: lg_grp_nm | CJ14: alloc_grp_nm | CN14: wg_nm | CR14: oper_nm | CV14: wk_cost_nm | CZ14: wk_rsn_nm | DD14: sls_upri_grp_nm | DH14: sls_upri_rank_nm | DL14: setoff_grp_nm | DP14: ship_valid_grp_nm | DT14: itm_ship_grp_nm | DX14: trnspt_nm | EB14: cntnr_nm | EF14: port_nm | EJ14: gd_nm | EN14: trd_nm | ER14: slip_form_nm | EV14: pf_grp_nm | EZ14: itm_spec_grp_nm | FD14: itm_comp_grp_nm | FH14: jnl_act_nm | FL14: jnl_grp_nm | FP14: jnl_ptn_nm | FT14: auto_jnl_key_nm | FX14: insp_ptn_nm | GB14: wk_day_nm | GF14: ship_term_nm | GJ14: ship_wk_nm | GN14: rsrc_nm | GR14: hs_grp_nm | GV14: alc_ptn_nm | GZ14: ctg_grp_nm | HD14: act_ptn_nm | HH14: gp_alc_nm | HL14: calc_ctg_nm | HP14: rpt_ptn_nm | HT14: menu_nm | HX14: site_co_nm
A15: 10 | D15: memo1 | E15: #MA.MST_MEMO1 | G15: Memo 1 | H15: メモ１ | I15: E
A16: 10 | D16: memo2 | E16: #MA.MST_MEMO2 | G16: Memo 2 | H16: メモ２ | I16: E
A17: 10 | D17: memo3 | E17: #MA.MST_MEMO3 | G17: Memo 3 | H17: メモ３ | I17: E
A18: 10 | D18: off_del_flg | E18: #MA.FLG | G18: Logical delete. Off | H18: 論理削除.オフ | I18: E
A19: 10 | D19: on_del_flg | E19: #MA.FLG | G19: Logical delete. On | H19: 論理削除.オン | I19: E
A20: 10 | D20: match_typ | E20: C | G20: Match type | H20: マッチタイプ | I20: E
A22: 20 | B22: * | D22: Srch01_Rslt1 | E22: L | M22: L | Q22: L | U22: L | Y22: L | AC22: L | AG22: L | AK22: L | AO22: L | AS22: L | AW22: L | BA22: L | BE22: L | BI22: L | BM22: L | BQ22: L | BU22: L | BY22: L | CC22: L | CG22: L | CK22: L | CO22: L | CS22: L | CW22: L | DA22: L | DE22: L | DI22: L | DM22: L | DQ22: L | DU22: L | DY22: L | EC22: L | EG22: L | EK22: L | EO22: L | ES22: L | EW22: L | FA22: L | FE22: L | FI22: L | FM22: L | FQ22: L | FU22: L | FY22: L | GC22: L | GG22: L | GK22: L | GO22: L | GS22: L | GW22: L | HA22: L | HE22: L | HI22: L | HM22: L | HQ22: L | HU22: L | HY22: L
A23: 20 | D23: del_flg | E23: #MA.FLG | G23: Logical delete | H23: 論理削除 | J23: E | M23: E | Q23: E | U23: E | Y23: E | AC23: E | AG23: E | AK23: E | AO23: E | AS23: E | AW23: E | BA23: E | BE23: E | BI23: E | BM23: E | BQ23: E | BU23: E | BY23: E | CC23: E | CG23: E | CK23: E | CO23: E | CS23: E | CW23: E | DA23: E | DE23: E | DI23: E | DM23: E | DQ23: E | DU23: E | DY23: E | EC23: E | EG23: E | EK23: E | EO23: E | ES23: E | EW23: E | FA23: E | FE23: E | FI23: E | FM23: E | FQ23: E | FU23: E | FY23: E | GC23: E | GG23: E | GK23: E | GO23: E | GS23: E | GW23: E | HA23: E | HE23: E | HI23: E | HM23: E | HQ23: E | HU23: E | HY23: E
A24: 20 | D24: da_cd | E24: #MA.DA_CD | G24: Data access cd. | H24: データアクセスＣＤ | J24: E | M24: E
A25: 20 | D25: da_nm_lcl | E25: #MA.DA_NM | G25: Data access name | H25: データアクセス名 | J25: E | M25: da_nm
A26: 20 | D26: da_nm | E26: #MA.DA_NM | G26: Standard data access name | H26: 標準データアクセス名 | J26: E | M26: base_da_nm
A27: 20 | D27: dpt_cd | E27: #MA.DPT_CD | G27: Dept. cd. | H27: 部門ＣＤ | J27: E | Q27: E
A28: 20 | D28: def_dpt_nm_lcl | E28: #MA.DPT_NM | G28: Dept. name | H28: 部門名 | J28: E | Q28: def_dpt_nm
A29: 20 | D29: def_dpt_nm | E29: #MA.DPT_NM | G29: Standard dept. name | H29: 標準部門名 | J29: E | Q29: base_def_dpt_nm
A30: 20 | D30: dpt_lvl_cd | E30: #MA.DPT_LVL_CD | G30: Dept. hierarchy cd. | H30: 部門階層ＣＤ | J30: E | U30: E
A31: 20 | D31: dpt_lvl_nm_lcl | E31: #MA.DPT_LVL_NM | G31: Dept. hierarchy name | H31: 部門階層名 | J31: E | U31: dpt_lvl_nm
A32: 20 | D32: dpt_lvl_nm | E32: #MA.DPT_LVL_NM | G32: Standard dept. hierarchy name | H32: 標準部門階層名 | J32: E | U32: base_dpt_lvl_nm
A33: 20 | D33: aprv_role_cd | E33: #MA.APRV_ROLE_CD | G33: Approval role cd. | H33: 承認役割ＣＤ | J33: E | Y33: E
A34: 20 | D34: aprv_role_nm_lcl | E34: #MA.APRV_ROLE_NM | G34: Approval role name | H34: 承認役割名 | J34: E | Y34: aprv_role_nm
A35: 20 | D35: aprv_role_nm | E35: #MA.APRV_ROLE_NM | G35: Standard approval role name | H35: 標準承認役割名 | J35: E | Y35: base_aprv_role_nm
A36: 20 | D36: cntry_cd | E36: #MA.CNTRY_CD | G36: Country cd. | H36: 国ＣＤ | J36: E | AC36: E
A37: 20 | D37: cntry_nm_lcl | E37: #MA.CNTRY_NM | G37: Country name | H37: 国名 | J37: E | AC37: cntry_nm
A38: 20 | D38: cntry_nm | E38: #MA.CNTRY_NM | G38: Standard Country name | H38: 標準国名 | J38: E | AC38: base_cntry_nm
A39: 20 | D39: area_cd | E39: #MA.AREA_CD | G39: Region cd. | H39: 地域ＣＤ | J39: E | AG39: E
A40: 20 | D40: area_nm_lcl | E40: #MA.AREA_NM | G40: Region name | H40: 地域名 | J40: E | AG40: area_nm
A41: 20 | D41: area_nm | E41: #MA.AREA_NM | G41: Standard Region name | H41: 標準地域名 | J41: E | AG41: base_area_nm
A42: 20 | D42: cur_cd | E42: #MA.CUR_CD | G42: Currency cd. | H42: 通貨ＣＤ | J42: E | AK42: E
A43: 20 | D43: cur_nm_lcl | E43: #MA.CUR_NM | G43: Currency name | H43: 通貨名 | J43: E | AK43: cur_nm
A44: 20 | D44: cur_nm | E44: #MA.CUR_NM | G44: Standard currency name | H44: 標準通貨名 | J44: E | AK44: base_cur_nm
A45: 20 | D45: amt_dec_place | E45: #MA.DEC_PLACE | G45: Amount number of decimal places | H45: 金額小数部有効桁数 | J45: E | AK45: E
A46: 20 | D46: upri_dec_place | E46: #MA.DEC_PLACE | G46: Unit price number of decimal places | H46: 単価小数部有効桁数 | J46: E | AK46: E
A47: 20 | D47: unit_cd | E47: #MA.UNIT_CD | G47: Unit cd. | H47: 単位ＣＤ | J47: E | AO47: E
A48: 20 | D48: unit_nm_lcl | E48: #MA.UNIT_NM | G48: Unit name | H48: 単位名 | J48: E | AO48: unit_nm
A49: 20 | D49: unit_nm | E49: #MA.UNIT_NM | G49: Standard unit name | H49: 標準単位名 | J49: E | AO49: base_unit_nm
A50: 20 | D50: dec_place | E50: #MA.DEC_PLACE | G50: Number of decimal places | H50: 小数部有効桁数 | J50: E | AO50: E
A51: 20 | D51: unit_rnd_typ | E51: #MA.RND_TYP | G51: Rounding type | H51: 端数処理区分 | J51: E | K51: MAC_RND_TYP | AO51: rnd_typ
A52: 20 | D52: unit_rnd_typ_nm | E52: #MA.RND_TYP_NM | G52: Rounding type name | H52: 端数処理区分名 | J52: E
A53: 20 | D53: bank_cd | E53: #MA.BANK_CD | G53: Bank cd. | H53: 銀行ＣＤ | J53: E | AS53: E
A54: 20 | D54: bank_nm_lcl | E54: #MA.BANK_NM | G54: Bank name | H54: 銀行名 | J54: E | AS54: bank_nm
A55: 20 | D55: bank_nm | E55: #MA.BANK_NM | G55: Standard bank name | H55: 標準銀行名 | J55: E | AS55: base_bank_nm
A56: 20 | D56: bank_cal_cd | E56: #MA.CAL_CD | G56: Calendar cd. | H56: カレンダＣＤ | J56: E | AS56: cal_cd
A57: 20 | D57: bank_cal_nm | E57: #MA.CAL_NM | G57: Calendar name | H57: カレンダ名 | J57: E | AS57: cal_nm
A58: 20 | D58: bank_branch_bank_cd | E58: #MA.BANK_CD | G58: Bank cd. | H58: 銀行ＣＤ | J58: E | AW58: bank_cd
A59: 20 | D59: bank_branch_bank_nm | E59: #MA.BANK_NM | G59: Bank name | H59: 銀行名 | J59: E | AW59: bank_nm
A60: 20 | D60: branch_cd | E60: #MA.BANK_BRANCH_CD | G60: Bank branch cd. | H60: 銀行支店ＣＤ | J60: E | AW60: E
A61: 20 | D61: branch_nm_lcl | E61: #MA.BANK_BRANCH_NM | G61: Bank branch name | H61: 銀行支店名 | J61: E | AW61: branch_nm
A62: 20 | D62: branch_nm | E62: #MA.BANK_BRANCH_NM | G62: Standard bank branch name | H62: 標準銀行支店名 | J62: E | AW62: base_branch_nm
A63: 20 | D63: bank_branch_cal_cd | E63: #MA.CAL_CD | G63: Calendar cd. | H63: カレンダＣＤ | J63: E | AW63: cal_cd
A64: 20 | D64: bank_branch_cal_nm | E64: #MA.CAL_NM | G64: Calendar name | H64: カレンダ名 | J64: E | AW64: cal_nm
A65: 20 | D65: bank_ac_cd | E65: #MA.BANK_AC_CD | G65: Bank account cd. | H65: 口座ＣＤ | J65: E | BA65: E
A66: 20 | D66: bank_ac_nm_lcl | E66: #MA.BANK_AC_NM | G66: Bank account name | H66: 口座名 | J66: E | BA66: bank_ac_nm
A67: 20 | D67: bank_ac_nm | E67: #MA.BANK_AC_NM | G67: Standard account name | H67: 標準口座名 | J67: E | BA67: base_bank_ac_nm
A68: 20 | D68: ext_flg | E68: #MA.FLG | G68: External | H68: 社外 | J68: E | BA68: ext_flg
A69: 20 | D69: bank_ac_bank_cd | E69: #MA.BANK_CD | G69: Bank cd. | H69: 銀行ＣＤ | J69: E | BA69: bank_cd
A70: 20 | D70: bank_ac_bank_nm | E70: #MA.BANK_NM | G70: Bank name | H70: 銀行名 | J70: E | BA70: bank_nm
A71: 20 | D71: bank_ac_branch_cd | E71: #MA.BANK_BRANCH_CD | G71: Bank branch cd. | H71: 銀行支店ＣＤ | J71: E | BA71: branch_cd
A72: 20 | D72: bank_ac_branch_nm | E72: #MA.BANK_BRANCH_NM | G72: Bank branch name | H72: 銀行支店名 | J72: E | BA72: branch_nm
A73: 20 | D73: bank_ac_no | E73: #MA.BANK_AC_NO | G73: Bank account number | H73: 口座番号 | J73: E | BA73: E
A74: 20 | D74: bank_ac_typ | E74: #MA.BANK_AC_TYP | G74: Bank account type | H74: 口座区分 | J74: E | K74: MAC_BANK_AC_TYP | BA74: E
A75: 20 | D75: bank_ac_typ_nm | E75: #MA.BANK_AC_TYP_NM | G75: Bank account type name | H75: 口座区分名 | J75: E
A76: 20 | D76: bank_ac_holder | E76: #MA.BANK_AC_HOLDER | G76: Bank account holder | H76: 口座名義 | J76: E | BA76: E
A77: 20 | D77: bank_ac_holder_sub | E77: #MA.BANK_AC_HOLDER_SUB | G77: Account holder alias name | H77: 口座名義別名 | J77: E | BA77: E
A78: 20 | D78: xrate_cd | E78: #MA.XRATE_CD | G78: Exchange rate cd. | H78: 為替レートＣＤ | J78: E | BE78: E
A79: 20 | D79: xrate_nm_lcl | E79: #MA.XRATE_NM | G79: Exchange rate name | H79: 為替レート名 | J79: E | BE79: xrate_nm
A80: 20 | D80: xrate_nm | E80: #MA.XRATE_NM | G80: Standard exchange rate name | H80: 標準為替レート名 | J80: E | BE80: base_xrate_nm
A81: 20 | D81: cal_cd | E81: #MA.CAL_CD | G81: Calendar cd. | H81: カレンダＣＤ | J81: E | BI81: E
A82: 20 | D82: cal_nm_lcl | E82: #MA.CAL_NM | G82: Calendar name | H82: カレンダ名 | J82: E | BI82: cal_nm
A83: 20 | D83: cal_nm | E83: #MA.CAL_NM | G83: Standard calendar name | H83: 標準カレンダ名 | J83: E | BI83: base_cal_nm
A84: 20 | D84: itm_jnl_cd | E84: #MA.ITM_JNL_CD | G84: Item journal cd. | H84: 品目仕訳ＣＤ | J84: E | BM84: E
A85: 20 | D85: itm_jnl_nm_lcl | E85: #MA.ITM_JNL_NM | G85: Item journal name | H85: 品目仕訳名 | J85: E | BM85: itm_jnl_nm
A86: 20 | D86: itm_jnl_nm | E86: #MA.ITM_JNL_NM | G86: Standard Item journal name | H86: 標準品目仕訳名 | J86: E | BM86: base_itm_jnl_nm
A87: 20 | D87: ar_typ | E87: #MA.AR_TYP | G87: AR type | H87: 債権区分 | J87: E | K87: MAC_AR_TYP | BM87: E
A88: 20 | D88: ar_typ_nm | E88: #MA.AR_TYP_NM | G88: AR type name | H88: 債権区分名 | J88: E
A89: 20 | D89: ap_typ | E89: #MA.AP_TYP | G89: AP type | H89: 債務区分 | J89: E | K89: MAC_AP_TYP | BM89: E
A90: 20 | D90: ap_typ_nm | E90: #MA.AP_TYP_NM | G90: AP type name | H90: 債務区分名 | J90: E
A91: 20 | D91: ac_itm_grp_cd | E91: #MA.AC_ITM_GRP_CD | G91: Accounting item classification cd. | H91: 会計品目分類ＣＤ | J91: E | BQ91: E
A92: 20 | D92: ac_itm_grp_nm_lcl | E92: #MA.AC_ITM_GRP_NM | G92: Accounting item classification name | H92: 会計品目分類名 | J92: E | BQ92: ac_itm_grp_nm
A93: 20 | D93: ac_itm_grp_nm | E93: #MA.AC_ITM_GRP_NM | G93: Standard Accounting item classification name | H93: 標準会計品目分類名 | J93: E | BQ93: base_ac_itm_grp_nm
A94: 20 | D94: ac_rsn_cd | E94: #MA.AC_RSN_CD | G94: Accounting reason cd. | H94: 会計理由ＣＤ | J94: E | BU94: E
A95: 20 | D95: ac_rsn_nm_lcl | E95: #MA.AC_RSN_NM | G95: Accounting reason name | H95: 会計理由名 | J95: E | BU95: ac_rsn_nm
A96: 20 | D96: ac_rsn_nm | E96: #MA.AC_RSN_NM | G96: Standard Accounting reason name | H96: 標準会計理由名 | J96: E | BU96: base_ac_rsn_nm
A97: 20 | D97: ac_rsn_ar_typ | E97: #MA.AR_TYP | G97: AR type | H97: 債権区分 | J97: E | K97: MAC_AR_TYP | BU97: ar_typ
A98: 20 | D98: ac_rsn_ar_typ_nm | E98: #MA.AR_TYP_NM | G98: AR type name | H98: 債権区分名 | J98: E
A99: 20 | D99: ac_rsn_ap_typ | E99: #MA.AP_TYP | G99: AP type | H99: 債務区分 | J99: E | K99: MAC_AP_TYP | BU99: ap_typ
A100: 20 | D100: ac_rsn_ap_typ_nm | E100: #MA.AP_TYP_NM | G100: AP type name | H100: 債務区分名 | J100: E
A101: 20 | D101: ac_invalid_flg | E101: #MA.FLG | G101: Not for journal | H101: 仕訳対象外 | J101: E | BU101: E
...

Sheet Upd01
A1: * | B1: * | D1: L | E1: 1
A2: * | D2: オペレーション実装仕様書 Operation Specification Implementation Sheet | E2: ModuleID : | F2: =IF(LogicCommon!C2="","",LogicCommon!C2) -> MA | G2: LogicID : | H2: =IF(LogicCommon!E2="","",LogicCommon!E2) -> MABCL0030 | I2: Ope.ID : | J2: Upd01 | K2: Pj.ID : | L2: =IF(LogicCommon!G2="","",LogicCommon!G2) -> MC | M2: Ope.Body : | N2: "mcframe.serverMAUD.MAUDL6020.MAUDL_LCLRLUpdater"
A3: * | D3: =IF(LogicCommon!A3="","",LogicCommon!A3) | E3: SubModuleID : | F3: =IF(LogicCommon!C3="","",LogicCommon!C3) -> MABC | G3: LogicClass : | H3: =IF(LogicCommon!E3="","",LogicCommon!E3) -> MABCL_MultiReg | I3: Ope.Method : | J3: @ | K3: SuperClassPj.ID : | L3: =IF(LogicCommon!G3="","",LogicCommon!G3) | M3: ReportID : | O3: Gene.Type : | P3: ALL
A4: * | E4: Version : | F4: 000000 | G4: LogicName : | H4: =IF(LogicCommon!E4="","",LogicCommon!E4) -> マルチマスタ登録 | I4: Ope.Name : | J4: 登録 | K4: SuperLogicID : | L4: =IF(LogicCommon!G4="","",LogicCommon!G4) -> MA.MAUDL5010
A5: * | E5: ACType : | K5: 1 | O5: 2 | S5: 3 | W5: 4 | AA5: 5 | AE5: 6 | AI5: 7 | AM5: 8 | AQ5: 9 | AU5: 10 | AY5: 11 | BC5: 12 | BG5: 13 | BK5: 14 | BO5: 15 | BS5: 16 | BW5: 17 | CA5: 18 | CE5: 19 | CI5: 20 | CM5: 21 | CQ5: 22 | CU5: 23 | CY5: 24 | DC5: 25 | DG5: 26 | DK5: 27 | DO5: 28 | DS5: 29 | DW5: 30 | EA5: 31 | EE5: 32 | EI5: 33 | EM5: 34 | EQ5: 35 | EU5: 36 | EY5: 37 | FC5: 38 | FG5: 39 | FK5: 40 | FO5: 41 | FS5: 42 | FW5: 43 | GA5: 44 | GE5: 45 | GI5: 46 | GM5: 47 | GQ5: 48 | GU5: 49 | GY5: 50 | HC5: 51 | HG5: 52 | HK5: 53 | HO5: 54 | HS5: 55 | HW5: 56 | IA5: 57 | IE5: 58 | II5: 59 | IM5: 60 | IQ5: 61 | IU5: 62 | IY5: 63 | JC5: 64 | JG5: 65 | JK5: 66 | JO5: 67 | JS5: 68 | JW5: 69 | KA5: 70 | KE5: 71 | KI5: 72 | KM5: 73 | KQ5: 74 | KU5: 75 | KY5: 76 | LC5: 77 | LG5: 78 | LK5: 79 | LO5: 80 | LS5: 81 | LW5: 82 | MA5: 83 | ME5: 84 | MI5: 85 | MM5: 86 | MQ5: 87 | MU5: 88 | MY5: 89 | NC5: 90 | NG5: 91 | NK5: 92 | NO5: 93 | NS5: 94 | NW5: 95 | OA5: 96 | OE5: 97 | OI5: 98 | OM5: 99 | OQ5: 100 | OU5: 101 | OY5: 102 | PC5: 103 | PG5: 104 | PK5: 105 | PO5: 106 | PS5: 107 | PW5: 108 | QA5: 109 | QE5: 110 | QI5: 111 | QM5: 112
A6: * | D6: 概要 : | E6: 複数のマスタ、名称マスタの登録を行います。（マスタ画面用） | K6: Da | L6: MABCL0031 | S6: Dpt_Base | T6: MABCL0031 | AA6: Dpt_Lvl | AB6: MABCL0031 | AI6: Aprv_Role | AJ6: MABCL0031 | AQ6: Cntry | AR6: MABCL0031 | AY6: Area | AZ6: MABCL0031 | BG6: Cur | BH6: MABCL0031 | BO6: Unit | BP6: MABCL0031 | BW6: Bank | BX6: MABCL0031 | CE6: Bank_Branch | CF6: MABCL0031 | CM6: Bank_Ac | CN6: MABCL0032 | CU6: Xrate | CV6: MABCL0032 | DC6: Cal_Base | DD6: MABCL0032 | DK6: Itm_Jnl | DL6: MABCL0032 | DS6: Ac_Itm_Grp | DT6: MABCL0032 | EA6: Ac_Rsn | EB6: MABCL0032 | EI6: Site | EJ6: MABCL0032 | EQ6: Loc_Grp | ER6: MABCL0032 | EY6: Lg_Grp | EZ6: MABCL0032 | FG6: Alloc_Grp | FH6: MABCL0032 | FO6: Wg | FP6: MABCL0033 | FW6: Oper | FX6: MABCL0033 | GE6: Wk_Cost | GF6: MABCL0033 | GM6: Wk_Rsn | GN6: MABCL0033 | GU6: Sls_Upri_Grp | GV6: MABCL0033 | HC6: Sls_Upri_Rank | HD6: MABCL0033 | HK6: Setoff_Grp | HL6: MABCL0033 | HS6: Ship_Valid | HT6: MABCL0033 | IA6: Itm_Ship_Grp | IB6: MABCL0033 | II6: Trnspt | IJ6: MABCL0033 | IQ6: Ex_Cntnr | IR6: MABCL0034 | IY6: Exim_Port | IZ6: MABCL0034 | JG6: Stk_Gd | JH6: MABCL0034 | JO6: Trd | JP6: MABCL0034 | JW6: Slip_Form | JX6: MABCL0034 | KE6: Pf_Grp | KF6: MABCL0034 | KM6: Itm_Spec_Grp | KN6: MABCL0034 | KU6: Itm_Comp_Grp | KV6: MABCL0034 | LC6: Jnl_Act | LD6: MABCL0034 | LK6: Jnl_Grp | LL6: MABCL0034 | LS6: Jnl_Ptn_Base | LT6: MABCL0035 | MA6: Auto_Jnl_Key | MB6: MABCL0035 | MI6: Insp_Ptn | MJ6: MABCL0035 | MQ6: Wk_Day | MR6: MABCL0035 | MY6: Ship_Term | MZ6: MABCL0035 | NG6: Ship_Wk | NH6: MABCL0035 | NO6: Rsrc | NP6: MABCL0035 | NW6: Hs_Grp | NX6: MABCL0035 | OE6: Alc_Ptn | OF6: MABCL0035 | OM6: Ctg_Grp | ON6: MABCL0035 | OU6: Act_Ptn | OV6: MABCL0035 | PC6: Gp_Alc | PD6: MABCL0036 | PK6: Calc_Ctg | PL6: MABCL0036 | PS6: Rpt_Ptn | PT6: MABCL0036 | QA6: Cost_Menu | QB6: MABCL0036 | QI6: Site_Co | QJ6: MABCL0036
A7: # | I7: U | K7: o | L7: =UPPER(K6)&".chk"&TEXT(K5,"00") -> DA.chk01 | M7: o | N7: =UPPER(K6)&".upd"&TEXT(K5,"00") -> DA.upd01 | O7: o | P7: =UPPER(K6)&".chk"&TEXT(O5,"00") -> DA.chk02 | Q7: o | R7: =UPPER(K6)&".upd"&TEXT(O5,"00") -> DA.upd02 | S7: o | T7: =UPPER(S6)&".chk"&TEXT(S5,"00") -> DPT_BASE.chk03 | U7: o | V7: =UPPER(S6)&".upd"&TEXT(S5,"00") -> DPT_BASE.upd03 | W7: o | X7: =UPPER(S6)&".chk"&TEXT(W5,"00") -> DPT_BASE.chk04 | Y7: o | Z7: =UPPER(S6)&".upd"&TEXT(W5,"00") -> DPT_BASE.upd04 | AA7: o | AB7: =UPPER(AA6)&".chk"&TEXT(AA5,"00") -> DPT_LVL.chk05 | AC7: o | AD7: =UPPER(AA6)&".upd"&TEXT(AA5,"00") -> DPT_LVL.upd05 | AE7: o | AF7: =UPPER(AA6)&".chk"&TEXT(AE5,"00") -> DPT_LVL.chk06 | AG7: o | AH7: =UPPER(AA6)&".upd"&TEXT(AE5,"00") -> DPT_LVL.upd06 | AI7: o | AJ7: =UPPER(AI6)&".chk"&TEXT(AI5,"00") -> APRV_ROLE.chk07 | AK7: o | AL7: =UPPER(AI6)&".upd"&TEXT(AI5,"00") -> APRV_ROLE.upd07 | AM7: o | AN7: =UPPER(AI6)&".chk"&TEXT(AM5,"00") -> APRV_ROLE.chk08 | AO7: o | AP7: =UPPER(AI6)&".upd"&TEXT(AM5,"00") -> APRV_ROLE.upd08 | AQ7: o | AR7: =UPPER(AQ6)&".chk"&TEXT(AQ5,"00") -> CNTRY.chk09 | AS7: o | AT7: =UPPER(AQ6)&".upd"&TEXT(AQ5,"00") -> CNTRY.upd09 | AU7: o | AV7: =UPPER(AQ6)&".chk"&TEXT(AU5,"00") -> CNTRY.chk10 | AW7: o | AX7: =UPPER(AQ6)&".upd"&TEXT(AU5,"00") -> CNTRY.upd10 | AY7: o | AZ7: =UPPER(AY6)&".chk"&TEXT(AY5,"00") -> AREA.chk11 | BA7: o | BB7: =UPPER(AY6)&".upd"&TEXT(AY5,"00") -> AREA.upd11 | BC7: o | BD7: =UPPER(AY6)&".chk"&TEXT(BC5,"00") -> AREA.chk12 | BE7: o | BF7: =UPPER(AY6)&".upd"&TEXT(BC5,"00") -> AREA.upd12 | BG7: o | BH7: =UPPER(BG6)&".chk"&TEXT(BG5,"00") -> CUR.chk13 | BI7: o | BJ7: =UPPER(BG6)&".upd"&TEXT(BG5,"00") -> CUR.upd13 | BK7: o | BL7: =UPPER(BG6)&".chk"&TEXT(BK5,"00") -> CUR.chk14 | BM7: o | BN7: =UPPER(BG6)&".upd"&TEXT(BK5,"00") -> CUR.upd14 | BO7: o | BP7: =UPPER(BO6)&".chk"&TEXT(BO5,"00") -> UNIT.chk15 | BQ7: o | BR7: =UPPER(BO6)&".upd"&TEXT(BO5,"00") -> UNIT.upd15 | BS7: o | BT7: =UPPER(BO6)&".chk"&TEXT(BS5,"00") -> UNIT.chk16 | BU7: o | BV7: =UPPER(BO6)&".upd"&TEXT(BS5,"00") -> UNIT.upd16 | BW7: o | BX7: =UPPER(BW6)&".chk"&TEXT(BW5,"00") -> BANK.chk17 | BY7: o | BZ7: =UPPER(BW6)&".upd"&TEXT(BW5,"00") -> BANK.upd17 | CA7: o | CB7: =UPPER(BW6)&".chk"&TEXT(CA5,"00") -> BANK.chk18 | CC7: o | CD7: =UPPER(BW6)&".upd"&TEXT(CA5,"00") -> BANK.upd18 | CE7: o | CF7: =UPPER(CE6)&".chk"&TEXT(CE5,"00") -> BANK_BRANCH.chk19 | CG7: o | CH7: =UPPER(CE6)&".upd"&TEXT(CE5,"00") -> BANK_BRANCH.upd19 | CI7: o | CJ7: =UPPER(CE6)&".chk"&TEXT(CI5,"00") -> BANK_BRANCH.chk20 | CK7: o | CL7: =UPPER(CE6)&".upd"&TEXT(CI5,"00") -> BANK_BRANCH.upd20 | CM7: o | CN7: =UPPER(CM6)&".chk"&TEXT(CM5,"00") -> BANK_AC.chk21 | CO7: o | CP7: =UPPER(CM6)&".upd"&TEXT(CM5,"00") -> BANK_AC.upd21 | CQ7: o | CR7: =UPPER(CM6)&".chk"&TEXT(CQ5,"00") -> BANK_AC.chk22 | CS7: o | CT7: =UPPER(CM6)&".upd"&TEXT(CQ5,"00") -> BANK_AC.upd22 | CU7: o | CV7: =UPPER(CU6)&".chk"&TEXT(CU5,"00") -> XRATE.chk23 | CW7: o | CX7: =UPPER(CU6)&".upd"&TEXT(CU5,"00") -> XRATE.upd23 | CY7: o | CZ7: =UPPER(CU6)&".chk"&TEXT(CY5,"00") -> XRATE.chk24 | DA7: o | DB7: =UPPER(CU6)&".upd"&TEXT(CY5,"00") -> XRATE.upd24 | DC7: o | DD7: =UPPER(DC6)&".chk"&TEXT(DC5,"00") -> CAL_BASE.chk25 | DE7: o | DF7: =UPPER(DC6)&".upd"&TEXT(DC5,"00") -> CAL_BASE.upd25 | DG7: o | DH7: =UPPER(DC6)&".chk"&TEXT(DG5,"00") -> CAL_BASE.chk26 | DI7: o | DJ7: =UPPER(DC6)&".upd"&TEXT(DG5,"00") -> CAL_BASE.upd26 | DK7: o | DL7: =UPPER(DK6)&".chk"&TEXT(DK5,"00") -> ITM_JNL.chk27 | DM7: o | DN7: =UPPER(DK6)&".upd"&TEXT(DK5,"00") -> ITM_JNL.upd27 | DO7: o | DP7: =UPPER(DK6)&".chk"&TEXT(DO5,"00") -> ITM_JNL.chk28 | DQ7: o | DR7: =UPPER(DK6)&".upd"&TEXT(DO5,"00") -> ITM_JNL.upd28 | DS7: o | DT7: =UPPER(DS6)&".chk"&TEXT(DS5,"00") -> AC_ITM_GRP.chk29 | DU7: o | DV7: =UPPER(DS6)&".upd"&TEXT(DS5,"00") -> AC_ITM_GRP.upd29 | DW7: o | DX7: =UPPER(DS6)&".chk"&TEXT(DW5,"00") -> AC_ITM_GRP.chk30 | DY7: o | DZ7: =UPPER(DS6)&".upd"&TEXT(DW5,"00") -> AC_ITM_GRP.upd30 | EA7: o | EB7: =UPPER(EA6)&".chk"&TEXT(EA5,"00") -> AC_RSN.chk31 | EC7: o | ED7: =UPPER(EA6)&".upd"&TEXT(EA5,"00") -> AC_RSN.upd31 | EE7: o | EF7: =UPPER(EA6)&".chk"&TEXT(EE5,"00") -> AC_RSN.chk32 | EG7: o | EH7: =UPPER(EA6)&".upd"&TEXT(EE5,"00") -> AC_RSN.upd32 | EI7: o | EJ7: =UPPER(EI6)&".chk"&TEXT(EI5,"00") -> SITE.chk33 | EK7: o | EL7: =UPPER(EI6)&".upd"&TEXT(EI5,"00") -> SITE.upd33 | EM7: o | EN7: =UPPER(EI6)&".chk"&TEXT(EM5,"00") -> SITE.chk34 | EO7: o | EP7: =UPPER(EI6)&".upd"&TEXT(EM5,"00") -> SITE.upd34 | EQ7: o | ER7: =UPPER(EQ6)&".chk"&TEXT(EQ5,"00") -> LOC_GRP.chk35 | ES7: o | ET7: =UPPER(EQ6)&".upd"&TEXT(EQ5,"00") -> LOC_GRP.upd35 | EU7: o | EV7: =UPPER(EQ6)&".chk"&TEXT(EU5,"00") -> LOC_GRP.chk36 | EW7: o | EX7: =UPPER(EQ6)&".upd"&TEXT(EU5,"00") -> LOC_GRP.upd36 | EY7: o | EZ7: =UPPER(EY6)&".chk"&TEXT(EY5,"00") -> LG_GRP.chk37 | FA7: o | FB7: =UPPER(EY6)&".upd"&TEXT(EY5,"00") -> LG_GRP.upd37 | FC7: o | FD7: =UPPER(EY6)&".chk"&TEXT(FC5,"00") -> LG_GRP.chk38 | FE7: o | FF7: =UPPER(EY6)&".upd"&TEXT(FC5,"00") -> LG_GRP.upd38 | FG7: o | FH7: =UPPER(FG6)&".chk"&TEXT(FG5,"00") -> ALLOC_GRP.chk39 | FI7: o | FJ7: =UPPER(FG6)&".upd"&TEXT(FG5,"00") -> ALLOC_GRP.upd39 | FK7: o | FL7: =UPPER(FG6)&".chk"&TEXT(FK5,"00") -> ALLOC_GRP.chk40 | FM7: o | FN7: =UPPER(FG6)&".upd"&TEXT(FK5,"00") -> ALLOC_GRP.upd40 | FO7: o | FP7: =UPPER(FO6)&".chk"&TEXT(FO5,"00") -> WG.chk41 | FQ7: o | FR7: =UPPER(FO6)&".upd"&TEXT(FO5,"00") -> WG.upd41 | FS7: o | FT7: =UPPER(FO6)&".chk"&TEXT(FS5,"00") -> WG.chk42 | FU7: o | FV7: =UPPER(FO6)&".upd"&TEXT(FS5,"00") -> WG.upd42 | FW7: o | FX7: =UPPER(FW6)&".chk"&TEXT(FW5,"00") -> OPER.chk43 | FY7: o | FZ7: =UPPER(FW6)&".upd"&TEXT(FW5,"00") -> OPER.upd43 | GA7: o | GB7: =UPPER(FW6)&".chk"&TEXT(GA5,"00") -> OPER.chk44 | GC7: o | GD7: =UPPER(FW6)&".upd"&TEXT(GA5,"00") -> OPER.upd44 | GE7: o | GF7: =UPPER(GE6)&".chk"&TEXT(GE5,"00") -> WK_COST.chk45 | GG7: o | GH7: =UPPER(GE6)&".upd"&TEXT(GE5,"00") -> WK_COST.upd45 | GI7: o | GJ7: =UPPER(GE6)&".chk"&TEXT(GI5,"00") -> WK_COST.chk46 | GK7: o | GL7: =UPPER(GE6)&".upd"&TEXT(GI5,"00") -> WK_COST.upd46 | GM7: o | GN7: =UPPER(GM6)&".chk"&TEXT(GM5,"00") -> WK_RSN.chk47 | GO7: o | GP7: =UPPER(GM6)&".upd"&TEXT(GM5,"00") -> WK_RSN.upd47 | GQ7: o | GR7: =UPPER(GM6)&".chk"&TEXT(GQ5,"00") -> WK_RSN.chk48 | GS7: o | GT7: =UPPER(GM6)&".upd"&TEXT(GQ5,"00") -> WK_RSN.upd48 | GU7: o | GV7: =UPPER(GU6)&".chk"&TEXT(GU5,"00") -> SLS_UPRI_GRP.chk49 | GW7: o | GX7: =UPPER(GU6)&".upd"&TEXT(GU5,"00") -> SLS_UPRI_GRP.upd49 | GY7: o | GZ7: =UPPER(GU6)&".chk"&TEXT(GY5,"00") -> SLS_UPRI_GRP.chk50 | HA7: o | HB7: =UPPER(GU6)&".upd"&TEXT(GY5,"00") -> SLS_UPRI_GRP.upd50 | HC7: o | HD7: =UPPER(HC6)&".chk"&TEXT(HC5,"00") -> SLS_UPRI_RANK.chk51 | HE7: o | HF7: =UPPER(HC6)&".upd"&TEXT(HC5,"00") -> SLS_UPRI_RANK.upd51 | HG7: o | HH7: =UPPER(HC6)&".chk"&TEXT(HG5,"00") -> SLS_UPRI_RANK.chk52 | HI7: o | HJ7: =UPPER(HC6)&".upd"&TEXT(HG5,"00") -> SLS_UPRI_RANK.upd52 | HK7: o | HL7: =UPPER(HK6)&".chk"&TEXT(HK5,"00") -> SETOFF_GRP.chk53 | HM7: o | HN7: =UPPER(HK6)&".upd"&TEXT(HK5,"00") -> SETOFF_GRP.upd53 | HO7: o | HP7: =UPPER(HK6)&".chk"&TEXT(HO5,"00") -> SETOFF_GRP.chk54 | HQ7: o | HR7: =UPPER(HK6)&".upd"&TEXT(HO5,"00") -> SETOFF_GRP.upd54 | HS7: o | HT7: =UPPER(HS6)&".chk"&TEXT(HS5,"00") -> SHIP_VALID.chk55 | HU7: o | HV7: =UPPER(HS6)&".upd"&TEXT(HS5,"00") -> SHIP_VALID.upd55 | HW7: o | HX7: =UPPER(HS6)&".chk"&TEXT(HW5,"00") -> SHIP_VALID.chk56 | HY7: o | HZ7: =UPPER(HS6)&".upd"&TEXT(HW5,"00") -> SHIP_VALID.upd56 | IA7: o | IB7: =UPPER(IA6)&".chk"&TEXT(IA5,"00") -> ITM_SHIP_GRP.chk57 | IC7: o | ID7: =UPPER(IA6)&".upd"&TEXT(IA5,"00") -> ITM_SHIP_GRP.upd57 | IE7: o | IF7: =UPPER(IA6)&".chk"&TEXT(IE5,"00") -> ITM_SHIP_GRP.chk58 | IG7: o | IH7: =UPPER(IA6)&".upd"&TEXT(IE5,"00") -> ITM_SHIP_GRP.upd58 | II7: o | IJ7: =UPPER(II6)&".chk"&TEXT(II5,"00") -> TRNSPT.chk59 | IK7: o | IL7: =UPPER(II6)&".upd"&TEXT(II5,"00") -> TRNSPT.upd59 | IM7: o | IN7: =UPPER(II6)&".chk"&TEXT(IM5,"00") -> TRNSPT.chk60 | IO7: o | IP7: =UPPER(II6)&".upd"&TEXT(IM5,"00") -> TRNSPT.upd60 | IQ7: o | IR7: =UPPER(IQ6)&".chk"&TEXT(IQ5,"00") -> EX_CNTNR.chk61 | IS7: o | IT7: =UPPER(IQ6)&".upd"&TEXT(IQ5,"00") -> EX_CNTNR.upd61 | IU7: o | IV7: =UPPER(IQ6)&".chk"&TEXT(IU5,"00") -> EX_CNTNR.chk62 | IW7: o | IX7: =UPPER(IQ6)&".upd"&TEXT(IU5,"00") -> EX_CNTNR.upd62 | IY7: o | IZ7: =UPPER(IY6)&".chk"&TEXT(IY5,"00") -> EXIM_PORT.chk63 | JA7: o | JB7: =UPPER(IY6)&".upd"&TEXT(IY5,"00") -> EXIM_PORT.upd63 | JC7: o | JD7: =UPPER(IY6)&".chk"&TEXT(JC5,"00") -> EXIM_PORT.chk64 | JE7: o | JF7: =UPPER(IY6)&".upd"&TEXT(JC5,"00") -> EXIM_PORT.upd64 | JG7: o | JH7: =UPPER(JG6)&".chk"&TEXT(JG5,"00") -> STK_GD.chk65 | JI7: o | JJ7: =UPPER(JG6)&".upd"&TEXT(JG5,"00") -> STK_GD.upd65 | JK7: o | JL7: =UPPER(JG6)&".chk"&TEXT(JK5,"00") -> STK_GD.chk66 | JM7: o | JN7: =UPPER(JG6)&".upd"&TEXT(JK5,"00") -> STK_GD.upd66 | JO7: o | JP7: =UPPER(JO6)&".chk"&TEXT(JO5,"00") -> TRD.chk67 | JQ7: o | JR7: =UPPER(JO6)&".upd"&TEXT(JO5,"00") -> TRD.upd67 | JS7: o | JT7: =UPPER(JO6)&".chk"&TEXT(JS5,"00") -> TRD.chk68 | JU7: o | JV7: =UPPER(JO6)&".upd"&TEXT(JS5,"00") -> TRD.upd68 | JW7: o | JX7: =UPPER(JW6)&".chk"&TEXT(JW5,"00") -> SLIP_FORM.chk69 | JY7: o | JZ7: =UPPER(JW6)&".upd"&TEXT(JW5,"00") -> SLIP_FORM.upd69 | KA7: o | KB7: =UPPER(JW6)&".chk"&TEXT(KA5,"00") -> SLIP_FORM.chk70 | KC7: o | KD7: =UPPER(JW6)&".upd"&TEXT(KA5,"00") -> SLIP_FORM.upd70 | KE7: o | KF7: =UPPER(KE6)&".chk"&TEXT(KE5,"00") -> PF_GRP.chk71 | KG7: o | KH7: =UPPER(KE6)&".upd"&TEXT(KE5,"00") -> PF_GRP.upd71 | KI7: o | KJ7: =UPPER(KE6)&".chk"&TEXT(KI5,"00") -> PF_GRP.chk72 | KK7: o | KL7: =UPPER(KE6)&".upd"&TEXT(KI5,"00") -> PF_GRP.upd72 | KM7: o | KN7: =UPPER(KM6)&".chk"&TEXT(KM5,"00") -> ITM_SPEC_GRP.chk73 | KO7: o | KP7: =UPPER(KM6)&".upd"&TEXT(KM5,"00") -> ITM_SPEC_GRP.upd73 | KQ7: o | KR7: =UPPER(KM6)&".chk"&TEXT(KQ5,"00") -> ITM_SPEC_GRP.chk74 | KS7: o | KT7: =UPPER(KM6)&".upd"&TEXT(KQ5,"00") -> ITM_SPEC_GRP.upd74 | KU7: o | KV7: =UPPER(KU6)&".chk"&TEXT(KU5,"00") -> ITM_COMP_GRP.chk75 | KW7: o | KX7: =UPPER(KU6)&".upd"&TEXT(KU5,"00") -> ITM_COMP_GRP.upd75 | KY7: o | KZ7: =UPPER(KU6)&".chk"&TEXT(KY5,"00") -> ITM_COMP_GRP.chk76 | LA7: o | LB7: =UPPER(KU6)&".upd"&TEXT(KY5,"00") -> ITM_COMP_GRP.upd76 | LC7: o | LD7: =UPPER(LC6)&".chk"&TEXT(LC5,"00") -> JNL_ACT.chk77 | LE7: o | LF7: =UPPER(LC6)&".upd"&TEXT(LC5,"00") -> JNL_ACT.upd77 | LG7: o | LH7: =UPPER(LC6)&".chk"&TEXT(LG5,"00") -> JNL_ACT.chk78 | LI7: o | LJ7: =UPPER(LC6)&".upd"&TEXT(LG5,"00") -> JNL_ACT.upd78 | LK7: o | LL7: =UPPER(LK6)&".chk"&TEXT(LK5,"00") -> JNL_GRP.chk79 | LM7: o | LN7: =UPPER(LK6)&".upd"&TEXT(LK5,"00") -> JNL_GRP.upd79 | LO7: o | LP7: =UPPER(LK6)&".chk"&TEXT(LO5,"00") -> JNL_GRP.chk80 | LQ7: o | LR7: =UPPER(LK6)&".upd"&TEXT(LO5,"00") -> JNL_GRP.upd80 | LS7: o | LT7: =UPPER(LS6)&".chk"&TEXT(LS5,"00") -> JNL_PTN_BASE.chk81 | LU7: o | LV7: =UPPER(LS6)&".upd"&TEXT(LS5,"00") -> JNL_PTN_BASE.upd81 | LW7: o | LX7: =UPPER(LS6)&".chk"&TEXT(LW5,"00") -> JNL_PTN_BASE.chk82 | LY7: o | LZ7: =UPPER(LS6)&".upd"&TEXT(LW5,"00") -> JNL_PTN_BASE.upd82 | MA7: o | MB7: =UPPER(MA6)&".chk"&TEXT(MA5,"00") -> AUTO_JNL_KEY.chk83 | MC7: o | MD7: =UPPER(MA6)&".upd"&TEXT(MA5,"00") -> AUTO_JNL_KEY.upd83 | ME7: o | MF7: =UPPER(MA6)&".chk"&TEXT(ME5,"00") -> AUTO_JNL_KEY.chk84 | MG7: o | MH7: =UPPER(MA6)&".upd"&TEXT(ME5,"00") -> AUTO_JNL_KEY.upd84 | MI7: o | MJ7: =UPPER(MI6)&".chk"&TEXT(MI5,"00") -> INSP_PTN.chk85 | MK7: o | ML7: =UPPER(MI6)&".upd"&TEXT(MI5,"00") -> INSP_PTN.upd85 | MM7: o | MN7: =UPPER(MI6)&".chk"&TEXT(MM5,"00") -> INSP_PTN.chk86 | MO7: o | MP7: =UPPER(MI6)&".upd"&TEXT(MM5,"00") -> INSP_PTN.upd86 | MQ7: o | MR7: =UPPER(MQ6)&".chk"&TEXT(MQ5,"00") -> WK_DAY.chk87 | MS7: o | MT7: =UPPER(MQ6)&".upd"&TEXT(MQ5,"00") -> WK_DAY.upd87 | MU7: o | MV7: =UPPER(MQ6)&".chk"&TEXT(MU5,"00") -> WK_DAY.chk88 | MW7: o | MX7: =UPPER(MQ6)&".upd"&TEXT(MU5,"00") -> WK_DAY.upd88 | MY7: o | MZ7: =UPPER(MY6)&".chk"&TEXT(MY5,"00") -> SHIP_TERM.chk89 | NA7: o | NB7: =UPPER(MY6)&".upd"&TEXT(MY5,"00") -> SHIP_TERM.upd89 | NC7: o | ND7: =UPPER(MY6)&".chk"&TEXT(NC5,"00") -> SHIP_TERM.chk90 | NE7: o | NF7: =UPPER(MY6)&".upd"&TEXT(NC5,"00") -> SHIP_TERM.upd90 | NG7: o | NH7: =UPPER(NG6)&".chk"&TEXT(NG5,"00") -> SHIP_WK.chk91 | NI7: o | NJ7: =UPPER(NG6)&".upd"&TEXT(NG5,"00") -> SHIP_WK.upd91 | NK7: o | NL7: =UPPER(NG6)&".chk"&TEXT(NK5,"00") -> SHIP_WK.chk92 | NM7: o | NN7: =UPPER(NG6)&".upd"&TEXT(NK5,"00") -> SHIP_WK.upd92 | NO7: o | NP7: =UPPER(NO6)&".chk"&TEXT(NO5,"00") -> RSRC.chk93 | NQ7: o | NR7: =UPPER(NO6)&".upd"&TEXT(NO5,"00") -> RSRC.upd93 | NS7: o | NT7: =UPPER(NO6)&".chk"&TEXT(NS5,"00") -> RSRC.chk94 | NU7: o | NV7: =UPPER(NO6)&".upd"&TEXT(NS5,"00") -> RSRC.upd94 | NW7: o | NX7: =UPPER(NW6)&".chk"&TEXT(NW5,"00") -> HS_GRP.chk95 | NY7: o | NZ7: =UPPER(NW6)&".upd"&TEXT(NW5,"00") -> HS_GRP.upd95 | OA7: o | OB7: =UPPER(NW6)&".chk"&TEXT(OA5,"00") -> HS_GRP.chk96 | OC7: o | OD7: =UPPER(NW6)&".upd"&TEXT(OA5,"00") -> HS_GRP.upd96 | OE7: o | OF7: =UPPER(OE6)&".chk"&TEXT(OE5,"00") -> ALC_PTN.chk97 | OG7: o | OH7: =UPPER(OE6)&".upd"&TEXT(OE5,"00") -> ALC_PTN.upd97 | OI7: o | OJ7: =UPPER(OE6)&".chk"&TEXT(OI5,"00") -> ALC_PTN.chk98 | OK7: o | OL7: =UPPER(OE6)&".upd"&TEXT(OI5,"00") -> ALC_PTN.upd98 | OM7: o | ON7: =UPPER(OM6)&".chk"&TEXT(OM5,"00") -> CTG_GRP.chk99 | OO7: o | OP7: =UPPER(OM6)&".upd"&TEXT(OM5,"00") -> CTG_GRP.upd99 | OQ7: o | OR7: =UPPER(OM6)&".chk"&TEXT(OQ5,"00") -> CTG_GRP.chk100 | OS7: o | OT7: =UPPER(OM6)&".upd"&TEXT(OQ5,"00") -> CTG_GRP.upd100 | OU7: o | OV7: =UPPER(OU6)&".chk"&TEXT(OU5,"00") -> ACT_PTN.chk101 | OW7: o | OX7: =UPPER(OU6)&".upd"&TEXT(OU5,"00") -> ACT_PTN.upd101 | OY7: o | OZ7: =UPPER(OU6)&".chk"&TEXT(OY5,"00") -> ACT_PTN.chk102 | PA7: o | PB7: =UPPER(OU6)&".upd"&TEXT(OY5,"00") -> ACT_PTN.upd102 | PC7: o | PD7: =UPPER(PC6)&".chk"&TEXT(PC5,"00") -> GP_ALC.chk103 | PE7: o | PF7: =UPPER(PC6)&".upd"&TEXT(PC5,"00") -> GP_ALC.upd103 | PG7: o | PH7: =UPPER(PC6)&".chk"&TEXT(PG5,"00") -> GP_ALC.chk104 | PI7: o | PJ7: =UPPER(PC6)&".upd"&TEXT(PG5,"00") -> GP_ALC.upd104 | PK7: o | PL7: =UPPER(PK6)&".chk"&TEXT(PK5,"00") -> CALC_CTG.chk105 | PM7: o | PN7: =UPPER(PK6)&".upd"&TEXT(PK5,"00") -> CALC_CTG.upd105 | PO7: o | PP7: =UPPER(PK6)&".chk"&TEXT(PO5,"00") -> CALC_CTG.chk106 | PQ7: o | PR7: =UPPER(PK6)&".upd"&TEXT(PO5,"00") -> CALC_CTG.upd106 | PS7: o | PT7: =UPPER(PS6)&".chk"&TEXT(PS5,"00") -> RPT_PTN.chk107 | PU7: o | PV7: =UPPER(PS6)&".upd"&TEXT(PS5,"00") -> RPT_PTN.upd107 | PW7: o | PX7: =UPPER(PS6)&".chk"&TEXT(PW5,"00") -> RPT_PTN.chk108 | PY7: o | PZ7: =UPPER(PS6)&".upd"&TEXT(PW5,"00") -> RPT_PTN.upd108 | QA7: o | QB7: =UPPER(QA6)&".chk"&TEXT(QA5,"00") -> COST_MENU.chk109 | QC7: o | QD7: =UPPER(QA6)&".upd"&TEXT(QA5,"00") -> COST_MENU.upd109 | QE7: o | QF7: =UPPER(QA6)&".chk"&TEXT(QE5,"00") -> COST_MENU.chk110 | QG7: o | QH7: =UPPER(QA6)&".upd"&TEXT(QE5,"00") -> COST_MENU.upd110 | QI7: o | QJ7: =UPPER(QI6)&".chk"&TEXT(QI5,"00") -> SITE_CO.chk111 | QK7: o | QL7: =UPPER(QI6)&".upd"&TEXT(QI5,"00") -> SITE_CO.upd111 | QM7: o | QN7: =UPPER(QI6)&".chk"&TEXT(QM5,"00") -> SITE_CO.chk112 | QO7: o | QP7: =UPPER(QI6)&".upd"&TEXT(QM5,"00") -> SITE_CO.upd112
A8: # | D8: ブロック名 Block Name | E8: 型 Type | G8: super/share | H8: 対象ブロック名 Target Block Name | K8: TargetName | L8: ="OPE.MA."&L6&"."&SUBSTITUTE(K6,"_","")&"_UpdChk01" -> OPE.MA.MABCL0031.Da_UpdChk01 | M8: TargetName | N8: ="OPE.MA."&L6&"."&SUBSTITUTE(K6,"_","")&"_Upd01" -> OPE.MA.MABCL0031.Da_Upd01 | O8: TargetName | P8: ="OPE.MA."&L6&"."&SUBSTITUTE(K6,"_","")&"Lcl_UpdChk01" -> OPE.MA.MABCL0031.DaLcl_UpdChk01 | Q8: TargetName | R8: ="OPE.MA."&L6&"."&SUBSTITUTE(K6,"_","")&"Lcl_Upd01" -> OPE.MA.MABCL0031.DaLcl_Upd01 | S8: TargetName | T8: ="OPE.MA."&T6&"."&SUBSTITUTE(S6,"_","")&"_UpdChk01" -> OPE.MA.MABCL0031.DptBase_UpdChk01 | U8: TargetName | V8: ="OPE.MA."&T6&"."&SUBSTITUTE(S6,"_","")&"_Upd01" -> OPE.MA.MABCL0031.DptBase_Upd01 | W8: TargetName | X8: ="OPE.MA."&T6&"."&SUBSTITUTE(S6,"_","")&"Lcl_UpdChk01" -> OPE.MA.MABCL0031.DptBaseLcl_UpdChk01 | Y8: TargetName | Z8: ="OPE.MA."&T6&"."&SUBSTITUTE(S6,"_","")&"Lcl_Upd01" -> OPE.MA.MABCL0031.DptBaseLcl_Upd01 | AA8: TargetName | AB8: ="OPE.MA."&AB6&"."&SUBSTITUTE(AA6,"_","")&"_UpdChk01" -> OPE.MA.MABCL0031.DptLvl_UpdChk01 | AC8: TargetName | AD8: ="OPE.MA."&AB6&"."&SUBSTITUTE(AA6,"_","")&"_Upd01" -> OPE.MA.MABCL0031.DptLvl_Upd01 | AE8: TargetName | AF8: ="OPE.MA."&AB6&"."&SUBSTITUTE(AA6,"_","")&"Lcl_UpdChk01" -> OPE.MA.MABCL0031.DptLvlLcl_UpdChk01 | AG8: TargetName | AH8: ="OPE.MA."&AB6&"."&SUBSTITUTE(AA6,"_","")&"Lcl_Upd01" -> OPE.MA.MABCL0031.DptLvlLcl_Upd01 | AI8: TargetName | AJ8: ="OPE.MA."&AJ6&"."&SUBSTITUTE(AI6,"_","")&"_UpdChk01" -> OPE.MA.MABCL0031.AprvRole_UpdChk01 | AK8: TargetName | AL8: ="OPE.MA."&AJ6&"."&SUBSTITUTE(AI6,"_","")&"_Upd01" -> OPE.MA.MABCL0031.AprvRole_Upd01 | AM8: TargetName | AN8: ="OPE.MA."&AJ6&"."&SUBSTITUTE(AI6,"_","")&"Lcl_UpdChk01" -> OPE.MA.MABCL0031.AprvRoleLcl_UpdChk01 | AO8: TargetName | AP8: ="OPE.MA."&AJ6&"."&SUBSTITUTE(AI6,"_","")&"Lcl_Upd01" -> OPE.MA.MABCL0031.AprvRoleLcl_Upd01 | AQ8: TargetName | AR8: ="OPE.MA."&AR6&"."&SUBSTITUTE(AQ6,"_","")&"_UpdChk01" -> OPE.MA.MABCL0031.Cntry_UpdChk01 | AS8: TargetName | AT8: ="OPE.MA."&AR6&"."&SUBSTITUTE(AQ6,"_","")&"_Upd01" -> OPE.MA.MABCL0031.Cntry_Upd01 | AU8: TargetName | AV8: ="OPE.MA."&AR6&"."&SUBSTITUTE(AQ6,"_","")&"Lcl_UpdChk01" -> OPE.MA.MABCL0031.CntryLcl_UpdChk01 | AW8: TargetName | AX8: ="OPE.MA."&AR6&"."&SUBSTITUTE(AQ6,"_","")&"Lcl_Upd01" -> OPE.MA.MABCL0031.CntryLcl_Upd01 | AY8: TargetName | AZ8: ="OPE.MA."&AZ6&"."&SUBSTITUTE(AY6,"_","")&"_UpdChk01" -> OPE.MA.MABCL0031.Area_UpdChk01 | BA8: TargetName | BB8: ="OPE.MA."&AZ6&"."&SUBSTITUTE(AY6,"_","")&"_Upd01" -> OPE.MA.MABCL0031.Area_Upd01 | BC8: TargetName | BD8: ="OPE.MA."&AZ6&"."&SUBSTITUTE(AY6,"_","")&"Lcl_UpdChk01" -> OPE.MA.MABCL0031.AreaLcl_UpdChk01 | BE8: TargetName | BF8: ="OPE.MA."&AZ6&"."&SUBSTITUTE(AY6,"_","")&"Lcl_Upd01" -> OPE.MA.MABCL0031.AreaLcl_Upd01 | BG8: TargetName | BH8: ="OPE.MA."&BH6&"."&SUBSTITUTE(BG6,"_","")&"_UpdChk01" -> OPE.MA.MABCL0031.Cur_UpdChk01 | BI8: TargetName | BJ8: ="OPE.MA."&BH6&"."&SUBSTITUTE(BG6,"_","")&"_Upd01" -> OPE.MA.MABCL0031.Cur_Upd01 | BK8: TargetName | BL8: ="OPE.MA."&BH6&"."&SUBSTITUTE(BG6,"_","")&"Lcl_UpdChk01" -> OPE.MA.MABCL0031.CurLcl_UpdChk01 | BM8: TargetName | BN8: ="OPE.MA."&BH6&"."&SUBSTITUTE(BG6,"_","")&"Lcl_Upd01" -> OPE.MA.MABCL0031.CurLcl_Upd01 | BO8: TargetName | BP8: ="OPE.MA."&BP6&"."&SUBSTITUTE(BO6,"_","")&"_UpdChk01" -> OPE.MA.MABCL0031.Unit_UpdChk01 | BQ8: TargetName | BR8: ="OPE.MA."&BP6&"."&SUBSTITUTE(BO6,"_","")&"_Upd01" -> OPE.MA.MABCL0031.Unit_Upd01 | BS8: TargetName | BT8: ="OPE.MA."&BP6&"."&SUBSTITUTE(BO6,"_","")&"Lcl_UpdChk01" -> OPE.MA.MABCL0031.UnitLcl_UpdChk01 | BU8: TargetName | BV8: ="OPE.MA."&BP6&"."&SUBSTITUTE(BO6,"_","")&"Lcl_Upd01" -> OPE.MA.MABCL0031.UnitLcl_Upd01 | BW8: TargetName | BX8: ="OPE.MA."&BX6&"."&SUBSTITUTE(BW6,"_","")&"_UpdChk01" -> OPE.MA.MABCL0031.Bank_UpdChk01 | BY8: TargetName | BZ8: ="OPE.MA."&BX6&"."&SUBSTITUTE(BW6,"_","")&"_Upd01" -> OPE.MA.MABCL0031.Bank_Upd01 | CA8: TargetName | CB8: ="OPE.MA."&BX6&"."&SUBSTITUTE(BW6,"_","")&"Lcl_UpdChk01" -> OPE.MA.MABCL0031.BankLcl_UpdChk01 | CC8: TargetName | CD8: ="OPE.MA."&BX6&"."&SUBSTITUTE(BW6,"_","")&"Lcl_Upd01" -> OPE.MA.MABCL0031.BankLcl_Upd01 | CE8: TargetName | CF8: ="OPE.MA."&CF6&"."&SUBSTITUTE(CE6,"_","")&"_UpdChk01" -> OPE.MA.MABCL0031.BankBranch_UpdChk01 | CG8: TargetName | CH8: ="OPE.MA."&CF6&"."&SUBSTITUTE(CE6,"_","")&"_Upd01" -> OPE.MA.MABCL0031.BankBranch_Upd01 | CI8: TargetName | CJ8: ="OPE.MA."&CF6&"."&SUBSTITUTE(CE6,"_","")&"Lcl_UpdChk01" -> OPE.MA.MABCL0031.BankBranchLcl_UpdChk01 | CK8: TargetName | CL8: ="OPE.MA."&CF6&"."&SUBSTITUTE(CE6,"_","")&"Lcl_Upd01" -> OPE.MA.MABCL0031.BankBranchLcl_Upd01 | CM8: TargetName | CN8: ="OPE.MA."&CN6&"."&SUBSTITUTE(CM6,"_","")&"_UpdChk01" -> OPE.MA.MABCL0032.BankAc_UpdChk01 | CO8: TargetName | CP8: ="OPE.MA."&CN6&"."&SUBSTITUTE(CM6,"_","")&"_Upd01" -> OPE.MA.MABCL0032.BankAc_Upd01 | CQ8: TargetName | CR8: ="OPE.MA."&CN6&"."&SUBSTITUTE(CM6,"_","")&"Lcl_UpdChk01" -> OPE.MA.MABCL0032.BankAcLcl_UpdChk01 | CS8: TargetName | CT8: ="OPE.MA."&CN6&"."&SUBSTITUTE(CM6,"_","")&"Lcl_Upd01" -> OPE.MA.MABCL0032.BankAcLcl_Upd01 | CU8: TargetName | CV8: ="OPE.MA."&CV6&"."&SUBSTITUTE(CU6,"_","")&"_UpdChk01" -> OPE.MA.MABCL0032.Xrate_UpdChk01 | CW8: TargetName | CX8: ="OPE.MA."&CV6&"."&SUBSTITUTE(CU6,"_","")&"_Upd01" -> OPE.MA.MABCL0032.Xrate_Upd01 | CY8: TargetName | CZ8: ="OPE.MA."&CV6&"."&SUBSTITUTE(CU6,"_","")&"Lcl_UpdChk01" -> OPE.MA.MABCL0032.XrateLcl_UpdChk01 | DA8: TargetName | DB8: ="OPE.MA."&CV6&"."&SUBSTITUTE(CU6,"_","")&"Lcl_Upd01" -> OPE.MA.MABCL0032.XrateLcl_Upd01 | DC8: TargetName | DD8: ="OPE.MA."&DD6&"."&SUBSTITUTE(DC6,"_","")&"_UpdChk01" -> OPE.MA.MABCL0032.CalBase_UpdChk01 | DE8: TargetName | DF8: ="OPE.MA."&DD6&"."&SUBSTITUTE(DC6,"_","")&"_Upd01" -> OPE.MA.MABCL0032.CalBase_Upd01 | DG8: TargetName | DH8: ="OPE.MA."&DD6&"."&SUBSTITUTE(DC6,"_","")&"Lcl_UpdChk01" -> OPE.MA.MABCL0032.CalBaseLcl_UpdChk01 | DI8: TargetName | DJ8: ="OPE.MA."&DD6&"."&SUBSTITUTE(DC6,"_","")&"Lcl_Upd01" -> OPE.MA.MABCL0032.CalBaseLcl_Upd01 | DK8: TargetName | DL8: ="OPE.MA."&DL6&"."&SUBSTITUTE(DK6,"_","")&"_UpdChk01" -> OPE.MA.MABCL0032.ItmJnl_UpdChk01 | DM8: TargetName | DN8: ="OPE.MA."&DL6&"."&SUBSTITUTE(DK6,"_","")&"_Upd01" -> OPE.MA.MABCL0032.ItmJnl_Upd01 | DO8: TargetName | DP8: ="OPE.MA."&DL6&"."&SUBSTITUTE(DK6,"_","")&"Lcl_UpdChk01" -> OPE.MA.MABCL0032.ItmJnlLcl_UpdChk01 | DQ8: TargetName | DR8: ="OPE.MA."&DL6&"."&SUBSTITUTE(DK6,"_","")&"Lcl_Upd01" -> OPE.MA.MABCL0032.ItmJnlLcl_Upd01 | DS8: TargetName | DT8: ="OPE.MA."&DT6&"."&SUBSTITUTE(DS6,"_","")&"_UpdChk01" -> OPE.MA.MABCL0032.AcItmGrp_UpdChk01 | DU8: TargetName | DV8: ="OPE.MA."&DT6&"."&SUBSTITUTE(DS6,"_","")&"_Upd01" -> OPE.MA.MABCL0032.AcItmGrp_Upd01 | DW8: TargetName | DX8: ="OPE.MA."&DT6&"."&SUBSTITUTE(DS6,"_","")&"Lcl_UpdChk01" -> OPE.MA.MABCL0032.AcItmGrpLcl_UpdChk01 | DY8: TargetName | DZ8: ="OPE.MA."&DT6&"."&SUBSTITUTE(DS6,"_","")&"Lcl_Upd01" -> OPE.MA.MABCL0032.AcItmGrpLcl_Upd01 | EA8: TargetName | EB8: ="OPE.MA."&EB6&"."&SUBSTITUTE(EA6,"_","")&"_UpdChk01" -> OPE.MA.MABCL0032.AcRsn_UpdChk01 | EC8: TargetName | ED8: ="OPE.MA."&EB6&"."&SUBSTITUTE(EA6,"_","")&"_Upd01" -> OPE.MA.MABCL0032.AcRsn_Upd01 | EE8: TargetName | EF8: ="OPE.MA."&EB6&"."&SUBSTITUTE(EA6,"_","")&"Lcl_UpdChk01" -> OPE.MA.MABCL0032.AcRsnLcl_UpdChk01 | EG8: TargetName | EH8: ="OPE.MA."&EB6&"."&SUBSTITUTE(EA6,"_","")&"Lcl_Upd01" -> OPE.MA.MABCL0032.AcRsnLcl_Upd01 | EI8: TargetName | EJ8: ="OPE.MA."&EJ6&"."&SUBSTITUTE(EI6,"_","")&"_UpdChk01" -> OPE.MA.MABCL0032.Site_UpdChk01 | EK8: TargetName | EL8: ="OPE.MA."&EJ6&"."&SUBSTITUTE(EI6,"_","")&"_Upd01" -> OPE.MA.MABCL0032.Site_Upd01 | EM8: TargetName | EN8: ="OPE.MA."&EJ6&"."&SUBSTITUTE(EI6,"_","")&"Lcl_UpdChk01" -> OPE.MA.MABCL0032.SiteLcl_UpdChk01 | EO8: TargetName | EP8: ="OPE.MA."&EJ6&"."&SUBSTITUTE(EI6,"_","")&"Lcl_Upd01" -> OPE.MA.MABCL0032.SiteLcl_Upd01 | EQ8: TargetName | ER8: ="OPE.MA."&ER6&"."&SUBSTITUTE(EQ6,"_","")&"_UpdChk01" -> OPE.MA.MABCL0032.LocGrp_UpdChk01 | ES8: TargetName | ET8: ="OPE.MA."&ER6&"."&SUBSTITUTE(EQ6,"_","")&"_Upd01" -> OPE.MA.MABCL0032.LocGrp_Upd01 | EU8: TargetName | EV8: ="OPE.MA."&ER6&"."&SUBSTITUTE(EQ6,"_","")&"Lcl_UpdChk01" -> OPE.MA.MABCL0032.LocGrpLcl_UpdChk01 | EW8: TargetName | EX8: ="OPE.MA."&ER6&"."&SUBSTITUTE(EQ6,"_","")&"Lcl_Upd01" -> OPE.MA.MABCL0032.LocGrpLcl_Upd01 | EY8: TargetName | EZ8: ="OPE.MA."&EZ6&"."&SUBSTITUTE(EY6,"_","")&"_UpdChk01" -> OPE.MA.MABCL0032.LgGrp_UpdChk01 | FA8: TargetName | FB8: ="OPE.MA."&EZ6&"."&SUBSTITUTE(EY6,"_","")&"_Upd01" -> OPE.MA.MABCL0032.LgGrp_Upd01 | FC8: TargetName | FD8: ="OPE.MA."&EZ6&"."&SUBSTITUTE(EY6,"_","")&"Lcl_UpdChk01" -> OPE.MA.MABCL0032.LgGrpLcl_UpdChk01 | FE8: TargetName | FF8: ="OPE.MA."&EZ6&"."&SUBSTITUTE(EY6,"_","")&"Lcl_Upd01" -> OPE.MA.MABCL0032.LgGrpLcl_Upd01 | FG8: TargetName | FH8: ="OPE.MA."&FH6&"."&SUBSTITUTE(FG6,"_","")&"_UpdChk01" -> OPE.MA.MABCL0032.AllocGrp_UpdChk01 | FI8: TargetName | FJ8: ="OPE.MA."&FH6&"."&SUBSTITUTE(FG6,"_","")&"_Upd01" -> OPE.MA.MABCL0032.AllocGrp_Upd01 | FK8: TargetName | FL8: ="OPE.MA."&FH6&"."&SUBSTITUTE(FG6,"_","")&"Lcl_UpdChk01" -> OPE.MA.MABCL0032.AllocGrpLcl_UpdChk01 | FM8: TargetName | FN8: ="OPE.MA."&FH6&"."&SUBSTITUTE(FG6,"_","")&"Lcl_Upd01" -> OPE.MA.MABCL0032.AllocGrpLcl_Upd01 | FO8: TargetName | FP8: ="OPE.MA."&FP6&"."&SUBSTITUTE(FO6,"_","")&"_UpdChk01" -> OPE.MA.MABCL0033.Wg_UpdChk01 | FQ8: TargetName | FR8: ="OPE.MA."&FP6&"."&SUBSTITUTE(FO6,"_","")&"_Upd01" -> OPE.MA.MABCL0033.Wg_Upd01 | FS8: TargetName | FT8: ="OPE.MA."&FP6&"."&SUBSTITUTE(FO6,"_","")&"Lcl_UpdChk01" -> OPE.MA.MABCL0033.WgLcl_UpdChk01 | FU8: TargetName | FV8: ="OPE.MA."&FP6&"."&SUBSTITUTE(FO6,"_","")&"Lcl_Upd01" -> OPE.MA.MABCL0033.WgLcl_Upd01 | FW8: TargetName | FX8: ="OPE.MA."&FX6&"."&SUBSTITUTE(FW6,"_","")&"_UpdChk01" -> OPE.MA.MABCL0033.Oper_UpdChk01 | FY8: TargetName | FZ8: ="OPE.MA."&FX6&"."&SUBSTITUTE(FW6,"_","")&"_Upd01" -> OPE.MA.MABCL0033.Oper_Upd01 | GA8: TargetName | GB8: ="OPE.MA."&FX6&"."&SUBSTITUTE(FW6,"_","")&"Lcl_UpdChk01" -> OPE.MA.MABCL0033.OperLcl_UpdChk01 | GC8: TargetName | GD8: ="OPE.MA."&FX6&"."&SUBSTITUTE(FW6,"_","")&"Lcl_Upd01" -> OPE.MA.MABCL0033.OperLcl_Upd01 | GE8: TargetName | GF8: ="OPE.MA."&GF6&"."&SUBSTITUTE(GE6,"_","")&"_UpdChk01" -> OPE.MA.MABCL0033.WkCost_UpdChk01 | GG8: TargetName | GH8: ="OPE.MA."&GF6&"."&SUBSTITUTE(GE6,"_","")&"_Upd01" -> OPE.MA.MABCL0033.WkCost_Upd01 | GI8: TargetName | GJ8: ="OPE.MA."&GF6&"."&SUBSTITUTE(GE6,"_","")&"Lcl_UpdChk01" -> OPE.MA.MABCL0033.WkCostLcl_UpdChk01 | GK8: TargetName | GL8: ="OPE.MA."&GF6&"."&SUBSTITUTE(GE6,"_","")&"Lcl_Upd01" -> OPE.MA.MABCL0033.WkCostLcl_Upd01 | GM8: TargetName | GN8: ="OPE.MA."&GN6&"."&SUBSTITUTE(GM6,"_","")&"_UpdChk01" -> OPE.MA.MABCL0033.WkRsn_UpdChk01 | GO8: TargetName | GP8: ="OPE.MA."&GN6&"."&SUBSTITUTE(GM6,"_","")&"_Upd01" -> OPE.MA.MABCL0033.WkRsn_Upd01 | GQ8: TargetName | GR8: ="OPE.MA."&GN6&"."&SUBSTITUTE(GM6,"_","")&"Lcl_UpdChk01" -> OPE.MA.MABCL0033.WkRsnLcl_UpdChk01 | GS8: TargetName | GT8: ="OPE.MA."&GN6&"."&SUBSTITUTE(GM6,"_","")&"Lcl_Upd01" -> OPE.MA.MABCL0033.WkRsnLcl_Upd01 | GU8: TargetName | GV8: ="OPE.MA."&GV6&"."&SUBSTITUTE(GU6,"_","")&"_UpdChk01" -> OPE.MA.MABCL0033.SlsUpriGrp_UpdChk01 | GW8: TargetName | GX8: ="OPE.MA."&GV6&"."&SUBSTITUTE(GU6,"_","")&"_Upd01" -> OPE.MA.MABCL0033.SlsUpriGrp_Upd01 | GY8: TargetName | GZ8: ="OPE.MA."&GV6&"."&SUBSTITUTE(GU6,"_","")&"Lcl_UpdChk01" -> OPE.MA.MABCL0033.SlsUpriGrpLcl_UpdChk01 | HA8: TargetName | HB8: ="OPE.MA."&GV6&"."&SUBSTITUTE(GU6,"_","")&"Lcl_Upd01" -> OPE.MA.MABCL0033.SlsUpriGrpLcl_Upd01 | HC8: TargetName | HD8: ="OPE.MA."&HD6&"."&SUBSTITUTE(HC6,"_","")&"_UpdChk01" -> OPE.MA.MABCL0033.SlsUpriRank_UpdChk01 | HE8: TargetName | HF8: ="OPE.MA."&HD6&"."&SUBSTITUTE(HC6,"_","")&"_Upd01" -> OPE.MA.MABCL0033.SlsUpriRank_Upd01 | HG8: TargetName | HH8: ="OPE.MA."&HD6&"."&SUBSTITUTE(HC6,"_","")&"Lcl_UpdChk01" -> OPE.MA.MABCL0033.SlsUpriRankLcl_UpdChk01 | HI8: TargetName | HJ8: ="OPE.MA."&HD6&"."&SUBSTITUTE(HC6,"_","")&"Lcl_Upd01" -> OPE.MA.MABCL0033.SlsUpriRankLcl_Upd01 | HK8: TargetName | HL8: ="OPE.MA."&HL6&"."&SUBSTITUTE(HK6,"_","")&"_UpdChk01" -> OPE.MA.MABCL0033.SetoffGrp_UpdChk01 | HM8: TargetName | HN8: ="OPE.MA."&HL6&"."&SUBSTITUTE(HK6,"_","")&"_Upd01" -> OPE.MA.MABCL0033.SetoffGrp_Upd01 | HO8: TargetName | HP8: ="OPE.MA."&HL6&"."&SUBSTITUTE(HK6,"_","")&"Lcl_UpdChk01" -> OPE.MA.MABCL0033.SetoffGrpLcl_UpdChk01 | HQ8: TargetName | HR8: ="OPE.MA."&HL6&"."&SUBSTITUTE(HK6,"_","")&"Lcl_Upd01" -> OPE.MA.MABCL0033.SetoffGrpLcl_Upd01 | HS8: TargetName | HT8: ="OPE.MA."&HT6&"."&SUBSTITUTE(HS6,"_","")&"_UpdChk01" -> OPE.MA.MABCL0033.ShipValid_UpdChk01 | HU8: TargetName | HV8: ="OPE.MA."&HT6&"."&SUBSTITUTE(HS6,"_","")&"_Upd01" -> OPE.MA.MABCL0033.ShipValid_Upd01 | HW8: TargetName | HX8: ="OPE.MA."&HT6&"."&SUBSTITUTE(HS6,"_","")&"Lcl_UpdChk01" -> OPE.MA.MABCL0033.ShipValidLcl_UpdChk01 | HY8: TargetName | HZ8: ="OPE.MA."&HT6&"."&SUBSTITUTE(HS6,"_","")&"Lcl_Upd01" -> OPE.MA.MABCL0033.ShipValidLcl_Upd01 | IA8: TargetName | IB8: ="OPE.MA."&IB6&"."&SUBSTITUTE(IA6,"_","")&"_UpdChk01" -> OPE.MA.MABCL0033.ItmShipGrp_UpdChk01 | IC8: TargetName | ID8: ="OPE.MA."&IB6&"."&SUBSTITUTE(IA6,"_","")&"_Upd01" -> OPE.MA.MABCL0033.ItmShipGrp_Upd01 | IE8: TargetName | IF8: ="OPE.MA."&IB6&"."&SUBSTITUTE(IA6,"_","")&"Lcl_UpdChk01" -> OPE.MA.MABCL0033.ItmShipGrpLcl_UpdChk01 | IG8: TargetName | IH8: ="OPE.MA."&IB6&"."&SUBSTITUTE(IA6,"_","")&"Lcl_Upd01" -> OPE.MA.MABCL0033.ItmShipGrpLcl_Upd01 | II8: TargetName | IJ8: ="OPE.MA."&IJ6&"."&SUBSTITUTE(II6,"_","")&"_UpdChk01" -> OPE.MA.MABCL0033.Trnspt_UpdChk01 | IK8: TargetName | IL8: ="OPE.MA."&IJ6&"."&SUBSTITUTE(II6,"_","")&"_Upd01" -> OPE.MA.MABCL0033.Trnspt_Upd01 | IM8: TargetName | IN8: ="OPE.MA."&IJ6&"."&SUBSTITUTE(II6,"_","")&"Lcl_UpdChk01" -> OPE.MA.MABCL0033.TrnsptLcl_UpdChk01 | IO8: TargetName | IP8: ="OPE.MA."&IJ6&"."&SUBSTITUTE(II6,"_","")&"Lcl_Upd01" -> OPE.MA.MABCL0033.TrnsptLcl_Upd01 | IQ8: TargetName | IR8: ="OPE.MA."&IR6&"."&SUBSTITUTE(IQ6,"_","")&"_UpdChk01" -> OPE.MA.MABCL0034.ExCntnr_UpdChk01 | IS8: TargetName | IT8: ="OPE.MA."&IR6&"."&SUBSTITUTE(IQ6,"_","")&"_Upd01" -> OPE.MA.MABCL0034.ExCntnr_Upd01 | IU8: TargetName | IV8: ="OPE.MA."&IR6&"."&SUBSTITUTE(IQ6,"_","")&"Lcl_UpdChk01" -> OPE.MA.MABCL0034.ExCntnrLcl_UpdChk01 | IW8: TargetName | IX8: ="OPE.MA."&IR6&"."&SUBSTITUTE(IQ6,"_","")&"Lcl_Upd01" -> OPE.MA.MABCL0034.ExCntnrLcl_Upd01 | IY8: TargetName | IZ8: ="OPE.MA."&IZ6&"."&SUBSTITUTE(IY6,"_","")&"_UpdChk01" -> OPE.MA.MABCL0034.EximPort_UpdChk01 | JA8: TargetName | JB8: ="OPE.MA."&IZ6&"."&SUBSTITUTE(IY6,"_","")&"_Upd01" -> OPE.MA.MABCL0034.EximPort_Upd01 | JC8: TargetName | JD8: ="OPE.MA."&IZ6&"."&SUBSTITUTE(IY6,"_","")&"Lcl_UpdChk01" -> OPE.MA.MABCL0034.EximPortLcl_UpdChk01 | JE8: TargetName | JF8: ="OPE.MA."&IZ6&"."&SUBSTITUTE(IY6,"_","")&"Lcl_Upd01" -> OPE.MA.MABCL0034.EximPortLcl_Upd01 | JG8: TargetName | JH8: ="OPE.MA."&JH6&"."&SUBSTITUTE(JG6,"_","")&"_UpdChk01" -> OPE.MA.MABCL0034.StkGd_UpdChk01 | JI8: TargetName | JJ8: ="OPE.MA."&JH6&"."&SUBSTITUTE(JG6,"_","")&"_Upd01" -> OPE.MA.MABCL0034.StkGd_Upd01 | JK8: TargetName | JL8: ="OPE.MA."&JH6&"."&SUBSTITUTE(JG6,"_","")&"Lcl_UpdChk01" -> OPE.MA.MABCL0034.StkGdLcl_UpdChk01 | JM8: TargetName | JN8: ="OPE.MA."&JH6&"."&SUBSTITUTE(JG6,"_","")&"Lcl_Upd01" -> OPE.MA.MABCL0034.StkGdLcl_Upd01 | JO8: TargetName | JP8: ="OPE.MA."&JP6&"."&SUBSTITUTE(JO6,"_","")&"_UpdChk01" -> OPE.MA.MABCL0034.Trd_UpdChk01 | JQ8: TargetName | JR8: ="OPE.MA."&JP6&"."&SUBSTITUTE(JO6,"_","")&"_Upd01" -> OPE.MA.MABCL0034.Trd_Upd01 | JS8: TargetName | JT8: ="OPE.MA."&JP6&"."&SUBSTITUTE(JO6,"_","")&"Lcl_UpdChk01" -> OPE.MA.MABCL0034.TrdLcl_UpdChk01 | JU8: TargetName | JV8: ="OPE.MA."&JP6&"."&SUBSTITUTE(JO6,"_","")&"Lcl_Upd01" -> OPE.MA.MABCL0034.TrdLcl_Upd01 | JW8: TargetName | JX8: ="OPE.MA."&JX6&"."&SUBSTITUTE(JW6,"_","")&"_UpdChk01" -> OPE.MA.MABCL0034.SlipForm_UpdChk01 | JY8: TargetName | JZ8: ="OPE.MA."&JX6&"."&SUBSTITUTE(JW6,"_","")&"_Upd01" -> OPE.MA.MABCL0034.SlipForm_Upd01 | KA8: TargetName | KB8: ="OPE.MA."&JX6&"."&SUBSTITUTE(JW6,"_","")&"Lcl_UpdChk01" -> OPE.MA.MABCL0034.SlipFormLcl_UpdChk01 | KC8: TargetName | KD8: ="OPE.MA."&JX6&"."&SUBSTITUTE(JW6,"_","")&"Lcl_Upd01" -> OPE.MA.MABCL0034.SlipFormLcl_Upd01 | KE8: TargetName | KF8: ="OPE.MA."&KF6&"."&SUBSTITUTE(KE6,"_","")&"_UpdChk01" -> OPE.MA.MABCL0034.PfGrp_UpdChk01 | KG8: TargetName | KH8: ="OPE.MA."&KF6&"."&SUBSTITUTE(KE6,"_","")&"_Upd01" -> OPE.MA.MABCL0034.PfGrp_Upd01 | KI8: TargetName | KJ8: ="OPE.MA."&KF6&"."&SUBSTITUTE(KE6,"_","")&"Lcl_UpdChk01" -> OPE.MA.MABCL0034.PfGrpLcl_UpdChk01 | KK8: TargetName | KL8: ="OPE.MA."&KF6&"."&SUBSTITUTE(KE6,"_","")&"Lcl_Upd01" -> OPE.MA.MABCL0034.PfGrpLcl_Upd01 | KM8: TargetName | KN8: ="OPE.MA."&KN6&"."&SUBSTITUTE(KM6,"_","")&"_UpdChk01" -> OPE.MA.MABCL0034.ItmSpecGrp_UpdChk01 | KO8: TargetName | KP8: ="OPE.MA."&KN6&"."&SUBSTITUTE(KM6,"_","")&"_Upd01" -> OPE.MA.MABCL0034.ItmSpecGrp_Upd01 | KQ8: TargetName | KR8: ="OPE.MA."&KN6&"."&SUBSTITUTE(KM6,"_","")&"Lcl_UpdChk01" -> OPE.MA.MABCL0034.ItmSpecGrpLcl_UpdChk01 | KS8: TargetName | KT8: ="OPE.MA."&KN6&"."&SUBSTITUTE(KM6,"_","")&"Lcl_Upd01" -> OPE.MA.MABCL0034.ItmSpecGrpLcl_Upd01 | KU8: TargetName | KV8: ="OPE.MA."&KV6&"."&SUBSTITUTE(KU6,"_","")&"_UpdChk01" -> OPE.MA.MABCL0034.ItmCompGrp_UpdChk01 | KW8: TargetName | KX8: ="OPE.MA."&KV6&"."&SUBSTITUTE(KU6,"_","")&"_Upd01" -> OPE.MA.MABCL0034.ItmCompGrp_Upd01 | KY8: TargetName | KZ8: ="OPE.MA."&KV6&"."&SUBSTITUTE(KU6,"_","")&"Lcl_UpdChk01" -> OPE.MA.MABCL0034.ItmCompGrpLcl_UpdChk01 | LA8: TargetName | LB8: ="OPE.MA."&KV6&"."&SUBSTITUTE(KU6,"_","")&"Lcl_Upd01" -> OPE.MA.MABCL0034.ItmCompGrpLcl_Upd01 | LC8: TargetName | LD8: ="OPE.MA."&LD6&"."&SUBSTITUTE(LC6,"_","")&"_UpdChk01" -> OPE.MA.MABCL0034.JnlAct_UpdChk01 | LE8: TargetName | LF8: ="OPE.MA."&LD6&"."&SUBSTITUTE(LC6,"_","")&"_Upd01" -> OPE.MA.MABCL0034.JnlAct_Upd01 | LG8: TargetName | LH8: ="OPE.MA."&LD6&"."&SUBSTITUTE(LC6,"_","")&"Lcl_UpdChk01" -> OPE.MA.MABCL0034.JnlActLcl_UpdChk01 | LI8: TargetName | LJ8: ="OPE.MA."&LD6&"."&SUBSTITUTE(LC6,"_","")&"Lcl_Upd01" -> OPE.MA.MABCL0034.JnlActLcl_Upd01 | LK8: TargetName | LL8: ="OPE.MA."&LL6&"."&SUBSTITUTE(LK6,"_","")&"_UpdChk01" -> OPE.MA.MABCL0034.JnlGrp_UpdChk01 | LM8: TargetName | LN8: ="OPE.MA."&LL6&"."&SUBSTITUTE(LK6,"_","")&"_Upd01" -> OPE.MA.MABCL0034.JnlGrp_Upd01 | LO8: TargetName | LP8: ="OPE.MA."&LL6&"."&SUBSTITUTE(LK6,"_","")&"Lcl_UpdChk01" -> OPE.MA.MABCL0034.JnlGrpLcl_UpdChk01 | LQ8: TargetName | LR8: ="OPE.MA."&LL6&"."&SUBSTITUTE(LK6,"_","")&"Lcl_Upd01" -> OPE.MA.MABCL0034.JnlGrpLcl_Upd01 | LS8: TargetName | LT8: ="OPE.MA."&LT6&"."&SUBSTITUTE(LS6,"_","")&"_UpdChk01" -> OPE.MA.MABCL0035.JnlPtnBase_UpdChk01 | LU8: TargetName | LV8: ="OPE.MA."&LT6&"."&SUBSTITUTE(LS6,"_","")&"_Upd01" -> OPE.MA.MABCL0035.JnlPtnBase_Upd01 | LW8: TargetName | LX8: ="OPE.MA."&LT6&"."&SUBSTITUTE(LS6,"_","")&"Lcl_UpdChk01" -> OPE.MA.MABCL0035.JnlPtnBaseLcl_UpdChk01 | LY8: TargetName | LZ8: ="OPE.MA."&LT6&"."&SUBSTITUTE(LS6,"_","")&"Lcl_Upd01" -> OPE.MA.MABCL0035.JnlPtnBaseLcl_Upd01 | MA8: TargetName | MB8: ="OPE.MA."&MB6&"."&SUBSTITUTE(MA6,"_","")&"_UpdChk01" -> OPE.MA.MABCL0035.AutoJnlKey_UpdChk01 | MC8: TargetName | MD8: ="OPE.MA."&MB6&"."&SUBSTITUTE(MA6,"_","")&"_Upd01" -> OPE.MA.MABCL0035.AutoJnlKey_Upd01 | ME8: TargetName | MF8: ="OPE.MA."&MB6&"."&SUBSTITUTE(MA6,"_","")&"Lcl_UpdChk01" -> OPE.MA.MABCL0035.AutoJnlKeyLcl_UpdChk01 | MG8: TargetName | MH8: ="OPE.MA."&MB6&"."&SUBSTITUTE(MA6,"_","")&"Lcl_Upd01" -> OPE.MA.MABCL0035.AutoJnlKeyLcl_Upd01 | MI8: TargetName | MJ8: ="OPE.MA."&MJ6&"."&SUBSTITUTE(MI6,"_","")&"_UpdChk01" -> OPE.MA.MABCL0035.InspPtn_UpdChk01 | MK8: TargetName | ML8: ="OPE.MA."&MJ6&"."&SUBSTITUTE(MI6,"_","")&"_Upd01" -> OPE.MA.MABCL0035.InspPtn_Upd01 | MM8: TargetName | MN8: ="OPE.MA."&MJ6&"."&SUBSTITUTE(MI6,"_","")&"Lcl_UpdChk01" -> OPE.MA.MABCL0035.InspPtnLcl_UpdChk01 | MO8: TargetName | MP8: ="OPE.MA."&MJ6&"."&SUBSTITUTE(MI6,"_","")&"Lcl_Upd01" -> OPE.MA.MABCL0035.InspPtnLcl_Upd01 | MQ8: TargetName | MR8: ="OPE.MA."&MR6&"."&SUBSTITUTE(MQ6,"_","")&"_UpdChk01" -> OPE.MA.MABCL0035.WkDay_UpdChk01 | MS8: TargetName | MT8: ="OPE.MA."&MR6&"."&SUBSTITUTE(MQ6,"_","")&"_Upd01" -> OPE.MA.MABCL0035.WkDay_Upd01 | MU8: TargetName | MV8: ="OPE.MA."&MR6&"."&SUBSTITUTE(MQ6,"_","")&"Lcl_UpdChk01" -> OPE.MA.MABCL0035.WkDayLcl_UpdChk01 | MW8: TargetName | MX8: ="OPE.MA."&MR6&"."&SUBSTITUTE(MQ6,"_","")&"Lcl_Upd01" -> OPE.MA.MABCL0035.WkDayLcl_Upd01 | MY8: TargetName | MZ8: ="OPE.MA."&MZ6&"."&SUBSTITUTE(MY6,"_","")&"_UpdChk01" -> OPE.MA.MABCL0035.ShipTerm_UpdChk01 | NA8: TargetName | NB8: ="OPE.MA."&MZ6&"."&SUBSTITUTE(MY6,"_","")&"_Upd01" -> OPE.MA.MABCL0035.ShipTerm_Upd01 | NC8: TargetName | ND8: ="OPE.MA."&MZ6&"."&SUBSTITUTE(MY6,"_","")&"Lcl_UpdChk01" -> OPE.MA.MABCL0035.ShipTermLcl_UpdChk01 | NE8: TargetName | NF8: ="OPE.MA."&MZ6&"."&SUBSTITUTE(MY6,"_","")&"Lcl_Upd01" -> OPE.MA.MABCL0035.ShipTermLcl_Upd01 | NG8: TargetName | NH8: ="OPE.MA."&NH6&"."&SUBSTITUTE(NG6,"_","")&"_UpdChk01" -> OPE.MA.MABCL0035.ShipWk_UpdChk01 | NI8: TargetName | NJ8: ="OPE.MA."&NH6&"."&SUBSTITUTE(NG6,"_","")&"_Upd01" -> OPE.MA.MABCL0035.ShipWk_Upd01 | NK8: TargetName | NL8: ="OPE.MA."&NH6&"."&SUBSTITUTE(NG6,"_","")&"Lcl_UpdChk01" -> OPE.MA.MABCL0035.ShipWkLcl_UpdChk01 | NM8: TargetName | NN8: ="OPE.MA."&NH6&"."&SUBSTITUTE(NG6,"_","")&"Lcl_Upd01" -> OPE.MA.MABCL0035.ShipWkLcl_Upd01 | NO8: TargetName | NP8: ="OPE.MA."&NP6&"."&SUBSTITUTE(NO6,"_","")&"_UpdChk01" -> OPE.MA.MABCL0035.Rsrc_UpdChk01 | NQ8: TargetName | NR8: ="OPE.MA."&NP6&"."&SUBSTITUTE(NO6,"_","")&"_Upd01" -> OPE.MA.MABCL0035.Rsrc_Upd01 | NS8: TargetName | NT8: ="OPE.MA."&NP6&"."&SUBSTITUTE(NO6,"_","")&"Lcl_UpdChk01" -> OPE.MA.MABCL0035.RsrcLcl_UpdChk01 | NU8: TargetName | NV8: ="OPE.MA."&NP6&"."&SUBSTITUTE(NO6,"_","")&"Lcl_Upd01" -> OPE.MA.MABCL0035.RsrcLcl_Upd01 | NW8: TargetName | NX8: ="OPE.MA."&NX6&"."&SUBSTITUTE(NW6,"_","")&"_UpdChk01" -> OPE.MA.MABCL0035.HsGrp_UpdChk01 | NY8: TargetName | NZ8: ="OPE.MA."&NX6&"."&SUBSTITUTE(NW6,"_","")&"_Upd01" -> OPE.MA.MABCL0035.HsGrp_Upd01 | OA8: TargetName | OB8: ="OPE.MA."&NX6&"."&SUBSTITUTE(NW6,"_","")&"Lcl_UpdChk01" -> OPE.MA.MABCL0035.HsGrpLcl_UpdChk01 | OC8: TargetName | OD8: ="OPE.MA."&NX6&"."&SUBSTITUTE(NW6,"_","")&"Lcl_Upd01" -> OPE.MA.MABCL0035.HsGrpLcl_Upd01 | OE8: TargetName | OF8: ="OPE.MA."&OF6&"."&SUBSTITUTE(OE6,"_","")&"_UpdChk01" -> OPE.MA.MABCL0035.AlcPtn_UpdChk01 | OG8: TargetName | OH8: ="OPE.MA."&OF6&"."&SUBSTITUTE(OE6,"_","")&"_Upd01" -> OPE.MA.MABCL0035.AlcPtn_Upd01 | OI8: TargetName | OJ8: ="OPE.MA."&OF6&"."&SUBSTITUTE(OE6,"_","")&"Lcl_UpdChk01" -> OPE.MA.MABCL0035.AlcPtnLcl_UpdChk01 | OK8: TargetName | OL8: ="OPE.MA."&OF6&"."&SUBSTITUTE(OE6,"_","")&"Lcl_Upd01" -> OPE.MA.MABCL0035.AlcPtnLcl_Upd01 | OM8: TargetName | ON8: ="OPE.MA."&ON6&"."&SUBSTITUTE(OM6,"_","")&"_UpdChk01" -> OPE.MA.MABCL0035.CtgGrp_UpdChk01 | OO8: TargetName | OP8: ="OPE.MA."&ON6&"."&SUBSTITUTE(OM6,"_","")&"_Upd01" -> OPE.MA.MABCL0035.CtgGrp_Upd01 | OQ8: TargetName | OR8: ="OPE.MA."&ON6&"."&SUBSTITUTE(OM6,"_","")&"Lcl_UpdChk01" -> OPE.MA.MABCL0035.CtgGrpLcl_UpdChk01 | OS8: TargetName | OT8: ="OPE.MA."&ON6&"."&SUBSTITUTE(OM6,"_","")&"Lcl_Upd01" -> OPE.MA.MABCL0035.CtgGrpLcl_Upd01 | OU8: TargetName | OV8: ="OPE.MA."&OV6&"."&SUBSTITUTE(OU6,"_","")&"_UpdChk01" -> OPE.MA.MABCL0035.ActPtn_UpdChk01 | OW8: TargetName | OX8: ="OPE.MA."&OV6&"."&SUBSTITUTE(OU6,"_","")&"_Upd01" -> OPE.MA.MABCL0035.ActPtn_Upd01 | OY8: TargetName | OZ8: ="OPE.MA."&OV6&"."&SUBSTITUTE(OU6,"_","")&"Lcl_UpdChk01" -> OPE.MA.MABCL0035.ActPtnLcl_UpdChk01 | PA8: TargetName | PB8: ="OPE.MA."&OV6&"."&SUBSTITUTE(OU6,"_","")&"Lcl_Upd01" -> OPE.MA.MABCL0035.ActPtnLcl_Upd01 | PC8: TargetName | PD8: ="OPE.MA."&PD6&"."&SUBSTITUTE(PC6,"_","")&"_UpdChk01" -> OPE.MA.MABCL0036.GpAlc_UpdChk01 | PE8: TargetName | PF8: ="OPE.MA."&PD6&"."&SUBSTITUTE(PC6,"_","")&"_Upd01" -> OPE.MA.MABCL0036.GpAlc_Upd01 | PG8: TargetName | PH8: ="OPE.MA."&PD6&"."&SUBSTITUTE(PC6,"_","")&"Lcl_UpdChk01" -> OPE.MA.MABCL0036.GpAlcLcl_UpdChk01 | PI8: TargetName | PJ8: ="OPE.MA."&PD6&"."&SUBSTITUTE(PC6,"_","")&"Lcl_Upd01" -> OPE.MA.MABCL0036.GpAlcLcl_Upd01 | PK8: TargetName | PL8: ="OPE.MA."&PL6&"."&SUBSTITUTE(PK6,"_","")&"_UpdChk01" -> OPE.MA.MABCL0036.CalcCtg_UpdChk01 | PM8: TargetName | PN8: ="OPE.MA."&PL6&"."&SUBSTITUTE(PK6,"_","")&"_Upd01" -> OPE.MA.MABCL0036.CalcCtg_Upd01 | PO8: TargetName | PP8: ="OPE.MA."&PL6&"."&SUBSTITUTE(PK6,"_","")&"Lcl_UpdChk01" -> OPE.MA.MABCL0036.CalcCtgLcl_UpdChk01 | PQ8: TargetName | PR8: ="OPE.MA."&PL6&"."&SUBSTITUTE(PK6,"_","")&"Lcl_Upd01" -> OPE.MA.MABCL0036.CalcCtgLcl_Upd01 | PS8: TargetName | PT8: ="OPE.MA."&PT6&"."&SUBSTITUTE(PS6,"_","")&"_UpdChk01" -> OPE.MA.MABCL0036.RptPtn_UpdChk01 | PU8: TargetName | PV8: ="OPE.MA."&PT6&"."&SUBSTITUTE(PS6,"_","")&"_Upd01" -> OPE.MA.MABCL0036.RptPtn_Upd01 | PW8: TargetName | PX8: ="OPE.MA."&PT6&"."&SUBSTITUTE(PS6,"_","")&"Lcl_UpdChk01" -> OPE.MA.MABCL0036.RptPtnLcl_UpdChk01 | PY8: TargetName | PZ8: ="OPE.MA."&PT6&"."&SUBSTITUTE(PS6,"_","")&"Lcl_Upd01" -> OPE.MA.MABCL0036.RptPtnLcl_Upd01 | QA8: TargetName | QB8: ="OPE.MA."&QB6&"."&SUBSTITUTE(QA6,"_","")&"_UpdChk01" -> OPE.MA.MABCL0036.CostMenu_UpdChk01 | QC8: TargetName | QD8: ="OPE.MA."&QB6&"."&SUBSTITUTE(QA6,"_","")&"_Upd01" -> OPE.MA.MABCL0036.CostMenu_Upd01 | QE8: TargetName | QF8: ="OPE.MA."&QB6&"."&SUBSTITUTE(QA6,"_","")&"Lcl_UpdChk01" -> OPE.MA.MABCL0036.CostMenuLcl_UpdChk01 | QG8: TargetName | QH8: ="OPE.MA."&QB6&"."&SUBSTITUTE(QA6,"_","")&"Lcl_Upd01" -> OPE.MA.MABCL0036.CostMenuLcl_Upd01 | QI8: TargetName | QJ8: ="OPE.MA."&QJ6&"."&SUBSTITUTE(QI6,"_","")&"_UpdChk01" -> OPE.MA.MABCL0036.SiteCo_UpdChk01 | QK8: TargetName | QL8: ="OPE.MA."&QJ6&"."&SUBSTITUTE(QI6,"_","")&"_Upd01" -> OPE.MA.MABCL0036.SiteCo_Upd01 | QM8: TargetName | QN8: ="OPE.MA."&QJ6&"."&SUBSTITUTE(QI6,"_","")&"Lcl_UpdChk01" -> OPE.MA.MABCL0036.SiteCoLcl_UpdChk01 | QO8: TargetName | QP8: ="OPE.MA."&QJ6&"."&SUBSTITUTE(QI6,"_","")&"Lcl_Upd01" -> OPE.MA.MABCL0036.SiteCoLcl_Upd01 | QS8: ブロック備考 Block Remarks
A9: # | D9: 項目名 Field Name | E9: 型 Type | F9: 桁 Digits | G9: フルネーム Full Name | H9: 日本語名 Japanese Name | I9: 上り項目 Request Message Field | J9: 下り項目 Response Message Field | QQ9: 条件および編集方法 Conditions and Editing Methods | QS9: 項目備考 Field Remarks
A10: # | K10: 上り項目 Request Message Field | L10: 下り項目 Response Message Field | M10: 上り項目 Request Message Field | N10: 下り項目 Response Message Field | O10: 上り項目 Request Message Field | P10: 下り項目 Response Message Field | Q10: 上り項目 Request Message Field | R10: 下り項目 Response Message Field | S10: 上り項目 Request Message Field | T10: 下り項目 Response Message Field | U10: 上り項目 Request Message Field | V10: 下り項目 Response Message Field | W10: 上り項目 Request Message Field | X10: 下り項目 Response Message Field | Y10: 上り項目 Request Message Field | Z10: 下り項目 Response Message Field | AA10: 上り項目 Request Message Field | AB10: 下り項目 Response Message Field | AC10: 上り項目 Request Message Field | AD10: 下り項目 Response Message Field | AE10: 上り項目 Request Message Field | AF10: 下り項目 Response Message Field | AG10: 上り項目 Request Message Field | AH10: 下り項目 Response Message Field | AI10: 上り項目 Request Message Field | AJ10: 下り項目 Response Message Field | AK10: 上り項目 Request Message Field | AL10: 下り項目 Response Message Field | AM10: 上り項目 Request Message Field | AN10: 下り項目 Response Message Field | AO10: 上り項目 Request Message Field | AP10: 下り項目 Response Message Field | AQ10: 上り項目 Request Message Field | AR10: 下り項目 Response Message Field | AS10: 上り項目 Request Message Field | AT10: 下り項目 Response Message Field | AU10: 上り項目 Request Message Field | AV10: 下り項目 Response Message Field | AW10: 上り項目 Request Message Field | AX10: 下り項目 Response Message Field | AY10: 上り項目 Request Message Field | AZ10: 下り項目 Response Message Field | BA10: 上り項目 Request Message Field | BB10: 下り項目 Response Message Field | BC10: 上り項目 Request Message Field | BD10: 下り項目 Response Message Field | BE10: 上り項目 Request Message Field | BF10: 下り項目 Response Message Field | BG10: 上り項目 Request Message Field | BH10: 下り項目 Response Message Field | BI10: 上り項目 Request Message Field | BJ10: 下り項目 Response Message Field | BK10: 上り項目 Request Message Field | BL10: 下り項目 Response Message Field | BM10: 上り項目 Request Message Field | BN10: 下り項目 Response Message Field | BO10: 上り項目 Request Message Field | BP10: 下り項目 Response Message Field | BQ10: 上り項目 Request Message Field | BR10: 下り項目 Response Message Field | BS10: 上り項目 Request Message Field | BT10: 下り項目 Response Message Field | BU10: 上り項目 Request Message Field | BV10: 下り項目 Response Message Field | BW10: 上り項目 Request Message Field | BX10: 下り項目 Response Message Field | BY10: 上り項目 Request Message Field | BZ10: 下り項目 Response Message Field | CA10: 上り項目 Request Message Field | CB10: 下り項目 Response Message Field | CC10: 上り項目 Request Message Field | CD10: 下り項目 Response Message Field | CE10: 上り項目 Request Message Field | CF10: 下り項目 Response Message Field | CG10: 上り項目 Request Message Field | CH10: 下り項目 Response Message Field | CI10: 上り項目 Request Message Field | CJ10: 下り項目 Response Message Field | CK10: 上り項目 Request Message Field | CL10: 下り項目 Response Message Field | CM10: 上り項目 Request Message Field | CN10: 下り項目 Response Message Field | CO10: 上り項目 Request Message Field | CP10: 下り項目 Response Message Field | CQ10: 上り項目 Request Message Field | CR10: 下り項目 Response Message Field | CS10: 上り項目 Request Message Field | CT10: 下り項目 Response Message Field | CU10: 上り項目 Request Message Field | CV10: 下り項目 Response Message Field | CW10: 上り項目 Request Message Field | CX10: 下り項目 Response Message Field | CY10: 上り項目 Request Message Field | CZ10: 下り項目 Response Message Field | DA10: 上り項目 Request Message Field | DB10: 下り項目 Response Message Field | DC10: 上り項目 Request Message Field | DD10: 下り項目 Response Message Field | DE10: 上り項目 Request Message Field | DF10: 下り項目 Response Message Field | DG10: 上り項目 Request Message Field | DH10: 下り項目 Response Message Field | DI10: 上り項目 Request Message Field | DJ10: 下り項目 Response Message Field | DK10: 上り項目 Request Message Field | DL10: 下り項目 Response Message Field | DM10: 上り項目 Request Message Field | DN10: 下り項目 Response Message Field | DO10: 上り項目 Request Message Field | DP10: 下り項目 Response Message Field | DQ10: 上り項目 Request Message Field | DR10: 下り項目 Response Message Field | DS10: 上り項目 Request Message Field | DT10: 下り項目 Response Message Field | DU10: 上り項目 Request Message Field | DV10: 下り項目 Response Message Field | DW10: 上り項目 Request Message Field | DX10: 下り項目 Response Message Field | DY10: 上り項目 Request Message Field | DZ10: 下り項目 Response Message Field | EA10: 上り項目 Request Message Field | EB10: 下り項目 Response Message Field | EC10: 上り項目 Request Message Field | ED10: 下り項目 Response Message Field | EE10: 上り項目 Request Message Field | EF10: 下り項目 Response Message Field | EG10: 上り項目 Request Message Field | EH10: 下り項目 Response Message Field | EI10: 上り項目 Request Message Field | EJ10: 下り項目 Response Message Field | EK10: 上り項目 Request Message Field | EL10: 下り項目 Response Message Field | EM10: 上り項目 Request Message Field | EN10: 下り項目 Response Message Field | EO10: 上り項目 Request Message Field | EP10: 下り項目 Response Message Field | EQ10: 上り項目 Request Message Field | ER10: 下り項目 Response Message Field | ES10: 上り項目 Request Message Field | ET10: 下り項目 Response Message Field | EU10: 上り項目 Request Message Field | EV10: 下り項目 Response Message Field | EW10: 上り項目 Request Message Field | EX10: 下り項目 Response Message Field | EY10: 上り項目 Request Message Field | EZ10: 下り項目 Response Message Field | FA10: 上り項目 Request Message Field | FB10: 下り項目 Response Message Field | FC10: 上り項目 Request Message Field | FD10: 下り項目 Response Message Field | FE10: 上り項目 Request Message Field | FF10: 下り項目 Response Message Field | FG10: 上り項目 Request Message Field | FH10: 下り項目 Response Message Field | FI10: 上り項目 Request Message Field | FJ10: 下り項目 Response Message Field | FK10: 上り項目 Request Message Field | FL10: 下り項目 Response Message Field | FM10: 上り項目 Request Message Field | FN10: 下り項目 Response Message Field | FO10: 上り項目 Request Message Field | FP10: 下り項目 Response Message Field | FQ10: 上り項目 Request Message Field | FR10: 下り項目 Response Message Field | FS10: 上り項目 Request Message Field | FT10: 下り項目 Response Message Field | FU10: 上り項目 Request Message Field | FV10: 下り項目 Response Message Field | FW10: 上り項目 Request Message Field | FX10: 下り項目 Response Message Field | FY10: 上り項目 Request Message Field | FZ10: 下り項目 Response Message Field | GA10: 上り項目 Request Message Field | GB10: 下り項目 Response Message Field | GC10: 上り項目 Request Message Field | GD10: 下り項目 Response Message Field | GE10: 上り項目 Request Message Field | GF10: 下り項目 Response Message Field | GG10: 上り項目 Request Message Field | GH10: 下り項目 Response Message Field | GI10: 上り項目 Request Message Field | GJ10: 下り項目 Response Message Field | GK10: 上り項目 Request Message Field | GL10: 下り項目 Response Message Field | GM10: 上り項目 Request Message Field | GN10: 下り項目 Response Message Field | GO10: 上り項目 Request Message Field | GP10: 下り項目 Response Message Field | GQ10: 上り項目 Request Message Field | GR10: 下り項目 Response Message Field | GS10: 上り項目 Request Message Field | GT10: 下り項目 Response Message Field | GU10: 上り項目 Request Message Field | GV10: 下り項目 Response Message Field | GW10: 上り項目 Request Message Field | GX10: 下り項目 Response Message Field | GY10: 上り項目 Request Message Field | GZ10: 下り項目 Response Message Field | HA10: 上り項目 Request Message Field | HB10: 下り項目 Response Message Field | HC10: 上り項目 Request Message Field | HD10: 下り項目 Response Message Field | HE10: 上り項目 Request Message Field | HF10: 下り項目 Response Message Field | HG10: 上り項目 Request Message Field | HH10: 下り項目 Response Message Field | HI10: 上り項目 Request Message Field | HJ10: 下り項目 Response Message Field | HK10: 上り項目 Request Message Field | HL10: 下り項目 Response Message Field | HM10: 上り項目 Request Message Field | HN10: 下り項目 Response Message Field | HO10: 上り項目 Request Message Field | HP10: 下り項目 Response Message Field | HQ10: 上り項目 Request Message Field | HR10: 下り項目 Response Message Field | HS10: 上り項目 Request Message Field | HT10: 下り項目 Response Message Field | HU10: 上り項目 Request Message Field | HV10: 下り項目 Response Message Field | HW10: 上り項目 Request Message Field | HX10: 下り項目 Response Message Field | HY10: 上り項目 Request Message Field | HZ10: 下り項目 Response Message Field | IA10: 上り項目 Request Message Field | IB10: 下り項目 Response Message Field | IC10: 上り項目 Request Message Field | ID10: 下り項目 Response Message Field | IE10: 上り項目 Request Message Field | IF10: 下り項目 Response Message Field | IG10: 上り項目 Request Message Field | IH10: 下り項目 Response Message Field | II10: 上り項目 Request Message Field | IJ10: 下り項目 Response Message Field | IK10: 上り項目 Request Message Field | IL10: 下り項目 Response Message Field | IM10: 上り項目 Request Message Field | IN10: 下り項目 Response Message Field | IO10: 上り項目 Request Message Field | IP10: 下り項目 Response Message Field | IQ10: 上り項目 Request Message Field | IR10: 下り項目 Response Message Field | IS10: 上り項目 Request Message Field | IT10: 下り項目 Response Message Field | IU10: 上り項目 Request Message Field | IV10: 下り項目 Response Message Field | IW10: 上り項目 Request Message Field | IX10: 下り項目 Response Message Field | IY10: 上り項目 Request Message Field | IZ10: 下り項目 Response Message Field | JA10: 上り項目 Request Message Field | JB10: 下り項目 Response Message Field | JC10: 上り項目 Request Message Field | JD10: 下り項目 Response Message Field | JE10: 上り項目 Request Message Field | JF10: 下り項目 Response Message Field | JG10: 上り項目 Request Message Field | JH10: 下り項目 Response Message Field | JI10: 上り項目 Request Message Field | JJ10: 下り項目 Response Message Field | JK10: 上り項目 Request Message Field | JL10: 下り項目 Response Message Field | JM10: 上り項目 Request Message Field | JN10: 下り項目 Response Message Field | JO10: 上り項目 Request Message Field | JP10: 下り項目 Response Message Field | JQ10: 上り項目 Request Message Field | JR10: 下り項目 Response Message Field | JS10: 上り項目 Request Message Field | JT10: 下り項目 Response Message Field | JU10: 上り項目 Request Message Field | JV10: 下り項目 Response Message Field | JW10: 上り項目 Request Message Field | JX10: 下り項目 Response Message Field | JY10: 上り項目 Request Message Field | JZ10: 下り項目 Response Message Field | KA10: 上り項目 Request Message Field | KB10: 下り項目 Response Message Field | KC10: 上り項目 Request Message Field | KD10: 下り項目 Response Message Field | KE10: 上り項目 Request Message Field | KF10: 下り項目 Response Message Field | KG10: 上り項目 Request Message Field | KH10: 下り項目 Response Message Field | KI10: 上り項目 Request Message Field | KJ10: 下り項目 Response Message Field | KK10: 上り項目 Request Message Field | KL10: 下り項目 Response Message Field | KM10: 上り項目 Request Message Field | KN10: 下り項目 Response Message Field | KO10: 上り項目 Request Message Field | KP10: 下り項目 Response Message Field | KQ10: 上り項目 Request Message Field | KR10: 下り項目 Response Message Field | KS10: 上り項目 Request Message Field | KT10: 下り項目 Response Message Field | KU10: 上り項目 Request Message Field | KV10: 下り項目 Response Message Field | KW10: 上り項目 Request Message Field | KX10: 下り項目 Response Message Field | KY10: 上り項目 Request Message Field | KZ10: 下り項目 Response Message Field | LA10: 上り項目 Request Message Field | LB10: 下り項目 Response Message Field | LC10: 上り項目 Request Message Field | LD10: 下り項目 Response Message Field | LE10: 上り項目 Request Message Field | LF10: 下り項目 Response Message Field | LG10: 上り項目 Request Message Field | LH10: 下り項目 Response Message Field | LI10: 上り項目 Request Message Field | LJ10: 下り項目 Response Message Field | LK10: 上り項目 Request Message Field | LL10: 下り項目 Response Message Field | LM10: 上り項目 Request Message Field | LN10: 下り項目 Response Message Field | LO10: 上り項目 Request Message Field | LP10: 下り項目 Response Message Field | LQ10: 上り項目 Request Message Field | LR10: 下り項目 Response Message Field | LS10: 上り項目 Request Message Field | LT10: 下り項目 Response Message Field | LU10: 上り項目 Request Message Field | LV10: 下り項目 Response Message Field | LW10: 上り項目 Request Message Field | LX10: 下り項目 Response Message Field | LY10: 上り項目 Request Message Field | LZ10: 下り項目 Response Message Field | MA10: 上り項目 Request Message Field | MB10: 下り項目 Response Message Field | MC10: 上り項目 Request Message Field | MD10: 下り項目 Response Message Field | ME10: 上り項目 Request Message Field | MF10: 下り項目 Response Message Field | MG10: 上り項目 Request Message Field | MH10: 下り項目 Response Message Field | MI10: 上り項目 Request Message Field | MJ10: 下り項目 Response Message Field | MK10: 上り項目 Request Message Field | ML10: 下り項目 Response Message Field | MM10: 上り項目 Request Message Field | MN10: 下り項目 Response Message Field | MO10: 上り項目 Request Message Field | MP10: 下り項目 Response Message Field | MQ10: 上り項目 Request Message Field | MR10: 下り項目 Response Message Field | MS10: 上り項目 Request Message Field | MT10: 下り項目 Response Message Field | MU10: 上り項目 Request Message Field | MV10: 下り項目 Response Message Field | MW10: 上り項目 Request Message Field | MX10: 下り項目 Response Message Field | MY10: 上り項目 Request Message Field | MZ10: 下り項目 Response Message Field | NA10: 上り項目 Request Message Field | NB10: 下り項目 Response Message Field | NC10: 上り項目 Request Message Field | ND10: 下り項目 Response Message Field | NE10: 上り項目 Request Message Field | NF10: 下り項目 Response Message Field | NG10: 上り項目 Request Message Field | NH10: 下り項目 Response Message Field | NI10: 上り項目 Request Message Field | NJ10: 下り項目 Response Message Field | NK10: 上り項目 Request Message Field | NL10: 下り項目 Response Message Field | NM10: 上り項目 Request Message Field | NN10: 下り項目 Response Message Field | NO10: 上り項目 Request Message Field | NP10: 下り項目 Response Message Field | NQ10: 上り項目 Request Message Field | NR10: 下り項目 Response Message Field | NS10: 上り項目 Request Message Field | NT10: 下り項目 Response Message Field | NU10: 上り項目 Request Message Field | NV10: 下り項目 Response Message Field | NW10: 上り項目 Request Message Field | NX10: 下り項目 Response Message Field | NY10: 上り項目 Request Message Field | NZ10: 下り項目 Response Message Field | OA10: 上り項目 Request Message Field | OB10: 下り項目 Response Message Field | OC10: 上り項目 Request Message Field | OD10: 下り項目 Response Message Field | OE10: 上り項目 Request Message Field | OF10: 下り項目 Response Message Field | OG10: 上り項目 Request Message Field | OH10: 下り項目 Response Message Field | OI10: 上り項目 Request Message Field | OJ10: 下り項目 Response Message Field | OK10: 上り項目 Request Message Field | OL10: 下り項目 Response Message Field | OM10: 上り項目 Request Message Field | ON10: 下り項目 Response Message Field | OO10: 上り項目 Request Message Field | OP10: 下り項目 Response Message Field | OQ10: 上り項目 Request Message Field | OR10: 下り項目 Response Message Field | OS10: 上り項目 Request Message Field | OT10: 下り項目 Response Message Field | OU10: 上り項目 Request Message Field | OV10: 下り項目 Response Message Field | OW10: 上り項目 Request Message Field | OX10: 下り項目 Response Message Field | OY10: 上り項目 Request Message Field | OZ10: 下り項目 Response Message Field | PA10: 上り項目 Request Message Field | PB10: 下り項目 Response Message Field | PC10: 上り項目 Request Message Field | PD10: 下り項目 Response Message Field | PE10: 上り項目 Request Message Field | PF10: 下り項目 Response Message Field | PG10: 上り項目 Request Message Field | PH10: 下り項目 Response Message Field | PI10: 上り項目 Request Message Field | PJ10: 下り項目 Response Message Field | PK10: 上り項目 Request Message Field | PL10: 下り項目 Response Message Field | PM10: 上り項目 Request Message Field | PN10: 下り項目 Response Message Field | PO10: 上り項目 Request Message Field | PP10: 下り項目 Response Message Field | PQ10: 上り項目 Request Message Field | PR10: 下り項目 Response Message Field | PS10: 上り項目 Request Message Field | PT10: 下り項目 Response Message Field | PU10: 上り項目 Request Message Field | PV10: 下り項目 Response Message Field | PW10: 上り項目 Request Message Field | PX10: 下り項目 Response Message Field | PY10: 上り項目 Request Message Field | PZ10: 下り項目 Response Message Field | QA10: 上り項目 Request Message Field | QB10: 下り項目 Response Message Field | QC10: 上り項目 Request Message Field | QD10: 下り項目 Response Message Field | QE10: 上り項目 Request Message Field | QF10: 下り項目 Response Message Field | QG10: 上り項目 Request Message Field | QH10: 下り項目 Response Message Field | QI10: 上り項目 Request Message Field | QJ10: 下り項目 Response Message Field | QK10: 上り項目 Request Message Field | QL10: 下り項目 Response Message Field | QM10: 上り項目 Request Message Field | QN10: 下り項目 Response Message Field | QO10: 上り項目 Request Message Field | QP10: 下り項目 Response Message Field
A11: 10 | B11: * | D11: Upd01_Dtl1 | E11: L | K11: Da_UpdChk01_Dtl | M11: Da_Upd01_Dtl | S11: DptBase_UpdChk01_Dtl | U11: DptBase_Upd01_Dtl | AA11: DptLvl_UpdChk01_Dtl | AC11: DptLvl_Upd01_Dtl | AI11: AprvRole_UpdChk01_Dtl | AK11: AprvRole_Upd01_Dtl | AQ11: Cntry_UpdChk01_Dtl | AS11: Cntry_Upd01_Dtl | AY11: Area_UpdChk01_Dtl | BA11: Area_Upd01_Dtl | BG11: Cur_UpdChk01_Dtl | BI11: Cur_Upd01_Dtl | BO11: Unit_UpdChk01_Dtl | BQ11: Unit_Upd01_Dtl | BW11: Bank_UpdChk01_Dtl | BY11: Bank_Upd01_Dtl | CE11: BankBranch_UpdChk01_Dtl | CG11: BankBranch_Upd01_Dtl | CM11: BankAc_UpdChk01_Dtl | CO11: BankAc_Upd01_Dtl | CU11: Xrate_UpdChk01_Dtl | CW11: Xrate_Upd01_Dtl | DC11: CalBase_UpdChk01_Dtl | DE11: CalBase_Upd01_Dtl | DK11: ItmJnl_UpdChk01_Dtl | DM11: ItmJnl_Upd01_Dtl | DS11: AcItmGrp_UpdChk01_Dtl | DU11: AcItmGrp_Upd01_Dtl | EA11: AcRsn_UpdChk01_Dtl | EC11: AcRsn_Upd01_Dtl | EI11: Site_UpdChk01_Dtl | EK11: Site_Upd01_Dtl | EQ11: LocGrp_UpdChk01_Dtl | ES11: LocGrp_Upd01_Dtl | EY11: LgGrp_UpdChk01_Dtl | FA11: LgGrp_Upd01_Dtl | FG11: AllocGrp_UpdChk01_Dtl | FI11: AllocGrp_Upd01_Dtl | FO11: Wg_UpdChk01_Dtl | FQ11: Wg_Upd01_Dtl | FW11: Oper_UpdChk01_Dtl | FY11: Oper_Upd01_Dtl | GE11: WkCost_UpdChk01_Dtl | GG11: WkCost_Upd01_Dtl | GM11: WkRsn_UpdChk01_Dtl | GO11: WkRsn_Upd01_Dtl | GU11: SlsUpriGrp_UpdChk01_Dtl | GW11: SlsUpriGrp_Upd01_Dtl | HC11: SlsUpriRank_UpdChk01_Dtl | HE11: SlsUpriRank_Upd01_Dtl | HK11: SetoffGrp_UpdChk01_Dtl | HM11: SetoffGrp_Upd01_Dtl | HS11: ShipValid_UpdChk01_Dtl | HU11: ShipValid_Upd01_Dtl | IA11: ItmShipGrp_UpdChk01_Dtl | IC11: ItmShipGrp_Upd01_Dtl | II11: Trnspt_UpdChk01_Dtl | IK11: Trnspt_Upd01_Dtl | IQ11: ExCntnr_UpdChk01_Dtl | IS11: ExCntnr_Upd01_Dtl | IY11: EximPort_UpdChk01_Dtl | JA11: EximPort_Upd01_Dtl | JG11: StkGd_UpdChk01_Dtl | JI11: StkGd_Upd01_Dtl | JO11: Trd_UpdChk01_Dtl | JQ11: Trd_Upd01_Dtl | JW11: SlipForm_UpdChk01_Dtl | JY11: SlipForm_Upd01_Dtl | KE11: PfGrp_UpdChk01_Dtl | KG11: PfGrp_Upd01_Dtl | KM11: ItmSpecGrp_UpdChk01_Dtl | KO11: ItmSpecGrp_Upd01_Dtl | KU11: ItmCompGrp_UpdChk01_Dtl | KW11: ItmCompGrp_Upd01_Dtl | LC11: JnlAct_UpdChk01_Dtl | LE11: JnlAct_Upd01_Dtl | LK11: JnlGrp_UpdChk01_Dtl | LM11: JnlGrp_Upd01_Dtl | LS11: JnlPtnBase_UpdChk01_Dtl | LU11: JnlPtnBase_Upd01_Dtl | MA11: AutoJnlKey_UpdChk01_Dtl | MC11: AutoJnlKey_Upd01_Dtl | MI11: InspPtn_UpdChk01_Dtl | MK11: InspPtn_Upd01_Dtl | MQ11: WkDay_UpdChk01_Dtl | MS11: WkDay_Upd01_Dtl | MY11: ShipTerm_UpdChk01_Dtl | NA11: ShipTerm_Upd01_Dtl | NG11: ShipWk_UpdChk01_Dtl | NI11: ShipWk_Upd01_Dtl | NO11: Rsrc_UpdChk01_Dtl | NQ11: Rsrc_Upd01_Dtl | NW11: HsGrp_UpdChk01_Dtl | NY11: HsGrp_Upd01_Dtl | OE11: AlcPtn_UpdChk01_Dtl | OG11: AlcPtn_Upd01_Dtl | OM11: CtgGrp_UpdChk01_Dtl | OO11: CtgGrp_Upd01_Dtl | OU11: ActPtn_UpdChk01_Dtl | OW11: ActPtn_Upd01_Dtl | PC11: GpAlc_UpdChk01_Dtl | PE11: GpAlc_Upd01_Dtl | PK11: CalcCtg_UpdChk01_Dtl | PM11: CalcCtg_Upd01_Dtl | PS11: RptPtn_UpdChk01_Dtl | PU11: RptPtn_Upd01_Dtl | QA11: CostMenu_UpdChk01_Dtl | QC11: CostMenu_Upd01_Dtl | QI11: SiteCo_UpdChk01_Dtl | QK11: SiteCo_Upd01_Dtl
A12: 10 | D12: da_cd | E12: #MA.DA_CD | G12: Data access cd. | H12: データアクセスＣＤ | I12: E | K12: E | M12: E
A13: 10 | D13: da_nm | E13: #MA.DA_NM | G13: Standard data access name | H13: 標準データアクセス名 | I13: E | K13: E | M13: E
A14: 10 | D14: dpt_cd | E14: #MA.DPT_CD | G14: Dept. cd. | H14: 部門ＣＤ | I14: E | S14: E | U14: E
A15: 10 | D15: def_dpt_nm | E15: #MA.DPT_NM | G15: Standard dept. name | H15: 標準部門名 | I15: E | S15: E | U15: E
A16: 10 | D16: dpt_lvl_cd | E16: #MA.DPT_LVL_CD | G16: Dept. hierarchy cd. | H16: 部門階層ＣＤ | I16: E | AA16: E | AC16: E
A17: 10 | D17: dpt_lvl_nm | E17: #MA.DPT_LVL_NM | G17: Standard dept. hierarchy name | H17: 標準部門階層名 | I17: E | AA17: E | AC17: E
A18: 10 | D18: aprv_role_cd | E18: #MA.APRV_ROLE_CD | G18: Approval role cd. | H18: 承認役割ＣＤ | I18: E | AI18: E | AK18: E
A19: 10 | D19: aprv_role_nm | E19: #MA.APRV_ROLE_NM | G19: Standard approval role name | H19: 標準承認役割名 | I19: E | AI19: E | AK19: E
A20: 10 | D20: cntry_cd | E20: #MA.CNTRY_CD | G20: Country cd. | H20: 国ＣＤ | I20: E | AQ20: E | AS20: E
A21: 10 | D21: cntry_nm | E21: #MA.CNTRY_NM | G21: Standard Country name | H21: 標準国名 | I21: E | AQ21: E | AS21: E
A22: 10 | D22: area_cd | E22: #MA.AREA_CD | G22: Region cd. | H22: 地域ＣＤ | I22: E | AY22: E | BA22: E
A23: 10 | D23: area_nm | E23: #MA.AREA_NM | G23: Standard Region name | H23: 標準地域名 | I23: E | AY23: E | BA23: E
A24: 10 | D24: cur_cd | E24: #MA.CUR_CD | G24: Currency cd. | H24: 通貨ＣＤ | I24: E | BG24: E | BI24: E
A25: 10 | D25: cur_nm | E25: #MA.CUR_NM | G25: Standard currency name | H25: 標準通貨名 | I25: E | BG25: E | BI25: E
A26: 10 | D26: amt_dec_place | E26: #MA.DEC_PLACE | G26: Amount number of decimal places | H26: 金額小数部有効桁数 | I26: E | BG26: E | BI26: E
A27: 10 | D27: upri_dec_place | E27: #MA.DEC_PLACE | G27: Unit price number of decimal places | H27: 単価小数部有効桁数 | I27: E | BG27: E | BI27: E
A28: 10 | D28: unit_cd | E28: #MA.UNIT_CD | G28: Unit cd. | H28: 単位ＣＤ | I28: E | BO28: E | BQ28: E
A29: 10 | D29: unit_nm | E29: #MA.UNIT_NM | G29: Standard unit name | H29: 標準単位名 | I29: E | BO29: E | BQ29: E
A30: 10 | D30: dec_place | E30: #MA.DEC_PLACE | G30: Number of decimal places | H30: 小数部有効桁数 | I30: E | BO30: E | BQ30: E
A31: 10 | D31: unit_rnd_typ | E31: #MA.RND_TYP | G31: Rounding type | H31: 端数処理区分 | I31: E | BO31: rnd_typ | BQ31: rnd_typ
A32: 10 | D32: bank_cd | E32: #MA.BANK_CD | G32: Bank cd. | H32: 銀行ＣＤ | I32: E | BW32: E | BY32: E
A33: 10 | D33: bank_nm | E33: #MA.BANK_NM | G33: Standard bank name | H33: 標準銀行名 | I33: E | BW33: E | BY33: E
A34: 10 | D34: bank_cal_cd | E34: #MA.CAL_CD | G34: Calendar cd. | H34: カレンダＣＤ | I34: E | BW34: cal_cd | BY34: cal_cd
A35: 10 | D35: bank_branch_bank_cd | E35: #MA.BANK_CD | G35: Bank cd. | H35: 銀行ＣＤ | I35: E | CE35: bank_cd | CG35: bank_cd
A36: 10 | D36: branch_cd | E36: #MA.BANK_BRANCH_CD | G36: Bank branch cd. | H36: 銀行支店ＣＤ | I36: E | CE36: E | CG36: E
A37: 10 | D37: branch_nm | E37: #MA.BANK_BRANCH_NM | G37: Standard bank branch name | H37: 標準銀行支店名 | I37: E | CE37: E | CG37: E
A38: 10 | D38: bank_branch_cal_cd | E38: #MA.CAL_CD | G38: Calendar cd. | H38: カレンダＣＤ | I38: E | CE38: cal_cd | CG38: cal_cd
A39: 10 | D39: bank_ac_cd | E39: #MA.BANK_AC_CD | G39: Bank account cd. | H39: 口座ＣＤ | I39: E | CM39: E | CO39: E
A40: 10 | D40: bank_ac_nm | E40: #MA.BANK_AC_NM | G40: Standard account name | H40: 標準口座名 | I40: E | CM40: E | CO40: E
A41: 10 | D41: ext_flg | E41: #MA.FLG | G41: External | H41: 社外 | I41: E | CM41: E | CO41: E
A42: 10 | D42: bank_ac_bank_cd | E42: #MA.BANK_CD | G42: Bank cd. | H42: 銀行ＣＤ | I42: E | CM42: bank_cd | CO42: bank_cd
A43: 10 | D43: bank_ac_branch_cd | E43: #MA.BANK_BRANCH_CD | G43: Bank branch cd. | H43: 銀行支店ＣＤ | I43: E | CM43: branch_cd | CO43: branch_cd
A44: 10 | D44: bank_ac_no | E44: #MA.BANK_AC_NO | G44: Bank account number | H44: 口座番号 | I44: E | CM44: E | CO44: E
A45: 10 | D45: bank_ac_typ | E45: #MA.BANK_AC_TYP | G45: Bank account type | H45: 口座区分 | I45: E | CM45: E | CO45: E
A46: 10 | D46: bank_ac_holder | E46: #MA.BANK_AC_HOLDER | G46: Bank account holder | H46: 口座名義 | I46: E | CM46: E | CO46: E
A47: 10 | D47: bank_ac_holder_sub | E47: #MA.BANK_AC_HOLDER_SUB | G47: Account holder alias name | H47: 口座名義別名 | I47: E | CM47: E | CO47: E
A48: 10 | D48: xrate_cd | E48: #MA.XRATE_CD | G48: Exchange rate cd. | H48: 為替レートＣＤ | I48: E | CU48: E | CW48: E
A49: 10 | D49: xrate_nm | E49: #MA.XRATE_NM | G49: Standard exchange rate name | H49: 標準為替レート名 | I49: E | CU49: E | CW49: E
A50: 10 | D50: cal_cd | E50: #MA.CAL_CD | G50: Calendar cd. | H50: カレンダＣＤ | I50: E | DC50: E | DE50: E
A51: 10 | D51: cal_nm | E51: #MA.CAL_NM | G51: Standard calendar name | H51: 標準カレンダ名 | I51: E | DC51: E | DE51: E
A52: 10 | D52: itm_jnl_cd | E52: #MA.ITM_JNL_CD | G52: Item journal cd. | H52: 品目仕訳ＣＤ | I52: E | DK52: E | DM52: E
A53: 10 | D53: itm_jnl_nm | E53: #MA.ITM_JNL_NM | G53: Standard Item journal name | H53: 標準品目仕訳名 | I53: E | DK53: E | DM53: E
A54: 10 | D54: ar_typ | E54: #MA.AR_TYP | G54: AR type | H54: 債権区分 | I54: E | DK54: E | DM54: E
A55: 10 | D55: ap_typ | E55: #MA.AP_TYP | G55: AP type | H55: 債務区分 | I55: E | DK55: E | DM55: E
A56: 10 | D56: ac_itm_grp_cd | E56: #MA.AC_ITM_GRP_CD | G56: Accounting item classification cd. | H56: 会計品目分類ＣＤ | I56: E | DS56: E | DU56: E
A57: 10 | D57: ac_itm_grp_nm | E57: #MA.AC_ITM_GRP_NM | G57: Standard Accounting item classification name | H57: 標準会計品目分類名 | I57: E | DS57: E | DU57: E
A58: 10 | D58: ac_rsn_cd | E58: #MA.AC_RSN_CD | G58: Accounting reason cd. | H58: 会計理由ＣＤ | I58: E | EA58: E | EC58: E
A59: 10 | D59: ac_rsn_nm | E59: #MA.AC_RSN_NM | G59: Standard Accounting reason name | H59: 標準会計理由名 | I59: E | EA59: E | EC59: E
A60: 10 | D60: ac_rsn_ar_typ | E60: #MA.AR_TYP | G60: AR type | H60: 債権区分 | I60: E | EA60: ar_typ | EC60: ar_typ
A61: 10 | D61: ac_rsn_ap_typ | E61: #MA.AP_TYP | G61: AP type | H61: 債務区分 | I61: E | EA61: ap_typ | EC61: ap_typ
A62: 10 | D62: ac_invalid_flg | E62: #MA.FLG | G62: Not for journal | H62: 仕訳対象外 | I62: E | EA62: E | EC62: E
A63: 10 | D63: cost_invalid_flg | E63: #MA.FLG | G63: Not costing | H63: 原価対象外 | I63: E | EA63: E | EC63: E
A64: 10 | D64: site_cd | E64: #MA.SITE_CD | G64: Factory/Distribution warehouse cd. | H64: 工場・物流倉庫ＣＤ | I64: E | EI64: E | EK64: E
A65: 10 | D65: site_nm | E65: #MA.SITE_NM | G65: Standard factory/distribution warehouse name | H65: 標準工場・物流倉庫名 | I65: E | EI65: E | EK65: E
A66: 10 | D66: arr_flg | E66: #MA.FLG | G66: Receipt | H66: 入荷 | I66: E | EI66: E | EK66: E
A67: 10 | D67: zip_cd | E67: #MA.ZIP_CD | G67: Zip code | H67: 郵便番号 | I67: E | EI67: E | EK67: E
A68: 10 | D68: addr1 | E68: #MA.ADDR1 | G68: Address 1 | H68: 住所１ | I68: E | EI68: E | EK68: E
A69: 10 | D69: addr2 | E69: #MA.ADDR2 | G69: Address 2 | H69: 住所２ | I69: E | EI69: E | EK69: E
A70: 10 | D70: addr3 | E70: #MA.ADDR3 | G70: Address 3 | H70: 住所３ | I70: E | EI70: E | EK70: E
A71: 10 | D71: addr4 | E71: #MA.ADDR4 | G71: Address 4 | H71: 住所４ | I71: E | EI71: E | EK71: E
A72: 10 | D72: tel | E72: #MA.TEL | G72: TEL | H72: ＴＥＬ | I72: E | EI72: E | EK72: E
A73: 10 | D73: fax | E73: #MA.TEL | G73: FAX | H73: ＦＡＸ | I73: E | EI73: E | EK73: E
A74: 10 | D74: def_loc_grp_cd | E74: #MA.LOC_GRP_CD | G74: Mfg. location group cd. | H74: 製造場所グループＣＤ | I74: E | EI74: E | EK74: E
A75: 10 | D75: def_alloc_grp_cd | E75: #MA.ALLOC_GRP_CD | G75: Gross allocation location group cd. | H75: 総量引当場所グループＣＤ | I75: E | EI75: E | EK75: E
... A77: 10 | D77: def_cal_cd | E77: #MA.CAL_CD | G77: Calendar cd. | H77: カレンダＣＤ | I77: E | EI77: E | EK77: E
A78: 10 | D78: loc_grp_cd | E78: #MA.LOC_GRP_CD | G78: Mfg. location group cd. | H78: 製造場所グループＣＤ | I78: E | EQ78: E | ES78: E
A79: 10 | D79: loc_grp_nm | E79: #MA.LOC_GRP_NM | G79: Standard mfg. location group name | H79: 標準製造場所グループ名 | I79: E | EQ79: E | ES79: E
A80: 10 | D80: loc_grp_wg_cd | E80: #MA.WG_CD | G80: WG cd. | H80: ワーキンググループＣＤ | I80: E | EQ80: wg_cd | ES80: wg_cd
A81: 10 | D81: lg_grp_cd | E81: #MA.LG_GRP_CD | G81: Distribution group cd. | H81: 物流グループＣＤ | I81: E | EY81: E | FA81: E
A82: 10 | D82: lg_grp_nm | E82: #MA.LG_GRP_NM | G82: Standard distribution group name | H82: 標準物流グループ名 | I82: E | EY82: E | FA82: E
A83: 10 | D83: loc_flg | E83: #MA.FLG | G83: Set location | H83: 場所設定 | I83: E | EY83: E | FA83: E
A84: 10 | D84: lg_grp_wg_cd | E84: #MA.WG_CD | G84: WG cd. | H84: ワーキンググループＣＤ | I84: E | EY84: wg_cd | FA84: wg_cd
A85: 10 | D85: ship_slip_flg | E85: #MA.FLG | G85: Issue shipping slip | H85: 出荷伝票発行 | I85: E | EY85: E | FA85: E
A86: 10 | D86: pick_list_flg | E86: #MA.FLG | G86: Issue picking list | H86: ピッキングリスト発行 | I86: E | EY86: E | FA86: E
A87: 10 | D87: ship_inst_flg | E87: #MA.FLG | G87: Shipping order sheet issue | H87: 出荷指図書発行 | I87: E | EY87: E | FA87: E
A88: 10 | D88: ship_slip_act_flg | E88: #MA.FLG | G88: Issue shipping slip (Result) | H88: 出荷伝票発行（実績） | I88: E | EY88: E | FA88: E
A89: 10 | D89: lg_grp_cal_cd | E89: #MA.CAL_CD | G89: Calendar cd. | H89: カレンダＣＤ | I89: E | EY89: cal_cd | FA89: cal_cd
A90: 10 | D90: lg_grp_site_co_cd | E90: #MA.SITE_CO_CD | G90: Warehousing business cd. | H90: 倉庫事業者ＣＤ | I90: E | EY90: site_co_cd | FA90: site_co_cd
A91: 10 | D91: gi_minus_stk_chk_flg | E91: #MA.FLG | G91: Check negative inventory at GI | H91: 出庫時マイナス在庫確認 | I91: E | EY91: E | FA91: E
A92: 10 | D92: ship_loc_prio_flg | E92: #MA.FLG | G92: Precede shipping location | H92: 出荷場所優先 | I92: E | EY92: E | FA92: E
A93: 10 | D93: alloc_grp_cd | E93: #MA.ALLOC_GRP_CD | G93: Gross allocation location group cd. | H93: 総量引当場所グループＣＤ | I93: E | FG93: E | FI93: E
A94: 10 | D94: alloc_grp_nm | E94: #MA.ALLOC_GRP_NM | G94: Standard gross allocation location group name | H94: 標準総量引当場所グループ名 | I94: E | FG94: E | FI94: E
A95: 10 | D95: wg_cd | E95: #MA.WG_CD | G95: WG cd. | H95: ワーキンググループＣＤ | I95: E | FO95: E | FQ95: E
A96: 10 | D96: wg_nm | E96: #MA.WG_NM | G96: Standard WG name | H96: 標準ワーキンググループ名 | I96: E | FO96: E | FQ96: E
A97: 10 | D97: sls_flg | E97: #MA.FLG | G97: Sales | H97: 販売 | I97: E | FO97: E | FQ97: E
A98: 10 | D98: lg_flg | E98: #MA.FLG | G98: Distribution | H98: 物流 | I98: E | FO98: E | FQ98: E
A99: 10 | D99: mfg_flg | E99: #MA.FLG | G99: Mfg. | H99: 製造 | I99: E | FO99: E | FQ99: E
A100: 10 | D100: purc_flg | E100: #MA.FLG | G100: Purchase | H100: 購買 | I100: E | FO100: E | FQ100: E
A101: 10 | D101: ar_flg | E101: #MA.FLG | G101: AR | H101: 債権 | I101: E | FO101: E | FQ101: E
...

Sheet Del01
A1: * | B1: * | D1: L | E1: 1
A2: * | D2: オペレーション実装仕様書 Operation Specification Implementation Sheet | E2: ModuleID : | F2: =IF(LogicCommon!C2="","",LogicCommon!C2) -> MA | G2: LogicID : | H2: =IF(LogicCommon!E2="","",LogicCommon!E2) -> MABCL0030 | I2: Ope.ID : | J2: Del01 | K2: Pj.ID : | L2: =IF(LogicCommon!G2="","",LogicCommon!G2) -> MC | M2: Ope.Body : | N2: "mcframe.serverMAUD.MAUDL6020.MAUDL_LCLRLDeleter"
A3: * | D3: =IF(LogicCommon!A3="","",LogicCommon!A3) | E3: SubModuleID : | F3: =IF(LogicCommon!C3="","",LogicCommon!C3) -> MABC | G3: LogicClass : | H3: =IF(LogicCommon!E3="","",LogicCommon!E3) -> MABCL_MultiReg | I3: Ope.Method : | J3: @ | K3: SuperClassPj.ID : | L3: =IF(LogicCommon!G3="","",LogicCommon!G3) | M3: ReportID : | O3: Gene.Type : | P3: ALL
A4: * | E4: Version : | F4: 000000 | G4: LogicName : | H4: =IF(LogicCommon!E4="","",LogicCommon!E4) -> マルチマスタ登録 | I4: Ope.Name : | J4: 削除 | K4: SuperLogicID : | L4: =IF(LogicCommon!G4="","",LogicCommon!G4) -> MA.MAUDL5010
A5: * | E5: ACType : | K5: 1 | O5: 2 | S5: 3 | W5: 4 | AA5: 5 | AE5: 6 | AI5: 7 | AM5: 8 | AQ5: 9 | AU5: 10 | AY5: 11 | BC5: 12 | BG5: 13 | BK5: 14 | BO5: 15 | BS5: 16 | BW5: 17 | CA5: 18 | CE5: 19 | CI5: 20 | CM5: 21 | CQ5: 22 | CU5: 23 | CY5: 24 | DC5: 25 | DG5: 26 | DK5: 27 | DO5: 28 | DS5: 29 | DW5: 30 | EA5: 31 | EE5: 32 | EI5: 33 | EM5: 34 | EQ5: 35 | EU5: 36 | EY5: 37 | FC5: 38 | FG5: 39 | FK5: 40 | FO5: 41 | FS5: 42 | FW5: 43 | GA5: 44 | GE5: 45 | GI5: 46 | GM5: 47 | GQ5: 48 | GU5: 49 | GY5: 50 | HC5: 51 | HG5: 52 | HK5: 53 | HO5: 54 | HS5: 55 | HW5: 56
A6: * | D6: 概要 : | E6: 複数のマスタ、名称マスタの削除を行います。 | K6: Da | L6: MABCL0031 | O6: Dpt_Base | P6: MABCL0031 | S6: Dpt_Lvl | T6: MABCL0031 | W6: Aprv_Role | X6: MABCL0031 | AA6: Cntry | AB6: MABCL0031 | AE6: Area | AF6: MABCL0031 | AI6: Cur | AJ6: MABCL0031 | AM6: Unit | AN6: MABCL0031 | AQ6: Bank | AR6: MABCL0031 | AU6: Bank_Branch | AV6: MABCL0031 | AY6: Bank_Ac | AZ6: MABCL0032 | BC6: Xrate | BD6: MABCL0032 | BG6: Cal_Base | BH6: MABCL0032 | BK6: Itm_Jnl | BL6: MABCL0032 | BO6: Ac_Itm_Grp | BP6: MABCL0032 | BS6: Ac_Rsn | BT6: MABCL0032 | BW6: Site | BX6: MABCL0032 | CA6: Loc_Grp | CB6: MABCL0032 | CE6: Lg_Grp | CF6: MABCL0032 | CI6: Alloc_Grp | CJ6: MABCL0032 | CM6: Wg | CN6: MABCL0033 | CQ6: Oper | CR6: MABCL0033 | CU6: Wk_Cost | CV6: MABCL0033 | CY6: Wk_Rsn | CZ6: MABCL0033 | DC6: Sls_Upri_Grp | DD6: MABCL0033 | DG6: Sls_Upri_Rank | DH6: MABCL0033 | DK6: Setoff_Grp | DL6: MABCL0033 | DO6: Ship_Valid | DP6: MABCL0033 | DS6: Itm_Ship_Grp | DT6: MABCL0033 | DW6: Trnspt | DX6: MABCL0033 | EA6: Ex_Cntnr | EB6: MABCL0034 | EE6: Exim_Port | EF6: MABCL0034 | EI6: Stk_Gd | EJ6: MABCL0034 | EM6: Trd | EN6: MABCL0034 | EQ6: Slip_Form | ER6: MABCL0034 | EU6: Pf_Grp | EV6: MABCL0034 | EY6: Itm_Spec_Grp | EZ6: MABCL0034 | FC6: Itm_Comp_Grp | FD6: MABCL0034 | FG6: Jnl_Act | FH6: MABCL0034 | FK6: Jnl_Grp | FL6: MABCL0034 | FO6: Jnl_Ptn_Base | FP6: MABCL0035 | FS6: Auto_Jnl_Key | FT6: MABCL0035 | FW6: Insp_Ptn | FX6: MABCL0035 | GA6: Wk_Day | GB6: MABCL0035 | GE6: Ship_Term | GF6: MABCL0035 | GI6: Ship_Wk | GJ6: MABCL0035 | GM6: Rsrc | GN6: MABCL0035 | GQ6: Hs_Grp | GR6: MABCL0035 | GU6: Alc_Ptn | GV6: MABCL0035 | GY6: Ctg_Grp | GZ6: MABCL0035 | HC6: Act_Ptn | HD6: MABCL0035 | HG6: Gp_Alc | HH6: MABCL0036 | HK6: Calc_Ctg | HL6: MABCL0036 | HO6: Rpt_Ptn | HP6: MABCL0036 | HS6: Cost_Menu | HT6: MABCL0036 | HW6: Site_Co | HX6: MABCL0036
A7: # | I7: U | K7: o | L7: =UPPER(K6)&".chk"&TEXT(K5,"00") -> DA.chk01 | M7: o | N7: =UPPER(K6)&".del"&TEXT(K5,"00") -> DA.del01 | O7: o | P7: =UPPER(O6)&".chk"&TEXT(O5,"00") -> DPT_BASE.chk02 | Q7: o | R7: =UPPER(O6)&".del"&TEXT(O5,"00") -> DPT_BASE.del02 | S7: o | T7: =UPPER(S6)&".chk"&TEXT(S5,"00") -> DPT_LVL.chk03 | U7: o | V7: =UPPER(S6)&".del"&TEXT(S5,"00") -> DPT_LVL.del03 | W7: o | X7: =UPPER(W6)&".chk"&TEXT(W5,"00") -> APRV_ROLE.chk04 | Y7: o | Z7: =UPPER(W6)&".del"&TEXT(W5,"00") -> APRV_ROLE.del04 | AA7: o | AB7: =UPPER(AA6)&".chk"&TEXT(AA5,"00") -> CNTRY.chk05 | AC7: o | AD7: =UPPER(AA6)&".del"&TEXT(AA5,"00") -> CNTRY.del05 | AE7: o | AF7: =UPPER(AE6)&".chk"&TEXT(AE5,"00") -> AREA.chk06 | AG7: o | AH7: =UPPER(AE6)&".del"&TEXT(AE5,"00") -> AREA.del06 | AI7: o | AJ7: =UPPER(AI6)&".chk"&TEXT(AI5,"00") -> CUR.chk07 | AK7: o | AL7: =UPPER(AI6)&".del"&TEXT(AI5,"00") -> CUR.del07 | AM7: o | AN7: =UPPER(AM6)&".chk"&TEXT(AM5,"00") -> UNIT.chk08 | AO7: o | AP7: =UPPER(AM6)&".del"&TEXT(AM5,"00") -> UNIT.del08 | AQ7: o | AR7: =UPPER(AQ6)&".chk"&TEXT(AQ5,"00") -> BANK.chk09 | AS7: o | AT7: =UPPER(AQ6)&".del"&TEXT(AQ5,"00") -> BANK.del09 | AU7: o | AV7: =UPPER(AU6)&".chk"&TEXT(AU5,"00") -> BANK_BRANCH.chk10 | AW7: o | AX7: =UPPER(AU6)&".del"&TEXT(AU5,"00") -> BANK_BRANCH.del10 | AY7: o | AZ7: =UPPER(AY6)&".chk"&TEXT(AY5,"00") -> BANK_AC.chk11 | BA7: o | BB7: =UPPER(AY6)&".del"&TEXT(AY5,"00") -> BANK_AC.del11 | BC7: o | BD7: =UPPER(BC6)&".chk"&TEXT(BC5,"00") -> XRATE.chk12 | BE7: o | BF7: =UPPER(BC6)&".del"&TEXT(BC5,"00") -> XRATE.del12 | BG7: o | BH7: =UPPER(BG6)&".chk"&TEXT(BG5,"00") -> CAL_BASE.chk13 | BI7: o | BJ7: =UPPER(BG6)&".del"&TEXT(BG5,"00") -> CAL_BASE.del13 | BK7: o | BL7: =UPPER(BK6)&".chk"&TEXT(BK5,"00") -> ITM_JNL.chk14 | BM7: o | BN7: =UPPER(BK6)&".del"&TEXT(BK5,"00") -> ITM_JNL.del14 | BO7: o | BP7: =UPPER(BO6)&".chk"&TEXT(BO5,"00") -> AC_ITM_GRP.chk15 | BQ7: o | BR7: =UPPER(BO6)&".del"&TEXT(BO5,"00") -> AC_ITM_GRP.del15 | BS7: o | BT7: =UPPER(BS6)&".chk"&TEXT(BS5,"00") -> AC_RSN.chk16 | BU7: o | BV7: =UPPER(BS6)&".del"&TEXT(BS5,"00") -> AC_RSN.del16 | BW7: o | BX7: =UPPER(BW6)&".chk"&TEXT(BW5,"00") -> SITE.chk17 | BY7: o | BZ7: =UPPER(BW6)&".del"&TEXT(BW5,"00") -> SITE.del17 | CA7: o | CB7: =UPPER(CA6)&".chk"&TEXT(CA5,"00") -> LOC_GRP.chk18 | CC7: o | CD7: =UPPER(CA6)&".del"&TEXT(CA5,"00") -> LOC_GRP.del18 | CE7: o | CF7: =UPPER(CE6)&".chk"&TEXT(CE5,"00") -> LG_GRP.chk19 | CG7: o | CH7: =UPPER(CE6)&".del"&TEXT(CE5,"00") -> LG_GRP.del19 | CI7: o | CJ7: =UPPER(CI6)&".chk"&TEXT(CI5,"00") -> ALLOC_GRP.chk20 | CK7: o | CL7: =UPPER(CI6)&".del"&TEXT(CI5,"00") -> ALLOC_GRP.del20 | CM7: o | CN7: =UPPER(CM6)&".chk"&TEXT(CM5,"00") -> WG.chk21 | CO7: o | CP7: =UPPER(CM6)&".del"&TEXT(CM5,"00") -> WG.del21 | CQ7: o | CR7: =UPPER(CQ6)&".chk"&TEXT(CQ5,"00") -> OPER.chk22 | CS7: o | CT7: =UPPER(CQ6)&".del"&TEXT(CQ5,"00") -> OPER.del22 | CU7: o | CV7: =UPPER(CU6)&".chk"&TEXT(CU5,"00") -> WK_COST.chk23 | CW7: o | CX7: =UPPER(CU6)&".del"&TEXT(CU5,"00") -> WK_COST.del23 | CY7: o | CZ7: =UPPER(CY6)&".chk"&TEXT(CY5,"00") -> WK_RSN.chk24 | DA7: o | DB7: =UPPER(CY6)&".del"&TEXT(CY5,"00") -> WK_RSN.del24 | DC7: o | DD7: =UPPER(DC6)&".chk"&TEXT(DC5,"00") -> SLS_UPRI_GRP.chk25 | DE7: o | DF7: =UPPER(DC6)&".del"&TEXT(DC5,"00") -> SLS_UPRI_GRP.del25 | DG7: o | DH7: =UPPER(DG6)&".chk"&TEXT(DG5,"00") -> SLS_UPRI_RANK.chk26 | DI7: o | DJ7: =UPPER(DG6)&".del"&TEXT(DG5,"00") -> SLS_UPRI_RANK.del26 | DK7: o | DL7: =UPPER(DK6)&".chk"&TEXT(DK5,"00") -> SETOFF_GRP.chk27 | DM7: o | DN7: =UPPER(DK6)&".del"&TEXT(DK5,"00") -> SETOFF_GRP.del27 | DO7: o | DP7: =UPPER(DO6)&".chk"&TEXT(DO5,"00") -> SHIP_VALID.chk28 | DQ7: o | DR7: =UPPER(DO6)&".del"&TEXT(DO5,"00") -> SHIP_VALID.del28 | DS7: o | DT7: =UPPER(DS6)&".chk"&TEXT(DS5,"00") -> ITM_SHIP_GRP.chk29 | DU7: o | DV7: =UPPER(DS6)&".del"&TEXT(DS5,"00") -> ITM_SHIP_GRP.del29 | DW7: o | DX7: =UPPER(DW6)&".chk"&TEXT(DW5,"00") -> TRNSPT.chk30 | DY7: o | DZ7: =UPPER(DW6)&".del"&TEXT(DW5,"00") -> TRNSPT.del30 | EA7: o | EB7: =UPPER(EA6)&".chk"&TEXT(EA5,"00") -> EX_CNTNR.chk31 | EC7: o | ED7: =UPPER(EA6)&".del"&TEXT(EA5,"00") -> EX_CNTNR.del31 | EE7: o | EF7: =UPPER(EE6)&".chk"&TEXT(EE5,"00") -> EXIM_PORT.chk32 | EG7: o | EH7: =UPPER(EE6)&".del"&TEXT(EE5,"00") -> EXIM_PORT.del32 | EI7: o | EJ7: =UPPER(EI6)&".chk"&TEXT(EI5,"00") -> STK_GD.chk33 | EK7: o | EL7: =UPPER(EI6)&".del"&TEXT(EI5,"00") -> STK_GD.del33 | EM7: o | EN7: =UPPER(EM6)&".chk"&TEXT(EM5,"00") -> TRD.chk34 | EO7: o | EP7: =UPPER(EM6)&".del"&TEXT(EM5,"00") -> TRD.del34 | EQ7: o | ER7: =UPPER(EQ6)&".chk"&TEXT(EQ5,"00") -> SLIP_FORM.chk35 | ES7: o | ET7: =UPPER(EQ6)&".del"&TEXT(EQ5,"00") -> SLIP_FORM.del35 | EU7: o | EV7: =UPPER(EU6)&".chk"&TEXT(EU5,"00") -> PF_GRP.chk36 | EW7: o | EX7: =UPPER(EU6)&".del"&TEXT(EU5,"00") -> PF_GRP.del36 | EY7: o | EZ7: =UPPER(EY6)&".chk"&TEXT(EY5,"00") -> ITM_SPEC_GRP.chk37 | FA7: o | FB7: =UPPER(EY6)&".del"&TEXT(EY5,"00") -> ITM_SPEC_GRP.del37 | FC7: o | FD7: =UPPER(FC6)&".chk"&TEXT(FC5,"00") -> ITM_COMP_GRP.chk38 | FE7: o | FF7: =UPPER(FC6)&".del"&TEXT(FC5,"00") -> ITM_COMP_GRP.del38 | FG7: o | FH7: =UPPER(FG6)&".chk"&TEXT(FG5,"00") -> JNL_ACT.chk39 | FI7: o | FJ7: =UPPER(FG6)&".del"&TEXT(FG5,"00") -> JNL_ACT.del39 | FK7: o | FL7: =UPPER(FK6)&".chk"&TEXT(FK5,"00") -> JNL_GRP.chk40 | FM7: o | FN7: =UPPER(FK6)&".del"&TEXT(FK5,"00") -> JNL_GRP.del40 | FO7: o | FP7: =UPPER(FO6)&".chk"&TEXT(FO5,"00") -> JNL_PTN_BASE.chk41 | FQ7: o | FR7: =UPPER(FO6)&".del"&TEXT(FO5,"00") -> JNL_PTN_BASE.del41 | FS7: o | FT7: =UPPER(FS6)&".chk"&TEXT(FS5,"00") -> AUTO_JNL_KEY.chk42 | FU7: o | FV7: =UPPER(FS6)&".del"&TEXT(FS5,"00") -> AUTO_JNL_KEY.del42 | FW7: o | FX7: =UPPER(FW6)&".chk"&TEXT(FW5,"00") -> INSP_PTN.chk43 | FY7: o | FZ7: =UPPER(FW6)&".del"&TEXT(FW5,"00") -> INSP_PTN.del43 | GA7: o | GB7: =UPPER(GA6)&".chk"&TEXT(GA5,"00") -> WK_DAY.chk44 | GC7: o | GD7: =UPPER(GA6)&".del"&TEXT(GA5,"00") -> WK_DAY.del44 | GE7: o | GF7: =UPPER(GE6)&".chk"&TEXT(GE5,"00") -> SHIP_TERM.chk45 | GG7: o | GH7: =UPPER(GE6)&".del"&TEXT(GE5,"00") -> SHIP_TERM.del45 | GI7: o | GJ7: =UPPER(GI6)&".chk"&TEXT(GI5,"00") -> SHIP_WK.chk46 | GK7: o | GL7: =UPPER(GI6)&".del"&TEXT(GI5,"00") -> SHIP_WK.del46 | GM7: o | GN7: =UPPER(GM6)&".chk"&TEXT(GM5,"00") -> RSRC.chk47 | GO7: o | GP7: =UPPER(GM6)&".del"&TEXT(GM5,"00") -> RSRC.del47 | GQ7: o | GR7: =UPPER(GQ6)&".chk"&TEXT(GQ5,"00") -> HS_GRP.chk48 | GS7: o | GT7: =UPPER(GQ6)&".del"&TEXT(GQ5,"00") -> HS_GRP.del48 | GU7: o | GV7: =UPPER(GU6)&".chk"&TEXT(GU5,"00") -> ALC_PTN.chk49 | GW7: o | GX7: =UPPER(GU6)&".del"&TEXT(GU5,"00") -> ALC_PTN.del49 | GY7: o | GZ7: =UPPER(GY6)&".chk"&TEXT(GY5,"00") -> CTG_GRP.chk50 | HA7: o | HB7: =UPPER(GY6)&".del"&TEXT(GY5,"00") -> CTG_GRP.del50 | HC7: o | HD7: =UPPER(HC6)&".chk"&TEXT(HC5,"00") -> ACT_PTN.chk51 | HE7: o | HF7: =UPPER(HC6)&".del"&TEXT(HC5,"00") -> ACT_PTN.del51 | HG7: o | HH7: =UPPER(HG6)&".chk"&TEXT(HG5,"00") -> GP_ALC.chk52 | HI7: o | HJ7: =UPPER(HG6)&".del"&TEXT(HG5,"00") -> GP_ALC.del52 | HK7: o | HL7: =UPPER(HK6)&".chk"&TEXT(HK5,"00") -> CALC_CTG.chk53 | HM7: o | HN7: =UPPER(HK6)&".del"&TEXT(HK5,"00") -> CALC_CTG.del53 | HO7: o | HP7: =UPPER(HO6)&".chk"&TEXT(HO5,"00") -> RPT_PTN.chk54 | HQ7: o | HR7: =UPPER(HO6)&".del"&TEXT(HO5,"00") -> RPT_PTN.del54 | HS7: o | HT7: =UPPER(HS6)&".chk"&TEXT(HS5,"00") -> COST_MENU.chk55 | HU7: o | HV7: =UPPER(HS6)&".del"&TEXT(HS5,"00") -> COST_MENU.del55 | HW7: o | HX7: =UPPER(HW6)&".chk"&TEXT(HW5,"00") -> SITE_CO.chk56 | HY7: o | HZ7: =UPPER(HW6)&".del"&TEXT(HW5,"00") -> SITE_CO.del56
A8: # | D8: ブロック名 Block Name | E8: 型 Type | G8: super/share | H8: 対象ブロック名 Target Block Name | K8: TargetName | L8: ="OPE.MA."&L6&"."&SUBSTITUTE(K6,"_","")&"_DelChk01" -> OPE.MA.MABCL0031.Da_DelChk01 | M8: TargetName | N8: ="OPE.MA."&L6&"."&SUBSTITUTE(K6,"_","")&"_Del01" -> OPE.MA.MABCL0031.Da_Del01 | O8: TargetName | P8: ="OPE.MA."&P6&"."&SUBSTITUTE(O6,"_","")&"_DelChk01" -> OPE.MA.MABCL0031.DptBase_DelChk01 | Q8: TargetName | R8: ="OPE.MA."&P6&"."&SUBSTITUTE(O6,"_","")&"_Del01" -> OPE.MA.MABCL0031.DptBase_Del01 | S8: TargetName | T8: ="OPE.MA."&T6&"."&SUBSTITUTE(S6,"_","")&"_DelChk01" -> OPE.MA.MABCL0031.DptLvl_DelChk01 | U8: TargetName | V8: ="OPE.MA."&T6&"."&SUBSTITUTE(S6,"_","")&"_Del01" -> OPE.MA.MABCL0031.DptLvl_Del01 | W8: TargetName | X8: ="OPE.MA."&X6&"."&SUBSTITUTE(W6,"_","")&"_DelChk01" -> OPE.MA.MABCL0031.AprvRole_DelChk01 | Y8: TargetName | Z8: ="OPE.MA."&X6&"."&SUBSTITUTE(W6,"_","")&"_Del01" -> OPE.MA.MABCL0031.AprvRole_Del01 | AA8: TargetName | AB8: ="OPE.MA."&AB6&"."&SUBSTITUTE(AA6,"_","")&"_DelChk01" -> OPE.MA.MABCL0031.Cntry_DelChk01 | AC8: TargetName | AD8: ="OPE.MA."&AB6&"."&SUBSTITUTE(AA6,"_","")&"_Del01" -> OPE.MA.MABCL0031.Cntry_Del01 | AE8: TargetName | AF8: ="OPE.MA."&AF6&"."&SUBSTITUTE(AE6,"_","")&"_DelChk01" -> OPE.MA.MABCL0031.Area_DelChk01 | AG8: TargetName | AH8: ="OPE.MA."&AF6&"."&SUBSTITUTE(AE6,"_","")&"_Del01" -> OPE.MA.MABCL0031.Area_Del01 | AI8: TargetName | AJ8: ="OPE.MA."&AJ6&"."&SUBSTITUTE(AI6,"_","")&"_DelChk01" -> OPE.MA.MABCL0031.Cur_DelChk01 | AK8: TargetName | AL8: ="OPE.MA."&AJ6&"."&SUBSTITUTE(AI6,"_","")&"_Del01" -> OPE.MA.MABCL0031.Cur_Del01 | AM8: TargetName | AN8: ="OPE.MA."&AN6&"."&SUBSTITUTE(AM6,"_","")&"_DelChk01" -> OPE.MA.MABCL0031.Unit_DelChk01 | AO8: TargetName | AP8: ="OPE.MA."&AN6&"."&SUBSTITUTE(AM6,"_","")&"_Del01" -> OPE.MA.MABCL0031.Unit_Del01 | AQ8: TargetName | AR8: ="OPE.MA."&AR6&"."&SUBSTITUTE(AQ6,"_","")&"_DelChk01" -> OPE.MA.MABCL0031.Bank_DelChk01 | AS8: TargetName | AT8: ="OPE.MA."&AR6&"."&SUBSTITUTE(AQ6,"_","")&"_Del01" -> OPE.MA.MABCL0031.Bank_Del01 | AU8: TargetName | AV8: ="OPE.MA."&AV6&"."&SUBSTITUTE(AU6,"_","")&"_DelChk01" -> OPE.MA.MABCL0031.BankBranch_DelChk01 | AW8: TargetName | AX8: ="OPE.MA."&AV6&"."&SUBSTITUTE(AU6,"_","")&"_Del01" -> OPE.MA.MABCL0031.BankBranch_Del01 | AY8: TargetName | AZ8: ="OPE.MA."&AZ6&"."&SUBSTITUTE(AY6,"_","")&"_DelChk01" -> OPE.MA.MABCL0032.BankAc_DelChk01 | BA8: TargetName | BB8: ="OPE.MA."&AZ6&"."&SUBSTITUTE(AY6,"_","")&"_Del01" -> OPE.MA.MABCL0032.BankAc_Del01 | BC8: TargetName | BD8: ="OPE.MA."&BD6&"."&SUBSTITUTE(BC6,"_","")&"_DelChk01" -> OPE.MA.MABCL0032.Xrate_DelChk01 | BE8: TargetName | BF8: ="OPE.MA."&BD6&"."&SUBSTITUTE(BC6,"_","")&"_Del01" -> OPE.MA.MABCL0032.Xrate_Del01 | BG8: TargetName | BH8: ="OPE.MA."&BH6&"."&SUBSTITUTE(BG6,"_","")&"_DelChk01" -> OPE.MA.MABCL0032.CalBase_DelChk01 | BI8: TargetName | BJ8: ="OPE.MA."&BH6&"."&SUBSTITUTE(BG6,"_","")&"_Del01" -> OPE.MA.MABCL0032.CalBase_Del01 | BK8: TargetName | BL8: ="OPE.MA."&BL6&"."&SUBSTITUTE(BK6,"_","")&"_DelChk01" -> OPE.MA.MABCL0032.ItmJnl_DelChk01 | BM8: TargetName | BN8: ="OPE.MA."&BL6&"."&SUBSTITUTE(BK6,"_","")&"_Del01" -> OPE.MA.MABCL0032.ItmJnl_Del01 | BO8: TargetName | BP8: ="OPE.MA."&BP6&"."&SUBSTITUTE(BO6,"_","")&"_DelChk01" -> OPE.MA.MABCL0032.AcItmGrp_DelChk01 | BQ8: TargetName | BR8: ="OPE.MA."&BP6&"."&SUBSTITUTE(BO6,"_","")&"_Del01" -> OPE.MA.MABCL0032.AcItmGrp_Del01 | BS8: TargetName | BT8: ="OPE.MA."&BT6&"."&SUBSTITUTE(BS6,"_","")&"_DelChk01" -> OPE.MA.MABCL0032.AcRsn_DelChk01 | BU8: TargetName | BV8: ="OPE.MA."&BT6&"."&SUBSTITUTE(BS6,"_","")&"_Del01" -> OPE.MA.MABCL0032.AcRsn_Del01 | BW8: TargetName | BX8: ="OPE.MA."&BX6&"."&SUBSTITUTE(BW6,"_","")&"_DelChk01" -> OPE.MA.MABCL0032.Site_DelChk01 | BY8: TargetName | BZ8: ="OPE.MA."&BX6&"."&SUBSTITUTE(BW6,"_","")&"_Del01" -> OPE.MA.MABCL0032.Site_Del01 | CA8: TargetName | CB8: ="OPE.MA."&CB6&"."&SUBSTITUTE(CA6,"_","")&"_DelChk01" -> OPE.MA.MABCL0032.LocGrp_DelChk01 | CC8: TargetName | CD8: ="OPE.MA."&CB6&"."&SUBSTITUTE(CA6,"_","")&"_Del01" -> OPE.MA.MABCL0032.LocGrp_Del01 | CE8: TargetName | CF8: ="OPE.MA."&CF6&"."&SUBSTITUTE(CE6,"_","")&"_DelChk01" -> OPE.MA.MABCL0032.LgGrp_DelChk01 | CG8: TargetName | CH8: ="OPE.MA."&CF6&"."&SUBSTITUTE(CE6,"_","")&"_Del01" -> OPE.MA.MABCL0032.LgGrp_Del01 | CI8: TargetName | CJ8: ="OPE.MA."&CJ6&"."&SUBSTITUTE(CI6,"_","")&"_DelChk01" -> OPE.MA.MABCL0032.AllocGrp_DelChk01 | CK8: TargetName | CL8: ="OPE.MA."&CJ6&"."&SUBSTITUTE(CI6,"_","")&"_Del01" -> OPE.MA.MABCL0032.AllocGrp_Del01 | CM8: TargetName | CN8: ="OPE.MA."&CN6&"."&SUBSTITUTE(CM6,"_","")&"_DelChk01" -> OPE.MA.MABCL0033.Wg_DelChk01 | CO8: TargetName | CP8: ="OPE.MA."&CN6&"."&SUBSTITUTE(CM6,"_","")&"_Del01" -> OPE.MA.MABCL0033.Wg_Del01 | CQ8: TargetName | CR8: ="OPE.MA."&CR6&"."&SUBSTITUTE(CQ6,"_","")&"_DelChk01" -> OPE.MA.MABCL0033.Oper_DelChk01 | CS8: TargetName | CT8: ="OPE.MA."&CR6&"."&SUBSTITUTE(CQ6,"_","")&"_Del01" -> OPE.MA.MABCL0033.Oper_Del01 | CU8: TargetName | CV8: ="OPE.MA."&CV6&"."&SUBSTITUTE(CU6,"_","")&"_DelChk01" -> OPE.MA.MABCL0033.WkCost_DelChk01 | CW8: TargetName | CX8: ="OPE.MA."&CV6&"."&SUBSTITUTE(CU6,"_","")&"_Del01" -> OPE.MA.MABCL0033.WkCost_Del01 | CY8: TargetName | CZ8: ="OPE.MA."&CZ6&"."&SUBSTITUTE(CY6,"_","")&"_DelChk01" -> OPE.MA.MABCL0033.WkRsn_DelChk01 | DA8: TargetName | DB8: ="OPE.MA."&CZ6&"."&SUBSTITUTE(CY6,"_","")&"_Del01" -> OPE.MA.MABCL0033.WkRsn_Del01 | DC8: TargetName | DD8: ="OPE.MA."&DD6&"."&SUBSTITUTE(DC6,"_","")&"_DelChk01" -> OPE.MA.MABCL0033.SlsUpriGrp_DelChk01 | DE8: TargetName | DF8: ="OPE.MA."&DD6&"."&SUBSTITUTE(DC6,"_","")&"_Del01" -> OPE.MA.MABCL0033.SlsUpriGrp_Del01 | DG8: TargetName | DH8: ="OPE.MA."&DH6&"."&SUBSTITUTE(DG6,"_","")&"_DelChk01" -> OPE.MA.MABCL0033.SlsUpriRank_DelChk01 | DI8: TargetName | DJ8: ="OPE.MA."&DH6&"."&SUBSTITUTE(DG6,"_","")&"_Del01" -> OPE.MA.MABCL0033.SlsUpriRank_Del01 | DK8: TargetName | DL8: ="OPE.MA."&DL6&"."&SUBSTITUTE(DK6,"_","")&"_DelChk01" -> OPE.MA.MABCL0033.SetoffGrp_DelChk01 | DM8: TargetName | DN8: ="OPE.MA."&DL6&"."&SUBSTITUTE(DK6,"_","")&"_Del01" -> OPE.MA.MABCL0033.SetoffGrp_Del01 | DO8: TargetName | DP8: ="OPE.MA."&DP6&"."&SUBSTITUTE(DO6,"_","")&"_DelChk01" -> OPE.MA.MABCL0033.ShipValid_DelChk01 | DQ8: TargetName | DR8: ="OPE.MA."&DP6&"."&SUBSTITUTE(DO6,"_","")&"_Del01" -> OPE.MA.MABCL0033.ShipValid_Del01 | DS8: TargetName | DT8: ="OPE.MA."&DT6&"."&SUBSTITUTE(DS6,"_","")&"_DelChk01" -> OPE.MA.MABCL0033.ItmShipGrp_DelChk01 | DU8: TargetName | DV8: ="OPE.MA."&DT6&"."&SUBSTITUTE(DS6,"_","")&"_Del01" -> OPE.MA.MABCL0033.ItmShipGrp_Del01 | DW8: TargetName | DX8: ="OPE.MA."&DX6&"."&SUBSTITUTE(DW6,"_","")&"_DelChk01" -> OPE.MA.MABCL0033.Trnspt_DelChk01 | DY8: TargetName | DZ8: ="OPE.MA."&DX6&"."&SUBSTITUTE(DW6,"_","")&"_Del01" -> OPE.MA.MABCL0033.Trnspt_Del01 | EA8: TargetName | EB8: ="OPE.MA."&EB6&"."&SUBSTITUTE(EA6,"_","")&"_DelChk01" -> OPE.MA.MABCL0034.ExCntnr_DelChk01 | EC8: TargetName | ED8: ="OPE.MA."&EB6&"."&SUBSTITUTE(EA6,"_","")&"_Del01" -> OPE.MA.MABCL0034.ExCntnr_Del01 | EE8: TargetName | EF8: ="OPE.MA."&EF6&"."&SUBSTITUTE(EE6,"_","")&"_DelChk01" -> OPE.MA.MABCL0034.EximPort_DelChk01 | EG8: TargetName | EH8: ="OPE.MA."&EF6&"."&SUBSTITUTE(EE6,"_","")&"_Del01" -> OPE.MA.MABCL0034.EximPort_Del01 | EI8: TargetName | EJ8: ="OPE.MA."&EJ6&"."&SUBSTITUTE(EI6,"_","")&"_DelChk01" -> OPE.MA.MABCL0034.StkGd_DelChk01 | EK8: TargetName | EL8: ="OPE.MA."&EJ6&"."&SUBSTITUTE(EI6,"_","")&"_Del01" -> OPE.MA.MABCL0034.StkGd_Del01 | EM8: TargetName | EN8: ="OPE.MA."&EN6&"."&SUBSTITUTE(EM6,"_","")&"_DelChk01" -> OPE.MA.MABCL0034.Trd_DelChk01 | EO8: TargetName | EP8: ="OPE.MA."&EN6&"."&SUBSTITUTE(EM6,"_","")&"_Del01" -> OPE.MA.MABCL0034.Trd_Del01 | EQ8: TargetName | ER8: ="OPE.MA."&ER6&"."&SUBSTITUTE(EQ6,"_","")&"_DelChk01" -> OPE.MA.MABCL0034.SlipForm_DelChk01 | ES8: TargetName | ET8: ="OPE.MA."&ER6&"."&SUBSTITUTE(EQ6,"_","")&"_Del01" -> OPE.MA.MABCL0034.SlipForm_Del01 | EU8: TargetName | EV8: ="OPE.MA."&EV6&"."&SUBSTITUTE(EU6,"_","")&"_DelChk01" -> OPE.MA.MABCL0034.PfGrp_DelChk01 | EW8: TargetName | EX8: ="OPE.MA."&EV6&"."&SUBSTITUTE(EU6,"_","")&"_Del01" -> OPE.MA.MABCL0034.PfGrp_Del01 | EY8: TargetName | EZ8: ="OPE.MA."&EZ6&"."&SUBSTITUTE(EY6,"_","")&"_DelChk01" -> OPE.MA.MABCL0034.ItmSpecGrp_DelChk01 | FA8: TargetName | FB8: ="OPE.MA."&EZ6&"."&SUBSTITUTE(EY6,"_","")&"_Del01" -> OPE.MA.MABCL0034.ItmSpecGrp_Del01 | FC8: TargetName | FD8: ="OPE.MA."&FD6&"."&SUBSTITUTE(FC6,"_","")&"_DelChk01" -> OPE.MA.MABCL0034.ItmCompGrp_DelChk01 | FE8: TargetName | FF8: ="OPE.MA."&FD6&"."&SUBSTITUTE(FC6,"_","")&"_Del01" -> OPE.MA.MABCL0034.ItmCompGrp_Del01 | FG8: TargetName | FH8: ="OPE.MA."&FH6&"."&SUBSTITUTE(FG6,"_","")&"_DelChk01" -> OPE.MA.MABCL0034.JnlAct_DelChk01 | FI8: TargetName | FJ8: ="OPE.MA."&FH6&"."&SUBSTITUTE(FG6,"_","")&"_Del01" -> OPE.MA.MABCL0034.JnlAct_Del01 | FK8: TargetName | FL8: ="OPE.MA."&FL6&"."&SUBSTITUTE(FK6,"_","")&"_DelChk01" -> OPE.MA.MABCL0034.JnlGrp_DelChk01 | FM8: TargetName | FN8: ="OPE.MA."&FL6&"."&SUBSTITUTE(FK6,"_","")&"_Del01" -> OPE.MA.MABCL0034.JnlGrp_Del01 | FO8: TargetName | FP8: ="OPE.MA."&FP6&"."&SUBSTITUTE(FO6,"_","")&"_DelChk01" -> OPE.MA.MABCL0035.JnlPtnBase_DelChk01 | FQ8: TargetName | FR8: ="OPE.MA."&FP6&"."&SUBSTITUTE(FO6,"_","")&"_Del01" -> OPE.MA.MABCL0035.JnlPtnBase_Del01 | FS8: TargetName | FT8: ="OPE.MA."&FT6&"."&SUBSTITUTE(FS6,"_","")&"_DelChk01" -> OPE.MA.MABCL0035.AutoJnlKey_DelChk01 | FU8: TargetName | FV8: ="OPE.MA."&FT6&"."&SUBSTITUTE(FS6,"_","")&"_Del01" -> OPE.MA.MABCL0035.AutoJnlKey_Del01 | FW8: TargetName | FX8: ="OPE.MA."&FX6&"."&SUBSTITUTE(FW6,"_","")&"_DelChk01" -> OPE.MA.MABCL0035.InspPtn_DelChk01 | FY8: TargetName | FZ8: ="OPE.MA."&FX6&"."&SUBSTITUTE(FW6,"_","")&"_Del01" -> OPE.MA.MABCL0035.InspPtn_Del01 | GA8: TargetName | GB8: ="OPE.MA."&GB6&"."&SUBSTITUTE(GA6,"_","")&"_DelChk01" -> OPE.MA.MABCL0035.WkDay_DelChk01 | GC8: TargetName | GD8: ="OPE.MA."&GB6&"."&SUBSTITUTE(GA6,"_","")&"_Del01" -> OPE.MA.MABCL0035.WkDay_Del01 | GE8: TargetName | GF8: ="OPE.MA."&GF6&"."&SUBSTITUTE(GE6,"_","")&"_DelChk01" -> OPE.MA.MABCL0035.ShipTerm_DelChk01 | GG8: TargetName | GH8: ="OPE.MA."&GF6&"."&SUBSTITUTE(GE6,"_","")&"_Del01" -> OPE.MA.MABCL0035.ShipTerm_Del01 | GI8: TargetName | GJ8: ="OPE.MA."&GJ6&"."&SUBSTITUTE(GI6,"_","")&"_DelChk01" -> OPE.MA.MABCL0035.ShipWk_DelChk01 | GK8: TargetName | GL8: ="OPE.MA."&GJ6&"."&SUBSTITUTE(GI6,"_","")&"_Del01" -> OPE.MA.MABCL0035.ShipWk_Del01 | GM8: TargetName | GN8: ="OPE.MA."&GN6&"."&SUBSTITUTE(GM6,"_","")&"_DelChk01" -> OPE.MA.MABCL0035.Rsrc_DelChk01 | GO8: TargetName | GP8: ="OPE.MA."&GN6&"."&SUBSTITUTE(GM6,"_","")&"_Del01" -> OPE.MA.MABCL0035.Rsrc_Del01 | GQ8: TargetName | GR8: ="OPE.MA."&GR6&"."&SUBSTITUTE(GQ6,"_","")&"_DelChk01" -> OPE.MA.MABCL0035.HsGrp_DelChk01 | GS8: TargetName | GT8: ="OPE.MA."&GR6&"."&SUBSTITUTE(GQ6,"_","")&"_Del01" -> OPE.MA.MABCL0035.HsGrp_Del01 | GU8: TargetName | GV8: ="OPE.MA."&GV6&"."&SUBSTITUTE(GU6,"_","")&"_DelChk01" -> OPE.MA.MABCL0035.AlcPtn_DelChk01 | GW8: TargetName | GX8: ="OPE.MA."&GV6&"."&SUBSTITUTE(GU6,"_","")&"_Del01" -> OPE.MA.MABCL0035.AlcPtn_Del01 | GY8: TargetName | GZ8: ="OPE.MA."&GZ6&"."&SUBSTITUTE(GY6,"_","")&"_DelChk01" -> OPE.MA.MABCL0035.CtgGrp_DelChk01 | HA8: TargetName | HB8: ="OPE.MA."&GZ6&"."&SUBSTITUTE(GY6,"_","")&"_Del01" -> OPE.MA.MABCL0035.CtgGrp_Del01 | HC8: TargetName | HD8: ="OPE.MA."&HD6&"."&SUBSTITUTE(HC6,"_","")&"_DelChk01" -> OPE.MA.MABCL0035.ActPtn_DelChk01 | HE8: TargetName | HF8: ="OPE.MA."&HD6&"."&SUBSTITUTE(HC6,"_","")&"_Del01" -> OPE.MA.MABCL0035.ActPtn_Del01 | HG8: TargetName | HH8: ="OPE.MA."&HH6&"."&SUBSTITUTE(HG6,"_","")&"_DelChk01" -> OPE.MA.MABCL0036.GpAlc_DelChk01 | HI8: TargetName | HJ8: ="OPE.MA."&HH6&"."&SUBSTITUTE(HG6,"_","")&"_Del01" -> OPE.MA.MABCL0036.GpAlc_Del01 | HK8: TargetName | HL8: ="OPE.MA."&HL6&"."&SUBSTITUTE(HK6,"_","")&"_DelChk01" -> OPE.MA.MABCL0036.CalcCtg_DelChk01 | HM8: TargetName | HN8: ="OPE.MA."&HL6&"."&SUBSTITUTE(HK6,"_","")&"_Del01" -> OPE.MA.MABCL0036.CalcCtg_Del01 | HO8: TargetName | HP8: ="OPE.MA."&HP6&"."&SUBSTITUTE(HO6,"_","")&"_DelChk01" -> OPE.MA.MABCL0036.RptPtn_DelChk01 | HQ8: TargetName | HR8: ="OPE.MA."&HP6&"."&SUBSTITUTE(HO6,"_","")&"_Del01" -> OPE.MA.MABCL0036.RptPtn_Del01 | HS8: TargetName | HT8: ="OPE.MA."&HT6&"."&SUBSTITUTE(HS6,"_","")&"_DelChk01" -> OPE.MA.MABCL0036.CostMenu_DelChk01 | HU8: TargetName | HV8: ="OPE.MA."&HT6&"."&SUBSTITUTE(HS6,"_","")&"_Del01" -> OPE.MA.MABCL0036.CostMenu_Del01 | HW8: TargetName | HX8: ="OPE.MA."&HX6&"."&SUBSTITUTE(HW6,"_","")&"_DelChk01" -> OPE.MA.MABCL0036.SiteCo_DelChk01 | HY8: TargetName | HZ8: ="OPE.MA."&HX6&"."&SUBSTITUTE(HW6,"_","")&"_Del01" -> OPE.MA.MABCL0036.SiteCo_Del01 | IC8: ブロック備考 Block Remarks
A9: # | D9: 項目名 Field Name | E9: 型 Type | F9: 桁 Digits | G9: フルネーム Full Name | H9: 日本語名 Japanese Name | I9: 上り項目 Request Message Field | J9: 下り項目 Response Message Field | IA9: 条件および編集方法 Conditions and Editing Methods | IC9: 項目備考 Field Remarks
A10: # | K10: 上り項目 Request Message Field | L10: 下り項目 Response Message Field | M10: 上り項目 Request Message Field | N10: 下り項目 Response Message Field | O10: 上り項目 Request Message Field | P10: 下り項目 Response Message Field | Q10: 上り項目 Request Message Field | R10: 下り項目 Response Message Field | S10: 上り項目 Request Message Field | T10: 下り項目 Response Message Field | U10: 上り項目 Request Message Field | V10: 下り項目 Response Message Field | W10: 上り項目 Request Message Field | X10: 下り項目 Response Message Field | Y10: 上り項目 Request Message Field | Z10: 下り項目 Response Message Field | AA10: 上り項目 Request Message Field | AB10: 下り項目 Response Message Field | AC10: 上り項目 Request Message Field | AD10: 下り項目 Response Message Field | AE10: 上り項目 Request Message Field | AF10: 下り項目 Response Message Field | AG10: 上り項目 Request Message Field | AH10: 下り項目 Response Message Field | AI10: 上り項目 Request Message Field | AJ10: 下り項目 Response Message Field | AK10: 上り項目 Request Message Field | AL10: 下り項目 Response Message Field | AM10: 上り項目 Request Message Field | AN10: 下り項目 Response Message Field | AO10: 上り項目 Request Message Field | AP10: 下り項目 Response Message Field | AQ10: 上り項目 Request Message Field | AR10: 下り項目 Response Message Field | AS10: 上り項目 Request Message Field | AT10: 下り項目 Response Message Field | AU10: 上り項目 Request Message Field | AV10: 下り項目 Response Message Field | AW10: 上り項目 Request Message Field | AX10: 下り項目 Response Message Field | AY10: 上り項目 Request Message Field | AZ10: 下り項目 Response Message Field | BA10: 上り項目 Request Message Field | BB10: 下り項目 Response Message Field | BC10: 上り項目 Request Message Field | BD10: 下り項目 Response Message Field | BE10: 上り項目 Request Message Field | BF10: 下り項目 Response Message Field | BG10: 上り項目 Request Message Field | BH10: 下り項目 Response Message Field | BI10: 上り項目 Request Message Field | BJ10: 下り項目 Response Message Field | BK10: 上り項目 Request Message Field | BL10: 下り項目 Response Message Field | BM10: 上り項目 Request Message Field | BN10: 下り項目 Response Message Field | BO10: 上り項目 Request Message Field | BP10: 下り項目 Response Message Field | BQ10: 上り項目 Request Message Field | BR10: 下り項目 Response Message Field | BS10: 上り項目 Request Message Field | BT10: 下り項目 Response Message Field | BU10: 上り項目 Request Message Field | BV10: 下り項目 Response Message Field | BW10: 上り項目 Request Message Field | BX10: 下り項目 Response Message Field | BY10: 上り項目 Request Message Field | BZ10: 下り項目 Response Message Field | CA10: 上り項目 Request Message Field | CB10: 下り項目 Response Message Field | CC10: 上り項目 Request Message Field | CD10: 下り項目 Response Message Field | CE10: 上り項目 Request Message Field | CF10: 下り項目 Response Message Field | CG10: 上り項目 Request Message Field | CH10: 下り項目 Response Message Field | CI10: 上り項目 Request Message Field | CJ10: 下り項目 Response Message Field | CK10: 上り項目 Request Message Field | CL10: 下り項目 Response Message Field | CM10: 上り項目 Request Message Field | CN10: 下り項目 Response Message Field | CO10: 上り項目 Request Message Field | CP10: 下り項目 Response Message Field | CQ10: 上り項目 Request Message Field | CR10: 下り項目 Response Message Field | CS10: 上り項目 Request Message Field | CT10: 下り項目 Response Message Field | CU10: 上り項目 Request Message Field | CV10: 下り項目 Response Message Field | CW10: 上り項目 Request Message Field | CX10: 下り項目 Response Message Field | CY10: 上り項目 Request Message Field | CZ10: 下り項目 Response Message Field | DA10: 上り項目 Request Message Field | DB10: 下り項目 Response Message Field | DC10: 上り項目 Request Message Field | DD10: 下り項目 Response Message Field | DE10: 上り項目 Request Message Field | DF10: 下り項目 Response Message Field | DG10: 上り項目 Request Message Field | DH10: 下り項目 Response Message Field | DI10: 上り項目 Request Message Field | DJ10: 下り項目 Response Message Field | DK10: 上り項目 Request Message Field | DL10: 下り項目 Response Message Field | DM10: 上り項目 Request Message Field | DN10: 下り項目 Response Message Field | DO10: 上り項目 Request Message Field | DP10: 下り項目 Response Message Field | DQ10: 上り項目 Request Message Field | DR10: 下り項目 Response Message Field | DS10: 上り項目 Request Message Field | DT10: 下り項目 Response Message Field | DU10: 上り項目 Request Message Field | DV10: 下り項目 Response Message Field | DW10: 上り項目 Request Message Field | DX10: 下り項目 Response Message Field | DY10: 上り項目 Request Message Field | DZ10: 下り項目 Response Message Field | EA10: 上り項目 Request Message Field | EB10: 下り項目 Response Message Field | EC10: 上り項目 Request Message Field | ED10: 下り項目 Response Message Field | EE10: 上り項目 Request Message Field | EF10: 下り項目 Response Message Field | EG10: 上り項目 Request Message Field | EH10: 下り項目 Response Message Field | EI10: 上り項目 Request Message Field | EJ10: 下り項目 Response Message Field | EK10: 上り項目 Request Message Field | EL10: 下り項目 Response Message Field | EM10: 上り項目 Request Message Field | EN10: 下り項目 Response Message Field | EO10: 上り項目 Request Message Field | EP10: 下り項目 Response Message Field | EQ10: 上り項目 Request Message Field | ER10: 下り項目 Response Message Field | ES10: 上り項目 Request Message Field | ET10: 下り項目 Response Message Field | EU10: 上り項目 Request Message Field | EV10: 下り項目 Response Message Field | EW10: 上り項目 Request Message Field | EX10: 下り項目 Response Message Field | EY10: 上り項目 Request Message Field | EZ10: 下り項目 Response Message Field | FA10: 上り項目 Request Message Field | FB10: 下り項目 Response Message Field | FC10: 上り項目 Request Message Field | FD10: 下り項目 Response Message Field | FE10: 上り項目 Request Message Field | FF10: 下り項目 Response Message Field | FG10: 上り項目 Request Message Field | FH10: 下り項目 Response Message Field | FI10: 上り項目 Request Message Field | FJ10: 下り項目 Response Message Field | FK10: 上り項目 Request Message Field | FL10: 下り項目 Response Message Field | FM10: 上り項目 Request Message Field | FN10: 下り項目 Response Message Field | FO10: 上り項目 Request Message Field | FP10: 下り項目 Response Message Field | FQ10: 上り項目 Request Message Field | FR10: 下り項目 Response Message Field | FS10: 上り項目 Request Message Field | FT10: 下り項目 Response Message Field | FU10: 上り項目 Request Message Field | FV10: 下り項目 Response Message Field | FW10: 上り項目 Request Message Field | FX10: 下り項目 Response Message Field | FY10: 上り項目 Request Message Field | FZ10: 下り項目 Response Message Field | GA10: 上り項目 Request Message Field | GB10: 下り項目 Response Message Field | GC10: 上り項目 Request Message Field | GD10: 下り項目 Response Message Field | GE10: 上り項目 Request Message Field | GF10: 下り項目 Response Message Field | GG10: 上り項目 Request Message Field | GH10: 下り項目 Response Message Field | GI10: 上り項目 Request Message Field | GJ10: 下り項目 Response Message Field | GK10: 上り項目 Request Message Field | GL10: 下り項目 Response Message Field | GM10: 上り項目 Request Message Field | GN10: 下り項目 Response Message Field | GO10: 上り項目 Request Message Field | GP10: 下り項目 Response Message Field | GQ10: 上り項目 Request Message Field | GR10: 下り項目 Response Message Field | GS10: 上り項目 Request Message Field | GT10: 下り項目 Response Message Field | GU10: 上り項目 Request Message Field | GV10: 下り項目 Response Message Field | GW10: 上り項目 Request Message Field | GX10: 下り項目 Response Message Field | GY10: 上り項目 Request Message Field | GZ10: 下り項目 Response Message Field | HA10: 上り項目 Request Message Field | HB10: 下り項目 Response Message Field | HC10: 上り項目 Request Message Field | HD10: 下り項目 Response Message Field | HE10: 上り項目 Request Message Field | HF10: 下り項目 Response Message Field | HG10: 上り項目 Request Message Field | HH10: 下り項目 Response Message Field | HI10: 上り項目 Request Message Field | HJ10: 下り項目 Response Message Field | HK10: 上り項目 Request Message Field | HL10: 下り項目 Response Message Field | HM10: 上り項目 Request Message Field | HN10: 下り項目 Response Message Field | HO10: 上り項目 Request Message Field | HP10: 下り項目 Response Message Field | HQ10: 上り項目 Request Message Field | HR10: 下り項目 Response Message Field | HS10: 上り項目 Request Message Field | HT10: 下り項目 Response Message Field | HU10: 上り項目 Request Message Field | HV10: 下り項目 Response Message Field | HW10: 上り項目 Request Message Field | HX10: 下り項目 Response Message Field | HY10: 上り項目 Request Message Field | HZ10: 下り項目 Response Message Field
A11: 10 | B11: * | D11: Del01_Dtl1 | E11: L | K11: Da_DelChk01_Dtl | M11: Da_Del01_Dtl | O11: DptBase_DelChk01_Dtl | Q11: DptBase_Del01_Dtl | S11: DptLvl_DelChk01_Dtl | U11: DptLvl_Del01_Dtl | W11: AprvRole_DelChk01_Dtl | Y11: AprvRole_Del01_Dtl | AA11: Cntry_DelChk01_Dtl | AC11: Cntry_Del01_Dtl | AE11: Area_DelChk01_Dtl | AG11: Area_Del01_Dtl | AI11: Cur_DelChk01_Dtl | AK11: Cur_Del01_Dtl | AM11: Unit_DelChk01_Dtl | AO11: Unit_Del01_Dtl | AQ11: Bank_DelChk01_Dtl | AS11: Bank_Del01_Dtl | AU11: BankBranch_DelChk01_Dtl | AW11: BankBranch_Del01_Dtl | AY11: BankAc_DelChk01_Dtl | BA11: BankAc_Del01_Dtl | BC11: Xrate_DelChk01_Dtl | BE11: Xrate_Del01_Dtl | BG11: CalBase_DelChk01_Dtl | BI11: CalBase_Del01_Dtl | BK11: ItmJnl_DelChk01_Dtl | BM11: ItmJnl_Del01_Dtl | BO11: AcItmGrp_DelChk01_Dtl | BQ11: AcItmGrp_Del01_Dtl | BS11: AcRsn_DelChk01_Dtl | BU11: AcRsn_Del01_Dtl | BW11: Site_DelChk01_Dtl | BY11: Site_Del01_Dtl | CA11: LocGrp_DelChk01_Dtl | CC11: LocGrp_Del01_Dtl | CE11: LgGrp_DelChk01_Dtl | CG11: LgGrp_Del01_Dtl | CI11: AllocGrp_DelChk01_Dtl | CK11: AllocGrp_Del01_Dtl | CM11: Wg_DelChk01_Dtl | CO11: Wg_Del01_Dtl | CQ11: Oper_DelChk01_Dtl | CS11: Oper_Del01_Dtl | CU11: WkCost_DelChk01_Dtl | CW11: WkCost_Del01_Dtl | CY11: WkRsn_DelChk01_Dtl | DA11: WkRsn_Del01_Dtl | DC11: SlsUpriGrp_DelChk01_Dtl | DE11: SlsUpriGrp_Del01_Dtl | DG11: SlsUpriRank_DelChk01_Dtl | DI11: SlsUpriRank_Del01_Dtl | DK11: SetoffGrp_DelChk01_Dtl | DM11: SetoffGrp_Del01_Dtl | DO11: ShipValid_DelChk01_Dtl | DQ11: ShipValid_Del01_Dtl | DS11: ItmShipGrp_DelChk01_Dtl | DU11: ItmShipGrp_Del01_Dtl | DW11: Trnspt_DelChk01_Dtl | DY11: Trnspt_Del01_Dtl | EA11: ExCntnr_DelChk01_Dtl | EC11: ExCntnr_Del01_Dtl | EE11: EximPort_DelChk01_Dtl | EG11: EximPort_Del01_Dtl | EI11: StkGd_DelChk01_Dtl | EK11: StkGd_Del01_Dtl | EM11: Trd_DelChk01_Dtl | EO11: Trd_Del01_Dtl | EQ11: SlipForm_DelChk01_Dtl | ES11: SlipForm_Del01_Dtl | EU11: PfGrp_DelChk01_Dtl | EW11: PfGrp_Del01_Dtl | EY11: ItmSpecGrp_DelChk01_Dtl | FA11: ItmSpecGrp_Del01_Dtl | FC11: ItmCompGrp_DelChk01_Dtl | FE11: ItmCompGrp_Del01_Dtl | FG11: JnlAct_DelChk01_Dtl | FI11: JnlAct_Del01_Dtl | FK11: JnlGrp_DelChk01_Dtl | FM11: JnlGrp_Del01_Dtl | FO11: JnlPtnBase_DelChk01_Dtl | FQ11: JnlPtnBase_Del01_Dtl | FS11: AutoJnlKey_DelChk01_Dtl | FU11: AutoJnlKey_Del01_Dtl | FW11: InspPtn_DelChk01_Dtl | FY11: InspPtn_Del01_Dtl | GA11: WkDay_DelChk01_Dtl | GC11: WkDay_Del01_Dtl | GE11: ShipTerm_DelChk01_Dtl | GG11: ShipTerm_Del01_Dtl | GI11: ShipWk_DelChk01_Dtl | GK11: ShipWk_Del01_Dtl | GM11: Rsrc_DelChk01_Dtl | GO11: Rsrc_Del01_Dtl | GQ11: HsGrp_DelChk01_Dtl | GS11: HsGrp_Del01_Dtl | GU11: AlcPtn_DelChk01_Dtl | GW11: AlcPtn_Del01_Dtl | GY11: CtgGrp_DelChk01_Dtl | HA11: CtgGrp_Del01_Dtl | HC11: ActPtn_DelChk01_Dtl | HE11: ActPtn_Del01_Dtl | HG11: GpAlc_DelChk01_Dtl | HI11: GpAlc_Del01_Dtl | HK11: CalcCtg_DelChk01_Dtl | HM11: CalcCtg_Del01_Dtl | HO11: RptPtn_DelChk01_Dtl | HQ11: RptPtn_Del01_Dtl | HS11: CostMenu_DelChk01_Dtl | HU11: CostMenu_Del01_Dtl | HW11: SiteCo_DelChk01_Dtl | HY11: SiteCo_Del01_Dtl
A12: 10 | D12: da_cd | E12: #MA.DA_CD | G12: Data access cd. | H12: データアクセスＣＤ | I12: E | K12: E | M12: E
A13: 10 | D13: dpt_cd | E13: #MA.DPT_CD | G13: Dept. cd. | H13: 部門ＣＤ | I13: E | O13: E | Q13: E
A14: 10 | D14: dpt_lvl_cd | E14: #MA.DPT_LVL_CD | G14: Dept. hierarchy cd. | H14: 部門階層ＣＤ | I14: E | S14: E | U14: E
A15: 10 | D15: aprv_role_cd | E15: #MA.APRV_ROLE_CD | G15: Approval role cd. | H15: 承認役割ＣＤ | I15: E | W15: E | Y15: E
A16: 10 | D16: cntry_cd | E16: #MA.CNTRY_CD | G16: Country cd. | H16: 国ＣＤ | I16: E | AA16: E | AC16: E
A17: 10 | D17: area_cd | E17: #MA.AREA_CD | G17: Region cd. | H17: 地域ＣＤ | I17: E | AE17: E | AG17: E
A18: 10 | D18: cur_cd | E18: #MA.CUR_CD | G18: Currency cd. | H18: 通貨ＣＤ | I18: E | AI18: E | AK18: E
A19: 10 | D19: unit_cd | E19: #MA.UNIT_CD | G19: Unit cd. | H19: 単位ＣＤ | I19: E | AM19: E | AO19: E
A20: 10 | D20: bank_cd | E20: #MA.BANK_CD | G20: Bank cd. | H20: 銀行ＣＤ | I20: E | AQ20: E | AS20: E
A21: 10 | D21: bank_branch_bank_cd | E21: #MA.BANK_CD | G21: Bank cd. | H21: 銀行ＣＤ | I21: E | AU21: bank_cd | AW21: bank_cd
A22: 10 | D22: branch_cd | E22: #MA.BANK_BRANCH_CD | G22: Bank branch cd. | H22: 銀行支店ＣＤ | I22: E | AU22: E | AW22: E
A23: 10 | D23: bank_ac_cd | E23: #MA.BANK_AC_CD | G23: Bank account cd. | H23: 口座ＣＤ | I23: E | AY23: E | BA23: E
A24: 10 | D24: xrate_cd | E24: #MA.XRATE_CD | G24: Exchange rate cd. | H24: 為替レートＣＤ | I24: E | BC24: E | BE24: E
A25: 10 | D25: cal_cd | E25: #MA.CAL_CD | G25: Calendar cd. | H25: カレンダＣＤ | I25: E | BG25: E | BI25: E
A26: 10 | D26: itm_jnl_cd | E26: #MA.ITM_JNL_CD | G26: Item journal cd. | H26: 品目仕訳ＣＤ | I26: E | BK26: E | BM26: E
A27: 10 | D27: ac_itm_grp_cd | E27: #MA.AC_ITM_GRP_CD | G27: Accounting item classification cd. | H27: 会計品目分類ＣＤ | I27: E | BO27: E | BQ27: E
A28: 10 | D28: ac_rsn_cd | E28: #MA.AC_RSN_CD | G28: Accounting reason cd. | H28: 会計理由ＣＤ | I28: E | BS28: E | BU28: E
A29: 10 | D29: site_cd | E29: #MA.SITE_CD | G29: Factory/Distribution warehouse cd. | H29: 工場・物流倉庫ＣＤ | I29: E | BW29: E | BY29: E
A30: 10 | D30: loc_grp_cd | E30: #MA.LOC_GRP_CD | G30: Mfg. location group cd. | H30: 製造場所グループＣＤ | I30: E | CA30: E | CC30: E
A31: 10 | D31: lg_grp_cd | E31: #MA.LG_GRP_CD | G31: Distribution group cd. | H31: 物流グループＣＤ | I31: E | CE31: E | CG31: E
A32: 10 | D32: alloc_grp_cd | E32: #MA.ALLOC_GRP_CD | G32: Gross allocation location group cd. | H32: 総量引当場所グループＣＤ | I32: E | CI32: E | CK32: E
A33: 10 | D33: wg_cd | E33: #MA.WG_CD | G33: WG cd. | H33: ワーキンググループＣＤ | I33: E | CM33: E | CO33: E
A34: 10 | D34: oper_cd | E34: #MA.OPER_CD | G34: Operation cd. | H34: 工程ＣＤ | I34: E | CQ34: E | CS34: E
A35: 10 | D35: wk_cost_cd | E35: #MA.WK_COST_CD | G35: Work element cd. | H35: 工数管理ＣＤ | I35: E | CU35: E | CW35: E
A36: 10 | D36: wk_rsn_cd | E36: #MA.WK_RSN_CD | G36: Man-hour reason cd. | H36: 工数理由ＣＤ | I36: E | CY36: E | DA36: E
A37: 10 | D37: sls_upri_grp_cd | E37: #MA.SLS_UPRI_GRP_CD | G37: Sales unit price classification cd. | H37: 販売単価分類ＣＤ | I37: E | DC37: E | DE37: E
A38: 10 | D38: sls_upri_rank_cd | E38: #MA.SLS_UPRI_RANK_CD | G38: Sales unit price rank cd. | H38: 販売単価ランクＣＤ | I38: E | DG38: E | DI38: E
A39: 10 | D39: setoff_grp_cd | E39: #MA.SETOFF_GRP_CD | G39: Offset group cd. | H39: 相殺グループＣＤ | I39: E | DK39: E | DM39: E
A40: 10 | D40: ship_valid_grp_cd | E40: #MA.SHIP_VALID_GRP_CD | G40: Shipping expiration date group cd. | H40: 出荷有効期限グループＣＤ | I40: E | DO40: E | DQ40: E
A41: 10 | D41: itm_ship_grp_cd | E41: #MA.ITM_SHIP_GRP_CD | G41: Item shipping group cd. | H41: 品目出荷グループＣＤ | I41: E | DS41: E | DU41: E
A42: 10 | D42: trnspt_cd | E42: #MA.TRNSPT_CD | G42: Transportation method cd. | H42: 輸送方法ＣＤ | I42: E | DW42: E | DY42: E
A43: 10 | D43: cntnr_cd | E43: #MA.CNTNR_CD | G43: Export packing container cd. | H43: 輸出梱包容器ＣＤ | I43: E | EA43: E | EC43: E
A44: 10 | D44: port_cd | E44: #MA.PORT_CD | G44: Harbor cd. | H44: 港ＣＤ | I44: E | EE44: E | EG44: E
A45: 10 | D45: gd_cd | E45: #MA.STK_GD_CD | G45: Grading cd. | H45: 格付ＣＤ | I45: E | EI45: E | EK45: E
A46: 10 | D46: trd_cd | E46: #MA.TRD_CD | G46: Transaction cd. | H46: 取引ＣＤ | I46: E | EM46: E | EO46: E
A47: 10 | D47: slip_form_cd | E47: #MA.SLIP_FORM_CD | G47: Slip report cd. | H47: 伝票帳票ＣＤ | I47: E | EQ47: E | ES47: E
A48: 10 | D48: pf_grp_cd | E48: #MA.PF_GRP_CD | G48: Purchase forecast group cd. | H48: 購買内示グループＣＤ | I48: E | EU48: E | EW48: E
A49: 10 | D49: itm_spec_grp_cd | E49: #MA.ITM_SPEC_GRP_CD | G49: Item specification classification cd. | H49: 品目仕様分類ＣＤ | I49: E | EY49: E | FA49: E
A50: 10 | D50: itm_comp_grp_cd | E50: #MA.ITM_COMP_GRP_CD | G50: Item configuration group cd. | H50: 品目構成グループＣＤ | I50: E | FC50: E | FE50: E
A51: 10 | D51: jnl_act_cd | E51: #MA.JNL_ACT_CD | G51: Journalizing cd. | H51: 仕訳実行ＣＤ | I51: E | FG51: E | FI51: E
A52: 10 | D52: jnl_grp_cd | E52: #MA.JNL_GRP_CD | G52: Journal group cd. | H52: 仕訳グループＣＤ | I52: E | FK52: E | FM52: E
A53: 10 | D53: jnl_ptn_cd | E53: #MA.JNL_PTN_CD | G53: Auto-journal pattern cd. | H53: 自動仕訳パタンＣＤ | I53: E | FO53: E | FQ53: E
A54: 10 | D54: auto_jnl_key_cd | E54: #MA.AUTO_JNL_KEY_CD | G54: Auto-journal key cd. | H54: 自動仕訳キーＣＤ | I54: E | FS54: E | FU54: E
A55: 10 | D55: insp_ptn_cd | E55: #MA.INSP_PTN_CD | G55: Inspection pattern cd. | H55: 検査パタンＣＤ | I55: E | FW55: E | FY55: E
A56: 10 | D56: wk_day_cd | E56: #MA.WK_DAY_CD | G56: Work type cd. | H56: 勤務種類ＣＤ | I56: E | GA56: E | GC56: E
A57: 10 | D57: ship_term_cd | E57: #MA.SHIP_TERM_CD | G57: Shipping conditions cd. | H57: 出荷条件ＣＤ | I57: E | GE57: E | GG57: E
A58: 10 | D58: ship_wk_cd | E58: #MA.SHIP_WK_CD | G58: Shipping operation cd. | H58: 出荷作業ＣＤ | I58: E | GI58: E | GK58: E
A59: 10 | D59: rsrc_cd | E59: #MA.RSRC_CD | G59: Resource cd. | H59: 資源ＣＤ | I59: E | GM59: E | GO59: E
A60: 10 | D60: hs_grp_cd | E60: #MA.HS_GRP_CD | G60: HS classification cd. | H60: ＨＳ分類ＣＤ | I60: E | GQ60: E | GS60: E
A61: 10 | D61: alc_ptn_cd | E61: #MA.ALC_PTN_CD | G61: Allocation pattern cd. | H61: 配賦パタンＣＤ | I61: E | GU61: E | GW61: E
A62: 10 | D62: ctg_grp_cd | E62: #MA.CTG_GRP_CD | G62: Item category group cd. | H62: 品群グループＣＤ | I62: E | GY62: E | HA62: E
A63: 10 | D63: act_ptn_cd | E63: #MA.ACT_PTN_CD | G63: Calculation run pattern cd. | H63: 計算実行パタンＣＤ | I63: E | HC63: E | HE63: E
A64: 10 | D64: gp_alc_cd | E64: #MA.GP_ALC_CD | G64: General purpose allocation classification cd. | H64: 汎用配賦分類ＣＤ | I64: E | HG64: E | HI64: E
A65: 10 | D65: calc_ctg_cd | E65: #MA.CALC_CTG_CD | G65: Calculation category cd. | H65: 計算カテゴリＣＤ | I65: E | HK65: E | HM65: E
A66: 10 | D66: rpt_ptn_cd | E66: #MA.RPT_PTN_CD | G66: Report pattern cd. | H66: レポートパタンＣＤ | I66: E | HO66: E | HQ66: E
A67: 10 | D67: menu_cd | E67: #MA.MENU_CD | G67: Menu cd. | H67: メニューＣＤ | I67: E | HS67: E | HU67: E
A68: 10 | D68: site_co_cd | E68: #MA.SITE_CO_CD | G68: Warehousing business cd. | H68: 倉庫事業者ＣＤ | I68: E | HW68: E | HY68: E
A69: 10 | D69: upd_cntr | E69: #MA.UPD_CNT | G69: Update counter | H69: 更新カウンタ | I69: E | K69: E | M69: E | O69: E | Q69: E | S69: E | U69: E | W69: E | Y69: E | AA69: E | AC69: E | AE69: E | AG69: E | AI69: E | AK69: E | AM69: E | AO69: E | AQ69: E | AS69: E | AU69: E | AW69: E | AY69: E | BA69: E | BC69: E | BE69: E | BG69: E | BI69: E | BK69: E | BM69: E | BO69: E | BQ69: E | BS69: E | BU69: E | BW69: E | BY69: E | CA69: E | CC69: E | CE69: E | CG69: E | CI69: E | CK69: E | CM69: E | CO69: E | CQ69: E | CS69: E | CU69: E | CW69: E | CY69: E | DA69: E | DC69: E | DE69: E | DG69: E | DI69: E | DK69: E | DM69: E | DO69: E | DQ69: E | DS69: E | DU69: E | DW69: E | DY69: E | EA69: E | EC69: E | EE69: E | EG69: E | EI69: E | EK69: E | EM69: E | EO69: E | EQ69: E | ES69: E | EU69: E | EW69: E | EY69: E | FA69: E | FC69: E | FE69: E | FG69: E | FI69: E | FK69: E | FM69: E | FO69: E | FQ69: E | FS69: E | FU69: E | FW69: E | FY69: E | GA69: E | GC69: E | GE69: E | GG69: E | GI69: E | GK69: E | GM69: E | GO69: E | GQ69: E | GS69: E | GU69: E | GW69: E | GY69: E | HA69: E | HC69: E | HE69: E | HG69: E | HI69: E | HK69: E | HM69: E | HO69: E | HQ69: E | HS69: E | HU69: E | HW69: E | HY69: E
A71: 20 | B71: * | D71: Del01_Cnd | E71: R
A72: 20 | D72: mst_nm | E72: #MA.ORA_OBJ_NM | G72: Master name | H72: マスタ名 | I72: E
D73: 詳細 :

Sheet 来歴
A1: 変更来歴
A3: Rev. | H3: 修正番号 | O3: 変更内容 | AQ3: 変更箇所
A4: 1 | O4: 初版
A5: 1.1 | H5: MA7032#031 | O5: Srch01_Rslt1ブロックに以下の項目を追加 ・ship_wk_cal_cd、ship_wk_cal_nm | AQ5: Srch01
A6: " | H6: " | O6: Upd01_Dtl1ブロックに以下の項目を追加 ・ship_wk_cal_cd | AQ6: Upd01
A7: 1.2 | O7: 英語の名称を追記 | AQ7: 全般
