Workbook

Sheet LogicCommon
A2: ロジック共通定義 | B2: ModuleID : | C2: MA | D2: LogicID : | E2: MABCL0570 | F2: Pj.ID : | G2: MC
B3: SubModuleID : | C3: MABC | D3: LogicClass : | E3: MABCL_SpplReg | F3: SuperClassPj.ID :
D4: LogicName : | E4: 発注先登録 | F4: SuperLogicID : | G4: MA.MAUDL5010
A5: 概要 :
A6: 詳細 :

Sheet Bp_UpdChk01
A1: * | B1: * | D1: L | E1: 1
A2: * | D2: オペレーション実装仕様書 Operation Specification Implementation Sheet | E2: ModuleID : | F2: =IF(LogicCommon!C2="","",LogicCommon!C2) -> MA | G2: LogicID : | H2: =IF(LogicCommon!E2="","",LogicCommon!E2) -> MABCL0570 | I2: Ope.ID : | J2: Bp_UpdChk01 | K2: Pj.ID : | L2: =IF(LogicCommon!G2="","",LogicCommon!G2) -> MC | M2: Ope.Body : | N2: =L4 & ".Checker" -> MA.MAUDL5010.Checker
A3: * | D3: =IF(LogicCommon!A3="","",LogicCommon!A3) | E3: SubModuleID : | F3: =IF(LogicCommon!C3="","",LogicCommon!C3) -> MABC | G3: LogicClass : | H3: =IF(LogicCommon!E3="","",LogicCommon!E3) -> MABCL_SpplReg | I3: Ope.Method : | J3: @ | K3: SuperClassPj.ID : | L3: =IF(LogicCommon!G3="","",LogicCommon!G3) | M3: ReportID : | O3: Gene.Type : | P3: ALL
A4: * | E4: Version : | F4: 000000 | G4: LogicName : | H4: =IF(LogicCommon!E4="","",LogicCommon!E4) -> 発注先登録 | I4: Ope.Name : | J4: 登録前チェック | K4: SuperLogicID : | L4: =IF(LogicCommon!G4="","",LogicCommon!G4) -> MA.MAUDL5010
A5: * | E5: ACType :
A6: * | D6: 概要 : | E6: 取引先マスタを登録する前のチェックを行う | T6: ID
A7: # | I7: U | K7: K | L7: K | M7: K | N7: K | O7: K | P7: K | Q7: K | R7: K | S7: o
A8: # | D8: ブロック名 Block Name | E8: 型 Type | G8: super/share | H8: 対象ブロック名 Target Block Name | K8: REQUIRED | L8: CONST | M8: LIST_LOGIC | N8: LIST_OUT | O8: LIST_OUT_BASE | P8: LIST_IN | Q8: LIST_IN_BASE | R8: SMALL_LARGE | S8: TargetName | W8: ブロック備考 Block Remarks
A9: # | D9: 項目名 Field Name | E9: 型 Type | F9: 桁 Digits | G9: フルネーム Full Name | H9: 日本語名 Japanese Name | I9: 上り項目 Request Message Field | J9: 下り項目 Response Message Field | U9: 条件および編集方法 Conditions and Editing Methods | W9: 項目備考 Field Remarks
A10: # | S10: 上り項目 Request Message Field | T10: 下り項目 Response Message Field
A11: 10 | B11: * | D11: Bp_UpdChk01_Dtl | E11: L
A12: 10 | D12: bp_cd | E12: #MA.BP_CD | G12: BP cd. | H12: 取引先ＣＤ | I12: E | K12: E | M12: MA.MAUAL0010.Bp | N12: cntry_cd | O12: cntry_cd | P12: MAC_BP_IS_SRCH_TYP.SPPL | Q12: bp_is_srch_typ
A13: 10 | D13: asppl_cd | E13: #MA.BP_CD | G13: AP supplier cd. | H13: 買掛先ＣＤ | I13: E | K13: E | M13: MA.MAUAL0010.Bp | P13: MAC_BP_IS_SRCH_TYP.ASPPL | Q13: bp_is_srch_typ
A14: 10 | D14: cntry_cd | E14: #MA.CNTRY_CD | G14: Country cd. | H14: 国ＣＤ | I14: -
A15: 10 | D15: sppl_cntct_dpt | E15: #MA.CNTCT_DPT | G15: Supplier dept. | H15: 発注先部署 | I15: E
A16: 10 | D16: sppl_cntct_psn | E16: #MA.CNTCT_PSN | G16: Supplier PIC | H16: 発注先担当者 | I16: E
A17: 10 | D17: sppl_cntct_psn_title | E17: #MA.BP_PSN_TITLE | G17: Supplier PIC form of address | H17: 発注先担当者敬称 | I17: E
A18: 10 | D18: subcon_flg | E18: #MA.FLG | G18: For subcontract | H18: 下請対象 | I18: E
A19: 10 | D19: onr_prsppl_flg | E19: #MA.FLG | G19: Chargeable supplier | H19: 有償支給先 | I19: E
A20: 10 | D20: repurc_obli_flg | E20: #MA.FLG | G20: Repurchase obligation | H20: 買戻義務 | I20: E
A21: 10 | D21: vmi_purc_dpt_cd | E21: #MA.DPT_CD | G21: VMI purchasing dept. cd. | H21: ＶＭＩ購買部門ＣＤ | I21: E
A22: 10 | D22: check_vmi_purc_dpt_cd | E22: #MA.DPT_CD | G22: VMI purchasing dept. cd. | H22: ＶＭＩ購買部門ＣＤ | I22: E | M22: MA.MAUAL0010.Dpt | P22: MAC_DPT_IS_SRCH_TYP.PURC;true | Q22: dpt_is_srch_typ;mode_today_flg
A23: 10 | D23: purc_upri_req_typ | E23: #MA.PURC_UPRI_REQ_TYP | G23: Purchase unit price acquisition type | H23: 購買単価取得区分 | I23: E | L23: MAC_PURC_UPRI_REQ_TYP
A24: 10 | D24: purc_upri_cng_flg | E24: #MA.FLG | G24: Allow purchasing unit price change | H24: 購買単価変更許可 | I24: E
A25: 10 | D25: prms_recv_flg | E25: #MA.FLG | G25: Check order promising | H25: 納期回答確認 | I25: E
A26: 10 | D26: purc_amt_rnd_typ | E26: #MA.RND_TYP | G26: Rounding type (Purchase amount) | H26: 仕入金額端数処理区分 | I26: E | K26: E | L26: MAC_RND_TYP
A27: 10 | D27: purc_tax_calc_typ | E27: #MA.TAX_CALC_TYP | G27: Purchase tax calculation type | H27: 仕入税計算区分 | I27: E | K27: E | L27: MAC_TAX_CALC_TYP
A28: 10 | D28: purc_tax_rnd_typ | E28: #MA.RND_TYP | G28: Rounding type (Purchase tax) | H28: 仕入税額端数処理区分 | I28: E | K28: E | L28: MAC_RND_TYP
A29: 10 | D29: purc_tax_cd | E29: #MA.TAX_CD | G29: Purchase tax cd. | H29: 仕入税ＣＤ | I29: E | M29: MA.MAUAL0010.PurcTax
A30: 10 | D30: purc_tax_cd_prio_flg | E30: #MA.FLG | G30: Purchase tax priority | H30: 仕入税優先 | I30: E
A31: 10 | D31: sppl_cal_cd | E31: #MA.CAL_CD | G31: Supplier calendar cd. | H31: 発注先カレンダＣＤ | I31: E | M31: MA.MAUAL0010.CalBase
A32: 10 | D32: po_print_cd | E32: #MA.PO_PRINT_CD | G32: Display PO sheet cd. | H32: 注文書表示ＣＤ | I32: E | M32: MA.MAUAL0010.PoPrint
A33: 10 | D33: sppl_ship_form_cd | E33: #MA.SLIP_FORM_CD | G33: Supplier delivery note cd. | H33: 発注先納品書ＣＤ | I33: E | M33: MA.MAUAL0010.SlipForm
A34: 10 | D34: po_dlv_slip_flg | E34: #MA.FLG | G34: Delivery note at PO | H34: 発注時納品書 | I34: E
A35: 10 | D35: dlv_inst_dlv_slip_flg | E35: #MA.FLG | G35: Delivery note at delivery order | H35: 納入指示時納品書 | I35: E
A36: 10 | D36: prms_rcpt_dlv_slip_flg | E36: #MA.FLG | G36: Delivery note at order promising result receipt | H36: 納期回答受領時納品書 | I36: E
A37: 10 | D37: prov_rcv_typ | E37: #MA.PROV_RCV_TYP | G37: In-transit supply management type | H37: 支給積送管理区分 | I37: E | K37: E | L37: MAC_PROV_RCV_TYP
A38: 10 | D38: purc_slip_each_lot_typ | E38: #MA.SLIP_EACH_LOT_TYP | G38: Purchase lot details split type | H38: 仕入ロット明細分割区分 | I38: E | K38: E | L38: MAC_SLIP_EACH_LOT_TYP
A39: 10 | D39: sppl_tterm_cd1 | E39: #MA.TTERM_CD | G39: Supplier transaction terms cd. 1 | H39: 発注先取引条件ＣＤ１ | I39: E | M39: MA.MAUAL0010.Tterm1
A40: 10 | D40: sppl_tterm_cd2 | E40: #MA.TTERM_CD | G40: Supplier transaction terms cd. 2 | H40: 発注先取引条件ＣＤ２ | I40: E | M40: MA.MAUAL0010.Tterm2
A41: 10 | D41: sppl_tterm_cd3 | E41: #MA.TTERM_CD | G41: Supplier transaction terms cd. 3 | H41: 発注先取引条件ＣＤ３ | I41: E | M41: MA.MAUAL0010.Tterm3
A42: 10 | D42: pay_crryovr_times | E42: #MA.CRRYOVR_TIMES | G42: Payment carry-over count | H42: 支払繰越回数 | I42: E | K42: E | R42: 0:99
A43: 10 | D43: wrk_po_flg | E43: #MA.FLG | G43: PO sheet by sales project | H43: 案件別注文書 | I43: E
A44: 10 | D44: wrk_ap_flg | E44: #MA.FLG | G44: AP management by sales project | H44: 案件別債務管理 | I44: E
A45: 10 | D45: sppl_iv_flg | E45: #MA.FLG | G45: Supplier invoice transaction | H45: 発注先インボイス取引 | I45: E
A46: 10 | D46: rcpt_iv_dup_flg | E46: #MA.FLG | G46: Allow purchase invoice duplication | H46: 受領インボイス重複許可 | I46: E
A47: 10 | D47: outsrc_upri_typ | E47: #MA.OUTSRC_UPRI_TYP | G47: Subcontracting unit price type | H47: 外注単価区分 | I47: E | L47: MAC_OUTSRC_UPRI_TYP
A48: 10 | D48: purc_basis_typ | E48: #MA.PURC_BASIS_TYP | G48: Purchase recording type | H48: 仕入計上区分 | I48: E | L48: MAC_PURC_BASIS_TYP
A49: 10 | D49: prov_basis_typ | E49: #MA.PROV_BASIS_TYP | G49: Supply recording type | H49: 支給計上区分 | I49: E | L49: MAC_PROV_BASIS_TYP
A50: 10 | D50: prov_upri_cng_flg | E50: #MA.FLG | G50: Allow supply unit price change | H50: 支給単価変更許可 | I50: E
A51: 10 | D51: prov_tax_cd | E51: #MA.TAX_CD | G51: Supply tax cd. | H51: 支給税ＣＤ | I51: E | M51: MA.MAUAL0010.ProvTax
A52: 10 | D52: prov_tax_cd_prio_flg | E52: #MA.FLG | G52: Supply tax first | H52: 支給税優先 | I52: E
A53: 10 | D53: prov_amt_rnd_typ | E53: #MA.RND_TYP | G53: Supply amount rounding type | H53: 支給金額端数処理区分 | I53: E | L53: MAC_RND_TYP
A54: 10 | D54: prov_tax_calc_typ | E54: #MA.TAX_CALC_TYP | G54: Supply tax calculation type | H54: 支給税計算区分 | I54: E | L54: MAC_TAX_CALC_TYP
A55: 10 | D55: prov_tax_rnd_typ | E55: #MA.RND_TYP | G55: Supply tax rounding type | H55: 支給税額端数処理区分 | I55: E | L55: MAC_RND_TYP
A56: 10 | D56: bsppl_flg | E56: #MA.FLG | G56: Scheduled payee | H56: 支払予定管理先 | I56: E
A57: 10 | D57: bsppl_cd | E57: #MA.BP_CD | G57: Scheduled payee cd. | H57: 支払予定管理先ＣＤ | I57: E | M57: MA.MAUAL0010.Bp | P57: MAC_BP_IS_SRCH_TYP.BSPPL;bsppl_flg;bp_cd | Q57: bp_is_srch_typ;check_rem_flg;ref_bp_cd
A58: 10 | D58: ap_dpt_cd | E58: #MA.DPT_CD | G58: AP dept. cd. | H58: 債務部門ＣＤ | I58: E
A59: 10 | D59: check_ap_dpt_cd | E59: #MA.DPT_CD | G59: AP dept. cd. | H59: 債務部門ＣＤ | I59: E | M59: MA.MAUAL0010.Dpt | P59: MAC_DPT_IS_SRCH_TYP.AP;true | Q59: dpt_is_srch_typ;mode_today_flg
A60: 10 | D60: sppl_prnt_typ | E60: #MA.PRNT_TYP | G60: Report issue type (Supplier) | H60: 帳票発行区分（発注先） | I60: E | L60: MAC_PRNT_TYP
A61: 10 | D61: upd_cntr | E61: #MA.UPD_CNT | G61: Update counter | H61: 更新カウンタ | I61: E
D62: 詳細 :

Sheet Bp_Upd01
A1: * | B1: * | D1: L | E1: 1
A2: * | D2: オペレーション実装仕様書 Operation Specification Implementation Sheet | E2: ModuleID : | F2: =IF(LogicCommon!C2="","",LogicCommon!C2) -> MA | G2: LogicID : | H2: =IF(LogicCommon!E2="","",LogicCommon!E2) -> MABCL0570 | I2: Ope.ID : | J2: Bp_Upd01 | K2: Pj.ID : | L2: =IF(LogicCommon!G2="","",LogicCommon!G2) -> MC | M2: Ope.Body : | N2: "mcframe.serverMAUD.MAUDL6010.MAUDL_RLUpdater"
A3: * | D3: =IF(LogicCommon!A3="","",LogicCommon!A3) | E3: SubModuleID : | F3: =IF(LogicCommon!C3="","",LogicCommon!C3) -> MABC | G3: LogicClass : | H3: =IF(LogicCommon!E3="","",LogicCommon!E3) -> MABCL_SpplReg | I3: Ope.Method : | J3: @ | K3: SuperClassPj.ID : | L3: =IF(LogicCommon!G3="","",LogicCommon!G3) | M3: ReportID : | O3: Gene.Type : | P3: ALL
A4: * | E4: Version : | F4: 000000 | G4: LogicName : | H4: =IF(LogicCommon!E4="","",LogicCommon!E4) -> 発注先登録 | I4: Ope.Name : | J4: 登録処理 | K4: SuperLogicID : | L4: =IF(LogicCommon!G4="","",LogicCommon!G4) -> MA.MAUDL5010
A5: * | E5: ACType :
A6: * | D6: 概要 : | E6: 取引先マスタを登録する | L6: ID | N6: ID | P6: ID | R6: ID
A7: # | I7: U | K7: o | L7: UPDATE.updMaster | M7: o | N7: MAIN.chkMaster | O7: o | Q7: o
A8: # | D8: ブロック名 Block Name | E8: 型 Type | G8: super/share | H8: 対象ブロック名 Target Block Name | K8: TargetName | L8: DBC.MA.MAM_BP | M8: TargetName | N8: DBC.MA.MAM_BP | O8: TargetName | Q8: TargetName | U8: ブロック備考 Block Remarks
A9: # | D9: 項目名 Field Name | E9: 型 Type | F9: 桁 Digits | G9: フルネーム Full Name | H9: 日本語名 Japanese Name | I9: 上り項目 Request Message Field | J9: 下り項目 Response Message Field | S9: 条件および編集方法 Conditions and Editing Methods | U9: 項目備考 Field Remarks
A10: # | K10: 上り項目 Request Message Field | L10: 下り項目 Response Message Field | M10: 上り項目 Request Message Field | N10: 下り項目 Response Message Field | O10: 上り項目 Request Message Field | P10: 下り項目 Response Message Field | Q10: 上り項目 Request Message Field | R10: 下り項目 Response Message Field
A11: 10 | B11: * | D11: Bp_Upd01_Dtl | E11: L | G11: $share$ | H11: MA.MABCL0570.Bp_UpdChk01.Bp_UpdChk01_Dtl | K11: L | M11: L
A12: 10 | D12: bp_cd | E12: #MA.BP_CD | G12: BP cd. | H12: 取引先ＣＤ | I12: E | K12: E | M12: E
A13: 10 | D13: asppl_cd | E13: #MA.BP_CD | G13: AP supplier cd. | H13: 買掛先ＣＤ | I13: E | K13: E
A14: 10 | D14: vmi_purc_dpt_cd | E14: #MA.DPT_CD | G14: VMI purchasing dept. cd. | H14: ＶＭＩ購買部門ＣＤ | I14: E | K14: E
A15: 10 | D15: sppl_cntct_dpt | E15: #MA.CNTCT_DPT | G15: Supplier dept. | H15: 発注先部署 | I15: E | K15: E
A16: 10 | D16: sppl_cntct_psn | E16: #MA.CNTCT_PSN | G16: Supplier PIC | H16: 発注先担当者 | I16: E | K16: E
A17: 10 | D17: sppl_cntct_psn_title | E17: #MA.BP_PSN_TITLE | G17: Supplier PIC form of address | H17: 発注先担当者敬称 | I17: E | K17: E
A18: 10 | D18: subcon_flg | E18: #MA.FLG | G18: For subcontract | H18: 下請対象 | I18: E | K18: E
A19: 10 | D19: purc_upri_req_typ | E19: #MA.PURC_UPRI_REQ_TYP | G19: Purchase unit price acquisition type | H19: 購買単価取得区分 | I19: E | K19: E
A20: 10 | D20: purc_upri_cng_flg | E20: #MA.FLG | G20: Allow purchasing unit price change | H20: 購買単価変更許可 | I20: E | K20: E
A21: 10 | D21: purc_amt_rnd_typ | E21: #MA.RND_TYP | G21: Rounding type (Purchase amount) | H21: 仕入金額端数処理区分 | I21: E | K21: E
A22: 10 | D22: purc_tax_calc_typ | E22: #MA.TAX_CALC_TYP | G22: Purchase tax calculation type | H22: 仕入税計算区分 | I22: E | K22: E
A23: 10 | D23: purc_tax_rnd_typ | E23: #MA.RND_TYP | G23: Rounding type (Purchase tax) | H23: 仕入税額端数処理区分 | I23: E | K23: E
A24: 10 | D24: pay_crryovr_times | E24: #MA.CRRYOVR_TIMES | G24: Payment carry-over count | H24: 支払繰越回数 | I24: E | K24: E
... A57: 10 | D57: upd_cntr | E57: #MA.UPD_CNT | G57: Update counter | H57: 更新カウンタ | I57: E | K57: E
D58: 詳細 :

Sheet Srch01
A1: * | B1: * | D1: L | E1: 1
A2: * | D2: オペレーション実装仕様書 Operation Specification Implementation Sheet | E2: ModuleID : | F2: =IF(LogicCommon!C2="","",LogicCommon!C2) -> MA | G2: LogicID : | H2: =IF(LogicCommon!E2="","",LogicCommon!E2) -> MABCL0570 | I2: Ope.ID : | J2: Srch01 | K2: Pj.ID : | L2: =IF(LogicCommon!G2="","",LogicCommon!G2) -> MC | M2: Ope.Body : | N2: "mcframe.serverMAUD.MAUDL6010.MAUDL_RLSearcher"
A3: * | D3: =IF(LogicCommon!A3="","",LogicCommon!A3) | E3: SubModuleID : | F3: =IF(LogicCommon!C3="","",LogicCommon!C3) -> MABC | G3: LogicClass : | H3: =IF(LogicCommon!E3="","",LogicCommon!E3) -> MABCL_SpplReg | I3: Ope.Method : | J3: @ | K3: SuperClassPj.ID : | L3: =IF(LogicCommon!G3="","",LogicCommon!G3) | M3: ReportID : | O3: Gene.Type : | P3: ALL
A4: * | E4: Version : | F4: 000000 | G4: LogicName : | H4: =IF(LogicCommon!E4="","",LogicCommon!E4) -> 発注先登録 | I4: Ope.Name : | J4: 検索 | K4: SuperLogicID : | L4: =IF(LogicCommon!G4="","",LogicCommon!G4) -> MA.MAUDL5010
A5: * | E5: ACType :
A6: * | D6: 概要 : | E6: 検索処理を行う | M6: ID | O6: ID | Q6: ID | S6: ID | U6: ID | W6: ID | Y6: ID
A7: # | I7: U | K7: K | L7: o | M7: SELECT.c0 | N7: o | O7: SELECT_SUB1.c1 | P7: o | Q7: SELECT_SUB2.c2 | R7: o | S7: SELECT_SUB3.c3 | T7: o | U7: SELECT_SUB4.c4 | V7: o | W7: SELECT_SUB5.c5 | X7: o | Y7: SELECT_SUB6.c6
A8: # | D8: ブロック名 Block Name | E8: 型 Type | G8: super/share | H8: 対象ブロック名 Target Block Name | K8: CONST | L8: TargetName | M8: DBC.MA.MAM_BP | N8: TargetName | O8: DBC.MA.MAM_ITM_DTL_ | P8: TargetName | Q8: DBC.MA.MAM_ITM_INSP | R8: TargetName | S8: DBC.MA.MAM_PURC_DDLV_LT | T8: TargetName | U8: DBC.MA.MAM_EDI_IF_CTL | V8: TargetName | W8: DBC.MA.MAM_BP_ITM | X8: TargetName | Y8: DBC.MA.MAM_SPPL_USR | AB8: ブロック備考 Block Remarks
A9: # | D9: 項目名 Field Name | E9: 型 Type | F9: 桁 Digits | G9: フルネーム Full Name | H9: 日本語名 Japanese Name | I9: 上り項目 Request Message Field | J9: 下り項目 Response Message Field | Z9: 条件および編集方法 Conditions and Editing Methods | AB9: 項目備考 Field Remarks
A10: # | L10: 上り項目 Request Message Field | M10: 下り項目 Response Message Field | N10: 上り項目 Request Message Field | O10: 下り項目 Response Message Field | P10: 上り項目 Request Message Field | Q10: 下り項目 Response Message Field | R10: 上り項目 Request Message Field | S10: 下り項目 Response Message Field | T10: 上り項目 Request Message Field | U10: 下り項目 Response Message Field | V10: 上り項目 Request Message Field | W10: 下り項目 Response Message Field | X10: 上り項目 Request Message Field | Y10: 下り項目 Response Message Field
A11: 10 | B11: * | D11: Srch01_Cnd | E11: R
A12: 10 | D12: st_dt_fr | E12: #MA.DT | G12: Application start date FROM | H12: 適用開始日ＦＲＯＭ | I12: E
A13: 10 | D13: st_dt_to | E13: #MA.DT | G13: Application start date TO | H13: 適用開始日ＴＯ | I13: E
A14: 10 | D14: end_dt_fr | E14: #MA.DT | G14: Application end date FROM | H14: 適用終了日ＦＲＯＭ | I14: E
A15: 10 | D15: end_dt_to | E15: #MA.DT | G15: Application end date TO | H15: 適用終了日ＴＯ | I15: E
A16: 10 | D16: bp_cd | E16: #MA.BP_CD | G16: BP cd. | H16: 取引先ＣＤ | I16: E
A17: 10 | D17: bp_nm | E17: #MA.BP_NM | G17: BP name | H17: 取引先名 | I17: E
A18: 10 | D18: off_del_flg | E18: #MA.FLG | G18: Logical delete. Off | H18: 論理削除.オフ | I18: E
A19: 10 | D19: on_del_flg | E19: #MA.FLG | G19: Logical delete. On | H19: 論理削除.オン | I19: E
A21: 20 | B21: * | D21: Srch01_Rslt1 | E21: L | M21: L
A22: 20 | D22: bp_cd | E22: #MA.BP_CD | G22: BP cd. | H22: 取引先ＣＤ | J22: E | M22: E
A23: 20 | D23: asppl_flg | E23: #MA.FLG | G23: AP supplier | H23: 買掛先 | J23: E | M23: E
A24: 20 | D24: cntry_cd | E24: #MA.CNTRY_CD | G24: Country cd. | H24: 国ＣＤ | J24: E | M24: E
A25: 20 | D25: asppl_cd | E25: #MA.BP_CD | G25: AP supplier cd. | H25: 買掛先ＣＤ | J25: E | M25: E
A26: 20 | D26: asppl_nm | E26: #MA.BP_NM | G26: AP supplier name | H26: 買掛先名 | J26: E | M26: E
A27: 20 | D27: vmi_purc_dpt_cd | E27: #MA.DPT_CD | G27: VMI purchasing dept. cd. | H27: ＶＭＩ購買部門ＣＤ | J27: E | M27: E
A28: 20 | D28: vmi_purc_dpt_nm | E28: #MA.DPT_NM | G28: VMI purchasing dept. name | H28: ＶＭＩ購買部門名 | J28: E | M28: E
A29: 20 | D29: sppl_cntct_dpt | E29: #MA.CNTCT_DPT | G29: Supplier dept. | H29: 発注先部署 | J29: E | M29: E
A30: 20 | D30: sppl_cntct_psn | E30: #MA.CNTCT_PSN | G30: Supplier PIC | H30: 発注先担当者 | J30: E | M30: E
A31: 20 | D31: sppl_cntct_psn_title | E31: #MA.BP_PSN_TITLE | G31: Supplier PIC form of address | H31: 発注先担当者敬称 | J31: E | M31: E
A32: 20 | D32: subcon_flg | E32: #MA.FLG | G32: For subcontract | H32: 下請対象 | J32: E | M32: E
A33: 20 | D33: purc_upri_req_typ | E33: #MA.PURC_UPRI_REQ_TYP | G33: Purchase unit price acquisition type | H33: 購買単価取得区分 | J33: E | K33: MAC_PURC_UPRI_REQ_TYP | M33: E
A34: 20 | D34: =D33&"_nm" -> purc_upri_req_typ_nm | E34: =E33&"_NM" -> #MA.PURC_UPRI_REQ_TYP_NM | G34: Purchase unit price acquisition type name | H34: 購買単価取得区分名 | J34: E
A35: 20 | D35: purc_upri_cng_flg | E35: #MA.FLG | G35: Allow purchasing unit price change | H35: 購買単価変更許可 | J35: E | M35: E
A36: 20 | D36: purc_amt_rnd_typ | E36: #MA.RND_TYP | G36: Rounding type (Purchase amount) | H36: 仕入金額端数処理区分 | J36: E | K36: MAC_RND_TYP | M36: E
A37: 20 | D37: =D36&"_nm" -> purc_amt_rnd_typ_nm | E37: =E36&"_NM" -> #MA.RND_TYP_NM | G37: Rounding type name (Purchase amount) | H37: 仕入金額端数処理区分名 | J37: E
A38: 20 | D38: purc_tax_calc_typ | E38: #MA.TAX_CALC_TYP | G38: Purchase tax calculation type | H38: 仕入税計算区分 | J38: E | K38: MAC_TAX_CALC_TYP | M38: E
A39: 20 | D39: =D38&"_nm" -> purc_tax_calc_typ_nm | E39: =E38&"_NM" -> #MA.TAX_CALC_TYP_NM | G39: Purchase tax calculation type name | H39: 仕入税計算区分名 | J39: E
A40: 20 | D40: purc_tax_rnd_typ | E40: #MA.RND_TYP | G40: Rounding type (Purchase tax) | H40: 仕入税額端数処理区分 | J40: E | K40: MAC_RND_TYP | M40: E
A41: 20 | D41: =D40&"_nm" -> purc_tax_rnd_typ_nm | E41: =E40&"_NM" -> #MA.RND_TYP_NM | G41: Purchase tax amount rounding type | H41: 仕入税額端数処理区分名 | J41: E
A42: 20 | D42: pay_crryovr_times | E42: #MA.CRRYOVR_TIMES | G42: Payment carry-over count | H42: 支払繰越回数 | J42: E | M42: E
A43: 20 | D43: sppl_cal_cd | E43: #MA.CAL_CD | G43: Supplier calendar cd. | H43: 発注先カレンダＣＤ | J43: E | M43: E
A44: 20 | D44: sppl_cal_nm | E44: #MA.CAL_NM | G44: Supplier calendar name | H44: 発注先カレンダ名 | J44: E | M44: E
A45: 20 | D45: po_print_cd | E45: #MA.PO_PRINT_CD | G45: Display PO sheet cd. | H45: 注文書表示ＣＤ | J45: E | M45: E
A46: 20 | D46: po_print_nm | E46: #MA.PO_PRINT_NM | G46: Display PO sheet name | H46: 注文書表示名 | J46: E | M46: E
A47: 20 | D47: sppl_ship_form_cd | E47: #MA.SLIP_FORM_CD | G47: Supplier delivery note cd. | H47: 発注先納品書ＣＤ | J47: E | M47: E
A48: 20 | D48: po_dlv_slip_flg | E48: #MA.FLG | G48: Delivery note at PO | H48: 発注時納品書 | J48: E | M48: E
A49: 20 | D49: dlv_inst_dlv_slip_flg | E49: #MA.FLG | G49: Delivery note at delivery order | H49: 納入指示時納品書 | J49: E | M49: E
A50: 20 | D50: prms_rcpt_dlv_slip_flg | E50: #MA.FLG | G50: Delivery note at order promising result receipt | H50: 納期回答受領時納品書 | J50: E | M50: E
A51: 20 | D51: sppl_ship_form_nm | E51: #MA.SLIP_FORM_NM | G51: Supplier delivery note name | H51: 発注先納品書名 | J51: E | M51: E
A52: 20 | D52: prms_recv_flg | E52: #MA.FLG | G52: Check order promising | H52: 納期回答確認 | J52: E | M52: E
A53: 20 | D53: purc_tax_cd | E53: #MA.TAX_CD | G53: Purchase tax cd. | H53: 仕入税ＣＤ | J53: E | M53: E
... A65: 20 | D65: wrk_ap_flg | E65: #MA.FLG | G65: AP management by sales project | H65: 案件別債務管理 | J65: E | M65: E
A66: 20 | D66: purc_slip_each_lot_typ | E66: #MA.SLIP_EACH_LOT_TYP | G66: Purchase lot details split type | H66: 仕入ロット明細分割区分 | J66: E | K66: MAC_SLIP_EACH_LOT_TYP | M66: E
A67: 20 | D67: =D66&"_nm" -> purc_slip_each_lot_typ_nm | E67: =E66&"_NM" -> #MA.SLIP_EACH_LOT_TYP_NM | G67: Purchase lot details split type name | H67: 仕入ロット明細分割区分名 | J67: E
A68: 20 | D68: prov_rcv_typ | E68: #MA.PROV_RCV_TYP | G68: In-transit supply management type | H68: 支給積送管理区分 | J68: E | K68: MAC_PROV_RCV_TYP | M68: E
A69: 20 | D69: =D68&"_nm" -> prov_rcv_typ_nm | E69: =E68&"_NM" -> #MA.PROV_RCV_TYP_NM | G69: Supply in-transit management type | H69: 支給積送管理区分名 | J69: E
A70: 20 | D70: onr_prsppl_flg | E70: #MA.FLG | G70: Chargeable supplier | H70: 有償支給先 | J70: E | M70: E
A71: 20 | D71: repurc_obli_flg | E71: #MA.FLG | G71: Repurchase obligation | H71: 買戻義務 | J71: E | M71: E
A72: 20 | D72: outsrc_upri_typ | E72: #MA.OUTSRC_UPRI_TYP | G72: Subcontracting unit price type | H72: 外注単価区分 | J72: E | K72: MAC_OUTSRC_UPRI_TYP | M72: E
A73: 20 | D73: outsrc_upri_typ_nm | E73: #MA.OUTSRC_UPRI_TYP_NM | G73: Subcontracting unit price type name | H73: 外注単価区分名 | J73: E
A74: 20 | D74: purc_basis_typ | E74: #MA.PURC_BASIS_TYP | G74: Purchase recording type | H74: 仕入計上区分 | J74: E | K74: MAC_PURC_BASIS_TYP | M74: E
A75: 20 | D75: =D74&"_nm" -> purc_basis_typ_nm | E75: =E74&"_NM" -> #MA.PURC_BASIS_TYP_NM | G75: Purchase recording type name | H75: 仕入計上区分名 | J75: E
A76: 20 | D76: prov_basis_typ | E76: #MA.PROV_BASIS_TYP | G76: Supply recording type | H76: 支給計上区分 | J76: E | K76: MAC_PROV_BASIS_TYP | M76: E
A77: 20 | D77: =D76&"_nm" -> prov_basis_typ_nm | E77: =E76&"_NM" -> #MA.PROV_BASIS_TYP_NM | G77: Supply recording type name | H77: 支給計上区分名 | J77: E
A78: 20 | D78: prov_upri_cng_flg | E78: #MA.FLG | G78: Allow supply unit price change | H78: 支給単価変更許可 | J78: E | M78: E
A79: 20 | D79: prov_tax_cd | E79: #MA.TAX_CD | G79: Supply tax cd. | H79: 支給税ＣＤ | J79: E | M79: E
A80: 20 | D80: prov_tax_nm | E80: #MA.TAX_NM | G80: Supply tax name | H80: 支給税名 | J80: E | M80: E
A81: 20 | D81: prov_tax_cd_prio_flg | E81: #MA.FLG | G81: Supply tax first | H81: 支給税優先 | J81: E | M81: E
A82: 20 | D82: prov_amt_rnd_typ | E82: #MA.RND_TYP | G82: Supply amount rounding type | H82: 支給金額端数処理区分 | J82: E | K82: MAC_RND_TYP | M82: E
A83: 20 | D83: =D82&"_nm" -> prov_amt_rnd_typ_nm | E83: =E82&"_NM" -> #MA.RND_TYP_NM | G83: Supply amount rounding type | H83: 支給金額端数処理区分名 | J83: E
A84: 20 | D84: prov_tax_calc_typ | E84: #MA.TAX_CALC_TYP | G84: Supply tax calculation type | H84: 支給税計算区分 | J84: E | K84: MAC_TAX_CALC_TYP | M84: E
A85: 20 | D85: =D84&"_nm" -> prov_tax_calc_typ_nm | E85: =E84&"_NM" -> #MA.TAX_CALC_TYP_NM | G85: Supply tax calculation type name | H85: 支給税計算区分名 | J85: E
A86: 20 | D86: prov_tax_rnd_typ | E86: #MA.RND_TYP | G86: Supply tax rounding type | H86: 支給税額端数処理区分 | J86: E | K86: MAC_RND_TYP | M86: E
A87: 20 | D87: =D86&"_nm" -> prov_tax_rnd_typ_nm | E87: =E86&"_NM" -> #MA.RND_TYP_NM | G87: Supply tax amount rounding type | H87: 支給税額端数処理区分名 | J87: E
A88: 20 | D88: bsppl_flg | E88: #MA.FLG | G88: Scheduled payee | H88: 支払予定管理先 | J88: E | M88: E
A89: 20 | D89: bsppl_cd | E89: #MA.BP_CD | G89: Scheduled payee cd. | H89: 支払予定管理先ＣＤ | J89: E | M89: E
A90: 20 | D90: bsppl_nm | E90: #MA.BP_NM | G90: Scheduled payee name | H90: 支払予定管理先名 | J90: E | M90: E
A91: 20 | D91: ap_dpt_cd | E91: #MA.DPT_CD | G91: AP dept. cd. | H91: 債務部門ＣＤ | J91: E | M91: E
A92: 20 | D92: ap_dpt_nm | E92: #MA.DPT_NM | G92: AP dept. name | H92: 債務部門名 | J92: E | M92: E
A93: 20 | D93: sppl_prnt_typ | E93: #MA.PRNT_TYP | G93: Report issue type (Supplier) | H93: 帳票発行区分（発注先） | J93: E | K93: MAC_PRNT_TYP | M93: E
A94: 20 | D94: sppl_prnt_typ_nm | E94: #MA.PRNT_TYP_NM | G94: Report issue type name (Supplier) | H94: 帳票発行区分名（発注先） | J94: E
A95: 20 | D95: ins_usr_id | E95: #MA.FCM_USR_ID | G95: Entry user ID | H95: 登録ユーザＩＤ | J95: E | M95: E
A96: 20 | D96: ins_usr_nm | E96: #MA.FCM_USR_NM | G96: Entry user name | H96: 登録ユーザ名 | J96: E | M96: E
A97: 20 | D97: ins_ts | E97: #MA.SYS_TS | G97: Entry date and time | H97: 登録日時 | J97: E | M97: E
A98: 20 | D98: ins_func_id | E98: #MA.FUNC_ID | G98: Entry function ID | H98: 登録機能ＩＤ | J98: E | M98: E
A99: 20 | D99: ins_func_nm | E99: #MA.FUNC_NM | G99: Entry function name | H99: 登録機能名 | J99: E
A100: 20 | D100: upd_cntr | E100: #MA.UPD_CNT | G100: Update counter | H100: 更新カウンタ | J100: E | M100: E
A101: 20 | D101: upd_usr_id | E101: #MA.FCM_USR_ID | G101: Update user ID | H101: 更新ユーザＩＤ | J101: E | M101: E
A102: 20 | D102: upd_usr_nm | E102: #MA.FCM_USR_NM | G102: Update user name | H102: 更新ユーザ名 | J102: E | M102: E
A103: 20 | D103: upd_ts | E103: #MA.SYS_TS | G103: Update date and time | H103: 更新日時 | J103: E | M103: E
A104: 20 | D104: upd_func_id | E104: #MA.FUNC_ID | G104: Update function ID | H104: 更新機能ＩＤ | J104: E | M104: E
A105: 20 | D105: upd_func_nm | E105: #MA.FUNC_NM | G105: Update function name | H105: 更新機能名 | J105: E
A106: 20 | D106: upd_srv_req_no | E106: #MA.SRV_REQ_NO | G106: Update request No. | H106: 更新リクエストＮＯ | J106: E | M106: E
A107: 20 | D107: del_usr_id | E107: #MA.FCM_USR_ID | G107: Logical delete user ID | H107: 論理削除ユーザＩＤ | J107: E | M107: E
A108: 20 | D108: del_usr_nm | E108: #MA.FCM_USR_NM | G108: Logical delete user name | H108: 論理削除ユーザ名 | J108: E | M108: E
A109: 20 | D109: del_ts | E109: #MA.SYS_TS | G109: Logical delete date and time | H109: 論理削除日時 | J109: E | M109: E
A111: 30 | B111: * | D111: Srch01_Rslt2 | E111: L | O111: L
A112: 30 | D112: del_flg | E112: #MA.FLG | G112: Logical delete | H112: 論理削除 | J112: E | O112: E
A113: 30 | D113: sppl_cd | E113: #MA.BP_CD | G113: Supplier cd. | H113: 発注先ＣＤ | J113: E | O113: E
...

Sheet Upd01
A1: * | B1: * | D1: L | E1: 1
A2: * | D2: オペレーション実装仕様書 Operation Specification Implementation Sheet | E2: ModuleID : | F2: =IF(LogicCommon!C2="","",LogicCommon!C2) -> MA | G2: LogicID : | H2: =IF(LogicCommon!E2="","",LogicCommon!E2) -> MABCL0570 | I2: Ope.ID : | J2: Upd01 | K2: Pj.ID : | L2: =IF(LogicCommon!G2="","",LogicCommon!G2) -> MC | M2: Ope.Body : | N2: "mcframe.serverMAUD.MAUDL6010.MAUDL_RLUpdater"
A3: * | D3: =IF(LogicCommon!A3="","",LogicCommon!A3) | E3: SubModuleID : | F3: =IF(LogicCommon!C3="","",LogicCommon!C3) -> MABC | G3: LogicClass : | H3: =IF(LogicCommon!E3="","",LogicCommon!E3) -> MABCL_SpplReg | I3: Ope.Method : | J3: @ | K3: SuperClassPj.ID : | L3: =IF(LogicCommon!G3="","",LogicCommon!G3) | M3: ReportID : | O3: Gene.Type : | P3: ALL
A4: * | E4: Version : | F4: 000000 | G4: LogicName : | H4: =IF(LogicCommon!E4="","",LogicCommon!E4) -> 発注先登録 | I4: Ope.Name : | J4: 登録 | K4: SuperLogicID : | L4: =IF(LogicCommon!G4="","",LogicCommon!G4) -> MA.MAUDL5010
A5: * | E5: ACType :
A6: * | D6: 概要 : | E6: 登録処理を行う | L6: ID | N6: ID | P6: ID | R6: ID | T6: ID | V6: ID | X6: ID | Z6: ID | AB6: ID | AD6: ID | AF6: ID | AH6: ID | AJ6: ID | AL6: ID
A7: # | I7: U | K7: o | L7: CALL_OPE01.chk01 | M7: o | N7: CALL_OPE01.upd01 | O7: o | P7: CALL_OPE02.chk02 | Q7: o | R7: CALL_OPE02.upd02 | S7: o | T7: CALL_OPE03.chk03 | U7: o | V7: CALL_OPE03.upd03 | W7: o | X7: CALL_OPE04.chk04 | Y7: o | Z7: CALL_OPE04.upd04 | AA7: o | AB7: CALL_OPE05.chk05 | AC7: o | AD7: CALL_OPE05.upd05 | AE7: o | AF7: CALL_OPE06.chk06 | AG7: o | AH7: CALL_OPE06.upd06 | AI7: o | AJ7: CALL_OPE07.chk07 | AK7: o | AL7: CALL_OPE07.upd07
A8: # | D8: ブロック名 Block Name | E8: 型 Type | G8: super/share | H8: 対象ブロック名 Target Block Name | K8: TargetName | L8: OPE.MA.MABCL0570.Bp_UpdChk01 | M8: TargetName | N8: OPE.MA.MABCL0570.Bp_Upd01 | O8: TargetName | P8: OPE.MA.MABSL0010.ItmDtl_UpdChk01 | Q8: TargetName | R8: OPE.MA.MABSL0010.ItmDtl_Upd01 | S8: TargetName | T8: OPE.MA.MABSL0190.ItmInsp_UpdChk01 | U8: TargetName | V8: OPE.MA.MABSL0190.ItmInsp_Upd01 | W8: TargetName | X8: OPE.MA.MABSL0530.PurcDdlvLt_UpdChk01 | Y8: TargetName | Z8: OPE.MA.MABSL0530.PurcDdlvLt_Upd01 | AA8: TargetName | AB8: OPE.MA.MABSL1230.EdiIfCtl_UpdChk01 | AC8: TargetName | AD8: OPE.MA.MABSL1230.EdiIfCtl_Upd01 | AE8: TargetName | AF8: OPE.MA.MABSL0640.BpItm_UpdChk01 | AG8: TargetName | AH8: OPE.MA.MABSL0640.BpItm_Upd01 | AI8: TargetName | AJ8: OPE.MA.MABSL0670.SpplUsr_UpdChk01 | AK8: TargetName | AL8: OPE.MA.MABSL0670.SpplUsr_Upd01 | AO8: ブロック備考 Block Remarks
A9: # | D9: 項目名 Field Name | E9: 型 Type | F9: 桁 Digits | G9: フルネーム Full Name | H9: 日本語名 Japanese Name | I9: 上り項目 Request Message Field | J9: 下り項目 Response Message Field | AM9: 条件および編集方法 Conditions and Editing Methods | AO9: 項目備考 Field Remarks
A10: # | K10: 上り項目 Request Message Field | L10: 下り項目 Response Message Field | M10: 上り項目 Request Message Field | N10: 下り項目 Response Message Field | O10: 上り項目 Request Message Field | P10: 下り項目 Response Message Field | Q10: 上り項目 Request Message Field | R10: 下り項目 Response Message Field | S10: 上り項目 Request Message Field | T10: 下り項目 Response Message Field | U10: 上り項目 Request Message Field | V10: 下り項目 Response Message Field | W10: 上り項目 Request Message Field | X10: 下り項目 Response Message Field | Y10: 上り項目 Request Message Field | Z10: 下り項目 Response Message Field | AA10: 上り項目 Request Message Field | AB10: 下り項目 Response Message Field | AC10: 上り項目 Request Message Field | AD10: 下り項目 Response Message Field | AE10: 上り項目 Request Message Field | AF10: 下り項目 Response Message Field | AG10: 上り項目 Request Message Field | AH10: 下り項目 Response Message Field | AI10: 上り項目 Request Message Field | AJ10: 下り項目 Response Message Field | AK10: 上り項目 Request Message Field | AL10: 下り項目 Response Message Field
A11: 10 | B11: * | D11: Upd01_Dtl1 | E11: L | G11: $share$ | H11: MA.MABCL0570.Bp_Upd01.Bp_Upd01_Dtl | K11: Bp_UpdChk01_Dtl | M11: Bp_Upd01_Dtl
A12: 10 | D12: bp_cd | E12: #MA.BP_CD | G12: BP cd. | H12: 取引先ＣＤ | I12: E | K12: E | M12: E
A13: 10 | D13: asppl_cd | E13: #MA.BP_CD | G13: AP supplier cd. | H13: 買掛先ＣＤ | I13: E | K13: E | M13: E
A14: 10 | D14: vmi_purc_dpt_cd | E14: #MA.DPT_CD | G14: VMI purchasing dept. cd. | H14: ＶＭＩ購買部門ＣＤ | I14: E | K14: E | M14: E
A15: 10 | D15: check_vmi_purc_dpt_cd | E15: #MA.DPT_CD | G15: VMI purchasing dept. cd. | H15: ＶＭＩ購買部門ＣＤ | I15: E | K15: E
A16: 10 | D16: sppl_cntct_dpt | E16: #MA.CNTCT_DPT | G16: Supplier dept. | H16: 発注先部署 | I16: E | K16: E | M16: E
A17: 10 | D17: sppl_cntct_psn | E17: #MA.CNTCT_PSN | G17: Supplier PIC | H17: 発注先担当者 | I17: E | K17: E | M17: E
A18: 10 | D18: sppl_cntct_psn_title | E18: #MA.BP_PSN_TITLE | G18: Supplier PIC form of address | H18: 発注先担当者敬称 | I18: E | K18: E | M18: E
A19: 10 | D19: subcon_flg | E19: #MA.FLG | G19: For subcontract | H19: 下請対象 | I19: E | K19: E | M19: E
A20: 10 | D20: purc_upri_req_typ | E20: #MA.PURC_UPRI_REQ_TYP | G20: Purchase unit price acquisition type | H20: 購買単価取得区分 | I20: E | K20: E | M20: E
A21: 10 | D21: purc_upri_cng_flg | E21: #MA.FLG | G21: Allow purchasing unit price change | H21: 購買単価変更許可 | I21: E | K21: E | M21: E
A22: 10 | D22: purc_amt_rnd_typ | E22: #MA.RND_TYP | G22: Rounding type (Purchase amount) | H22: 仕入金額端数処理区分 | I22: E | K22: E | M22: E
A23: 10 | D23: purc_tax_calc_typ | E23: #MA.TAX_CALC_TYP | G23: Purchase tax calculation type | H23: 仕入税計算区分 | I23: E | K23: E | M23: E
A24: 10 | D24: purc_tax_rnd_typ | E24: #MA.RND_TYP | G24: Rounding type (Purchase tax) | H24: 仕入税額端数処理区分 | I24: E | K24: E | M24: E
A25: 10 | D25: pay_crryovr_times | E25: #MA.CRRYOVR_TIMES | G25: Payment carry-over count | H25: 支払繰越回数 | I25: E | K25: E | M25: E
A26: 10 | D26: sppl_cal_cd | E26: #MA.CAL_CD | G26: Supplier calendar cd. | H26: 発注先カレンダＣＤ | I26: E | K26: E | M26: E
A27: 10 | D27: po_print_cd | E27: #MA.PO_PRINT_CD | G27: Display PO sheet cd. | H27: 注文書表示ＣＤ | I27: E | K27: E | M27: E
... A54: 10 | D54: prov_tax_rnd_typ | E54: #MA.RND_TYP | G54: Supply tax rounding type | H54: 支給税額端数処理区分 | I54: E | K54: E | M54: E
A55: 10 | D55: bsppl_flg | E55: #MA.FLG | G55: Scheduled payee | H55: 支払予定管理先 | I55: E | K55: E
A56: 10 | D56: bsppl_cd | E56: #MA.BP_CD | G56: Scheduled payee cd. | H56: 支払予定管理先ＣＤ | I56: E | K56: E | M56: E
A57: 10 | D57: ap_dpt_cd | E57: #MA.DPT_CD | G57: AP dept. cd. | H57: 債務部門ＣＤ | I57: E | K57: E | M57: E
A58: 10 | D58: check_ap_dpt_cd | E58: #MA.DPT_CD | G58: AP dept. cd. | H58: 債務部門ＣＤ | I58: E | K58: E
A59: 10 | D59: sppl_prnt_typ | E59: #MA.PRNT_TYP | G59: Report issue type (Supplier) | H59: 帳票発行区分（発注先） | I59: E | K59: E | M59: E
A60: 10 | D60: upd_cntr | E60: #MA.UPD_CNT | G60: Update counter | H60: 更新カウンタ | I60: E | K60: E | M60: E
A62: 20 | B62: * | D62: Upd01_Dtl2 | E62: L | G62: $share$ | H62: MA.MABSL0010.ItmDtl_Upd01.ItmDtl_Upd01_Dtl | O62: ItmDtl_UpdChk01_Dtl | Q62: ItmDtl_Upd01_Dtl
A63: 20 | D63: sppl_cd | E63: #MA.BP_CD | G63: Supplier cd. | H63: 発注先ＣＤ | I63: E | O63: E | Q63: E
A64: 20 | D64: wg_cd | E64: #MA.WG_CD | G64: WG cd. | H64: ワーキンググループＣＤ | I64: E | O64: E | Q64: E
A65: 20 | D65: itm_cd | E65: #MA.ITM_CD | G65: Item cd. | H65: 品目ＣＤ | I65: E | O65: E | Q65: E
A66: 20 | D66: itm_sub1 | E66: #MA.ITM_SUB1 | G66: Branch No. 1 | H66: 枝番１ | I66: E | O66: E | Q66: E
A67: 20 | D67: itm_sub2 | E67: #MA.ITM_SUB2 | G67: Branch No. 2 | H67: 枝番２ | I67: E | O67: E | Q67: E
A68: 20 | D68: itm_sub3 | E68: #MA.ITM_SUB3 | G68: Branch No. 3 | H68: 枝番３ | I68: E | O68: E | Q68: E
A69: 20 | D69: maker_cd | E69: #MA.BP_CD | G69: Maker cd. | H69: メーカＣＤ | I69: E | O69: E | Q69: E
A70: 20 | D70: st_dt_key | E70: #MA.DT | G70: Application start date_[Before change] | H70: 適用開始日_[変更前] | I70: E | O70: E | Q70: E
A71: 20 | D71: st_dt | E71: #MA.DT | G71: Application start date | H71: 適用開始日 | I71: E | O71: E | Q71: E
A72: 20 | D72: end_dt | E72: #MA.DT | G72: Application end date | H72: 適用終了日 | I72: E | O72: E | Q72: E
A73: 20 | D73: purc_id_typ | E73: #MA.PURC_ID_TYP | G73: Purchase identification type | H73: 購買識別区分 | I73: E | O73: E | Q73: E
A74: 20 | D74: purc_lt | E74: #MA.LT | G74: Purchase LT | H74: 購入ＬＴ | I74: E | O74: E | Q74: E
... A102: 20 | D102: upd_cntr | E102: #MA.UPD_CNT | G102: Update counter | H102: 更新カウンタ | I102: E | O102: E | Q102: E
A103: 20 | D103: mfg_loc_cd | E103: #MA.LOC_CD | G103: Mfg. location cd. | H103: 製造場所ＣＤ | O103: E | Q103: E
A104: 20 | D104: rqst_loc_cd | E104: #MA.LOC_CD | G104: Requested location cd. | H104: 依頼先場所ＣＤ | O104: E | Q104: E
A105: 20 | D105: bom_ptn | E105: #MA.BOM_PTN | G105: BOM pattern | H105: 構成パタン | O105: E | Q105: E
A107: 30 | B107: * | D107: Upd01_Dtl3 | E107: L | G107: $share$ | H107: MA.MABSL0190.ItmInsp_Upd01.ItmInsp_Upd01_Dtl | S107: ItmInsp_UpdChk01_Dtl | U107: ItmInsp_Upd01_Dtl
A108: 30 | D108: sppl_cd | E108: #MA.BP_CD | G108: Supplier cd. | H108: 発注先ＣＤ | I108: E | S108: E | U108: E
A109: 30 | D109: itm_cd | E109: #MA.ITM_CD | G109: Item cd. | H109: 品目ＣＤ | I109: E | S109: E | U109: E
A110: 30 | D110: itm_sub1 | E110: #MA.ITM_SUB1 | G110: Branch No. 1 | H110: 枝番１ | I110: E | S110: E | U110: E
A111: 30 | D111: itm_sub2 | E111: #MA.ITM_SUB2 | G111: Branch No. 2 | H111: 枝番２ | I111: E | S111: E | U111: E
A112: 30 | D112: itm_sub3 | E112: #MA.ITM_SUB3 | G112: Branch No. 3 | H112: 枝番３ | I112: E | S112: E | U112: E
A113: 30 | D113: maker_cd | E113: #MA.BP_CD | G113: Maker cd. | H113: メーカＣＤ | I113: E | S113: E | U113: E
A114: 30 | D114: to_site_cd | E114: #MA.SITE_CD | G114: Factory/Distribution warehouse cd. | H114: 工場・物流倉庫ＣＤ | I114: E | S114: E | U114: E
A115: 30 | D115: st_dt_key | E115: #MA.DT | G115: Application start date_[Before change] | H115: 適用開始日_[変更前] | I115: E | S115: E | U115: E
A116: 30 | D116: st_dt | E116: #MA.DT | G116: Application start date | H116: 適用開始日 | I116: E | S116: E | U116: E
A117: 30 | D117: end_dt | E117: #MA.DT | G117: Application end date | H117: 適用終了日 | I117: E | S117: E | U117: E
A118: 30 | D118: no_insp_flg | E118: #MA.FLG | G118: Not for inspection | H118: 検査対象外 | I118: E | S118: E | U118: E
A119: 30 | D119: insp_ptn_cd | E119: #MA.INSP_PTN_CD | G119: Inspection pattern cd. | H119: 検査パタンＣＤ | I119: E | S119: E | U119: E
... A137: 30 | D137: upd_cntr | E137: #MA.UPD_CNT | G137: Update counter | H137: 更新カウンタ | I137: E | S137: E | U137: E
A138: 30 | D138: mfg_loc_cd | E138: #MA.LOC_CD | G138: Mfg. location cd. | H138: 製造場所ＣＤ | S138: E | U138: E
A139: 30 | D139: from_site_cd | E139: #MA.SITE_CD | G139: Shipping point factory/distribution warehouse cd. | H139: 出荷元工場・物流倉庫ＣＤ | S139: E | U139: E
A141: 40 | B141: * | D141: Upd01_Dtl4 | E141: L | G141: $share$ | H141: MA.MABSL0530.PurcDdlvLt_Upd01.PurcDdlvLt_Upd01_Dtl | W141: PurcDdlvLt_UpdChk01_Dtl | Y141: PurcDdlvLt_Upd01_Dtl
A142: 40 | D142: sppl_cd | E142: #MA.BP_CD | G142: Supplier cd. | H142: 発注先ＣＤ | I142: E | W142: E | Y142: E
A143: 40 | D143: itm_cd | E143: #MA.ITM_CD | G143: Item cd. | H143: 品目ＣＤ | I143: E | W143: E | Y143: E
A144: 40 | D144: itm_sub1 | E144: #MA.ITM_SUB1 | G144: Branch No. 1 | H144: 枝番１ | I144: E | W144: E | Y144: E
A145: 40 | D145: itm_sub2 | E145: #MA.ITM_SUB2 | G145: Branch No. 2 | H145: 枝番２ | I145: E | W145: E | Y145: E
A146: 40 | D146: itm_sub3 | E146: #MA.ITM_SUB3 | G146: Branch No. 3 | H146: 枝番３ | I146: E | W146: E | Y146: E
A147: 40 | D147: lg_grp_cd | E147: #MA.LG_GRP_CD | G147: Distribution group cd. | H147: 物流グループＣＤ | I147: E | W147: E | Y147: E
A148: 40 | D148: st_dt_key | E148: #MA.DT | G148: Application start date_[Before change] | H148: 適用開始日_[変更前] | I148: E | W148: E | Y148: E
A149: 40 | D149: st_dt | E149: #MA.DT | G149: Application start date | H149: 適用開始日 | I149: E | W149: E | Y149: E
A150: 40 | D150: end_dt | E150: #MA.DT | G150: Application end date | H150: 適用終了日 | I150: E | W150: E | Y150: E
A151: 40 | D151: purc_lt | E151: #MA.LT | G151: Purchase LT | H151: 購入ＬＴ | I151: E | W151: E | Y151: E
A152: 40 | D152: purc_lt_add_qty | E152: #MA.QTY | G152: Purchase LT adds standard qty. | H152: 購入ＬＴ加算基準数量 | I152: E | W152: E | Y152: E
A153: 40 | D153: memo1 | E153: #MA.MST_MEMO1 | G153: Memo 1 | H153: メモ１ | I153: E | W153: E | Y153: E
... A157: 40 | D157: upd_cntr | E157: #MA.UPD_CNT | G157: Update counter | H157: 更新カウンタ | I157: E | W157: E | Y157: E
A159: 50 | B159: * | D159: Upd01_Dtl5 | E159: L | G159: $share$ | H159: MA.MABSL1230.EdiIfCtl_Upd01.EdiIfCtl_Upd01_Dtl | AA159: EdiIfCtl_UpdChk01_Dtl | AC159: EdiIfCtl_Upd01_Dtl
A160: 50 | D160: bp_cd | E160: #MA.BP_CD | G160: BP cd. | H160: 取引先ＣＤ | I160: E | AA160: E | AC160: E
A161: 50 | D161: if_proc_typ | E161: #MA.IF_PROC_TYP | G161: IF process type | H161: ＩＦ処理区分 | I161: E | AA161: E | AC161: E
A162: 50 | D162: not_onr_prov_flg | E162: #MA.FLG | G162: Not for chargeable supply | H162: 有償支給対象外 | I162: E | AA162: E | AC162: E
A163: 50 | D163: st_dt_key | E163: #MA.DT | G163: Application start date_[Before change] | H163: 適用開始日_[変更前] | I163: E | AA163: E | AC163: E
A164: 50 | D164: st_dt | E164: #MA.DT | G164: Application start date | H164: 適用開始日 | I164: E | AA164: E | AC164: E
A165: 50 | D165: end_dt | E165: #MA.DT | G165: Application end date | H165: 適用終了日 | I165: E | AA165: E | AC165: E
A166: 50 | D166: ext_sys_cd | E166: #MA.EXT_SYS_CD | G166: External system cd. | H166: 外部システムＣＤ | I166: E | AA166: E | AC166: E
A167: 50 | D167: memo1 | E167: #MA.MST_MEMO1 | G167: Memo 1 | H167: メモ１ | I167: E | AA167: E | AC167: E
A168: 50 | D168: memo2 | E168: #MA.MST_MEMO2 | G168: Memo 2 | H168: メモ２ | I168: E | AA168: E | AC168: E
A169: 50 | D169: memo3 | E169: #MA.MST_MEMO3 | G169: Memo 3 | H169: メモ３ | I169: E | AA169: E | AC169: E
A170: 50 | D170: del_flg | E170: #MA.FLG | G170: Logical delete | H170: 論理削除 | I170: E | AA170: E | AC170: E
A171: 50 | D171: upd_cntr | E171: #MA.UPD_CNT | G171: Update counter | H171: 更新カウンタ | I171: E | AA171: E | AC171: E
A173: 60 | B173: * | D173: Upd01_Dtl6 | E173: L | G173: $share$ | H173: MA.MABSL0640.BpItm_Upd01.BpItm_Upd01_Dtl | AE173: BpItm_UpdChk01_Dtl | AG173: BpItm_Upd01_Dtl
A174: 60 | D174: bp_cd | E174: #MA.BP_CD | G174: BP cd. | H174: 取引先ＣＤ | I174: E | AE174: E | AG174: E
A175: 60 | D175: itm_cd | E175: #MA.ITM_CD | G175: Item cd. | H175: 品目ＣＤ | I175: E | AE175: E | AG175: E
A176: 60 | D176: itm_sub1 | E176: #MA.ITM_SUB1 | G176: Branch No. 1 | H176: 枝番１ | I176: E | AE176: E | AG176: E
A177: 60 | D177: itm_sub2 | E177: #MA.ITM_SUB2 | G177: Branch No. 2 | H177: 枝番２ | I177: E | AE177: E | AG177: E
A178: 60 | D178: itm_sub3 | E178: #MA.ITM_SUB3 | G178: Branch No. 3 | H178: 枝番３ | I178: E | AE178: E | AG178: E
...

Sheet 来歴
A1: 変更来歴
A3: Rev. | H3: 修正番号 | O3: 変更内容 | AQ3: 変更箇所
A4: 1 | O4: 初版
A5: 1.1 | O5: 英語の名称を追記 | AQ5: 全般
