Workbook

Sheet LogicCommon
A2: オペレーション実装仕様書 | B2: ModuleID : | C2: MS | D2: LogicID : | E2: MSBCL6050 | F2: Pj.ID : | G2: MC
B3: SubModuleID : | C3: MSBC | D3: LogicClass : | E3: MSBCL_MfgActRegService | F3: SuperClassPj.ID :
D4: LogicName : | E4: 製造実績登録サービス | F4: SuperLogicID : | G4: MS.MSUDL5010
A5: 概要 : | B5: 製造実績を登録する。
A6: 詳細 :

Sheet MfgActReg_Chk01
A1: * | B1: * | D1: L | E1: 1
A2: * | D2: オペレーション実装仕様書 Operation Specification Implementation Sheet | E2: ModuleID : | F2: =IF(LogicCommon!C2="","",LogicCommon!C2) -> MS | G2: LogicID : | H2: =IF(LogicCommon!E2="","",LogicCommon!E2) -> MSBCL6050 | I2: Ope.ID : | J2: MfgActReg_Chk01 | K2: Pj.ID : | L2: =IF(LogicCommon!G2="","",LogicCommon!G2) -> MC | M2: Ope.Body : | N2: MA.MAUDL5010.Checker
A3: * | D3: =IF(LogicCommon!A3="","",LogicCommon!A3) | E3: SubModuleID : | F3: =IF(LogicCommon!C3="","",LogicCommon!C3) -> MSBC | G3: LogicClass : | H3: =IF(LogicCommon!E3="","",LogicCommon!E3) -> MSBCL_MfgActRegService | I3: Ope.Method : | J3: MfgActReg_Chk01 | K3: SuperClassPj.ID : | L3: =IF(LogicCommon!G3="","",LogicCommon!G3) | O3: Gene.Type : | P3: ALL
A4: * | E4: Version : | F4: 000000 | G4: LogicName : | H4: =IF(LogicCommon!E4="","",LogicCommon!E4) -> 製造実績登録サービス | I4: Ope.Name : | J4: 登録・訂正・取消 | K4: SuperLogicID : | L4: =IF(LogicCommon!G4="","",LogicCommon!G4) -> MS.MSUDL5010 | M4: ImplOpe.ID:
A5: * | E5: ACType :
A6: * | D6: 概要 : | E6: 製造実績の登録・訂正・取消前チェックの共通処理 | AD6: ID | AF6: ID
A7: # | I7: U | K7: K | L7: K | M7: K | N7: K | O7: K | P7: K | Q7: K | R7: K | S7: K | T7: K | U7: K | V7: K | W7: K | X7: K | Y7: K | Z7: K | AA7: K | AB7: K | AC7: o | AE7: o
A8: # | D8: ブロック名 Block Name | E8: 型 Type | G8: super/share | H8: 対象ブロック名 Target Block Name | K8: REQ_UPD_CNT_CHK | L8: REQUIRED | M8: CHK_NUM | N8: SMALL_LARGE | O8: CHK_DT | P8: BEFORE_AFTER | Q8: CHK_PTN | R8: DUPLICATE | S8: TOO_MANY_INPUTS | T8: AT_LEAST_ONE | U8: ONLY_ONE_INPUT | V8: LIST_LOGIC | W8: LIST_OUT | X8: LIST_OUT_BASE | Y8: LIST_IN | Z8: LIST_IN_BASE | AA8: CONST | AB8: NULL_VAL | AC8: TargetName | AE8: TargetName | AI8: ブロック備考 Block Remarks
A9: # | D9: 項目名 Field Name | E9: 型 Type | F9: 桁 Digits | G9: フルネーム Full Name | H9: 日本語名 Japanese Name | I9: 上り項目 Request Message Field | J9: 下り項目 Response Message Field | AG9: 条件および編集方法 Conditions and Editing Methods | AI9: 項目備考 Field Remarks
A10: # | AC10: 上り項目 Request Message Field | AD10: 下り項目 Response Message Field | AE10: 上り項目 Request Message Field | AF10: 下り項目 Response Message Field
A11: 10 | B11: * | D11: MfgActReg_Chk01_Hdr | E11: L
A12: 10 | D12: data_crud_typ | E12: #MA.DATA_CRUD_TYP | G12: Data update type | H12: データ更新区分 | I12: - | J12: E
A13: 10 | D13: peg_no | E13: #MA.INT | G13: Pegging No. | H13: 紐付けＮＯ | I13: E | J13: E | R13: E
A14: 10 | D14: err_flg | E14: #MA.FLG | G14: Error | H14: エラー | I14: - | J14: E
A15: 10 | D15: rtn_sts_typ | E15: #MA.RTN_STS_TYP | G15: Process result status type | H15: 処理結果状況区分 | I15: - | J15: E
A16: 10 | D16: mfg_sts_typ | E16: #MS.MFG_STS_TYP | G16: Mfg. status type | H16: 製造状況区分 | I16: E | J16: E | L16: E | AA16: MSC_MFG_STS_TYP
A17: 10 | D17: mfg_sts_typ_nm | E17: #MS.MFG_STS_TYP_NM | G17: Mfg. status name | H17: 製造状況区分名 | I17: - | J17: -
A18: 10 | D18: itm_cd | E18: #MA.ITM_CD | G18: Item cd. | H18: 品目ＣＤ | I18: - | J18: E
A19: 10 | D19: itm_sub1 | E19: #MA.ITM_SUB1 | G19: Branch No. 1 | H19: 枝番１ | I19: - | J19: E
A20: 10 | D20: itm_sub2 | E20: #MA.ITM_SUB2 | G20: Branch No. 2 | H20: 枝番２ | I20: - | J20: E
A21: 10 | D21: itm_sub3 | E21: #MA.ITM_SUB3 | G21: Branch No. 3 | H21: 枝番３ | I21: - | J21: E
A22: 10 | D22: inst_lot_no | E22: #MA.LOT_NO | G22: Lot No. (Order) | H22: ロットＮＯ（指図） | I22: - | J22: E
A23: 10 | D23: inst_sublot_no | E23: #MA.SUBLOT_NO | G23: Sublot No. (Order) | H23: サブロットＮＯ（指図） | I23: - | J23: E
A24: 10 | D24: sno1 | E24: #MA.SNO1 | G24: SEIBAN No. 1 | H24: 手配ＮＯ１ | I24: - | J24: E
A25: 10 | D25: sno2 | E25: #MA.SNO2 | G25: SEIBAN No. 2 | H25: 手配ＮＯ２ | I25: - | J25: E
A26: 10 | D26: sno3 | E26: #MA.SNO3 | G26: SEIBAN No. 3 | H26: 手配ＮＯ３ | I26: - | J26: E
A27: 10 | D27: sno4 | E27: #MA.SNO4 | G27: SEIBAN No. 4 | H27: 手配ＮＯ４ | I27: - | J27: E
A28: 10 | D28: sno1_mng_typ | E28: #MA.SNO_MNG_TYP | G28: SEIBAN No. 1 management type | H28: 手配ＮＯ１管理区分 | I28: - | J28: E
... A31: 10 | D31: sno4_mng_typ | E31: #MA.SNO_MNG_TYP | G31: SEIBAN No. 4 management type | H31: 手配ＮＯ４管理区分 | I31: - | J31: E
A32: 10 | D32: st_act_tm | E32: #MA.TM | G32: Actual start date and time | H32: 着手実績日時 | I32: E | J32: E | L32: E | O32: tmBfToday | P32: st_end_act:BF
A33: 10 | D33: st_ac_dt | E33: #MA.DT | G33: Start recording date | H33: 着手計上日 | I33: E | J33: E | L33: E | O33: bfToday | P33: st_end_ac:BF
A34: 10 | D34: old_st_ac_dt | E34: #MA.DT | G34: Start recording date before update | H34: 更新前着手計上日 | I34: - | J34: -
A35: 10 | D35: end_act_tm | E35: #MA.TM | G35: Actual end date and time | H35: 終了実績日時 | I35: E | J35: E | O35: tmBfToday | P35: st_end_act:AF
A36: 10 | D36: end_ac_dt | E36: #MA.DT | G36: End recording date | H36: 終了計上日 | I36: E | J36: E | O36: bfToday | P36: st_end_ac:AF
A37: 10 | D37: old_end_ac_dt | E37: #MA.DT | G37: End recording date before update | H37: 更新前終了計上日 | I37: - | J37: -
A38: 10 | D38: itm_mfg_inst_qty | E38: #MA.QTY | G38: Item mfg. order qty. | H38: 品目製造指図数量 | I38: - | J38: E
A39: 10 | D39: base_unit_st_act_qty | E39: #MA.QTY | G39: Start qty. | H39: 着手数量 | I39: E | J39: E | L39: E | M39: positive
A40: 10 | D40: base_unit_yield_qty | E40: #MA.QTY | G40: Conforming qty. | H40: 良品数量 | I40: - | J40: E
A41: 10 | D41: base_unit_dfct_qty | E41: #MA.QTY | G41: Defective qty. | H41: 不良数量 | I41: - | J41: E
A42: 10 | D42: rem_abort_flg | E42: #MA.FLG | G42: Cancel remaining qty. | H42: 残数打切 | I42: E | J42: E
A43: 10 | D43: base_unit_cd | E43: #MA.UNIT_CD | G43: Base unit cd. | H43: 基準単位ＣＤ | I43: - | J43: E
A44: 10 | D44: base_unit_dec_place | E44: #MA.DEC_PLACE | G44: Base unit number of decimal places | H44: 基準単位小数部有効桁数 | I44: - | J44: E
A45: 10 | D45: base_unit_conv_rnd_typ | E45: #MA.RND_TYP | G45: Base unit rounding type | H45: 基準単位端数処理区分 | I45: - | J45: E
A46: 10 | D46: act_usr_cd | E46: #MA.USR_CD | G46: Result management PIC cd. | H46: 実績責任者ＣＤ | I46: E | J46: E | V46: MA.MAUAL0010.Usr | Y46: st_ac_dt | Z46: dt
A47: 10 | D47: act_dpt_cd | E47: #MA.DPT_CD | G47: Result dept. cd. | H47: 実績部門ＣＤ | I47: E | J47: E | V47: MA.MAUAL0010.Dpt | Y47: MAC_DPT_IS_SRCH_TYP.MFG;st_ac_dt;act_usr_cd | Z47: dpt_is_srch_typ;dt;usr_cd
A48: 10 | D48: act_rpt_rmrks | E48: #MS.MFG_ACT_RPT_RMRKS | G48: Mfg. record sheet remarks | H48: 製造記録書備考 | I48: E | J48: E
A49: 10 | D49: intr_rmrks | E49: #MS.MFG_ACT_INTR_RMRKS | G49: Internal remarks | H49: 内部備考 | I49: E | J49: E
A50: 10 | D50: mfg_act_sub_char1 | E50: #MS.MFG_ACT_SUB_CHAR1 | G50: Mfg. result spare 1 | H50: 製造実績予備１ | I50: E | J50: E
A51: 10 | D51: mfg_act_sub_char2 | E51: #MS.MFG_ACT_SUB_CHAR2 | G51: Mfg. result spare 2 | H51: 製造実績予備２ | I51: E | J51: E
A52: 10 | D52: mfg_act_sub_char3 | E52: #MS.MFG_ACT_SUB_CHAR3 | G52: Mfg. result spare 3 | H52: 製造実績予備３ | I52: E | J52: E
A53: 10 | D53: act_prnt_flg | E53: #MA.FLG | G53: Mfg. record sheet issued | H53: 製造記録書発行済 | I53: - | J53: E
A54: 10 | D54: act_prnt_tm | E54: #MA.TM | G54: Mfg. record sheet issued date and time | H54: 製造記録書発行日時 | I54: - | J54: E
A55: 10 | D55: prnt_seq | E55: #MA.PRNT_SEQ | G55: Mfg. record sheet sequence number | H55: 製造記録書連番 | I55: - | J55: E
A56: 10 | D56: itm_yield | E56: #MA.YIELD | G56: Item actual yield | H56: 品目実際収率 | I56: E | J56: E
A57: 10 | D57: mfg_mtd_typ | E57: #MS.MFG_MTD_TYP | G57: Production method type | H57: 生産方法区分 | I57: - | J57: E
A58: 10 | D58: mfg_inst_unit_typ | E58: #MA.MFG_INST_UNIT_TYP | G58: Mfg. order unit type | H58: 製造指図単位区分 | I58: - | J58: E
A59: 10 | D59: sppl_cd | E59: #MA.BP_CD | G59: Subcontractor cd. | H59: 外注先ＣＤ | I59: - | J59: E
... A64: 10 | D64: wg_cd | E64: #MA.WG_CD | G64: WG cd. | H64: ワーキンググループＣＤ | I64: - | J64: E
A65: 10 | D65: mfg_inst_no | E65: #MA.MFG_INST_NO | G65: Mfg. order No. | H65: 製造指図ＮＯ | I65: E | J65: E | K65: E
A66: 10 | D66: mfg_inst_upd_cntr | E66: #MA.UPD_CNT | G66: Mfg. order update counter | H66: 製造指図更新カウンタ | I66: E | J66: E
A67: 10 | D67: mfg_inst_pr_upd_cntr | E67: #MA.UPD_CNT | G67: Production order progress update counter | H67: 製造指図進捗更新カウンタ | I67: E | J67: E
A68: 10 | D68: mfg_act_upd_cntr | E68: #MA.UPD_CNT | G68: Mfg. result update counter | H68: 製造実績更新カウンタ | I68: E | J68: E
A69: 10 | D69: div_seq | E69: #MS.DIV_SEQ | G69: Split sequence number | H69: 分割連番 | I69: E | J69: E
A70: 10 | D70: mfg_act_no | E70: #MA.MFG_ACT_NO | G70: Mfg. result No. | H70: 製造実績ＮＯ | I70: E | J70: E
A71: 10 | D71: itm_ord_no | E71: #MA.ITM_ORD_NO | G71: Item order No. | H71: 品目オーダＮＯ | I71: - | J71: E
A72: 10 | D72: aprv_flg | E72: #MA.FLG | G72: For Approval | H72: 承認対象 | I72: - | J72: E
A73: 10 | D73: mfg_aprv_role_cd | E73: #MA.APRV_ROLE_CD | G73: Mfg. approval role cd. | H73: 製造承認役割ＣＤ | I73: - | J73: E
A74: 10 | D74: old_mfg_aprv_sts_typ | E74: #MS.MFG_APRV_STS_TYP | G74: Mfg. approval status type before update | H74: 更新前製造承認状況区分 | I74: - | J74: E
A75: 10 | D75: old_end_act_tm | E75: #MA.TM | G75: Actual end time before update | H75: 更新前終了実績日時 | I75: - | J75: E
A76: 10 | D76: mfg_aprv_sts_typ | E76: #MS.MFG_APRV_STS_TYP | G76: Mfg. approval status type | H76: 製造承認状況区分 | I76: - | J76: E
A77: 10 | D77: aprv_dt | E77: #MA.DT | G77: Approval date | H77: 承認日 | I77: - | J77: -
... A101: 10 | D101: bkf_failure_cnt | E101: #MA.INT | G101: Number of backflush failed | H101: バックフラッシュ失敗件数 | I101: E | J101: E
A102: 10 | D102: is_src_md_mfg_srv_flg | E102: #MA.FLG | I102: E | J102: E
A104: 20 | B104: * | D104: MfgActReg_Chk01_DtlOper | E104: L
A105: 20 | D105: data_crud_typ | E105: #MA.DATA_CRUD_TYP | G105: Data update type | H105: データ更新区分 | I105: - | J105: E
A106: 20 | D106: hdr_peg_no | E106: #MA.INT | G106: Header pegging No. | H106: ヘッダ紐付けＮＯ | I106: E | J106: E | L106: E
A107: 20 | D107: peg_no | E107: #MA.INT | G107: Operation pegging No. | H107: 工程紐付けＮＯ | I107: E | J107: E | L107: E | R107: E
A108: 20 | D108: err_flg | E108: #MA.FLG | G108: Error | H108: エラー | I108: - | J108: E
A109: 20 | D109: div_seq | E109: #MS.DIV_SEQ | G109: Split sequence number | H109: 分割連番 | I109: - | J109: -
A110: 20 | D110: oper_cd | E110: #MA.OPER_CD | G110: Operation cd. | H110: 工程ＣＤ | I110: - | J110: E
A111: 20 | D111: oper_unit_act_qty | E111: #MA.QTY | G111: Operation unit result qty. | H111: 工程単位実績数量 | I111: E | J111: E | L111: E | N111: 0:
A112: 20 | D112: oper_std_qty | E112: #MA.QTY | G112: Operation base unit qty. | H112: 工程基準単位数量 | I112: - | J112: E
A113: 20 | D113: oper_conv_qty | E113: #MA.QTY | G113: Operation conversion unit qty. | H113: 工程換算単位数量 | I113: - | J113: E
A114: 20 | D114: oper_unit_conv_rnd_typ | E114: #MA.RND_TYP | G114: Operation conversion rounding type | H114: 工程換算端数処理区分 | I114: - | J114: E
A115: 20 | D115: oper_unit_dec_place | E115: #MA.DEC_PLACE | G115: Operation unit number of decimal places | H115: 工程単位小数部有効桁数 | I115: - | J115: E
A116: 20 | D116: oper_unit_cd | E116: #MA.UNIT_CD | G116: Operation unit cd. | H116: 工程単位ＣＤ | I116: - | J116: E
A117: 20 | D117: oper_yield | E117: #MA.YIELD | G117: Operation actual yield | H117: 工程実際収率 | I117: E | J117: E
A118: 20 | D118: disp_seq | E118: #MA.INT | G118: Routing | H118: 工順 | I118: E | J118: E
A119: 20 | D119: oper_act_intr_rmrks | E119: #MS.OPER_ACT_INTR_RMRKS | G119: Internal remarks | H119: 内部備考 | I119: E | J119: E
A120: 20 | D120: oper_act_rpt_rmrks | E120: #MS.OPER_ACT_RPT_RMRKS | G120: Record sheet remarks | H120: 記録書備考 | I120: E | J120: E
A121: 20 | D121: oper_act_sub_char1 | E121: #MS.OPER_ACT_SUB_CHAR1 | G121: Operation spare 1 | H121: 工程予備１ | I121: E | J121: E
A122: 20 | D122: oper_act_sub_char2 | E122: #MS.OPER_ACT_SUB_CHAR2 | G122: Operation spare 2 | H122: 工程予備２ | I122: E | J122: E
A123: 20 | D123: oper_act_sub_char3 | E123: #MS.OPER_ACT_SUB_CHAR3 | G123: Operation spare 3 | H123: 工程予備３ | I123: E | J123: E
... A128: 20 | D128: oper_ord_no | E128: #MA.OPER_ORD_NO | G128: Operation order No. | H128: 工程オーダＮＯ | I128: E | J128: E
A129: 20 | D129: oper_inst_no | E129: #MA.OPER_INST_NO | G129: Operation order No. | H129: 工程指図ＮＯ | I129: E | J129: E | L129: E
A130: 20 | D130: oper_act_no | E130: #MA.OPER_ACT_NO | G130: Operation result No. | H130: 工程実績ＮＯ | I130: E | J130: E
A131: 20 | D131: mes_id | E131: #MS.MES_ID | G131: MES ID | H131: ＭＥＳＩＤ | I131: - | J131: E
A132: 20 | D132: data_no | E132: #MA.IF_DATA_NO | G132: Data No. | H132: データＮＯ | I132: - | J132: E
A133: 20 | D133: arr_act_no | E133: #MA.ARR_ACT_NO | G133: Receipt result No. | H133: 入荷実績ＮＯ | I133: - | J133: E
A134: 20 | D134: purc_act_io_no | E134: #MA.PURC_ACT_IO_NO | G134: Purchase result GR/GI No. | H134: 仕入実績受払ＮＯ | I134: - | J134: E
...

Sheet MfgActReg_Chk02
A1: * | B1: * | D1: L | E1: 1
A2: * | D2: オペレーション実装仕様書 Operation Specification Implementation Sheet | E2: ModuleID : | F2: =IF(LogicCommon!C2="","",LogicCommon!C2) -> MS | G2: LogicID : | H2: =IF(LogicCommon!E2="","",LogicCommon!E2) -> MSBCL6050 | I2: Ope.ID : | J2: MfgActReg_Chk02 | K2: Pj.ID : | L2: =IF(LogicCommon!G2="","",LogicCommon!G2) -> MC | M2: Ope.Body : | N2: MA.MAUDL5010.Checker
A3: * | D3: =IF(LogicCommon!A3="","",LogicCommon!A3) | E3: SubModuleID : | F3: =IF(LogicCommon!C3="","",LogicCommon!C3) -> MSBC | G3: LogicClass : | H3: =IF(LogicCommon!E3="","",LogicCommon!E3) -> MSBCL_MfgActRegService | I3: Ope.Method : | J3: MfgActReg_Chk02 | K3: SuperClassPj.ID : | L3: =IF(LogicCommon!G3="","",LogicCommon!G3) | O3: Gene.Type : | P3: ALL
A4: * | E4: Version : | F4: 000000 | G4: LogicName : | H4: =IF(LogicCommon!E4="","",LogicCommon!E4) -> 製造実績登録サービス | I4: Ope.Name : | J4: 取消前チェック | K4: SuperLogicID : | L4: =IF(LogicCommon!G4="","",LogicCommon!G4) -> MS.MSUDL5010 | M4: ImplOpe.ID:
A5: * | E5: ACType :
A6: * | D6: 概要 : | E6: 製造実績の取消前チェックの共通処理 | AD6: ID | AF6: ID | AH6: ID
A7: # | I7: U | K7: K | L7: K | M7: K | N7: K | O7: K | P7: K | Q7: K | R7: K | S7: K | T7: K | U7: K | V7: K | W7: K | X7: K | Y7: K | Z7: K | AA7: K | AB7: K | AC7: o | AD7: MAR.chk01 | AE7: o | AG7: o
A8: # | D8: ブロック名 Block Name | E8: 型 Type | G8: super/share | H8: 対象ブロック名 Target Block Name | K8: REQ_UPD_CNT_CHK | L8: REQUIRED | M8: CHK_NUM | N8: SMALL_LARGE | O8: CHK_DT | P8: BEFORE_AFTER | Q8: CHK_PTN | R8: DUPLICATE | S8: TOO_MANY_INPUTS | T8: AT_LEAST_ONE | U8: ONLY_ONE_INPUT | V8: LIST_LOGIC | W8: LIST_OUT | X8: LIST_OUT_BASE | Y8: LIST_IN | Z8: LIST_IN_BASE | AA8: CONST | AB8: NULL_VAL | AC8: TargetName | AD8: OPE.MS.MSBCL6050.MfgActReg_Chk01 | AE8: TargetName | AG8: TargetName | AK8: ブロック備考 Block Remarks
A9: # | D9: 項目名 Field Name | E9: 型 Type | F9: 桁 Digits | G9: フルネーム Full Name | H9: 日本語名 Japanese Name | I9: 上り項目 Request Message Field | J9: 下り項目 Response Message Field | AI9: 条件および編集方法 Conditions and Editing Methods | AK9: 項目備考 Field Remarks
A10: # | AC10: 上り項目 Request Message Field | AD10: 下り項目 Response Message Field | AE10: 上り項目 Request Message Field | AF10: 下り項目 Response Message Field | AG10: 上り項目 Request Message Field | AH10: 下り項目 Response Message Field
A11: 10 | B11: * | D11: MfgActReg_Chk02_Hdr | E11: L | AC11: MfgActReg_Chk01_Hdr | AD11: MfgActReg_Chk01_Hdr
A12: 10 | D12: data_crud_typ | E12: #MA.DATA_CRUD_TYP | G12: Data update type | H12: データ更新区分 | I12: - | J12: E | AD12: E
A13: 10 | D13: peg_no | E13: #MA.INT | G13: Pegging No. | H13: 紐付けＮＯ | I13: E | J13: E | AC13: E | AD13: E
A14: 10 | D14: err_flg | E14: #MA.FLG | G14: Error | H14: エラー | I14: - | J14: E | AD14: E
A15: 10 | D15: rtn_sts_typ | E15: #MA.RTN_STS_TYP | G15: Process result status type | H15: 処理結果状況区分 | I15: - | J15: E | AD15: E
A16: 10 | D16: itm_cd | E16: #MA.ITM_CD | G16: Item cd. | H16: 品目ＣＤ | I16: - | J16: E | AD16: E
A17: 10 | D17: itm_sub1 | E17: #MA.ITM_SUB1 | G17: Branch No. 1 | H17: 枝番１ | I17: - | J17: E | AD17: E
A18: 10 | D18: itm_sub2 | E18: #MA.ITM_SUB2 | G18: Branch No. 2 | H18: 枝番２ | I18: - | J18: E | AD18: E
A19: 10 | D19: itm_sub3 | E19: #MA.ITM_SUB3 | G19: Branch No. 3 | H19: 枝番３ | I19: - | J19: E | AD19: E
A20: 10 | D20: sno1 | E20: #MA.SNO1 | G20: SEIBAN No. 1 | H20: 手配ＮＯ１ | I20: - | J20: E | AD20: E
A21: 10 | D21: sno2 | E21: #MA.SNO2 | G21: SEIBAN No. 2 | H21: 手配ＮＯ２ | I21: - | J21: E | AD21: E
A22: 10 | D22: sno3 | E22: #MA.SNO3 | G22: SEIBAN No. 3 | H22: 手配ＮＯ３ | I22: - | J22: E | AD22: E
A23: 10 | D23: sno4 | E23: #MA.SNO4 | G23: SEIBAN No. 4 | H23: 手配ＮＯ４ | I23: - | J23: E | AD23: E
A24: 10 | D24: base_unit_st_act_qty | E24: #MA.QTY | G24: Start qty. | H24: 着手数量 | I24: - | J24: E | AD24: E
A25: 10 | D25: base_unit_yield_qty | E25: #MA.QTY | G25: Conforming qty. | H25: 良品数量 | I25: - | J25: E | AD25: E
... A36: 10 | D36: old_end_act_tm | E36: #MA.TM | G36: Actual end time before update | H36: 更新前終了実績日時 | I36: - | J36: E | AD36: E
A37: 10 | D37: mfg_inst_no | E37: #MA.MFG_INST_NO | G37: Mfg. order No. | H37: 製造指図ＮＯ | I37: E | J37: E | AC37: E | AD37: E
A38: 10 | D38: mfg_inst_upd_cntr | E38: #MA.UPD_CNT | G38: Mfg. order update counter | H38: 製造指図更新カウンタ | I38: E | J38: E | AC38: E | AD38: E
A39: 10 | D39: mfg_inst_pr_upd_cntr | E39: #MA.UPD_CNT | G39: Production order progress update counter | H39: 製造指図進捗更新カウンタ | I39: E | J39: E | AC39: E | AD39: E
A40: 10 | D40: mfg_act_upd_cntr | E40: #MA.UPD_CNT | G40: Mfg. result update counter | H40: 製造実績更新カウンタ | I40: E | J40: E | AC40: E | AD40: E
A41: 10 | D41: div_seq | E41: #MS.DIV_SEQ | G41: Split sequence number | H41: 分割連番 | I41: E | J41: E | AC41: E | AD41: E
A42: 10 | D42: mfg_act_no | E42: #MA.MFG_ACT_NO | G42: Mfg. result No. | H42: 製造実績ＮＯ | I42: E | J42: E | AC42: E | AD42: E
A43: 10 | D43: itm_ord_no | E43: #MA.ITM_ORD_NO | G43: Item order No. | H43: 品目オーダＮＯ | I43: - | J43: E | AD43: E
A44: 10 | D44: itm_mfg_inst_no | E44: #MA.ITM_MFG_INST_NO | G44: Item mfg. order No. | H44: 品目製造指図ＮＯ | I44: - | J44: E | AD44: E
A45: 10 | D45: upd_cntr_chk_flg | E45: #MA.FLG | G45: Check for update counter | H45: 更新カウンタチェック | I45: E | J45: - | AC45: E
A46: 10 | D46: lst_del_flg | E46: #MA.FLG | G46: Bulk cancellation flg. | H46: 一括取消ＦＬＧ | I46: E | J46: -
A47: 10 | D47: is_src_batch_flg | E47: #MA.FLG | G47: Caller batch process | H47: 呼出元バッチ処理 | I47: E | J47: E | AC47: E | AD47: E
A49: 20 | B49: * | D49: MfgActReg_Chk02_DtlOper | E49: L | AC49: MfgActReg_Chk01_DtlOper | AD49: MfgActReg_Chk01_DtlOper
A50: 20 | D50: data_crud_typ | E50: #MA.DATA_CRUD_TYP | G50: Data update type | H50: データ更新区分 | I50: - | J50: E | AD50: E
A51: 20 | D51: hdr_peg_no | E51: #MA.INT | G51: Header pegging No. | H51: ヘッダ紐付けＮＯ | I51: - | J51: E | AC51: E | AD51: E
A52: 20 | D52: peg_no | E52: #MA.INT | G52: Operation pegging No. | H52: 工程紐付けＮＯ | I52: - | J52: E | AC52: E | AD52: E
A53: 20 | D53: err_flg | E53: #MA.FLG | G53: Error | H53: エラー | I53: - | J53: E | AD53: E
A54: 20 | D54: oper_ord_no | E54: #MA.OPER_ORD_NO | G54: Operation order No. | H54: 工程オーダＮＯ | I54: - | J54: E | AD54: E
A55: 20 | D55: oper_inst_no | E55: #MA.OPER_INST_NO | G55: Operation order No. | H55: 工程指図ＮＯ | I55: - | J55: E | AC55: E | AD55: E
A56: 20 | D56: oper_act_no | E56: #MA.OPER_ACT_NO | G56: Operation result No. | H56: 工程実績ＮＯ | I56: - | J56: E | AC56: E | AD56: E
A58: 30 | B58: * | D58: MfgActReg_Chk02_DtlInpt | E58: L | AC58: MfgActReg_Chk01_DtlInpt | AD58: MfgActReg_Chk01_DtlInpt
A59: 30 | D59: data_crud_typ | E59: #MA.DATA_CRUD_TYP | G59: Data update type | H59: データ更新区分 | I59: - | J59: E | AD59: E
A60: 30 | D60: hdr_peg_no | E60: #MA.INT | G60: Header pegging No. | H60: ヘッダ紐付けＮＯ | I60: - | J60: E | AC60: E | AD60: E
A61: 30 | D61: oper_peg_no | E61: #MA.INT | G61: Operation pegging No. | H61: 工程紐付けＮＯ | I61: - | J61: E | AC61: E | AD61: E
A62: 30 | D62: peg_no | E62: #MA.INT | G62: Input pegging No. | H62: 投入紐付けＮＯ | I62: - | J62: E | AC62: E | AD62: E
A63: 30 | D63: err_flg | E63: #MA.FLG | G63: Error | H63: エラー | I63: - | J63: E | AD63: E
A64: 30 | D64: itm_cd | E64: #MA.ITM_CD | G64: Item | H64: 品目 | I64: - | J64: E | AD64: E
A65: 30 | D65: itm_sub1 | E65: #MA.ITM_SUB1 | G65: Branch No. 1 | H65: 枝番１ | I65: - | J65: E | AD65: E
A66: 30 | D66: itm_sub2 | E66: #MA.ITM_SUB2 | G66: Branch No. 2 | H66: 枝番２ | I66: - | J66: E | AD66: E
A67: 30 | D67: itm_sub3 | E67: #MA.ITM_SUB3 | G67: Branch No. 3 | H67: 枝番３ | I67: - | J67: E | AD67: E
A68: 30 | D68: old_ver_no | E68: #MA.VER_NO | G68: Version No. | H68: 版ＮＯ | I68: - | J68: E | AD68: E
A69: 30 | D69: inpt_schd_no | E69: #MA.INPT_ACT_NO | G69: Input schedule No. | H69: 投入予定ＮＯ | I69: - | J69: E | AC69: E | AD69: E
A70: 30 | D70: inpt_act_no | E70: #MA.INPT_ACT_NO | G70: Input result No. | H70: 投入実績ＮＯ | I70: E | J70: E | AC70: E | AD70: E
A71: 30 | D71: can_ac_dt | E71: #MA.DT | G71: Cancellation recording date | H71: 取消計上日 | I71: E | J71: E | O71: bfToday | AC71: E | AD71: E
A73: 40 | B73: * | D73: MfgActReg_Chk02_DtlLoss | E73: L | AC73: MfgActReg_Chk01_DtlLoss | AD73: MfgActReg_Chk01_DtlLoss
A74: 40 | D74: data_crud_typ | E74: #MA.DATA_CRUD_TYP | G74: Data update type | H74: データ更新区分 | I74: - | J74: E | AD74: E
A75: 40 | D75: inpt_peg_no | E75: #MA.INT | G75: Input pegging No. | H75: 投入紐付けＮＯ | I75: - | J75: E | AC75: E | AD75: E
A76: 40 | D76: err_flg | E76: #MA.FLG | G76: Error | H76: エラー | I76: - | J76: E | AD76: E
A77: 40 | D77: fxd_loss_flg | E77: #MA.FLG | G77: Constant loss | H77: 固定ロス | I77: - | J77: E | AD77: E
A78: 40 | D78: loss_act_no | E78: #MA.LOSS_ACT_NO | G78: Loss result No. | H78: ロス実績ＮＯ | I78: - | J78: E | AC78: E | AD78: E
A79: 40 | D79: loss_rsn_cd | E79: #MA.BIZ_RSN_CD | G79: Loss reason cd. | H79: ロス理由ＣＤ | I79: - | J79: E | AD79: E
A81: 50 | B81: * | D81: MfgActReg_Chk02_DtlWk | E81: L | AC81: MfgActReg_Chk01_DtlWk | AD81: MfgActReg_Chk01_DtlWk
A82: 50 | D82: data_crud_typ | E82: #MA.DATA_CRUD_TYP | G82: Data update type | H82: データ更新区分 | I82: - | J82: E | AD82: E
A83: 50 | D83: hdr_peg_no | E83: #MA.INT | G83: Header pegging No. | H83: ヘッダ紐付けＮＯ | I83: - | J83: E | AC83: E | AD83: E
A84: 50 | D84: oper_peg_no | E84: #MA.INT | G84: Operation pegging No. | H84: 工程紐付けＮＯ | I84: - | J84: E | AC84: E | AD84: E
A85: 50 | D85: peg_no | E85: #MA.INT | G85: Man-hour pegging No. | H85: 工数紐付けＮＯ | I85: - | J85: E | AC85: E | AD85: E
A86: 50 | D86: err_flg | E86: #MA.FLG | G86: Error | H86: エラー | I86: - | J86: E | AD86: E
A87: 50 | D87: wk_schd_no | E87: #MA.WK_SCHD_NO | G87: Man-hour schedule No. | H87: 工数予定ＮＯ | I87: - | J87: E | AC87: E | AD87: E
A88: 50 | D88: wk_act_no | E88: #MA.WK_ACT_NO | G88: Man-hour result No. | H88: 工数実績ＮＯ | I88: - | J88: E | AC88: E | AD88: E
A90: 60 | B90: * | D90: MfgActReg_Chk02_DtlYield | E90: L | AC90: MfgActReg_Chk01_DtlYield | AD90: MfgActReg_Chk01_DtlYield
A91: 60 | D91: data_crud_typ | E91: #MA.DATA_CRUD_TYP | G91: Data update type | H91: データ更新区分 | I91: - | J91: E | AD91: E
A92: 60 | D92: hdr_peg_no | E92: #MA.INT | G92: Header pegging No. | H92: ヘッダ紐付けＮＯ | I92: - | J92: E | AC92: E | AD92: E
A93: 60 | D93: oper_peg_no | E93: #MA.INT | G93: Operation pegging No. | H93: 工程紐付けＮＯ | I93: - | J93: E | AC93: E | AD93: E
A94: 60 | D94: peg_no | E94: #MA.INT | G94: Output pegging No. | H94: 出来高紐付けＮＯ | I94: - | J94: E | AC94: E | AD94: E
A95: 60 | D95: err_flg | E95: #MA.FLG | G95: Error | H95: エラー | I95: - | J95: E | AD95: E
A96: 60 | D96: lot_no | E96: #MA.LOT_NO | G96: Lot No. | H96: ロットＮＯ | I96: - | J96: E | AD96: E
A97: 60 | D97: sublot_no | E97: #MA.SUBLOT_NO | G97: Sublot No. | H97: サブロットＮＯ | I97: - | J97: E | AD97: E
A98: 60 | D98: strg_loc_cd | E98: #MA.LOC_CD | G98: Storage location cd. | H98: 格納場所ＣＤ | I98: - | J98: E | AD98: E
A99: 60 | D99: yield_schd_no | E99: #MA.YIELD_SCHD_NO | G99: Output schedule No. | H99: 出来高予定ＮＯ | I99: - | J99: E | AC99: E | AD99: E
A100: 60 | D100: yield_act_no | E100: #MA.YIELD_ACT_NO | G100: Output result No. | H100: 出来高実績ＮＯ | I100: E | J100: E | AC100: E | AD100: E
A101: 60 | D101: can_ac_dt | E101: #MA.DT | G101: Cancellation recording date | H101: 取消計上日 | I101: E | J101: E | O101: bfToday | AC101: E | AD101: E
A102: 60 | D102: not_stk_flg | E102: #MA.FLG | G102: MRO supply | H102: 非在庫 | I102: - | J102: E | AD102: E
A103: 60 | D103: old_lot_no | E103: #MA.LOT_NO | G103: Lot No. before update | H103: 更新前ロットＮＯ | I103: - | J103: E | AD103: E
A104: 60 | D104: old_sublot_no | E104: #MA.SUBLOT_NO | G104: Sublot No. before update | H104: 更新前サブロットＮＯ | I104: - | J104: E | AD104: E
A105: 60 | D105: old_yield_typ | E105: #MA.YIELD_TYP | G105: Output type before update | H105: 更新前出来高区分 | I105: - | J105: E | AD105: E
A106: 60 | D106: old_base_unit_yield_act_qty | E106: #MA.QTY | G106: Base unit output qty. before update | H106: 更新前基準単位出来高数 | I106: - | J106: E | AD106: E
A108: 70 | B108: * | D108: MfgActReg_Chk02_DtlByProd | E108: L | AC108: MfgActReg_Chk01_DtlByProd | AD108: MfgActReg_Chk01_DtlByProd
A109: 70 | D109: data_crud_typ | E109: #MA.DATA_CRUD_TYP | G109: Data update type | H109: データ更新区分 | I109: - | J109: E | AD109: E
A110: 70 | D110: hdr_peg_no | E110: #MA.INT | G110: Header pegging No. | H110: ヘッダ紐付けＮＯ | I110: - | J110: E | AC110: E | AD110: E
A111: 70 | D111: oper_peg_no | E111: #MA.INT | G111: Operation pegging No. | H111: 工程紐付けＮＯ | I111: - | J111: E | AC111: E | AD111: E
A112: 70 | D112: peg_no | E112: #MA.INT | G112: By-product pegging No. | H112: 副産品紐付けＮＯ | I112: - | J112: E | AC112: E | AD112: E
A113: 70 | D113: err_flg | E113: #MA.FLG | G113: Error | H113: エラー | I113: - | J113: E | AD113: E
A114: 70 | D114: itm_cd | E114: #MA.ITM_CD | G114: Item cd. | H114: 品目ＣＤ | I114: - | J114: E | AD114: E
A115: 70 | D115: itm_sub1 | E115: #MA.ITM_SUB1 | G115: Branch No. 1 | H115: 枝番１ | I115: - | J115: E | AD115: E
A116: 70 | D116: itm_sub2 | E116: #MA.ITM_SUB2 | G116: Branch No. 2 | H116: 枝番２ | I116: - | J116: E | AD116: E
...

Sheet MfgActReg_Chk03
A1: * | B1: * | D1: L | E1: 1
A2: * | D2: オペレーション実装仕様書 Operation Specification Implementation Sheet | E2: ModuleID : | F2: =IF(LogicCommon!C2="","",LogicCommon!C2) -> MS | G2: LogicID : | H2: =IF(LogicCommon!E2="","",LogicCommon!E2) -> MSBCL6050 | I2: Ope.ID : | J2: MfgActReg_Chk03 | K2: Pj.ID : | L2: =IF(LogicCommon!G2="","",LogicCommon!G2) -> MC | M2: Ope.Body : | N2: MA.MAUDL5010.Checker
A3: * | D3: =IF(LogicCommon!A3="","",LogicCommon!A3) | E3: SubModuleID : | F3: =IF(LogicCommon!C3="","",LogicCommon!C3) -> MSBC | G3: LogicClass : | H3: =IF(LogicCommon!E3="","",LogicCommon!E3) -> MSBCL_MfgActRegService | I3: Ope.Method : | J3: MfgActReg_Chk03 | K3: SuperClassPj.ID : | L3: =IF(LogicCommon!G3="","",LogicCommon!G3) | O3: Gene.Type : | P3: ALL
A4: * | E4: Version : | F4: 000000 | G4: LogicName : | H4: =IF(LogicCommon!E4="","",LogicCommon!E4) -> 製造実績登録サービス | I4: Ope.Name : | J4: 一括登録・訂正前チェック | K4: SuperLogicID : | L4: =IF(LogicCommon!G4="","",LogicCommon!G4) -> MS.MSUDL5010 | M4: ImplOpe.ID:
A5: * | E5: ACType :
A6: * | D6: 概要 : | E6: 製造実績の一括登録・訂正前チェックの共通処理 | AD6: ID | AE6: ID | AF6: ID
A7: # | I7: U | K7: K | L7: K | M7: K | N7: K | O7: K | P7: K | Q7: K | R7: K | S7: K | T7: K | U7: K | V7: K | W7: K | X7: K | Y7: K | Z7: K | AA7: K | AB7: K | AC7: o | AE7: o
A8: # | D8: ブロック名 Block Name | E8: 型 Type | G8: super/share | H8: 対象ブロック名 Target Block Name | K8: REQ_UPD_CNT_CHK | L8: REQUIRED | M8: CHK_NUM | N8: SMALL_LARGE | O8: CHK_DT | P8: BEFORE_AFTER | Q8: CHK_PTN | R8: DUPLICATE | S8: TOO_MANY_INPUTS | T8: AT_LEAST_ONE | U8: ONLY_ONE_INPUT | V8: LIST_LOGIC | W8: LIST_OUT | X8: LIST_OUT_BASE | Y8: LIST_IN | Z8: LIST_IN_BASE | AA8: CONST | AB8: NULL_VAL | AC8: TargetName | AE8: TargetName | AI8: ブロック備考 Block Remarks
A9: # | D9: 項目名 Field Name | E9: 型 Type | F9: 桁 Digits | G9: フルネーム Full Name | H9: 日本語名 Japanese Name | I9: 上り項目 Request Message Field | J9: 下り項目 Response Message Field | AG9: 条件および編集方法 Conditions and Editing Methods | AI9: 項目備考 Field Remarks
A10: # | AC10: 上り項目 Request Message Field | AD10: 下り項目 Response Message Field | AE10: 上り項目 Request Message Field | AF10: 下り項目 Response Message Field
A11: 10 | B11: * | D11: MfgActReg_Chk03_Ctrl | E11: R
A12: 10 | D12: oper_unit_flg | E12: #MA.FLG | G12: Operation unit result | H12: 工程単位実績 | I12: E
A13: 10 | D13: is_src_batch_flg | E13: #MA.FLG | G13: Caller batch process | H13: 呼出元バッチ処理 | I13: E
A14: 10 | D14: upd_cntr_chk_flg | E14: #MA.FLG | G14: Check for update counter | H14: 更新カウンタチェック | I14: E
A16: 20 | B16: * | D16: MfgActReg_Chk03_Hdr1 | E16: L
A17: 20 | D17: peg_no | E17: #MA.INT | G17: Pegging No. | H17: 紐付けＮＯ | I17: E | J17: E | L17: E | R17: E
A18: 20 | D18: err_flg | E18: #MA.FLG | G18: Error | H18: エラー | J18: E
A19: 20 | D19: rtn_sts_typ | E19: #MA.RTN_STS_TYP | G19: Process result status type | H19: 処理結果状況区分 | J19: E
A20: 20 | D20: st_act_tm | E20: #MA.TM | G20: Actual start date | H20: 着手実績日 | I20: E | L20: E
A21: 20 | D21: st_ac_dt | E21: #MA.DT | G21: Start recording date | H21: 着手計上日 | I21: E | L21: E
A22: 20 | D22: end_act_tm | E22: #MA.TM | G22: Actual end date | H22: 終了実績日 | I22: E
A23: 20 | D23: end_ac_dt | E23: #MA.DT | G23: End recording date | H23: 終了計上日 | I23: E
A24: 20 | D24: base_unit_st_act_qty | E24: #MA.QTY | G24: Start qty. | H24: 着手数量 | I24: E | L24: E | M24: positive
A25: 20 | D25: oper_unit_act_qty | E25: #MA.QTY | G25: Operation unit result qty. | H25: 工程単位実績数量 | I25: E | L25: E | N25: 0:
A26: 20 | D26: mfg_inst_no | E26: #MA.MFG_INST_NO | G26: Mfg. order No. | H26: 製造指図ＮＯ | I26: E | K26: E
A27: 20 | D27: div_seq | E27: #MS.DIV_SEQ | G27: Split sequence number | H27: 分割連番 | I27: E
A28: 20 | D28: mfg_act_no | E28: #MA.MFG_ACT_NO | G28: Mfg. result No. | H28: 製造実績ＮＯ | I28: E
A29: 20 | D29: mfg_inst_upd_cntr | E29: #MA.UPD_CNT | G29: Mfg. order update counter | H29: 製造指図更新カウンタ | I29: E
A30: 20 | D30: mfg_inst_pr_upd_cntr | E30: #MA.UPD_CNT | G30: Production order progress update counter | H30: 製造指図進捗更新カウンタ | I30: E
A31: 20 | D31: mfg_act_upd_cntr | E31: #MA.UPD_CNT | G31: Mfg. result update counter | H31: 製造実績更新カウンタ | I31: E
A33: 30 | B33: * | D33: MfgActReg_Chk03_Hdr2 | E33: L
A34: 30 | D34: peg_no | E34: #MA.INT | G34: Pegging No. | H34: 紐付けＮＯ | I34: E | J34: E | L34: E | R34: E
A35: 30 | D35: err_flg | E35: #MA.FLG | G35: Error | H35: エラー | J35: E
A36: 30 | D36: mfg_sts_typ | E36: #MS.MFG_STS_TYP | G36: Mfg. status type | H36: 製造状況区分 | I36: E | J36: E | L36: E
A37: 30 | D37: st_act_tm | E37: #MA.TM | G37: Actual start date | H37: 着手実績日 | I37: E | L37: E
A38: 30 | D38: st_ac_dt | E38: #MA.DT | G38: Start recording date | H38: 着手計上日 | I38: E | L38: E
A39: 30 | D39: end_act_tm | E39: #MA.TM | G39: Actual end date | H39: 終了実績日 | I39: E
A40: 30 | D40: end_ac_dt | E40: #MA.DT | G40: End recording date | H40: 終了計上日 | I40: E
A41: 30 | D41: base_unit_st_act_qty | E41: #MA.QTY | G41: Start qty. | H41: 着手数量 | I41: E | M41: positive
A42: 30 | D42: mfg_inst_no | E42: #MA.MFG_INST_NO | G42: Mfg. order No. | H42: 製造指図ＮＯ | I42: E | K42: E
A43: 30 | D43: div_seq | E43: #MS.DIV_SEQ | G43: Split sequence number | H43: 分割連番 | I43: E
A44: 30 | D44: mfg_act_no | E44: #MA.MFG_ACT_NO | G44: Mfg. result No. | H44: 製造実績ＮＯ | I44: E
A45: 30 | D45: mfg_inst_upd_cntr | E45: #MA.UPD_CNT | G45: Mfg. order update counter | H45: 製造指図更新カウンタ | I45: E
A46: 30 | D46: mfg_inst_pr_upd_cntr | E46: #MA.UPD_CNT | G46: Production order progress update counter | H46: 製造指図進捗更新カウンタ | I46: E
A47: 30 | D47: mfg_act_upd_cntr | E47: #MA.UPD_CNT | G47: Mfg. result update counter | H47: 製造実績更新カウンタ | I47: E
A49: 40 | B49: * | D49: MfgActReg_Chk03_DtlYieldByProd | E49: L
A50: 40 | D50: peg_no | E50: #MA.INT | G50: Pegging No. | H50: 紐付けＮＯ | I50: E | L50: E | R50: E
A51: 40 | D51: err_flg | E51: #MA.FLG | G51: Error | H51: エラー
A52: 40 | D52: hdr_peg_no | E52: #MA.INT | G52: Header pegging No. | H52: ヘッダ紐付けＮＯ | I52: E | L52: E
A53: 40 | D53: yield_typ | E53: #MA.YIELD_TYP | G53: Output type | H53: 出来高区分 | I53: E | L53: E
A54: 40 | D54: itm_cd | E54: #MA.ITM_CD | G54: Item cd. | H54: 品目ＣＤ | I54: E
A55: 40 | D55: itm_sub1 | E55: #MA.ITM_SUB1 | G55: Branch No. 1 | H55: 枝番１ | I55: E
A56: 40 | D56: itm_sub2 | E56: #MA.ITM_SUB2 | G56: Branch No. 2 | H56: 枝番２ | I56: E
A57: 40 | D57: itm_sub3 | E57: #MA.ITM_SUB3 | G57: Branch No. 3 | H57: 枝番３ | I57: E
A58: 40 | D58: trd_unit_cd | E58: #MA.UNIT_CD | G58: Unit cd. | H58: 単位ＣＤ | I58: E | L58: E
A59: 40 | D59: trd_unit_yield_act_qty | E59: #MA.QTY | G59: Output qty. | H59: 出来高数量 | I59: E | L59: E | N59: 0:
A60: 40 | D60: act_tm | E60: #MA.TM | G60: Actual date | H60: 実績日 | I60: E | L60: E
A61: 40 | D61: ac_dt | E61: #MA.DT | G61: Recording date | H61: 計上日 | I61: E | L61: E
A62: 40 | D62: can_ac_dt | E62: #MA.DT | G62: Cancellation recording date | H62: 取消計上日 | I62: E
A63: 40 | D63: quality_typ | E63: #MA.QUALITY_TYP | G63: Conforming type | H63: 良品区分 | I63: E | L63: E
A64: 40 | D64: gd_cd | E64: #MA.STK_GD_CD | G64: Grading cd. | H64: 格付ＣＤ | I64: E | L64: E
A65: 40 | D65: strg_loc_cd | E65: #MA.LOC_CD | G65: Storage location cd. | H65: 格納場所ＣＤ | I65: E | L65: E
D66: 詳細 :

Sheet MfgActReg_Chk04
A1: * | B1: * | D1: L | E1: 1
A2: * | D2: オペレーション実装仕様書 Operation Specification Implementation Sheet | E2: ModuleID : | F2: =IF(LogicCommon!C2="","",LogicCommon!C2) -> MS | G2: LogicID : | H2: =IF(LogicCommon!E2="","",LogicCommon!E2) -> MSBCL6050 | I2: Ope.ID : | J2: MfgActReg_Chk04 | K2: Pj.ID : | L2: =IF(LogicCommon!G2="","",LogicCommon!G2) -> MC | M2: Ope.Body : | N2: MA.MAUDL5010.Checker
A3: * | D3: =IF(LogicCommon!A3="","",LogicCommon!A3) | E3: SubModuleID : | F3: =IF(LogicCommon!C3="","",LogicCommon!C3) -> MSBC | G3: LogicClass : | H3: =IF(LogicCommon!E3="","",LogicCommon!E3) -> MSBCL_MfgActRegService | I3: Ope.Method : | J3: MfgActReg_Chk04 | K3: SuperClassPj.ID : | L3: =IF(LogicCommon!G3="","",LogicCommon!G3) | O3: Gene.Type : | P3: ALL
A4: * | E4: Version : | F4: 000000 | G4: LogicName : | H4: =IF(LogicCommon!E4="","",LogicCommon!E4) -> 製造実績登録サービス | I4: Ope.Name : | J4: 工数実績登録・訂正前チェック | K4: SuperLogicID : | L4: =IF(LogicCommon!G4="","",LogicCommon!G4) -> MS.MSUDL5010 | M4: ImplOpe.ID:
A5: * | E5: ACType :
A6: * | D6: 概要 : | E6: 工数実績の登録・訂正前チェックを行う。 | AD6: ID | AF6: ID | AH6: ID
A7: # | I7: U | K7: K | L7: K | M7: K | N7: K | O7: K | P7: K | Q7: K | R7: K | S7: K | T7: K | U7: K | V7: K | W7: K | X7: K | Y7: K | Z7: K | AA7: K | AB7: K | AC7: o | AE7: o | AG7: o
A8: # | D8: ブロック名 Block Name | E8: 型 Type | G8: super/share | H8: 対象ブロック名 Target Block Name | K8: REQ_UPD_CNT_CHK | L8: REQUIRED | M8: CHK_NUM | N8: SMALL_LARGE | O8: CHK_DT | P8: BEFORE_AFTER | Q8: CHK_PTN | R8: DUPLICATE | S8: TOO_MANY_INPUTS | T8: AT_LEAST_ONE | U8: ONLY_ONE_INPUT | V8: LIST_LOGIC | W8: LIST_OUT | X8: LIST_OUT_BASE | Y8: LIST_IN | Z8: LIST_IN_BASE | AA8: CONST | AB8: NULL_VAL | AE8: TargetName | AG8: TargetName | AK8: ブロック備考 Block Remarks
A9: # | D9: 項目名 Field Name | E9: 型 Type | F9: 桁 Digits | G9: フルネーム Full Name | H9: 日本語名 Japanese Name | I9: 上り項目 Request Message Field | J9: 下り項目 Response Message Field | AI9: 条件および編集方法 Conditions and Editing Methods | AK9: 項目備考 Field Remarks
A10: # | AC10: 上り項目 Request Message Field | AD10: 下り項目 Response Message Field | AE10: 上り項目 Request Message Field | AF10: 下り項目 Response Message Field | AG10: 上り項目 Request Message Field | AH10: 下り項目 Response Message Field
A11: 10 | B11: * | D11: MfgActReg_Chk04_Rslt | E11: L
A12: 10 | D12: peg_no | E12: #MA.INT | G12: Pegging No. | H12: 紐付けＮＯ | I12: E | J12: E
A13: 10 | D13: err_flg | E13: #MA.FLG | G13: Error flg. | H13: エラーＦＬＧ | I13: - | J13: E
A14: 10 | D14: data_crud_typ | E14: #MA.DATA_CRUD_TYP | G14: Data update type | H14: データ更新区分 | I14: E | J14: E
A15: 10 | D15: inst_wk_act_flg | E15: #MA.FLG | G15: Order direct man-hour result | H15: 指図工数実績 | I15: E | J15: E
A16: 10 | D16: mfg_inst_no | E16: #MA.MFG_INST_NO | G16: Mfg. order No. | H16: 製造指図ＮＯ | I16: E | J16: E
A17: 10 | D17: div_seq | E17: #MS.DIV_SEQ | G17: Split sequence number | H17: 分割連番 | I17: E | J17: E
A18: 10 | D18: disp_seq | E18: #MA.INT | G18: Display order | H18: 表示順 | I18: - | J18: -
A19: 10 | D19: oper_ptn | E19: #MA.OPER_PTN | G19: Operation pattern | H19: 工程パタン | I19: - | J19: -
A20: 10 | D20: oper_disp_seq | E20: #MA.INT | G20: Routing | H20: 工順 | I20: - | J20: -
A21: 10 | D21: oper_cd | E21: #MA.OPER_CD | G21: Operation cd. | H21: 工程ＣＤ | I21: E | J21: E | V21: MA.MAUAL0010.Oper | W21: oper_nm | Y21: true | Z21: mode_nullval_flg
A22: 10 | D22: oper_nm | E22: #MA.OPER_NM | G22: Operation name | H22: 工程名 | I22: - | J22: E
A23: 10 | D23: oper_seq | E23: #MA.OPER_SEQ | G23: Operation sequence number | H23: 工程連番 | I23: - | J23: -
A24: 10 | D24: wk_cost_cd | E24: #MA.WK_COST_CD | G24: Work element cd. | H24: 工数管理ＣＤ | I24: E | J24: E | V24: MA.MAUAL0010.WkCost | W24: wk_cost_nm;wk_cost_unit_nm;wk_cost_dec_place;wk_cost_rnd_typ | X24: wk_cost_nm;wk_cost_unit_nm;dec_place;rnd_typ
A25: 10 | D25: wk_cost_nm | E25: #MA.WK_COST_NM | G25: Work element name | H25: 工数管理名 | I25: - | J25: E
A26: 10 | D26: ac_dt | E26: #MA.DT | G26: Recording date | H26: 計上日 | I26: E | J26: E | L26: E | O26: bfToday
A27: 10 | D27: old_ac_dt | E27: #MA.DT | G27: Recording date before update | H27: 更新前計上日 | I27: - | J27: E
A28: 10 | D28: st_tm | E28: #MA.TM | G28: Start time | H28: 着手時刻 | I28: E | J28: E
A29: 10 | D29: end_tm | E29: #MA.TM | G29: End time | H29: 終了時刻 | I29: E | J29: E
A30: 10 | D30: brk_pd | E30: #MA.INT4 | G30: Downtime | H30: 中断時間 | I30: E | J30: E | N30: 0:1440
A31: 10 | D31: schd_sum_wk_cost | E31: #MA.WK_COST_QTY | G31: Schedule man-hour | H31: 予定工数 | I31: - | J31: -
A32: 10 | D32: schd_wk_cost | E32: #MA.WK_COST_QTY | G32: Schedule man-hour (Qty.-dependent) | H32: 予定工数（数量依存） | I32: - | J32: -
A33: 10 | D33: schd_fxd_wk_cost | E33: #MA.WK_COST_QTY | G33: Schedule man-hour (Constant) | H33: 予定工数（固定） | I33: - | J33: -
A34: 10 | D34: act_wk_cost | E34: #MA.WK_COST_QTY | G34: Result man-hour | H34: 実績工数 | I34: E | J34: E
A35: 10 | D35: abort_flg | E35: #MA.FLG | G35: Cancel remaining | H35: 打切 | I35: E | J35: E
A36: 10 | D36: rem_wk_cost | E36: #MA.WK_COST_QTY | G36: Remaining man-hour | H36: 残工数 | I36: - | J36: -
A37: 10 | D37: wk_cost_unit_nm | E37: #MA.WK_COST_UNIT_NM | G37: Work element unit name | H37: 工数管理単位名 | I37: - | J37: E
A38: 10 | D38: wk_cost_dec_place | E38: #MA.DEC_PLACE | G38: Number of decimal places | H38: 小数部有効桁数 | I38: - | J38: E
A39: 10 | D39: wk_cost_rnd_typ | E39: #MA.RND_TYP | G39: Rounding type | H39: 端数処理区分 | I39: - | J39: E
A40: 10 | D40: wk_day_cd | E40: #MA.WK_DAY_CD | G40: Work type cd. | H40: 勤務種類ＣＤ | I40: E | J40: E | V40: MA.MAUAL0010.WkDay | W40: wk_day_nm
A41: 10 | D41: wk_day_nm | E41: #MA.WK_DAY_NM | G41: Work type name | H41: 勤務種類名 | I41: - | J41: E
A42: 10 | D42: wk_rsn_cd | E42: #MA.WK_RSN_CD | G42: Man-hour reason cd. | H42: 工数理由ＣＤ | I42: E | J42: E | V42: MA.MAUAL0010.WkRsn | W42: wk_rsn_nm
A43: 10 | D43: wk_rsn_nm | E43: #MA.WK_RSN_NM | G43: Man-hour reason name | H43: 工数理由名 | I43: - | J43: E
A44: 10 | D44: dpt_cd | E44: #MA.DPT_CD | G44: Dept. cd. | H44: 部門ＣＤ | I44: E | J44: E | V44: MA.MAUAL0010.Dpt | W44: dpt_nm;dpt_wg_cd;dpt_wg_nm | X44: dpt_nm;wg_cd;wg_nm | Y44: ac_dt | Z44: dt
A45: 10 | D45: dpt_nm | E45: #MA.DPT_NM | G45: Dept. name | H45: 部門名 | I45: - | J45: E
A46: 10 | D46: loc_cd | E46: #MA.LOC_CD | G46: Location cd. | H46: 場所ＣＤ | I46: E | J46: E | V46: MA.MAUAL0010.Loc | W46: loc_nm;loc_wg_cd;loc_wg_nm;site_cd;site_nm;loc_grp_cd;loc_grp_nm;str_ln_tgt_flg | X46: loc_nm;wg_cd;wg_nm;site_cd;site_nm;loc_grp_cd;loc_grp_nm;str_ln_tgt_flg | Y46: MAC_LOC_IS_SRCH_TYP.MFG_WG_HOUSE | Z46: loc_is_srch_typ
A47: 10 | D47: loc_nm | E47: #MA.LOC_NM | G47: Location name | H47: 場所名 | I47: - | J47: E
A48: 10 | D48: str_ln_tgt_flg | E48: #MA.FLG | G48: For rack/line | H48: 棚・ライン対象 | I48: - | J48: E
A49: 10 | D49: str_ln_cd | E49: #MA.STR_LN_CD | G49: Rack/Line cd. | H49: 棚・ラインＣＤ | I49: E | J49: E | V49: MA.MAUAL0010.StrLn | W49: str_ln_nm | Y49: loc_cd;true | Z49: loc_cd;mode_nullval_flg
A50: 10 | D50: str_ln_nm | E50: #MA.STR_LN_NM | G50: Rack/Line name | H50: 棚・ライン名 | I50: - | J50: E
A51: 10 | D51: str_ln_cd_none_flg | E51: #MA.FLG | G51: Without rack/line | H51: 棚・ライン無 | I51: - | J51: E
A52: 10 | D52: wk_usr_cd | E52: #MA.USR_CD | G52: Worker cd. | H52: 作業者ＣＤ | I52: E | J52: E | V52: MA.MAUAL0010.Usr | W52: wk_usr_nm | X52: usr_nm
A53: 10 | D53: wk_usr_nm | E53: #MA.USR_NM | G53: Worker name | H53: 作業者名 | I53: - | J53: E
A54: 10 | D54: wk_usr_dpt_cd | E54: #MA.DPT_CD | G54: Worker dept. cd. | H54: 作業者部門ＣＤ | I54: E | J54: E | V54: MA.MAUAL0010.Dpt | W54: wk_usr_dpt_nm | X54: dpt_nm | Y54: ac_dt;wk_usr_cd;MAC_DPT_IS_SRCH_TYP.MFG | Z54: dt;usr_cd;dpt_is_srch_typ
A55: 10 | D55: wk_usr_dpt_nm | E55: #MA.DPT_NM | G55: Worker dept. | H55: 作業者部門名 | I55: - | J55: E
A56: 10 | D56: fclty | E56: #MA.FCLTY | G56: Equipment | H56: 設備 | I56: E | J56: E
A57: 10 | D57: wk_cost_calc_flg | E57: #MA.FLG | G57: Auto-calculate man-hour | H57: 自動工数計算 | I57: - | J57: -
A58: 10 | D58: wk_cost_calc_ctl_flg | E58: #MA.FLG | G58: Allow update of man-hour auto-calculation | H58: 自動工数計算更新許可 | I58: E | J58: E
A59: 10 | D59: schd_intr_rmrks | E59: #MS.WK_SCHD_INTR_RMRKS | G59: Internal remarks (Schedule) | H59: 内部備考（予定） | I59: - | J59: -
A60: 10 | D60: schd_sub_char1 | E60: #MS.WK_SCHD_SUB_CHAR1 | G60: Spare 1 (Schedule) | H60: 予備１（予定） | I60: - | J60: -
A61: 10 | D61: schd_sub_char2 | E61: #MS.WK_SCHD_SUB_CHAR2 | G61: Spare 2 (Schedule) | H61: 予備２（予定） | I61: - | J61: -
A62: 10 | D62: schd_sub_char3 | E62: #MS.WK_SCHD_SUB_CHAR3 | G62: Spare 3 (Schedule) | H62: 予備３（予定） | I62: - | J62: -
A63: 10 | D63: act_intr_rmrks | E63: #MS.WK_ACT_INTR_RMRKS | G63: Internal remarks (Result) | H63: 内部備考（実績） | I63: E | J63: E
A64: 10 | D64: act_sub_char1 | E64: #MS.WK_ACT_SUB_CHAR1 | G64: Spare 1 (Result) | H64: 予備１（実績） | I64: E | J64: E
A65: 10 | D65: act_sub_char2 | E65: #MS.WK_ACT_SUB_CHAR2 | G65: Spare 2 (Result) | H65: 予備２（実績） | I65: E | J65: E
A66: 10 | D66: act_sub_char3 | E66: #MS.WK_ACT_SUB_CHAR3 | G66: Spare 3 (Result) | H66: 予備３（実績） | I66: E | J66: E
... A69: 10 | D69: itm_sub2 | E69: #MA.ITM_SUB2 | G69: Branch No. 2 | H69: 枝番２ | I69: E | J69: E
A70: 10 | D70: itm_sub3 | E70: #MA.ITM_SUB3 | G70: Branch No. 3 | H70: 枝番３ | I70: E | J70: E | V70: MA.MAUAL0010.ItmSub3 | W70: itm_nm;lot_mng_typ;sublot_mng_typ;sno1_mng_typ;sno2_mng_typ;sno3_mng_typ;sno4_mng_typ | Y70: MAC_ITM_IS_SRCH_TYP.STK1;itm_cd;itm_sub1;itm_sub2 | Z70: itm_is_srch_typ;itm_cd;itm_sub1;itm_sub2
A71: 10 | D71: itm_nm | E71: #MA.ITM_NM | G71: Item name | H71: 品名 | I71: - | J71: E
A72: 10 | D72: lot_mng_typ | E72: #MA.LOT_MNG_TYP | G72: Lot management type | H72: ロット管理区分 | I72: - | J72: E
A73: 10 | D73: sublot_mng_typ | E73: #MA.SUBLOT_MNG_TYP | G73: Sublot management type | H73: サブロット管理区分 | I73: - | J73: E
A74: 10 | D74: sno1_mng_typ | E74: #MA.SNO_MNG_TYP | G74: SEIBAN No. 1 management type | H74: 手配ＮＯ１管理区分 | I74: - | J74: E
A75: 10 | D75: sno2_mng_typ | E75: #MA.SNO_MNG_TYP | G75: SEIBAN No. 2 management type | H75: 手配ＮＯ２管理区分 | I75: - | J75: E
A76: 10 | D76: sno3_mng_typ | E76: #MA.SNO_MNG_TYP | G76: SEIBAN No. 3 management type | H76: 手配ＮＯ３管理区分 | I76: - | J76: E
A77: 10 | D77: sno4_mng_typ | E77: #MA.SNO_MNG_TYP | G77: SEIBAN No. 4 management type | H77: 手配ＮＯ４管理区分 | I77: - | J77: E
A78: 10 | D78: lot_no | E78: #MA.LOT_NO | G78: Lot No. | H78: ロットＮＯ | I78: E | J78: E | V78: MS.MSUAL0070.LotNo | Y78: itm_cd;itm_sub1;itm_sub2;itm_sub3 | Z78: itm_cd;itm_sub1;itm_sub2;itm_sub3
A79: 10 | D79: sublot_no | E79: #MA.SUBLOT_NO | G79: Sublot No. | H79: サブロットＮＯ | I79: E | J79: E | V79: MS.MSUAL0070.SublotNo | Y79: itm_cd;itm_sub1;itm_sub2;itm_sub3;lot_no | Z79: itm_cd;itm_sub1;itm_sub2;itm_sub3;lot_no
A80: 10 | D80: sno1 | E80: #MA.SNO1 | G80: SEIBAN No. 1 | H80: 手配ＮＯ１ | I80: E | J80: E
A81: 10 | D81: sno2 | E81: #MA.SNO2 | G81: SEIBAN No. 2 | H81: 手配ＮＯ２ | I81: E | J81: E
A82: 10 | D82: sno3 | E82: #MA.SNO3 | G82: SEIBAN No. 3 | H82: 手配ＮＯ３ | I82: E | J82: E
A83: 10 | D83: sno4 | E83: #MA.SNO4 | G83: SEIBAN No. 4 | H83: 手配ＮＯ４ | I83: E | J83: E
A84: 10 | D84: wrk_no | E84: #MA.WRK_NO | G84: Sales project No. | H84: 案件ＮＯ | I84: - | J84: E
A85: 10 | D85: wrk_nm | E85: #MA.WRK_NM | G85: Sales project name | H85: 案件名 | I85: - | J85: E
A86: 10 | D86: oper_st_schd_dt | E86: #MA.DT | G86: Scheduled operation start date | H86: 工程着手予定日 | I86: - | J86: -
A87: 10 | D87: oper_st_schd_hm | E87: #MA.TM | G87: Scheduled operation start time | H87: 工程着手予定時刻 | I87: - | J87: -
A88: 10 | D88: oper_end_schd_dt | E88: #MA.DT | G88: Scheduled operation end date | H88: 工程終了予定日 | I88: - | J88: -
A89: 10 | D89: oper_end_schd_hm | E89: #MA.TM | G89: Scheduled operation end time | H89: 工程終了予定時刻 | I89: - | J89: -
A90: 10 | D90: wk_mfg_sts_typ | E90: #MS.MFG_STS_TYP | G90: Status (Man-hours) | H90: 状況（工数） | I90: - | J90: -
A91: 10 | D91: wk_mfg_sts_typ_nm | E91: #MS.MFG_STS_TYP_NM | G91: Status name (Man-hours) | H91: 状況名（工数） | I91: - | J91: -
... A101: 10 | D101: oper_act_no | E101: #MA.OPER_ACT_NO | G101: Operation result No. | H101: 工程実績ＮＯ | I101: - | J101: E
A102: 10 | D102: wk_act_no | E102: #MA.WK_ACT_NO | G102: Man-hour result No. | H102: 工数実績ＮＯ | I102: E | J102: E | R102: E
A103: 10 | D103: dpt_wg_cd | E103: #MA.WG_CD | G103: Dept. WG cd. | H103: 部門ワーキンググループＣＤ | I103: - | J103: E
A104: 10 | D104: dpt_wg_nm | E104: #MA.WG_NM | G104: Dept. WG name | H104: 部門ワーキンググループ名 | I104: - | J104: E
A105: 10 | D105: loc_wg_cd | E105: #MA.WG_CD | G105: Location WG cd. | H105: 場所ワーキンググループＣＤ | I105: - | J105: E
A106: 10 | D106: loc_wg_nm | E106: #MA.WG_NM | G106: Location WG name | H106: 場所ワーキンググループ名 | I106: - | J106: E
A107: 10 | D107: loc_grp_cd | E107: #MA.LOC_GRP_CD | G107: Location group cd. | H107: 場所グループＣＤ | I107: - | J107: E
A108: 10 | D108: loc_grp_nm | E108: #MA.LOC_GRP_NM | G108: Location group name | H108: 場所グループ名 | I108: - | J108: E
A109: 10 | D109: site_cd | E109: #MA.SITE_CD | G109: Factory/Distribution warehouse cd. | H109: 工場・物流倉庫ＣＤ | I109: - | J109: E
A110: 10 | D110: site_nm | E110: #MA.SITE_NM | G110: Factory/Distribution warehouse name | H110: 工場・物流倉庫名 | I110: - | J110: E
A111: 10 | D111: itm_typ | E111: #MA.ITM_TYP | G111: Item type | H111: 品目区分 | I111: - | J111: -
...

Sheet MfgActReg_Chk05
A1: * | B1: * | D1: L | E1: 1
A2: * | D2: オペレーション実装仕様書 Operation Specification Implementation Sheet | E2: ModuleID : | F2: =IF(LogicCommon!C2="","",LogicCommon!C2) -> MS | G2: LogicID : | H2: =IF(LogicCommon!E2="","",LogicCommon!E2) -> MSBCL6050 | I2: Ope.ID : | J2: MfgActReg_Chk05 | K2: Pj.ID : | L2: =IF(LogicCommon!G2="","",LogicCommon!G2) -> MC | M2: Ope.Body : | N2: MA.MAUDL5010.Checker
A3: * | D3: =IF(LogicCommon!A3="","",LogicCommon!A3) | E3: SubModuleID : | F3: =IF(LogicCommon!C3="","",LogicCommon!C3) -> MSBC | G3: LogicClass : | H3: =IF(LogicCommon!E3="","",LogicCommon!E3) -> MSBCL_MfgActRegService | I3: Ope.Method : | J3: MfgActReg_Chk05 | K3: SuperClassPj.ID : | L3: =IF(LogicCommon!G3="","",LogicCommon!G3) | O3: Gene.Type : | P3: ALL
A4: * | E4: Version : | F4: 000000 | G4: LogicName : | H4: =IF(LogicCommon!E4="","",LogicCommon!E4) -> 製造実績登録サービス | I4: Ope.Name : | J4: 工数実績取消前チェック | K4: SuperLogicID : | L4: =IF(LogicCommon!G4="","",LogicCommon!G4) -> MS.MSUDL5010 | M4: ImplOpe.ID:
A5: * | E5: ACType :
A6: * | D6: 概要 : | E6: 工数実績の取消前チェックを行う。 | AA6: ID | AC6: ID | AE6: ID
A7: # | I7: U | K7: K | L7: K | M7: K | N7: K | O7: K | P7: K | Q7: K | R7: K | S7: K | T7: K | U7: K | V7: K | W7: K | X7: K | Y7: K | Z7: o | AB7: o | AD7: o
A8: # | D8: ブロック名 Block Name | E8: 型 Type | G8: super/share | H8: 対象ブロック名 Target Block Name | K8: REQ_UPD_CNT_CHK | L8: REQUIRED | M8: CHK_NUM | N8: SMALL_LARGE | O8: CHK_DT | P8: BEFORE_AFTER | Q8: CHK_PTN | R8: DUPLICATE | S8: TOO_MANY_INPUTS | T8: AT_LEAST_ONE | U8: ONLY_ONE_INPUT | V8: LIST_LOGIC | W8: LIST_OUT | X8: LIST_OUT_BASE | Y8: CONST | Z8: TargetName | AB8: TargetName | AD8: TargetName | AH8: ブロック備考 Block Remarks
A9: # | D9: 項目名 Field Name | E9: 型 Type | F9: 桁 Digits | G9: フルネーム Full Name | H9: 日本語名 Japanese Name | I9: 上り項目 Request Message Field | J9: 下り項目 Response Message Field | AF9: 条件および編集方法 Conditions and Editing Methods | AH9: 項目備考 Field Remarks
A10: # | Z10: 上り項目 Request Message Field | AA10: 下り項目 Response Message Field | AB10: 上り項目 Request Message Field | AC10: 下り項目 Response Message Field | AD10: 上り項目 Request Message Field | AE10: 下り項目 Response Message Field
A11: 10 | B11: * | D11: MfgActReg_Chk05_Rslt | E11: L | G11: $share$ | H11: MS.MSBCL6050.MfgActReg_Chk04.MfgActReg_Chk04_Rslt
A12: 10 | D12: peg_no | E12: #MA.INT | G12: Pegging No. | H12: 紐付けＮＯ | I12: E | J12: E
A13: 10 | D13: err_flg | E13: #MA.FLG | G13: Error flg. | H13: エラーＦＬＧ | I13: - | J13: E
A14: 10 | D14: data_crud_typ | E14: #MA.DATA_CRUD_TYP | G14: Data update type | H14: データ更新区分 | I14: E | J14: E
A15: 10 | D15: inst_wk_act_flg | E15: #MA.FLG | G15: Order direct man-hour result | H15: 指図工数実績 | I15: E | J15: E
A16: 10 | D16: mfg_inst_no | E16: #MA.MFG_INST_NO | G16: Mfg. order No. | H16: 製造指図ＮＯ | I16: E | J16: E
A17: 10 | D17: div_seq | E17: #MS.DIV_SEQ | G17: Split sequence number | H17: 分割連番 | I17: E | J17: E
A18: 10 | D18: disp_seq | E18: #MA.INT | G18: Display order | H18: 表示順 | I18: - | J18: -
A19: 10 | D19: oper_ptn | E19: #MA.OPER_PTN | G19: Operation pattern | H19: 工程パタン | I19: - | J19: -
A20: 10 | D20: oper_disp_seq | E20: #MA.INT | G20: Routing | H20: 工順 | I20: - | J20: -
A21: 10 | D21: oper_cd | E21: #MA.OPER_CD | G21: Operation cd. | H21: 工程ＣＤ | I21: - | J21: -
A22: 10 | D22: oper_nm | E22: #MA.OPER_NM | G22: Operation name | H22: 工程名 | I22: - | J22: -
A23: 10 | D23: oper_seq | E23: #MA.OPER_SEQ | G23: Operation sequence number | H23: 工程連番 | I23: - | J23: -
... A101: 10 | D101: oper_act_no | E101: #MA.OPER_ACT_NO | G101: Operation result No. | H101: 工程実績ＮＯ | I101: E | J101: E
A102: 10 | D102: wk_act_no | E102: #MA.WK_ACT_NO | G102: Man-hour result No. | H102: 工数実績ＮＯ | I102: E | J102: E | K102: E
A103: 10 | D103: dpt_wg_cd | E103: #MA.WG_CD | G103: Dept. WG cd. | H103: 部門ワーキンググループＣＤ | I103: - | J103: -
A104: 10 | D104: dpt_wg_nm | E104: #MA.WG_NM | G104: Dept. WG name | H104: 部門ワーキンググループ名 | I104: - | J104: -
A105: 10 | D105: loc_wg_cd | E105: #MA.WG_CD | G105: Location WG cd. | H105: 場所ワーキンググループＣＤ | I105: - | J105: -
A106: 10 | D106: loc_wg_nm | E106: #MA.WG_NM | G106: Location WG name | H106: 場所ワーキンググループ名 | I106: - | J106: -
A107: 10 | D107: loc_grp_cd | E107: #MA.LOC_GRP_CD | G107: Location group cd. | H107: 場所グループＣＤ | I107: - | J107: -
A108: 10 | D108: loc_grp_nm | E108: #MA.LOC_GRP_NM | G108: Location group name | H108: 場所グループ名 | I108: - | J108: -
A109: 10 | D109: site_cd | E109: #MA.SITE_CD | G109: Factory/Distribution warehouse cd. | H109: 工場・物流倉庫ＣＤ | I109: - | J109: -
A110: 10 | D110: site_nm | E110: #MA.SITE_NM | G110: Factory/Distribution warehouse name | H110: 工場・物流倉庫名 | I110: - | J110: -
A111: 10 | D111: itm_typ | E111: #MA.ITM_TYP | G111: Item type | H111: 品目区分 | I111: - | J111: -
A112: 10 | D112: itm_typ_nm | E112: #MA.ITM_TYP_NM | G112: Item type name | H112: 品目区分名 | I112: - | J112: -
A113: 10 | D113: itm_typ_d_cd | E113: #MA.ITM_TYP_D_CD | G113: Item type details cd. | H113: 品目区分詳細ＣＤ | I113: - | J113: -
A114: 10 | D114: itm_typ_d_nm | E114: #MA.ITM_TYP_D_NM | G114: Item type details name | H114: 品目区分詳細名 | I114: - | J114: -
... A151: 10 | D151: ext_wk_act_no | E151: #MA.EXT_WK_ACT_NO | G151: External man-hour result No. | H151: 外部工数実績ＮＯ | I151: - | J151: -
A153: 20 | B153: * | D153: MfgActReg_Chk05_Ctrl | E153: R
A154: 20 | D154: upd_cntr_chk_flg | E154: #MA.FLG | G154: Check for update counter | H154: 更新カウンタチェック | I154: E | J154: -
A155: 20 | D155: is_src_batch_flg | E155: #MA.FLG | G155: Caller batch process | H155: 呼出元バッチ処理 | I155: E | J155: -
D156: 詳細 :

Sheet MfgActReg_Upd01
A1: * | B1: * | D1: L | E1: 1
A2: * | D2: オペレーション実装仕様書 Operation Specification Implementation Sheet | E2: ModuleID : | F2: =IF(LogicCommon!C2="","",LogicCommon!C2) -> MS | G2: LogicID : | H2: =IF(LogicCommon!E2="","",LogicCommon!E2) -> MSBCL6050 | I2: Ope.ID : | J2: MfgActReg_Upd01 | K2: Pj.ID : | L2: =IF(LogicCommon!G2="","",LogicCommon!G2) -> MC | M2: Ope.Body : | N2: "mcframe.serverMAUD.MAUDL5010.MAUDL_Operation"
A3: * | D3: =IF(LogicCommon!A3="","",LogicCommon!A3) | E3: SubModuleID : | F3: =IF(LogicCommon!C3="","",LogicCommon!C3) -> MSBC | G3: LogicClass : | H3: =IF(LogicCommon!E3="","",LogicCommon!E3) -> MSBCL_MfgActRegService | I3: Ope.Method : | J3: MfgActReg_Upd01 | K3: SuperClassPj.ID : | L3: =IF(LogicCommon!G3="","",LogicCommon!G3) | O3: Gene.Type : | P3: ALL
A4: * | E4: Version : | F4: 000000 | G4: LogicName : | H4: =IF(LogicCommon!E4="","",LogicCommon!E4) -> 製造実績登録サービス | I4: Ope.Name : | J4: 登録・訂正・取消 | K4: SuperLogicID : | L4: =IF(LogicCommon!G4="","",LogicCommon!G4) -> MS.MSUDL5010 | M4: ImplOpe.ID:
A5: * | E5: ACType :
A6: * | D6: 概要 : | E6: 製造実績の登録・訂正・取消の共通処理 | M6: ID | O6: ID | Q6: ID | S6: ID | U6: ID | W6: ID
A7: # | I7: U | K7: K | L7: o | M7: MAT.matUpd01 | N7: o | O7: MAT.matUpd02 | P7: o | Q7: MAT.matUpd03 | R7: o | S7: MATI.matUpd04 | T7: o | U7: MAT.matUpd05 | V7: o | W7: MAT.matUpd06
A8: # | D8: ブロック名 Block Name | E8: 型 Type | G8: super/share | H8: 対象ブロック名 Target Block Name | L8: TargetName | M8: OPE.MS.MSBCL6060.MfgActTblReg_Upd01 | N8: TargetName | O8: OPE.MS.MSBCL6060.MfgActTblReg_Upd02 | P8: TargetName | Q8: OPE.MS.MSBCL6060.MfgActTblReg_Upd03 | R8: TargetName | S8: OPE.MS.MSBCL6060.MfgActTblReg_Upd04 | T8: TargetName | U8: OPE.MS.MSBCL6060.MfgActTblReg_Upd05 | V8: TargetName | W8: OPE.MS.MSBCL6060.MfgActTblReg_Upd06 | Z8: ブロック備考 Block Remarks
A9: # | D9: 項目名 Field Name | E9: 型 Type | F9: 桁 Digits | G9: フルネーム Full Name | H9: 日本語名 Japanese Name | I9: 上り項目 Request Message Field | J9: 下り項目 Response Message Field | X9: 条件および編集方法 Conditions and Editing Methods | Z9: 項目備考 Field Remarks
A10: # | L10: 上り項目 Request Message Field | M10: 下り項目 Response Message Field | N10: 上り項目 Request Message Field | O10: 下り項目 Response Message Field | P10: 上り項目 Request Message Field | Q10: 下り項目 Response Message Field | R10: 上り項目 Request Message Field | S10: 下り項目 Response Message Field | T10: 上り項目 Request Message Field | U10: 下り項目 Response Message Field | V10: 上り項目 Request Message Field | W10: 下り項目 Response Message Field
A11: 10 | B11: * | D11: MfgActReg_Upd01_Hdr | E11: L | L11: MfgActTblReg_Upd01_Dtl | R11: MfgActTblReg_Upd04_Hdr
A12: 10 | D12: data_crud_typ | E12: #MA.DATA_CRUD_TYP | G12: Data update type | H12: データ更新区分 | I12: E | J12: - | L12: E
A13: 10 | D13: peg_no | E13: #MA.INT | G13: Pegging No. | H13: 紐付けＮＯ | I13: E | J13: E | L13: E | R13: hdr_peg_no
A14: 10 | D14: err_flg | E14: #MA.FLG | G14: Error | H14: エラー | I14: - | J14: -
A15: 10 | D15: rtn_sts_typ | E15: #MA.RTN_STS_TYP | G15: Process result status type | H15: 処理結果状況区分 | I15: - | J15: E
A16: 10 | D16: mfg_sts_typ | E16: #MS.MFG_STS_TYP | G16: Mfg. status type | H16: 製造状況区分 | I16: E | J16: E
A17: 10 | D17: mfg_sts_typ_nm | E17: #MS.MFG_STS_TYP_NM | G17: Mfg. status name | H17: 製造状況区分名 | I17: - | J17: E
A18: 10 | D18: itm_cd | E18: #MA.ITM_CD | G18: Item cd. | H18: 品目ＣＤ | I18: E | J18: -
A19: 10 | D19: itm_sub1 | E19: #MA.ITM_SUB1 | G19: Branch No. 1 | H19: 枝番１ | I19: E | J19: -
A20: 10 | D20: itm_sub2 | E20: #MA.ITM_SUB2 | G20: Branch No. 2 | H20: 枝番２ | I20: E | J20: -
A21: 10 | D21: itm_sub3 | E21: #MA.ITM_SUB3 | G21: Branch No. 3 | H21: 枝番３ | I21: E | J21: -
A22: 10 | D22: itm_nm | E22: #MA.ITM_NM | G22: Item name | H22: 品名 | I22: E | J22: -
A23: 10 | D23: inst_lot_no | E23: #MA.LOT_NO | G23: Lot No. (Order) | H23: ロットＮＯ（指図） | I23: E | J23: -
A24: 10 | D24: inst_sublot_no | E24: #MA.SUBLOT_NO | G24: Sublot No. (Order) | H24: サブロットＮＯ（指図） | I24: E | J24: -
A25: 10 | D25: sno1 | E25: #MA.SNO1 | G25: SEIBAN No. 1 | H25: 手配ＮＯ１ | I25: E | J25: -
... A32: 10 | D32: sno4_mng_typ | E32: #MA.SNO_MNG_TYP | G32: SEIBAN No. 4 management type | H32: 手配ＮＯ４管理区分 | I32: E | J32: -
A33: 10 | D33: st_act_tm | E33: #MA.TM | G33: Actual start date and time | H33: 着手実績日時 | I33: E | J33: - | L33: E
A34: 10 | D34: st_ac_dt | E34: #MA.DT | G34: Start recording date | H34: 着手計上日 | I34: E | J34: - | L34: E
A35: 10 | D35: end_act_tm | E35: #MA.TM | G35: Actual end date and time | H35: 終了実績日時 | I35: E | J35: - | L35: E
A36: 10 | D36: end_ac_dt | E36: #MA.DT | G36: End recording date | H36: 終了計上日 | I36: E | J36: - | L36: E
A37: 10 | D37: itm_mfg_inst_qty | E37: #MA.QTY | G37: Item mfg. order qty. | H37: 品目製造指図数量 | I37: E | J37: -
A38: 10 | D38: base_unit_st_act_qty | E38: #MA.QTY | G38: Start qty. | H38: 着手数量 | I38: E | J38: -
A39: 10 | D39: rem_abort_flg | E39: #MA.FLG | G39: Cancel remaining qty. | H39: 残数打切 | I39: E | J39: -
A40: 10 | D40: base_unit_dec_place | E40: #MA.DEC_PLACE | G40: Base unit number of decimal places | H40: 基準単位小数部有効桁数 | I40: E | J40: -
A41: 10 | D41: base_unit_conv_rnd_typ | E41: #MA.RND_TYP | G41: Base unit rounding type | H41: 基準単位端数処理区分 | I41: E | J41: -
A42: 10 | D42: base_unit_yield_qty | E42: #MA.QTY | G42: Conforming qty. | H42: 良品数量 | I42: E | J42: - | L42: E
A43: 10 | D43: base_unit_dfct_qty | E43: #MA.QTY | G43: Defective qty. | H43: 不良数量 | I43: E | J43: - | L43: E
A44: 10 | D44: base_unit_cd | E44: #MA.UNIT_CD | G44: Base unit cd. | H44: 基準単位ＣＤ | I44: E | J44: - | L44: E
A45: 10 | D45: act_usr_cd | E45: #MA.USR_CD | G45: Result management PIC cd. | H45: 実績責任者ＣＤ | I45: E | J45: - | L45: E
A46: 10 | D46: act_dpt_cd | E46: #MA.DPT_CD | G46: Result dept. cd. | H46: 実績部門ＣＤ | I46: E | J46: - | L46: E
A47: 10 | D47: act_rpt_rmrks | E47: #MS.MFG_ACT_RPT_RMRKS | G47: Mfg. record sheet remarks | H47: 製造記録書備考 | I47: E | J47: - | L47: mfg_act_rpt_rmrks
A48: 10 | D48: intr_rmrks | E48: #MS.MFG_ACT_INTR_RMRKS | G48: Internal remarks | H48: 内部備考 | I48: E | J48: - | L48: mfg_act_intr_rmrks
A49: 10 | D49: mfg_act_sub_char1 | E49: #MS.MFG_ACT_SUB_CHAR1 | G49: Mfg. result spare 1 | H49: 製造実績予備１ | I49: E | J49: - | L49: E
A50: 10 | D50: mfg_act_sub_char2 | E50: #MS.MFG_ACT_SUB_CHAR2 | G50: Mfg. result spare 2 | H50: 製造実績予備２ | I50: E | J50: - | L50: E
A51: 10 | D51: mfg_act_sub_char3 | E51: #MS.MFG_ACT_SUB_CHAR3 | G51: Mfg. result spare 3 | H51: 製造実績予備３ | I51: E | J51: - | L51: E
A52: 10 | D52: act_prnt_flg | E52: #MA.FLG | G52: Mfg. record sheet issued | H52: 製造記録書発行済 | I52: E | J52: - | L52: E
A53: 10 | D53: act_prnt_tm | E53: #MA.TM | G53: Mfg. record sheet issued date and time | H53: 製造記録書発行日時 | I53: E | J53: - | L53: E
... A55: 10 | D55: itm_yield | E55: #MA.YIELD | G55: Item actual yield | H55: 品目実際収率 | I55: E | J55: - | L55: E
A56: 10 | D56: mfg_mtd_typ | E56: #MS.MFG_MTD_TYP | G56: Production method type | H56: 生産方法区分 | I56: E | J56: -
A57: 10 | D57: mfg_inst_unit_typ | E57: #MA.MFG_INST_UNIT_TYP | G57: Mfg. order unit type | H57: 製造指図単位区分 | I57: E | J57: -
A58: 10 | D58: sppl_cd | E58: #MA.BP_CD | G58: Subcontractor cd. | H58: 外注先ＣＤ | I58: E | J58: -
A59: 10 | D59: mfg_loc_cd | E59: #MA.LOC_CD | G59: Mfg. location cd. | H59: 製造場所ＣＤ | I59: E | J59: -
A60: 10 | D60: mfg_str_ln_cd | E60: #MA.STR_LN_CD | G60: Mfg. rack/line cd. | H60: 製造棚・ラインＣＤ | I60: E | J60: -
A61: 10 | D61: bom_ptn | E61: #MA.BOM_PTN | G61: BOM pattern | H61: ＢＯＭパタン | I61: E | J61: -
A62: 10 | D62: site_cd | E62: #MA.SITE_CD | G62: Factory/Distribution warehouse cd. | H62: 工場・物流倉庫ＣＤ | I62: E | J62: -
A63: 10 | D63: wg_cd | E63: #MA.WG_CD | G63: WG cd. | H63: ワーキンググループＣＤ | I63: E | J63: -
A64: 10 | D64: mfg_inst_no | E64: #MA.MFG_INST_NO | G64: Mfg. order No. | H64: 製造指図ＮＯ | I64: E | J64: - | L64: E
A65: 10 | D65: mfg_inst_upd_cntr | E65: #MA.UPD_CNT | G65: Mfg. order update counter | H65: 製造指図更新カウンタ | I65: - | J65: -
A66: 10 | D66: mfg_inst_pr_upd_cntr | E66: #MA.UPD_CNT | G66: Production order progress update counter | H66: 製造指図進捗更新カウンタ | I66: - | J66: -
A67: 10 | D67: mfg_act_upd_cntr | E67: #MA.UPD_CNT | G67: Mfg. result update counter | H67: 製造実績更新カウンタ | I67: - | J67: -
A68: 10 | D68: div_seq | E68: #MS.DIV_SEQ | G68: Split sequence number | H68: 分割連番 | I68: E | J68: E | L68: E
A69: 10 | D69: mfg_act_no | E69: #MA.MFG_ACT_NO | G69: Mfg. result No. | H69: 製造実績ＮＯ | I69: E | J69: E | L69: E
A70: 10 | D70: itm_ord_no | E70: #MA.ITM_ORD_NO | G70: Item order No. | H70: 品目オーダＮＯ | I70: E | J70: -
A71: 10 | D71: aprv_flg | E71: #MA.FLG | G71: For Approval | H71: 承認対象 | I71: E | J71: -
A72: 10 | D72: mfg_aprv_role_cd | E72: #MA.APRV_ROLE_CD | G72: Mfg. approval role cd. | H72: 製造承認役割ＣＤ | I72: E | J72: -
A73: 10 | D73: old_mfg_aprv_sts_typ | E73: #MS.MFG_APRV_STS_TYP | G73: Approval status type before update | H73: 更新前承認状況区分 | I73: E | J73: -
A74: 10 | D74: old_end_act_tm | E74: #MA.TM | G74: Actual end time before update | H74: 更新前終了実績日時 | I74: E | J74: -
A75: 10 | D75: mfg_aprv_sts_typ | E75: #MS.MFG_APRV_STS_TYP | G75: Mfg. approval status type | H75: 製造承認状況区分 | I75: - | J75: - | L75: E
A76: 10 | D76: aprv_dt | E76: #MA.DT | G76: Approval date | H76: 承認日 | I76: - | J76: - | L76: E
A77: 10 | D77: aprv_dpt_cd | E77: #MA.DPT_CD | G77: Approval dept. cd. | H77: 承認部門ＣＤ | I77: - | J77: - | L77: E
A78: 10 | D78: aprv_usr_cd | E78: #MA.USR_CD | G78: Approver cd. | H78: 承認者ＣＤ | I78: - | J78: - | L78: E
A79: 10 | D79: aprv_tm | E79: #MA.TM | G79: Approval date and time | H79: 承認日時 | I79: - | J79: - | L79: E
A80: 10 | D80: aprv_rsn | E80: #MS.APRV_RSN | G80: Approval reason | H80: 承認理由 | I80: - | J80: - | L80: E
A81: 10 | D81: itm_mfg_inst_no | E81: #MA.ITM_MFG_INST_NO | G81: Item mfg. order No. | H81: 品目製造指図ＮＯ | I81: E | J81: - | L81: E
A82: 10 | D82: trd_cd | E82: #MA.TRD_CD | G82: Transaction cd. | H82: 取引ＣＤ | I82: E | J82: - | L82: E
A83: 10 | D83: lot_mng_typ | E83: #MA.LOT_MNG_TYP | G83: Lot management type | H83: ロット管理区分 | I83: E | J83: -
A84: 10 | D84: lot_no_typ | E84: #MA.LOT_NO_TYP | G84: Lot No. numbering type | H84: ロットＮＯ発番区分 | I84: E | J84: -
A85: 10 | D85: lot_no_ptn_cd | E85: #MA.NUM_PTN_CD | G85: Lot No. numbering pattern cd. | H85: ロットＮＯ発番パタンＣＤ | I85: E | J85: -
A86: 10 | D86: sublot_mng_typ | E86: #MA.SUBLOT_MNG_TYP | G86: Sublot management type | H86: サブロット管理区分 | I86: E | J86: -
A87: 10 | D87: sublot_no_typ | E87: #MA.LOT_NO_TYP | G87: Sublot No. numbering type | H87: サブロットＮＯ発番区分 | I87: E | J87: -
A88: 10 | D88: sublot_no_ptn_cd | E88: #MA.NUM_PTN_CD | G88: Sublot No. numbering pattern cd. | H88: サブロットＮＯ発番パタンＣＤ | I88: E | J88: -
A89: 10 | D89: arr_purc_auto_reg_flg | E89: #MA.FLG | G89: Auto-create at receipt/purchase | H89: 入荷・仕入時自動作成 | I89: E | J89: - | L89: E
A90: 10 | D90: act_immed_prnt_flg | E90: #MA.FLG | G90: Record sheet immediate issue | H90: 記録書即時発行 | I90: E | J90: -
A91: 10 | D91: is_src_outsrc_srv_flg | E91: #MA.FLG | G91: Caller subcontractor mfg. result service | H91: 呼出元外注製造実績サービス | I91: E | J91: -
A92: 10 | D92: all_inpt_cmpl_flg | E92: #MA.FLG | G92: All input completed | H92: 全投入完了 | I92: - | J92: -
A93: 10 | D93: lst_reg_flg | E93: #MA.FLG | G93: Bulk execution | H93: 一括実行 | I93: E | J93: -
A94: 10 | D94: is_src_batch_flg | E94: #MA.FLG | G94: Caller batch process | H94: 呼出元バッチ処理 | I94: E | J94: -
A95: 10 | D95: bkf_tgt_cnt | E95: #MA.INT | G95: Number of BF | H95: バックフラッシュ対象件数 | I95: E | J95: E | R95: E
A96: 10 | D96: bkf_success_cnt | E96: #MA.INT | G96: Number of backflush succeeded | H96: バックフラッシュ成功件数 | I96: E | J96: E | R96: E
A97: 10 | D97: bkf_failure_cnt | E97: #MA.INT | G97: Number of backflush failed | H97: バックフラッシュ失敗件数 | I97: E | J97: E | R97: E
A98: 10 | D98: is_src_md_mfg_srv_flg | E98: #MA.FLG | I98: E | J98: -
A99: 10 | D99: unschd_act_flg | E99: #MA.FLG | G99: Unplanned result | H99: 計画外実績 | I99: E | J99: -
A100: 10 | D100: oper_ptn | E100: #MA.OPER_PTN | G100: Operation pattern | H100: 工程パタン | I100: E | J100: -
A101: 10 | D101: master_dt | E101: #MA.DT | G101: Master application date | H101: マスタ適用日 | I101: E | J101: -
A102: 10 | D102: mfg_str_ln_cd_none_flg | E102: #MA.FLG | G102: Without mfg. rack/line | H102: 製造棚・ライン無 | I102: E | J102: -
A103: 10 | D103: strg_loc_cd | E103: #MA.LOC_CD | G103: Storage location cd. | H103: 格納場所ＣＤ | I103: E | J103: -
A104: 10 | D104: strg_str_ln_cd | E104: #MA.STR_LN_CD | G104: Storage rack/line cd. | H104: 格納棚・ラインＣＤ | I104: E | J104: -
A105: 10 | D105: strg_str_ln_cd_none_flg | E105: #MA.FLG | G105: Without storage rack/line | H105: 格納棚・ライン無 | I105: E | J105: -
A106: 10 | D106: not_bkf_upd_flg | E106: #MA.FLG | G106: Not update BF | H106: ＢＦ更新しない | I106: E | J106: -
A107: 10 | D107: not_wk_cost_upd_calc_flg | E107: #MA.FLG | G107: Do not auto-calculate man-hour | H107: 自動工数計算しない | I107: E | J107: -
...

Sheet MfgActReg_Upd02
A1: * | B1: * | D1: L | E1: 1
A2: * | D2: オペレーション実装仕様書 Operation Specification Implementation Sheet | E2: ModuleID : | F2: =IF(LogicCommon!C2="","",LogicCommon!C2) -> MS | G2: LogicID : | H2: =IF(LogicCommon!E2="","",LogicCommon!E2) -> MSBCL6050 | I2: Ope.ID : | J2: MfgActReg_Upd02 | K2: Pj.ID : | L2: =IF(LogicCommon!G2="","",LogicCommon!G2) -> MC | M2: Ope.Body : | N2: "mcframe.serverMAUD.MAUDL5010.MAUDL_Operation"
A3: * | D3: =IF(LogicCommon!A3="","",LogicCommon!A3) | E3: SubModuleID : | F3: =IF(LogicCommon!C3="","",LogicCommon!C3) -> MSBC | G3: LogicClass : | H3: =IF(LogicCommon!E3="","",LogicCommon!E3) -> MSBCL_MfgActRegService | I3: Ope.Method : | J3: MfgActReg_Upd02 | K3: SuperClassPj.ID : | L3: =IF(LogicCommon!G3="","",LogicCommon!G3) | O3: Gene.Type : | P3: ALL
A4: * | E4: Version : | F4: 000000 | G4: LogicName : | H4: =IF(LogicCommon!E4="","",LogicCommon!E4) -> 製造実績登録サービス | I4: Ope.Name : | J4: 一括登録・訂正 | K4: SuperLogicID : | L4: =IF(LogicCommon!G4="","",LogicCommon!G4) -> MS.MSUDL5010 | M4: ImplOpe.ID:
A5: * | E5: ACType :
A6: * | D6: 概要 : | E6: 製造実績の一括登録・訂正処理 | M6: ID | O6: ID | Q6: ID
A7: # | I7: U | K7: K | L7: o | M7: MAR1.marUpd01 | N7: o | O7: MAR2.marChk03 | P7: o
A8: # | D8: ブロック名 Block Name | E8: 型 Type | G8: super/share | H8: 対象ブロック名 Target Block Name | L8: TargetName | M8: OPE.MS.MSBCL6050.MfgActReg_Upd01 | N8: TargetName | O8: OPE.MS.MSBCL6050.MfgActReg_Chk03 | P8: TargetName | T8: ブロック備考 Block Remarks
A9: # | D9: 項目名 Field Name | E9: 型 Type | F9: 桁 Digits | G9: フルネーム Full Name | H9: 日本語名 Japanese Name | I9: 上り項目 Request Message Field | J9: 下り項目 Response Message Field | R9: 条件および編集方法 Conditions and Editing Methods | T9: 項目備考 Field Remarks
A10: # | L10: 上り項目 Request Message Field | M10: 下り項目 Response Message Field | N10: 上り項目 Request Message Field | O10: 下り項目 Response Message Field | P10: 上り項目 Request Message Field | Q10: 下り項目 Response Message Field
A11: 10 | B11: * | D11: MfgActReg_Upd02_Ctrl | E11: R | N11: MfgActReg_Chk03_Ctrl
A12: 10 | D12: oper_unit_flg | E12: #MA.FLG | G12: Operation unit result | H12: 工程単位実績 | I12: E | J12: - | N12: E
A13: 10 | D13: act_immed_prnt_flg | E13: #MA.FLG | G13: Record sheet immediate issue | H13: 記録書即時発行 | I13: E | J13: -
A14: 10 | D14: not_bkf_upd_flg | E14: #MA.FLG | G14: Not update BF | H14: ＢＦ更新しない | I14: E | J14: -
A15: 10 | D15: not_wk_cost_upd_calc_flg | E15: #MA.FLG | G15: Do not auto-calculate man-hour | H15: 自動工数計算しない | I15: E | J15: -
A16: 10 | D16: not_io_act_srv_exec_flg | E16: #MA.FLG | G16: GR/GI result service call not required | H16: 受払実績サービス呼び出し不要 | I16: E | J16: -
A17: 10 | D17: is_src_batch_flg | E17: #MA.FLG | G17: Caller batch process | H17: 呼出元バッチ処理 | I17: E | J17: - | N17: E
A18: 10 | D18: upd_cntr_chk_flg | E18: #MA.FLG | G18: Check for update counter | H18: 更新カウンタチェック | I18: E | J18: - | N18: E
A19: 10 | D19: not_commit_flg | E19: #MA.FLG | G19: Do not commit | H19: コミットしない | I19: E | J19: -
A20: 10 | D20: is_oper_act_cmpl_batch_flg | E20: #MA.FLG | G20: Call from operation result completion batch | H20: 工程実績完了バッチから呼び出す | I20: E | J20: -
A22: 20 | B22: * | D22: MfgActReg_Upd02_Hdr1 | E22: L | N22: MfgActReg_Chk03_Hdr1
A23: 20 | D23: peg_no | E23: #MA.INT | G23: Pegging No. | H23: 紐付けＮＯ | I23: E | J23: E | N23: E
A24: 20 | D24: mfg_sts_typ | E24: #MS.MFG_STS_TYP | G24: Mfg. status type | H24: 製造状況区分 | I24: E | J24: E
A25: 20 | D25: mfg_sts_typ_nm | E25: #MS.MFG_STS_TYP_NM | G25: Mfg. status name | H25: 製造状況区分名 | I25: - | J25: E
A26: 20 | D26: st_act_tm | E26: #MA.TM | G26: Actual start date | H26: 着手実績日 | I26: E | J26: - | N26: E
A27: 20 | D27: st_ac_dt | E27: #MA.DT | G27: Start recording date | H27: 着手計上日 | I27: E | J27: - | N27: E
A28: 20 | D28: end_act_tm | E28: #MA.TM | G28: Actual end date | H28: 終了実績日 | I28: E | J28: - | N28: E
A29: 20 | D29: end_ac_dt | E29: #MA.DT | G29: End recording date | H29: 終了計上日 | I29: E | J29: - | N29: E
A30: 20 | D30: base_unit_st_act_qty | E30: #MA.QTY | G30: Start qty. | H30: 着手数量 | I30: E | J30: - | N30: E
A31: 20 | D31: rem_abort_flg | E31: #MA.FLG | G31: Cancel remaining qty. | H31: 残数打切 | I31: E | J31: -
A32: 20 | D32: act_usr_cd | E32: #MA.USR_CD | G32: Result management PIC cd. | H32: 実績責任者ＣＤ | I32: E | J32: -
A33: 20 | D33: act_dpt_cd | E33: #MA.DPT_CD | G33: Result dept. cd. | H33: 実績部門ＣＤ | I33: E | J33: -
A34: 20 | D34: mfg_act_rpt_rmrks | E34: #MS.MFG_ACT_RPT_RMRKS | G34: Mfg. record sheet remarks | H34: 製造記録書備考 | I34: E | J34: -
A35: 20 | D35: mfg_act_intr_rmrks | E35: #MS.MFG_ACT_INTR_RMRKS | G35: Internal remarks | H35: 内部備考 | I35: E | J35: -
A36: 20 | D36: mfg_act_sub_char1 | E36: #MS.MFG_ACT_SUB_CHAR1 | G36: Mfg. result spare 1 | H36: 製造実績予備１ | I36: E | J36: -
A37: 20 | D37: mfg_act_sub_char2 | E37: #MS.MFG_ACT_SUB_CHAR2 | G37: Mfg. result spare 2 | H37: 製造実績予備２ | I37: E | J37: -
A38: 20 | D38: mfg_act_sub_char3 | E38: #MS.MFG_ACT_SUB_CHAR3 | G38: Mfg. result spare 3 | H38: 製造実績予備３ | I38: E | J38: -
A39: 20 | D39: itm_yield | E39: #MA.YIELD | G39: Item actual yield | H39: 品目実際収率 | I39: E | J39: -
A40: 20 | D40: oper_unit_act_qty | E40: #MA.QTY | G40: Operation unit result qty. | H40: 工程単位実績数量 | I40: E | J40: - | N40: E
A41: 20 | D41: oper_act_intr_rmrks | E41: #MS.OPER_ACT_INTR_RMRKS | G41: Operation internal remarks | H41: 工程内部備考 | I41: E | J41: -
A42: 20 | D42: oper_act_rpt_rmrks | E42: #MS.OPER_ACT_RPT_RMRKS | G42: Operation record sheet remarks | H42: 工程記録書備考 | I42: E | J42: -
A43: 20 | D43: oper_act_sub_char1 | E43: #MS.OPER_ACT_SUB_CHAR1 | G43: Operation spare 1 | H43: 工程予備１ | I43: E | J43: -
A44: 20 | D44: oper_act_sub_char2 | E44: #MS.OPER_ACT_SUB_CHAR2 | G44: Operation spare 2 | H44: 工程予備２ | I44: E | J44: -
A45: 20 | D45: oper_act_sub_char3 | E45: #MS.OPER_ACT_SUB_CHAR3 | G45: Operation spare 3 | H45: 工程予備３ | I45: E | J45: -
A46: 20 | D46: oper_yield | E46: #MA.YIELD | G46: Operation actual yield | H46: 工程実際収率 | I46: E | J46: -
A47: 20 | D47: oper_inst_no | E47: #MA.OPER_INST_NO | G47: Operation order No. | H47: 工程指図ＮＯ | I47: E | J47: -
A48: 20 | D48: oper_act_no | E48: #MA.OPER_ACT_NO | G48: Operation result No. | H48: 工程実績ＮＯ | I48: E | J48: E
A49: 20 | D49: mfg_inst_no | E49: #MA.MFG_INST_NO | G49: Mfg. order No. | H49: 製造指図ＮＯ | I49: E | J49: - | N49: E
A50: 20 | D50: div_seq | E50: #MS.DIV_SEQ | G50: Split sequence number | H50: 分割連番 | I50: E | J50: E | N50: E
A51: 20 | D51: mfg_act_no | E51: #MA.MFG_ACT_NO | G51: Mfg. result No. | H51: 製造実績ＮＯ | I51: E | J51: E | N51: E
A52: 20 | D52: mfg_inst_upd_cntr | E52: #MA.UPD_CNT | G52: Mfg. order update counter | H52: 製造指図更新カウンタ | I52: E | J52: - | N52: E
A53: 20 | D53: mfg_inst_pr_upd_cntr | E53: #MA.UPD_CNT | G53: Production order progress update counter | H53: 製造指図進捗更新カウンタ | I53: E | J53: -
A54: 20 | D54: mfg_act_upd_cntr | E54: #MA.UPD_CNT | G54: Mfg. result update counter | H54: 製造実績更新カウンタ | I54: E | J54: - | N54: E
A55: 20 | D55: err_flg | E55: #MA.FLG | G55: Error | H55: エラー | I55: - | J55: -
A56: 20 | D56: rtn_sts_typ | E56: #MA.RTN_STS_TYP | G56: Process result status type | H56: 処理結果状況区分 | I56: - | J56: E
A57: 20 | D57: bkf_tgt_cnt | E57: #MA.INT | G57: Number of BF | H57: バックフラッシュ対象件数 | I57: - | J57: E
A58: 20 | D58: bkf_success_cnt | E58: #MA.INT | G58: Number of backflush succeeded | H58: バックフラッシュ成功件数 | I58: - | J58: E
A59: 20 | D59: bkf_failure_cnt | E59: #MA.INT | G59: Number of backflush failed | H59: バックフラッシュ失敗件数 | I59: - | J59: E
A60: 20 | D60: batch_data_no | E60: #MA.BATCH_DATA_NO | G60: Batch data No. | H60: バッチデータＮＯ | I60: - | J60: -
A61: 20 | D61: batch_log_no | E61: #MA.BATCH_LOG_NO | G61: Log No. | H61: ログＮＯ | I61: - | J61: -
A62: 20 | D62: log_sub_key1 | E62: #MA.BATCH_LOG_SUB_KEY1 | G62: Log sub key 1 | H62: ログサブキー１ | I62: - | J62: -
A63: 20 | D63: log_sub_key2 | E63: #MA.BATCH_LOG_SUB_KEY2 | G63: Log sub key 2 | H63: ログサブキー２ | I63: - | J63: -
A64: 20 | D64: mfg_loc_cd | E64: #MA.LOC_CD | G64: Mfg. location cd. | H64: 製造場所ＣＤ | I64: - | J64: -
A65: 20 | D65: log_grp_cd | E65: #MA.LOC_GRP_CD | G65: Location group cd. | H65: 場所グループＣＤ | I65: - | J65: -
A66: 20 | D66: oper_cd | E66: #MA.OPER_CD | G66: Operation cd. | H66: 工程ＣＤ | I66: - | J66: -
... A75: 20 | D75: if_auto_reg_flg | E75: #MA.FLG | G75: IF auto-create | H75: ＩＦ自動作成 | I75: E | J75: -
A77: 30 | B77: * | D77: MfgActReg_Upd02_Hdr2 | E77: L | G77: $share$ | H77: MS.MSBCL6050.MfgActReg_Upd02.MfgActReg_Upd02_Hdr1 | N77: MfgActReg_Chk03_Hdr2
A78: 30 | D78: peg_no | E78: #MA.INT | G78: Pegging No. | H78: 紐付けＮＯ | I78: E | J78: E | N78: E
A79: 30 | D79: mfg_sts_typ | E79: #MS.MFG_STS_TYP | G79: Mfg. status type | H79: 製造状況区分 | I79: E | J79: E | N79: E
A80: 30 | D80: mfg_sts_typ_nm | E80: #MS.MFG_STS_TYP_NM | G80: Mfg. status name | H80: 製造状況区分名 | I80: - | J80: E
A81: 30 | D81: st_act_tm | E81: #MA.TM | G81: Actual start date | H81: 着手実績日 | I81: E | J81: - | N81: E
A82: 30 | D82: st_ac_dt | E82: #MA.DT | G82: Start recording date | H82: 着手計上日 | I82: E | J82: - | N82: E
A83: 30 | D83: end_act_tm | E83: #MA.TM | G83: Actual end date | H83: 終了実績日 | I83: E | J83: - | N83: E
A84: 30 | D84: end_ac_dt | E84: #MA.DT | G84: End recording date | H84: 終了計上日 | I84: E | J84: - | N84: E
A85: 30 | D85: base_unit_st_act_qty | E85: #MA.QTY | G85: Start qty. | H85: 着手数量 | I85: E | J85: - | N85: E
A86: 30 | D86: rem_abort_flg | E86: #MA.FLG | G86: Cancel remaining qty. | H86: 残数打切 | I86: E | J86: -
A87: 30 | D87: act_usr_cd | E87: #MA.USR_CD | G87: Result management PIC cd. | H87: 実績責任者ＣＤ | I87: E | J87: -
A88: 30 | D88: act_dpt_cd | E88: #MA.DPT_CD | G88: Result dept. cd. | H88: 実績部門ＣＤ | I88: E | J88: -
A89: 30 | D89: mfg_act_rpt_rmrks | E89: #MS.MFG_ACT_RPT_RMRKS | G89: Mfg. record sheet remarks | H89: 製造記録書備考 | I89: E | J89: -
A90: 30 | D90: mfg_act_intr_rmrks | E90: #MS.MFG_ACT_INTR_RMRKS | G90: Internal remarks | H90: 内部備考 | I90: E | J90: -
A91: 30 | D91: mfg_act_sub_char1 | E91: #MS.MFG_ACT_SUB_CHAR1 | G91: Mfg. result spare 1 | H91: 製造実績予備１ | I91: E | J91: -
A92: 30 | D92: mfg_act_sub_char2 | E92: #MS.MFG_ACT_SUB_CHAR2 | G92: Mfg. result spare 2 | H92: 製造実績予備２ | I92: E | J92: -
A93: 30 | D93: mfg_act_sub_char3 | E93: #MS.MFG_ACT_SUB_CHAR3 | G93: Mfg. result spare 3 | H93: 製造実績予備３ | I93: E | J93: -
A94: 30 | D94: itm_yield | E94: #MA.YIELD | G94: Item actual yield | H94: 品目実際収率 | I94: E | J94: -
A95: 30 | D95: mfg_inst_no | E95: #MA.MFG_INST_NO | G95: Mfg. order No. | H95: 製造指図ＮＯ | I95: E | J95: - | N95: E
A96: 30 | D96: div_seq | E96: #MS.DIV_SEQ | G96: Split sequence number | H96: 分割連番 | I96: E | J96: E | N96: E
A97: 30 | D97: mfg_act_no | E97: #MA.MFG_ACT_NO | G97: Mfg. result No. | H97: 製造実績ＮＯ | I97: E | J97: E | N97: E
A98: 30 | D98: mfg_inst_upd_cntr | E98: #MA.UPD_CNT | G98: Mfg. order update counter | H98: 製造指図更新カウンタ | I98: E | J98: - | N98: E
A99: 30 | D99: mfg_inst_pr_upd_cntr | E99: #MA.UPD_CNT | G99: Production order progress update counter | H99: 製造指図進捗更新カウンタ | I99: E | J99: - | N99: E
A100: 30 | D100: mfg_act_upd_cntr | E100: #MA.UPD_CNT | G100: Mfg. result update counter | H100: 製造実績更新カウンタ | I100: E | J100: - | N100: E
A101: 30 | D101: err_flg | E101: #MA.FLG | G101: Error | H101: エラー | I101: - | J101: -
A102: 30 | D102: rtn_sts_typ | E102: #MA.RTN_STS_TYP | G102: Process result status type | H102: 処理結果状況区分 | I102: - | J102: E
A103: 30 | D103: bkf_tgt_cnt | E103: #MA.INT | G103: Number of BF | H103: バックフラッシュ対象件数 | I103: - | J103: E
A104: 30 | D104: bkf_success_cnt | E104: #MA.INT | G104: Number of backflush succeeded | H104: バックフラッシュ成功件数 | I104: - | J104: E
A105: 30 | D105: bkf_failure_cnt | E105: #MA.INT | G105: Number of backflush failed | H105: バックフラッシュ失敗件数 | I105: - | J105: E
A106: 30 | D106: batch_data_no | E106: #MA.BATCH_DATA_NO | G106: Batch data No. | H106: バッチデータＮＯ | I106: - | J106: -
A107: 30 | D107: batch_log_no | E107: #MA.BATCH_LOG_NO | G107: Log No. | H107: ログＮＯ | I107: - | J107: -
A108: 30 | D108: log_sub_key1 | E108: #MA.BATCH_LOG_SUB_KEY1 | G108: Log sub key 1 | H108: ログサブキー１ | I108: - | J108: -
A109: 30 | D109: log_sub_key2 | E109: #MA.BATCH_LOG_SUB_KEY2 | G109: Log sub key 2 | H109: ログサブキー２ | I109: - | J109: -
A110: 30 | D110: mfg_loc_cd | E110: #MA.LOC_CD | G110: Mfg. location cd. | H110: 製造場所ＣＤ | I110: - | J110: -
...

Sheet MfgActReg_Upd03
A1: * | B1: * | D1: L | E1: 1
A2: * | D2: オペレーション実装仕様書 Operation Specification Implementation Sheet | E2: ModuleID : | F2: =IF(LogicCommon!C2="","",LogicCommon!C2) -> MS | G2: LogicID : | H2: =IF(LogicCommon!E2="","",LogicCommon!E2) -> MSBCL6050 | I2: Ope.ID : | J2: MfgActReg_Upd03 | K2: Pj.ID : | L2: =IF(LogicCommon!G2="","",LogicCommon!G2) -> MC | M2: Ope.Body : | N2: "mcframe.serverMAUD.MAUDL5010.MAUDL_Operation"
A3: * | D3: =IF(LogicCommon!A3="","",LogicCommon!A3) | E3: SubModuleID : | F3: =IF(LogicCommon!C3="","",LogicCommon!C3) -> MSBC | G3: LogicClass : | H3: =IF(LogicCommon!E3="","",LogicCommon!E3) -> MSBCL_MfgActRegService | I3: Ope.Method : | J3: MfgActReg_Upd03 | K3: SuperClassPj.ID : | L3: =IF(LogicCommon!G3="","",LogicCommon!G3) | O3: Gene.Type : | P3: ALL
A4: * | E4: Version : | F4: 000000 | G4: LogicName : | H4: =IF(LogicCommon!E4="","",LogicCommon!E4) -> 製造実績登録サービス | I4: Ope.Name : | J4: 工数実績登録・訂正 | K4: SuperLogicID : | L4: =IF(LogicCommon!G4="","",LogicCommon!G4) -> MS.MSUDL5010 | M4: ImplOpe.ID:
A5: * | E5: ACType :
A6: * | D6: 概要 : | E6: 工数実績の登録・訂正処理 | M6: ID | O6: ID | Q6: ID
A7: # | I7: U | K7: K | L7: o | N7: o | P7: o
A8: # | D8: ブロック名 Block Name | E8: 型 Type | G8: super/share | H8: 対象ブロック名 Target Block Name | L8: TargetName | N8: TargetName | P8: TargetName | T8: ブロック備考 Block Remarks
A9: # | D9: 項目名 Field Name | E9: 型 Type | F9: 桁 Digits | G9: フルネーム Full Name | H9: 日本語名 Japanese Name | I9: 上り項目 Request Message Field | J9: 下り項目 Response Message Field | R9: 条件および編集方法 Conditions and Editing Methods | T9: 項目備考 Field Remarks
A10: # | L10: 上り項目 Request Message Field | M10: 下り項目 Response Message Field | N10: 上り項目 Request Message Field | O10: 下り項目 Response Message Field | P10: 上り項目 Request Message Field | Q10: 下り項目 Response Message Field
A11: 10 | B11: * | D11: MfgActReg_Upd03_Rslt | E11: L | G11: $share$ | H11: MS.MSBCL6050.MfgActReg_Chk04.MfgActReg_Chk04_Rslt
A12: 10 | D12: peg_no | E12: #MA.INT | G12: Pegging No. | H12: 紐付けＮＯ | I12: E | J12: E
A13: 10 | D13: err_flg | E13: #MA.FLG | G13: Error flg. | H13: エラーＦＬＧ | I13: E | J13: E
A14: 10 | D14: data_crud_typ | E14: #MA.DATA_CRUD_TYP | G14: Data update type | H14: データ更新区分 | I14: E | J14: -
A15: 10 | D15: inst_wk_act_flg | E15: #MA.FLG | G15: Order direct man-hour result | H15: 指図工数実績 | I15: E | J15: -
A16: 10 | D16: mfg_inst_no | E16: #MA.MFG_INST_NO | G16: Mfg. order No. | H16: 製造指図ＮＯ | I16: E | J16: -
A17: 10 | D17: div_seq | E17: #MS.DIV_SEQ | G17: Split sequence number | H17: 分割連番 | I17: E | J17: -
A18: 10 | D18: disp_seq | E18: #MA.INT | G18: Display order | H18: 表示順 | I18: - | J18: -
A19: 10 | D19: oper_ptn | E19: #MA.OPER_PTN | G19: Operation pattern | H19: 工程パタン | I19: - | J19: -
A20: 10 | D20: oper_disp_seq | E20: #MA.INT | G20: Routing | H20: 工順 | I20: - | J20: -
A21: 10 | D21: oper_cd | E21: #MA.OPER_CD | G21: Operation cd. | H21: 工程ＣＤ | I21: E | J21: -
A22: 10 | D22: oper_nm | E22: #MA.OPER_NM | G22: Operation name | H22: 工程名 | I22: E | J22: -
A23: 10 | D23: oper_seq | E23: #MA.OPER_SEQ | G23: Operation sequence number | H23: 工程連番 | I23: - | J23: -
... A151: 10 | D151: ext_wk_act_no | E151: #MA.EXT_WK_ACT_NO | G151: External man-hour result No. | H151: 外部工数実績ＮＯ | I151: E | J151: -
A153: 20 | B153: * | D153: MfgActReg_Upd03_Ctrl | E153: R
A154: 20 | D154: not_commit_flg | E154: #MA.FLG | G154: Do not commit | H154: コミットしない | I154: E | J154: -
D155: 詳細 :

Sheet MfgActReg_Upd04
A1: * | B1: * | D1: L | E1: 1
A2: * | D2: オペレーション実装仕様書 Operation Specification Implementation Sheet | E2: ModuleID : | F2: =IF(LogicCommon!C2="","",LogicCommon!C2) -> MS | G2: LogicID : | H2: =IF(LogicCommon!E2="","",LogicCommon!E2) -> MSBCL6050 | I2: Ope.ID : | J2: MfgActReg_Upd04 | K2: Pj.ID : | L2: =IF(LogicCommon!G2="","",LogicCommon!G2) -> MC | M2: Ope.Body : | N2: "mcframe.serverMAUD.MAUDL5010.MAUDL_Operation"
A3: * | D3: =IF(LogicCommon!A3="","",LogicCommon!A3) | E3: SubModuleID : | F3: =IF(LogicCommon!C3="","",LogicCommon!C3) -> MSBC | G3: LogicClass : | H3: =IF(LogicCommon!E3="","",LogicCommon!E3) -> MSBCL_MfgActRegService | I3: Ope.Method : | J3: MfgActReg_Upd04 | K3: SuperClassPj.ID : | L3: =IF(LogicCommon!G3="","",LogicCommon!G3) | O3: Gene.Type : | P3: ALL
A4: * | E4: Version : | F4: 000000 | G4: LogicName : | H4: =IF(LogicCommon!E4="","",LogicCommon!E4) -> 製造実績登録サービス | I4: Ope.Name : | J4: 工程実績完了 | K4: SuperLogicID : | L4: =IF(LogicCommon!G4="","",LogicCommon!G4) -> MS.MSUDL5010 | M4: ImplOpe.ID:
A5: * | E5: ACType :
A6: * | D6: 概要 : | E6: 製造実績受信ＩＦで自動作成された工程実績に紐付くすべての実績が完了になった場合、工程実績を完了にする。 | M6: ID | O6: ID | Q6: ID
A7: # | I7: U | K7: K | L7: o | N7: o | P7: o
A8: # | D8: ブロック名 Block Name | E8: 型 Type | G8: super/share | H8: 対象ブロック名 Target Block Name | L8: TargetName | N8: TargetName | P8: TargetName | T8: ブロック備考 Block Remarks
A9: # | D9: 項目名 Field Name | E9: 型 Type | F9: 桁 Digits | G9: フルネーム Full Name | H9: 日本語名 Japanese Name | I9: 上り項目 Request Message Field | J9: 下り項目 Response Message Field | R9: 条件および編集方法 Conditions and Editing Methods | T9: 項目備考 Field Remarks
A10: # | L10: 上り項目 Request Message Field | M10: 下り項目 Response Message Field | N10: 上り項目 Request Message Field | O10: 下り項目 Response Message Field | P10: 上り項目 Request Message Field | Q10: 下り項目 Response Message Field
A11: 10 | B11: * | D11: MfgActReg_Upd04_Ctrl | E11: R
A12: 10 | D12: is_src_batch_flg | E12: #MA.FLG | G12: Caller batch process | H12: 呼出元バッチ処理 | I12: E | J12: -
A13: 10 | D13: upd_cntr_chk_flg | E13: #MA.FLG | G13: Check for update counter | H13: 更新カウンタチェック | I13: E | J13: -
A14: 10 | D14: not_commit_flg | E14: #MA.FLG | G14: Do not commit | H14: コミットしない | I14: E | J14: -
A15: 10 | D15: not_wk_cost_upd_calc_flg | E15: #MA.FLG | G15: Do not auto-calculate man-hour | H15: 自動工数計算しない | I15: E | J15: -
A17: 20 | B17: * | D17: MfgActReg_Upd04_DtlOper | E17: L
A18: 20 | D18: peg_no | E18: #MA.INT | G18: Pegging No. | H18: 紐付けＮＯ | I18: E | J18: E
A19: 20 | D19: oper_act_no | E19: #MA.OPER_ACT_NO | G19: Operation result No. | H19: 工程実績ＮＯ | I19: E | J19: -
A20: 20 | D20: mfg_inst_no | E20: #MA.MFG_INST_NO | G20: Mfg. order No. | H20: 製造指図ＮＯ | I20: - | J20: -
A21: 20 | D21: rtn_sts_typ | E21: #MA.RTN_STS_TYP | G21: Process result status type | H21: 処理結果状況区分 | I21: - | J21: E
D22: 詳細 :

Sheet MfgActReg_Del01
A1: * | B1: * | D1: L | E1: 1
A2: * | D2: オペレーション実装仕様書 Operation Specification Implementation Sheet | E2: ModuleID : | F2: =IF(LogicCommon!C2="","",LogicCommon!C2) -> MS | G2: LogicID : | H2: =IF(LogicCommon!E2="","",LogicCommon!E2) -> MSBCL6050 | I2: Ope.ID : | J2: MfgActReg_Del01 | K2: Pj.ID : | L2: =IF(LogicCommon!G2="","",LogicCommon!G2) -> MC | M2: Ope.Body : | N2: "mcframe.serverMAUD.MAUDL5010.MAUDL_Operation"
A3: * | D3: =IF(LogicCommon!A3="","",LogicCommon!A3) | E3: SubModuleID : | F3: =IF(LogicCommon!C3="","",LogicCommon!C3) -> MSBC | G3: LogicClass : | H3: =IF(LogicCommon!E3="","",LogicCommon!E3) -> MSBCL_MfgActRegService | I3: Ope.Method : | J3: MfgActReg_Del01 | K3: SuperClassPj.ID : | L3: =IF(LogicCommon!G3="","",LogicCommon!G3) | O3: Gene.Type : | P3: ALL
A4: * | E4: Version : | F4: 000000 | G4: LogicName : | H4: =IF(LogicCommon!E4="","",LogicCommon!E4) -> 製造実績登録サービス | I4: Ope.Name : | J4: 取消 | K4: SuperLogicID : | L4: =IF(LogicCommon!G4="","",LogicCommon!G4) -> MS.MSUDL5010 | M4: ImplOpe.ID:
A5: * | E5: ACType :
A6: * | D6: 概要 : | E6: 製造実績の取消の共通処理 | M6: ID | O6: ID | Q6: ID
A7: # | I7: U | K7: K | L7: o | M7: MA.maChk02 | N7: o | P7: o
A8: # | D8: ブロック名 Block Name | E8: 型 Type | G8: super/share | H8: 対象ブロック名 Target Block Name | L8: TargetName | M8: OPE.MS.MSBCL6050.MfgActReg_Chk02 | N8: TargetName | P8: TargetName | T8: ブロック備考 Block Remarks
A9: # | D9: 項目名 Field Name | E9: 型 Type | F9: 桁 Digits | G9: フルネーム Full Name | H9: 日本語名 Japanese Name | I9: 上り項目 Request Message Field | J9: 下り項目 Response Message Field | R9: 条件および編集方法 Conditions and Editing Methods | T9: 項目備考 Field Remarks
A10: # | L10: 上り項目 Request Message Field | M10: 下り項目 Response Message Field | N10: 上り項目 Request Message Field | O10: 下り項目 Response Message Field | P10: 上り項目 Request Message Field | Q10: 下り項目 Response Message Field
A11: 10 | B11: * | D11: MfgActReg_Del01_Ctrl | E11: R | L11: MfgActReg_Chk02_Ctrl
A12: 10 | D12: lst_del_flg | E12: #MA.FLG | G12: Bulk cancellation flg. | H12: 一括取消ＦＬＧ | I12: E | J12: - | L12: E
A13: 10 | D13: upd_cntr_chk_flg | E13: #MA.FLG | G13: Check for update counter | H13: 更新カウンタチェック | I13: E | J13: - | L13: E
A14: 10 | D14: is_src_batch_flg | E14: #MA.FLG | G14: Caller batch process | H14: 呼出元バッチ処理 | I14: E | J14: - | L14: E
A15: 10 | D15: not_commit_flg | E15: #MA.FLG | G15: Do not commit | H15: コミットしない | I15: E | J15: - | L15: -
A17: 20 | B17: * | D17: MfgActReg_Del01_Hdr | E17: L | L17: MfgActReg_Chk02_Hdr | M17: MfgActReg_Chk02_Hdr
A18: 20 | D18: peg_no | E18: #MA.INT | G18: Pegging No. | H18: 紐付けＮＯ | I18: E | J18: E | L18: E
A19: 20 | D19: mfg_act_no | E19: #MA.MFG_ACT_NO | G19: Mfg. result No. | H19: 製造実績ＮＯ | I19: E | J19: - | L19: E
A20: 20 | D20: mfg_inst_upd_cntr | E20: #MA.UPD_CNT | G20: Mfg. order update counter | H20: 製造指図更新カウンタ | I20: E | J20: - | L20: E
A21: 20 | D21: mfg_inst_pr_upd_cntr | E21: #MA.UPD_CNT | G21: Production order progress update counter | H21: 製造指図進捗更新カウンタ | I21: E | L21: E
A22: 20 | D22: mfg_act_upd_cntr | E22: #MA.UPD_CNT | G22: Mfg. result update counter | H22: 製造実績更新カウンタ | I22: E | J22: - | L22: E
A23: 20 | D23: mfg_inst_no | E23: #MA.MFG_INST_NO | G23: Mfg. order No. | H23: 製造指図ＮＯ | I23: E | J23: - | L23: E
A24: 20 | D24: div_seq | E24: #MS.DIV_SEQ | G24: Split sequence number | H24: 分割連番 | I24: E | J24: - | L24: E
A25: 20 | D25: err_flg | E25: #MA.FLG | G25: Error | H25: エラー | I25: - | J25: E | L25: - | M25: E
A26: 20 | D26: rtn_sts_typ | E26: #MA.RTN_STS_TYP | G26: Process result status type | H26: 処理結果状況区分 | I26: - | J26: E | L26: - | M26: E
A27: 20 | D27: upd_cntr_chk_flg | E27: #MA.FLG | G27: Check for update counter | H27: 更新カウンタチェック | I27: - | J27: - | L27: E
A28: 20 | D28: is_src_batch_flg | E28: #MA.FLG | G28: Caller batch process | H28: 呼出元バッチ処理 | I28: - | J28: - | L28: E
A30: 30 | B30: * | D30: MfgActReg_Del01_DtlInpt | E30: L | L30: MfgActReg_Chk02_DtlInpt
A31: 30 | D31: inpt_act_no | E31: #MA.INPT_ACT_NO | G31: Input result No. | H31: 投入実績ＮＯ | I31: E | J31: - | L31: E
A32: 30 | D32: can_ac_dt | E32: #MA.DT | G32: Cancellation recording date | H32: 取消計上日 | I32: E | J32: - | L32: E
A34: 40 | B34: * | D34: MfgActReg_Del01_DtlYield | E34: L | L34: MfgActReg_Chk02_DtlYield
A35: 40 | D35: yield_act_no | E35: #MA.YIELD_ACT_NO | G35: Output result No. | H35: 出来高実績ＮＯ | I35: E | J35: - | L35: E
A36: 40 | D36: can_ac_dt | E36: #MA.DT | G36: Cancellation recording date | H36: 取消計上日 | I36: E | J36: - | L36: E
A38: 50 | B38: * | D38: MfgActReg_Del01_DtlByProd | E38: L | L38: MfgActReg_Chk02_DtlByProd
A39: 50 | D39: yield_act_no | E39: #MA.YIELD_ACT_NO | G39: Output result No. | H39: 出来高実績ＮＯ | I39: E | J39: - | L39: E
A40: 50 | D40: can_ac_dt | E40: #MA.DT | G40: Cancellation recording date | H40: 取消計上日 | I40: E | J40: - | L40: E
D41: 詳細 :

Sheet MfgActReg_Del02
A1: * | B1: * | D1: L | E1: 1
A2: * | D2: オペレーション実装仕様書 Operation Specification Implementation Sheet | E2: ModuleID : | F2: =IF(LogicCommon!C2="","",LogicCommon!C2) -> MS | G2: LogicID : | H2: =IF(LogicCommon!E2="","",LogicCommon!E2) -> MSBCL6050 | I2: Ope.ID : | J2: MfgActReg_Del02 | K2: Pj.ID : | L2: =IF(LogicCommon!G2="","",LogicCommon!G2) -> MC | M2: Ope.Body : | N2: "mcframe.serverMAUD.MAUDL5010.MAUDL_Operation"
A3: * | D3: =IF(LogicCommon!A3="","",LogicCommon!A3) | E3: SubModuleID : | F3: =IF(LogicCommon!C3="","",LogicCommon!C3) -> MSBC | G3: LogicClass : | H3: =IF(LogicCommon!E3="","",LogicCommon!E3) -> MSBCL_MfgActRegService | I3: Ope.Method : | J3: MfgActReg_Del02 | K3: SuperClassPj.ID : | L3: =IF(LogicCommon!G3="","",LogicCommon!G3) | O3: Gene.Type : | P3: ALL
A4: * | E4: Version : | F4: 000000 | G4: LogicName : | H4: =IF(LogicCommon!E4="","",LogicCommon!E4) -> 製造実績登録サービス | I4: Ope.Name : | J4: 工数実績取消 | K4: SuperLogicID : | L4: =IF(LogicCommon!G4="","",LogicCommon!G4) -> MS.MSUDL5010 | M4: ImplOpe.ID:
A5: * | E5: ACType :
A6: * | D6: 概要 : | E6: 工数実績の取消処理 | M6: ID | O6: ID | Q6: ID
A7: # | I7: U | K7: K | L7: o | N7: o | P7: o
A8: # | D8: ブロック名 Block Name | E8: 型 Type | G8: super/share | H8: 対象ブロック名 Target Block Name | L8: TargetName | N8: TargetName | P8: TargetName | T8: ブロック備考 Block Remarks
A9: # | D9: 項目名 Field Name | E9: 型 Type | F9: 桁 Digits | G9: フルネーム Full Name | H9: 日本語名 Japanese Name | I9: 上り項目 Request Message Field | J9: 下り項目 Response Message Field | R9: 条件および編集方法 Conditions and Editing Methods | T9: 項目備考 Field Remarks
A10: # | L10: 上り項目 Request Message Field | M10: 下り項目 Response Message Field | N10: 上り項目 Request Message Field | O10: 下り項目 Response Message Field | P10: 上り項目 Request Message Field | Q10: 下り項目 Response Message Field
A11: 10 | B11: * | D11: MfgActReg_Del02_Rslt | E11: L | G11: $share$ | H11: MS.MSBCL6050.MfgActReg_Chk04.MfgActReg_Chk04_Rslt
A12: 10 | D12: peg_no | E12: #MA.INT | G12: Pegging No. | H12: 紐付けＮＯ | I12: E | J12: E
A13: 10 | D13: err_flg | E13: #MA.FLG | G13: Error flg. | H13: エラーＦＬＧ | I13: E | J13: E
A14: 10 | D14: data_crud_typ | E14: #MA.DATA_CRUD_TYP | G14: Data update type | H14: データ更新区分 | I14: E | J14: -
A15: 10 | D15: inst_wk_act_flg | E15: #MA.FLG | G15: Order direct man-hour result | H15: 指図工数実績 | I15: E | J15: -
A16: 10 | D16: mfg_inst_no | E16: #MA.MFG_INST_NO | G16: Mfg. order No. | H16: 製造指図ＮＯ | I16: E | J16: -
A17: 10 | D17: div_seq | E17: #MS.DIV_SEQ | G17: Split sequence number | H17: 分割連番 | I17: E | J17: -
A18: 10 | D18: disp_seq | E18: #MA.INT | G18: Display order | H18: 表示順 | I18: - | J18: -
A19: 10 | D19: oper_ptn | E19: #MA.OPER_PTN | G19: Operation pattern | H19: 工程パタン | I19: - | J19: -
A20: 10 | D20: oper_disp_seq | E20: #MA.INT | G20: Routing | H20: 工順 | I20: - | J20: -
A21: 10 | D21: oper_cd | E21: #MA.OPER_CD | G21: Operation cd. | H21: 工程ＣＤ | I21: - | J21: -
A22: 10 | D22: oper_nm | E22: #MA.OPER_NM | G22: Operation name | H22: 工程名 | I22: - | J22: -
A23: 10 | D23: oper_seq | E23: #MA.OPER_SEQ | G23: Operation sequence number | H23: 工程連番 | I23: - | J23: -
... A151: 10 | D151: ext_wk_act_no | E151: #MA.EXT_WK_ACT_NO | G151: External man-hour result No. | H151: 外部工数実績ＮＯ | I151: - | J151: -
A153: 20 | B153: * | D153: MfgActReg_Del02_Ctrl | E153: R
A154: 20 | D154: not_commit_flg | E154: #MA.FLG | G154: Do not commit | H154: コミットしない | I154: E | J154: -
D155: 詳細 :

Sheet Sheet1

Sheet 来歴
A1: 変更来歴
A3: Rev. | H3: 修正番号 | O3: 変更内容 | AQ3: 変更箇所
A4: 1 | O4: 初版
A5: 1.1 | H5: MS7032#065 | O5: MfgActReg_Chk01_Hdrブロックにis_md_src_mfg_srv_flgを追加 | AQ5: MfgActReg_Chk01
A6: 〃 | H6: 〃 | O6: MfgActReg_Upd01_HdrブロックとMfgActReg_Upd01_DtlInptブロックにis_src_md_mfg_srv_flgを追加 | AQ6: MfgActReg_Upd01
A7: 1.2 | H7: MS7032#174 | O7: MfgActReg_Chk01_DtlInptブロックにis_only_abort_flgを追加 | AQ7: MfgActReg_Chk01
A8: 〃 | H8: 〃 | O8: MfgActReg_Upd01_DtlInptブロックにis_only_abort_flgを追加 | AQ8: MfgActReg_Upd01
A9: 〃 | H9: 〃 | O9: MfgActReg_Upd02_DtlInptブロックにis_only_abort_flgを追加 | AQ9: MfgActReg_Upd02
A10: 1.3 | O10: 英語の名称を追記 | AQ10: 全般
