Workbook

Sheet LogicCommon
A2: ロジック共通定義 | B2: ModuleID : | C2: MA | D2: LogicID : | E2: MABGL0010 | F2: Pj.ID : | G2: MC
B3: SubModuleID : | C3: MABG | D3: LogicClass : | E3: MABGL_CoParmReg | F3: SuperClassPj.ID :
D4: LogicName : | E4: 原価会社パラメータマスタ登録 | F4: SuperLogicID : | G4: MA.MAUDL5010
A5: 概要 :
A6: 詳細 :

Sheet CoParm_UpdChk01
A1: * | B1: * | D1: L | E1: 1
A2: * | D2: オペレーション実装仕様書 Operation Specification Implementation Sheet | E2: ModuleID : | F2: =IF(LogicCommon!C2="","",LogicCommon!C2) -> MA | G2: LogicID : | H2: =IF(LogicCommon!E2="","",LogicCommon!E2) -> MABGL0010 | I2: Ope.ID : | J2: CoParm_UpdChk01 | K2: Pj.ID : | L2: =IF(LogicCommon!G2="","",LogicCommon!G2) -> MC | M2: Ope.Body : | N2: =L4 & ".Checker" -> MA.MAUDL5010.Checker
A3: * | D3: =IF(LogicCommon!A3="","",LogicCommon!A3) | E3: SubModuleID : | F3: =IF(LogicCommon!C3="","",LogicCommon!C3) -> MABG | G3: LogicClass : | H3: =IF(LogicCommon!E3="","",LogicCommon!E3) -> MABGL_CoParmReg | I3: Ope.Method : | J3: @ | K3: SuperClassPj.ID : | L3: =IF(LogicCommon!G3="","",LogicCommon!G3) | M3: ReportID : | O3: Gene.Type : | P3: ALL
A4: * | E4: Version : | F4: 000000 | G4: LogicName : | H4: =IF(LogicCommon!E4="","",LogicCommon!E4) -> 原価会社パラメータマスタ登録 | I4: Ope.Name : | J4: 登録前チェック | K4: SuperLogicID : | L4: =IF(LogicCommon!G4="","",LogicCommon!G4) -> MA.MAUDL5010
A5: * | E5: ACType :
A6: * | D6: 概要 : | E6: 原価会社パラメータマスタを登録する前のチェックを行う | T6: ID
A7: # | I7: U | K7: K | L7: K | M7: K | N7: K | O7: K | P7: K | Q7: K | R7: K | S7: o
A8: # | D8: ブロック名 Block Name | E8: 型 Type | G8: super/share | H8: 対象ブロック名 Target Block Name | K8: REQUIRED | L8: CONST | M8: LIST_LOGIC | N8: LIST_OUT | O8: LIST_OUT_BASE | P8: LIST_IN | Q8: LIST_IN_BASE | R8: SMALL_LARGE | S8: TargetName | W8: ブロック備考 Block Remarks
A9: # | D9: 項目名 Field Name | E9: 型 Type | F9: 桁 Digits | G9: フルネーム Full Name | H9: 日本語名 Japanese Name | I9: 上り項目 Request Message Field | J9: 下り項目 Response Message Field | U9: 条件および編集方法 Conditions and Editing Methods | W9: 項目備考 Field Remarks
A10: # | S10: 上り項目 Request Message Field | T10: 下り項目 Response Message Field
A11: 10 | B11: * | D11: CoParm_UpdChk01_Dtl | E11: L | G11: $super$ | H11: DBC:MA.MAM_CO_PARM
A12: 10 | D12: co_cd | E12: #MA.CO_CD | G12: Company cd. | H12: 会社ＣＤ | I12: E | K12: E
A13: 10 | D13: std_rnd_typ | E13: #MA.RND_TYP | G13: Rounding type (Standard) | H13: 標準端数処理区分 | I13: E | K13: E | L13: MAC_RND_TYP
A14: 10 | D14: std_dec_place | E14: #MA.DEC_PLACE | G14: Standard number of decimal places | H14: 標準小数部有効桁数 | I14: E | K14: E | R14: 0:8
A15: 10 | D15: amt_rnd_typ | E15: #MA.RND_TYP | G15: Rounding type (Amount) | H15: 金額端数処理区分 | I15: E | K15: E | L15: MAC_RND_TYP
A16: 10 | D16: amt_dec_place | E16: #MA.DEC_PLACE | G16: Amount number of decimal places | H16: 金額小数部有効桁数 | I16: E | K16: E | R16: 0:8
A17: 10 | D17: ave_rnd_typ | E17: #MA.RND_TYP | G17: Rounding type (Unit price) | H17: 単価端数処理区分 | I17: E | K17: E | L17: MAC_RND_TYP
A18: 10 | D18: ave_dec_place | E18: #MA.DEC_PLACE | G18: Unit price number of decimal places | H18: 単価小数部有効桁数 | I18: E | K18: E | R18: 0:8
A19: 10 | D19: adj_typ | E19: #MA.ADJ_TYP | G19: Fraction adjustment type | H19: 端数調整区分 | I19: E | K19: E | L19: MAC_ADJ_TYP
A20: 10 | D20: mrgn_expns_cd | E20: #MA.EXPNS_CD | G20: Adjustment cost element cd. | H20: 調整費目ＣＤ | I20: E | K20: E | M20: MA.MAUAL0010.Expns | P20: MAC_EXPNS_TYP.PROD | Q20: expns_typ
A21: 10 | D21: purc_expns_cd | E21: #MA.EXPNS_CD | G21: Purchase cost element item cd. | H21: 購買費目ＣＤ | I21: E | M21: MA.MAUAL0010.Expns | P21: MAC_EXPNS_TYP.PROD | Q21: expns_typ
A22: 10 | D22: out_expns_cd | E22: #MA.EXPNS_CD | G22: Subcontract cost element cd. | H22: 外注費目ＣＤ | I22: E | M22: MA.MAUAL0010.Expns | P22: MAC_EXPNS_TYP.PROD | Q22: expns_typ
A23: 10 | D23: inpt_expns_cd | E23: #MA.EXPNS_CD | G23: Input cost element cd. | H23: 投入費目ＣＤ | I23: E | M23: MA.MAUAL0010.Expns | P23: MAC_EXPNS_TYP.PROD | Q23: expns_typ
A24: 10 | D24: ss_expns_cd | E24: #MA.EXPNS_CD | G24: Self supply cost element cd. | H24: 自給費目ＣＤ | I24: E | M24: MA.MAUAL0010.Expns | P24: MAC_EXPNS_TYP.PROD | Q24: expns_typ
A25: 10 | D25: prov_expns_cd | E25: #MA.EXPNS_CD | G25: Cost element cd. for gain or loss of chargeable item | H25: 有償差額費目ＣＤ | I25: E | M25: MA.MAUAL0010.Expns | P25: MAC_EXPNS_TYP.SPPL | Q25: expns_typ
A26: 10 | D26: pre_alc_max_lvl | E26: #MA.PRE_ALC_MAX_LVL | G26: Departmental alloc. max. hierarchy | H26: 一次配賦最大階層 | I26: E | R26: 0:999
A27: 10 | D27: pre_alc_max_rec | E27: #MA.PRE_ALC_MAX_REC | G27: Departmental alloc. max. number of records | H27: 一次配賦最大レコード数 | I27: E | R27: 0:999999999
A28: 10 | D28: diff_use_typ | E28: #MA.DIFF_USE_TYP | G28: Variance use type | H28: 差異使用区分 | I28: E | L28: MAC_DIFF_USE_TYP
A29: 10 | D29: lot_use_typ | E29: #MA.PS_USE_TYP | G29: Lot No. use type for production/sales | H29: ロットＮＯ生販使用区分 | I29: E | L29: MAC_PS_USE_TYP
A30: 10 | D30: sublot_use_typ | E30: #MA.PS_USE_TYP | G30: Sublot No. use type for production/sales | H30: サブロットＮＯ生販使用区分 | I30: E | L30: MAC_PS_USE_TYP
A31: 10 | D31: sno1_use_typ | E31: #MA.PS_USE_TYP | G31: SEIBAN No. 1 production/sales use type | H31: 手配ＮＯ１生販使用区分 | I31: E | L31: MAC_PS_USE_TYP
A32: 10 | D32: sno2_use_typ | E32: #MA.PS_USE_TYP | G32: SEIBAN No. 2 production/sales use type | H32: 手配ＮＯ２生販使用区分 | I32: E | L32: MAC_PS_USE_TYP
A33: 10 | D33: sno3_use_typ | E33: #MA.PS_USE_TYP | G33: SEIBAN No. 3 production/sales use type | H33: 手配ＮＯ３生販使用区分 | I33: E | L33: MAC_PS_USE_TYP
A34: 10 | D34: sno4_use_typ | E34: #MA.PS_USE_TYP | G34: SEIBAN No. 4 production/sales use type | H34: 手配ＮＯ４生販使用区分 | I34: E | L34: MAC_PS_USE_TYP
A35: 10 | D35: def_calc_ctg_cd | E35: #MA.CALC_CTG_CD | G35: Default calculation category | H35: デフォルト計算カテゴリ | I35: E | M35: MA.MAUAL0010.CalcCtg
A36: 10 | D36: fix_dpt_cd | E36: #MA.COST_DPT_CD | G36: Constant management dept. cd. | H36: 固定管理部門ＣＤ | I36: E | M36: MA.MAUAL0010.CostDpt | P36: true | Q36: ignore_ym_flg
A37: 10 | D37: trd_ratio_flg | E37: #MA.FLG | G37: Use standard unit cost at transfer ratio setting | H37: 振替比率設定時に標準単価を使用する | I37: E
A38: 10 | D38: stop_slip_flg | E38: #MA.FLG | G38: Take in canceled slip | H38: 取り消した伝票を取り込む | I38: E
A39: 10 | D39: non_prod_flg | E39: #MA.FLG | G39: Do not import production data | H39: 生産データを取り込まない | I39: E
A40: 10 | D40: oper_sum_flg | E40: #MA.FLG | G40: Import operation cd. as operation result No. | H40: 工程ＣＤを工程実績ＮＯとして取り込む | I40: E
A41: 10 | D41: non_sls_flg | E41: #MA.FLG | G41: Do not import sales data | H41: 販売データを取り込まない | I41: E
A42: 10 | D42: asst_flg | E42: #MA.FLG | G42: Import sales asset as production asset | H42: 販売資産を生産資産として取り込む | I42: E
A43: 10 | D43: stk_bp_flg | E43: #MA.FLG | G43: Include receiving point inventory | H43: 出荷先の在庫を考慮する | I43: E
A44: 10 | D44: non_transit_flg | E44: #MA.FLG | G44: Do not import purchase data of items in transit | H44: 未着品仕入データを取り込まない | I44: E
A45: 10 | D45: wg_non_mov_flg | E45: #MA.FLG | G45: WG with non-moving | H45: ワーキンググループ滞留使用 | I45: E
A46: 10 | D46: lot_non_mov_flg | E46: #MA.FLG | G46: Lot No. with non-moving | H46: ロットＮＯ滞留使用 | I46: E
A47: 10 | D47: sublot_non_mov_flg | E47: #MA.FLG | G47: Sublot No. with non-moving | H47: サブロットＮＯ滞留使用 | I47: E
A48: 10 | D48: sno1_non_mov_flg | E48: #MA.FLG | G48: SEIBAN No. 1 with non-moving | H48: 手配ＮＯ１滞留使用 | I48: E
... A51: 10 | D51: sno4_non_mov_flg | E51: #MA.FLG | G51: SEIBAN No. 4 with non-moving | H51: 手配ＮＯ４滞留使用 | I51: E
A52: 10 | D52: tmp_dpt_cd | E52: #MA.COST_DPT_CD | G52: Transfer dept. cd. | H52: 振替用部門ＣＤ | I52: E | M52: MA.MAUAL0010.CostDpt | P52: true | Q52: ignore_ym_flg
A53: 10 | D53: act_trd_calc_ctg_cd | E53: #MA.CALC_CTG_CD | G53: Result transfer calculation category cd. | H53: 実績振替計算カテゴリＣＤ | I53: E | M53: MA.MAUAL0010.CalcCtg
A54: 10 | D54: chk_mst_flg | E54: #MA.FLG | G54: Check existence of master | H54: マスタの存在チェックを行う | I54: E
A55: 10 | D55: stktk_sum_flg | E55: #MA.FLG | G55: Do not consolidate the inventory count | H55: 棚卸を集約しない | I55: E
A56: 10 | D56: oth_ccn_sum_flg | E56: #MA.FLG | G56: Do not consolidate other accounting data | H56: 他勘定を集約しない | I56: E
A57: 10 | D57: std_disp_digit | E57: #MA.DISP_DIGIT | G57: Display digits (Standard decimal places) | H57: 標準小数部表示桁 | I57: E | K57: E | R57: 0:9
A58: 10 | D58: amt_disp_digit | E58: #MA.DISP_DIGIT | G58: Display digits (Amount decimal places) | H58: 金額小数部表示桁 | I58: E | K58: E | R58: 0:9
A59: 10 | D59: unit_disp_digit | E59: #MA.DISP_DIGIT | G59: Display digits (Unit price decimal places) | H59: 単価小数部表示桁 | I59: E | K59: E | R59: 0:9
A60: 10 | D60: rate_disp_digit | E60: #MA.DISP_DIGIT | G60: Display digits (Ratio decimal places) | H60: 比率小数部表示桁 | I60: E | R60: 0:9
A61: 10 | D61: excel_pln_flg | E61: #MA.FLG | G61: Input/output planning data in Excel | H61: 計画データをＥｘｃｅｌで入出力する | I61: E
A62: 10 | D62: excel_act_flg | E62: #MA.FLG | G62: Input/output result data in Excel | H62: 実績データをＥｘｃｅｌで入出力する | I62: E
A63: 10 | D63: excel_alc_flg | E63: #MA.FLG | G63: Input/output allocation data in Excel | H63: 配賦データをＥｘｃｅｌで入出力する | I63: E
A64: 10 | D64: upd_cntr | E64: #MA.UPD_CNT | G64: Update counter | H64: 更新カウンタ | I64: E
D65: 詳細 :

Sheet CoParm_Upd01
A1: * | B1: * | D1: L | E1: 1
A2: * | D2: オペレーション実装仕様書 Operation Specification Implementation Sheet | E2: ModuleID : | F2: =IF(LogicCommon!C2="","",LogicCommon!C2) -> MA | G2: LogicID : | H2: =IF(LogicCommon!E2="","",LogicCommon!E2) -> MABGL0010 | I2: Ope.ID : | J2: CoParm_Upd01 | K2: Pj.ID : | L2: =IF(LogicCommon!G2="","",LogicCommon!G2) -> MC | M2: Ope.Body : | N2: "mcframe.serverMAUD.MAUDL6010.MAUDL_RLUpdater"
A3: * | D3: =IF(LogicCommon!A3="","",LogicCommon!A3) | E3: SubModuleID : | F3: =IF(LogicCommon!C3="","",LogicCommon!C3) -> MABG | G3: LogicClass : | H3: =IF(LogicCommon!E3="","",LogicCommon!E3) -> MABGL_CoParmReg | I3: Ope.Method : | J3: @ | K3: SuperClassPj.ID : | L3: =IF(LogicCommon!G3="","",LogicCommon!G3) | M3: ReportID : | O3: Gene.Type : | P3: ALL
A4: * | E4: Version : | F4: 000000 | G4: LogicName : | H4: =IF(LogicCommon!E4="","",LogicCommon!E4) -> 原価会社パラメータマスタ登録 | I4: Ope.Name : | J4: 登録処理 | K4: SuperLogicID : | L4: =IF(LogicCommon!G4="","",LogicCommon!G4) -> MA.MAUDL5010
A5: * | E5: ACType :
A6: * | D6: 概要 : | E6: 原価会社パラメータマスタを登録する | L6: ID | N6: ID | P6: ID | R6: ID
A7: # | I7: U | K7: o | L7: UPDATE.updMaster | M7: o | N7: MAIN.chkMaster | O7: o | Q7: o
A8: # | D8: ブロック名 Block Name | E8: 型 Type | G8: super/share | H8: 対象ブロック名 Target Block Name | K8: TargetName | L8: DBC.MA.MAM_CO_PARM | M8: TargetName | N8: DBC.MA.MAM_CO_PARM | O8: TargetName | Q8: TargetName | U8: ブロック備考 Block Remarks
A9: # | D9: 項目名 Field Name | E9: 型 Type | F9: 桁 Digits | G9: フルネーム Full Name | H9: 日本語名 Japanese Name | I9: 上り項目 Request Message Field | J9: 下り項目 Response Message Field | S9: 条件および編集方法 Conditions and Editing Methods | U9: 項目備考 Field Remarks
A10: # | K10: 上り項目 Request Message Field | L10: 下り項目 Response Message Field | M10: 上り項目 Request Message Field | N10: 下り項目 Response Message Field | O10: 上り項目 Request Message Field | P10: 下り項目 Response Message Field | Q10: 上り項目 Request Message Field | R10: 下り項目 Response Message Field
A11: 10 | B11: * | D11: CoParm_Upd01_Dtl | E11: L | G11: $share$ | H11: MA.MABGL0010.CoParm_UpdChk01.CoParm_UpdChk01_Dtl | K11: L | M11: L
A12: 10 | D12: co_cd | E12: #MA.CO_CD | G12: Company cd. | H12: 会社ＣＤ | I12: E | K12: E | M12: E
A13: 10 | D13: std_rnd_typ | E13: #MA.RND_TYP | G13: Rounding type (Standard) | H13: 標準端数処理区分 | I13: E | K13: E
A14: 10 | D14: std_dec_place | E14: #MA.DEC_PLACE | G14: Standard number of decimal places | H14: 標準小数部有効桁数 | I14: E | K14: E
A15: 10 | D15: amt_rnd_typ | E15: #MA.RND_TYP | G15: Rounding type (Amount) | H15: 金額端数処理区分 | I15: E | K15: E
A16: 10 | D16: amt_dec_place | E16: #MA.DEC_PLACE | G16: Amount number of decimal places | H16: 金額小数部有効桁数 | I16: E | K16: E
A17: 10 | D17: ave_rnd_typ | E17: #MA.RND_TYP | G17: Rounding type (Unit price) | H17: 単価端数処理区分 | I17: E | K17: E
A18: 10 | D18: ave_dec_place | E18: #MA.DEC_PLACE | G18: Unit price number of decimal places | H18: 単価小数部有効桁数 | I18: E | K18: E
A19: 10 | D19: adj_typ | E19: #MA.ADJ_TYP | G19: Fraction adjustment type | H19: 端数調整区分 | I19: E | K19: E
A20: 10 | D20: mrgn_expns_cd | E20: #MA.EXPNS_CD | G20: Adjustment cost element cd. | H20: 調整費目ＣＤ | I20: E | K20: E
A21: 10 | D21: purc_expns_cd | E21: #MA.EXPNS_CD | G21: Purchase cost element item cd. | H21: 購買費目ＣＤ | I21: E | K21: E
A22: 10 | D22: out_expns_cd | E22: #MA.EXPNS_CD | G22: Subcontract cost element cd. | H22: 外注費目ＣＤ | I22: E | K22: E
A23: 10 | D23: inpt_expns_cd | E23: #MA.EXPNS_CD | G23: Input cost element cd. | H23: 投入費目ＣＤ | I23: E | K23: E
A24: 10 | D24: ss_expns_cd | E24: #MA.EXPNS_CD | G24: Self supply cost element cd. | H24: 自給費目ＣＤ | I24: E | K24: E
... A64: 10 | D64: upd_cntr | E64: #MA.UPD_CNT | G64: Update counter | H64: 更新カウンタ | I64: E | K64: E
D65: 詳細 :

Sheet CoParm_DelChk01
A1: * | B1: * | D1: L | E1: 1
A2: * | D2: オペレーション実装仕様書 Operation Specification Implementation Sheet | E2: ModuleID : | F2: =IF(LogicCommon!C2="","",LogicCommon!C2) -> MA | G2: LogicID : | H2: =IF(LogicCommon!E2="","",LogicCommon!E2) -> MABGL0010 | I2: Ope.ID : | J2: CoParm_DelChk01 | K2: Pj.ID : | L2: =IF(LogicCommon!G2="","",LogicCommon!G2) -> MC | M2: Ope.Body : | N2: =L4 & ".Checker" -> MA.MAUDL5010.Checker
A3: * | D3: =IF(LogicCommon!A3="","",LogicCommon!A3) | E3: SubModuleID : | F3: =IF(LogicCommon!C3="","",LogicCommon!C3) -> MABG | G3: LogicClass : | H3: =IF(LogicCommon!E3="","",LogicCommon!E3) -> MABGL_CoParmReg | I3: Ope.Method : | J3: @ | K3: SuperClassPj.ID : | L3: =IF(LogicCommon!G3="","",LogicCommon!G3) | M3: ReportID : | O3: Gene.Type : | P3: ALL
A4: * | E4: Version : | F4: 000000 | G4: LogicName : | H4: =IF(LogicCommon!E4="","",LogicCommon!E4) -> 原価会社パラメータマスタ登録 | I4: Ope.Name : | J4: 削除前チェック | K4: SuperLogicID : | L4: =IF(LogicCommon!G4="","",LogicCommon!G4) -> MA.MAUDL5010
A5: * | E5: ACType :
A6: * | D6: 概要 : | E6: 原価会社パラメータマスタを削除する前のチェックを行う | Q6: ID
A7: # | I7: U | K7: K | P7: o
A8: # | D8: ブロック名 Block Name | E8: 型 Type | G8: super/share | H8: 対象ブロック名 Target Block Name | K8: REQUIRED | P8: TargetName | T8: ブロック備考 Block Remarks
A9: # | D9: 項目名 Field Name | E9: 型 Type | F9: 桁 Digits | G9: フルネーム Full Name | H9: 日本語名 Japanese Name | I9: 上り項目 Request Message Field | J9: 下り項目 Response Message Field | R9: 条件および編集方法 Conditions and Editing Methods | T9: 項目備考 Field Remarks
A10: # | P10: 上り項目 Request Message Field | Q10: 下り項目 Response Message Field
A11: 10 | B11: * | D11: CoParm_DelChk01_Dtl | E11: L
A12: 10 | D12: co_cd | E12: #MA.CO_CD | G12: Company cd. | H12: 会社ＣＤ | I12: E | K12: E
A13: 10 | D13: upd_cntr | E13: #MA.UPD_CNT | G13: Update counter | H13: 更新カウンタ | I13: E
D14: 詳細 :

Sheet CoParm_Del01
A1: * | B1: * | D1: L | E1: 1
A2: * | D2: オペレーション実装仕様書 Operation Specification Implementation Sheet | E2: ModuleID : | F2: =IF(LogicCommon!C2="","",LogicCommon!C2) -> MA | G2: LogicID : | H2: =IF(LogicCommon!E2="","",LogicCommon!E2) -> MABGL0010 | I2: Ope.ID : | J2: CoParm_Del01 | K2: Pj.ID : | L2: =IF(LogicCommon!G2="","",LogicCommon!G2) -> MC | M2: Ope.Body : | N2: "mcframe.serverMAUD.MAUDL6010.MAUDL_RLDeleter"
A3: * | D3: =IF(LogicCommon!A3="","",LogicCommon!A3) | E3: SubModuleID : | F3: =IF(LogicCommon!C3="","",LogicCommon!C3) -> MABG | G3: LogicClass : | H3: =IF(LogicCommon!E3="","",LogicCommon!E3) -> MABGL_CoParmReg | I3: Ope.Method : | J3: @ | K3: SuperClassPj.ID : | L3: =IF(LogicCommon!G3="","",LogicCommon!G3) | M3: ReportID : | O3: Gene.Type : | P3: ALL
A4: * | E4: Version : | F4: 000000 | G4: LogicName : | H4: =IF(LogicCommon!E4="","",LogicCommon!E4) -> 原価会社パラメータマスタ登録 | I4: Ope.Name : | J4: 削除処理 | K4: SuperLogicID : | L4: =IF(LogicCommon!G4="","",LogicCommon!G4) -> MA.MAUDL5010
A5: * | E5: ACType :
A6: * | D6: 概要 : | E6: 原価会社パラメータマスタを削除する | L6: ID | N6: ID
A7: # | I7: U | K7: o | L7: UPDATE.updMaster1 | M7: o
A8: # | D8: ブロック名 Block Name | E8: 型 Type | G8: super/share | H8: 対象ブロック名 Target Block Name | K8: TargetName | L8: DBC.MA.MAM_CO_PARM | M8: TargetName | Q8: ブロック備考 Block Remarks
A9: # | D9: 項目名 Field Name | E9: 型 Type | F9: 桁 Digits | G9: フルネーム Full Name | H9: 日本語名 Japanese Name | I9: 上り項目 Request Message Field | J9: 下り項目 Response Message Field | O9: 条件および編集方法 Conditions and Editing Methods | Q9: 項目備考 Field Remarks
A10: # | K10: 上り項目 Request Message Field | L10: 下り項目 Response Message Field | M10: 上り項目 Request Message Field | N10: 下り項目 Response Message Field
A11: 10 | B11: * | D11: CoParm_Del01_Dtl | E11: L | G11: $share$ | H11: MA.MABGL0010.CoParm_DelChk01.CoParm_DelChk01_Dtl | K11: L
A12: 10 | D12: co_cd | E12: #MA.CO_CD | G12: Company cd. | H12: 会社ＣＤ | I12: E | K12: E
A13: 10 | D13: upd_cntr | E13: #MA.UPD_CNT | G13: Update counter | H13: 更新カウンタ | I13: E | K13: E
D14: 詳細 :

Sheet Srch01
A1: * | B1: * | D1: L | E1: 1
A2: * | D2: オペレーション実装仕様書 Operation Specification Implementation Sheet | E2: ModuleID : | F2: =IF(LogicCommon!C2="","",LogicCommon!C2) -> MA | G2: LogicID : | H2: =IF(LogicCommon!E2="","",LogicCommon!E2) -> MABGL0010 | I2: Ope.ID : | J2: Srch01 | K2: Pj.ID : | L2: =IF(LogicCommon!G2="","",LogicCommon!G2) -> MC | M2: Ope.Body : | N2: "mcframe.serverMAUD.MAUDL6010.MAUDL_RLSearcher"
A3: * | D3: =IF(LogicCommon!A3="","",LogicCommon!A3) | E3: SubModuleID : | F3: =IF(LogicCommon!C3="","",LogicCommon!C3) -> MABG | G3: LogicClass : | H3: =IF(LogicCommon!E3="","",LogicCommon!E3) -> MABGL_CoParmReg | I3: Ope.Method : | J3: @ | K3: SuperClassPj.ID : | L3: =IF(LogicCommon!G3="","",LogicCommon!G3) | M3: ReportID : | O3: Gene.Type : | P3: ALL
A4: * | E4: Version : | F4: 000000 | G4: LogicName : | H4: =IF(LogicCommon!E4="","",LogicCommon!E4) -> 原価会社パラメータマスタ登録 | I4: Ope.Name : | J4: 検索 | K4: SuperLogicID : | L4: =IF(LogicCommon!G4="","",LogicCommon!G4) -> MA.MAUDL5010
A5: * | E5: ACType :
A6: * | D6: 概要 : | E6: 検索処理を行う | M6: ID | O6: ID | Q6: ID
A7: # | I7: U | K7: K | L7: o | M7: SELECT.c0 | N7: o | P7: o
A8: # | D8: ブロック名 Block Name | E8: 型 Type | G8: super/share | H8: 対象ブロック名 Target Block Name | K8: CONST | L8: TargetName | M8: DBC.MA.MAM_CO_PARM | N8: TargetName | P8: TargetName | T8: ブロック備考 Block Remarks
A9: # | D9: 項目名 Field Name | E9: 型 Type | F9: 桁 Digits | G9: フルネーム Full Name | H9: 日本語名 Japanese Name | I9: 上り項目 Request Message Field | J9: 下り項目 Response Message Field | R9: 条件および編集方法 Conditions and Editing Methods | T9: 項目備考 Field Remarks
A10: # | L10: 上り項目 Request Message Field | M10: 下り項目 Response Message Field | N10: 上り項目 Request Message Field | O10: 下り項目 Response Message Field | P10: 上り項目 Request Message Field | Q10: 下り項目 Response Message Field
A11: 10 | B11: * | D11: Srch01_Cnd | E11: R | L11: R
A12: 10 | D12: co_cd | E12: #MA.CO_CD | G12: Company cd. | H12: 会社ＣＤ | I12: E
A13: 10 | D13: co_nm | E13: #MA.CO_NM | G13: Company name | H13: 会社名 | I13: E
A14: 10 | D14: this_term | E14: #MA.YM | G14: Term (Correspond to cost login info. change) | H14: 期（原価ログイン情報変更対応） | I14: E
A16: 20 | B16: * | D16: Srch01_Rslt1 | E16: L | M16: L
A17: 20 | D17: co_cd | E17: #MA.CO_CD | G17: Company cd. | H17: 会社ＣＤ
A18: 20 | D18: std_rnd_typ | E18: #MA.RND_TYP | G18: Rounding type (Standard) | H18: 標準端数処理区分 | J18: E | K18: MAC_RND_TYP | M18: E
A19: 20 | D19: std_rnd_typ_nm | E19: #MA.RND_TYP_NM | G19: Rounding type name (Standard) | H19: 標準端数処理区分名 | J19: E
A20: 20 | D20: std_dec_place | E20: #MA.DEC_PLACE | G20: Standard number of decimal places | H20: 標準小数部有効桁数 | J20: E | M20: E
A21: 20 | D21: amt_rnd_typ | E21: #MA.RND_TYP | G21: Rounding type (Amount) | H21: 金額端数処理区分 | J21: E | K21: MAC_RND_TYP | M21: E
A22: 20 | D22: amt_rnd_typ_nm | E22: #MA.RND_TYP_NM | G22: Rounding type name (Amount) | H22: 金額端数処理区分名 | J22: E
A23: 20 | D23: amt_dec_place | E23: #MA.DEC_PLACE | G23: Amount number of decimal places | H23: 金額小数部有効桁数 | J23: E | M23: E
A24: 20 | D24: ave_rnd_typ | E24: #MA.RND_TYP | G24: Rounding type (Unit price) | H24: 単価端数処理区分 | J24: E | K24: MAC_RND_TYP | M24: E
A25: 20 | D25: ave_rnd_typ_nm | E25: #MA.RND_TYP_NM | G25: Rounding type name (Unit price) | H25: 単価端数処理区分名 | J25: E
A26: 20 | D26: ave_dec_place | E26: #MA.DEC_PLACE | G26: Unit price number of decimal places | H26: 単価小数部有効桁数 | J26: E | M26: E
A27: 20 | D27: adj_typ | E27: #MA.ADJ_TYP | G27: Fraction adjustment type | H27: 端数調整区分 | J27: E | K27: MAC_ADJ_TYP | M27: E
A28: 20 | D28: adj_typ_nm | E28: #MA.ADJ_TYP_NM | G28: Fraction adjustment type name | H28: 端数調整区分名 | J28: E
A29: 20 | D29: mrgn_expns_cd | E29: #MA.EXPNS_CD | G29: Adjustment cost element cd. | H29: 調整費目ＣＤ | J29: E | M29: E
A30: 20 | D30: mrgn_expns_nm | E30: #MA.EXPNS_NM | G30: Adjustment cost element name | H30: 調整費目名 | J30: E | M30: E
A31: 20 | D31: purc_expns_cd | E31: #MA.EXPNS_CD | G31: Purchase cost element item cd. | H31: 購買費目ＣＤ | J31: E | M31: E
A32: 20 | D32: purc_expns_nm | E32: #MA.EXPNS_NM | G32: Purchase cost element name | H32: 購買費目名 | J32: E | M32: E
A33: 20 | D33: out_expns_cd | E33: #MA.EXPNS_CD | G33: Subcontract cost element cd. | H33: 外注費目ＣＤ | J33: E | M33: E
A34: 20 | D34: out_expns_nm | E34: #MA.EXPNS_NM | G34: Subcontract cost element name | H34: 外注費目名 | J34: E | M34: E
A35: 20 | D35: inpt_expns_cd | E35: #MA.EXPNS_CD | G35: Input cost element cd. | H35: 投入費目ＣＤ | J35: E | M35: E
A36: 20 | D36: inpt_expns_nm | E36: #MA.EXPNS_NM | G36: Input cost element name | H36: 投入費目名 | J36: E | M36: E
A37: 20 | D37: ss_expns_cd | E37: #MA.EXPNS_CD | G37: Self supply cost element cd. | H37: 自給費目ＣＤ | J37: E | M37: E
A38: 20 | D38: ss_expns_nm | E38: #MA.EXPNS_NM | G38: Self supply cost element name | H38: 自給費目名 | J38: E | M38: E
A39: 20 | D39: prov_expns_cd | E39: #MA.EXPNS_CD | G39: Cost element cd. for gain or loss of chargeable item | H39: 有償差額費目ＣＤ | J39: E | M39: E
A40: 20 | D40: prov_expns_nm | E40: #MA.EXPNS_NM | G40: Gain or loss of chargeable supply cost element name | H40: 有償差額費目名 | J40: E | M40: E
... A42: 20 | D42: pre_alc_max_rec | E42: #MA.PRE_ALC_MAX_REC | G42: Departmental alloc. max. number of records | H42: 一次配賦最大レコード数 | J42: E | M42: E
A43: 20 | D43: diff_use_typ | E43: #MA.DIFF_USE_TYP | G43: Variance use type | H43: 差異使用区分 | J43: E | K43: MAC_DIFF_USE_TYP | M43: E
A44: 20 | D44: diff_use_typ_nm | E44: #MA.DIFF_USE_TYP_NM | G44: Variance use type name | H44: 差異使用区分名 | J44: E
A45: 20 | D45: lot_use_typ | E45: #MA.PS_USE_TYP | G45: Lot No. use type for production/sales | H45: ロットＮＯ生販使用区分 | J45: E | K45: MAC_PS_USE_TYP | M45: E
A46: 20 | D46: lot_use_typ_nm | E46: #MA.PS_USE_TYP_NM | G46: Lot No. production/sales use type name | H46: ロットＮＯ生販使用区分名 | J46: E
A47: 20 | D47: sublot_use_typ | E47: #MA.PS_USE_TYP | G47: Sublot No. use type for production/sales | H47: サブロットＮＯ生販使用区分 | J47: E | K47: MAC_PS_USE_TYP | M47: E
A48: 20 | D48: sublot_use_typ_nm | E48: #MA.PS_USE_TYP_NM | G48: Sublot No. production/sales use type name | H48: サブロットＮＯ生販使用区分名 | J48: E
A49: 20 | D49: sno1_use_typ | E49: #MA.PS_USE_TYP | G49: SEIBAN No. 1 production/sales use type | H49: 手配ＮＯ１生販使用区分 | J49: E | K49: MAC_PS_USE_TYP | M49: E
A50: 20 | D50: sno1_use_typ_nm | E50: #MA.PS_USE_TYP_NM | G50: SEIBAN No. 1 production/sales type name | H50: 手配ＮＯ１生販使用区分名 | J50: E
A51: 20 | D51: sno2_use_typ | E51: #MA.PS_USE_TYP | G51: SEIBAN No. 2 production/sales use type | H51: 手配ＮＯ２生販使用区分 | J51: E | K51: MAC_PS_USE_TYP | M51: E
A52: 20 | D52: sno2_use_typ_nm | E52: #MA.PS_USE_TYP_NM | G52: SEIBAN No. 2 production/sales use type name | H52: 手配ＮＯ２生販使用区分名 | J52: E
A53: 20 | D53: sno3_use_typ | E53: #MA.PS_USE_TYP | G53: SEIBAN No. 3 production/sales use type | H53: 手配ＮＯ３生販使用区分 | J53: E | K53: MAC_PS_USE_TYP | M53: E
A54: 20 | D54: sno3_use_typ_nm | E54: #MA.PS_USE_TYP_NM | G54: SEIBAN No. 3 production/sales use type name | H54: 手配ＮＯ３生販使用区分名 | J54: E
A55: 20 | D55: sno4_use_typ | E55: #MA.PS_USE_TYP | G55: SEIBAN No. 4 production/sales use type | H55: 手配ＮＯ４生販使用区分 | J55: E | K55: MAC_PS_USE_TYP | M55: E
A56: 20 | D56: sno4_use_typ_nm | E56: #MA.PS_USE_TYP_NM | G56: SEIBAN No. 4 production/sales use type name | H56: 手配ＮＯ４生販使用区分名 | J56: E
A57: 20 | D57: def_calc_ctg_cd | E57: #MA.CALC_CTG_CD | G57: Default calculation category | H57: デフォルト計算カテゴリ | J57: E | M57: E
A58: 20 | D58: def_calc_ctg_nm | E58: #MA.CALC_CTG_NM | G58: Default calculation category name | H58: デフォルト計算カテゴリ名 | J58: E | M58: E
A59: 20 | D59: fix_dpt_cd | E59: #MA.COST_DPT_CD | G59: Constant management dept. cd. | H59: 固定管理部門ＣＤ | J59: E | M59: E
A60: 20 | D60: fix_dpt_nm | E60: #MA.COST_DPT_NM | G60: Constant management dept. name | H60: 固定管理部門名 | J60: E | M60: E
A61: 20 | D61: trd_ratio_flg | E61: #MA.FLG | G61: Use standard unit cost at transfer ratio setting | H61: 振替比率設定時に標準単価を使用する | J61: E | M61: E
A62: 20 | D62: stop_slip_flg | E62: #MA.FLG | G62: Take in canceled slip | H62: 取り消した伝票を取り込む | J62: E | M62: E
A63: 20 | D63: non_prod_flg | E63: #MA.FLG | G63: Do not import production data | H63: 生産データを取り込まない | J63: E | M63: E
A64: 20 | D64: oper_sum_flg | E64: #MA.FLG | G64: Import operation cd. as operation result No. | H64: 工程ＣＤを工程実績ＮＯとして取り込む | J64: E | M64: E
A65: 20 | D65: non_sls_flg | E65: #MA.FLG | G65: Do not import sales data | H65: 販売データを取り込まない | J65: E | M65: E
A66: 20 | D66: asst_flg | E66: #MA.FLG | G66: Import sales asset as production asset | H66: 販売資産を生産資産として取り込む | J66: E | M66: E
A67: 20 | D67: stk_bp_flg | E67: #MA.FLG | G67: Include receiving point inventory | H67: 出荷先の在庫を考慮する | J67: E | M67: E
A68: 20 | D68: non_transit_flg | E68: #MA.FLG | G68: Do not import purchase data of items in transit | H68: 未着品仕入データを取り込まない | J68: E | M68: E
... A93: 20 | D93: ins_func_id | E93: #MA.FUNC_ID | G93: Entry function ID | H93: 登録機能ＩＤ | J93: E | M93: E
A94: 20 | D94: ins_func_nm | E94: #MA.FUNC_NM | G94: Entry function name | H94: 登録機能名 | J94: E
A95: 20 | D95: upd_cntr | E95: #MA.UPD_CNT | G95: Update counter | H95: 更新カウンタ | J95: E | M95: E
A96: 20 | D96: upd_usr_id | E96: #MA.FCM_USR_ID | G96: Update user ID | H96: 更新ユーザＩＤ | J96: E | M96: E
A97: 20 | D97: upd_usr_nm | E97: #MA.FCM_USR_NM | G97: Update user name | H97: 更新ユーザ名 | J97: E | M97: E
A98: 20 | D98: upd_ts | E98: #MA.SYS_TS | G98: Update date and time | H98: 更新日時 | J98: E | M98: E
A99: 20 | D99: upd_func_id | E99: #MA.FUNC_ID | G99: Update function ID | H99: 更新機能ＩＤ | J99: E | M99: E
A100: 20 | D100: upd_func_nm | E100: #MA.FUNC_NM | G100: Update function name | H100: 更新機能名 | J100: E
A101: 20 | D101: upd_srv_req_no | E101: #MA.SRV_REQ_NO | G101: Update request No. | H101: 更新リクエストＮＯ | J101: E | M101: E
D102: 詳細 :

Sheet Upd01
A1: * | B1: * | D1: L | E1: 1
A2: * | D2: オペレーション実装仕様書 Operation Specification Implementation Sheet | E2: ModuleID : | F2: =IF(LogicCommon!C2="","",LogicCommon!C2) -> MA | G2: LogicID : | H2: =IF(LogicCommon!E2="","",LogicCommon!E2) -> MABGL0010 | I2: Ope.ID : | J2: Upd01 | K2: Pj.ID : | L2: =IF(LogicCommon!G2="","",LogicCommon!G2) -> MC | M2: Ope.Body : | N2: "mcframe.serverMAUD.MAUDL6010.MAUDL_RLUpdater"
A3: * | D3: =IF(LogicCommon!A3="","",LogicCommon!A3) | E3: SubModuleID : | F3: =IF(LogicCommon!C3="","",LogicCommon!C3) -> MABG | G3: LogicClass : | H3: =IF(LogicCommon!E3="","",LogicCommon!E3) -> MABGL_CoParmReg | I3: Ope.Method : | J3: @ | K3: SuperClassPj.ID : | L3: =IF(LogicCommon!G3="","",LogicCommon!G3) | M3: ReportID : | O3: Gene.Type : | P3: ALL
A4: * | E4: Version : | F4: 000000 | G4: LogicName : | H4: =IF(LogicCommon!E4="","",LogicCommon!E4) -> 原価会社パラメータマスタ登録 | I4: Ope.Name : | J4: 登録 | K4: SuperLogicID : | L4: =IF(LogicCommon!G4="","",LogicCommon!G4) -> MA.MAUDL5010
A5: * | E5: ACType :
A6: * | D6: 概要 : | E6: 登録処理を行う | L6: ID | N6: ID | P6: ID
A7: # | I7: U | K7: o | L7: CALL_OPE01.chk01 | M7: o | N7: CALL_OPE01.upd01 | O7: o
A8: # | D8: ブロック名 Block Name | E8: 型 Type | G8: super/share | H8: 対象ブロック名 Target Block Name | K8: TargetName | L8: OPE.MA.MABGL0010.CoParm_UpdChk01 | M8: TargetName | N8: OPE.MA.MABGL0010.CoParm_Upd01 | O8: TargetName | S8: ブロック備考 Block Remarks
A9: # | D9: 項目名 Field Name | E9: 型 Type | F9: 桁 Digits | G9: フルネーム Full Name | H9: 日本語名 Japanese Name | I9: 上り項目 Request Message Field | J9: 下り項目 Response Message Field | Q9: 条件および編集方法 Conditions and Editing Methods | S9: 項目備考 Field Remarks
A10: # | K10: 上り項目 Request Message Field | L10: 下り項目 Response Message Field | M10: 上り項目 Request Message Field | N10: 下り項目 Response Message Field | O10: 上り項目 Request Message Field | P10: 下り項目 Response Message Field
A11: 10 | B11: * | D11: Upd01_Dtl1 | E11: L | G11: $share$ | H11: MA.MABGL0010.CoParm_Upd01.CoParm_Upd01_Dtl | K11: CoParm_UpdChk01_Dtl | M11: CoParm_Upd01_Dtl
A12: 10 | D12: co_cd | E12: #MA.CO_CD | G12: Company cd. | H12: 会社ＣＤ | I12: E | K12: E | M12: E
A13: 10 | D13: std_rnd_typ | E13: #MA.RND_TYP | G13: Rounding type (Standard) | H13: 標準端数処理区分 | I13: E | K13: E | M13: E
A14: 10 | D14: std_dec_place | E14: #MA.DEC_PLACE | G14: Standard number of decimal places | H14: 標準小数部有効桁数 | I14: E | K14: E | M14: E
A15: 10 | D15: amt_rnd_typ | E15: #MA.RND_TYP | G15: Rounding type (Amount) | H15: 金額端数処理区分 | I15: E | K15: E | M15: E
A16: 10 | D16: amt_dec_place | E16: #MA.DEC_PLACE | G16: Amount number of decimal places | H16: 金額小数部有効桁数 | I16: E | K16: E | M16: E
A17: 10 | D17: ave_rnd_typ | E17: #MA.RND_TYP | G17: Rounding type (Unit price) | H17: 単価端数処理区分 | I17: E | K17: E | M17: E
A18: 10 | D18: ave_dec_place | E18: #MA.DEC_PLACE | G18: Unit price number of decimal places | H18: 単価小数部有効桁数 | I18: E | K18: E | M18: E
A19: 10 | D19: adj_typ | E19: #MA.ADJ_TYP | G19: Fraction adjustment type | H19: 端数調整区分 | I19: E | K19: E | M19: E
A20: 10 | D20: mrgn_expns_cd | E20: #MA.EXPNS_CD | G20: Adjustment cost element cd. | H20: 調整費目ＣＤ | I20: E | K20: E | M20: E
A21: 10 | D21: purc_expns_cd | E21: #MA.EXPNS_CD | G21: Purchase cost element item cd. | H21: 購買費目ＣＤ | I21: E | K21: E | M21: E
A22: 10 | D22: out_expns_cd | E22: #MA.EXPNS_CD | G22: Subcontract cost element cd. | H22: 外注費目ＣＤ | I22: E | K22: E | M22: E
A23: 10 | D23: inpt_expns_cd | E23: #MA.EXPNS_CD | G23: Input cost element cd. | H23: 投入費目ＣＤ | I23: E | K23: E | M23: E
... A64: 10 | D64: upd_cntr | E64: #MA.UPD_CNT | G64: Update counter | H64: 更新カウンタ | I64: E | K64: E | M64: E
D65: 詳細 :

Sheet Del01
A1: * | B1: * | D1: L | E1: 1
A2: * | D2: オペレーション実装仕様書 Operation Specification Implementation Sheet | E2: ModuleID : | F2: =IF(LogicCommon!C2="","",LogicCommon!C2) -> MA | G2: LogicID : | H2: =IF(LogicCommon!E2="","",LogicCommon!E2) -> MABGL0010 | I2: Ope.ID : | J2: Del01 | K2: Pj.ID : | L2: =IF(LogicCommon!G2="","",LogicCommon!G2) -> MC | M2: Ope.Body : | N2: "mcframe.serverMAUD.MAUDL6010.MAUDL_RLDeleter"
A3: * | D3: =IF(LogicCommon!A3="","",LogicCommon!A3) | E3: SubModuleID : | F3: =IF(LogicCommon!C3="","",LogicCommon!C3) -> MABG | G3: LogicClass : | H3: =IF(LogicCommon!E3="","",LogicCommon!E3) -> MABGL_CoParmReg | I3: Ope.Method : | J3: @ | K3: SuperClassPj.ID : | L3: =IF(LogicCommon!G3="","",LogicCommon!G3) | M3: ReportID : | O3: Gene.Type : | P3: ALL
A4: * | E4: Version : | F4: 000000 | G4: LogicName : | H4: =IF(LogicCommon!E4="","",LogicCommon!E4) -> 原価会社パラメータマスタ登録 | I4: Ope.Name : | J4: 削除 | K4: SuperLogicID : | L4: =IF(LogicCommon!G4="","",LogicCommon!G4) -> MA.MAUDL5010
A5: * | E5: ACType :
A6: * | D6: 概要 : | E6: 削除処理を行う | L6: ID | N6: ID
A7: # | I7: U | K7: o | L7: CALL_OPE01.chk01 | M7: o | N7: CALL_OPE01.del01
A8: # | D8: ブロック名 Block Name | E8: 型 Type | G8: super/share | H8: 対象ブロック名 Target Block Name | K8: TargetName | L8: OPE.MA.MABGL0010.CoParm_DelChk01 | M8: TargetName | N8: OPE.MA.MABGL0010.CoParm_Del01 | Q8: ブロック備考 Block Remarks
A9: # | D9: 項目名 Field Name | E9: 型 Type | F9: 桁 Digits | G9: フルネーム Full Name | H9: 日本語名 Japanese Name | I9: 上り項目 Request Message Field | J9: 下り項目 Response Message Field | O9: 条件および編集方法 Conditions and Editing Methods | Q9: 項目備考 Field Remarks
A10: # | K10: 上り項目 Request Message Field | L10: 下り項目 Response Message Field | M10: 上り項目 Request Message Field | N10: 下り項目 Response Message Field
A11: 10 | B11: * | D11: Del01_Dtl1 | E11: L | G11: $share$ | H11: MA.MABGL0010.CoParm_Del01.CoParm_Del01_Dtl | K11: CoParm_DelChk01_Dtl | M11: CoParm_Del01_Dtl
A12: 10 | D12: co_cd | E12: #MA.CO_CD | G12: Company cd. | H12: 会社ＣＤ | I12: E | K12: E | M12: E
A13: 10 | D13: upd_cntr | E13: #MA.UPD_CNT | G13: Update counter | H13: 更新カウンタ | I13: E | K13: E | M13: E
D14: 詳細 :

Sheet 来歴
A1: 変更来歴
A3: Rev. | H3: 修正番号 | O3: 変更内容 | AQ3: 変更箇所
A4: 1 | O4: 初版
A5: 1.1 | O5: 英語の名称を追記 | AQ5: 全般
