Workbook

Sheet LogicCommon
A2: オペレーション実装仕様書 | B2: ModuleID : | C2: MS | D2: LogicID : | E2: MSBBL6010 | F2: Pj.ID : | G2: MC
B3: SubModuleID : | C3: MSBB | D3: LogicClass : | E3: MSBBL_SlsActService | F3: SuperClassPj.ID :
D4: LogicName : | E4: 売上実績サービス | F4: SuperLogicID : | G4: MS.MSBBL9010
A5: 概要 :
A6: 詳細 :

Sheet SlsAct_Upd01
A1: * | B1: * | D1: L | E1: 1
A2: * | D2: オペレーション実装仕様書 Operation Specification Implementation Sheet | E2: ModuleID : | F2: =IF(LogicCommon!C2="","",LogicCommon!C2) -> MS | G2: LogicID : | H2: =IF(LogicCommon!E2="","",LogicCommon!E2) -> MSBBL6010 | I2: Ope.ID : | J2: SlsAct_Upd01 | K2: Pj.ID : | L2: =IF(LogicCommon!G2="","",LogicCommon!G2) -> MC | M2: Ope.Body : | N2: "mcframe.serverMAUD.MAUDL5010.MAUDL_Operation"
A3: * | D3: =IF(LogicCommon!A3="","",LogicCommon!A3) | E3: SubModuleID : | F3: =IF(LogicCommon!C3="","",LogicCommon!C3) -> MSBB | G3: LogicClass : | H3: =IF(LogicCommon!E3="","",LogicCommon!E3) -> MSBBL_SlsActService | I3: Ope.Method : | J3: =J2 -> SlsAct_Upd01 | K3: SuperClassPj.ID : | L3: =IF(LogicCommon!G3="","",LogicCommon!G3) | O3: Gene.Type : | P3: ALL
A4: * | E4: Version : | F4: 000000 | G4: LogicName : | H4: =IF(LogicCommon!E4="","",LogicCommon!E4) -> 売上実績サービス | I4: Ope.Name : | J4: 登録 | K4: SuperLogicID : | L4: =IF(LogicCommon!G4="","",LogicCommon!G4) -> MS.MSBBL9010 | M4: ImplOpe.ID:
A5: * | E5: ACType :
A6: * | D6: 概要 : | E6: 売上実績を登録する | M6: ID | O6: ID | Q6: ID
A7: # | I7: U | K7: K | L7: o | N7: o | P7: o
A8: # | D8: ブロック名 Block Name | E8: 型 Type | G8: super/share | H8: 対象ブロック名 Target Block Name | L8: TargetName | N8: TargetName | P8: TargetName | T8: ブロック備考 Block Remarks
A9: # | D9: 項目名 Field Name | E9: 型 Type | F9: 桁 Digits | G9: フルネーム Full Name | H9: 日本語名 Japanese Name | I9: 上り項目 Request Message Field | J9: 下り項目 Response Message Field | R9: 条件および編集方法 Conditions and Editing Methods | T9: 項目備考 Field Remarks
A10: # | L10: 上り項目 Request Message Field | M10: 下り項目 Response Message Field | N10: 上り項目 Request Message Field | O10: 下り項目 Response Message Field | P10: 上り項目 Request Message Field | Q10: 下り項目 Response Message Field
A11: 10 | B11: * | D11: SlsAct_Upd01_Hdr | E11: L
A12: 10 | D12: hdr_peg_no | E12: #MA.INT | G12: Header pegging No. | H12: ヘッダ紐付けＮＯ | I12: E
A13: 10 | D13: data_crud_typ | E13: #MA.DATA_CRUD_TYP | G13: Data update type | H13: データ更新区分 | I13: E
A14: 10 | D14: sls_act_no | E14: #MA.SLS_ACT_NO | G14: Sales result No. | H14: 売上実績ＮＯ | I14: E
A15: 10 | D15: sls_act_seq | E15: #MA.SLIP_SEQ | G15: Sales result sequence number | H15: 売上実績連番 | I15: E
A16: 10 | D16: sls_act_rev | E16: #MA.SLIP_REV | G16: Sales result rev. number | H16: 売上実績改訂番号 | I16: E
A17: 10 | D17: trd_cd | E17: #MA.TRD_CD | G17: Transaction cd. | H17: 取引ＣＤ | I17: E
A18: 10 | D18: trd_ptn_typ | E18: #MA.TRD_PTN_TYP | G18: Transaction pattern type | H18: 取引パタン区分 | I18: E
A19: 10 | D19: ac_dt | E19: #MA.DT | G19: Recording date | H19: 計上日 | I19: E
A20: 10 | D20: can_ac_dt | E20: #MA.DT | G20: Cancellation recording date | H20: 取消計上日 | I20: E
A21: 10 | D21: sls_usr_cd | E21: #MA.USR_CD | G21: Sales PIC cd. | H21: 売上担当者ＣＤ | I21: E
A22: 10 | D22: sls_dpt_cd | E22: #MA.DPT_CD | G22: Sales dept. cd. | H22: 売上部門ＣＤ | I22: E
A23: 10 | D23: wg_cd | E23: #MA.WG_CD | G23: WG cd. | H23: ワーキンググループＣＤ | I23: E
... A45: 10 | D45: iv_no | E45: #MA.IV_NO | G45: Invoice No. | H45: インボイスＮＯ | I45: E
A46: 10 | D46: iv_rev | E46: #MA.SLIP_REV | G46: Invoice rev. number | H46: インボイス改訂番号
A47: 10 | D47: ref_iv_no | E47: #MA.IV_NO | G47: Corresponding I/V No. | H47: 対応インボイスＮＯ | I47: E
A48: 10 | D48: rcpt_iv_mng_no | E48: #MA.RCPT_IV_MNG_NO | G48: Purchase invoice management No. | H48: 受領インボイス管理ＮＯ | I48: E
A49: 10 | D49: rcpt_iv_no | E49: #MA.IV_NO | G49: Purchase invoice No. | H49: 受領インボイスＮＯ | I49: E
A50: 10 | D50: num_flg | E50: #MA.FLG | G50: Auto | H50: 自動 | I50: E
A51: 10 | D51: iv_dt | E51: #MA.DT | G51: Invoice date | H51: インボイス日付 | I51: E
A52: 10 | D52: pl_skip_flg | E52: #MA.FLG | G52: Omit packing list | H52: パッキングリスト省略 | I52: E
A53: 10 | D53: iv_immed_prnt_flg | E53: #MA.FLG | G53: Invoice immediate issue | H53: インボイス即時発行 | I53: E
A54: 10 | D54: iv_rmrks | E54: #MS.IV_RMRKS | G54: Invoice remarks | H54: インボイス備考 | I54: E
A55: 10 | D55: case_mrk1 | E55: #MS.CASE_MRK | G55: Case mark 1 | H55: ケースマーク１ | I55: E
A56: 10 | D56: case_mrk2 | E56: #MS.CASE_MRK | G56: Case mark 2 | H56: ケースマーク２ | I56: E
A57: 10 | D57: case_mrk3 | E57: #MS.CASE_MRK | G57: Case mark 3 | H57: ケースマーク３ | I57: E
A58: 10 | D58: case_mrk4 | E58: #MS.CASE_MRK | G58: Case mark 4 | H58: ケースマーク４ | I58: E
... A117: 10 | D117: ship_act_sync_flg | E117: #MA.FLG | G117: Shipping result simultaneously recording | H117: 出荷実績同時計上 | I117: E
A118: 10 | D118: new_hdr_peg_no | E118: #MA.INT | G118: New header pegging No. | H118: 新ヘッダ紐付けＮＯ
A119: 10 | D119: hdr_dlv_cd | E119: #MA.BP_CD | G119: Header delivery destination cd. | H119: ヘッダ納品先ＣＤ
A120: 10 | D120: hdr_dlv_sundry_flg | E120: #MA.FLG | G120: Miscellaneous header delivery destination | H120: ヘッダ納品先諸口
A121: 10 | D121: hdr_dlv_nm | E121: #MA.BP_NM | G121: Header delivery destination name | H121: ヘッダ納品先名
A122: 10 | D122: hdr_dlv_zip_cd | E122: #MA.ZIP_CD | G122: Header delivery destination zip code | H122: ヘッダ納品先郵便番号
A123: 10 | D123: hdr_dlv_addr1 | E123: #MA.ADDR | G123: Heading delivery destination address 1 | H123: ヘッダ納品先住所１
A124: 10 | D124: hdr_dlv_addr2 | E124: #MA.ADDR | G124: Heading delivery destination address 2 | H124: ヘッダ納品先住所２
A125: 10 | D125: hdr_dlv_addr3 | E125: #MA.ADDR | G125: Heading delivery destination address 3 | H125: ヘッダ納品先住所３
A126: 10 | D126: hdr_dlv_addr4 | E126: #MA.ADDR | G126: Heading delivery destination address 4 | H126: ヘッダ納品先住所４
A127: 10 | D127: hdr_dlv_cntct_dpt | E127: #MA.BP_CNTCT_DPT | G127: Header delivery destination dept. | H127: ヘッダ納品先部署
A128: 10 | D128: hdr_dlv_cntct_psn | E128: #MA.BP_CNTCT_PSN | G128: Header delivery destination PIC | H128: ヘッダ納品先担当者
A129: 10 | D129: hdr_dlv_tel | E129: #MA.TEL | G129: Header delivery destination TEL | H129: ヘッダ納品先ＴＥＬ
... A137: 10 | D137: trd_cur_upri_dec_place | E137: #MA.DEC_PLACE | G137: Transaction currency unit price number of decimal places | H137: 取引通貨単価小数部有効桁数
A138: 10 | D138: trd_cur_amt_dec_place | E138: #MA.DEC_PLACE | G138: Transaction currency amount number of decimal places | H138: 取引通貨金額小数部有効桁数 | I138: E
A139: 10 | D139: base_cur_upri_dec_place | E139: #MA.DEC_PLACE | G139: Base currency unit price number of decimal places | H139: 基準通貨単価小数部有効桁数
A140: 10 | D140: base_cur_amt_dec_place | E140: #MA.DEC_PLACE | G140: Base currency amount number of decimal places | H140: 基準通貨金額小数部有効桁数
A141: 10 | D141: ptax_cur_upri_dec_place | E141: #MA.DEC_PLACE | G141: Tax currency unit number of decimal places | H141: 納税通貨単価小数部有効桁数
A142: 10 | D142: ptax_cur_amt_dec_place | E142: #MA.DEC_PLACE | G142: Tax currency amount number of decimal places | H142: 納税通貨金額小数部有効桁数
A143: 10 | D143: xrate_rnd_typ | E143: #MA.RND_TYP | G143: Exchange rounding type | H143: 為替端数処理区分
A144: 10 | D144: amt_rnd_typ | E144: #MA.RND_TYP | G144: Rounding type (Amount) | H144: 金額端数処理区分 | I144: E
A145: 10 | D145: tax_rnd_typ | E145: #MA.RND_TYP | G145: Tax rounding type | H145: 税端数処理区分 | I145: E
A146: 10 | D146: slip_sts_typ | E146: #MA.SLIP_STS_TYP | G146: Slip status type | H146: 伝票状況区分
A147: 10 | D147: ac_ym | E147: #MA.YM | G147: Recording month | H147: 計上年月
A148: 10 | D148: dlv_slip_seq | E148: #MA.SLIP_SEQ | G148: Delivery note sequence number | H148: 納品書連番
A149: 10 | D149: dlv_slip_rev | E149: #MA.SLIP_REV | G149: Delivery note rev. number | H149: 納品書改訂番号
A150: 10 | D150: bef_dlv_slip_no | E150: #MA.DLV_SLIP_NO | G150: Leading delivery note No. | H150: 先行納品書ＮＯ
A151: 10 | D151: bef_iv_no | E151: #MA.IV_NO | G151: Leading invoice No. | H151: 先行インボイスＮＯ
A152: 10 | D152: bef_aprv_flg | E152: #MA.FLG | G152: Approval target before correction | H152: 訂正前承認対象
A153: 10 | D153: ddlv_sls_flg | E153: #MA.FLG | G153: Direct-delivery sales | H153: 直送売上
A154: 10 | D154: bill_cl_typ | E154: #MA.BILL_CL_TYP | G154: Billing closing type | H154: 請求締処理区分
A155: 10 | D155: ship_lg_grp_cd | E155: #MA.LG_GRP_CD | G155: Shipping distribution group cd. | H155: 出荷物流グループＣＤ
A156: 10 | D156: edi_flg | E156: #MA.FLG | G156: EDI | H156: ＥＤＩ | I156: E
A157: 10 | D157: ship_dlv_slip_no | E157: #MA.DLV_SLIP_NO | G157: Delivery note No. at shipping | H157: 出荷時納品書ＮＯ | I157: E
A158: 10 | D158: purc_ddlv_dlv_slip_no | E158: #MA.DLV_SLIP_NO | G158: Direct delivery delivery note No. | H158: 仕入直送納品書ＮＯ | I158: E
A159: 10 | D159: iv_upd_cntr | E159: #MA.UPD_CNT | G159: Invoice header update counter | H159: インボイスヘッダ更新カウンタ | I159: E
A160: 10 | D160: iv_service_exec_flg | E160: #MA.FLG | G160: Execute invoice service | H160: インボイスサービス実行 | I160: E
A161: 10 | D161: amt_calc_flg | E161: #MA.FLG | G161: Amount calculation | H161: 金額計算 | I161: E
A163: 20 | B163: * | D163: SlsAct_Upd01_Dtl | E163: L
A164: 20 | D164: hdr_peg_no | E164: #MA.INT | G164: Header pegging No. | H164: ヘッダ紐付けＮＯ | I164: E
A165: 20 | D165: dtl_peg_no | E165: #MA.INT | G165: Details pegging No. | H165: 明細紐付けＮＯ | I165: E
A166: 20 | D166: data_crud_typ | E166: #MA.DATA_CRUD_TYP | G166: Data update type | H166: データ更新区分 | I166: E
A167: 20 | D167: sls_act_d_no | E167: #MA.SLS_ACT_D_NO | G167: Sales result details No. | H167: 売上実績明細ＮＯ | I167: E
A168: 20 | D168: sls_act_d_seq | E168: #MA.SLIP_SEQ | G168: Sales result details sequence number | H168: 売上実績明細連番 | I168: E
A169: 20 | D169: disp_seq | E169: #MA.DISP_SEQ | G169: Display order | H169: 表示順 | I169: E
A170: 20 | D170: dlv_cd | E170: #MA.BP_CD | G170: Delivery destination cd. | H170: 納品先ＣＤ | I170: E
A171: 20 | D171: dlv_sundry_flg | E171: #MA.FLG | G171: Miscellaneous delivery destination | H171: 納品先諸口 | I171: E
A172: 20 | D172: dlv_nm | E172: #MA.BP_NM | G172: Delivery destination name | H172: 納品先名 | I172: E
A173: 20 | D173: dlv_zip_cd | E173: #MA.ZIP_CD | G173: Zip code (Delivery destination) | H173: 納品先郵便番号 | I173: E
A174: 20 | D174: dlv_addr1 | E174: #MA.ADDR | G174: Address 1 (Delivery destination) | H174: 納品先住所１ | I174: E
A175: 20 | D175: dlv_addr2 | E175: #MA.ADDR | G175: Address 2 (Delivery destination) | H175: 納品先住所２ | I175: E
... A249: 20 | D249: wtax_rate | E249: #MA.TAX_RATE | G249: Withholding tax rate | H249: 源泉税率 | I249: E
A250: 20 | D250: wtax_amt | E250: #MA.MONEY | G250: Withholding tax | H250: 源泉税額
A251: 20 | D251: slo_no | E251: #MA.SLO_NO | G251: Sales order No. | H251: 受注ＮＯ | I251: E
A252: 20 | D252: slo_d_no | E252: #MA.SLO_D_NO | G252: Sales order details No. | H252: 受注明細ＮＯ | I252: E
A253: 20 | D253: sls_ret_schd_no | E253: #MA.SLS_RET_SCHD_NO | G253: Sales return schedule No. | H253: 売上返品予定ＮＯ | I253: E
A254: 20 | D254: sls_ret_schd_d_no | E254: #MA.SLS_RET_SCHD_D_NO | G254: Sales return schedule details No. | H254: 売上返品予定明細ＮＯ | I254: E
A255: 20 | D255: ship_schd_no | E255: #MA.SHIP_SCHD_NO | G255: Shipping schedule No. | H255: 出荷予定ＮＯ | I255: E
A256: 20 | D256: sls_schd_no | E256: #MA.SLS_SCHD_NO | G256: Sales schedule No. | H256: 売上予定ＮＯ | I256: E
A257: 20 | D257: qtn_no | E257: #MA.QTN_NO | G257: Quotation No. | H257: 見積ＮＯ | I257: E
A258: 20 | D258: qtn_rev | E258: #MA.SLIP_REV | G258: Quotation rev. number | H258: 見積改訂番号 | I258: E
A259: 20 | D259: qtn_d_no | E259: #MA.QTN_D_NO | G259: Quotation details No. | H259: 見積明細ＮＯ | I259: E
A260: 20 | D260: purc_ddlv_po_no | E260: #MA.PO_NO | G260: Direct delivery PO No. | H260: 仕入直送発注ＮＯ | I260: E
...

Sheet SlsAct_Upd02
A1: * | B1: * | D1: L | E1: 1
A2: * | D2: オペレーション実装仕様書 Operation Specification Implementation Sheet | E2: ModuleID : | F2: =IF(LogicCommon!C2="","",LogicCommon!C2) -> MS | G2: LogicID : | H2: =IF(LogicCommon!E2="","",LogicCommon!E2) -> MSBBL6010 | I2: Ope.ID : | J2: SlsAct_Upd02 | K2: Pj.ID : | L2: =IF(LogicCommon!G2="","",LogicCommon!G2) -> MC | M2: Ope.Body : | N2: "mcframe.serverMAUD.MAUDL5010.MAUDL_Operation"
A3: * | D3: =IF(LogicCommon!A3="","",LogicCommon!A3) | E3: SubModuleID : | F3: =IF(LogicCommon!C3="","",LogicCommon!C3) -> MSBB | G3: LogicClass : | H3: =IF(LogicCommon!E3="","",LogicCommon!E3) -> MSBBL_SlsActService | I3: Ope.Method : | J3: =J2 -> SlsAct_Upd02 | K3: SuperClassPj.ID : | L3: =IF(LogicCommon!G3="","",LogicCommon!G3) | O3: Gene.Type : | P3: ALL
A4: * | E4: Version : | F4: 000000 | G4: LogicName : | H4: =IF(LogicCommon!E4="","",LogicCommon!E4) -> 売上実績サービス | I4: Ope.Name : | J4: 登録（出荷実績呼出用） | K4: SuperLogicID : | L4: =IF(LogicCommon!G4="","",LogicCommon!G4) -> MS.MSBBL9010 | M4: ImplOpe.ID:
A5: * | E5: ACType :
A6: * | D6: 概要 : | E6: 売上実績を登録する（出荷実績サービスより呼び出す） | M6: ID | O6: ID | Q6: ID
A7: # | I7: U | K7: K | L7: o | N7: o | P7: o
A8: # | D8: ブロック名 Block Name | E8: 型 Type | G8: super/share | H8: 対象ブロック名 Target Block Name | L8: TargetName | N8: TargetName | P8: TargetName | T8: ブロック備考 Block Remarks
A9: # | D9: 項目名 Field Name | E9: 型 Type | F9: 桁 Digits | G9: フルネーム Full Name | H9: 日本語名 Japanese Name | I9: 上り項目 Request Message Field | J9: 下り項目 Response Message Field | R9: 条件および編集方法 Conditions and Editing Methods | T9: 項目備考 Field Remarks
A10: # | L10: 上り項目 Request Message Field | M10: 下り項目 Response Message Field | N10: 上り項目 Request Message Field | O10: 下り項目 Response Message Field | P10: 上り項目 Request Message Field | Q10: 下り項目 Response Message Field
A11: 10 | B11: * | D11: SlsAct_Upd02_Cnd | E11: L
A12: 10 | D12: dlv_slip_no | E12: #MA.DLV_SLIP_NO | G12: Delivery note No. | H12: 納品書ＮＯ | I12: E
A13: 10 | D13: iv_no | E13: #MA.IV_NO | G13: Invoice No. | H13: インボイスＮＯ | I13: E
A14: 10 | D14: data_crud_typ | E14: #MA.DATA_CRUD_TYP | G14: Data update type | H14: データ更新区分 | I14: E
A15: 10 | D15: dlv_slip_seq | E15: #MA.SLIP_SEQ | G15: Delivery note sequence number | H15: 納品書連番
A16: 10 | D16: via_dlv_typ | E16: #MA.VIA_DLV_TYP | G16: Receiving point stopover type | H16: 配送先経由区分
A17: 10 | D17: split_flg | E17: #MA.FLG | G17: Split exists | H17: 分割有
A18: 10 | D18: can_ac_dt | E18: #MA.DT | G18: Cancellation recording date | H18: 取消計上日 | I18: E
A19: 10 | D19: ship_dt | E19: #MA.DT | G19: Shipping date | H19: 出荷日 | I19: E
A20: 10 | D20: ac_dt | E20: #MA.DT | G20: Recording date | H20: 計上日 | I20: E
A21: 10 | D21: use_iv_ship_act_map | E21: #MA.FLG | G21: Use invoice shipping result map | H21: インボイス出荷実績マップ使用 | I21: E
A23: 20 | B23: * | D23: SlsAct_Upd02_IvL | E23: L
A24: 20 | D24: trd_cd | E24: #MA.TRD_CD | G24: Transaction cd. | H24: 取引ＣＤ
A25: 20 | D25: trd_ptn_typ | E25: #MA.TRD_PTN_TYP | G25: Transaction pattern type | H25: 取引パタン区分
A26: 20 | D26: ac_dt | E26: #MA.DT | G26: Recording date | H26: 計上日
A27: 20 | D27: sls_dpt_cd | E27: #MA.DPT_CD | G27: Sales dept. cd. | H27: 売上部門ＣＤ
A28: 20 | D28: wg_cd | E28: #MA.WG_CD | G28: WG cd. | H28: ワーキンググループＣＤ
A29: 20 | D29: sls_usr_cd | E29: #MA.USR_CD | G29: Sales PIC cd. | H29: 売上担当者ＣＤ
A30: 20 | D30: eta_dt | E30: #MA.DT | G30: Estimated date of unloading | H30: 船卸予定日
A31: 20 | D31: cst_cd | E31: #MA.BP_CD | G31: Customer cd. | H31: 得意先ＣＤ
A32: 20 | D32: iv_no | E32: #MA.IV_NO | G32: Invoice No. | H32: インボイスＮＯ
A33: 20 | D33: rcpt_iv_mng_no | E33: #MA.RCPT_IV_MNG_NO | G33: Purchase invoice management No. | H33: 受領インボイス管理ＮＯ
A34: 20 | D34: rcpt_iv_no | E34: #MA.IV_NO | G34: Purchase invoice No. | H34: 受領インボイスＮＯ
A35: 20 | D35: tterm_cd1 | E35: #MA.TTERM_CD | G35: Transaction terms cd. 1 | H35: 取引条件ＣＤ１
... A137: 20 | D137: sls_dt | E137: #MA.DT | G137: Sales date | H137: 売上日
A139: 30 | B139: * | D139: SlsAct_Upd02_IoL | E139: L
A140: 30 | D140: ship_act_d_no | E140: #MA.SHIP_ACT_D_NO | G140: Shipping result details No. | H140: 出荷実績明細ＮＯ
A141: 30 | D141: iv_ship_act_d_no | E141: #MA.IV_SHIP_ACT_D_NO | G141: Shipping invoice result details No. | H141: インボイス出荷実績明細ＮＯ
A142: 30 | D142: sno1 | E142: #MA.SNO1 | G142: SEIBAN No. 1 | H142: 手配ＮＯ１
A143: 30 | D143: sno2 | E143: #MA.SNO2 | G143: SEIBAN No. 2 | H143: 手配ＮＯ２
A144: 30 | D144: sno3 | E144: #MA.SNO3 | G144: SEIBAN No. 3 | H144: 手配ＮＯ３
A145: 30 | D145: sno4 | E145: #MA.SNO4 | G145: SEIBAN No. 4 | H145: 手配ＮＯ４
A146: 30 | D146: gd_cd | E146: #MA.STK_GD_CD | G146: Grading cd. | H146: 格付ＣＤ
A147: 30 | D147: loc_cd | E147: #MA.LOC_CD | G147: Location cd. | H147: 場所ＣＤ
A148: 30 | D148: str_ln_cd | E148: #MA.STR_LN_CD | G148: Rack/Line cd. | H148: 棚・ラインＣＤ
A149: 30 | D149: lot_no | E149: #MA.LOT_NO | G149: Lot No. | H149: ロットＮＯ
A150: 30 | D150: sublot_no | E150: #MA.SUBLOT_NO | G150: Sublot No. | H150: サブロットＮＯ
A151: 30 | D151: trd_unit_cd | E151: #MA.UNIT_CD | G151: Transaction unit cd. | H151: 取引単位ＣＤ
... A159: 30 | D159: sls_act_io_seq | E159: #MA.SLIP_SEQ | G159: Sales result GR/GI sequence number | H159: 売上実績受払連番

Sheet SlsAct_Upd03
A1: * | B1: * | D1: L | E1: 1
A2: * | D2: オペレーション実装仕様書 Operation Specification Implementation Sheet | E2: ModuleID : | F2: =IF(LogicCommon!C2="","",LogicCommon!C2) -> MS | G2: LogicID : | H2: =IF(LogicCommon!E2="","",LogicCommon!E2) -> MSBBL6010 | I2: Ope.ID : | J2: SlsAct_Upd03 | K2: Pj.ID : | L2: =IF(LogicCommon!G2="","",LogicCommon!G2) -> MC | M2: Ope.Body : | N2: "mcframe.serverMAUD.MAUDL5010.MAUDL_Operation"
A3: * | D3: =IF(LogicCommon!A3="","",LogicCommon!A3) | E3: SubModuleID : | F3: =IF(LogicCommon!C3="","",LogicCommon!C3) -> MSBB | G3: LogicClass : | H3: =IF(LogicCommon!E3="","",LogicCommon!E3) -> MSBBL_SlsActService | I3: Ope.Method : | J3: =J2 -> SlsAct_Upd03 | K3: SuperClassPj.ID : | L3: =IF(LogicCommon!G3="","",LogicCommon!G3) | O3: Gene.Type : | P3: ALL
A4: * | E4: Version : | F4: 000000 | G4: LogicName : | H4: =IF(LogicCommon!E4="","",LogicCommon!E4) -> 売上実績サービス | I4: Ope.Name : | J4: 登録（承認用） | K4: SuperLogicID : | L4: =IF(LogicCommon!G4="","",LogicCommon!G4) -> MS.MSBBL9010 | M4: ImplOpe.ID:
A5: * | E5: ACType :
A6: * | D6: 概要 : | E6: 売上値引で承認/承認取消された場合に、売上実績を承認/承認取消として更新する | M6: ID | O6: ID | Q6: ID
A7: # | I7: U | K7: K | L7: o | N7: o | P7: o
A8: # | D8: ブロック名 Block Name | E8: 型 Type | G8: super/share | H8: 対象ブロック名 Target Block Name | L8: TargetName | N8: TargetName | P8: TargetName | T8: ブロック備考 Block Remarks
A9: # | D9: 項目名 Field Name | E9: 型 Type | F9: 桁 Digits | G9: フルネーム Full Name | H9: 日本語名 Japanese Name | I9: 上り項目 Request Message Field | J9: 下り項目 Response Message Field | R9: 条件および編集方法 Conditions and Editing Methods | T9: 項目備考 Field Remarks
A10: # | L10: 上り項目 Request Message Field | M10: 下り項目 Response Message Field | N10: 上り項目 Request Message Field | O10: 下り項目 Response Message Field | P10: 上り項目 Request Message Field | Q10: 下り項目 Response Message Field
A11: 10 | B11: * | D11: SlsAct_Upd03_Aprv | E11: L
A12: 10 | D12: sls_act_no | E12: #MA.SLS_ACT_NO | G12: Sales result No. | H12: 売上実績ＮＯ | I12: E
A13: 10 | D13: aprv_sts_typ | E13: #MA.APRV_STS_TYP | G13: Approval status type | H13: 承認状況区分 | I13: E

Sheet SlsAct_Upd04
A1: * | B1: * | D1: L | E1: 1
A2: * | D2: オペレーション実装仕様書 Operation Specification Implementation Sheet | E2: ModuleID : | F2: =IF(LogicCommon!C2="","",LogicCommon!C2) -> MS | G2: LogicID : | H2: =IF(LogicCommon!E2="","",LogicCommon!E2) -> MSBBL6010 | I2: Ope.ID : | J2: SlsAct_Upd04 | K2: Pj.ID : | L2: =IF(LogicCommon!G2="","",LogicCommon!G2) -> MC | M2: Ope.Body : | N2: "mcframe.serverMAUD.MAUDL5010.MAUDL_Operation"
A3: * | D3: =IF(LogicCommon!A3="","",LogicCommon!A3) | E3: SubModuleID : | F3: =IF(LogicCommon!C3="","",LogicCommon!C3) -> MSBB | G3: LogicClass : | H3: =IF(LogicCommon!E3="","",LogicCommon!E3) -> MSBBL_SlsActService | I3: Ope.Method : | J3: =J2 -> SlsAct_Upd04 | K3: SuperClassPj.ID : | L3: =IF(LogicCommon!G3="","",LogicCommon!G3) | O3: Gene.Type : | P3: ALL
A4: * | E4: Version : | F4: 000000 | G4: LogicName : | H4: =IF(LogicCommon!E4="","",LogicCommon!E4) -> 売上実績サービス | I4: Ope.Name : | J4: 請求繰越回数更新 | K4: SuperLogicID : | L4: =IF(LogicCommon!G4="","",LogicCommon!G4) -> MS.MSBBL9010 | M4: ImplOpe.ID:
A5: * | E5: ACType :
A6: * | D6: 概要 : | E6: 請求繰越回数を更新する | M6: ID | O6: ID | Q6: ID
A7: # | I7: U | K7: K | L7: o | N7: o | P7: o
A8: # | D8: ブロック名 Block Name | E8: 型 Type | G8: super/share | H8: 対象ブロック名 Target Block Name | L8: TargetName | N8: TargetName | P8: TargetName | T8: ブロック備考 Block Remarks
A9: # | D9: 項目名 Field Name | E9: 型 Type | F9: 桁 Digits | G9: フルネーム Full Name | H9: 日本語名 Japanese Name | I9: 上り項目 Request Message Field | J9: 下り項目 Response Message Field | R9: 条件および編集方法 Conditions and Editing Methods | T9: 項目備考 Field Remarks
A10: # | L10: 上り項目 Request Message Field | M10: 下り項目 Response Message Field | N10: 上り項目 Request Message Field | O10: 下り項目 Response Message Field | P10: 上り項目 Request Message Field | Q10: 下り項目 Response Message Field
A11: 10 | B11: * | D11: SlsAct_Upd04_Dtl | E11: L
A12: 10 | D12: sls_act_d_no | E12: #MA.SLS_ACT_D_NO | G12: Sales result details No. | H12: 売上実績明細ＮＯ | I12: E
A13: 10 | D13: sls_act_d_seq | E13: #MA.SLIP_SEQ | G13: Sales result details sequence number | H13: 売上実績明細連番 | I13: E
A14: 10 | D14: bill_crryovr_times | E14: #MA.CRRYOVR_TIMES | G14: Billing carry-over count | H14: 請求繰越回数 | I14: E

Sheet 来歴
A1: 変更来歴
A3: Rev. | H3: 修正番号 | O3: 変更内容 | AQ3: 変更箇所
A4: 1 | O4: 初版
A5: 1.1 | H5: MS7031#166 | O5: SlsAct_Upd01_Rslt_Dtlブロックに以下の項目を追加 ・sls_act_no ・sls_act_seq ・sls_act_rev ・dlv_slip_no ・iv_no | AQ5: SlsAct_Upd01シート
A6: 1.2 | O6: 英語の名称を追記 | AQ6: 全般
