Workbook

Sheet LogicCommon
A2: オペレーション実装仕様書 | B2: ModuleID : | C2: MS | D2: LogicID : | E2: MSBBL6220 | F2: Pj.ID : | G2: MC
B3: SubModuleID : | C3: MSBB | D3: LogicClass : | E3: MSBBL_SlsSchdService | F3: SuperClassPj.ID :
D4: LogicName : | E4: 売上予定サービス | F4: SuperLogicID : | G4: MS.MSUDL5010
A5: 概要 :
A6: 詳細 :

Sheet Sls_Schd_Upd01
A1: * | B1: * | D1: L | E1: 1
A2: * | D2: オペレーション実装仕様書 Operation Specification Implementation Sheet | E2: ModuleID : | F2: =IF(LogicCommon!C2="","",LogicCommon!C2) -> MS | G2: LogicID : | H2: =IF(LogicCommon!E2="","",LogicCommon!E2) -> MSBBL6220 | I2: Ope.ID : | J2: Sls_Schd_Upd01 | K2: Pj.ID : | L2: =IF(LogicCommon!G2="","",LogicCommon!G2) -> MC | M2: Ope.Body : | N2: "mcframe.serverMAUD.MAUDL5010.MAUDL_Operation"
A3: * | D3: =IF(LogicCommon!A3="","",LogicCommon!A3) | E3: SubModuleID : | F3: =IF(LogicCommon!C3="","",LogicCommon!C3) -> MSBB | G3: LogicClass : | H3: =IF(LogicCommon!E3="","",LogicCommon!E3) -> MSBBL_SlsSchdService | I3: Ope.Method : | J3: =J2 -> Sls_Schd_Upd01 | K3: SuperClassPj.ID : | L3: =IF(LogicCommon!G3="","",LogicCommon!G3) | O3: Gene.Type : | P3: ALL
A4: * | E4: Version : | F4: 000000 | G4: LogicName : | H4: =IF(LogicCommon!E4="","",LogicCommon!E4) -> 売上予定サービス | I4: Ope.Name : | J4: 出荷予定変更、海外の受注登録、受注無しの出荷実績登録により更新、受注削除、出荷実績削除等による削除 | K4: SuperLogicID : | L4: =IF(LogicCommon!G4="","",LogicCommon!G4) -> MS.MSUDL5010 | M4: ImplOpe.ID:
A5: * | E5: ACType :
A6: * | D6: 概要 : | M6: ID | O6: ID | Q6: ID
A7: # | I7: U | K7: K | L7: o | N7: o | P7: o
A8: # | D8: ブロック名 Block Name | E8: 型 Type | G8: super/share | H8: 対象ブロック名 Target Block Name | L8: TargetName | N8: TargetName | P8: TargetName | T8: ブロック備考 Block Remarks
A9: # | D9: 項目名 Field Name | E9: 型 Type | F9: 桁 Digits | G9: フルネーム Full Name | H9: 日本語名 Japanese Name | I9: 上り項目 Request Message Field | J9: 下り項目 Response Message Field | R9: 条件および編集方法 Conditions and Editing Methods | T9: 項目備考 Field Remarks
A10: # | L10: 上り項目 Request Message Field | M10: 下り項目 Response Message Field | N10: 上り項目 Request Message Field | O10: 下り項目 Response Message Field | P10: 上り項目 Request Message Field | Q10: 下り項目 Response Message Field
A11: 10 | B11: * | D11: Sls_Schd_Upd01_Dtl | E11: L
A12: 10 | D12: sls_schd_src_typ | E12: #MS.SLS_SCHD_SRC_TYP | G12: Sales schedule creating source type | H12: 売上予定作成元区分 | I12: E
A13: 10 | D13: data_crud_typ | E13: #MA.DATA_CRUD_TYP | G13: Data update type | H13: データ更新区分 | I13: E
A14: 10 | D14: ship_schd_no | E14: #MA.SHIP_SCHD_NO | G14: Shipping schedule No. | H14: 出荷予定ＮＯ | I14: E
A15: 10 | D15: ship_inst_d_no | E15: #MA.SHIP_INST_D_NO | G15: Shipping order details No. | H15: 出荷指図明細ＮＯ | I15: E
A16: 10 | D16: dlv_inst_rcpt_no | E16: #MA.DLV_INST_RCPT_NO | G16: Delivery order received No. | H16: 納入指示受領ＮＯ | I16: E
A17: 10 | D17: slo_d_no | E17: #MA.SLO_D_NO | G17: Sales order details No. | H17: 受注明細NO | I17: E
A18: 10 | D18: dlv_slip_d_no | E18: #MA.DLV_SLIP_D_NO | G18: Delivery note details No. | H18: 納品書明細ＮＯ | I18: E
A19: 10 | D19: ship_schd_dt | E19: #MA.DT | G19: Scheduled shipping date | H19: 出荷予定日 | I19: E
A20: 10 | D20: dlv_schd_dt | E20: #MA.DT | G20: Scheduled delivery date | H20: 納品予定日 | I20: E
A21: 10 | D21: sls_schd_dt | E21: #MA.DT | G21: Scheduled sales date | H21: 売上予定日 | I21: E
A22: 10 | D22: trd_unit_qty | E22: #MA.QTY | G22: Transaction unit qty. | H22: 取引単位数量 | I22: E
A23: 10 | D23: trd_unit_cd | E23: #MA.UNIT_CD | G23: Transaction unit cd. | H23: 取引単位ＣＤ | I23: E
... A27: 10 | D27: cred_no_up_flg | E27: #MA.FLG | G27: No credit update | H27: 与信更新無 | I27: E

Sheet Sls_Schd_Upd02
A1: * | B1: * | D1: L | E1: 1
A2: * | D2: オペレーション実装仕様書 Operation Specification Implementation Sheet | E2: ModuleID : | F2: =IF(LogicCommon!C2="","",LogicCommon!C2) -> MS | G2: LogicID : | H2: =IF(LogicCommon!E2="","",LogicCommon!E2) -> MSBBL6220 | I2: Ope.ID : | J2: Sls_Schd_Upd02 | K2: Pj.ID : | L2: =IF(LogicCommon!G2="","",LogicCommon!G2) -> MC | M2: Ope.Body : | N2: "mcframe.serverMAUD.MAUDL5010.MAUDL_Operation"
A3: * | D3: =IF(LogicCommon!A3="","",LogicCommon!A3) | E3: SubModuleID : | F3: =IF(LogicCommon!C3="","",LogicCommon!C3) -> MSBB | G3: LogicClass : | H3: =IF(LogicCommon!E3="","",LogicCommon!E3) -> MSBBL_SlsSchdService | I3: Ope.Method : | J3: =J2 -> Sls_Schd_Upd02 | K3: SuperClassPj.ID : | L3: =IF(LogicCommon!G3="","",LogicCommon!G3) | O3: Gene.Type : | P3: ALL
A4: * | E4: Version : | F4: 000000 | G4: LogicName : | H4: =IF(LogicCommon!E4="","",LogicCommon!E4) -> 売上予定サービス | I4: Ope.Name : | J4: 受注有の出荷実績登録による更新 | K4: SuperLogicID : | L4: =IF(LogicCommon!G4="","",LogicCommon!G4) -> MS.MSUDL5010 | M4: ImplOpe.ID:
A5: * | E5: ACType :
A6: * | D6: 概要 : | M6: ID | O6: ID | Q6: ID
A7: # | I7: U | K7: K | L7: o | N7: o | P7: o
A8: # | D8: ブロック名 Block Name | E8: 型 Type | G8: super/share | H8: 対象ブロック名 Target Block Name | L8: TargetName | N8: TargetName | P8: TargetName | T8: ブロック備考 Block Remarks
A9: # | D9: 項目名 Field Name | E9: 型 Type | F9: 桁 Digits | G9: フルネーム Full Name | H9: 日本語名 Japanese Name | I9: 上り項目 Request Message Field | J9: 下り項目 Response Message Field | R9: 条件および編集方法 Conditions and Editing Methods | T9: 項目備考 Field Remarks
A10: # | L10: 上り項目 Request Message Field | M10: 下り項目 Response Message Field | N10: 上り項目 Request Message Field | O10: 下り項目 Response Message Field | P10: 上り項目 Request Message Field | Q10: 下り項目 Response Message Field
A11: 10 | B11: * | D11: Sls_Schd_Upd02_Dtl | E11: L
A12: 10 | D12: data_crud_typ | E12: #MA.DATA_CRUD_TYP | G12: Data update type | H12: データ更新区分 | I12: E
A13: 10 | D13: ship_schd_no | E13: #MA.SHIP_SCHD_NO | G13: Shipping schedule No. | H13: 出荷予定ＮＯ | I13: E
A14: 10 | D14: dlv_slip_d_no | E14: #MA.DLV_SLIP_D_NO | G14: Delivery note details No. | H14: 納品書明細ＮＯ | I14: E
A15: 10 | D15: iv_d_no | E15: #MA.IV_D_NO | G15: Invoice details No. | H15: インボイス明細ＮＯ | I15: E
A16: 10 | D16: slo_d_no | E16: #MA.SLO_D_NO | G16: Sales order details No. | H16: 受注明細NO | I16: E
A17: 10 | D17: sls_schd_dt | E17: #MA.DT | G17: Scheduled sales date | H17: 売上予定日 | I17: E
A18: 10 | D18: trd_unit_qty | E18: #MA.QTY | G18: Transaction unit qty. | H18: 取引単位数量 | I18: E
A19: 10 | D19: trd_unit_cd | E19: #MA.UNIT_CD | G19: Transaction unit cd. | H19: 取引単位ＣＤ | I19: E
A20: 10 | D20: base_unit_qty | E20: #MA.QTY | G20: Base unit qty. | H20: 基準単位数量 | I20: E
A21: 10 | D21: base_unit_cd | E21: #MA.UNIT_CD | G21: Base unit cd. | H21: 基準単位ＣＤ | I21: E
A22: 10 | D22: abort_flg | E22: #MA.FLG | G22: Cancel remaining | H22: 打切 | I22: E
A23: 10 | D23: cred_no_up_flg | E23: #MA.FLG | G23: No credit update | H23: 与信更新無 | I23: E
A25: 20 | B25: * | D25: Sls_Schd_Upd02_ShipAct | E25: L
A26: 20 | D26: data_crud_typ | E26: #MA.DATA_CRUD_TYP | G26: Data update type | H26: データ更新区分 | I26: E
A27: 20 | D27: ship_schd_no | E27: #MA.SHIP_SCHD_NO | G27: Shipping schedule No. | H27: 出荷予定ＮＯ | I27: E
A28: 20 | D28: ship_act_d_no | E28: #MA.SHIP_ACT_D_NO | G28: Shipping result details No. | H28: 出荷実績明細ＮＯ | I28: E

Sheet Sls_Schd_Upd03
A1: * | B1: * | D1: L | E1: 1
A2: * | D2: オペレーション実装仕様書 Operation Specification Implementation Sheet | E2: ModuleID : | F2: =IF(LogicCommon!C2="","",LogicCommon!C2) -> MS | G2: LogicID : | H2: =IF(LogicCommon!E2="","",LogicCommon!E2) -> MSBBL6220 | I2: Ope.ID : | J2: Sls_Schd_Upd03 | K2: Pj.ID : | L2: =IF(LogicCommon!G2="","",LogicCommon!G2) -> MC | M2: Ope.Body : | N2: "mcframe.serverMAUD.MAUDL5010.MAUDL_Operation"
A3: * | D3: =IF(LogicCommon!A3="","",LogicCommon!A3) | E3: SubModuleID : | F3: =IF(LogicCommon!C3="","",LogicCommon!C3) -> MSBB | G3: LogicClass : | H3: =IF(LogicCommon!E3="","",LogicCommon!E3) -> MSBBL_SlsSchdService | I3: Ope.Method : | J3: =J2 -> Sls_Schd_Upd03 | K3: SuperClassPj.ID : | L3: =IF(LogicCommon!G3="","",LogicCommon!G3) | O3: Gene.Type : | P3: ALL
A4: * | E4: Version : | F4: 000000 | G4: LogicName : | H4: =IF(LogicCommon!E4="","",LogicCommon!E4) -> 売上予定サービス | I4: Ope.Name : | J4: 売上計上により更新 | K4: SuperLogicID : | L4: =IF(LogicCommon!G4="","",LogicCommon!G4) -> MS.MSUDL5010 | M4: ImplOpe.ID:
A5: * | E5: ACType :
A6: * | D6: 概要 : | M6: ID | O6: ID | Q6: ID
A7: # | I7: U | K7: K | L7: o | N7: o | P7: o
A8: # | D8: ブロック名 Block Name | E8: 型 Type | G8: super/share | H8: 対象ブロック名 Target Block Name | L8: TargetName | N8: TargetName | P8: TargetName | T8: ブロック備考 Block Remarks
A9: # | D9: 項目名 Field Name | E9: 型 Type | F9: 桁 Digits | G9: フルネーム Full Name | H9: 日本語名 Japanese Name | I9: 上り項目 Request Message Field | J9: 下り項目 Response Message Field | R9: 条件および編集方法 Conditions and Editing Methods | T9: 項目備考 Field Remarks
A10: # | L10: 上り項目 Request Message Field | M10: 下り項目 Response Message Field | N10: 上り項目 Request Message Field | O10: 下り項目 Response Message Field | P10: 上り項目 Request Message Field | Q10: 下り項目 Response Message Field
A11: 10 | B11: * | D11: Sls_Schd_Upd03_Dtl | E11: L
A12: 10 | D12: data_crud_typ | E12: #MA.DATA_CRUD_TYP | G12: Data update type | H12: データ更新区分 | I12: E
A13: 10 | D13: sls_schd_no | E13: #MA.SLS_SCHD_NO | G13: Sales schedule No. | H13: 売上予定ＮＯ | I13: E
A14: 10 | D14: abort_flg | E14: #MA.FLG | G14: Cancel remaining | H14: 打切 | I14: E
A15: 10 | D15: base_unit_sls_qty | E15: #MA.QTY | G15: Base unit sales qty. | H15: 基準単位売上数量 | I15: E
A16: 10 | D16: sls_schd_dt | E16: #MA.DT | G16: Scheduled sales date | H16: 売上予定日 | I16: E
A17: 10 | D17: manual_upd_flg | E17: #MA.FLG | G17: Manual correction | H17: マニュアル訂正 | I17: E

Sheet Sls_Schd_Upd04
A1: * | B1: * | D1: L | E1: 1
A2: * | D2: オペレーション実装仕様書 Operation Specification Implementation Sheet | E2: ModuleID : | F2: =IF(LogicCommon!C2="","",LogicCommon!C2) -> MS | G2: LogicID : | H2: =IF(LogicCommon!E2="","",LogicCommon!E2) -> MSBBL6220 | I2: Ope.ID : | J2: Sls_Schd_Upd04 | K2: Pj.ID : | L2: =IF(LogicCommon!G2="","",LogicCommon!G2) -> MC | M2: Ope.Body : | N2: "mcframe.serverMAUD.MAUDL5010.MAUDL_Operation"
A3: * | D3: =IF(LogicCommon!A3="","",LogicCommon!A3) | E3: SubModuleID : | F3: =IF(LogicCommon!C3="","",LogicCommon!C3) -> MSBB | G3: LogicClass : | H3: =IF(LogicCommon!E3="","",LogicCommon!E3) -> MSBBL_SlsSchdService | I3: Ope.Method : | J3: =J2 -> Sls_Schd_Upd04 | K3: SuperClassPj.ID : | L3: =IF(LogicCommon!G3="","",LogicCommon!G3) | O3: Gene.Type : | P3: ALL
A4: * | E4: Version : | F4: 000000 | G4: LogicName : | H4: =IF(LogicCommon!E4="","",LogicCommon!E4) -> 売上予定サービス | I4: Ope.Name : | J4: 仕入直送の受注登録、発注・仕入予定変更による更新 | K4: SuperLogicID : | L4: =IF(LogicCommon!G4="","",LogicCommon!G4) -> MS.MSUDL5010 | M4: ImplOpe.ID:
A5: * | E5: ACType :
A6: * | D6: 概要 : | M6: ID | O6: ID | Q6: ID
A7: # | I7: U | K7: K | L7: o | N7: o | P7: o
A8: # | D8: ブロック名 Block Name | E8: 型 Type | G8: super/share | H8: 対象ブロック名 Target Block Name | L8: TargetName | N8: TargetName | P8: TargetName | T8: ブロック備考 Block Remarks
A9: # | D9: 項目名 Field Name | E9: 型 Type | F9: 桁 Digits | G9: フルネーム Full Name | H9: 日本語名 Japanese Name | I9: 上り項目 Request Message Field | J9: 下り項目 Response Message Field | R9: 条件および編集方法 Conditions and Editing Methods | T9: 項目備考 Field Remarks
A10: # | L10: 上り項目 Request Message Field | M10: 下り項目 Response Message Field | N10: 上り項目 Request Message Field | O10: 下り項目 Response Message Field | P10: 上り項目 Request Message Field | Q10: 下り項目 Response Message Field
A11: 10 | B11: * | D11: Sls_Schd_Upd04_Dtl | E11: L
A12: 10 | D12: sls_schd_src_typ | E12: #MS.SLS_SCHD_SRC_TYP | G12: Sales schedule creating source type | H12: 売上予定作成元区分 | I12: E
A13: 10 | D13: data_crud_typ | E13: #MA.DATA_CRUD_TYP | G13: Data update type | H13: データ更新区分 | I13: E
A14: 10 | D14: iv_d_no | E14: #MA.IV_D_NO | G14: Invoice details No. | H14: インボイス明細ＮＯ | I14: E
A15: 10 | D15: purc_schd_no | E15: #MA.PURC_SCHD_NO | G15: Purchase schedule No. | H15: 仕入予定ＮＯ | I15: E
A16: 10 | D16: purc_act_d_no | E16: #MA.PURC_ACT_NO | G16: Purchase result details No. | H16: 仕入実績明細ＮＯ | I16: E
A17: 10 | D17: accpt_dfct_flg | E17: #MA.FLG | G17: Defective acceptance | H17: 検収不良 | I17: E
A18: 10 | D18: po_schd_no | E18: #MA.PO_SCHD_NO | G18: PO schedule No. | H18: 発注予定ＮＯ | I18: E
A19: 10 | D19: slo_d_no | E19: #MA.SLO_D_NO | G19: Sales order details No. | H19: 受注明細NO | I19: E
A20: 10 | D20: wg_rqst_no | E20: #MA.WG_RQST_NO | G20: No. of inventory request from other WG | H20: WG間依頼ＮＯ | I20: E
A21: 10 | D21: sls_schd_dt | E21: #MA.DT | G21: Scheduled sales date | H21: 売上予定日 | I21: E
A22: 10 | D22: trd_unit_qty | E22: #MA.QTY | G22: Transaction unit qty. | H22: 取引単位数量 | I22: E
A23: 10 | D23: trd_unit_cd | E23: #MA.UNIT_CD | G23: Transaction unit cd. | H23: 取引単位ＣＤ | I23: E
... A31: 10 | D31: sls_purc_sync_flg | E31: #MA.FLG | G31: Sales and purchase simultaneously recorded | H31: 売上仕入同時計上 | I31: E
A32: 10 | D32: ship_schd_del_flg | E32: #MA.FLG | G32: Delete shipping schedule | H32: 出荷予定削除
A33: 10 | D33: ship_schd_no | E33: #MA.SHIP_SCHD_NO | G33: Shipping schedule No. | H33: 出荷予定NO
A34: 10 | D34: sls_schd_no | E34: #MA.SLS_SCHD_NO | G34: Sales schedule No. | H34: 売上予定ＮＯ
A35: 10 | D35: dlv_cd | E35: #MA.BP_CD | G35: Delivery destination cd. | H35: 納品先ＣＤ | I35: E
A36: 10 | D36: dlv_sundry_flg | E36: #MA.FLG | G36: Miscellaneous delivery destination | H36: 納品先諸口 | I36: E
A37: 10 | D37: dlv_nm | E37: #MA.BP_NM | G37: Delivery destination name | H37: 納品先名 | I37: E
A38: 10 | D38: dlv_cntct_dpt | E38: #MA.BP_CNTCT_DPT | G38: Delivery destination dept. | H38: 納品先部署 | I38: E
A39: 10 | D39: dlv_cntct_psn | E39: #MA.BP_CNTCT_PSN | G39: Delivery destination PIC | H39: 納品先担当者 | I39: E
A40: 10 | D40: dlv_zip_cd | E40: #MA.ZIP_CD | G40: Zip code (Delivery destination) | H40: 納品先郵便番号 | I40: E
A41: 10 | D41: dlv_addr1 | E41: #MA.ADDR | G41: Address 1 (Delivery destination) | H41: 納品先住所1 | I41: E
A42: 10 | D42: dlv_addr2 | E42: #MA.ADDR | G42: Address 2 (Delivery destination) | H42: 納品先住所2 | I42: E
A43: 10 | D43: dlv_addr3 | E43: #MA.ADDR | G43: Address 3 (Delivery destination) | H43: 納品先住所3 | I43: E
A44: 10 | D44: dlv_addr4 | E44: #MA.ADDR | G44: Address 4 (Delivery destination) | H44: 納品先住所4 | I44: E
A45: 10 | D45: dlv_tel | E45: #MA.TEL | G45: TEL (Delivery destination) | H45: 納品先ＴＥＬ | I45: E
A46: 10 | D46: dlv_fax | E46: #MA.TEL | G46: FAX (Delivery destination) | H46: 納品先ＦＡＸ | I46: E
... A61: 10 | D61: tdlv_lg_grp_cd | E61: #MA.LG_GRP_CD | G61: Receiving point distribution group cd. | H61: 配送先物流グループＣＤ | I61: E

Sheet Sls_Schd_Upd05
A1: * | B1: * | D1: L | E1: 1
A2: * | D2: オペレーション実装仕様書 Operation Specification Implementation Sheet | E2: ModuleID : | F2: =IF(LogicCommon!C2="","",LogicCommon!C2) -> MS | G2: LogicID : | H2: =IF(LogicCommon!E2="","",LogicCommon!E2) -> MSBBL6220 | I2: Ope.ID : | J2: Sls_Schd_Upd05 | K2: Pj.ID : | L2: =IF(LogicCommon!G2="","",LogicCommon!G2) -> MC | M2: Ope.Body : | N2: "mcframe.serverMAUD.MAUDL5010.MAUDL_Operation"
A3: * | D3: =IF(LogicCommon!A3="","",LogicCommon!A3) | E3: SubModuleID : | F3: =IF(LogicCommon!C3="","",LogicCommon!C3) -> MSBB | G3: LogicClass : | H3: =IF(LogicCommon!E3="","",LogicCommon!E3) -> MSBBL_SlsSchdService | I3: Ope.Method : | J3: =J2 -> Sls_Schd_Upd05 | K3: SuperClassPj.ID : | L3: =IF(LogicCommon!G3="","",LogicCommon!G3) | O3: Gene.Type : | P3: ALL
A4: * | E4: Version : | F4: 000000 | G4: LogicName : | H4: =IF(LogicCommon!E4="","",LogicCommon!E4) -> 売上予定サービス | I4: Ope.Name : | J4: インボイス登録、輸出実績登録による更新 | K4: SuperLogicID : | L4: =IF(LogicCommon!G4="","",LogicCommon!G4) -> MS.MSUDL5010 | M4: ImplOpe.ID:
A5: * | E5: ACType :
A6: * | D6: 概要 : | M6: ID | O6: ID | Q6: ID
A7: # | I7: U | K7: K | L7: o | N7: o | P7: o
A8: # | D8: ブロック名 Block Name | E8: 型 Type | G8: super/share | H8: 対象ブロック名 Target Block Name | L8: TargetName | N8: TargetName | P8: TargetName | T8: ブロック備考 Block Remarks
A9: # | D9: 項目名 Field Name | E9: 型 Type | F9: 桁 Digits | G9: フルネーム Full Name | H9: 日本語名 Japanese Name | I9: 上り項目 Request Message Field | J9: 下り項目 Response Message Field | R9: 条件および編集方法 Conditions and Editing Methods | T9: 項目備考 Field Remarks
A10: # | L10: 上り項目 Request Message Field | M10: 下り項目 Response Message Field | N10: 上り項目 Request Message Field | O10: 下り項目 Response Message Field | P10: 上り項目 Request Message Field | Q10: 下り項目 Response Message Field
A11: 10 | B11: * | D11: Sls_Schd_Upd05_Dtl | E11: L
A12: 10 | D12: sls_schd_src_typ | E12: #MS.SLS_SCHD_SRC_TYP | G12: Sales schedule creating source type | H12: 売上予定作成元区分 | I12: E
A13: 10 | D13: data_crud_typ | E13: #MA.DATA_CRUD_TYP | G13: Data update type | H13: データ更新区分 | I13: E
A14: 10 | D14: iv_d_no | E14: #MA.IV_D_NO | G14: Invoice details No. | H14: インボイス明細ＮＯ | I14: E
A15: 10 | D15: slo_d_no | E15: #MA.SLO_D_NO | G15: Sales order details No. | H15: 受注明細NO | I15: E
A16: 10 | D16: dlv_slip_d_no | E16: #MA.DLV_SLIP_D_NO | G16: Delivery note details No. | H16: 納品書明細ＮＯ | I16: E
A17: 10 | D17: sls_schd_dt | E17: #MA.DT | G17: Scheduled sales date | H17: 売上予定日 | I17: E
A18: 10 | D18: trd_unit_qty | E18: #MA.QTY | G18: Transaction unit qty. | H18: 取引単位数量 | I18: E
A19: 10 | D19: trd_unit_cd | E19: #MA.UNIT_CD | G19: Transaction unit cd. | H19: 取引単位ＣＤ | I19: E
A20: 10 | D20: base_unit_qty | E20: #MA.QTY | G20: Base unit qty. | H20: 基準単位数量 | I20: E
A21: 10 | D21: base_unit_cd | E21: #MA.UNIT_CD | G21: Base unit cd. | H21: 基準単位ＣＤ | I21: E
A22: 10 | D22: iv_no | E22: #MA.IV_NO | G22: Invoice No. | H22: インボイスＮＯ | I22: E
A23: 10 | D23: ship_act_flg | E23: #MA.FLG | G23: Shipping result | H23: 出荷実績 | I23: E
... A26: 10 | D26: uplnd_flg | E26: #MA.FLG | G26: Unplanned shipping | H26: 計画外出荷 | I26: E
A28: 20 | B28: * | D28: Sls_Schd_Upd05_IVAct | E28: L
A29: 20 | D29: data_crud_typ | E29: #MA.DATA_CRUD_TYP | G29: Data update type | H29: データ更新区分 | I29: E
A30: 20 | D30: slo_d_no | E30: #MA.SLO_D_NO | G30: Sales order details No. | H30: 受注明細ＮＯ | I30: E
A31: 20 | D31: ship_act_d_no | E31: #MA.SHIP_ACT_D_NO | G31: Shipping result details No. | H31: 出荷実績明細ＮＯ | I31: E
A32: 20 | D32: iv_ship_act_d_no | E32: #MA.IV_SHIP_ACT_D_NO | G32: Shipping invoice result details No. | H32: インボイス出荷実績明細ＮＯ | I32: E

Sheet 来歴
A1: 変更来歴
A3: Rev. | H3: 修正番号 | O3: 変更内容 | AQ3: 変更箇所
A4: 1 | O4: 初版
A5: 1.1 | O5: 英語の名称を追記 | AQ5: 全般
