Workbook

Sheet LogicCommon
A2: オペレーション実装仕様書 | B2: ModuleID : | C2: MS | D2: LogicID : | E2: MSLAL5120 | F2: Pj.ID : | G2: MC
B3: SubModuleID : | C3: MSLA | D3: LogicClass : | E3: MSLAL_SloRecvIfService | F3: SuperClassPj.ID :
D4: LogicName : | E4: 受注受信ＩＦサービス | F4: SuperLogicID : | G4: MS.MSUDL5010
A5: 概要 : | B5: ＥＤＩで受注を取り込むための処理を提供する
A6: 詳細 :

Sheet SloRecvIf_Upd01
A1: * | B1: * | D1: L | E1: 1
A2: * | D2: オペレーション実装仕様書 Operation Specification Implementation Sheet | E2: ModuleID : | F2: =IF(LogicCommon!C2="","",LogicCommon!C2) -> MS | G2: LogicID : | H2: =IF(LogicCommon!E2="","",LogicCommon!E2) -> MSLAL5120 | I2: Ope.ID : | J2: SloRecvIf_Upd01 | K2: Pj.ID : | L2: =IF(LogicCommon!G2="","",LogicCommon!G2) -> MC | M2: Ope.Body : | N2: "mcframe.serverMAUD.MAUDL5010.MAUDL_Operation"
A3: * | D3: =IF(LogicCommon!A3="","",LogicCommon!A3) | E3: SubModuleID : | F3: =IF(LogicCommon!C3="","",LogicCommon!C3) -> MSLA | G3: LogicClass : | H3: =IF(LogicCommon!E3="","",LogicCommon!E3) -> MSLAL_SloRecvIfService | I3: Ope.Method : | J3: @ | K3: SuperClassPj.ID : | L3: =IF(LogicCommon!G3="","",LogicCommon!G3) | O3: Gene.Type : | P3: ALL
A4: * | E4: Version : | F4: 000000 | G4: LogicName : | H4: =IF(LogicCommon!E4="","",LogicCommon!E4) -> 受注受信ＩＦサービス | I4: Ope.Name : | J4: 受注取込１ | K4: SuperLogicID : | L4: =IF(LogicCommon!G4="","",LogicCommon!G4) -> MS.MSUDL5010 | M4: ImplOpe.ID: | N4: PF.PFUDL0040.Upd01
A5: * | E5: ACType :
A6: * | D6: 概要 : | E6: 受注受信ＩＦ取込を行う。（ＥＳＢのリアルタイム取込から呼び出される） | M6: ID | O6: ID | Q6: ID
A7: # | I7: U | K7: K | L7: o | N7: o | P7: o
A8: # | D8: ブロック名 Block Name | E8: 型 Type | G8: super/share | H8: 対象ブロック名 Target Block Name | L8: TargetName | N8: TargetName | P8: TargetName | T8: ブロック備考 Block Remarks
A9: # | D9: 項目名 Field Name | E9: 型 Type | F9: 桁 Digits | G9: フルネーム Full Name | H9: 日本語名 Japanese Name | I9: 上り項目 Request Message Field | J9: 下り項目 Response Message Field | R9: 条件および編集方法 Conditions and Editing Methods | T9: 項目備考 Field Remarks
A10: # | L10: 上り項目 Request Message Field | M10: 下り項目 Response Message Field | N10: 上り項目 Request Message Field | O10: 下り項目 Response Message Field | P10: 上り項目 Request Message Field | Q10: 下り項目 Response Message Field
A11: 10 | B11: * | D11: SloRecvIf_Upd01_Dtl | E11: L | G11: $share$ | H11: PF.PFUDL0040.Upd01.Upd01_Dtl
A12: 10 | D12: data_no | E12: #MA.IF_DATA_NO | G12: Data No. | H12: データＮＯ | I12: E | J12: -
A13: 10 | D13: ext_data_no | E13: #MA.IF_EXT_DATA_NO | G13: External system data No. | H13: 外部システムデータＮＯ | I13: E | J13: -
A14: 10 | D14: ext_sys_cd | E14: #MA.EXT_SYS_CD | G14: External system cd. | H14: 外部システムＣＤ | I14: E | J14: -
A15: 10 | D15: bp_cd | E15: #MA.BP_CD | G15: BP cd. | H15: 取引先ＣＤ | I15: E | J15: -
D16: 詳細 :

Sheet SloRecvIf_Upd02
A1: * | B1: * | D1: L | E1: 1
A2: * | D2: オペレーション実装仕様書 Operation Specification Implementation Sheet | E2: ModuleID : | F2: =IF(LogicCommon!C2="","",LogicCommon!C2) -> MS | G2: LogicID : | H2: =IF(LogicCommon!E2="","",LogicCommon!E2) -> MSLAL5120 | I2: Ope.ID : | J2: SloRecvIf_Upd02 | K2: Pj.ID : | L2: =IF(LogicCommon!G2="","",LogicCommon!G2) -> MC | M2: Ope.Body : | N2: "mcframe.serverMAUD.MAUDL5010.MAUDL_Operation"
A3: * | D3: =IF(LogicCommon!A3="","",LogicCommon!A3) | E3: SubModuleID : | F3: =IF(LogicCommon!C3="","",LogicCommon!C3) -> MSLA | G3: LogicClass : | H3: =IF(LogicCommon!E3="","",LogicCommon!E3) -> MSLAL_SloRecvIfService | I3: Ope.Method : | J3: @ | K3: SuperClassPj.ID : | L3: =IF(LogicCommon!G3="","",LogicCommon!G3) | O3: Gene.Type : | P3: ALL
A4: * | E4: Version : | F4: 000000 | G4: LogicName : | H4: =IF(LogicCommon!E4="","",LogicCommon!E4) -> 受注受信ＩＦサービス | I4: Ope.Name : | J4: 受注取込２ | K4: SuperLogicID : | L4: =IF(LogicCommon!G4="","",LogicCommon!G4) -> MS.MSUDL5010 | M4: ImplOpe.ID: | N4: MB.MBBEL5010.Upd01
A5: * | E5: ACType :
A6: * | D6: 概要 : | E6: 受注受信ＩＦ取込を行う。（ＩＦデータ確認、および受注受信ＩＦ取込バッチから呼び出される） | M6: ID | O6: ID | Q6: ID
A7: # | I7: U | K7: K | L7: o | N7: o | P7: o
A8: # | D8: ブロック名 Block Name | E8: 型 Type | G8: super/share | H8: 対象ブロック名 Target Block Name | L8: TargetName | N8: TargetName | P8: TargetName | T8: ブロック備考 Block Remarks
A9: # | D9: 項目名 Field Name | E9: 型 Type | F9: 桁 Digits | G9: フルネーム Full Name | H9: 日本語名 Japanese Name | I9: 上り項目 Request Message Field | J9: 下り項目 Response Message Field | R9: 条件および編集方法 Conditions and Editing Methods | T9: 項目備考 Field Remarks
A10: # | L10: 上り項目 Request Message Field | M10: 下り項目 Response Message Field | N10: 上り項目 Request Message Field | O10: 下り項目 Response Message Field | P10: 上り項目 Request Message Field | Q10: 下り項目 Response Message Field
A11: 10 | B11: * | D11: SloRecvIf_Upd01_Dtl | E11: L | G11: $share$ | H11: MB.MBBEL5010.Upd01.IfDataImp_Upd01_Dtl
A12: 10 | D12: data_no | E12: #MA.IF_DATA_NO | G12: Data No. | H12: データＮＯ | I12: E | J12: -
A13: 10 | D13: ext_data_no | E13: #MA.IF_EXT_DATA_NO | G13: External system data No. | H13: 外部システムデータＮＯ | I13: E | J13: -
A14: 10 | D14: ext_sys_cd | E14: #MA.EXT_SYS_CD | G14: External system cd. | H14: 外部システムＣＤ | I14: E | J14: -
A15: 10 | D15: bp_cd | E15: #MA.BP_CD | G15: BP cd. | H15: 取引先ＣＤ | I15: E | J15: -
L16: 上り項目 Request Message Field | M16: 下り項目 Response Message Field | N16: 上り項目 Request Message Field | O16: 下り項目 Response Message Field | P16: 上り項目 Request Message Field | Q16: 下り項目 Response Message Field
A17: 20 | B17: * | D17: SloRecvIf_Upd02_Cnd | E17: R | G17: $share$ | H17: MB.MBBEL5010.Upd01.IfDataImp_Upd01_Cnd
A18: 20 | D18: exe_unit_lump_flg | E18: #MA.FLG | G18: Process unit aggregation | H18: 処理単位まとめ | I18: E | J18: -
A19: 20 | D19: if_upd_typ | E19: #MA.IF_UPD_TYP | G19: IF update type | H19: ＩＦ更新区分 | I19: E | J19: -
A20: 20 | D20: src_actlumprecv_flg | E20: #MA.FLG | G20: Caller results import batch | H20: 呼出元実績一括受信バッチ | I20: E | J20: -
L21: 上り項目 Request Message Field | M21: 下り項目 Response Message Field | N21: 上り項目 Request Message Field | O21: 下り項目 Response Message Field | P21: 上り項目 Request Message Field | Q21: 下り項目 Response Message Field
A22: 30 | B22: * | D22: SloRecvIf_Upd02_Rslt | E22: R | G22: $share$ | H22: MB.MBBEL5010.Upd01.IfDataImp_Upd01_Rslt
A23: 30 | D23: total_num | E23: N | G23: Number of processed target | H23: 処理対象件数 | I23: - | J23: E
A24: 30 | D24: ok_num | E24: N | G24: Number of entries | H24: 登録件数 | I24: - | J24: E
A25: 30 | D25: err_num | E25: N | G25: Error count | H25: エラー件数 | I25: - | J25: E
A26: 30 | D26: skip_num | E26: N | G26: Skip count | H26: スキップ件数 | I26: - | J26: E
D27: 詳細 :

Sheet SloRecvIf_Upd03
A1: * | B1: * | D1: L | E1: 1
A2: * | D2: オペレーション実装仕様書 Operation Specification Implementation Sheet | E2: ModuleID : | F2: =IF(LogicCommon!C2="","",LogicCommon!C2) -> MS | G2: LogicID : | H2: =IF(LogicCommon!E2="","",LogicCommon!E2) -> MSLAL5120 | I2: Ope.ID : | J2: SloRecvIf_Upd03 | K2: Pj.ID : | L2: =IF(LogicCommon!G2="","",LogicCommon!G2) -> MC | M2: Ope.Body : | N2: "mcframe.serverMAUD.MAUDL5010.MAUDL_Operation"
A3: * | D3: =IF(LogicCommon!A3="","",LogicCommon!A3) | E3: SubModuleID : | F3: =IF(LogicCommon!C3="","",LogicCommon!C3) -> MSLA | G3: LogicClass : | H3: =IF(LogicCommon!E3="","",LogicCommon!E3) -> MSLAL_SloRecvIfService | I3: Ope.Method : | J3: @ | K3: SuperClassPj.ID : | L3: =IF(LogicCommon!G3="","",LogicCommon!G3) | O3: Gene.Type : | P3: ALL
A4: * | E4: Version : | F4: 000000 | G4: LogicName : | H4: =IF(LogicCommon!E4="","",LogicCommon!E4) -> 受注受信ＩＦサービス | I4: Ope.Name : | J4: 受注取込３ | K4: SuperLogicID : | L4: =IF(LogicCommon!G4="","",LogicCommon!G4) -> MS.MSUDL5010 | M4: ImplOpe.ID:
A5: * | E5: ACType :
A6: * | D6: 概要 : | E6: 受注受信ＩＦ取込を行う。（マルチスレッド実行用） | M6: ID | O6: ID | Q6: ID
A7: # | I7: U | K7: K | L7: o | N7: o | P7: o
A8: # | D8: ブロック名 Block Name | E8: 型 Type | G8: super/share | H8: 対象ブロック名 Target Block Name | L8: TargetName | N8: TargetName | P8: TargetName | T8: ブロック備考 Block Remarks
A9: # | D9: 項目名 Field Name | E9: 型 Type | F9: 桁 Digits | G9: フルネーム Full Name | H9: 日本語名 Japanese Name | I9: 上り項目 Request Message Field | J9: 下り項目 Response Message Field | R9: 条件および編集方法 Conditions and Editing Methods | T9: 項目備考 Field Remarks
A10: # | L10: 上り項目 Request Message Field | M10: 下り項目 Response Message Field | N10: 上り項目 Request Message Field | O10: 下り項目 Response Message Field | P10: 上り項目 Request Message Field | Q10: 下り項目 Response Message Field
A11: 10 | B11: * | D11: SloRecvIf_Upd03_Dtl | E11: L
A12: 10 | D12: slo | E12: R | F12: DBC:MS.MST_SLO_RECV_IF
A13: 10 | D13: slo.data_lno# | E13: RI | G13: Data row No. | H13: データ行ＮＯ | I13: E | J13: -
A14: 10 | D14: slo.data_no# | E14: RI | G14: Data No. | H14: データＮＯ | I14: E | J14: -
A15: 10 | D15: slo.ext_data_no# | E15: RI | G15: External system data No. | H15: 外部システムデータＮＯ | I15: E | J15: -
A16: 10 | D16: slo.ext_data_lno# | E16: RI | G16: External system data row No. | H16: 外部システムデータ行ＮＯ | I16: E | J16: -
A17: 10 | D17: slo.cst_po_no# | E17: RI | G17: Customer order No. | H17: 得意先注文ＮＯ | I17: E | J17: -
A18: 10 | D18: slo.cst_po_rev# | E18: RI | G18: Customer order rev. number | H18: 得意先注文改訂番号 | I18: E | J18: -
A19: 10 | D19: slo.cst_cd# | E19: RI | G19: Customer cd. | H19: 得意先ＣＤ | I19: E | J19: -
L20: 上り項目 Request Message Field | M20: 下り項目 Response Message Field | N20: 上り項目 Request Message Field | O20: 下り項目 Response Message Field | P20: 上り項目 Request Message Field | Q20: 下り項目 Response Message Field
A21: 20 | B21: * | D21: SloRecvIf_Upd03_Rslt | E21: R
A22: 20 | D22: total_num | E22: N | G22: Number of processed target | H22: 処理対象件数 | I22: - | J22: E
A23: 20 | D23: ok_num | E23: N | G23: Number of entries | H23: 登録件数 | I23: - | J23: E
A24: 20 | D24: err_num | E24: N | G24: Error count | H24: エラー件数 | I24: - | J24: E
A25: 20 | D25: skip_num | E25: N | G25: Skip count | H25: スキップ件数 | I25: - | J25: E
D26: 詳細 :

Sheet SloRecvIf_Upd04
A1: * | B1: * | D1: L | E1: 1
A2: * | D2: オペレーション実装仕様書 Operation Specification Implementation Sheet | E2: ModuleID : | F2: =IF(LogicCommon!C2="","",LogicCommon!C2) -> MS | G2: LogicID : | H2: =IF(LogicCommon!E2="","",LogicCommon!E2) -> MSLAL5120 | I2: Ope.ID : | J2: SloRecvIf_Upd04 | K2: Pj.ID : | L2: =IF(LogicCommon!G2="","",LogicCommon!G2) -> MC | M2: Ope.Body : | N2: "mcframe.serverMAUD.MAUDL5010.MAUDL_Operation"
A3: * | D3: =IF(LogicCommon!A3="","",LogicCommon!A3) | E3: SubModuleID : | F3: =IF(LogicCommon!C3="","",LogicCommon!C3) -> MSLA | G3: LogicClass : | H3: =IF(LogicCommon!E3="","",LogicCommon!E3) -> MSLAL_SloRecvIfService | I3: Ope.Method : | J3: @ | K3: SuperClassPj.ID : | L3: =IF(LogicCommon!G3="","",LogicCommon!G3) | O3: Gene.Type : | P3: ALL
A4: * | E4: Version : | F4: 000000 | G4: LogicName : | H4: =IF(LogicCommon!E4="","",LogicCommon!E4) -> 受注受信ＩＦサービス | I4: Ope.Name : | J4: 受注取込４ | K4: SuperLogicID : | L4: =IF(LogicCommon!G4="","",LogicCommon!G4) -> MS.MSUDL5010 | M4: ImplOpe.ID:
A5: * | E5: ACType :
A6: * | D6: 概要 : | E6: 受注受信ＩＦ取込を行う。（受注登録サービスを呼び出す本処理） | M6: ID | O6: ID | Q6: ID
A7: # | I7: U | K7: K | L7: o | N7: o | P7: o
A8: # | D8: ブロック名 Block Name | E8: 型 Type | G8: super/share | H8: 対象ブロック名 Target Block Name | L8: TargetName | N8: TargetName | P8: TargetName | T8: ブロック備考 Block Remarks
A9: # | D9: 項目名 Field Name | E9: 型 Type | F9: 桁 Digits | G9: フルネーム Full Name | H9: 日本語名 Japanese Name | I9: 上り項目 Request Message Field | J9: 下り項目 Response Message Field | R9: 条件および編集方法 Conditions and Editing Methods | T9: 項目備考 Field Remarks
A10: # | L10: 上り項目 Request Message Field | M10: 下り項目 Response Message Field | N10: 上り項目 Request Message Field | O10: 下り項目 Response Message Field | P10: 上り項目 Request Message Field | Q10: 下り項目 Response Message Field
A11: 10 | B11: * | D11: SloRecvIf_Upd04_Dtl | E11: L
A12: 10 | D12: slo | E12: R | F12: DBC:MS.MST_SLO_RECV_IF
A13: 10 | D13: slo.data_lno# | E13: RI | G13: Data row No. | H13: データ行ＮＯ | I13: E | J13: E
A14: 10 | D14: slo.data_no# | E14: RI | G14: Data No. | H14: データＮＯ | I14: E | J14: E
A15: 10 | D15: slo.ext_data_no# | E15: RI | G15: External system data No. | H15: 外部システムデータＮＯ | I15: E | J15: -
A16: 10 | D16: slo.ext_data_lno# | E16: RI | G16: External system data row No. | H16: 外部システムデータ行ＮＯ | I16: E | J16: -
A17: 10 | D17: slo.exe_sts_typ# | E17: RI | G17: PG execution status type | H17: ＰＧ実行状況区分 | I17: - | J17: E
A18: 10 | D18: slo.cst_po_no# | E18: RI | G18: Customer order No. | H18: 得意先注文ＮＯ | I18: E | J18: -
A19: 10 | D19: slo.cst_po_rev# | E19: RI | G19: Customer order rev. number | H19: 得意先注文改訂番号 | I19: E | J19: -
A20: 10 | D20: slo.cst_cd# | E20: RI | G20: Customer cd. | H20: 得意先ＣＤ | I20: E | J20: -
A21: 10 | D21: slo.sls_usr_cd# | E21: RI | G21: Sales PIC cd. | H21: 売上担当者ＣＤ | I21: - | J21: -
A22: 10 | D22: slo.log_sub_key1# | E22: RI | G22: Log sub key 1 | H22: ログサブキー１ | I22: - | J22: -
A23: 10 | D23: slo.log_sub_key2# | E23: RI | G23: Log sub key 2 | H23: ログサブキー２ | I23: - | J23: -
A24: 10 | D24: wg_cd | E24: #MA.WG_CD | G24: WG cd. | H24: ワーキンググループＣＤ | I24: - | J24: -
D25: 詳細 :

Sheet SloRecvIf_Chk01
A1: * | B1: * | D1: L | E1: 1
A2: * | D2: オペレーション実装仕様書 Operation Specification Implementation Sheet | E2: ModuleID : | F2: =IF(LogicCommon!C2="","",LogicCommon!C2) -> MS | G2: LogicID : | H2: =IF(LogicCommon!E2="","",LogicCommon!E2) -> MSLAL5120 | I2: Ope.ID : | J2: SloRecvIf_Chk01 | K2: Pj.ID : | L2: =IF(LogicCommon!G2="","",LogicCommon!G2) -> MC | M2: Ope.Body : | N2: MA.MAUDL5010.Checker
A3: * | D3: =IF(LogicCommon!A3="","",LogicCommon!A3) | E3: SubModuleID : | F3: =IF(LogicCommon!C3="","",LogicCommon!C3) -> MSLA | G3: LogicClass : | H3: =IF(LogicCommon!E3="","",LogicCommon!E3) -> MSLAL_SloRecvIfService | I3: Ope.Method : | J3: @ | K3: SuperClassPj.ID : | L3: =IF(LogicCommon!G3="","",LogicCommon!G3) | O3: Gene.Type : | P3: ALL
A4: * | E4: Version : | F4: 000000 | G4: LogicName : | H4: =IF(LogicCommon!E4="","",LogicCommon!E4) -> 受注受信ＩＦサービス | I4: Ope.Name : | J4: 取込前チェック | K4: SuperLogicID : | L4: =IF(LogicCommon!G4="","",LogicCommon!G4) -> MS.MSUDL5010 | M4: ImplOpe.ID:
A5: * | E5: ACType :
A6: * | D6: 概要 : | E6: 受注受信ＩＦ取込を行う前のチェック処理 | M6: ID | O6: ID | Q6: ID | AD6: ID | AF6: ID
A7: # | I7: U | K7: K | L7: K | M7: K | N7: K | O7: K | P7: K | Q7: K | R7: K | S7: K | T7: K | U7: K | V7: K | W7: K | X7: K | Y7: K | Z7: K | AA7: K | AB7: K | AC7: o | AE7: o
A8: # | D8: ブロック名 Block Name | E8: 型 Type | G8: super/share | H8: 対象ブロック名 Target Block Name | K8: REQ_UPD_CNT_CHK | L8: REQUIRED | M8: CHK_NUM | N8: SMALL_LARGE | O8: CHK_DT | P8: BEFORE_AFTER | Q8: CHK_PTN | R8: DUPLICATE | S8: TOO_MANY_INPUTS | T8: AT_LEAST_ONE | U8: ONLY_ONE_INPUT | V8: LIST_LOGIC | W8: LIST_OUT | X8: LIST_OUT_BASE | Y8: LIST_IN | Z8: LIST_IN_BASE | AA8: CONST | AB8: NULL_VAL | AC8: TargetName | AE8: TargetName | AI8: ブロック備考 Block Remarks
A9: # | D9: 項目名 Field Name | E9: 型 Type | F9: 桁 Digits | G9: フルネーム Full Name | H9: 日本語名 Japanese Name | I9: 上り項目 Request Message Field | J9: 下り項目 Response Message Field | AG9: 条件および編集方法 Conditions and Editing Methods | AI9: 項目備考 Field Remarks
A10: #
A11: 10 | B11: * | D11: SloRecvIf_Chk01_Dtl | E11: L | AC11: 上り項目 | AD11: 下り項目 | AE11: 上り項目 | AF11: 下り項目
A12: 10 | D12: slo | E12: R | F12: DBC:MS.MST_SLO_RECV_IF
A13: 10 | D13: slo.data_lno# | E13: RI | G13: Data row No. | H13: データ行ＮＯ | I13: E | J13: E
A14: 10 | D14: slo.data_no# | E14: RI | G14: Data No. | H14: データＮＯ | I14: E | J14: -
A15: 10 | D15: slo.data_crud_typ# | E15: RI | G15: Data update type | H15: データ更新区分 | I15: E | J15: - | AA15: MAC_DATA_CRUD_TYP
A16: 10 | D16: slo.ext_sys_cd# | E16: RI | G16: External system cd. | H16: 外部システムＣＤ | I16: E | J16: -
A17: 10 | D17: slo.exe_sts_typ# | E17: RI | G17: PG execution status type | H17: ＰＧ実行状況区分 | I17: E | J17: -
A18: 10 | D18: slo.ext_data_no# | E18: RI | G18: External system data No. | H18: 外部システムデータＮＯ | I18: E | J18: -
A19: 10 | D19: slo.ext_data_lno# | E19: RI | G19: External system data row No. | H19: 外部システムデータ行ＮＯ | I19: E | J19: -
A20: 10 | D20: slo.data_make_dt# | E20: RI | G20: Creation date and time of source record | H20: 送信元レコード作成日時 | I20: E | J20: -
A21: 10 | D21: slo.imp_flg# | E21: RI | G21: To import | H21: 取込対象 | I21: E | J21: -
A22: 10 | D22: slo.recv_dt# | E22: RI | G22: Receiving date | H22: 受信日 | I22: E | J22: -
A23: 10 | D23: slo.cst_po_no# | E23: RI | G23: Customer order No. | H23: 得意先注文ＮＯ | I23: E | J23: - | L23: E
A24: 10 | D24: slo.cst_po_rev# | E24: RI | G24: Customer order rev. number | H24: 得意先注文改訂番号 | I24: E | J24: -
A25: 10 | D25: slo.cst_po_d_no# | E25: RI | G25: Customer order details No. | H25: 得意先注文明細ＮＯ | I25: E | J25: -
A26: 10 | D26: slo.cst_cd# | E26: RI | G26: Customer cd. | H26: 得意先ＣＤ | I26: E | J26: - | L26: E | V26: MA.MAUAL0010.Bp | W26: cst_iv_flg;sls_basis_typ;cst_trd_cur_cd;cst_upri_dec_place;cst_amt_dec_place;sls_amt_rnd_typ;sls_tax_rnd_typ;cst_ar_dpt_cd;cst_bill_crryovr_times;ship_schd_split_typ;sls_upri_req_typ;cst_sls_usr_cd;cst_sls_dpt_cd;ar_dpt_typ;cst_tterm_cd1;cst_tterm_cd2;cst_tterm_cd3 | X26: cst_iv_flg;sls_basis_typ;cur_cd;upri_dec_place;amt_dec_place;sls_amt_rnd_typ;sls_tax_rnd_typ;ar_dpt_cd;bill_crryovr_times;ship_schd_split_typ;sls_upri_req_typ;cst_usr_cd;cst_dpt_cd;ar_dpt_typ;cst_tterm_cd1;cst_tterm_cd2;cst_tterm_cd3 | Y26: MAC_BP_IS_SRCH_TYP.CST_NOT_SUNDRY;slo_dt | Z26: bp_is_srch_typ;dt
A27: 10 | D27: slo.dest_cd1# | E27: RI | G27: Distribution channel cd. 1 | H27: 仕向先ＣＤ１ | I27: E | J27: -
A28: 10 | D28: slo.dest_cd2# | E28: RI | G28: Distribution channel cd. 2 | H28: 仕向先ＣＤ２ | I28: E | J28: -
A29: 10 | D29: slo.dest_cd3# | E29: RI | G29: Distribution channel cd. 3 | H29: 仕向先ＣＤ３ | I29: E | J29: -
A30: 10 | D30: slo.po_dt# | E30: RI | G30: PO date | H30: 注文日 | I30: E | J30: -
A31: 10 | D31: slo.purc_id_typ# | E31: RI | G31: Purchase identification type | H31: 購買識別区分 | I31: E | J31: -
A32: 10 | D32: slo.sls_cststk_flg# | E32: RI | G32: Sales keeping customer inventory | H32: 預り売上 | I32: E | J32: -
A33: 10 | D33: slo.slo_typ# | E33: RI | G33: Sales order type | H33: 受注区分 | I33: E | J33: -
A34: 10 | D34: slo.trd_cur_cd# | E34: RI | G34: Transaction currency cd. | H34: 取引通貨ＣＤ | I34: E | J34: - | V34: MA.MAUAL0010.Cur | W34: upri_dec_place;amt_dec_place | X34: upri_dec_place;amt_dec_place
A35: 10 | D35: slo.sls_dpt_cd# | E35: RI | G35: Sales dept. cd. | H35: 売上部門ＣＤ | I35: E | J35: - | V35: MA.MAUAL0010.Dpt | W35: dpt_wg_cd | X35: wg_cd | Y35: slo_dt;MAC_DPT_IS_SRCH_TYP.SLS;sls_usr_cd | Z35: dt;dpt_is_srch_typ;usr_cd
A36: 10 | D36: slo.sls_usr_cd# | E36: RI | G36: Sales PIC cd. | H36: 売上担当者ＣＤ | I36: E | J36: -
A37: 10 | D37: slo.dlv_cd# | E37: RI | G37: Delivery destination cd. | H37: 納品先ＣＤ | I37: E | J37: - | V37: MA.MAUAL0010.Bp | W37: mst_dlv_nm;dlv_sundry_flg;pri_prnt_flg;mst_dlv_zip_cd;mst_dlv_addr1;mst_dlv_addr2;mst_dlv_addr3;mst_dlv_addr4;mst_dlv_cntry_cd;mst_dlv_tel;mst_dlv_fax;mst_dlv_cntct_dpt;mst_dlv_cntct_psn;dlv_lg_grp_cd;tdlv_req_flg;prnt_lcl_cd | X37: bp_nm;dlv_sundry_flg;pri_prnt_flg;zip_cd;addr1;addr2;addr3;addr4;cntry_cd;tel;fax;dlv_cntct_dpt;dlv_cntct_psn;lg_grp_cd;tdlv_req_flg;prnt_lcl_cd | Y37: MAC_BP_IS_SRCH_TYP.DLV;slo_dt | Z37: bp_is_srch_typ;dt
A38: 10 | D38: slo.dlv_nm# | E38: RI | G38: Delivery destination name | H38: 納品先名 | I38: E | J38: -
A39: 10 | D39: slo.dlv_cntct_dpt# | E39: RI | G39: Delivery destination dept. | H39: 納品先部署 | I39: E | J39: -
A40: 10 | D40: slo.dlv_cntct_psn# | E40: RI | G40: Delivery destination PIC | H40: 納品先担当者 | I40: E | J40: -
A41: 10 | D41: slo.dlv_zip_cd# | E41: RI | G41: Zip code (Delivery destination) | H41: 納品先郵便番号 | I41: E | J41: -
A42: 10 | D42: slo.dlv_addr1# | E42: RI | G42: Address 1 (Delivery destination) | H42: 納品先住所１ | I42: E | J42: -
A43: 10 | D43: slo.dlv_addr2# | E43: RI | G43: Address 2 (Delivery destination) | H43: 納品先住所２ | I43: E | J43: -
A44: 10 | D44: slo.dlv_addr3# | E44: RI | G44: Address 3 (Delivery destination) | H44: 納品先住所３ | I44: E | J44: -
A45: 10 | D45: slo.dlv_addr4# | E45: RI | G45: Address 4 (Delivery destination) | H45: 納品先住所４ | I45: E | J45: -
A46: 10 | D46: slo.dlv_tel# | E46: RI | G46: TEL (Delivery destination) | H46: 納品先ＴＥＬ | I46: E | J46: -
A47: 10 | D47: slo.dlv_fax# | E47: RI | G47: FAX (Delivery destination) | H47: 納品先ＦＡＸ | I47: E | J47: -
A48: 10 | D48: slo.dlv_cntry_cd# | E48: RI | G48: Delivery destination country cd. | H48: 納品先国ＣＤ | I48: E | J48: -
A49: 10 | D49: slo.tdlv_cd# | E49: RI | G49: Receiving point cd. | H49: 配送先ＣＤ | I49: E | J49: - | V49: MA.MAUAL0010.Bp | W49: mst_tdlv_nm;tdlv_sundry_flg;tdlv_lg_grp_cd;mst_tdlv_zip_cd;mst_tdlv_addr1;mst_tdlv_addr2;mst_tdlv_addr3;mst_tdlv_addr4;mst_tdlv_tel;mst_tdlv_fax;mst_tdlv_cntct_dpt;mst_tdlv_cntct_psn;via_dlv_typ | X49: bp_nm;dlv_sundry_flg;lg_grp_cd;zip_cd;addr1;addr2;addr3;addr4;tel;fax;dlv_cntct_dpt;dlv_cntct_psn;via_dlv_typ | Y49: MAC_BP_IS_SRCH_TYP.TDLV;slo_dt | Z49: bp_is_srch_typ;dt
A50: 10 | D50: slo.tdlv_nm# | E50: RI | G50: Receiving point name | H50: 配送先名 | I50: E | J50: -
A51: 10 | D51: slo.tdlv_cntct_dpt# | E51: RI | G51: Receiving point dept. | H51: 配送先部署 | I51: E | J51: -
A52: 10 | D52: slo.tdlv_cntct_psn# | E52: RI | G52: Receiving point PIC | H52: 配送先担当者 | I52: E | J52: -
A53: 10 | D53: slo.tdlv_zip_cd# | E53: RI | G53: Receiving point zip code | H53: 配送先郵便番号 | I53: E | J53: -
A54: 10 | D54: slo.tdlv_addr1# | E54: RI | G54: Receiving point address 1 | H54: 配送先住所１ | I54: E | J54: -
A55: 10 | D55: slo.tdlv_addr2# | E55: RI | G55: Receiving point address 2 | H55: 配送先住所２ | I55: E | J55: -
A56: 10 | D56: slo.tdlv_addr3# | E56: RI | G56: Receiving point address 3 | H56: 配送先住所３ | I56: E | J56: -
A57: 10 | D57: slo.tdlv_addr4# | E57: RI | G57: Receiving point address 4 | H57: 配送先住所４ | I57: E | J57: -
A58: 10 | D58: slo.tdlv_tel# | E58: RI | G58: Receiving point TEL | H58: 配送先ＴＥＬ | I58: E | J58: -
A59: 10 | D59: slo.tdlv_fax# | E59: RI | G59: Receiving point FAX | H59: 配送先ＦＡＸ | I59: E | J59: -
A60: 10 | D60: slo.tdlv_cntry_cd# | E60: RI | G60: Receiving point country cd. | H60: 配送先国ＣＤ | I60: E | J60: -
A61: 10 | D61: slo.dlv_day_week_typ# | E61: RI | G61: Arrival day of week | H61: 着曜日 | I61: E | J61: - | AA61: MAC_DAY_WEEK_TYP
A62: 10 | D62: slo.pri_prnt_typ# | E62: RI | G62: Print price type | H62: 価格印字区分 | I62: E | J62: -
A63: 10 | D63: slo.wrk_no# | E63: RI | G63: Sales project No. | H63: 案件ＮＯ | I63: E | J63: -
A64: 10 | D64: slo.tterm_cd1# | E64: RI | G64: Transaction terms cd. 1 | H64: 取引条件ＣＤ１ | I64: E | J64: -
A65: 10 | D65: slo.tterm_rmrks1# | E65: RI | G65: Transaction terms remarks 1 | H65: 取引条件備考１ | I65: E | J65: -
A66: 10 | D66: slo.tterm_cd2# | E66: RI | G66: Transaction terms cd. 2 | H66: 取引条件ＣＤ２ | I66: E | J66: -
A67: 10 | D67: slo.tterm_rmrks2# | E67: RI | G67: Transaction terms remarks 2 | H67: 取引条件備考２ | I67: E | J67: -
A68: 10 | D68: slo.tterm_cd3# | E68: RI | G68: Transaction terms cd. 3 | H68: 取引条件ＣＤ３ | I68: E | J68: -
A69: 10 | D69: slo.tterm_rmrks3# | E69: RI | G69: Transaction terms remarks 3 | H69: 取引条件備考３ | I69: E | J69: -
A70: 10 | D70: slo.trnspt_cd# | E70: RI | G70: Transportation method cd. | H70: 輸送方法ＣＤ | I70: E | J70: -
A71: 10 | D71: slo.load_port_cd# | E71: RI | G71: Loading port cd. | H71: 船積港ＣＤ | I71: E | J71: -
A72: 10 | D72: slo.dschrg_port_cd# | E72: RI | G72: Unloading port cd. | H72: 船卸港ＣＤ | I72: E | J72: -
A73: 10 | D73: slo.via_port_cd# | E73: RI | G73: Stopover point cd. | H73: 経由地ＣＤ | I73: E | J73: -
... A78: 10 | D78: slo.itm_sub2# | E78: RI | G78: Branch No. 2 | H78: 枝番２ | I78: E | J78: -
A79: 10 | D79: slo.itm_sub3# | E79: RI | G79: Branch No. 3 | H79: 枝番３ | I79: E | J79: - | V79: MA.MAUAL0010.ItmSub3 | W79: mst_itm_nm;sundry_itm_flg;dscnt_itm_flg;stk_mng_typ;asset_mng_typ;itm_trd_unit_cd;itm_bill_crryovr_times;proc_typ;slo_proc_flg;ship_inst_typ;ship_term_cd;slo_sno1_flg;slo_sno2_flg;slo_sno3_flg;slo_sno4_flg;sno1_num_typ;sno2_num_typ;sno3_num_typ;sno4_num_typ;itm_ship_grp_cd;ver_flg;lot_mng_typ;sublot_mng_typ | X79: itm_nm;sundry_itm_flg;dscnt_itm_flg;stk_mng_typ;asset_mng_typ;ship_unit_cd;bill_crryovr_times;slo_proc_typ;slo_proc_flg;ship_inst_typ;ship_term_cd;slo_sno1_flg;slo_sno2_flg;slo_sno3_flg;slo_sno4_flg;sno1_num_typ;sno2_num_typ;sno3_num_typ;sno4_num_typ;itm_ship_grp_cd;ver_flg;lot_mng_typ;sublot_mng_typ | Y79: MAC_ITM_IS_SRCH_TYP.NOT_ASSET3;itm_cd;itm_sub1;itm_sub2 | Z79: itm_is_srch_typ;itm_cd;itm_sub1;itm_sub2
A80: 10 | D80: slo.itm_nm# | E80: RI | G80: Item name | H80: 品名 | I80: E | J80: -
A81: 10 | D81: slo.cntry_org_cd# | E81: RI | G81: Place of origin cd. | H81: 原産地ＣＤ | I81: E | J81: -
A82: 10 | D82: slo.sno1# | E82: RI | G82: SEIBAN No. 1 | H82: 手配ＮＯ１ | I82: E | J82: -
A83: 10 | D83: slo.sno2# | E83: RI | G83: SEIBAN No. 2 | H83: 手配ＮＯ２ | I83: E | J83: -
A84: 10 | D84: slo.sno3# | E84: RI | G84: SEIBAN No. 3 | H84: 手配ＮＯ３ | I84: E | J84: -
A85: 10 | D85: slo.sno4# | E85: RI | G85: SEIBAN No. 4 | H85: 手配ＮＯ４ | I85: E | J85: -
A86: 10 | D86: slo.gd_cd# | E86: RI | G86: Grading cd. | H86: 格付ＣＤ | I86: E | J86: -
A87: 10 | D87: slo.trd_unit_cd# | E87: RI | G87: Transaction unit cd. | H87: 取引単位ＣＤ | I87: E | J87: - | V87: MA.MAUAL0010.ItmUnit | W87: trd_unit_dec_place | X87: dec_place | Y87: itm_cd;itm_sub1;itm_sub2;itm_sub3
A88: 10 | D88: slo.trd_unit_qty# | E88: RI | G88: Transaction unit qty. | H88: 取引単位数量 | I88: E | J88: -
A89: 10 | D89: slo.inc_tax_flg# | E89: RI | G89: Tax inclusive | H89: 内税 | I89: E | J89: -
A90: 10 | D90: slo.interim_flg# | E90: RI | G90: Temporary unit price | H90: 仮単価 | I90: E | J90: -
A91: 10 | D91: slo.trd_cur_upri# | E91: RI | G91: Unit price (Transaction currency) | H91: 取引通貨単価 | I91: E | J91: -
A92: 10 | D92: slo.trd_cur_amt# | E92: RI | G92: Amount (Transaction currency) | H92: 取引通貨金額 | I92: E | J92: -
A93: 10 | D93: slo.tax_fix_flg# | E93: RI | G93: Set tax | H93: 税指定 | I93: E | J93: -
A94: 10 | D94: slo.tax_rate# | E94: RI | G94: Tax rate | H94: 税率 | I94: E | J94: -
A95: 10 | D95: slo.tax_typ# | E95: RI | G95: Tax type | H95: 税区分 | I95: E | J95: -
A96: 10 | D96: slo.trd_cur_tax_amt# | E96: RI | G96: Tax amount (Transaction currency) | H96: 取引通貨税額 | I96: E | J96: -
A97: 10 | D97: slo.trd_cur_dscnt_amt# | E97: RI | G97: Discount amount (Transaction currency) | H97: 取引通貨値引額 | I97: E | J97: -
A98: 10 | D98: slo.dscnt_rsn_cd# | E98: RI | G98: Discount reason cd. | H98: 値引理由ＣＤ | I98: E | J98: -
A99: 10 | D99: slo.ship_wh_cd# | E99: RI | G99: Shipping warehouse cd. | H99: 出荷倉庫ＣＤ | I99: E | J99: -
... A142: 10 | D142: sls_upri_req_typ | E142: #MA.SLS_UPRI_REQ_TYP | G142: Sales unit price acquisition type (Master) | H142: 販売単価取得区分（マスタ） | I142: - | J142: -
A143: 10 | D143: cst_sls_usr_cd | E143: #MA.USR_CD | G143: Sales PIC cd. (Master) | H143: 売上担当者ＣＤ（マスタ） | I143: - | J143: - | V143: MA.MAUAL0010.Usr | W143: sls_usr_def_dpt_cd | X143: dpt_cd
A144: 10 | D144: cst_sls_dpt_cd | E144: #MA.DPT_CD | G144: Sales dept. cd. (master) | H144: 売上部門ＣＤ（マスタ） | I144: - | J144: -
A145: 10 | D145: ar_dpt_typ | E145: #MA.DPT_CD | G145: AR dept. type (Master) | H145: 債権部門区分（マスタ） | I145: - | J145: -
A146: 10 | D146: cst_tterm_cd1 | E146: #MA.TTERM_CD | I146: - | J146: -
...

Sheet 来歴
A1: 変更来歴
A3: Rev. | H3: 修正番号 | O3: 変更内容 | AQ3: 変更箇所
A4: 1 | O4: 初版
A5: 1.1 | H5: MS7031#003 | O5: SloRecvIf_Chk01_Dtlブロック ・以下、3つの項目を追加 cst_tterm_cd1、cst_tterm_cd2、cst_tterm_cd3 ・slo.cst_cd#のLIST_OUTとLIST_OUT_BASEにcst_tterm_cd1;cst_tterm_cd2;cst_tterm_cd3を追加 | AQ5: SloRecvIf_Chk01
A6: 1.2 | H6: MS7031#404 | O6: SloRecvIf_Chk01_Dtlブロック、SloRecvIf_Chk01_Slo_Upd01_Dtlブロックに以下の項目を追加 not_lg_mix_flg、not_lot_mix_flg、not_sublot_mix_flg SloRecvIf_Chk01_Dtlブロックに以下の項目を追加 lot_mng_typ SloRecvIf_Chk01_Dtlブロックにあるslo.itm_sub3#のLIST_OUT、LIST_OUT_BASEに以下の項目を追加 lot_mng_typ | AQ6: SloRecvIf_Chk01
A7: 1.3 | O7: 英語の名称を追記 | AQ7: 全般
