Workbook

Sheet LogicCommon
A2: オペレーション実装仕様書 | B2: ModuleID : | C2: MS | D2: LogicID : | E2: MSLAL7160 | F2: Pj.ID : | G2: MC
B3: SubModuleID : | C3: MSLA | D3: LogicClass : | E3: MSLAL_AccptRecvConvService | F3: SuperClassPj.ID :
D4: LogicName : | E4: 検収受信変換サービス | F4: SuperLogicID : | G4: PF.PFUDL5010
A5: 概要 :
A6: 詳細 :

Sheet AccptRecvConv_Conv01
A1: * | B1: * | D1: L | E1: 1
A2: * | D2: オペレーション実装仕様書 Operation Specification Implementation Sheet | E2: ModuleID : | F2: =IF(LogicCommon!C2="","",LogicCommon!C2) -> MS | G2: LogicID : | H2: =IF(LogicCommon!E2="","",LogicCommon!E2) -> MSLAL7160 | I2: Ope.ID : | J2: AccptRecvConv_Conv01 | K2: Pj.ID : | L2: =IF(LogicCommon!G2="","",LogicCommon!G2) -> MC | M2: Ope.Body : | N2: PF.PFUDL5010.ConvBase01
A3: * | D3: =IF(LogicCommon!A3="","",LogicCommon!A3) | E3: SubModuleID : | F3: =IF(LogicCommon!C3="","",LogicCommon!C3) -> MSLA | G3: LogicClass : | H3: =IF(LogicCommon!E3="","",LogicCommon!E3) -> MSLAL_AccptRecvConvService | I3: Ope.Method : | J3: @ | K3: SuperClassPj.ID : | L3: =IF(LogicCommon!G3="","",LogicCommon!G3) | O3: Gene.Type : | P3: ALL
A4: * | E4: Version : | F4: 000000 | G4: LogicName : | H4: =IF(LogicCommon!E4="","",LogicCommon!E4) -> 検収受信変換サービス | I4: Ope.Name : | J4: コード変換 | K4: SuperLogicID : | L4: =IF(LogicCommon!G4="","",LogicCommon!G4) -> PF.PFUDL5010 | M4: ImplOpe.ID:
A5: * | E5: ACType :
A6: * | D6: 概要 : | M6: ID | O6: ID | Q6: ID
A7: # | I7: U | K7: K | L7: o | N7: o | P7: o
A8: # | D8: ブロック名 Block Name | E8: 型 Type | G8: super/share | H8: 対象ブロック名 Target Block Name | L8: TargetName | N8: TargetName | P8: TargetName | T8: ブロック備考 Block Remarks
A9: # | D9: 項目名 Field Name | E9: 型 Type | F9: 桁 Digits | G9: フルネーム Full Name | H9: 日本語名 Japanese Name | I9: 上り項目 Request Message Field | J9: 下り項目 Response Message Field | R9: 条件および編集方法 Conditions and Editing Methods | T9: 項目備考 Field Remarks
A10: # | L10: 上り項目 Request Message Field | M10: 下り項目 Response Message Field | N10: 上り項目 Request Message Field | O10: 下り項目 Response Message Field | P10: 上り項目 Request Message Field | Q10: 下り項目 Response Message Field

Sheet AccptRecvConv_Conv02
A1: * | B1: * | D1: L | E1: 1
A2: * | D2: オペレーション実装仕様書 Operation Specification Implementation Sheet | E2: ModuleID : | F2: =IF(LogicCommon!C2="","",LogicCommon!C2) -> MS | G2: LogicID : | H2: =IF(LogicCommon!E2="","",LogicCommon!E2) -> MSLAL7160 | I2: Ope.ID : | J2: AccptRecvConv_Conv02 | K2: Pj.ID : | L2: =IF(LogicCommon!G2="","",LogicCommon!G2) -> MC | M2: Ope.Body : | N2: PF.PFUDL5010.ConvBase03
A3: * | D3: =IF(LogicCommon!A3="","",LogicCommon!A3) | E3: SubModuleID : | F3: =IF(LogicCommon!C3="","",LogicCommon!C3) -> MSLA | G3: LogicClass : | H3: =IF(LogicCommon!E3="","",LogicCommon!E3) -> MSLAL_AccptRecvConvService | I3: Ope.Method : | J3: @ | K3: SuperClassPj.ID : | L3: =IF(LogicCommon!G3="","",LogicCommon!G3) | O3: Gene.Type : | P3: ALL
A4: * | E4: Version : | F4: 000000 | G4: LogicName : | H4: =IF(LogicCommon!E4="","",LogicCommon!E4) -> 検収受信変換サービス | I4: Ope.Name : | J4: ファイル変換 | K4: SuperLogicID : | L4: =IF(LogicCommon!G4="","",LogicCommon!G4) -> PF.PFUDL5010 | M4: ImplOpe.ID:
A5: * | E5: ACType :
A6: * | D6: 概要 : | M6: ID | O6: ID | Q6: ID
A7: # | I7: U | K7: K | L7: o | N7: o | P7: o
A8: # | D8: ブロック名 Block Name | E8: 型 Type | G8: super/share | H8: 対象ブロック名 Target Block Name | L8: TargetName | N8: TargetName | P8: TargetName | T8: ブロック備考 Block Remarks
A9: # | D9: 項目名 Field Name | E9: 型 Type | F9: 桁 Digits | G9: フルネーム Full Name | H9: 日本語名 Japanese Name | I9: 上り項目 Request Message Field | J9: 下り項目 Response Message Field | R9: 条件および編集方法 Conditions and Editing Methods | T9: 項目備考 Field Remarks
A10: # | L10: 上り項目 Request Message Field | M10: 下り項目 Response Message Field | N10: 上り項目 Request Message Field | O10: 下り項目 Response Message Field | P10: 上り項目 Request Message Field | Q10: 下り項目 Response Message Field

Sheet AccptRecvConv_Conv03
A1: * | B1: * | D1: L | E1: 1
A2: * | D2: オペレーション実装仕様書 Operation Specification Implementation Sheet | E2: ModuleID : | F2: =IF(LogicCommon!C2="","",LogicCommon!C2) -> MS | G2: LogicID : | H2: =IF(LogicCommon!E2="","",LogicCommon!E2) -> MSLAL7160 | I2: Ope.ID : | J2: AccptRecvConv_Conv03 | K2: Pj.ID : | L2: =IF(LogicCommon!G2="","",LogicCommon!G2) -> MC | M2: Ope.Body : | N2: PF.PFUDL5010.ConvBase04
A3: * | E3: SubModuleID : | F3: =IF(LogicCommon!C3="","",LogicCommon!C3) -> MSLA | G3: LogicClass : | H3: =IF(LogicCommon!E3="","",LogicCommon!E3) -> MSLAL_AccptRecvConvService | I3: Ope.Method : | J3: @ | K3: SuperClassPj.ID : | L3: =IF(LogicCommon!G3="","",LogicCommon!G3) | O3: Gene.Type : | P3: ALL
A4: * | E4: Version : | F4: 000000 | G4: LogicName : | H4: =IF(LogicCommon!E4="","",LogicCommon!E4) -> 検収受信変換サービス | I4: Ope.Name : | J4: 形式変換(会社間取引) | K4: SuperLogicID : | L4: =IF(LogicCommon!G4="","",LogicCommon!G4) -> PF.PFUDL5010 | M4: ImplOpe.ID:
A5: * | E5: ACType :
A6: * | D6: 概要 : | M6: ID | O6: ID | Q6: ID
A7: # | I7: U | K7: K | L7: o | N7: o | P7: o
A8: # | D8: ブロック名 Block Name | E8: 型 Type | G8: super/share | H8: 対象ブロック名 Target Block Name | L8: TargetName | N8: TargetName | P8: TargetName | T8: ブロック備考 Block Remarks
A9: # | D9: 項目名 Field Name | E9: 型 Type | F9: 桁 Digits | G9: フルネーム Full Name | H9: 日本語名 Japanese Name | I9: 上り項目 Request Message Field | J9: 下り項目 Response Message Field | R9: 条件および編集方法 Conditions and Editing Methods | T9: 項目備考 Field Remarks
A10: # | L10: 上り項目 Request Message Field | M10: 下り項目 Response Message Field | N10: 上り項目 Request Message Field | O10: 下り項目 Response Message Field | P10: 上り項目 Request Message Field | Q10: 下り項目 Response Message Field
A11: 10 | B11: * | D11: Dtl | E11: L | G11: $share$ | H11: RPR:MS.MSLAR0060.Dtl
A12: 10 | D12: data_lno | E12: #MA.IF_DATA_LNO | G12: Data row No. | H12: データ行ＮＯ | I12: E
A13: 10 | D13: data_no | E13: #MA.IF_DATA_NO | G13: Data No. | H13: データＮＯ | I13: E
A14: 10 | D14: trd_typ_cd | E14: #MA.IF_TRD_TYP_CD | G14: Transaction type cd. | H14: 取引種別ＣＤ | I14: E
A15: 10 | D15: data_make_dt | E15: #MA.YMDHMS | G15: Creation date and time of source record | H15: 送信元レコード作成日時 | I15: E
A16: 10 | D16: data_crud_typ | E16: #MA.DATA_CRUD_TYP | G16: Data update type | H16: データ更新区分 | I16: E
A17: 10 | D17: po_no | E17: #MA.PO_NO | G17: PO No. | H17: 発注ＮＯ | I17: E
A18: 10 | D18: po_d_no | E18: #MA.PO_D_NO | G18: PO details No. | H18: 発注明細ＮＯ | I18: E
A19: 10 | D19: dlv_slip_no | E19: #MA.DLV_SLIP_NO | G19: Delivery note No. | H19: 納品書ＮＯ | I19: E
A20: 10 | D20: dlv_slip_d_no | E20: #MA.DLV_SLIP_D_NO | G20: Delivery note details No. | H20: 納品書明細ＮＯ | I20: E
A21: 10 | D21: iv_flg | E21: #MA.FLG | G21: Invoice flg. | H21: インボイスＦＬＧ | I21: E
A22: 10 | D22: abort_flg | E22: #MA.FLG | G22: Cancel remaining flg. | H22: 打切ＦＬＧ | I22: E
A23: 10 | D23: po_co_cntry_cd | E23: #MA.IF_EXT_SYS_CD | G23: PO PIC country cd. | H23: 発注者国ＣＤ | I23: E
... A155: 10 | D155: sub_dt5 | E155: #MA.DT | G155: Spare DATE column 5 | H155: 予備ＤＡＴＥ項目５ | I155: E

Sheet 来歴
A1: 変更来歴
A3: Rev. | H3: 修正番号 | O3: 変更内容 | AQ3: 変更箇所
A4: 1 | O4: 初版
A5: 1.1 | O5: 英語の名称を追記 | AQ5: 全般
