Workbook

Sheet LogicCommon
A2: オペレーション実装仕様書 | B2: ModuleID : | C2: MS | D2: LogicID : | E2: MSBHL5020 | F2: Pj.ID : | G2: MC
B3: SubModuleID : | C3: MSBH | D3: LogicClass : | E3: MSBHL_ApDtlRegService | F3: SuperClassPj.ID :
D4: LogicName : | E4: 買掛明細登録サービス | F4: SuperLogicID : | G4: MS.MSUDL5010
A5: 概要 :
A6: 詳細 :

Sheet ApDtl_Chk01
A1: * | B1: * | D1: L | E1: 1
A2: * | D2: オペレーション実装仕様書 Operation Specification Implementation Sheet | E2: ModuleID : | F2: =IF(LogicCommon!C2="","",LogicCommon!C2) -> MS | G2: LogicID : | H2: =IF(LogicCommon!E2="","",LogicCommon!E2) -> MSBHL5020 | I2: Ope.ID : | J2: ApDtl_Chk01 | K2: Pj.ID : | L2: =IF(LogicCommon!G2="","",LogicCommon!G2) -> MC | M2: Ope.Body : | N2: MA.MAUDL5010.Checker
A3: * | D3: =IF(LogicCommon!A3="","",LogicCommon!A3) | E3: SubModuleID : | F3: =IF(LogicCommon!C3="","",LogicCommon!C3) -> MSBH | G3: LogicClass : | H3: =IF(LogicCommon!E3="","",LogicCommon!E3) -> MSBHL_ApDtlRegService | I3: Ope.Method : | J3: =J2 -> ApDtl_Chk01 | K3: SuperClassPj.ID : | L3: =IF(LogicCommon!G3="","",LogicCommon!G3) | O3: Gene.Type : | P3: ALL
A4: * | E4: Version : | F4: 000000 | G4: LogicName : | H4: =IF(LogicCommon!E4="","",LogicCommon!E4) -> 買掛明細登録サービス | I4: Ope.Name : | J4: 更新前チェック | K4: SuperLogicID : | L4: =IF(LogicCommon!G4="","",LogicCommon!G4) -> MS.MSUDL5010 | M4: ImplOpe.ID:
A5: * | E5: ACType :
A6: * | D6: 概要 : | E6: 買掛明細の登録・更新・取消が可能かチェックをする。 | AD6: ID | AF6: ID | AH6: ID
A7: # | I7: U | K7: K | L7: K | M7: K | N7: K | O7: K | P7: K | Q7: K | R7: K | S7: K | T7: K | U7: K | V7: K | W7: K | X7: K | Y7: K | Z7: K | AA7: K | AB7: K | AC7: o | AE7: o | AG7: o
A8: # | D8: ブロック名 Block Name | E8: 型 Type | G8: super/share | H8: 対象ブロック名 Target Block Name | K8: REQ_UPD_CNT_CHK | L8: REQUIRED | M8: CHK_NUM | N8: SMALL_LARGE | O8: CHK_DT | P8: BEFORE_AFTER | Q8: CHK_PTN | R8: DUPLICATE | S8: TOO_MANY_INPUTS | T8: AT_LEAST_ONE | U8: ONLY_ONE_INPUT | V8: LIST_LOGIC | W8: LIST_OUT | X8: LIST_OUT_BASE | Y8: LIST_IN | Z8: LIST_IN_BASE | AA8: CONST | AB8: NULL_VAL | AC8: TargetName | AE8: TargetName | AG8: TargetName | AK8: ブロック備考 Block Remarks
A9: # | D9: 項目名 Field Name | E9: 型 Type | F9: 桁 Digits | G9: フルネーム Full Name | H9: 日本語名 Japanese Name | I9: 上り項目 Request Message Field | J9: 下り項目 Response Message Field | AI9: 条件および編集方法 Conditions and Editing Methods | AK9: 項目備考 Field Remarks
A10: # | AC10: 上り項目 Request Message Field | AD10: 下り項目 Response Message Field | AE10: 上り項目 Request Message Field | AF10: 下り項目 Response Message Field | AG10: 上り項目 Request Message Field | AH10: 下り項目 Response Message Field
A11: 10 | B11: * | D11: ApDtl_Chk01_Dtl | E11: L
A12: 10 | D12: peg_no | E12: #MA.INT | G12: Pegging No. | H12: 紐付けＮＯ | I12: E | J12: E
A13: 10 | D13: err_flg | E13: #MA.FLG | G13: Error | H13: エラー | I13: - | J13: E
A14: 10 | D14: data_crud_typ | E14: #MA.DATA_CRUD_TYP | G14: Data update type | H14: データ更新区分 | I14: E | J14: E
A15: 10 | D15: can_purc_act_d_seq | E15: #MA.SLIP_SEQ | G15: Purchase cancellation result details sequence number | H15: 取消仕入実績明細連番 | I15: - | J15: -
A16: 10 | D16: can_purc_act_seq | E16: #MA.SLIP_SEQ | G16: Purchase cancellation result sequence number | H16: 取消仕入実績連番 | I16: - | J16: -
A17: 10 | D17: old_purc_act_d_seq | E17: #MA.SLIP_SEQ | G17: Original slip purchase result details sequence number | H17: 元伝仕入実績明細連番 | I17: E | J17: E
A18: 10 | D18: can_ap_dpt_cd | E18: #MA.DPT_CD | G18: AP cancellation dept. cd. | H18: 取消債務部門ＣＤ | I18: - | J18: -
A19: 10 | D19: can_ac_dt | E19: #MA.DT | G19: Cancellation recording date | H19: 取消計上日 | I19: E | J19: E
A20: 10 | D20: can_ac_ym | E20: #MA.YM | G20: Cancellation recording month | H20: 取消計上年月 | I20: E | J20: E
A21: 10 | D21: can_pay_basis_dt | E21: #MA.DT | G21: Payment cancellation start date | H21: 取消支払起算日 | I21: E | J21: E
A22: 10 | D22: ncv_flg | E22: #MA.FLG | G22: Free of charge | H22: 無償 | I22: E | J22: E
A23: 10 | D23: accpt_dfct_flg | E23: #MA.FLG | G23: Defective acceptance | H23: 検収不良 | I23: E | J23: E
... A26: 10 | D26: to_ap_d_no | E26: #MA.AP_D_NO | G26: Transfer destination AP details No. | H26: 振替先買掛明細ＮＯ | I26: - | J26: -
A27: 10 | D27: apd | E27: R | F27: DBC:MS.MST_AP_D
A28: 10 | D28: apd.ap_d_no# | E28: RI | G28: AP details No. | H28: 買掛明細ＮＯ | I28: - | J28: -
A29: 10 | D29: apd.po_no# | E29: RI | G29: PO No. | H29: 発注ＮＯ | I29: - | J29: -
A30: 10 | D30: apd.po_d_no# | E30: RI | G30: PO details No. | H30: 発注明細ＮＯ | I30: - | J30: -
A31: 10 | D31: apd.purc_act_d_no# | E31: RI | G31: Purchase result details No. | H31: 仕入実績明細ＮＯ | I31: E | J31: E
A32: 10 | D32: apd.purc_act_d_seq# | E32: RI | G32: Purchase result details sequence number | H32: 仕入実績明細連番 | I32: - | J32: -
A33: 10 | D33: apd.purc_act_no# | E33: RI | G33: Purchase result No. | H33: 仕入実績ＮＯ | I33: E | J33: E
A34: 10 | D34: apd.purc_act_seq# | E34: RI | G34: Purchase result sequence number | H34: 仕入実績連番 | I34: - | J34: -
A35: 10 | D35: apd.purc_act_rev# | E35: RI | G35: Purchase result rev. number | H35: 仕入実績改訂番号 | I35: - | J35: -
A36: 10 | D36: apd.bp_dlv_slip_no# | E36: RI | G36: Vendor delivery note No. | H36: 業者納品書ＮＯ | I36: - | J36: -
A37: 10 | D37: apd.bp_dlv_slip_d_no# | E37: RI | G37: Vendor delivery note details No. | H37: 業者納品書明細ＮＯ | I37: - | J37: -
A38: 10 | D38: apd.rcpt_iv_no# | E38: RI | G38: Purchase invoice No. | H38: 受領インボイスＮＯ | I38: - | J38: -
A39: 10 | D39: apd.rcpt_iv_mng_no# | E39: RI | G39: Purchase invoice management No. | H39: 受領インボイス管理ＮＯ | I39: E | J39: E
... A112: 10 | D112: apd.outsrc_flg# | E112: RI | G112: Subcontracting | H112: 外注 | I112: - | J112: -
D113: 詳細 :

Sheet ApDtl_Chk03
A1: * | B1: * | D1: L | E1: 1
A2: * | D2: オペレーション実装仕様書 Operation Specification Implementation Sheet | E2: ModuleID : | F2: =IF(LogicCommon!C2="","",LogicCommon!C2) -> MS | G2: LogicID : | H2: =IF(LogicCommon!E2="","",LogicCommon!E2) -> MSBHL5020 | I2: Ope.ID : | J2: ApDtl_Chk03 | K2: Pj.ID : | L2: =IF(LogicCommon!G2="","",LogicCommon!G2) -> MC | M2: Ope.Body : | N2: MA.MAUDL5010.Checker
A3: * | D3: =IF(LogicCommon!A3="","",LogicCommon!A3) | E3: SubModuleID : | F3: =IF(LogicCommon!C3="","",LogicCommon!C3) -> MSBH | G3: LogicClass : | H3: =IF(LogicCommon!E3="","",LogicCommon!E3) -> MSBHL_ApDtlRegService | I3: Ope.Method : | J3: =J2 -> ApDtl_Chk03 | K3: SuperClassPj.ID : | L3: =IF(LogicCommon!G3="","",LogicCommon!G3) | O3: Gene.Type : | P3: ALL
A4: * | E4: Version : | F4: 000000 | G4: LogicName : | H4: =IF(LogicCommon!E4="","",LogicCommon!E4) -> 買掛明細登録サービス | I4: Ope.Name : | J4: 残高振替前チェック | K4: SuperLogicID : | L4: =IF(LogicCommon!G4="","",LogicCommon!G4) -> MS.MSUDL5010 | M4: ImplOpe.ID:
A5: * | E5: ACType :
A6: * | D6: 概要 : | E6: 残高振替に伴う買掛明細の登録が可能かチェックをする。 | AD6: ID | AF6: ID | AH6: ID
A7: # | I7: U | K7: K | L7: K | M7: K | N7: K | O7: K | P7: K | Q7: K | R7: K | S7: K | T7: K | U7: K | V7: K | W7: K | X7: K | Y7: K | Z7: K | AA7: K | AB7: K | AC7: o | AE7: o | AG7: o
A8: # | D8: ブロック名 Block Name | E8: 型 Type | G8: super/share | H8: 対象ブロック名 Target Block Name | K8: REQ_UPD_CNT_CHK | L8: REQUIRED | M8: CHK_NUM | N8: SMALL_LARGE | O8: CHK_DT | P8: BEFORE_AFTER | Q8: CHK_PTN | R8: DUPLICATE | S8: TOO_MANY_INPUTS | T8: AT_LEAST_ONE | U8: ONLY_ONE_INPUT | V8: LIST_LOGIC | W8: LIST_OUT | X8: LIST_OUT_BASE | Y8: LIST_IN | Z8: LIST_IN_BASE | AA8: CONST | AB8: NULL_VAL | AC8: TargetName | AE8: TargetName | AG8: TargetName | AK8: ブロック備考 Block Remarks
A9: # | D9: 項目名 Field Name | E9: 型 Type | F9: 桁 Digits | G9: フルネーム Full Name | H9: 日本語名 Japanese Name | I9: 上り項目 Request Message Field | J9: 下り項目 Response Message Field | AI9: 条件および編集方法 Conditions and Editing Methods | AK9: 項目備考 Field Remarks
A10: # | AC10: 上り項目 Request Message Field | AD10: 下り項目 Response Message Field | AE10: 上り項目 Request Message Field | AF10: 下り項目 Response Message Field | AG10: 上り項目 Request Message Field | AH10: 下り項目 Response Message Field
A11: 10 | B11: * | D11: ApDtl_Chk03_Dtl | E11: L | G11: $share$ | H11: MS.MSBHL5020.ApDtl_Chk01.ApDtl_Chk01_Dtl
A12: 10 | D12: peg_no | E12: #MA.INT | G12: Pegging No. | H12: 紐付けＮＯ | I12: E | J12: E
A13: 10 | D13: err_flg | E13: #MA.FLG | G13: Error | H13: エラー | I13: - | J13: E
A14: 10 | D14: apd | E14: R | F14: DBC:MS.MST_AP_D
A15: 10 | D15: apd.bsppl_cd# | E15: RI | G15: Scheduled payee cd. | H15: 支払予定管理先ＣＤ | I15: E | J15: -
A16: 10 | D16: apd.pay_crryovr_times# | E16: RI | G16: Payment carry-over count | H16: 支払繰越回数 | I16: E | J16: -
A17: 10 | D17: apd.pay_basis_dt# | E17: RI | G17: Payment base date | H17: 支払起算日 | I17: E | J17: -
D18: 詳細 :

Sheet ApDtl_Upd01
A1: * | B1: * | D1: L | E1: 1
A2: * | D2: オペレーション実装仕様書 Operation Specification Implementation Sheet | E2: ModuleID : | F2: =IF(LogicCommon!C2="","",LogicCommon!C2) -> MS | G2: LogicID : | H2: =IF(LogicCommon!E2="","",LogicCommon!E2) -> MSBHL5020 | I2: Ope.ID : | J2: ApDtl_Upd01 | K2: Pj.ID : | L2: =IF(LogicCommon!G2="","",LogicCommon!G2) -> MC | M2: Ope.Body : | N2: "mcframe.serverMAUD.MAUDL5010.MAUDL_Operation"
A3: * | D3: =IF(LogicCommon!A3="","",LogicCommon!A3) | E3: SubModuleID : | F3: =IF(LogicCommon!C3="","",LogicCommon!C3) -> MSBH | G3: LogicClass : | H3: =IF(LogicCommon!E3="","",LogicCommon!E3) -> MSBHL_ApDtlRegService | I3: Ope.Method : | J3: =J2 -> ApDtl_Upd01 | K3: SuperClassPj.ID : | L3: =IF(LogicCommon!G3="","",LogicCommon!G3) | O3: Gene.Type : | P3: ALL
A4: * | E4: Version : | F4: 000000 | G4: LogicName : | H4: =IF(LogicCommon!E4="","",LogicCommon!E4) -> 買掛明細登録サービス | I4: Ope.Name : | J4: 更新 | K4: SuperLogicID : | L4: =IF(LogicCommon!G4="","",LogicCommon!G4) -> MS.MSUDL5010 | M4: ImplOpe.ID:
A5: * | E5: ACType :
A6: * | D6: 概要 : | E6: 買掛明細を登録・更新・取消する。 | M6: ID | O6: ID | Q6: ID
A7: # | I7: U | K7: K | L7: o | N7: o | P7: o
A8: # | D8: ブロック名 Block Name | E8: 型 Type | G8: super/share | H8: 対象ブロック名 Target Block Name | L8: TargetName | N8: TargetName | P8: TargetName | T8: ブロック備考 Block Remarks
A9: # | D9: 項目名 Field Name | E9: 型 Type | F9: 桁 Digits | G9: フルネーム Full Name | H9: 日本語名 Japanese Name | I9: 上り項目 Request Message Field | J9: 下り項目 Response Message Field | R9: 条件および編集方法 Conditions and Editing Methods | T9: 項目備考 Field Remarks
A10: # | L10: 上り項目 Request Message Field | M10: 下り項目 Response Message Field | N10: 上り項目 Request Message Field | O10: 下り項目 Response Message Field | P10: 上り項目 Request Message Field | Q10: 下り項目 Response Message Field
A11: 10 | B11: * | D11: ApDtl_Upd01_Dtl | E11: L | G11: $share$ | H11: MS.MSBHL5020.ApDtl_Chk01.ApDtl_Chk01_Dtl
A12: 10 | D12: peg_no | E12: #MA.INT | G12: Pegging No. | H12: 紐付けＮＯ | I12: E | J12: -
A13: 10 | D13: data_crud_typ | E13: #MA.DATA_CRUD_TYP | G13: Data update type | H13: データ更新区分 | I13: E | J13: -
A14: 10 | D14: can_purc_act_d_seq | E14: #MA.SLIP_SEQ | G14: Purchase cancellation result details sequence number | H14: 取消仕入実績明細連番 | I14: E | J14: -
A15: 10 | D15: can_purc_act_seq | E15: #MA.SLIP_SEQ | G15: Purchase cancellation result sequence number | H15: 取消仕入実績連番 | I15: E | J15: -
A16: 10 | D16: old_purc_act_d_seq | E16: #MA.SLIP_SEQ | G16: Original slip purchase result details sequence number | H16: 元伝仕入実績明細連番 | I16: E | J16: -
A17: 10 | D17: can_ap_dpt_cd | E17: #MA.DPT_CD | G17: AP cancellation dept. cd. | H17: 取消債務部門ＣＤ | I17: E | J17: -
A18: 10 | D18: can_ac_dt | E18: #MA.DT | G18: Cancellation recording date | H18: 取消計上日 | I18: E | J18: -
A19: 10 | D19: can_ac_ym | E19: #MA.YM | G19: Cancellation recording month | H19: 取消計上年月 | I19: E | J19: -
A20: 10 | D20: can_pay_basis_dt | E20: #MA.DT | G20: Payment cancellation start date | H20: 取消支払起算日 | I20: E | J20: -
A21: 10 | D21: ncv_flg | E21: #MA.FLG | G21: Free of charge | H21: 無償 | I21: E | J21: -
A22: 10 | D22: accpt_dfct_flg | E22: #MA.FLG | G22: Defective acceptance | H22: 検収不良 | I22: E | J22: -
A23: 10 | D23: base_dt | E23: #MA.DT | G23: Base date | H23: 基準日 | I23: - | J23: -
A24: 10 | D24: apd | E24: R | F24: DBC:MS.MST_AP_D
A25: 10 | D25: apd.ap_d_no# | E25: RI | G25: AP details No. | H25: 買掛明細ＮＯ | I25: - | J25: -
A26: 10 | D26: apd.po_no# | E26: RI | G26: PO No. | H26: 発注ＮＯ | I26: E | J26: -
A27: 10 | D27: apd.po_d_no# | E27: RI | G27: PO details No. | H27: 発注明細ＮＯ | I27: E | J27: -
A28: 10 | D28: apd.purc_act_d_no# | E28: RI | G28: Purchase result details No. | H28: 仕入実績明細ＮＯ | I28: E | J28: -
A29: 10 | D29: apd.purc_act_d_seq# | E29: RI | G29: Purchase result details sequence number | H29: 仕入実績明細連番 | I29: E | J29: -
A30: 10 | D30: apd.purc_act_no# | E30: RI | G30: Purchase result No. | H30: 仕入実績ＮＯ | I30: E | J30: -
A31: 10 | D31: apd.purc_act_seq# | E31: RI | G31: Purchase result sequence number | H31: 仕入実績連番 | I31: E | J31: -
A32: 10 | D32: apd.purc_act_rev# | E32: RI | G32: Purchase result rev. number | H32: 仕入実績改訂番号 | I32: E | J32: -
A33: 10 | D33: apd.bp_dlv_slip_no# | E33: RI | G33: Vendor delivery note No. | H33: 業者納品書ＮＯ | I33: E | J33: -
A34: 10 | D34: apd.bp_dlv_slip_d_no# | E34: RI | G34: Vendor delivery note details No. | H34: 業者納品書明細ＮＯ | I34: E | J34: -
A35: 10 | D35: apd.rcpt_iv_no# | E35: RI | G35: Purchase invoice No. | H35: 受領インボイスＮＯ | I35: E | J35: -
A36: 10 | D36: apd.rcpt_iv_mng_no# | E36: RI | G36: Purchase invoice management No. | H36: 受領インボイス管理ＮＯ | I36: E | J36: -
... A109: 10 | D109: apd.outsrc_flg# | E109: RI | G109: Subcontracting | H109: 外注 | I109: E | J109: -
D110: 詳細 :

Sheet ApDtl_Upd02
A1: * | B1: * | D1: L | E1: 1
A2: * | D2: オペレーション実装仕様書 Operation Specification Implementation Sheet | E2: ModuleID : | F2: =IF(LogicCommon!C2="","",LogicCommon!C2) -> MS | G2: LogicID : | H2: =IF(LogicCommon!E2="","",LogicCommon!E2) -> MSBHL5020 | I2: Ope.ID : | J2: ApDtl_Upd02 | K2: Pj.ID : | L2: =IF(LogicCommon!G2="","",LogicCommon!G2) -> MC | M2: Ope.Body : | N2: "mcframe.serverMAUD.MAUDL5010.MAUDL_Operation"
A3: * | D3: =IF(LogicCommon!A3="","",LogicCommon!A3) | E3: SubModuleID : | F3: =IF(LogicCommon!C3="","",LogicCommon!C3) -> MSBH | G3: LogicClass : | H3: =IF(LogicCommon!E3="","",LogicCommon!E3) -> MSBHL_ApDtlRegService | I3: Ope.Method : | J3: =J2 -> ApDtl_Upd02 | K3: SuperClassPj.ID : | L3: =IF(LogicCommon!G3="","",LogicCommon!G3) | O3: Gene.Type : | P3: ALL
A4: * | E4: Version : | F4: 000000 | G4: LogicName : | H4: =IF(LogicCommon!E4="","",LogicCommon!E4) -> 買掛明細登録サービス | I4: Ope.Name : | J4: 一部支払・全額繰越 | K4: SuperLogicID : | L4: =IF(LogicCommon!G4="","",LogicCommon!G4) -> MS.MSUDL5010 | M4: ImplOpe.ID:
A5: * | E5: ACType :
A6: * | D6: 概要 : | E6: 一部支払、もしくは全額支払に対する繰越処理を行う。 | M6: ID | O6: ID | Q6: ID
A7: # | I7: U | K7: K | L7: o | N7: o | P7: o
A8: # | D8: ブロック名 Block Name | E8: 型 Type | G8: super/share | H8: 対象ブロック名 Target Block Name | L8: TargetName | N8: TargetName | P8: TargetName | T8: ブロック備考 Block Remarks
A9: # | D9: 項目名 Field Name | E9: 型 Type | F9: 桁 Digits | G9: フルネーム Full Name | H9: 日本語名 Japanese Name | I9: 上り項目 Request Message Field | J9: 下り項目 Response Message Field | R9: 条件および編集方法 Conditions and Editing Methods | T9: 項目備考 Field Remarks
A10: # | L10: 上り項目 Request Message Field | M10: 下り項目 Response Message Field | N10: 上り項目 Request Message Field | O10: 下り項目 Response Message Field | P10: 上り項目 Request Message Field | Q10: 下り項目 Response Message Field
A11: 10 | B11: * | D11: ApDtl_Upd02_Dtl | E11: L
A12: 10 | D12: peg_no | E12: #MA.INT | G12: Pegging No. | H12: 紐付けＮＯ | I12: E | J12: E
A13: 10 | D13: crryovr_src_ap_d_no | E13: #MA.AP_D_NO | G13: Carry-over source AP details No. | H13: 繰越元買掛明細ＮＯ | I13: E | J13: -
A14: 10 | D14: pay_mtd_typ | E14: #MS.PAY_MTD_TYP | G14: Payment method type | H14: 支払方式区分 | I14: E | J14: -
A15: 10 | D15: pay_crryovr_times | E15: #MA.CRRYOVR_TIMES | G15: Current carry-over count | H15: 今回繰越回数 | I15: E | J15: -
A16: 10 | D16: co_bsppl_cl_day | E16: #MA.CL_DAY | G16: Closing day after carry-over | H16: 繰越後締日 | I16: E | J16: -
A17: 10 | D17: co_bsppl_cl_dt | E17: #MA.DT | G17: Closing year, month and date after carry-over | H17: 繰越後締年月日 | I17: E | J17: -
A18: 10 | D18: co_bsppl_dpt_cd | E18: #MA.DPT_CD | G18: Scheduled payee dept. cd. after carry-over | H18: 繰越後支払予定管理先部門ＣＤ | I18: E | J18: -
A19: 10 | D19: pay_amt | E19: #MA.MONEY | G19: Current payment amount | H19: 今回支払金額 | I19: E | J19: -
A20: 10 | D20: pay_tax_amt | E20: #MA.MONEY | G20: Current payment tax amount | H20: 今回支払税額 | I20: E | J20: -
A21: 10 | D21: pay_wtax_amt | E21: #MA.MONEY | G21: Current payment withholding tax amount | H21: 今回支払源泉税額 | I21: E | J21: -
A22: 10 | D22: pay_chk_no | E22: #MA.PAY_CHK_NO | G22: Payment collation No. | H22: 支払照合ＮＯ | I22: E | J22: -
A23: 10 | D23: pay_chk_mng_no | E23: #MA.PAY_CHK_MNG_NO | G23: Payment collation management No. | H23: 支払照合管理ＮＯ | I23: E | J23: -
... A30: 10 | D30: pay_base_cur_onr_prov_amt | E30: #MA.MONEY | G30: Current payment chargeable supply amount (Base currency) | H30: 今回支払基準通貨有償支給金額 | I30: - | J30: -
D31: 詳細 :

Sheet ApDtl_Upd03
A1: * | B1: * | D1: L | E1: 1
A2: * | D2: オペレーション実装仕様書 Operation Specification Implementation Sheet | E2: ModuleID : | F2: =IF(LogicCommon!C2="","",LogicCommon!C2) -> MS | G2: LogicID : | H2: =IF(LogicCommon!E2="","",LogicCommon!E2) -> MSBHL5020 | I2: Ope.ID : | J2: ApDtl_Upd03 | K2: Pj.ID : | L2: =IF(LogicCommon!G2="","",LogicCommon!G2) -> MC | M2: Ope.Body : | N2: "mcframe.serverMAUD.MAUDL5010.MAUDL_Operation"
A3: * | D3: =IF(LogicCommon!A3="","",LogicCommon!A3) | E3: SubModuleID : | F3: =IF(LogicCommon!C3="","",LogicCommon!C3) -> MSBH | G3: LogicClass : | H3: =IF(LogicCommon!E3="","",LogicCommon!E3) -> MSBHL_ApDtlRegService | I3: Ope.Method : | J3: =J2 -> ApDtl_Upd03 | K3: SuperClassPj.ID : | L3: =IF(LogicCommon!G3="","",LogicCommon!G3) | O3: Gene.Type : | P3: ALL
A4: * | E4: Version : | F4: 000000 | G4: LogicName : | H4: =IF(LogicCommon!E4="","",LogicCommon!E4) -> 買掛明細登録サービス | I4: Ope.Name : | J4: 残高振替 | K4: SuperLogicID : | L4: =IF(LogicCommon!G4="","",LogicCommon!G4) -> MS.MSUDL5010 | M4: ImplOpe.ID:
A5: * | E5: ACType :
A6: * | D6: 概要 : | E6: 残高振替に伴う買掛明細を登録する。 | M6: ID | O6: ID | Q6: ID
A7: # | I7: U | K7: K | L7: o | N7: o | P7: o
A8: # | D8: ブロック名 Block Name | E8: 型 Type | G8: super/share | H8: 対象ブロック名 Target Block Name | L8: TargetName | N8: TargetName | P8: TargetName | T8: ブロック備考 Block Remarks
A9: # | D9: 項目名 Field Name | E9: 型 Type | F9: 桁 Digits | G9: フルネーム Full Name | H9: 日本語名 Japanese Name | I9: 上り項目 Request Message Field | J9: 下り項目 Response Message Field | R9: 条件および編集方法 Conditions and Editing Methods | T9: 項目備考 Field Remarks
A10: # | L10: 上り項目 Request Message Field | M10: 下り項目 Response Message Field | N10: 上り項目 Request Message Field | O10: 下り項目 Response Message Field | P10: 上り項目 Request Message Field | Q10: 下り項目 Response Message Field
A11: 10 | B11: * | D11: ApDtl_Upd03_Dtl | E11: L | G11: $share$ | H11: MS.MSBHL5020.ApDtl_Chk01.ApDtl_Chk01_Dtl
A12: 10 | D12: peg_no | E12: #MA.INT | G12: Pegging No. | H12: 紐付けＮＯ | I12: E | J12: E
A13: 10 | D13: ap_appl_schd_no | E13: #MA.AP_APPL_SCHD_NO | G13: AP reconciliation schedule No. | H13: 買掛消込予定ＮＯ | I13: E | J13: E
A14: 10 | D14: to_ap_d_no | E14: #MA.AP_D_NO | G14: Transfer destination AP details No. | H14: 振替先買掛明細ＮＯ | I14: - | J14: E
A15: 10 | D15: apd | E15: R | F15: DBC:MS.MST_AP_D
A16: 10 | D16: apd.ap_d_no# | E16: RI | G16: AP details No. | H16: 買掛明細ＮＯ | I16: E | J16: E
A17: 10 | D17: apd.asppl_cd# | E17: RI | G17: AP supplier cd. | H17: 買掛先ＣＤ | I17: E | J17: -
A18: 10 | D18: apd.bsppl_cd# | E18: RI | G18: Scheduled payee cd. | H18: 支払予定管理先ＣＤ | I18: E | J18: -
A19: 10 | D19: apd.bsppl_dpt_cd# | E19: RI | G19: Scheduled payee dept. cd. | H19: 支払予定管理先部門ＣＤ | I19: E | J19: -
A20: 10 | D20: apd.ap_dpt_cd# | E20: RI | G20: AP dept. cd. | H20: 債務部門ＣＤ | I20: E | J20: -
A21: 10 | D21: apd.wrk_no# | E21: RI | G21: Sales project No. | H21: 案件ＮＯ | I21: E | J21: -
A22: 10 | D22: apd.act_dt# | E22: RI | G22: Actual date | H22: 実績日 | I22: E | J22: -
A23: 10 | D23: apd.ac_dt# | E23: RI | G23: Recording date | H23: 計上日 | I23: E | J23: -
A24: 10 | D24: apd.pay_crryovr_times# | E24: RI | G24: Payment carry-over count | H24: 支払繰越回数 | I24: E | J24: -
A25: 10 | D25: apd.pay_basis_dt# | E25: RI | G25: Payment base date | H25: 支払起算日 | I25: E | J25: -
A26: 10 | D26: apd.pay_schd_dt# | E26: RI | G26: Scheduled payment date | H26: 支払予定日 | I26: E | J26: -
A27: 10 | D27: apd.xrate# | E27: RI | G27: Exchange rate | H27: 為替レート | I27: E | J27: -
... A29: 10 | D29: apd.base_cur_amt# | E29: RI | G29: Amount (Base currency) | H29: 基準通貨金額 | I29: E | J29: -
D30: 詳細 :

Sheet ApDtl_Del01
A1: * | B1: * | D1: L | E1: 1
A2: * | D2: オペレーション実装仕様書 Operation Specification Implementation Sheet | E2: ModuleID : | F2: =IF(LogicCommon!C2="","",LogicCommon!C2) -> MS | G2: LogicID : | H2: =IF(LogicCommon!E2="","",LogicCommon!E2) -> MSBHL5020 | I2: Ope.ID : | J2: ApDtl_Del01 | K2: Pj.ID : | L2: =IF(LogicCommon!G2="","",LogicCommon!G2) -> MC | M2: Ope.Body : | N2: "mcframe.serverMAUD.MAUDL5010.MAUDL_Operation"
A3: * | D3: =IF(LogicCommon!A3="","",LogicCommon!A3) | E3: SubModuleID : | F3: =IF(LogicCommon!C3="","",LogicCommon!C3) -> MSBH | G3: LogicClass : | H3: =IF(LogicCommon!E3="","",LogicCommon!E3) -> MSBHL_ApDtlRegService | I3: Ope.Method : | J3: =J2 -> ApDtl_Del01 | K3: SuperClassPj.ID : | L3: =IF(LogicCommon!G3="","",LogicCommon!G3) | O3: Gene.Type : | P3: ALL
A4: * | E4: Version : | F4: 000000 | G4: LogicName : | H4: =IF(LogicCommon!E4="","",LogicCommon!E4) -> 買掛明細登録サービス | I4: Ope.Name : | J4: 一部支払・全額繰越取消 | K4: SuperLogicID : | L4: =IF(LogicCommon!G4="","",LogicCommon!G4) -> MS.MSUDL5010 | M4: ImplOpe.ID:
A5: * | E5: ACType :
A6: * | D6: 概要 : | E6: 一部支払、もしくは全額支払に対する繰越処理を取り消す。 | M6: ID | O6: ID | Q6: ID
A7: # | I7: U | K7: K | L7: o | N7: o | P7: o
A8: # | D8: ブロック名 Block Name | E8: 型 Type | G8: super/share | H8: 対象ブロック名 Target Block Name | L8: TargetName | N8: TargetName | P8: TargetName | T8: ブロック備考 Block Remarks
A9: # | D9: 項目名 Field Name | E9: 型 Type | F9: 桁 Digits | G9: フルネーム Full Name | H9: 日本語名 Japanese Name | I9: 上り項目 Request Message Field | J9: 下り項目 Response Message Field | R9: 条件および編集方法 Conditions and Editing Methods | T9: 項目備考 Field Remarks
A10: # | L10: 上り項目 Request Message Field | M10: 下り項目 Response Message Field | N10: 上り項目 Request Message Field | O10: 下り項目 Response Message Field | P10: 上り項目 Request Message Field | Q10: 下り項目 Response Message Field
A11: 10 | B11: * | D11: ApDtl_Del01_Dtl | E11: L
A12: 10 | D12: peg_no | E12: #MA.INT | G12: Pegging No. | H12: 紐付けＮＯ | I12: E | J12: -
A13: 10 | D13: ap_d_no | E13: #MA.AP_D_NO | G13: AP details No. | H13: 買掛明細ＮＯ | I13: E | J13: -
D14: 詳細 :

Sheet 来歴
A1: 変更来歴
A3: Rev. | H3: 修正番号 | O3: 変更内容 | AQ3: 変更箇所
A4: 1 | O4: 初版
A5: 1.1 | O5: 英語の名称を追記 | AQ5: 全般
