Workbook

Sheet LogicCommon
A2: オペレーション実装仕様書 | B2: ModuleID : | C2: MS | D2: LogicID : | E2: MSBEL5540 | F2: Pj.ID : | G2: MC
B3: SubModuleID : | C3: MSBE | D3: LogicClass : | E3: MSBEL_ShipActService | F3: SuperClassPj.ID :
D4: LogicName : | E4: 出荷実績サービス | F4: SuperLogicID : | G4: MS.MSUDL5010
A5: 概要 :
A6: 詳細 :

Sheet ShipAct_Upd01
A1: * | B1: * | D1: L | E1: 1
A2: * | D2: オペレーション実装仕様書 Operation Specification Implementation Sheet | E2: ModuleID : | F2: =IF(LogicCommon!C2="","",LogicCommon!C2) -> MS | G2: LogicID : | H2: =IF(LogicCommon!E2="","",LogicCommon!E2) -> MSBEL5540 | I2: Ope.ID : | J2: ShipAct_Upd01 | K2: Pj.ID : | L2: =IF(LogicCommon!G2="","",LogicCommon!G2) -> MC | M2: Ope.Body : | N2: "mcframe.serverMAUD.MAUDL5010.MAUDL_Operation"
A3: * | D3: =IF(LogicCommon!A3="","",LogicCommon!A3) | E3: SubModuleID : | F3: =IF(LogicCommon!C3="","",LogicCommon!C3) -> MSBE | G3: LogicClass : | H3: =IF(LogicCommon!E3="","",LogicCommon!E3) -> MSBEL_ShipActService | I3: Ope.Method : | J3: =J2 -> ShipAct_Upd01 | K3: SuperClassPj.ID : | L3: =IF(LogicCommon!G3="","",LogicCommon!G3) | O3: Gene.Type : | P3: ALL
A4: * | E4: Version : | F4: 000000 | G4: LogicName : | H4: =IF(LogicCommon!E4="","",LogicCommon!E4) -> 出荷実績サービス | I4: Ope.Name : | J4: 更新 | K4: SuperLogicID : | L4: =IF(LogicCommon!G4="","",LogicCommon!G4) -> MS.MSUDL5010 | M4: ImplOpe.ID:
A5: * | E5: ACType :
A6: * | D6: 概要 : | E6: 出荷実績を登録・更新・削除する。 | M6: ID | O6: ID | Q6: ID
A7: # | I7: U | K7: K | L7: o | N7: o | P7: o
A8: # | D8: ブロック名 Block Name | E8: 型 Type | G8: super/share | H8: 対象ブロック名 Target Block Name | K8: CONST | L8: TargetName | N8: TargetName | P8: TargetName | T8: ブロック備考 Block Remarks
A9: # | D9: 項目名 Field Name | E9: 型 Type | F9: 桁 Digits | G9: フルネーム Full Name | H9: 日本語名 Japanese Name | I9: 上り項目 Request Message Field | J9: 下り項目 Response Message Field | R9: 条件および編集方法 Conditions and Editing Methods | T9: 項目備考 Field Remarks
A10: # | L10: 上り項目 Request Message Field | M10: 下り項目 Response Message Field | N10: 上り項目 Request Message Field | O10: 下り項目 Response Message Field | P10: 上り項目 Request Message Field | Q10: 下り項目 Response Message Field
A11: 10 | B11: * | D11: ShipAct_Hdr | E11: L
A12: 10 | D12: data_crud_typ | E12: #MA.DATA_CRUD_TYP | G12: Data update type | H12: データ更新区分 | I12: E | J12: -
A13: 10 | D13: sa | E13: R | F13: DBC:MS.MST_SHIP_ACT | G13: Shipping result | H13: 出荷実績
A14: 10 | D14: sa.ship_act_no# | E14: RI | G14: Shipping result No. | H14: 出荷実績ＮＯ | I14: E | J14: E
A15: 10 | D15: sa.ship_act_rev# | E15: RI | G15: Shipping result rev. number | H15: 出荷実績改訂番号 | I15: - | J15: E
A16: 10 | D16: sa.ship_inst_no# | E16: RI | G16: Shipping order No. | H16: 出荷指図ＮＯ | I16: E | J16: -
A17: 10 | D17: sa.ac_dt# | E17: RI | G17: Recording date | H17: 計上日 | I17: E | J17: -
A18: 10 | D18: sa.ship_tm# | E18: RI | G18: Shipping date and time | H18: 出荷日時 | I18: E | J18: -
A19: 10 | D19: sa.dlv_tm# | E19: RI | G19: Delivery date and time | H19: 納品日時 | I19: E | J19: -
A20: 10 | D20: can_ac_dt | E20: #MA.DT | G20: Cancellation recording date | H20: 取消計上日 | I20: E | J20: -
A21: 10 | D21: sa.rqst_dpt_cd# | E21: RI | G21: Requesting dept. cd. | H21: 依頼元部門ＣＤ | I21: E | J21: -
A22: 10 | D22: sa.rqst_usr_cd# | E22: RI | G22: Requesting PIC cd. | H22: 依頼元担当者ＣＤ | I22: E | J22: -
A23: 10 | D23: sa.ship_fr_lg_grp_cd# | E23: RI | G23: Shipping point distribution group cd. | H23: 出荷元物流グループＣＤ | I23: E | J23: -
A24: 10 | D24: sa.wg_cd# | E24: RI | G24: WG cd. | H24: ＷＧ ＣＤ | I24: E | J24: -
A25: 10 | D25: sa.ship_term_cd# | E25: RI | G25: Shipping conditions cd. | H25: 出荷条件ＣＤ | I25: E | J25: -
... A65: 10 | D65: dlv_slip_no | E65: #MA.DLV_SLIP_NO | G65: Delivery note No. | H65: 納品書ＮＯ | I65: E | J65: -
A67: 20 | B67: * | D67: ShipAct_Dtl | E67: L
A68: 20 | D68: data_crud_typ | E68: #MA.DATA_CRUD_TYP | G68: Data update type | H68: データ更新区分 | I68: E | J68: -
A69: 20 | D69: sad | E69: R | F69: DBC:MS.MST_SHIP_ACT_D | G69: Shipping result details | H69: 出荷実績明細
A70: 20 | D70: sad.ship_act_d_no# | E70: RI | G70: Shipping result details No. | H70: 出荷実績明細ＮＯ | I70: E | J70: E
A71: 20 | D71: sad.ship_act_no# | E71: RI | G71: Shipping result No. | H71: 出荷実績ＮＯ | I71: - | J71: E
A72: 20 | D72: sad.disp_seq# | E72: RI | G72: Display order | H72: 表示順 | I72: E | J72: -
A73: 20 | D73: sad.ship_alloc_sts_no# | E73: RI | G73: Shipping allocation status No. | H73: 出荷引当状況ＮＯ | I73: E | J73: -
A74: 20 | D74: sad.trd_cd# | E74: RI | G74: Transaction cd. | H74: 取引ＣＤ | I74: E | J74: -
A75: 20 | D75: sad.trd_ptn_typ# | E75: RI | G75: Transaction pattern type | H75: 取引パタン区分 | I75: E | J75: -
A76: 20 | D76: sad.ship_loc_cd# | E76: RI | G76: Shipping location cd. | H76: 出荷場所ＣＤ | I76: E | J76: -
A77: 20 | D77: sad.ship_str_ln_cd# | E77: RI | G77: Shipping rack/line cd. | H77: 出荷棚・ラインＣＤ | I77: E | J77: -
A78: 20 | D78: sad.dlv_id_typ# | E78: RI | G78: Delivery destination identification type | H78: 納品先識別区分 | I78: E | J78: -
A79: 20 | D79: sad.dlv_id_cd# | E79: RI | G79: Delivery destination identification cd. | H79: 納品先識別ＣＤ | I79: E | J79: -
A80: 20 | D80: sad.dlv_id_nm# | E80: RI | G80: Delivery destination identification name | H80: 納品先識別名 | I80: E | J80: -
A81: 20 | D81: sad.dlv_zip_cd# | E81: RI | G81: Zip code (Delivery destination) | H81: 納品先郵便番号 | I81: E | J81: -
... A153: 20 | D153: ship_schd_no | E153: #MA.SHIP_SCHD_NO | G153: Shipping schedule No. | H153: 出荷予定ＮＯ | I153: - | J153: -
A154: 20 | D154: pr_sts_typ | E154: #MS.PR_STS_TYP | G154: Progress status type | H154: 進捗状況区分 | I154: - | J154: E | K154: MSC_PR_STS_TYP
A155: 20 | D155: pr_sts_typ_nm | E155: #MS.PR_STS_TYP_NM | G155: Progress status type name | H155: 進捗状況区分名 | I155: - | J155: E
A156: 20 | D156: ship_inst_d_no | E156: #MA.SHIP_INST_D_NO | G156: Shipping order details No. | H156: 出荷指図明細ＮＯ | I156: - | J156: -
A157: 20 | D157: iv_no | E157: #MA.IV_NO | G157: Invoice No. | H157: インボイスＮＯ | I157: E | J157: -
A158: 20 | D158: iv_d_no | E158: #MA.IV_D_NO | G158: Invoice details No. | H158: インボイス明細ＮＯ | I158: E | J158: -
A159: 20 | D159: slo_d_no | E159: #MA.SLO_D_NO | G159: Sales order details No. | H159: 受注明細ＮＯ | I159: - | J159: -
A160: 20 | D160: abort_flg | E160: #MA.FLG | G160: Cancel remaining | H160: 打切 | I160: E | J160: -
A161: 20 | D161: arr_loc_cd | E161: #MA.LOC_CD | G161: Receipt location cd. | H161: 入荷場所ＣＤ | I161: - | J161: -
A162: 20 | D162: arr_str_ln_cd | E162: #MA.STR_LN_CD | G162: Receipt rack/line cd. | H162: 入荷棚・ラインＣＤ | I162: - | J162: -
A163: 20 | D163: non_upd_flg | E163: #MA.FLG | G163: Not to update | H163: 更新対象外 | I163: E | J163: -
A164: 20 | D164: prov_typ | E164: #MA.PROV_TYP | G164: Supply type | H164: 支給区分 | I164: E | J164: -
A165: 20 | D165: prov_basis_typ | E165: #MA.PROV_BASIS_TYP | G165: Supply recording type | H165: 支給計上区分 | I165: E | J165: -
A166: 20 | D166: sync_flg | E166: #MA.FLG | G166: Synchronous | H166: 同期 | I166: - | J166: -
... A170: 20 | D170: ref_ship_act_d_no | E170: #MA.SHIP_ACT_D_NO | G170: Reference shipping result details No. | H170: 参照出荷実績明細ＮＯ | I170: E | J170: -
A171: 20 | D171: purc_sync_flg | E171: #MA.FLG | I171: E | J171: -
A172: 20 | D172: not_lot_mix_flg | E172: #MA.FLG | G172: Prohibit mixed lots | H172: ロット混在不可 | I172: E | J172: -
A173: 20 | D173: not_sublot_mix_flg | E173: #MA.FLG | G173: Prohibit mixed sublots | H173: サブロット混在不可 | I173: E | J173: -
A174: 20 | D174: org_peg_no | E174: #MA.INT | I174: E | J174: -
A176: 30 | B176: * | D176: ShipAct_Cnd | E176: R
A177: 30 | D177: bndl_prnt_flg | E177: #MA.FLG | G177: Multiple issue | H177: まとめ発行 | I177: E | J177: -

Sheet ShipAct_Upd02
A1: * | B1: * | D1: L | E1: 1
A2: * | D2: オペレーション実装仕様書 Operation Specification Implementation Sheet | E2: ModuleID : | F2: =IF(LogicCommon!C2="","",LogicCommon!C2) -> MS | G2: LogicID : | H2: =IF(LogicCommon!E2="","",LogicCommon!E2) -> MSBEL5540 | I2: Ope.ID : | J2: ShipAct_Upd02 | K2: Pj.ID : | L2: =IF(LogicCommon!G2="","",LogicCommon!G2) -> MC | M2: Ope.Body : | N2: "mcframe.serverMAUD.MAUDL5010.MAUDL_Operation"
A3: * | D3: =IF(LogicCommon!A3="","",LogicCommon!A3) | E3: SubModuleID : | F3: =IF(LogicCommon!C3="","",LogicCommon!C3) -> MSBE | G3: LogicClass : | H3: =IF(LogicCommon!E3="","",LogicCommon!E3) -> MSBEL_ShipActService | I3: Ope.Method : | J3: =J2 -> ShipAct_Upd02 | K3: SuperClassPj.ID : | L3: =IF(LogicCommon!G3="","",LogicCommon!G3) | O3: Gene.Type : | P3: ALL
A4: * | E4: Version : | F4: 000000 | G4: LogicName : | H4: =IF(LogicCommon!E4="","",LogicCommon!E4) -> 出荷実績サービス | I4: Ope.Name : | J4: 更新（出荷返品・入荷） | K4: SuperLogicID : | L4: =IF(LogicCommon!G4="","",LogicCommon!G4) -> MS.MSUDL5010 | M4: ImplOpe.ID:
A5: * | E5: ACType :
A6: * | D6: 概要 : | E6: 出荷返品および納品数量を更新する。 | M6: ID | O6: ID | Q6: ID
A7: # | I7: U | K7: K | L7: o | N7: o | P7: o
A8: # | D8: ブロック名 Block Name | E8: 型 Type | G8: super/share | H8: 対象ブロック名 Target Block Name | L8: TargetName | N8: TargetName | P8: TargetName | T8: ブロック備考 Block Remarks
A9: # | D9: 項目名 Field Name | E9: 型 Type | F9: 桁 Digits | G9: フルネーム Full Name | H9: 日本語名 Japanese Name | I9: 上り項目 Request Message Field | J9: 下り項目 Response Message Field | R9: 条件および編集方法 Conditions and Editing Methods | T9: 項目備考 Field Remarks
A10: # | L10: 上り項目 Request Message Field | M10: 下り項目 Response Message Field | N10: 上り項目 Request Message Field | O10: 下り項目 Response Message Field | P10: 上り項目 Request Message Field | Q10: 下り項目 Response Message Field
A11: 10 | B11: * | D11: ShipAct_Dtl | E11: L | G11: $share$ | H11: MS.MSBEL5540.ShipAct_Upd01.ShipAct_Dtl
A12: 10 | D12: data_crud_typ | E12: #MA.DATA_CRUD_TYP | G12: Data update type | H12: データ更新区分 | I12: - | J12: -
A13: 10 | D13: sad | E13: R | F13: DBC:MS.MST_SHIP_ACT_D | G13: Shipping result details | H13: 出荷実績明細
A14: 10 | D14: sad.ship_act_d_no# | E14: RI | G14: Shipping result details No. | H14: 出荷実績明細ＮＯ | I14: - | J14: -
A15: 10 | D15: sad.ship_act_no# | E15: RI | G15: Shipping result No. | H15: 出荷実績ＮＯ | I15: - | J15: -
A16: 10 | D16: sad.disp_seq# | E16: RI | G16: Display order | H16: 表示順 | I16: - | J16: -
A17: 10 | D17: sad.ship_alloc_sts_no# | E17: RI | G17: Shipping allocation status No. | H17: 出荷引当状況ＮＯ | I17: - | J17: -
A18: 10 | D18: sad.trd_cd# | E18: RI | G18: Transaction cd. | H18: 取引ＣＤ | I18: - | J18: -
A19: 10 | D19: sad.trd_ptn_typ# | E19: RI | G19: Transaction pattern type | H19: 取引パタン区分 | I19: - | J19: -
A20: 10 | D20: sad.ship_loc_cd# | E20: RI | G20: Shipping location cd. | H20: 出荷場所ＣＤ | I20: - | J20: -
A21: 10 | D21: sad.ship_str_ln_cd# | E21: RI | G21: Shipping rack/line cd. | H21: 出荷棚・ラインＣＤ | I21: - | J21: -
A22: 10 | D22: sad.dlv_id_typ# | E22: RI | G22: Delivery destination identification type | H22: 納品先識別区分 | I22: - | J22: -
A23: 10 | D23: sad.dlv_id_cd# | E23: RI | G23: Delivery destination identification cd. | H23: 納品先識別ＣＤ | I23: - | J23: -
A24: 10 | D24: sad.dlv_id_nm# | E24: RI | G24: Delivery destination identification name | H24: 納品先識別名 | I24: - | J24: -
A25: 10 | D25: sad.dlv_zip_cd# | E25: RI | G25: Zip code (Delivery destination) | H25: 納品先郵便番号 | I25: - | J25: -
... A102: 10 | D102: err_flg | E102: #MA.FLG | G102: Error | H102: エラー | I102: - | J102: -

Sheet ShipAct_Upd03
A1: * | B1: * | D1: L | E1: 1
A2: * | D2: オペレーション実装仕様書 Operation Specification Implementation Sheet | E2: ModuleID : | F2: =IF(LogicCommon!C2="","",LogicCommon!C2) -> MS | G2: LogicID : | H2: =IF(LogicCommon!E2="","",LogicCommon!E2) -> MSBEL5540 | I2: Ope.ID : | J2: ShipAct_Upd03 | K2: Pj.ID : | L2: =IF(LogicCommon!G2="","",LogicCommon!G2) -> MC | M2: Ope.Body : | N2: "mcframe.serverMAUD.MAUDL5010.MAUDL_Operation"
A3: * | D3: =IF(LogicCommon!A3="","",LogicCommon!A3) | E3: SubModuleID : | F3: =IF(LogicCommon!C3="","",LogicCommon!C3) -> MSBE | G3: LogicClass : | H3: =IF(LogicCommon!E3="","",LogicCommon!E3) -> MSBEL_ShipActService | I3: Ope.Method : | J3: =J2 -> ShipAct_Upd03 | K3: SuperClassPj.ID : | L3: =IF(LogicCommon!G3="","",LogicCommon!G3) | O3: Gene.Type : | P3: ALL
A4: * | E4: Version : | F4: 000000 | G4: LogicName : | H4: =IF(LogicCommon!E4="","",LogicCommon!E4) -> 出荷実績サービス | I4: Ope.Name : | J4: 現品票発行済更新 | K4: SuperLogicID : | L4: =IF(LogicCommon!G4="","",LogicCommon!G4) -> MS.MSUDL5010 | M4: ImplOpe.ID:
A5: * | E5: ACType :
A6: * | D6: 概要 : | E6: 現品票発行済フラグをオン(発行済)に更新する。 | M6: ID | O6: ID | Q6: ID
A7: # | I7: U | K7: K | L7: o | N7: o | P7: o
A8: # | D8: ブロック名 Block Name | E8: 型 Type | G8: super/share | H8: 対象ブロック名 Target Block Name | L8: TargetName | N8: TargetName | P8: TargetName | T8: ブロック備考 Block Remarks
A9: # | D9: 項目名 Field Name | E9: 型 Type | F9: 桁 Digits | G9: フルネーム Full Name | H9: 日本語名 Japanese Name | I9: 上り項目 Request Message Field | J9: 下り項目 Response Message Field | R9: 条件および編集方法 Conditions and Editing Methods | T9: 項目備考 Field Remarks
A10: # | L10: 上り項目 Request Message Field | M10: 下り項目 Response Message Field | N10: 上り項目 Request Message Field | O10: 下り項目 Response Message Field | P10: 上り項目 Request Message Field | Q10: 下り項目 Response Message Field
A11: 10 | B11: * | D11: ShipAct_Dtl | E11: L | G11: $share$ | H11: MS.MSBEL5540.ShipAct_Upd01.ShipAct_Dtl
A12: 10 | D12: data_crud_typ | E12: #MA.DATA_CRUD_TYP | G12: Data update type | H12: データ更新区分 | I12: - | J12: -
A13: 10 | D13: sad | E13: R | F13: DBC:MS.MST_SHIP_ACT_D | G13: Shipping result details | H13: 出荷実績明細
A14: 10 | D14: sad.ship_act_d_no# | E14: RI | G14: Shipping result details No. | H14: 出荷実績明細ＮＯ | I14: E | J14: -
A15: 10 | D15: sad.ship_act_no# | E15: RI | G15: Shipping result No. | H15: 出荷実績ＮＯ | I15: - | J15: -
A16: 10 | D16: sad.disp_seq# | E16: RI | G16: Display order | H16: 表示順 | I16: - | J16: -
A17: 10 | D17: sad.ship_alloc_sts_no# | E17: RI | G17: Shipping allocation status No. | H17: 出荷引当状況ＮＯ | I17: - | J17: -
A18: 10 | D18: sad.trd_cd# | E18: RI | G18: Transaction cd. | H18: 取引ＣＤ | I18: - | J18: -
A19: 10 | D19: sad.trd_ptn_typ# | E19: RI | G19: Transaction pattern type | H19: 取引パタン区分 | I19: - | J19: -
A20: 10 | D20: sad.ship_loc_cd# | E20: RI | G20: Shipping location cd. | H20: 出荷場所ＣＤ | I20: - | J20: -
A21: 10 | D21: sad.ship_str_ln_cd# | E21: RI | G21: Shipping rack/line cd. | H21: 出荷棚・ラインＣＤ | I21: - | J21: -
A22: 10 | D22: sad.dlv_id_typ# | E22: RI | G22: Delivery destination identification type | H22: 納品先識別区分 | I22: - | J22: -
A23: 10 | D23: sad.dlv_id_cd# | E23: RI | G23: Delivery destination identification cd. | H23: 納品先識別ＣＤ | I23: - | J23: -
A24: 10 | D24: sad.dlv_id_nm# | E24: RI | G24: Delivery destination identification name | H24: 納品先識別名 | I24: - | J24: -
A25: 10 | D25: sad.dlv_zip_cd# | E25: RI | G25: Zip code (Delivery destination) | H25: 納品先郵便番号 | I25: - | J25: -
... A102: 10 | D102: err_flg | E102: #MA.FLG | G102: Error | H102: エラー | I102: - | J102: -

Sheet ShipAct_Chk01
A1: * | B1: * | D1: L | E1: 1
A2: * | D2: オペレーション実装仕様書 Operation Specification Implementation Sheet | E2: ModuleID : | F2: =IF(LogicCommon!C2="","",LogicCommon!C2) -> MS | G2: LogicID : | H2: =IF(LogicCommon!E2="","",LogicCommon!E2) -> MSBEL5540 | I2: Ope.ID : | J2: ShipAct_Chk01 | K2: Pj.ID : | L2: =IF(LogicCommon!G2="","",LogicCommon!G2) -> MC | M2: Ope.Body : | N2: "mcframe.serverMAUD.MAUDL5010.MAUDL_Operation"
A3: * | D3: =IF(LogicCommon!A3="","",LogicCommon!A3) | E3: SubModuleID : | F3: =IF(LogicCommon!C3="","",LogicCommon!C3) -> MSBE | G3: LogicClass : | H3: =IF(LogicCommon!E3="","",LogicCommon!E3) -> MSBEL_ShipActService | I3: Ope.Method : | J3: =J2 -> ShipAct_Chk01 | K3: SuperClassPj.ID : | L3: =IF(LogicCommon!G3="","",LogicCommon!G3) | O3: Gene.Type : | P3: ALL
A4: * | E4: Version : | F4: 000000 | G4: LogicName : | H4: =IF(LogicCommon!E4="","",LogicCommon!E4) -> 出荷実績サービス | I4: Ope.Name : | J4: 更新前チェック（サービス呼出のみ） | K4: SuperLogicID : | L4: =IF(LogicCommon!G4="","",LogicCommon!G4) -> MS.MSUDL5010 | M4: ImplOpe.ID:
A5: * | E5: ACType :
A6: * | D6: 概要 : | E6: 出荷実績の登録・更新・削除の前に後続のチェックサービスを呼び出し登録・更新・削除が可能かチェックをする。 | M6: ID | O6: ID | Q6: ID
A7: # | I7: U | K7: K | L7: o | N7: o | P7: o
A8: # | D8: ブロック名 Block Name | E8: 型 Type | G8: super/share | H8: 対象ブロック名 Target Block Name | L8: TargetName | N8: TargetName | P8: TargetName | T8: ブロック備考 Block Remarks
A9: # | D9: 項目名 Field Name | E9: 型 Type | F9: 桁 Digits | G9: フルネーム Full Name | H9: 日本語名 Japanese Name | I9: 上り項目 Request Message Field | J9: 下り項目 Response Message Field | R9: 条件および編集方法 Conditions and Editing Methods | T9: 項目備考 Field Remarks
A10: # | L10: 上り項目 Request Message Field | M10: 下り項目 Response Message Field | N10: 上り項目 Request Message Field | O10: 下り項目 Response Message Field | P10: 上り項目 Request Message Field | Q10: 下り項目 Response Message Field
A11: 10 | B11: * | D11: ShipAct_Hdr | E11: L | G11: $share$ | H11: MS.MSBEL5540.ShipAct_Upd01.ShipAct_Hdr
A12: 10 | D12: data_crud_typ | E12: #MA.DATA_CRUD_TYP | G12: Data update type | H12: データ更新区分 | I12: E | J12: -
A13: 10 | D13: sa | E13: R | F13: DBC:MS.MST_SHIP_ACT | G13: Shipping result | H13: 出荷実績
A14: 10 | D14: sa.ship_act_no# | E14: RI | G14: Shipping result No. | H14: 出荷実績ＮＯ | I14: E | J14: -
A15: 10 | D15: sa.ship_act_rev# | E15: RI | G15: Shipping result rev. number | H15: 出荷実績改訂番号 | I15: - | J15: -
A16: 10 | D16: sa.ship_inst_no# | E16: RI | G16: Shipping order No. | H16: 出荷指図ＮＯ | I16: E | J16: -
A17: 10 | D17: sa.ac_dt# | E17: RI | G17: Recording date | H17: 計上日 | I17: E | J17: -
A18: 10 | D18: sa.ship_tm# | E18: RI | G18: Shipping date and time | H18: 出荷日時 | I18: E | J18: -
A19: 10 | D19: sa.dlv_tm# | E19: RI | G19: Delivery date and time | H19: 納品日時 | I19: E | J19: -
A20: 10 | D20: can_ac_dt | E20: #MA.DT | G20: Cancellation recording date | H20: 取消計上日 | I20: E | J20: -
A21: 10 | D21: sa.rqst_dpt_cd# | E21: RI | G21: Requesting dept. cd. | H21: 依頼元部門ＣＤ | I21: - | J21: -
A22: 10 | D22: sa.rqst_usr_cd# | E22: RI | G22: Requesting PIC cd. | H22: 依頼元担当者ＣＤ | I22: - | J22: -
A23: 10 | D23: sa.ship_fr_lg_grp_cd# | E23: RI | G23: Shipping point distribution group cd. | H23: 出荷元物流グループＣＤ | I23: E | J23: -
A24: 10 | D24: sa.wg_cd# | E24: RI | G24: WG cd. | H24: ＷＧ ＣＤ | I24: - | J24: -
A25: 10 | D25: sa.ship_term_cd# | E25: RI | G25: Shipping conditions cd. | H25: 出荷条件ＣＤ | I25: - | J25: -
... A63: 10 | D63: dlv_slip_no | E63: #MA.DLV_SLIP_NO | G63: Delivery note No. | H63: 納品書ＮＯ | I63: - | J63: -
A65: 20 | B65: * | D65: SihpAct_Dtl | E65: L | G65: $share$ | H65: MS.MSBEL5540.ShipAct_Upd01.ShipAct_Dtl
A66: 20 | D66: data_crud_typ | E66: #MA.DATA_CRUD_TYP | G66: Data update type | H66: データ更新区分 | I66: E | J66: -
A67: 20 | D67: sad | E67: R | F67: DBC:MS.MST_SHIP_ACT_D | G67: Shipping result details | H67: 出荷実績明細
A68: 20 | D68: sad.ship_act_d_no# | E68: RI | G68: Shipping result details No. | H68: 出荷実績明細ＮＯ | I68: E | J68: -
A69: 20 | D69: sad.ship_act_no# | E69: RI | G69: Shipping result No. | H69: 出荷実績ＮＯ | I69: - | J69: -
A70: 20 | D70: sad.disp_seq# | E70: RI | G70: Display order | H70: 表示順 | I70: - | J70: -
A71: 20 | D71: sad.ship_alloc_sts_no# | E71: RI | G71: Shipping allocation status No. | H71: 出荷引当状況ＮＯ | I71: E | J71: -
A72: 20 | D72: sad.trd_cd# | E72: RI | G72: Transaction cd. | H72: 取引ＣＤ | I72: E | J72: -
A73: 20 | D73: sad.trd_ptn_typ# | E73: RI | G73: Transaction pattern type | H73: 取引パタン区分 | I73: E | J73: -
A74: 20 | D74: sad.ship_loc_cd# | E74: RI | G74: Shipping location cd. | H74: 出荷場所ＣＤ | I74: E | J74: -
A75: 20 | D75: sad.ship_str_ln_cd# | E75: RI | G75: Shipping rack/line cd. | H75: 出荷棚・ラインＣＤ | I75: E | J75: -
A76: 20 | D76: sad.dlv_id_typ# | E76: RI | G76: Delivery destination identification type | H76: 納品先識別区分 | I76: E | J76: -
A77: 20 | D77: sad.dlv_id_cd# | E77: RI | G77: Delivery destination identification cd. | H77: 納品先識別ＣＤ | I77: E | J77: -
A78: 20 | D78: sad.dlv_id_nm# | E78: RI | G78: Delivery destination identification name | H78: 納品先識別名 | I78: - | J78: -
A79: 20 | D79: sad.dlv_zip_cd# | E79: RI | G79: Zip code (Delivery destination) | H79: 納品先郵便番号 | I79: - | J79: -
... A157: 20 | D157: ref_ship_act_d_no | E157: #MA.SHIP_ACT_D_NO | G157: Reference shipping result details No. | H157: 参照出荷実績明細ＮＯ | I157: E | J157: -
A158: 20 | D158: purc_sync_flg | E158: #MA.FLG | I158: E | J158: -
A159: 20 | D159: not_lot_mix_flg | E159: #MA.FLG | G159: Prohibit mixed lots | H159: ロット混在不可 | I159: E | J159: -
A160: 20 | D160: not_sublot_mix_flg | E160: #MA.FLG | G160: Prohibit mixed sublots | H160: サブロット混在不可 | I160: E | J160: -
A162: 30 | B162: * | D162: ShipAct_Del_Dtl | E162: L
A163: 30 | D163: ship_act_d_no | E163: #MA.SHIP_ACT_D_NO | G163: Shipping result details No. | H163: 出荷実績明細ＮＯ | I163: E | J163: -

Sheet ShipAct_InptChk01
A1: * | B1: * | D1: L | E1: 1
A2: * | D2: オペレーション実装仕様書 Operation Specification Implementation Sheet | E2: ModuleID : | F2: =IF(LogicCommon!C2="","",LogicCommon!C2) -> MS | G2: LogicID : | H2: =IF(LogicCommon!E2="","",LogicCommon!E2) -> MSBEL5540 | I2: Ope.ID : | J2: ShipAct_InptChk01 | K2: Pj.ID : | L2: =IF(LogicCommon!G2="","",LogicCommon!G2) -> MC | M2: Ope.Body : | N2: MA.MAUDL5010.Checker
A3: * | D3: =IF(LogicCommon!A3="","",LogicCommon!A3) | E3: SubModuleID : | F3: =IF(LogicCommon!C3="","",LogicCommon!C3) -> MSBE | G3: LogicClass : | H3: =IF(LogicCommon!E3="","",LogicCommon!E3) -> MSBEL_ShipActService | I3: Ope.Method : | J3: =J2 -> ShipAct_InptChk01 | K3: SuperClassPj.ID : | L3: =IF(LogicCommon!G3="","",LogicCommon!G3) | O3: Gene.Type : | P3: ALL
A4: * | E4: Version : | F4: 000000 | G4: LogicName : | H4: =IF(LogicCommon!E4="","",LogicCommon!E4) -> 出荷実績サービス | I4: Ope.Name : | J4: 登録・更新前チェック | K4: SuperLogicID : | L4: =IF(LogicCommon!G4="","",LogicCommon!G4) -> MS.MSUDL5010 | M4: ImplOpe.ID:
A5: * | E5: ACType :
A6: * | D6: 概要 : | E6: 出荷実績の登録・更新が可能かチェックをする。 | M6: ID | O6: ID | Q6: ID | AD6: ID | AF6: ID | AH6: ID
A7: # | I7: U | K7: K | L7: K | M7: K | N7: K | O7: K | P7: K | Q7: K | R7: K | S7: K | T7: K | U7: K | V7: K | W7: K | X7: K | Y7: K | Z7: K | AA7: K | AB7: K | AC7: o | AD7: SA.v0 | AE7: o | AG7: o
A8: # | D8: ブロック名 Block Name | E8: 型 Type | G8: super/share | H8: 対象ブロック名 Target Block Name | K8: REQ_UPD_CNT_CHK | L8: REQUIRED | M8: CHK_NUM | N8: SMALL_LARGE | O8: CHK_DT | P8: BEFORE_AFTER | Q8: CHK_PTN | R8: DUPLICATE | S8: TOO_MANY_INPUTS | T8: AT_LEAST_ONE | U8: ONLY_ONE_INPUT | V8: LIST_LOGIC | W8: LIST_OUT | X8: LIST_OUT_BASE | Y8: LIST_IN | Z8: LIST_IN_BASE | AA8: CONST | AB8: NULL_VAL | AC8: TargetName | AD8: OPE.MS.MSBEL5540.ShipAct_Chk01 | AE8: TargetName | AG8: TargetName | AK8: ブロック備考 Block Remarks
A9: # | D9: 項目名 Field Name | E9: 型 Type | F9: 桁 Digits | G9: フルネーム Full Name | H9: 日本語名 Japanese Name | I9: 上り項目 Request Message Field | J9: 下り項目 Response Message Field | AI9: 条件および編集方法 Conditions and Editing Methods | AK9: 項目備考 Field Remarks
A10: # | AC10: 上り項目 Request Message Field | AD10: 下り項目 Response Message Field | AE10: 上り項目 Request Message Field | AF10: 下り項目 Response Message Field | AG10: 上り項目 Request Message Field | AH10: 下り項目 Response Message Field
A11: 10 | B11: * | D11: ShipAct_InptChk01_Hdr | E11: L | AC11: ShipAct_Hdr | AD11: ShipAct_Hdr
A12: 10 | D12: data_crud_typ | E12: #MA.DATA_CRUD_TYP | G12: Data update type | H12: データ更新区分 | I12: E | J12: E | L12: E | AC12: E | AD12: -
A13: 10 | D13: ship_act_no | E13: #MA.SHIP_ACT_NO | G13: Shipping result No. | H13: 出荷実績ＮＯ | I13: E | J13: E | AC13: E | AD13: -
A14: 10 | D14: ship_act_rev | E14: #MA.SLIP_REV | G14: Shipping result rev. number | H14: 出荷実績改訂番号 | I14: - | J14: - | AC14: - | AD14: -
A15: 10 | D15: ship_inst_no | E15: #MA.SHIP_INST_NO | G15: Shipping order No. | H15: 出荷指図ＮＯ | I15: E | J15: E | AC15: E | AD15: -
A16: 10 | D16: ac_dt | E16: #MA.DT | G16: Recording date | H16: 計上日 | I16: E | J16: E | L16: E | O16: bfToday | AC16: E | AD16: -
A17: 10 | D17: can_ac_dt | E17: #MA.DT | G17: Cancellation recording date | H17: 取消計上日 | I17: E | J17: E | O17: bfToday | AC17: E | AD17: -
A18: 10 | D18: ship_tm | E18: #MA.TM | G18: Shipping date and time | H18: 出荷日時 | I18: E | J18: E | L18: E | O18: tmBfToday | P18: ship_tm:BF | AC18: E | AD18: -
A19: 10 | D19: ship_dt | E19: #MA.DT | G19: Shipping date | H19: 出荷日 | I19: - | J19: - | AC19: - | AD19: -
A20: 10 | D20: dlv_tm | E20: #MA.TM | G20: Delivery date and time | H20: 納品日時 | I20: E | J20: E | L20: E | P20: ship_tm:AF | AC20: E | AD20: -
A21: 10 | D21: rqst_usr_cd | E21: #MA.USR_CD | G21: Requesting PIC cd. | H21: 依頼元担当者ＣＤ | I21: E | J21: E | V21: MA.MAUAL0010.Usr | AC21: - | AD21: -
A22: 10 | D22: rqst_dpt_cd | E22: #MA.DPT_CD | G22: Requesting dept. cd. | H22: 依頼元部門ＣＤ | I22: E | J22: E | V22: MA.MAUAL0010.Dpt | Y22: rqst_usr_cd;ac_dt;MAC_DPT_IS_SRCH_TYP.SCE | Z22: usr_cd;dt;dpt_is_srch_typ | AC22: - | AD22: -
A23: 10 | D23: ship_fr_lg_grp_cd | E23: #MA.LG_GRP_CD | G23: Shipping point distribution group cd. | H23: 出荷元物流グループＣＤ | I23: E | J23: E | L23: E | V23: MA.MAUAL0010.LgGrp | W23: wg_cd | Y23: true | Z23: loc_flg | AC23: E | AD23: -
A24: 10 | D24: wg_cd | E24: #MA.WG_CD | G24: WG cd. | H24: ＷＧ ＣＤ | I24: - | J24: E | AC24: - | AD24: -
A25: 10 | D25: ship_term_cd | E25: #MA.SHIP_TERM_CD | G25: Shipping conditions cd. | H25: 出荷条件ＣＤ | I25: - | J25: E | V25: MA.MAUAL0010.ShipTerm | AC25: - | AD25: -
A26: 10 | D26: ship_usr_cd | E26: #MA.USR_CD | G26: Shipping PIC cd. | H26: 出荷担当者ＣＤ | I26: E | J26: E | V26: MA.MAUAL0010.Usr | AC26: - | AD26: -
A27: 10 | D27: ship_dpt_cd | E27: #MA.DPT_CD | G27: Shipping dept. cd. | H27: 出荷部門ＣＤ | I27: E | J27: E | V27: MA.MAUAL0010.Dpt | Y27: ship_usr_cd;ship_dt;true;MAC_DPT_IS_SRCH_TYP.SHIP | Z27: usr_cd;dt;ship_dpt_flg;dpt_is_srch_typ | AC27: - | AD27: -
A28: 10 | D28: cst_cd | E28: #MA.BP_CD | G28: Customer cd. | H28: 得意先ＣＤ | I28: E | J28: E | V28: MA.MAUAL0010.Bp | Y28: MAC_BP_IS_SRCH_TYP.CST_NOT_SUNDRY | Z28: bp_is_srch_typ | AC28: E | AD28: -
A29: 10 | D29: ship_to_id_typ | E29: #MS.SHIP_TO_ID_TYP | G29: Receiving point identification type | H29: 送付先識別区分 | I29: E | J29: E | L29: E | AA29: MSC_SHIP_TO_ID_TYP | AC29: E | AD29: -
A30: 10 | D30: ship_to_id_cd | E30: #MS.SHIP_TO_ID_CD | G30: Receiving point identification cd. | H30: 送付先識別ＣＤ | I30: E | J30: E | L30: E | V30: MS.MSUAL0060.ShipToId | W30: ship_to_sundry_flg;ship_to_id_nm;ship_to_zip_cd;ship_to_addr1;ship_to_addr2;ship_to_addr3;ship_to_addr4;ship_to_cntct_dpt;ship_to_cntct_psn;ship_to_tel;ship_to_fax;ship_to_lg_grp_cd | X30: ship_to_sundry_flg;ship_to_id_nm;zip_cd;addr1;addr2;addr3;addr4;ship_to_cntct_dpt;ship_to_cntct_psn;tel;fax;lg_grp_cd | Y30: ship_to_id_typ;ship_dt | Z30: ship_to_id_typ;base_dt | AC30: E | AD30: -
A31: 10 | D31: ship_to_id_nm | E31: #MS.SHIP_TO_ID_NM | G31: Receiving point Identification name | H31: 送付先識別名 | I31: E | J31: E | AC31: - | AD31: -
A32: 10 | D32: ship_to_zip_cd | E32: #MA.ZIP_CD | G32: Receiving point zip code | H32: 送付先郵便番号 | I32: E | J32: E | AC32: - | AD32: -
A33: 10 | D33: ship_to_addr1 | E33: #MA.ADDR1 | G33: Receiving point address 1 | H33: 送付先住所１ | I33: E | J33: E | AC33: - | AD33: -
A34: 10 | D34: ship_to_addr2 | E34: #MA.ADDR2 | G34: Receiving point address 2 | H34: 送付先住所２ | I34: E | J34: E | AC34: - | AD34: -
A35: 10 | D35: ship_to_addr3 | E35: #MA.ADDR3 | G35: Receiving point address 3 | H35: 送付先住所３ | I35: E | J35: E | AC35: - | AD35: -
A36: 10 | D36: ship_to_addr4 | E36: #MA.ADDR4 | G36: Receiving point address 4 | H36: 送付先住所４ | I36: E | J36: E | AC36: - | AD36: -
A37: 10 | D37: ship_to_cntct_dpt | E37: #MA.BP_CNTCT_DPT | G37: Receiving point dept. | H37: 送付先部署 | I37: E | J37: E | AC37: - | AD37: -
A38: 10 | D38: ship_to_cntct_psn | E38: #MA.BP_CNTCT_PSN | G38: Receiving point PIC | H38: 送付先担当者 | I38: E | J38: E | AC38: - | AD38: -
A39: 10 | D39: ship_to_tel | E39: #MA.TEL | G39: Receiving point TEL | H39: 送付先ＴＥＬ | I39: E | J39: E | AC39: - | AD39: -
A40: 10 | D40: ship_to_fax | E40: #MA.TEL | G40: Receiving point FAX | H40: 送付先ＦＡＸ | I40: E | J40: E | AC40: - | AD40: -
A41: 10 | D41: ship_to_sundry_flg | E41: #MA.FLG | G41: Miscellaneous receiving point | H41: 送付先諸口 | I41: - | J41: E | AC41: - | AD41: -
A42: 10 | D42: via_dlv_typ | E42: #MA.VIA_DLV_TYP | G42: Receiving point stopover type | H42: 配送先経由区分 | I42: - | J42: E | AC42: E | AD42: -
A43: 10 | D43: ship_to_lg_grp_cd | E43: #MA.LG_GRP_CD | G43: Receiving point distribution group cd. | H43: 出荷先物流グループＣＤ | I43: - | J43: E | V43: MA.MAUAL0010.LgGrp | AC43: - | AD43: -
A44: 10 | D44: iv_no | E44: #MA.IV_NO | G44: Invoice No. | H44: インボイスＮＯ | I44: E | J44: E | AC44: E | AD44: -
A45: 10 | D45: dlv_slip_no | E45: #MA.DLV_SLIP_NO | G45: Delivery note No. | H45: 納品書ＮＯ | I45: E | J45: E | AC45: - | AD45: -
A46: 10 | D46: uplnd_flg | E46: #MA.FLG | G46: Unplanned | H46: 計画外 | I46: E | J46: E | AC46: E | AD46: -
A47: 10 | D47: intr_rmrks | E47: #MS.SHIP_ACT_INTR_RMRKS | G47: Internal remarks | H47: 内部備考 | I47: E | J47: E | AC47: - | AD47: -
A48: 10 | D48: sub_char1 | E48: #MS.SHIP_ACT_SUB_CHAR1 | G48: Spare 1 | H48: 予備１ | I48: E | J48: E | AC48: - | AD48: -
A49: 10 | D49: sub_char2 | E49: #MS.SHIP_ACT_SUB_CHAR2 | G49: Spare 2 | H49: 予備２ | I49: E | J49: E | AC49: - | AD49: -
A50: 10 | D50: sub_char3 | E50: #MS.SHIP_ACT_SUB_CHAR3 | G50: Spare 3 | H50: 予備３ | I50: E | J50: E | AC50: - | AD50: -
A51: 10 | D51: dlv_slip_prnt_flg | E51: #MA.FLG | G51: Delivery note immediate issue | H51: 納品書即時発行 | I51: E | J51: E | AC51: - | AD51: -
A52: 10 | D52: ship_adv_prnt_flg | E52: #MA.FLG | G52: Shipping guide immediate issue | H52: 出荷案内書即時発行 | I52: E | J52: E | AC52: - | AD52: -
A53: 10 | D53: lot_chk_off_flg | E53: #MA.FLG | G53: Ignore lot check | H53: ロットチェック無視 | I53: E | J53: E | AC53: E | AD53: -
A54: 10 | D54: peg_no | E54: #MA.INT | G54: Pegging No. | H54: 紐付けＮＯ | I54: E | J54: E | AC54: E | AD54: E
A55: 10 | D55: err_flg | E55: #MA.FLG | G55: Error | H55: エラー | I55: - | J55: E | AC55: - | AD55: E
A57: 20 | B57: * | D57: ShipAct_InptChk01_Dtl | E57: L | AC57: SihpAct_Dtl | AD57: SihpAct_Dtl
A58: 20 | D58: data_crud_typ | E58: #MA.DATA_CRUD_TYP | G58: Data update type | H58: データ更新区分 | I58: E | J58: E | L58: E | AC58: E | AD58: -
A59: 20 | D59: ship_act_d_no | E59: #MA.SHIP_ACT_D_NO | G59: Shipping result details No. | H59: 出荷実績明細ＮＯ | I59: E | J59: E | AC59: E | AD59: -
A60: 20 | D60: ship_act_no | E60: #MA.SHIP_ACT_NO | G60: Shipping result No. | H60: 出荷実績ＮＯ | I60: - | J60: - | AC60: - | AD60: -
A61: 20 | D61: disp_seq | E61: #MA.DISP_SEQ | G61: Display order | H61: 表示順 | I61: - | J61: E | AC61: - | AD61: -
A62: 20 | D62: ship_alloc_sts_no | E62: #MA.SHIP_ALLOC_STS_NO | G62: Shipping allocation status No. | H62: 出荷引当状況ＮＯ | I62: E | J62: E | AC62: E | AD62: -
A63: 20 | D63: trd_cd | E63: #MA.TRD_CD | G63: Transaction cd. | H63: 取引ＣＤ | I63: E | J63: E | L63: E | V63: MA.MAUAL0010.Trd | W63: trd_ptn_typ | AC63: E | AD63: -
A64: 20 | D64: trd_ptn_typ | E64: #MA.TRD_PTN_TYP | G64: Transaction pattern type | H64: 取引パタン区分 | I64: - | J64: E | AC64: E | AD64: -
A65: 20 | D65: ship_fr_lg_grp_cd | E65: #MA.LG_GRP_CD | G65: Shipping point distribution group cd. | H65: 出荷元物流グループＣＤ | I65: - | J65: - | AC65: - | AD65: -
A66: 20 | D66: ship_loc_cd | E66: #MA.LOC_CD | G66: Shipping location cd. | H66: 出荷場所ＣＤ | I66: E | J66: E | V66: MA.MAUAL0010.Loc | W66: ship_str_ln_tgt_flg;ship_loc_sppl_cd | X66: str_ln_tgt_flg;sppl_cd | Y66: ship_fr_lg_grp_cd | Z66: lg_grp_cd | AC66: E | AD66: -
A67: 20 | D67: loc_is_srch_typ | E67: #MA.LOC_IS_SRCH_TYP | G67: Location input assist search type | H67: 場所入力補助検索区分 | I67: - | J67: -
A68: 20 | D68: ship_str_ln_tgt_flg | E68: #MA.FLG | G68: For shipping rack/line | H68: 出荷棚・ライン対象 | I68: - | J68: -
A69: 20 | D69: ship_str_ln_cd | E69: #MA.STR_LN_CD | G69: Shipping rack/line cd. | H69: 出荷棚・ラインＣＤ | I69: E | J69: E | V69: MA.MAUAL0010.StrLn | Y69: ship_loc_cd;true | Z69: loc_cd;mode_nullval_flg | AC69: E | AD69: -
A70: 20 | D70: ship_loc_sppl_cd | E70: #MA.BP_CD | G70: Shipping location supplier cd. | H70: 出荷場所発注先ＣＤ | I70: - | J70: -
A71: 20 | D71: dlv_id_typ | E71: #MS.DLV_ID_TYP | G71: Delivery destination identification type | H71: 納品先識別区分 | I71: E | J71: E | AA71: MSC_DLV_ID_TYP | AC71: E | AD71: -
A72: 20 | D72: dlv_id_cd | E72: #MS.DLV_ID_CD | G72: Delivery destination identification cd. | H72: 納品先識別ＣＤ | I72: E | J72: E | V72: MS.MSUAL0060.DlvId | W72: dlv_sundry_flg;dlv_id_nm;dlv_zip_cd;dlv_addr1;dlv_addr2;dlv_addr3;dlv_addr4;dlv_cntct_dpt;dlv_cntct_psn;dlv_tel;dlv_fax;dlv_str_ln_tgt_flg;dlv_sppl_cd | X72: dlv_sundry_flg;dlv_id_nm;zip_cd;addr1;addr2;addr3;addr4;dlv_cntct_dpt;dlv_cntct_psn;tel;fax;str_ln_tgt_flg;sppl_cd | Y72: dlv_id_typ;ship_dt | Z72: dlv_id_typ;base_dt | AC72: E | AD72: -
A73: 20 | D73: dlv_id_nm | E73: #MS.DLV_ID_NM | G73: Delivery destination identification name | H73: 納品先識別名 | I73: E | J73: E | AC73: - | AD73: -
A74: 20 | D74: dlv_zip_cd | E74: #MA.ZIP_CD | G74: Zip code (Delivery destination) | H74: 納品先郵便番号 | I74: E | J74: E | Q74: ZIP | AC74: - | AD74: -
A75: 20 | D75: dlv_addr1 | E75: #MA.ADDR1 | G75: Address 1 (Delivery destination) | H75: 納品先住所１ | I75: E | J75: E | AC75: - | AD75: -
A76: 20 | D76: dlv_addr2 | E76: #MA.ADDR2 | G76: Address 2 (Delivery destination) | H76: 納品先住所２ | I76: E | J76: E | AC76: - | AD76: -
A77: 20 | D77: dlv_addr3 | E77: #MA.ADDR3 | G77: Address 3 (Delivery destination) | H77: 納品先住所３ | I77: E | J77: E | AC77: - | AD77: -
A78: 20 | D78: dlv_addr4 | E78: #MA.ADDR4 | G78: Address 4 (Delivery destination) | H78: 納品先住所４ | I78: E | J78: E | AC78: - | AD78: -
A79: 20 | D79: dlv_cntct_dpt | E79: #MA.BP_CNTCT_DPT | G79: Delivery destination dept. | H79: 納品先部署 | I79: E | J79: E | AC79: - | AD79: -
A80: 20 | D80: dlv_cntct_psn | E80: #MA.BP_CNTCT_PSN | G80: Delivery destination PIC | H80: 納品先担当者 | I80: E | J80: E | AC80: - | AD80: -
A81: 20 | D81: dlv_tel | E81: #MA.TEL | G81: TEL (Delivery destination) | H81: 納品先ＴＥＬ | I81: E | J81: E | Q81: TEL | AC81: - | AD81: -
A82: 20 | D82: dlv_fax | E82: #MA.TEL | G82: FAX (Delivery destination) | H82: 納品先ＦＡＸ | I82: E | J82: E | Q82: TEL | AC82: - | AD82: -
A83: 20 | D83: dlv_sundry_flg | E83: #MA.FLG | G83: Miscellaneous delivery destination | H83: 納品先諸口 | I83: - | J83: E | AC83: - | AD83: -
A84: 20 | D84: dlv_str_ln_tgt_flg | E84: #MA.FLG | G84: For delivery destination rack/line | H84: 納品先棚・ライン対象 | I84: - | J84: -
A85: 20 | D85: dlv_str_ln_cd | E85: #MA.STR_LN_CD | G85: Delivery destination rack/line cd. | H85: 納品先棚・ラインＣＤ | I85: E | J85: E | AC85: - | AD85: -
A86: 20 | D86: dlv_sppl_cd | E86: #MA.BP_CD | G86: Delivery destination supplier cd. | H86: 納品先発注先ＣＤ | I86: - | J86: -
A87: 20 | D87: pri_prnt_flg | E87: #MA.FLG | G87: Print price | H87: 価格印字 | I87: E | J87: E | AC87: - | AD87: -
A88: 20 | D88: itm_cd | E88: #MA.ITM_CD | G88: Item cd. | H88: 品目ＣＤ | I88: E | J88: E | L88: E | AC88: E | AD88: -
A89: 20 | D89: itm_sub1 | E89: #MA.ITM_SUB1 | G89: Branch No. 1 | H89: 枝番１ | I89: E | J89: E | AC89: E | AD89: -
A90: 20 | D90: itm_sub2 | E90: #MA.ITM_SUB2 | G90: Branch No. 2 | H90: 枝番２ | I90: E | J90: E | AC90: E | AD90: -
A91: 20 | D91: itm_sub3 | E91: #MA.ITM_SUB3 | G91: Branch No. 3 | H91: 枝番３ | I91: E | J91: E | V91: MA.MAUAL0010.ItmSub3 | W91: sundry_itm_flg;itm_nm;stk_mng_typ;lot_mng_typ;sublot_mng_typ;sno1_mng_typ;sno2_mng_typ;sno3_mng_typ;sno4_mng_typ;base_unit_cd;base_unit_nm;base_unit_dec_place;base_unit_rnd_typ | X91: sundry_itm_flg;itm_nm;stk_mng_typ;lot_mng_typ;sublot_mng_typ;sno1_mng_typ;sno2_mng_typ;sno3_mng_typ;sno4_mng_typ;unit_cd;unit_nm;dec_place;rnd_typ | Y91: itm_cd;itm_sub1;itm_sub2;MAC_ITM_IS_SRCH_TYP.NOT_ASSET3 | Z91: itm_cd;itm_sub1;itm_sub2;itm_is_srch_typ | AC91: E | AD91: -
A92: 20 | D92: itm_nm | E92: #MA.ITM_NM | G92: Item name | H92: 品名 | I92: E | J92: E | AC92: E | AD92: -
A93: 20 | D93: iv_itm_nm | E93: #MA.ITM_NM | G93: Item name for invoice | H93: インボイス表記用品名 | I93: E | J93: E | AC93: - | AD93: -
A94: 20 | D94: sundry_itm_flg | E94: #MA.FLG | G94: Miscellaneous item | H94: 諸口品 | I94: - | J94: E | AC94: - | AD94: -
A95: 20 | D95: stk_mng_typ | E95: #MA.STK_MNG_TYP | G95: Inventory management type | H95: 在庫管理区分 | I95: - | J95: E | AC95: - | AD95: -
A96: 20 | D96: itm_is_srch_typ | E96: #MA.ITM_IS_SRCH_TYP | G96: Item input assist search type | H96: 品目入力補助検索区分 | I96: - | J96: - | AC96: - | AD96: -
A97: 20 | D97: sno1 | E97: #MA.SNO1 | G97: SEIBAN No. 1 | H97: 手配ＮＯ１ | I97: E | J97: E | AC97: E | AD97: -
A98: 20 | D98: sno2 | E98: #MA.SNO2 | G98: SEIBAN No. 2 | H98: 手配ＮＯ２ | I98: E | J98: E | AC98: E | AD98: -
A99: 20 | D99: sno3 | E99: #MA.SNO3 | G99: SEIBAN No. 3 | H99: 手配ＮＯ３ | I99: E | J99: E | AC99: E | AD99: -
A100: 20 | D100: sno4 | E100: #MA.SNO4 | G100: SEIBAN No. 4 | H100: 手配ＮＯ４ | I100: E | J100: E | AC100: E | AD100: -
A101: 20 | D101: lot_no | E101: #MA.LOT_NO | G101: Lot No. | H101: ロットＮＯ | I101: E | J101: E | AC101: E | AD101: -
...

Sheet ShipAct_InptChk02
A1: * | B1: * | D1: L | E1: 1
A2: * | D2: オペレーション実装仕様書 Operation Specification Implementation Sheet | E2: ModuleID : | F2: =IF(LogicCommon!C2="","",LogicCommon!C2) -> MS | G2: LogicID : | H2: =IF(LogicCommon!E2="","",LogicCommon!E2) -> MSBEL5540 | I2: Ope.ID : | J2: ShipAct_InptChk02 | K2: Pj.ID : | L2: =IF(LogicCommon!G2="","",LogicCommon!G2) -> MC | M2: Ope.Body : | N2: MA.MAUDL5010.Checker
A3: * | D3: =IF(LogicCommon!A3="","",LogicCommon!A3) | E3: SubModuleID : | F3: =IF(LogicCommon!C3="","",LogicCommon!C3) -> MSBE | G3: LogicClass : | H3: =IF(LogicCommon!E3="","",LogicCommon!E3) -> MSBEL_ShipActService | I3: Ope.Method : | J3: =J2 -> ShipAct_InptChk02 | K3: SuperClassPj.ID : | L3: =IF(LogicCommon!G3="","",LogicCommon!G3) | O3: Gene.Type : | P3: ALL
A4: * | E4: Version : | F4: 000000 | G4: LogicName : | H4: =IF(LogicCommon!E4="","",LogicCommon!E4) -> 出荷実績サービス | I4: Ope.Name : | J4: 削除前チェック | K4: SuperLogicID : | L4: =IF(LogicCommon!G4="","",LogicCommon!G4) -> MS.MSUDL5010 | M4: ImplOpe.ID:
A5: * | E5: ACType :
A6: * | D6: 概要 : | E6: 出荷実績の削除が可能かチェックをする。 | AD6: ID | AF6: ID | AH6: ID
A7: # | I7: U | K7: K | L7: K | M7: K | N7: K | O7: K | P7: K | Q7: K | R7: K | S7: K | T7: K | U7: K | V7: K | W7: K | X7: K | Y7: K | Z7: K | AA7: K | AB7: K | AC7: o | AD7: SA.v0 | AE7: o | AG7: o
A8: # | D8: ブロック名 Block Name | E8: 型 Type | G8: super/share | H8: 対象ブロック名 Target Block Name | K8: REQ_UPD_CNT_CHK | L8: REQUIRED | M8: CHK_NUM | N8: SMALL_LARGE | O8: CHK_DT | P8: BEFORE_AFTER | Q8: CHK_PTN | R8: DUPLICATE | S8: TOO_MANY_INPUTS | T8: ONLY_ONE_INPUT | U8: AT_LEAST_ONE | V8: LIST_LOGIC | W8: LIST_OUT | X8: LIST_OUT_BASE | Y8: LIST_IN | Z8: LIST_IN_BASE | AA8: CONST | AB8: NULL_VAL | AC8: TargetName | AD8: OPE.MS.MSBEL5540.ShipAct_Chk01 | AE8: TargetName | AG8: TargetName | AK8: ブロック備考 Block Remarks
A9: # | D9: 項目名 Field Name | E9: 型 Type | F9: 桁 Digits | G9: フルネーム Full Name | H9: 日本語名 Japanese Name | I9: 上り項目 Request Message Field | J9: 下り項目 Response Message Field | AI9: 条件および編集方法 Conditions and Editing Methods | AK9: 項目備考 Field Remarks
A10: # | AC10: 上り項目 Request Message Field | AD10: 下り項目 Response Message Field | AE10: 上り項目 Request Message Field | AF10: 下り項目 Response Message Field | AG10: 上り項目 Request Message Field | AH10: 下り項目 Response Message Field
A11: 10 | B11: * | D11: ShipAct_InptChk02_Hdr | E11: L | AC11: ShipAct_Hdr | AD11: ShipAct_Hdr
A12: 10 | D12: data_crud_typ | E12: #MA.DATA_CRUD_TYP | G12: Data update type | H12: データ更新区分 | I12: E | J12: E | L12: E | AC12: E | AD12: -
A13: 10 | D13: ship_act_no | E13: #MA.SHIP_ACT_NO | G13: Shipping result No. | H13: 出荷実績ＮＯ | I13: E | J13: E | L13: E | AC13: E | AD13: -
A14: 10 | D14: ship_act_rev | E14: #MA.SLIP_REV | G14: Shipping result rev. number | H14: 出荷実績改訂番号 | I14: - | J14: - | AC14: - | AD14: -
A15: 10 | D15: ship_inst_no | E15: #MA.SHIP_INST_NO | G15: Shipping order No. | H15: 出荷指図ＮＯ | I15: - | J15: - | AC15: - | AD15: -
A16: 10 | D16: ac_dt | E16: #MA.DT | G16: Recording date | H16: 計上日 | I16: - | J16: - | AC16: - | AD16: -
A17: 10 | D17: can_ac_dt | E17: #MA.DT | G17: Cancellation recording date | H17: 取消計上日 | I17: E | J17: E | L17: E | O17: bfToday | AC17: E | AD17: -
A18: 10 | D18: ship_tm | E18: #MA.TM | G18: Shipping date and time | H18: 出荷日時 | I18: - | J18: - | AC18: - | AD18: -
A19: 10 | D19: dlv_tm | E19: #MA.TM | G19: Delivery date and time | H19: 納品日時 | I19: - | J19: - | AC19: - | AD19: -
A20: 10 | D20: rqst_dpt_cd | E20: #MA.DPT_CD | G20: Requesting dept. cd. | H20: 依頼元部門ＣＤ | I20: - | J20: - | AC20: - | AD20: -
A21: 10 | D21: rqst_usr_cd | E21: #MA.USR_CD | G21: Requesting PIC cd. | H21: 依頼元担当者ＣＤ | I21: - | J21: - | AC21: - | AD21: -
A22: 10 | D22: ship_fr_lg_grp_cd | E22: #MA.LG_GRP_CD | G22: Shipping point distribution group cd. | H22: 出荷元物流グループＣＤ | I22: - | J22: - | AC22: - | AD22: -
A23: 10 | D23: wg_cd | E23: #MA.WG_CD | G23: WG cd. | H23: ＷＧ ＣＤ | I23: - | J23: - | AC23: - | AD23: -
A24: 10 | D24: ship_term_cd | E24: #MA.SHIP_TERM_CD | G24: Shipping conditions cd. | H24: 出荷条件ＣＤ | I24: - | J24: - | AC24: - | AD24: -
A25: 10 | D25: ship_dpt_cd | E25: #MA.DPT_CD | G25: Shipping dept. cd. | H25: 出荷部門ＣＤ | I25: - | J25: - | AC25: - | AD25: -
A26: 10 | D26: ship_usr_cd | E26: #MA.USR_CD | G26: Shipping PIC cd. | H26: 出荷担当者ＣＤ | I26: - | J26: - | AC26: - | AD26: -
A27: 10 | D27: ship_to_lg_grp_cd | E27: #MA.LG_GRP_CD | G27: Receiving point distribution group cd. | H27: 出荷先物流グループＣＤ | I27: - | J27: - | AC27: - | AD27: -
A28: 10 | D28: cst_cd | E28: #MA.BP_CD | G28: Customer cd. | H28: 得意先ＣＤ | I28: - | J28: - | AC28: - | AD28: -
A29: 10 | D29: ship_to_id_typ | E29: #MS.SHIP_TO_ID_TYP | G29: Receiving point identification type | H29: 送付先識別区分 | I29: - | J29: - | AC29: - | AD29: -
... A53: 10 | D53: err_flg | E53: #MA.FLG | G53: Error | H53: エラー | I53: - | J53: E | AC53: - | AD53: E
A55: 20 | B55: * | D55: ShipAct_InptChk02_Cntr | E55: L | G55: $share$ | H55: MS.MSBEL5540.ShipAct_InptChk01.ShipAct_InptChk01_Cntr
A56: 20 | D56: ship_alloc_sts_no | E56: #MA.SHIP_ALLOC_STS_NO | G56: Shipping allocation status No. | H56: 出荷引当状況ＮＯ | I56: E | J56: -
A57: 20 | D57: ship_pr_no | E57: #MA.SHIP_PR_NO | G57: Shipping progress No. | H57: 出荷進捗ＮＯ | I57: E | J57: -

Sheet ShipAct_RevUpd01
A1: * | B1: * | D1: L | E1: 1
A2: * | D2: オペレーション実装仕様書 Operation Specification Implementation Sheet | E2: ModuleID : | F2: MS | G2: LogicID : | H2: MSBEL5540 | I2: Ope.ID : | J2: ShipAct_RevUpd01 | K2: Pj.ID : | L2: MC | M2: Ope.Body : | N2: "mcframe.serverMAUD.MAUDL5010.MAUDL_Operation"
A3: * | E3: SubModuleID : | F3: MSBE | G3: LogicClass : | H3: MSBEL_ShipActService | I3: Ope.Method : | J3: ShipAct_RevUpd01 | K3: SuperClassPj.ID : | O3: Gene.Type : | P3: ALL
A4: * | E4: Version : | F4: 000000 | G4: LogicName : | H4: 出荷実績サービス | I4: Ope.Name : | J4: 出荷実績改訂履歴更新 | K4: SuperLogicID : | L4: MS.MSUDL5010 | M4: ImplOpe.ID: | N4: MA.MAUCL5020.RevData_Upd01
A5: * | E5: ACType :
A6: * | D6: 概要 : | E6: 出荷実績改訂履歴テーブルを更新する。改訂履歴データ更新用の共通処理（MAUCL5020）から呼び出される。 | M6: ID | O6: ID | Q6: ID
A7: # | I7: U | K7: K | L7: o | N7: o | P7: o
A8: # | D8: ブロック名 Block Name | E8: 型 Type | G8: super/share | H8: 対象ブロック名 Target Block Name | L8: TargetName | N8: TargetName | P8: TargetName | T8: ブロック備考 Block Remarks
A9: # | D9: 項目名 Field Name | E9: 型 Type | F9: 桁 Digits | G9: フルネーム Full Name | H9: 日本語名 Japanese Name | I9: 上り項目 Request Message Field | J9: 下り項目 Response Message Field | R9: 条件および編集方法 Conditions and Editing Methods | T9: 項目備考 Field Remarks
A10: # | L10: 上り項目 Request Message Field | M10: 下り項目 Response Message Field | N10: 上り項目 Request Message Field | O10: 下り項目 Response Message Field | P10: 上り項目 Request Message Field | Q10: 下り項目 Response Message Field
A11: 10 | B11: * | D11: ShipAct_RevUpd01_Dtl | E11: L | G11: $share$ | H11: MA.MAUCL5020.RevData_Upd01.RevData_Upd01_Dtl
A12: 10 | D12: rev_data_src_no | E12: #MA.SRC_NO | G12: Revision history data source No. | H12: 改訂履歴データ作成元ＮＯ | I12: E | J12: -
A13: 10 | D13: rev_no | E13: #MA.SLIP_REV | G13: Rev. number | H13: 改訂番号 | I13: E | J13: -

Sheet 来歴
A1: 変更来歴
A3: Rev. | H3: 修正番号 | O3: 変更内容 | AQ3: 変更箇所
A4: 1 | O4: 初版
A5: 1.1 | H5: MS7031#404 | O5: ShipAct_InptChk01_Dtlブロックに以下の項目を追加 not_lot_mix_flg、not_sublot_mix_flg | AQ5: ShipAct_InptChk01
A6: 〃 | H6: 〃 | O6: SihpAct_Dtlブロックに以下の項目を追加 not_lot_mix_flg、not_sublot_mix_flg | AQ6: ShipAct_Chk01
A7: 〃 | H7: 〃 | O7: SihpAct_Dtlブロックに以下の項目を追加 not_lot_mix_flg、not_sublot_mix_flg | AQ7: ShipAct_Upd01
A8: 1.2 | O8: 英語の名称を追記 | AQ8: 全般
A9: 1.3 | H9: MS7033#058 | O9: SihpAct_Dtlブロックに以下の項目を追加 org_peg_no | AQ9: ShipAct_Upd01
